Workbook

Sheet SUMMARY PAGE
A1: PROJECT: | G1: TOTAL PO. AMOUNT | H1: =SUM(G8:G82) -> 7007813.8
A2: A.F.E.# | G2: INVOICED | H2: =SUM(H8:H37) -> 5460281
A3: PROJECT # | G3: LEM TOTAL | H3: =SUM(J8:J37) -> 4886664.1
A4: E.W.R. # | E4: Percent Spent | H4: =H3/H1 -> 0.69731649
H6: INVOICED | I6: PO AMOUNT | J6: LEM TOTAL | K6: PO amount remaining from LEM total
A7: Sub Code | C7: Sub Description | E7: PO number | F7: Code | G7: PO AMOUNT (As of October 30th) | H7: TO DATE WITHOUT GST | I7: REMAINING WITHOUT GST
A8: 100 | B8: Vendor #1 | E8: 4500000000 | G8: 0 | H8: =SUMIF(H$86:I$227,A8,I$86:I$227) -> 0 | I8: =G8-H8 -> 0 | K8: =G8-J8 -> 0
A9: 103 | B9: Arete Design Solutions | E9: 4500091323 | G9: 90000 | H9: =SUMIF(H$86:I$281,A9,I$86:I$281) -> 87775 | I9: =G9-H9 -> 2225 | J9: =SUM('Arete Design Solutions'!R5) -> 87775 | K9: =G9-J9 -> 2225
A10: 104 | B10: Vendor #3 | E10: 4500000002 | G10: 70000 | H10: =SUMIF(H$86:I$281,A10,I$86:I$281) -> 36050 | I10: =G10-H10 -> 33950 | J10: ='Vendor #3'!AA5 -> 36050 | K10: =G10-J10 -> 33950
A11: 105 | B11: Vendor #4 | E11: 4500000003 | G11: 120000 | H11: =SUMIF(H$86:I$281,A11,I$86:I$281) -> 119300 | I11: =G11-H11 -> 700 | J11: =SUM('Vendor #4'!AB5) -> 116350 | K11: =G11-J11 -> 3650
A12: 106 | B12: Vendor #5 | E12: 4500000004 | G12: 25000 | H12: =SUMIF(H$86:I$227,A12,I$86:I$227) -> 15645.952 | I12: =G12-H12 -> 9354.0476 | J12: =H12 -> 15645.952 | K12: =G12-J12 -> 9354.0476
A13: 107 | B13: Vendor #6 | E13: 4500000005 | G13: =(74000+14800) -> 88800 | H13: =SUMIF(H$86:I$227,A13,I$86:I$227) -> 0 | I13: =G13-H13 -> 88800 | K13: =G13-J13 -> 88800
A14: 108 | B14: Vendor #7 | E14: 4500000006 | G14: 32500 | H14: =SUMIF(H$86:I$227,A14,I$86:I$227) -> 9675.2381 | I14: =G14-H14 -> 22824.762 | J14: =H14 -> 9675.2381 | K14: =G14-J14 -> 22824.762
A15: 109 | B15: Vendor #8 | E15: 4500000007 | G15: 210000 | H15: =SUMIF(H$86:H$575,A15,I$86:I$294) -> 193842 | I15: =G15-H15 -> 16158 | J15: =SUM('Vendor #8'!AA5) -> 193842 | K15: =G15-J15 -> 16158
A16: 110 | B16: Vendor #9 | E16: 4500000008 | G16: 12075 | H16: =SUMIF(H$86:I$227,A16,I$86:I$227) -> 9528.5714 | I16: =G16-H16 -> 2546.4286 | J16: =H16 -> 9528.5714 | K16: =G16-J16 -> 2546.4286
A17: 111 | B17: Vendor #10 | E17: 4500000009 | G17: 74347.94 | H17: =SUMIF(H$86:I$227,A17,I$86:I$227) -> 0 | I17: =G17-H17 -> 74347.94 | K17: =G17-J17 -> 74347.94
A18: 113 | B18: Vendor #11 | E18: 4500000010 | G18: 200000 | H18: =SUMIF(H$86:I$347,A18,I$86:I$354) -> 195250 | I18: =G18-H18 -> 4750 | J18: =SUM('Vendor #11'!AA5) -> 195250 | K18: =G18-J18 -> 4750
A19: 114 | B19: Vendor #12 | E19: 4500000011 | G19: 66300 | H19: =SUMIF(H$86:I$227,A19,I$86:I$227) -> 18245.5 | I19: =G19-H19 -> 48054.5 | J19: ='Vendor #12'!Y5 -> 18298 | K19: =G19-J19 -> 48002
A20: 115 | B20: Vendor #13 | E20: 4500000012 | G20: 140239 | H20: =SUMIF(H$86:I$289,A20,I$86:I$227) -> 131560.7 | I20: =G20-H20 -> 8678.3 | J20: =SUM('Vendor #13'!AA5) -> 131560.7 | K20: =G20-J20 -> 8678.3
A21: 116 | B21: Vendor #14- Survey | E21: 4500000013 | G21: 1374812 | H21: =SUMIF(H$86:I$343,A21,I$86:I$343) -> 1224133.5 | I21: =G21-H21 -> 150678.48 | J21: =SUM('Vendor #14'!AD7) -> 1224133.5 | K21: =G21-J21 -> 150678.49
A22: 120 | B22: Vendor #17 | E22: 4500000014 | G22: 94050 | H22: =SUMIF(H$86:I$302,A22,I$86:I$227) -> 85981 | I22: =G22-H22 -> 8069 | J22: =SUM('Vendor #17'!AG5) -> 89327 | K22: =G22-J22 -> 4723
A23: 121 | B23: Vendor #18 | E23: 4500000015 | G23: 950000 | H23: =SUMIF(H$86:I$281,A23,I$86:I$281) -> 848982.64 | I23: =G23-H23 -> 101017.36 | J23: =SUM('Vendor #18'!W5) -> 850360.14 | K23: =G23-J23 -> 99639.86
A24: 122 | B24: Vendor #19 | E24: 4500000016 | G24: 650000 | H24: =SUMIF(H$86:I$282,A24,I$86:I$282) -> 615159.5 | I24: =G24-H24 -> 34840.5 | J24: =SUM('Vendor #19'!AM5) -> 615159.5 | K24: =G24-J24 -> 34840.5
A25: 123 | B25: Vendor #20 | E25: 4500000017 | G25: 688004 | H25: =SUMIF(H$86:I$227,A25,I$86:I$227) -> 0 | I25: =G25-H25 -> 688004 | J25: =SUM('Vendor #20'!AW5) -> 228259.5 | K25: =G25-J25 -> 459744.5
A26: 125 | B26: Vendor #21 | E26: 4500000018 | G26: 117000 | H26: =SUMIF(H$86:I$227,A26,I$86:I$227) -> 117000 | I26: =G26-H26 -> 0 | J26: 117000 | K26: =G26-J26 -> 0
A27: 127 | B27: Vendor #23 | E27: 4500000019 | G27: 133650 | H27: =SUMIF(H$86:I$227,A27,I$86:I$227) -> 116045 | I27: =G27-H27 -> 17605 | J27: ='Vendor #23'!S5 -> 116045 | K27: =G27-J27 -> 17605
A28: 128 | B28: Vendor #24 | E28: 4500000020 | G28: 871045 | H28: =SUMIF(H$86:I$268,A28,I$86:I$262) -> 832506.4 | I28: =G28-H28 -> 38538.6 | J28: ='Vendor #24'!AJ4 -> 832404.02 | K28: =G28-J28 -> 38640.984
A29: 131 | B29: Vendor #27 | E29: 4500000021 | G29: 19990.9 | H29: =SUMIF(H$86:I$227,A29,I$86:I$227) -> 0 | I29: =G29-H29 -> 19990.9 | J29: ='Vendor #27'!AF7 -> 0 | K29: =G29-J29 -> 19990.9
A30: 132 | B30: Vendor #28 | E30: 4500000022 | G30: 980000 | H30: =SUMIF(H$86:I$227,A30,I$86:I$227) -> 803600 | I30: =G30-H30 -> 176400
H31: =SUMIF(H$86:I$227,A31,I$86:I$227) -> 0 | I31: =G31-H31 -> 0
H32: =SUMIF(H$86:I$227,A32,I$86:I$227) -> 0 | I32: =G32-H32 -> 0
H33: =SUMIF(H$86:I$227,A33,I$86:I$227) -> 0 | I33: =G33-H33 -> 0
A34: 136 | G34: 0 | H34: =SUMIF(H$86:I$227,A34,I$86:I$227) -> 0 | I34: =G34-H34 -> 0
A35: 137 | G35: 0 | H35: =SUMIF(H$86:I$227,A35,I$86:I$227) -> 0 | I35: =G35-H35 -> 0
A36: 138 | G36: 0 | H36: =SUMIF(H$86:I$227,A36,I$86:I$227) -> 0 | I36: =G36-H36 -> 0
A37: 139 | G37: 0 | H37: =SUMIF(H$86:I$227,A37,I$86:I$227) -> 0 | I37: =G37-H37 -> 0
A38: 140 | G38: 0 | H38: =SUMIF(H$86:I$227,A38,I$86:I$227) -> 0 | I38: =G38-H38 -> 0
A39: 141 | G39: 0 | H39: =SUMIF(H$86:I$227,A39,I$86:I$227) -> 0 | I39: =G39-H39 -> 0
A40: 142 | G40: 0 | H40: =SUMIF(H$86:I$227,A40,I$86:I$227) -> 0 | I40: =G40-H40 -> 0
A41: 143 | G41: 0 | H41: =SUMIF(H$86:I$227,A41,I$86:I$227) -> 0 | I41: =G41-H41 -> 0
A42: 144 | G42: 0 | H42: =SUMIF(H$86:I$227,A42,I$86:I$227) -> 0 | I42: =G42-H42 -> 0
A43: 145 | G43: 0 | H43: =SUMIF(H$86:I$227,A43,I$86:I$227) -> 0 | I43: =G43-H43 -> 0
A44: 146 | G44: 0 | H44: =SUMIF(H$86:I$227,A44,I$86:I$227) -> 0 | I44: =G44-H44 -> 0
A45: 147 | G45: 0 | H45: =SUMIF(H$86:I$227,A45,I$86:I$227) -> 0 | I45: =G45-H45 -> 0
... A83: 185 | G83: 0 | H83: =SUMIF(H$86:I$227,A83,I$86:I$227) -> 0 | I83: =G83-H83 -> 0
A85: DATE ENTERED | B85: INVOICE # | C85: TYPE | D85: VENDOR # | E85: Vendor Name | H85: Sub Code | I85: without GST / Inv Amt.
A86: 42124 | B86: 2015-10 | C86: Apr 16-30 | D86: 11117 | H86: 109 | I86: 1360
A87: 42139 | B87: 2015-12 | C87: May 1-15 | D87: 11117 | H87: 109 | I87: 2980
A88: 42155 | B88: 2015-14 | C88: May 16-31 | D88: 11117 | H88: 109 | I88: 9400
A89: 42179 | B89: 2015-15 | C89: June 1-15 | D89: 11117 | H89: 109 | I89: 14300
A90: 42186 | B90: 2015-17 | C90: June 16-30 | D90: 11117 | H90: 109 | I90: 19050
A91: 42201 | B91: 2015-18 | C91: July 1-15 | D91: 11117 | H91: 109 | I91: 19900
A92: 42219 | B92: 2015-19 | C92: July 16-31 | D92: 11117 | H92: 109 | I92: 22700
A93: 42232 | B93: 2015-20 | C93: August 1-15 | D93: 11117 | H93: 109 | I93: 13700
A94: 42255 | B94: 2015-21 | C94: Aug 16- 31, 2015 | D94: 11117 | H94: 109 | I94: 20100
A95: 42230 | B95: 1219 | C95: July 7-31 | H95: 114 | I95: 1372
A96: 42243 | B96: 1232 | C96: 42242 | H96: 114 | I96: 2794
A97: 42243 | B97: 1204 | C97: 42193 | H97: 114 | I97: 1490
A98: 42243 | B98: 1205 | C98: 42208 | H98: 114 | I98: 3360.5
A99: 42243 | B99: 1209 | C99: 42208 | H99: 114 | I99: 150
A100: 42243 | B100: 1192 | C100: 42172 | H100: 114 | I100: 6237
A101: 42243 | B101: 1194 | C101: 42179 | H101: 114 | I101: 825
A102: 42158 | B102: N/A | C102: PREVIOUS PO SPEND | D102: 112431 | H102: 110 | I102: =10005/1.05 -> 9528.5714
A103: 42216 | B103: 1001037136 | C103: July 1-31 | H103: 122 | I103: 191330
A104: 42212 | B104: 145167 | C104: June 1-15 | H104: 124 | I104: 1575
A105: 42227 | B105: 145750 | C105: 42204 | H105: 124 | I105: 1050
A106: 42235 | B106: 145931 | C106: July 28-31 | H106: 124 | I106: 16210
A107: 42235 | B107: 145932 | C107: Aug 1-14 | H107: 124 | I107: 5260
A108: 42257 | B108: 146059 | C108: Aug 16- 31, 2015 | H108: 124 | I108: 8404
A109: 42257 | B109: 146060 | C109: Aug 16- 31, 2015 | H109: 124 | I109: 9831
A110: 42233 | B110: 31 | C110: August 1-15 | D110: 110011 | H110: 104 | I110: 10475
A111: 42256 | B111: 32 | C111: Aug 16- 31, 2015 | H111: 104 | I111: 19700
A112: 42166 | B112: 48 | C112: May 1-31 | H112: 113 | I112: 11250
A113: 42186 | B113: 49 | C113: June 1-30 | H113: 113 | I113: 38000
A114: 42237 | B114: 50 | C114: July 1-31 | H114: 113 | I114: 37225
A115: 42257 | B115: 51 | C115: Aug 1- 31, 2015 | H115: 113 | I115: 32450
A116: 42163 | B116: 2015-047 | C116: May 1-31 | H116: 119 | I116: 13200
A117: 42178 | B117: 2015-048 | C117: June 1-15 | H117: 119 | I117: 27371
A118: 42207 | B118: 2015-050 | C118: June 16-30 | H118: 119 | I118: 76910
A119: 42229 | B119: 2015-052 | C119: July 16-31 | H119: 119 | I119: 222638
A120: 42200 | B120: 2015-051 | C120: July 1-15 | H120: 119 | I120: 151394
A121: 42241 | B121: 2015-053 | C121: Aug 1-15 | H121: 119 | I121: 287577
A122: 42185 | B122: 043-15 | C122: June 16-30 | H122: 127 | I122: 20415
A123: 42202 | B123: 043-16 | C123: July 1-15 | H123: 127 | I123: 23210
A124: 42241 | B124: 043-17 | C124: July 16-31 | H124: 127 | I124: 23260
A125: 42241 | B125: 043-18 | C125: Aug 1-15 | H125: 127 | I125: 18950
A126: 42256 | B126: 043-19 | C126: Aug 16- 31, 2015 | H126: 127 | I126: 21110
A127: 42158 | B127: N/A | C127: PREVIOUS PO SPEND | D127: 112406 | H127: 108 | I127: =(10159/1.05) -> 9675.2381
A128: 42222 | B128: 12416 | C128: July 27 - Aug 1 | H128: 121 | I128: 80657.5
A129: 42241 | B129: 12574 | C129: Aug 13-14 | H129: 121 | I129: 30742.5
A130: 42241 | B130: 12545 | C130: Aug 10-12 | H130: 121 | I130: 37785
A131: 42241 | B131: 12503 | C131: Aug 7-8 | H131: 121 | I131: 25822.5
A132: 42241 | B132: 12502 | C132: Aug 3-6 | H132: 121 | I132: 48297.5
A133: 42241 | B133: 12343 | C133: 42206 | H133: 121 | I133: 1860
A134: 42241 | B134: 12339 | C134: 42204 | H134: 121 | I134: 3085
A135: 42241 | B135: 12266 | C135: July 10-11 | H135: 121 | I135: 9955
A136: 42241 | B136: 12299 | C136: July 14-20 | H136: 121 | I136: 18770
A137: 42241 | B137: 12194 | C137: July 3-9 | H137: 121 | I137: 42420
A138: 42241 | B138: 12147 | C138: June 29-July 2 | H138: 121 | I138: 13330
A139: 42241 | B139: 12360 | C139: July 21-23 | H139: 121 | I139: 28412.5
...

Sheet Arete Design Solutions
A2: Arete Design Solutions
A4: Date | B4: Straight Hours Charged (ea.) | C4: Robert | D4: Rate | E4: Truck | F4: Rate | G4: Sub | H4: Rate | I4: KM's over 200 | J4: Rate | K4: Quad | L4: Rate | M4: Subtotal | N4: GST | O4: LEM Amount | P4: Affiliating Invoice | Q4: Approved By | R4: SUM OF ALL LEM'S (before GST)
R5: =SUM(M6:M156) -> 87775
A6: 42176 | C6: 1 | D6: 1100 | E6: 1 | F6: 200 | G6: 1 | H6: 175 | I6: 150 | J6: 1 | L6: 150 | M6: =(C6*D6)+(E6*F6)+(G6*H6)+(I6*J6)+(K6*L6) -> 1625 | N6: =(M6*5%) -> 81.25 | O6: =SUM(M6+N6) -> 1706.25 | P6: 0032
A7: 42177 | C7: 1 | D7: 1100 | E7: 1 | F7: 200 | G7: 1 | H7: 175 | J7: 1 | L7: 150 | M7: =(C7*D7)+(E7*F7)+(G7*H7)+(I7*J7)+(K7*L7) -> 1475 | N7: =(M7*5%) -> 73.75 | O7: =SUM(M7+N7) -> 1548.75 | P7: 0032
A8: 42178 | C8: 1 | D8: 1100 | E8: 1 | F8: 200 | G8: 1 | H8: 175 | J8: 1 | L8: 150 | M8: =(C8*D8)+(E8*F8)+(G8*H8)+(I8*J8)+(K8*L8) -> 1475 | N8: =(M8*5%) -> 73.75 | O8: =SUM(M8+N8) -> 1548.75 | P8: 0032
A9: 42179 | C9: 1 | D9: 1100 | E9: 1 | F9: 200 | G9: 1 | H9: 175 | J9: 1 | L9: 150 | M9: =(C9*D9)+(E9*F9)+(G9*H9)+(I9*J9)+(K9*L9) -> 1475 | N9: =(M9*5%) -> 73.75 | O9: =SUM(M9+N9) -> 1548.75 | P9: 0032
A10: 42180 | C10: 1 | D10: 1100 | E10: 1 | F10: 200 | G10: 1 | H10: 175 | J10: 1 | L10: 150 | M10: =(C10*D10)+(E10*F10)+(G10*H10)+(I10*J10)+(K10*L10) -> 1475 | N10: =(M10*5%) -> 73.75 | O10: =SUM(M10+N10) -> 1548.75 | P10: 0032
A11: 42181 | C11: 1 | D11: 1100 | E11: 1 | F11: 200 | G11: 1 | H11: 175 | J11: 1 | L11: 150 | M11: =(C11*D11)+(E11*F11)+(G11*H11)+(I11*J11)+(K11*L11) -> 1475 | N11: =(M11*5%) -> 73.75 | O11: =SUM(M11+N11) -> 1548.75 | P11: 0032
A12: 42182 | C12: 1 | D12: 1100 | E12: 1 | F12: 200 | G12: 1 | H12: 175 | J12: 1 | L12: 150 | M12: =(C12*D12)+(E12*F12)+(G12*H12)+(I12*J12)+(K12*L12) -> 1475 | N12: =(M12*5%) -> 73.75 | O12: =SUM(M12+N12) -> 1548.75 | P12: 0032
A13: 42183 | D13: 1100 | F13: 200 | G13: 1 | H13: 175 | J13: 1 | L13: 150 | M13: =(C13*D13)+(E13*F13)+(G13*H13)+(I13*J13)+(K13*L13) -> 175 | N13: =(M13*5%) -> 8.75 | O13: =SUM(M13+N13) -> 183.75 | P13: 0032
A14: 42184 | C14: 1 | D14: 1100 | E14: 1 | F14: 200 | G14: 1 | H14: 175 | J14: 1 | L14: 150 | M14: =(C14*D14)+(E14*F14)+(G14*H14)+(I14*J14)+(K14*L14) -> 1475 | N14: =(M14*5%) -> 73.75 | O14: =SUM(M14+N14) -> 1548.75 | P14: 0032
A15: 42185 | C15: 1 | D15: 1100 | E15: 1 | F15: 200 | G15: 1 | H15: 175 | J15: 1 | L15: 150 | M15: =(C15*D15)+(E15*F15)+(G15*H15)+(I15*J15)+(K15*L15) -> 1475 | N15: =(M15*5%) -> 73.75 | O15: =SUM(M15+N15) -> 1548.75 | P15: 0032
A16: 42186 | C16: 1 | D16: 1100 | E16: 1 | F16: 200 | G16: 1 | H16: 175 | J16: 1 | L16: 150 | M16: =(C16*D16)+(E16*F16)+(G16*H16)+(I16*J16)+(K16*L16) -> 1475 | N16: =(M16*5%) -> 73.75 | O16: =SUM(M16+N16) -> 1548.75 | P16: 0033
A17: 42187 | C17: 1 | D17: 1100 | E17: 1 | F17: 200 | G17: 1 | H17: 175 | J17: 1 | L17: 150 | M17: =(C17*D17)+(E17*F17)+(G17*H17)+(I17*J17)+(K17*L17) -> 1475 | N17: =(M17*5%) -> 73.75 | O17: =SUM(M17+N17) -> 1548.75 | P17: 0033
A18: 42188 | C18: 1 | D18: 1100 | E18: 1 | F18: 200 | G18: 1 | H18: 175 | J18: 1 | L18: 150 | M18: =(C18*D18)+(E18*F18)+(G18*H18)+(I18*J18)+(K18*L18) -> 1475 | N18: =(M18*5%) -> 73.75 | O18: =SUM(M18+N18) -> 1548.75 | P18: 0033
A19: 42189 | C19: 1 | D19: 1100 | E19: 1 | F19: 200 | G19: 1 | H19: 175 | J19: 1 | L19: 150 | M19: =(C19*D19)+(E19*F19)+(G19*H19)+(I19*J19)+(K19*L19) -> 1475 | N19: =(M19*5%) -> 73.75 | O19: =SUM(M19+N19) -> 1548.75 | P19: 0033
A20: 42190 | G20: 1 | H20: 175 | J20: 1 | L20: 150 | M20: =(C20*D20)+(E20*F20)+(G20*H20)+(I20*J20)+(K20*L20) -> 175 | N20: =(M20*5%) -> 8.75 | O20: =SUM(M20+N20) -> 183.75 | P20: 0033
A21: 42191 | C21: 1 | D21: 1100 | E21: 1 | F21: 200 | G21: 1 | H21: 175 | J21: 1 | L21: 150 | M21: =(C21*D21)+(E21*F21)+(G21*H21)+(I21*J21)+(K21*L21) -> 1475 | N21: =(M21*5%) -> 73.75 | O21: =SUM(M21+N21) -> 1548.75 | P21: 0033
A22: 42192 | C22: 1 | D22: 1100 | E22: 1 | F22: 200 | G22: 1 | H22: 175 | J22: 1 | L22: 150 | M22: =(C22*D22)+(E22*F22)+(G22*H22)+(I22*J22)+(K22*L22) -> 1475 | N22: =(M22*5%) -> 73.75 | O22: =SUM(M22+N22) -> 1548.75 | P22: 0033
A23: 42193 | C23: 1 | D23: 1100 | E23: 1 | F23: 200 | G23: 1 | H23: 175 | J23: 1 | L23: 150 | M23: =(C23*D23)+(E23*F23)+(G23*H23)+(I23*J23)+(K23*L23) -> 1475 | N23: =(M23*5%) -> 73.75 | O23: =SUM(M23+N23) -> 1548.75 | P23: 0033
A24: 42194 | C24: 1 | D24: 1100 | E24: 1 | F24: 200 | G24: 1 | H24: 175 | J24: 1 | L24: 150 | M24: =(C24*D24)+(E24*F24)+(G24*H24)+(I24*J24)+(K24*L24) -> 1475 | N24: =(M24*5%) -> 73.75 | O24: =SUM(M24+N24) -> 1548.75 | P24: 0033
A25: 42195 | C25: 1 | D25: 1100 | E25: 1 | F25: 200 | G25: 1 | H25: 175 | J25: 1 | L25: 150 | M25: =(C25*D25)+(E25*F25)+(G25*H25)+(I25*J25)+(K25*L25) -> 1475 | N25: =(M25*5%) -> 73.75 | O25: =SUM(M25+N25) -> 1548.75 | P25: 0033
A26: 42196 | C26: 1 | D26: 1100 | E26: 1 | F26: 200 | G26: 1 | H26: 175 | J26: 1 | L26: 150 | M26: =(C26*D26)+(E26*F26)+(G26*H26)+(I26*J26)+(K26*L26) -> 1475 | N26: =(M26*5%) -> 73.75 | O26: =SUM(M26+N26) -> 1548.75 | P26: 0033
A27: 42197 | D27: 1100 | F27: 200 | G27: 1 | H27: 175 | J27: 1 | L27: 150 | M27: =(C27*D27)+(E27*F27)+(G27*H27)+(I27*J27)+(K27*L27) -> 175 | N27: =(M27*5%) -> 8.75 | O27: =SUM(M27+N27) -> 183.75 | P27: 0033
A28: 42198 | D28: 1100 | F28: 200 | G28: 1 | H28: 175 | J28: 1 | L28: 150 | M28: =(C28*D28)+(E28*F28)+(G28*H28)+(I28*J28)+(K28*L28) -> 175 | N28: =(M28*5%) -> 8.75 | O28: =SUM(M28+N28) -> 183.75 | P28: 0033
A29: 42199 | C29: 1 | D29: 1100 | E29: 1 | F29: 200 | G29: 1 | H29: 175 | J29: 1 | L29: 150 | M29: =(C29*D29)+(E29*F29)+(G29*H29)+(I29*J29)+(K29*L29) -> 1475 | N29: =(M29*5%) -> 73.75 | O29: =SUM(M29+N29) -> 1548.75 | P29: 0033
A30: 42200 | C30: 1 | D30: 1100 | E30: 1 | F30: 200 | G30: 1 | H30: 175 | J30: 1 | L30: 150 | M30: =(C30*D30)+(E30*F30)+(G30*H30)+(I30*J30)+(K30*L30) -> 1475 | N30: =(M30*5%) -> 73.75 | O30: =SUM(M30+N30) -> 1548.75 | P30: 0033
A31: 42201 | C31: 1 | D31: 1100 | E31: 1 | F31: 200 | G31: 1 | H31: 175 | J31: 1 | L31: 150 | M31: =(C31*D31)+(E31*F31)+(G31*H31)+(I31*J31)+(K31*L31) -> 1475 | N31: =(M31*5%) -> 73.75 | O31: =SUM(M31+N31) -> 1548.75 | P31: 0034
A32: 42202 | D32: 1100 | F32: 200 | G32: 1 | H32: 175 | J32: 1 | L32: 150 | M32: =(C32*D32)+(E32*F32)+(G32*H32)+(I32*J32)+(K32*L32) -> 175 | N32: =(M32*5%) -> 8.75 | O32: =SUM(M32+N32) -> 183.75 | P32: 0034
A33: 42203 | D33: 1100 | F33: 200 | G33: 1 | H33: 175 | J33: 1 | L33: 150 | M33: =(C33*D33)+(E33*F33)+(G33*H33)+(I33*J33)+(K33*L33) -> 175 | N33: =(M33*5%) -> 8.75 | O33: =SUM(M33+N33) -> 183.75 | P33: 0034
A34: 42204 | D34: 1100 | F34: 200 | G34: 1 | H34: 175 | J34: 1 | L34: 150 | M34: =(C34*D34)+(E34*F34)+(G34*H34)+(I34*J34)+(K34*L34) -> 175 | N34: =(M34*5%) -> 8.75 | O34: =SUM(M34+N34) -> 183.75 | P34: 0034
A35: 42205 | C35: 1 | D35: 1100 | E35: 1 | F35: 200 | G35: 1 | H35: 175 | J35: 1 | L35: 150 | M35: =(C35*D35)+(E35*F35)+(G35*H35)+(I35*J35)+(K35*L35) -> 1475 | N35: =(M35*5%) -> 73.75 | O35: =SUM(M35+N35) -> 1548.75 | P35: 0034
A36: 42206 | C36: 1 | D36: 1100 | E36: 1 | F36: 200 | G36: 1 | H36: 175 | J36: 1 | L36: 150 | M36: =(C36*D36)+(E36*F36)+(G36*H36)+(I36*J36)+(K36*L36) -> 1475 | N36: =(M36*5%) -> 73.75 | O36: =SUM(M36+N36) -> 1548.75 | P36: 0034
A37: 42207 | C37: 1 | D37: 1100 | E37: 1 | F37: 200 | G37: 1 | H37: 175 | J37: 1 | L37: 150 | M37: =(C37*D37)+(E37*F37)+(G37*H37)+(I37*J37)+(K37*L37) -> 1475 | N37: =(M37*5%) -> 73.75 | O37: =SUM(M37+N37) -> 1548.75 | P37: 0034
A38: 42208 | C38: 1 | D38: 1100 | E38: 1 | F38: 200 | G38: 1 | H38: 175 | J38: 1 | L38: 150 | M38: =(C38*D38)+(E38*F38)+(G38*H38)+(I38*J38)+(K38*L38) -> 1475 | N38: =(M38*5%) -> 73.75 | O38: =SUM(M38+N38) -> 1548.75 | P38: 0034 | Q38: =SUM(M31:M46) -> 18400
A39: 42209 | C39: 1 | D39: 1100 | E39: 1 | F39: 200 | G39: 1 | H39: 175 | J39: 1 | L39: 150 | M39: =(C39*D39)+(E39*F39)+(G39*H39)+(I39*J39)+(K39*L39) -> 1475 | N39: =(M39*5%) -> 73.75 | O39: =SUM(M39+N39) -> 1548.75 | P39: 0034
A40: 42210 | C40: 1 | D40: 1100 | E40: 1 | F40: 200 | G40: 1 | H40: 175 | J40: 1 | L40: 150 | M40: =(C40*D40)+(E40*F40)+(G40*H40)+(I40*J40)+(K40*L40) -> 1475 | N40: =(M40*5%) -> 73.75 | O40: =SUM(M40+N40) -> 1548.75 | P40: 0034
A41: 42211 | D41: 1100 | F41: 200 | G41: 1 | H41: 175 | J41: 1 | L41: 150 | M41: =(C41*D41)+(E41*F41)+(G41*H41)+(I41*J41)+(K41*L41) -> 175 | N41: =(M41*5%) -> 8.75 | O41: =SUM(M41+N41) -> 183.75 | P41: 0034
A42: 42212 | C42: 1 | D42: 1100 | E42: 1 | F42: 200 | G42: 1 | H42: 175 | J42: 1 | L42: 150 | M42: =(C42*D42)+(E42*F42)+(G42*H42)+(I42*J42)+(K42*L42) -> 1475 | N42: =(M42*5%) -> 73.75 | O42: =SUM(M42+N42) -> 1548.75 | P42: 0034
A43: 42213 | C43: 1 | D43: 1100 | E43: 1 | F43: 200 | G43: 1 | H43: 175 | J43: 1 | L43: 150 | M43: =(C43*D43)+(E43*F43)+(G43*H43)+(I43*J43)+(K43*L43) -> 1475 | N43: =(M43*5%) -> 73.75 | O43: =SUM(M43+N43) -> 1548.75 | P43: 0034
A44: 42214 | C44: 1 | D44: 1100 | E44: 1 | F44: 200 | G44: 1 | H44: 175 | J44: 1 | L44: 150 | M44: =(C44*D44)+(E44*F44)+(G44*H44)+(I44*J44)+(K44*L44) -> 1475 | N44: =(M44*5%) -> 73.75 | O44: =SUM(M44+N44) -> 1548.75 | P44: 0034
A45: 42215 | C45: 1 | D45: 1100 | E45: 1 | F45: 200 | G45: 1 | H45: 175 | J45: 1 | L45: 150 | M45: =(C45*D45)+(E45*F45)+(G45*H45)+(I45*J45)+(K45*L45) -> 1475 | N45: =(M45*5%) -> 73.75 | O45: =SUM(M45+N45) -> 1548.75 | P45: 0034
A46: 42216 | C46: 1 | D46: 1100 | E46: 1 | F46: 200 | G46: 1 | H46: 175 | J46: 1 | L46: 150 | M46: =(C46*D46)+(E46*F46)+(G46*H46)+(I46*J46)+(K46*L46) -> 1475 | N46: =(M46*5%) -> 73.75 | O46: =SUM(M46+N46) -> 1548.75 | P46: 0034
A47: 42217 | C47: 1 | D47: 1100 | E47: 1 | F47: 200 | G47: 1 | H47: 175 | J47: 1 | L47: 150 | M47: =(C47*D47)+(E47*F47)+(G47*H47)+(I47*J47)+(K47*L47) -> 1475 | N47: =(M47*5%) -> 73.75 | O47: =SUM(M47+N47) -> 1548.75 | P47: 0035
A48: 42218 | D48: 1100 | F48: 200 | G48: 1 | H48: 175 | J48: 1 | L48: 150 | M48: =(C48*D48)+(E48*F48)+(G48*H48)+(I48*J48)+(K48*L48) -> 175 | N48: =(M48*5%) -> 8.75 | O48: =SUM(M48+N48) -> 183.75 | P48: 0035
A49: 42219 | C49: 1 | D49: 1100 | E49: 1 | F49: 200 | G49: 1 | H49: 175 | J49: 1 | L49: 150 | M49: =(C49*D49)+(E49*F49)+(G49*H49)+(I49*J49)+(K49*L49) -> 1475 | N49: =(M49*5%) -> 73.75 | O49: =SUM(M49+N49) -> 1548.75 | P49: 0035
A50: 42220 | C50: 1 | D50: 1100 | E50: 1 | F50: 200 | G50: 1 | H50: 175 | J50: 1 | L50: 150 | M50: =(C50*D50)+(E50*F50)+(G50*H50)+(I50*J50)+(K50*L50) -> 1475 | N50: =(M50*5%) -> 73.75 | O50: =SUM(M50+N50) -> 1548.75 | P50: 0035
A51: 42221 | C51: 1 | D51: 1100 | E51: 1 | F51: 200 | G51: 1 | H51: 175 | J51: 1 | L51: 150 | M51: =(C51*D51)+(E51*F51)+(G51*H51)+(I51*J51)+(K51*L51) -> 1475 | N51: =(M51*5%) -> 73.75 | O51: =SUM(M51+N51) -> 1548.75 | P51: 0035
A52: 42222 | C52: 1 | D52: 1100 | E52: 1 | F52: 200 | G52: 1 | H52: 175 | J52: 1 | L52: 150 | M52: =(C52*D52)+(E52*F52)+(G52*H52)+(I52*J52)+(K52*L52) -> 1475 | N52: =(M52*5%) -> 73.75 | O52: =SUM(M52+N52) -> 1548.75 | P52: 0035
A53: 42223 | C53: 1 | D53: 1100 | E53: 1 | F53: 200 | G53: 1 | H53: 175 | J53: 1 | L53: 150 | M53: =(C53*D53)+(E53*F53)+(G53*H53)+(I53*J53)+(K53*L53) -> 1475 | N53: =(M53*5%) -> 73.75 | O53: =SUM(M53+N53) -> 1548.75 | P53: 0035
A54: 42224 | C54: 1 | D54: 1100 | E54: 1 | F54: 200 | G54: 1 | H54: 175 | J54: 1 | L54: 150 | M54: =(C54*D54)+(E54*F54)+(G54*H54)+(I54*J54)+(K54*L54) -> 1475 | N54: =(M54*5%) -> 73.75 | O54: =SUM(M54+N54) -> 1548.75 | P54: 0035
A55: 42225 | D55: 1100 | F55: 200 | G55: 1 | H55: 175 | J55: 1 | L55: 150 | M55: =(C55*D55)+(E55*F55)+(G55*H55)+(I55*J55)+(K55*L55) -> 175 | N55: =(M55*5%) -> 8.75 | O55: =SUM(M55+N55) -> 183.75 | P55: 0035
A56: 42226 | C56: 1 | D56: 1100 | E56: 1 | F56: 200 | G56: 1 | H56: 175 | J56: 1 | L56: 150 | M56: =(C56*D56)+(E56*F56)+(G56*H56)+(I56*J56)+(K56*L56) -> 1475 | N56: =(M56*5%) -> 73.75 | O56: =SUM(M56+N56) -> 1548.75 | P56: 0035
A57: 42227 | C57: 1 | D57: 1100 | E57: 1 | F57: 200 | G57: 1 | H57: 175 | J57: 1 | L57: 150 | M57: =(C57*D57)+(E57*F57)+(G57*H57)+(I57*J57)+(K57*L57) -> 1475 | N57: =(M57*5%) -> 73.75 | O57: =SUM(M57+N57) -> 1548.75 | P57: 0035
A58: 42228 | C58: 1 | D58: 1100 | E58: 1 | F58: 200 | G58: 1 | H58: 175 | J58: 1 | L58: 150 | M58: =(C58*D58)+(E58*F58)+(G58*H58)+(I58*J58)+(K58*L58) -> 1475 | N58: =(M58*5%) -> 73.75 | O58: =SUM(M58+N58) -> 1548.75 | P58: 0035
A59: 42229 | C59: 1 | D59: 1100 | E59: 1 | F59: 200 | G59: 1 | H59: 175 | J59: 1 | L59: 150 | M59: =(C59*D59)+(E59*F59)+(G59*H59)+(I59*J59)+(K59*L59) -> 1475 | N59: =(M59*5%) -> 73.75 | O59: =SUM(M59+N59) -> 1548.75 | P59: 0035
A60: 42230 | C60: 1 | D60: 1100 | E60: 1 | F60: 200 | G60: 1 | H60: 175 | J60: 1 | L60: 150 | M60: =(C60*D60)+(E60*F60)+(G60*H60)+(I60*J60)+(K60*L60) -> 1475 | N60: =(M60*5%) -> 73.75 | O60: =SUM(M60+N60) -> 1548.75 | P60: 0035
A61: 42231 | C61: 1 | D61: 1100 | E61: 1 | F61: 200 | G61: 1 | H61: 175 | J61: 1 | L61: 150 | M61: =(C61*D61)+(E61*F61)+(G61*H61)+(I61*J61)+(K61*L61) -> 1475 | N61: =(M61*5%) -> 73.75 | O61: =SUM(M61+N61) -> 1548.75 | P61: 0035
A62: 42232 | D62: 1100 | F62: 200 | G62: 1 | H62: 175 | J62: 1 | L62: 150 | M62: =(C62*D62)+(E62*F62)+(G62*H62)+(I62*J62)+(K62*L62) -> 175 | N62: =(M62*5%) -> 8.75 | O62: =SUM(M62+N62) -> 183.75 | P62: 0037
A63: 42233 | C63: 1 | D63: 1100 | E63: 1 | F63: 200 | G63: 1 | H63: 175 | J63: 1 | L63: 150 | M63: =(C63*D63)+(E63*F63)+(G63*H63)+(I63*J63)+(K63*L63) -> 1475 | N63: =(M63*5%) -> 73.75 | O63: =SUM(M63+N63) -> 1548.75 | P63: 0037
A64: 42234 | C64: 1 | D64: 1100 | E64: 1 | F64: 200 | G64: 1 | H64: 175 | J64: 1 | L64: 150 | M64: =(C64*D64)+(E64*F64)+(G64*H64)+(I64*J64)+(K64*L64) -> 1475 | N64: =(M64*5%) -> 73.75 | O64: =SUM(M64+N64) -> 1548.75 | P64: 0037
A65: 42235 | D65: 1100 | F65: 200 | H65: 175 | J65: 1 | L65: 150 | M65: =(C65*D65)+(E65*F65)+(G65*H65)+(I65*J65)+(K65*L65) -> 0 | N65: =(M65*5%) -> 0 | O65: =SUM(M65+N65) -> 0 | P65: 0037
A66: 42240 | C66: 0 | D66: 1100 | F66: 200 | H66: 175 | J66: 1 | L66: 150 | M66: =(C66*D66)+(E66*F66)+(G66*H66)+(I66*J66)+(K66*L66) -> 0 | N66: =(M66*5%) -> 0 | O66: =SUM(M66+N66) -> 0 | P66: 0037
A67: 42241 | C67: 1 | D67: 1100 | E67: 1 | F67: 200 | G67: 1 | H67: 175 | J67: 1 | L67: 150 | M67: =(C67*D67)+(E67*F67)+(G67*H67)+(I67*J67)+(K67*L67) -> 1475 | N67: =(M67*5%) -> 73.75 | O67: =SUM(M67+N67) -> 1548.75 | P67: 0037
A68: 42242 | C68: 1 | D68: 1100 | E68: 1 | F68: 200 | G68: 1 | H68: 175 | J68: 1 | L68: 150 | M68: =(C68*D68)+(E68*F68)+(G68*H68)+(I68*J68)+(K68*L68) -> 1475 | N68: =(M68*5%) -> 73.75 | O68: =SUM(M68+N68) -> 1548.75 | P68: 0037
A69: 42243 | C69: 1 | D69: 1100 | E69: 1 | F69: 200 | G69: 1 | H69: 175 | J69: 1 | L69: 150 | M69: =(C69*D69)+(E69*F69)+(G69*H69)+(I69*J69)+(K69*L69) -> 1475 | N69: =(M69*5%) -> 73.75 | O69: =SUM(M69+N69) -> 1548.75 | P69: 0037
A70: 42244 | C70: 1 | D70: 1100 | E70: 1 | F70: 200 | G70: 1 | H70: 175 | J70: 1 | L70: 150 | M70: =(C70*D70)+(E70*F70)+(G70*H70)+(I70*J70)+(K70*L70) -> 1475 | N70: =(M70*5%) -> 73.75 | O70: =SUM(M70+N70) -> 1548.75 | P70: 0037
A71: 42245 | C71: 1 | D71: 1100 | E71: 1 | F71: 200 | G71: 1 | H71: 175 | J71: 1 | L71: 150 | M71: =(C71*D71)+(E71*F71)+(G71*H71)+(I71*J71)+(K71*L71) -> 1475 | N71: =(M71*5%) -> 73.75 | O71: =SUM(M71+N71) -> 1548.75 | P71: 0037
A72: 42246 | D72: 1100 | F72: 200 | G72: 1 | H72: 175 | J72: 1 | L72: 150 | M72: =(C72*D72)+(E72*F72)+(G72*H72)+(I72*J72)+(K72*L72) -> 175 | N72: =(M72*5%) -> 8.75 | O72: =SUM(M72+N72) -> 183.75 | P72: 0037
A73: 42247 | C73: 1 | D73: 1100 | E73: 1 | F73: 200 | G73: 1 | H73: 175 | J73: 1 | L73: 150 | M73: =(C73*D73)+(E73*F73)+(G73*H73)+(I73*J73)+(K73*L73) -> 1475 | N73: =(M73*5%) -> 73.75 | O73: =SUM(M73+N73) -> 1548.75 | P73: 0037
A74: 42248 | C74: 1 | D74: 1100 | E74: 1 | F74: 200 | G74: 1 | H74: 175 | J74: 1 | L74: 150 | M74: =(C74*D74)+(E74*F74)+(G74*H74)+(I74*J74)+(K74*L74) -> 1475 | N74: =(M74*5%) -> 73.75 | O74: =SUM(M74+N74) -> 1548.75 | P74: 0038
A75: 42249 | C75: 1 | D75: 1100 | E75: 1 | F75: 200 | G75: 1 | H75: 175 | J75: 1 | L75: 150 | M75: =(C75*D75)+(E75*F75)+(G75*H75)+(I75*J75)+(K75*L75) -> 1475 | N75: =(M75*5%) -> 73.75 | O75: =SUM(M75+N75) -> 1548.75 | P75: 0038
A76: 42250 | C76: 1 | D76: 1100 | E76: 1 | F76: 200 | G76: 1 | H76: 175 | J76: 1 | L76: 150 | M76: =(C76*D76)+(E76*F76)+(G76*H76)+(I76*J76)+(K76*L76) -> 1475 | N76: =(M76*5%) -> 73.75 | O76: =SUM(M76+N76) -> 1548.75 | P76: 0038
A77: 42251 | C77: 1 | D77: 1100 | E77: 1 | F77: 200 | H77: 175 | I77: 150 | J77: 1 | L77: 150 | M77: =(C77*D77)+(E77*F77)+(G77*H77)+(I77*J77)+(K77*L77) -> 1450 | N77: =(M77*5%) -> 72.5 | O77: =SUM(M77+N77) -> 1522.5 | P77: 0038

Sheet Vendor #3
A2: Vendor #3
A4: Date | B4: Straight Hours Charged (ea.) | C4: Overtime Hours Charged (ea.) | D4: Vendor #3 | E4: DAY RATE | F4: Truck | G4: Subsistence | H4: Kms | S4: Total Hours Charged | T4: Equipment Detail | U4: Km's Charged | V4: Subtotal | W4: GST | X4: LEM Amount | Y4: Affiliating Invoice | Z4: Approved By | AA4: SUM OF ALL LEM'S (before GST)
A5: RATES | E5: 1100 | F5: 200 | G5: 1 | H5: 1 | AA5: =SUM(V5:V133) -> 36050
A6: 42225 | D6: 1 | E6: 1 | F6: 1 | G6: 175 | H6: 150 | V6: =SUM(E6*$E$5+F6*$F$5+G6*$G$5+H6*$H$5+I6*$I$5+J6*$J$5+K6*$K$5) -> 1625 | W6: =(V6*5%) -> 81.25 | X6: =SUM(V6+W6) -> 1706.25 | Y6: 31
A7: 42226 | D7: 1 | E7: 1 | F7: 1 | G7: 175 | V7: =SUM(E7*$E$5+F7*$F$5+G7*$G$5+H7*$H$5+I7*$I$5+J7*$J$5+K7*$K$5) -> 1475 | W7: =(V7*5%) -> 73.75 | X7: =SUM(V7+W7) -> 1548.75 | Y7: 31
A8: 42227 | D8: 1 | E8: 1 | F8: 1 | G8: 175 | V8: =SUM(E8*$E$5+F8*$F$5+G8*$G$5+H8*$H$5+I8*$I$5+J8*$J$5+K8*$K$5) -> 1475 | W8: =(V8*5%) -> 73.75 | X8: =SUM(V8+W8) -> 1548.75 | Y8: 31
A9: 42228 | D9: 1 | E9: 1 | F9: 1 | G9: 175 | V9: =SUM(E9*$E$5+F9*$F$5+G9*$G$5+H9*$H$5+I9*$I$5+J9*$J$5+K9*$K$5) -> 1475 | W9: =(V9*5%) -> 73.75 | X9: =SUM(V9+W9) -> 1548.75 | Y9: 31
A10: 42229 | D10: 1 | E10: 1 | F10: 1 | G10: 175 | V10: =SUM(E10*$E$5+F10*$F$5+G10*$G$5+H10*$H$5+I10*$I$5+J10*$J$5+K10*$K$5) -> 1475 | W10: =(V10*5%) -> 73.75 | X10: =SUM(V10+W10) -> 1548.75 | Y10: 31
A11: 42230 | D11: 1 | E11: 1 | F11: 1 | G11: 175 | V11: =SUM(E11*$E$5+F11*$F$5+G11*$G$5+H11*$H$5+I11*$I$5+J11*$J$5+K11*$K$5) -> 1475 | W11: =(V11*5%) -> 73.75 | X11: =SUM(V11+W11) -> 1548.75 | Y11: 31
A12: 42231 | D12: 1 | E12: 1 | F12: 1 | G12: 175 | V12: =SUM(E12*$E$5+F12*$F$5+G12*$G$5+H12*$H$5+I12*$I$5+J12*$J$5+K12*$K$5) -> 1475 | W12: =(V12*5%) -> 73.75 | X12: =SUM(V12+W12) -> 1548.75 | Y12: 31
A13: 42232 | D13: 0 | E13: 0 | F13: 0 | G13: 175 | V13: =SUM(E13*$E$5+F13*$F$5+G13*$G$5+H13*$H$5+I13*$I$5+J13*$J$5+K13*$K$5) -> 175 | W13: =(V13*5%) -> 8.75 | X13: =SUM(V13+W13) -> 183.75 | Y13: 32
A14: 42233 | D14: 1 | E14: 1 | F14: 1 | G14: 175 | V14: =SUM(E14*$E$5+F14*$F$5+G14*$G$5+H14*$H$5+I14*$I$5+J14*$J$5+K14*$K$5) -> 1475 | W14: =(V14*5%) -> 73.75 | X14: =SUM(V14+W14) -> 1548.75 | Y14: 32
A15: 42234 | D15: 1 | E15: 1 | F15: 1 | G15: 175 | V15: =SUM(E15*$E$5+F15*$F$5+G15*$G$5+H15*$H$5+I15*$I$5+J15*$J$5+K15*$K$5) -> 1475 | W15: =(V15*5%) -> 73.75 | X15: =SUM(V15+W15) -> 1548.75 | Y15: 32
A16: 42235 | D16: 1 | E16: 1 | F16: 1 | G16: 175 | V16: =SUM(E16*$E$5+F16*$F$5+G16*$G$5+H16*$H$5+I16*$I$5+J16*$J$5+K16*$K$5) -> 1475 | W16: =(V16*5%) -> 73.75 | X16: =SUM(V16+W16) -> 1548.75 | Y16: 32
A17: 42236 | D17: 1 | E17: 1 | F17: 1 | G17: 175 | V17: =SUM(E17*$E$5+F17*$F$5+G17*$G$5+H17*$H$5+I17*$I$5+J17*$J$5+K17*$K$5) -> 1475 | W17: =(V17*5%) -> 73.75 | X17: =SUM(V17+W17) -> 1548.75 | Y17: 32
A18: 42237 | D18: 1 | E18: 1 | F18: 1 | G18: 175 | V18: =SUM(E18*$E$5+F18*$F$5+G18*$G$5+H18*$H$5+I18*$I$5+J18*$J$5+K18*$K$5) -> 1475 | W18: =(V18*5%) -> 73.75 | X18: =SUM(V18+W18) -> 1548.75 | Y18: 32
... A26: 42245 | D26: 1 | E26: 1 | F26: 1 | G26: 175 | V26: =SUM(E26*$E$5+F26*$F$5+G26*$G$5+H26*$H$5+I26*$I$5+J26*$J$5+K26*$K$5) -> 1475 | W26: =(V26*5%) -> 73.75 | X26: =SUM(V26+W26) -> 1548.75 | Y26: 32
A27: 42246 | G27: 175 | V27: =SUM(E27*$E$5+F27*$F$5+G27*$G$5+H27*$H$5+I27*$I$5+J27*$J$5+K27*$K$5) -> 175 | W27: =(V27*5%) -> 8.75 | X27: =SUM(V27+W27) -> 183.75 | Y27: 32
A28: 42247 | D28: 1 | E28: 1 | F28: 1 | G28: 175 | V28: =SUM(E28*$E$5+F28*$F$5+G28*$G$5+H28*$H$5+I28*$I$5+J28*$J$5+K28*$K$5) -> 1475 | W28: =(V28*5%) -> 73.75 | X28: =SUM(V28+W28) -> 1548.75 | Y28: 32
A29: 42248 | D29: 1 | E29: 1 | F29: 1 | G29: 175 | V29: =SUM(E29*$E$5+F29*$F$5+G29*$G$5+H29*$H$5+I29*$I$5+J29*$J$5+K29*$K$5) -> 1475 | W29: =(V29*5%) -> 73.75 | X29: =SUM(V29+W29) -> 1548.75 | Y29: 33
A30: 42249 | D30: 1 | E30: 1 | F30: 1 | G30: 175 | V30: =SUM(E30*$E$5+F30*$F$5+G30*$G$5+H30*$H$5+I30*$I$5+J30*$J$5+K30*$K$5) -> 1475 | W30: =(V30*5%) -> 73.75 | X30: =SUM(V30+W30) -> 1548.75 | Y30: 33
A31: 42250 | D31: 1 | E31: 1 | F31: 1 | G31: 175 | V31: =SUM(E31*$E$5+F31*$F$5+G31*$G$5+H31*$H$5+I31*$I$5+J31*$J$5+K31*$K$5) -> 1475 | W31: =(V31*5%) -> 73.75 | X31: =SUM(V31+W31) -> 1548.75 | Y31: 33
A32: 42251 | D32: 1 | E32: 1 | F32: 1 | H32: 150 | V32: =SUM(E32*$E$5+F32*$F$5+G32*$G$5+H32*$H$5+I32*$I$5+J32*$J$5+K32*$K$5) -> 1450 | W32: =(V32*5%) -> 72.5 | X32: =SUM(V32+W32) -> 1522.5 | Y32: 33

Sheet Vendor #4
A2: Vendor #4
A4: Date | B4: Straight Hours Charged (ea.) | C4: Overtime Hours Charged (ea.) | D4: Vendor #4 | E4: Labourer class | F4: Rate | G4: Truck | H4: Rate | I4: Sub | J4: Rate | K4: KM's over 200 | L4: Rate | M4: Quad | N4: Rate | O4: Labourer class | P4: Rate | Q4: Labourer class | R4: Rate | S4: Total Labour Rate per hr | T4: Total Hours Charged | U4: Equipment Detail | V4: Km's Charged | W4: Subtotal | X4: GST | Y4: LEM Amount | Z4: Affiliating Invoice | AA4: Approved By | AB4: SUM OF ALL LEM'S (beforeGST)
AB5: =SUM(W6:W112) -> 116350
A6: 42149 | D6: 1 | F6: 1100 | G6: 1 | H6: 200 | I6: 1 | J6: 175 | K6: 150 | L6: 1 | N6: 150 | P6: 0 | R6: 0 | S6: =SUM(L6,J6,H6,F6) -> 1476 | T6: =(B6+C6)*D6 -> 0 | W6: =(D6*F6)+(G6*H6)+(I6*J6)+(K6*L6)+(M6*N6) -> 1625 | X6: =(W6*5%) -> 81.25 | Y6: =SUM(W6+X6) -> 1706.25 | Z6: 13
A7: 42150 | D7: 1 | F7: 1100 | G7: 1 | H7: 200 | I7: 1 | J7: 175 | L7: 1 | N7: 150 | P7: 0 | R7: 0 | S7: =SUM(L7,J7,H7,F7) -> 1476 | T7: =(B7+C7)*D7 -> 0 | W7: =(D7*F7)+(G7*H7)+(I7*J7)+(K7*L7)+(M7*N7) -> 1475 | X7: =(W7*5%) -> 73.75 | Y7: =SUM(W7+X7) -> 1548.75 | Z7: 13
A8: 42151 | D8: 1 | F8: 1100 | G8: 1 | H8: 200 | I8: 1 | J8: 175 | L8: 1 | N8: 150 | P8: 0 | R8: 0 | S8: =SUM(L8,J8,H8,F8) -> 1476 | T8: =(B8+C8)*D8 -> 0 | W8: =(D8*F8)+(G8*H8)+(I8*J8)+(K8*L8)+(M8*N8) -> 1475 | X8: =(W8*5%) -> 73.75 | Y8: =SUM(W8+X8) -> 1548.75 | Z8: 13
A9: 42152 | D9: 1 | F9: 1100 | G9: 1 | H9: 200 | I9: 1 | J9: 175 | L9: 1 | N9: 150 | P9: 0 | R9: 0 | S9: =SUM(L9,J9,H9,F9) -> 1476 | T9: =(B9+C9)*D9 -> 0 | W9: =(D9*F9)+(G9*H9)+(I9*J9)+(K9*L9)+(M9*N9) -> 1475 | X9: =(W9*5%) -> 73.75 | Y9: =SUM(W9+X9) -> 1548.75 | Z9: 13
A10: 42153 | D10: 1 | F10: 1100 | G10: 1 | H10: 200 | I10: 1 | J10: 175 | L10: 1 | N10: 150 | P10: 0 | R10: 0 | S10: =SUM(L10,J10,H10,F10) -> 1476 | T10: =(B10+C10)*D10 -> 0 | W10: =(D10*F10)+(G10*H10)+(I10*J10)+(K10*L10)+(M10*N10) -> 1475 | X10: =(W10*5%) -> 73.75 | Y10: =SUM(W10+X10) -> 1548.75 | Z10: 13
A11: 42156 | D11: 1 | F11: 1100 | G11: 1 | H11: 200 | I11: 1 | J11: 175 | L11: 1 | N11: 150 | P11: 0 | R11: 0 | S11: =SUM(L11,J11,H11,F11) -> 1476 | T11: =(B11+C11)*D11 -> 0 | W11: =(D11*F11)+(G11*H11)+(I11*J11)+(K11*L11)+(M11*N11) -> 1475 | X11: =(W11*5%) -> 73.75 | Y11: =SUM(W11+X11) -> 1548.75 | Z11: 14
A12: 42157 | D12: 1 | F12: 1100 | G12: 1 | H12: 200 | I12: 1 | J12: 175 | L12: 1 | N12: 150 | P12: 0 | R12: 0 | S12: =SUM(L12,J12,H12,F12) -> 1476 | T12: =(B12+C12)*D12 -> 0 | W12: =(D12*F12)+(G12*H12)+(I12*J12)+(K12*L12)+(M12*N12) -> 1475 | X12: =(W12*5%) -> 73.75 | Y12: =SUM(W12+X12) -> 1548.75 | Z12: 14
A13: 42158 | D13: 1 | F13: 1100 | G13: 1 | H13: 200 | I13: 1 | J13: 175 | L13: 1 | N13: 150 | P13: 0 | R13: 0 | S13: =SUM(L13,J13,H13,F13) -> 1476 | T13: =(B13+C13)*D13 -> 0 | W13: =(D13*F13)+(G13*H13)+(I13*J13)+(K13*L13)+(M13*N13) -> 1475 | X13: =(W13*5%) -> 73.75 | Y13: =SUM(W13+X13) -> 1548.75 | Z13: 14
A14: 42159 | D14: 1 | F14: 1100 | G14: 1 | H14: 200 | I14: 1 | J14: 175 | L14: 1 | N14: 150 | P14: 0 | R14: 0 | S14: =SUM(L14,J14,H14,F14) -> 1476 | T14: =(B14+C14)*D14 -> 0 | W14: =(D14*F14)+(G14*H14)+(I14*J14)+(K14*L14)+(M14*N14) -> 1475 | X14: =(W14*5%) -> 73.75 | Y14: =SUM(W14+X14) -> 1548.75 | Z14: 14
A15: 42160 | D15: 1 | F15: 1100 | G15: 1 | H15: 200 | I15: 1 | J15: 175 | L15: 1 | N15: 150 | P15: 0 | R15: 0 | S15: =SUM(L15,J15,H15,F15) -> 1476 | T15: =(B15+C15)*D15 -> 0 | W15: =(D15*F15)+(G15*H15)+(I15*J15)+(K15*L15)+(M15*N15) -> 1475 | X15: =(W15*5%) -> 73.75 | Y15: =SUM(W15+X15) -> 1548.75 | Z15: 14
A16: 42172 | D16: 1 | F16: 1100 | G16: 1 | H16: 200 | I16: 1 | J16: 175 | L16: 1 | N16: 150 | P16: 0 | R16: 0 | S16: =SUM(L16,J16,H16,F16) -> 1476 | T16: =(B16+C16)*D16 -> 0 | W16: =(D16*F16)+(G16*H16)+(I16*J16)+(K16*L16)+(M16*N16) -> 1475 | X16: =(W16*5%) -> 73.75 | Y16: =SUM(W16+X16) -> 1548.75 | Z16: 14
A17: 42173 | D17: 1 | F17: 1100 | G17: 1 | H17: 200 | I17: 1 | J17: 175 | L17: 1 | N17: 150 | P17: 0 | R17: 0 | S17: =SUM(L17,J17,H17,F17) -> 1476 | T17: =(B17+C17)*D17 -> 0 | W17: =(D17*F17)+(G17*H17)+(I17*J17)+(K17*L17)+(M17*N17) -> 1475 | X17: =(W17*5%) -> 73.75 | Y17: =SUM(W17+X17) -> 1548.75 | Z17: 14
A18: 42176 | D18: 1 | F18: 1100 | G18: 1 | H18: 200 | I18: 1 | J18: 175 | L18: 1 | N18: 150 | P18: 0 | R18: 0 | S18: =SUM(L18,J18,H18,F18) -> 1476 | T18: =(B18+C18)*D18 -> 0 | W18: =(D18*F18)+(G18*H18)+(I18*J18)+(K18*L18)+(M18*N18) -> 1475 | X18: =(W18*5%) -> 73.75 | Y18: =SUM(W18+X18) -> 1548.75 | Z18: 14
... A23: 42181 | D23: 1 | F23: 1100 | G23: 1 | H23: 200 | I23: 1 | J23: 175 | L23: 1 | N23: 150 | P23: 0 | R23: 0 | S23: =SUM(L23,J23,H23,F23) -> 1476 | T23: =(B23+C23)*D23 -> 0 | W23: =(D23*F23)+(G23*H23)+(I23*J23)+(K23*L23)+(M23*N23) -> 1475 | X23: =(W23*5%) -> 73.75 | Y23: =SUM(W23+X23) -> 1548.75 | Z23: 14
A24: 42186 | F24: 1100 | H24: 200 | I24: 1 | J24: 175 | L24: 1 | N24: 150 | P24: 0 | R24: 0 | S24: =SUM(L24,J24,H24,F24) -> 1476 | T24: =(B24+C24)*D24 -> 0 | W24: =(D24*F24)+(G24*H24)+(I24*J24)+(K24*L24)+(M24*N24) -> 175 | X24: =(W24*5%) -> 8.75 | Y24: 2015-18 | Z24: 15
A25: 42187 | D25: 1 | F25: 1100 | G25: 1 | H25: 200 | I25: 1 | J25: 175 | L25: 1 | N25: 150 | P25: 0 | R25: 0 | S25: =SUM(L25,J25,H25,F25) -> 1476 | T25: =(B25+C25)*D25 -> 0 | W25: =(D25*F25)+(G25*H25)+(I25*J25)+(K25*L25)+(M25*N25) -> 1475 | X25: =(W25*5%) -> 73.75 | Y25: 2015-18 | Z25: 15
A26: 42188 | D26: 1 | F26: 1100 | G26: 1 | H26: 200 | I26: 1 | J26: 175 | L26: 1 | N26: 150 | P26: 0 | R26: 0 | S26: =SUM(L26,J26,H26,F26) -> 1476 | T26: =(B26+C26)*D26 -> 0 | W26: =(D26*F26)+(G26*H26)+(I26*J26)+(K26*L26)+(M26*N26) -> 1475 | X26: =(W26*5%) -> 73.75 | Y26: 2015-18 | Z26: 15
A27: 42189 | D27: 1 | F27: 1100 | G27: 1 | H27: 200 | I27: 1 | J27: 175 | L27: 1 | N27: 150 | P27: 0 | R27: 0 | S27: =SUM(L27,J27,H27,F27) -> 1476 | T27: =(B27+C27)*D27 -> 0 | W27: =(D27*F27)+(G27*H27)+(I27*J27)+(K27*L27)+(M27*N27) -> 1475 | X27: =(W27*5%) -> 73.75 | Y27: 2015-18 | Z27: 15
A28: 42190 | F28: 1100 | H28: 200 | I28: 1 | J28: 175 | L28: 1 | N28: 150 | P28: 0 | R28: 0 | S28: =SUM(L28,J28,H28,F28) -> 1476 | T28: =(B28+C28)*D28 -> 0 | W28: =(D28*F28)+(G28*H28)+(I28*J28)+(K28*L28)+(M28*N28) -> 175 | X28: =(W28*5%) -> 8.75 | Y28: 2015-18 | Z28: 15
A29: 42191 | D29: 1 | F29: 1100 | G29: 1 | H29: 200 | I29: 1 | J29: 175 | L29: 1 | N29: 150 | W29: =(D29*F29)+(G29*H29)+(I29*J29)+(K29*L29)+(M29*N29) -> 1475 | X29: =(W29*5%) -> 73.75 | Y29: 2015-18 | Z29: 15
A30: 42192 | D30: 1 | F30: 1100 | G30: 1 | H30: 200 | I30: 1 | J30: 175 | L30: 1 | N30: 150 | W30: =(D30*F30)+(G30*H30)+(I30*J30)+(K30*L30)+(M30*N30) -> 1475 | X30: =(W30*5%) -> 73.75 | Y30: 2015-18 | Z30: 15
A31: 42193 | D31: 1 | F31: 1100 | G31: 1 | H31: 200 | I31: 1 | J31: 175 | L31: 1 | N31: 150 | W31: =(D31*F31)+(G31*H31)+(I31*J31)+(K31*L31)+(M31*N31) -> 1475 | X31: =(W31*5%) -> 73.75 | Y31: 2015-18 | Z31: 15
A32: 42194 | D32: 1 | F32: 1100 | G32: 1 | H32: 200 | I32: 1 | J32: 175 | L32: 1 | N32: 150 | W32: =(D32*F32)+(G32*H32)+(I32*J32)+(K32*L32)+(M32*N32) -> 1475 | X32: =(W32*5%) -> 73.75 | Y32: 2015-18 | Z32: 15
A33: 42195 | D33: 1 | F33: 1100 | G33: 1 | H33: 200 | I33: 1 | J33: 175 | L33: 1 | N33: 150 | W33: =(D33*F33)+(G33*H33)+(I33*J33)+(K33*L33)+(M33*N33) -> 1475 | X33: =(W33*5%) -> 73.75 | Y33: 2015-18 | Z33: 15
A34: 42196 | D34: 1 | F34: 1100 | G34: 1 | H34: 200 | I34: 1 | J34: 175 | L34: 1 | N34: 150 | W34: =(D34*F34)+(G34*H34)+(I34*J34)+(K34*L34)+(M34*N34) -> 1475 | X34: =(W34*5%) -> 73.75 | Y34: 2015-18 | Z34: 15
A35: 42197 | F35: 1100 | H35: 200 | I35: 1 | J35: 175 | L35: 1 | N35: 150 | W35: =(D35*F35)+(G35*H35)+(I35*J35)+(K35*L35)+(M35*N35) -> 175 | X35: =(W35*5%) -> 8.75 | Y35: 2015-18 | Z35: 15
A36: 42198 | F36: 1100 | H36: 200 | I36: 1 | J36: 175 | L36: 1 | N36: 150 | W36: =(D36*F36)+(G36*H36)+(I36*J36)+(K36*L36)+(M36*N36) -> 175 | X36: =(W36*5%) -> 8.75 | Y36: 2015-18 | Z36: 15
A37: 42199 | F37: 1100 | H37: 200 | I37: 1 | J37: 175 | L37: 1 | N37: 150 | W37: =(D37*F37)+(G37*H37)+(I37*J37)+(K37*L37)+(M37*N37) -> 175 | X37: =(W37*5%) -> 8.75 | Y37: 2015-18 | Z37: 15
A38: 42200 | D38: 1 | F38: 1100 | G38: 1 | H38: 200 | I38: 1 | J38: 175 | L38: 1 | N38: 150 | W38: =(D38*F38)+(G38*H38)+(I38*J38)+(K38*L38)+(M38*N38) -> 1475 | X38: =(W38*5%) -> 73.75 | Y38: 2015-18 | Z38: 15 | AA38: =SUM(W24:W54) -> 34025
A39: 42201 | D39: 1 | F39: 1100 | G39: 1 | H39: 200 | I39: 1 | J39: 175 | L39: 1 | N39: 150 | W39: =(D39*F39)+(G39*H39)+(I39*J39)+(K39*L39)+(M39*N39) -> 1475 | X39: =(W39*5%) -> 73.75 | Y39: =SUM(W39+X39) -> 1548.75 | Z39: 15
A40: 42202 | F40: 1100 | H40: 200 | I40: 1 | J40: 175 | L40: 1 | N40: 150 | W40: =(D40*F40)+(G40*H40)+(I40*J40)+(K40*L40)+(M40*N40) -> 175 | X40: =(W40*5%) -> 8.75 | Y40: =SUM(W40+X40) -> 183.75 | Z40: 15
A41: 42203 | C41: 425 | F41: 1100 | H41: 200 | I41: 1 | J41: 175 | L41: 1 | N41: 150 | W41: =(D41*F41)+(G41*H41)+(I41*J41)+(K41*L41)+(M41*N41) -> 175 | X41: =(W41*5%) -> 8.75 | Y41: =SUM(W41+X41) -> 183.75 | Z41: 15
A42: 42204 | C42: 426 | F42: 1100 | H42: 200 | I42: 1 | J42: 175 | L42: 1 | N42: 150 | W42: =(D42*F42)+(G42*H42)+(I42*J42)+(K42*L42)+(M42*N42) -> 175 | X42: =(W42*5%) -> 8.75 | Y42: =SUM(W42+X42) -> 183.75 | Z42: 15
A43: 42205 | C43: 427 | D43: 1 | F43: 1100 | G43: 1 | H43: 200 | I43: 1 | J43: 175 | L43: 1 | N43: 150 | W43: =(D43*F43)+(G43*H43)+(I43*J43)+(K43*L43)+(M43*N43) -> 1475 | X43: =(W43*5%) -> 73.75 | Y43: =SUM(W43+X43) -> 1548.75 | Z43: 15
A44: 42206 | C44: 427 | D44: 1 | F44: 1100 | G44: 1 | H44: 200 | I44: 1 | J44: 175 | L44: 1 | N44: 150 | W44: =(D44*F44)+(G44*H44)+(I44*J44)+(K44*L44)+(M44*N44) -> 1475 | X44: =(W44*5%) -> 73.75 | Y44: =SUM(W44+X44) -> 1548.75 | Z44: 15
A45: 42207 | C45: 427 | D45: 1 | F45: 1100 | G45: 1 | H45: 200 | I45: 1 | J45: 175 | L45: 1 | N45: 150 | W45: =(D45*F45)+(G45*H45)+(I45*J45)+(K45*L45)+(M45*N45) -> 1475 | X45: =(W45*5%) -> 73.75 | Y45: =SUM(W45+X45) -> 1548.75 | Z45: 15
A46: 42208 | C46: 427 | D46: 1 | F46: 1100 | G46: 1 | H46: 200 | I46: 1 | J46: 175 | L46: 1 | N46: 150 | W46: =(D46*F46)+(G46*H46)+(I46*J46)+(K46*L46)+(M46*N46) -> 1475 | X46: =(W46*5%) -> 73.75 | Y46: =SUM(W46+X46) -> 1548.75 | Z46: 15
A47: 42209 | C47: 427 | D47: 1 | F47: 1100 | G47: 1 | H47: 200 | I47: 1 | J47: 175 | L47: 1 | N47: 150 | W47: =(D47*F47)+(G47*H47)+(I47*J47)+(K47*L47)+(M47*N47) -> 1475 | X47: =(W47*5%) -> 73.75 | Y47: =SUM(W47+X47) -> 1548.75 | Z47: 15
A48: 42210 | C48: 427 | D48: 1 | F48: 1100 | G48: 1 | H48: 200 | I48: 1 | J48: 175 | L48: 1 | N48: 150 | W48: =(D48*F48)+(G48*H48)+(I48*J48)+(K48*L48)+(M48*N48) -> 1475 | X48: =(W48*5%) -> 73.75 | Y48: =SUM(W48+X48) -> 1548.75 | Z48: 15
A49: 42211 | C49: 427 | F49: 1100 | H49: 200 | I49: 1 | J49: 175 | L49: 1 | N49: 150 | W49: =(D49*F49)+(G49*H49)+(I49*J49)+(K49*L49)+(M49*N49) -> 175 | X49: =(W49*5%) -> 8.75 | Y49: =SUM(W49+X49) -> 183.75 | Z49: 15
A50: 42212 | C50: 427 | D50: 1 | F50: 1100 | G50: 1 | H50: 200 | I50: 1 | J50: 175 | L50: 1 | N50: 150 | W50: =(D50*F50)+(G50*H50)+(I50*J50)+(K50*L50)+(M50*N50) -> 1475 | X50: =(W50*5%) -> 73.75 | Y50: =SUM(W50+X50) -> 1548.75 | Z50: 15
A51: 42213 | C51: 427 | D51: 1 | F51: 1100 | G51: 1 | H51: 200 | I51: 1 | J51: 175 | L51: 1 | N51: 150 | W51: =(D51*F51)+(G51*H51)+(I51*J51)+(K51*L51)+(M51*N51) -> 1475 | X51: =(W51*5%) -> 73.75 | Y51: =SUM(W51+X51) -> 1548.75 | Z51: 15
A52: 42214 | C52: 427 | D52: 1 | F52: 1100 | G52: 1 | H52: 200 | I52: 1 | J52: 175 | L52: 1 | N52: 150 | W52: =(D52*F52)+(G52*H52)+(I52*J52)+(K52*L52)+(M52*N52) -> 1475 | X52: =(W52*5%) -> 73.75 | Y52: =SUM(W52+X52) -> 1548.75 | Z52: 15
A53: 42215 | C53: 427 | D53: 1 | F53: 1100 | G53: 1 | H53: 200 | I53: 1 | J53: 175 | L53: 1 | N53: 150 | W53: =(D53*F53)+(G53*H53)+(I53*J53)+(K53*L53)+(M53*N53) -> 1475 | X53: =(W53*5%) -> 73.75 | Y53: =SUM(W53+X53) -> 1548.75 | Z53: 15
A54: 42216 | C54: 427 | D54: 1 | F54: 1100 | G54: 1 | H54: 200 | I54: 1 | J54: 175 | L54: 1 | N54: 150 | W54: =(D54*F54)+(G54*H54)+(I54*J54)+(K54*L54)+(M54*N54) -> 1475 | X54: =(W54*5%) -> 73.75 | Y54: =SUM(W54+X54) -> 1548.75 | Z54: 15
A55: 42217 | C55: 427 | D55: 1 | F55: 1100 | G55: 1 | H55: 200 | I55: 1 | J55: 175 | L55: 1 | N55: 150 | W55: =(D55*F55)+(G55*H55)+(I55*J55)+(K55*L55)+(M55*N55) -> 1475 | X55: =(W55*5%) -> 73.75 | Y55: =SUM(W55+X55) -> 1548.75 | Z55: 16
A56: 42218 | C56: 427 | F56: 1100 | H56: 200 | I56: 1 | J56: 175 | L56: 1 | N56: 150 | W56: =(D56*F56)+(G56*H56)+(I56*J56)+(K56*L56)+(M56*N56) -> 175 | X56: =(W56*5%) -> 8.75 | Y56: =SUM(W56+X56) -> 183.75 | Z56: 16
A57: 42219 | C57: 427 | D57: 1 | F57: 1100 | G57: 1 | H57: 200 | I57: 1 | J57: 175 | L57: 1 | N57: 150 | W57: =(D57*F57)+(G57*H57)+(I57*J57)+(K57*L57)+(M57*N57) -> 1475 | X57: =(W57*5%) -> 73.75 | Y57: =SUM(W57+X57) -> 1548.75 | Z57: 16
A58: 42220 | C58: 427 | D58: 1 | F58: 1100 | G58: 1 | H58: 200 | I58: 1 | J58: 175 | L58: 1 | N58: 150 | W58: =(D58*F58)+(G58*H58)+(I58*J58)+(K58*L58)+(M58*N58) -> 1475 | X58: =(W58*5%) -> 73.75 | Y58: =SUM(W58+X58) -> 1548.75 | Z58: 16
A59: 42221 | C59: 427 | D59: 1 | F59: 1100 | G59: 1 | H59: 200 | I59: 1 | J59: 175 | L59: 1 | N59: 150 | W59: =(D59*F59)+(G59*H59)+(I59*J59)+(K59*L59)+(M59*N59) -> 1475 | X59: =(W59*5%) -> 73.75 | Y59: =SUM(W59+X59) -> 1548.75 | Z59: 16
A60: 42222 | C60: 427 | D60: 1 | F60: 1100 | G60: 1 | H60: 200 | I60: 1 | J60: 175 | L60: 1 | N60: 150 | W60: =(D60*F60)+(G60*H60)+(I60*J60)+(K60*L60)+(M60*N60) -> 1475 | X60: =(W60*5%) -> 73.75 | Y60: =SUM(W60+X60) -> 1548.75 | Z60: 16
A61: 42223 | C61: 427 | D61: 1 | F61: 1100 | G61: 1 | H61: 200 | I61: 1 | J61: 175 | L61: 1 | N61: 150 | W61: =(D61*F61)+(G61*H61)+(I61*J61)+(K61*L61)+(M61*N61) -> 1475 | X61: =(W61*5%) -> 73.75 | Y61: =SUM(W61+X61) -> 1548.75 | Z61: 16
A62: 42224 | C62: 427 | D62: 1 | F62: 1100 | G62: 1 | H62: 200 | I62: 1 | J62: 175 | L62: 1 | N62: 150 | W62: =(D62*F62)+(G62*H62)+(I62*J62)+(K62*L62)+(M62*N62) -> 1475 | X62: =(W62*5%) -> 73.75 | Y62: =SUM(W62+X62) -> 1548.75 | Z62: 16
A63: 42225 | C63: 427 | F63: 1100 | H63: 200 | I63: 1 | J63: 175 | L63: 1 | N63: 150 | W63: =(D63*F63)+(G63*H63)+(I63*J63)+(K63*L63)+(M63*N63) -> 175 | X63: =(W63*5%) -> 8.75 | Y63: =SUM(W63+X63) -> 183.75 | Z63: 16
A64: 42226 | C64: 427 | D64: 1 | F64: 1100 | G64: 1 | H64: 200 | I64: 1 | J64: 175 | L64: 1 | N64: 150 | W64: =(D64*F64)+(G64*H64)+(I64*J64)+(K64*L64)+(M64*N64) -> 1475 | X64: =(W64*5%) -> 73.75 | Y64: =SUM(W64+X64) -> 1548.75 | Z64: 16
A65: 42227 | C65: 427 | D65: 1 | F65: 1100 | G65: 1 | H65: 200 | I65: 1 | J65: 175 | L65: 1 | N65: 150 | W65: =(D65*F65)+(G65*H65)+(I65*J65)+(K65*L65)+(M65*N65) -> 1475 | X65: =(W65*5%) -> 73.75 | Y65: =SUM(W65+X65) -> 1548.75 | Z65: 16
A66: 42228 | C66: 427 | D66: 1 | F66: 1100 | G66: 1 | H66: 200 | I66: 1 | J66: 175 | L66: 1 | N66: 150 | W66: =(D66*F66)+(G66*H66)+(I66*J66)+(K66*L66)+(M66*N66) -> 1475 | X66: =(W66*5%) -> 73.75 | Y66: =SUM(W66+X66) -> 1548.75 | Z66: 16
A67: 42229 | C67: 427 | D67: 1 | F67: 1100 | G67: 1 | H67: 200 | I67: 1 | J67: 175 | L67: 1 | N67: 150 | W67: =(D67*F67)+(G67*H67)+(I67*J67)+(K67*L67)+(M67*N67) -> 1475 | X67: =(W67*5%) -> 73.75 | Y67: =SUM(W67+X67) -> 1548.75 | Z67: 16
A68: 42230 | C68: 427 | D68: 1 | F68: 1100 | G68: 1 | H68: 200 | I68: 1 | J68: 175 | L68: 1 | N68: 150 | W68: =(D68*F68)+(G68*H68)+(I68*J68)+(K68*L68)+(M68*N68) -> 1475 | X68: =(W68*5%) -> 73.75 | Y68: =SUM(W68+X68) -> 1548.75 | Z68: 16
A69: 42231 | C69: 427 | D69: 1 | F69: 1100 | G69: 1 | H69: 200 | I69: 1 | J69: 175 | L69: 1 | N69: 150 | W69: =(D69*F69)+(G69*H69)+(I69*J69)+(K69*L69)+(M69*N69) -> 1475 | X69: =(W69*5%) -> 73.75 | Y69: =SUM(W69+X69) -> 1548.75 | Z69: 16
A70: 42232 | C70: 427 | F70: 1100 | H70: 200 | I70: 1 | J70: 175 | L70: 1 | N70: 150 | W70: =(D70*F70)+(G70*H70)+(I70*J70)+(K70*L70)+(M70*N70) -> 175 | X70: =(W70*5%) -> 8.75 | Y70: =SUM(W70+X70) -> 183.75 | Z70: 16
A71: 42233 | C71: 427 | D71: 1 | F71: 1100 | G71: 1 | H71: 200 | I71: 1 | J71: 175 | L71: 1 | N71: 150 | W71: =(D71*F71)+(G71*H71)+(I71*J71)+(K71*L71)+(M71*N71) -> 1475 | X71: =(W71*5%) -> 73.75 | Y71: =SUM(W71+X71) -> 1548.75 | Z71: 16
A72: 42234 | C72: 427 | D72: 1 | F72: 1100 | G72: 1 | H72: 200 | I72: 1 | J72: 175 | L72: 1 | N72: 150 | W72: =(D72*F72)+(G72*H72)+(I72*J72)+(K72*L72)+(M72*N72) -> 1475 | X72: =(W72*5%) -> 73.75 | Y72: =SUM(W72+X72) -> 1548.75 | Z72: 16
A73: 42235 | C73: 427 | D73: 1 | F73: 1100 | G73: 1 | H73: 200 | I73: 1 | J73: 175 | L73: 1 | N73: 150 | W73: =(D73*F73)+(G73*H73)+(I73*J73)+(K73*L73)+(M73*N73) -> 1475 | X73: =(W73*5%) -> 73.75 | Y73: =SUM(W73+X73) -> 1548.75 | Z73: 16
A74: 42236 | D74: 1 | F74: 1100 | G74: 1 | H74: 200 | I74: 1 | J74: 175 | L74: 1 | N74: 150 | W74: =(D74*F74)+(G74*H74)+(I74*J74)+(K74*L74)+(M74*N74) -> 1475 | X74: =(W74*5%) -> 73.75 | Y74: =SUM(W74+X74) -> 1548.75 | Z74: 16
A75: 42237 | D75: 1 | F75: 1100 | G75: 1 | H75: 200 | I75: 1 | J75: 175 | L75: 1 | N75: 150 | W75: =(D75*F75)+(G75*H75)+(I75*J75)+(K75*L75)+(M75*N75) -> 1475 | X75: =(W75*5%) -> 73.75 | Y75: =SUM(W75+X75) -> 1548.75 | Z75: 16
A76: 42238 | D76: 1 | F76: 1100 | G76: 1 | H76: 200 | I76: 1 | J76: 175 | L76: 1 | N76: 150 | W76: =(D76*F76)+(G76*H76)+(I76*J76)+(K76*L76)+(M76*N76) -> 1475 | X76: =(W76*5%) -> 73.75 | Y76: =SUM(W76+X76) -> 1548.75 | Z76: 16
A77: 42239 | D77: 0 | F77: 1100 | G77: 0 | H77: 200 | I77: 1 | J77: 175 | L77: 1 | N77: 150 | W77: =(D77*F77)+(G77*H77)+(I77*J77)+(K77*L77)+(M77*N77) -> 175 | X77: =(W77*5%) -> 8.75 | Y77: =SUM(W77+X77) -> 183.75 | Z77: 16
A78: 42240 | D78: 1 | F78: 1100 | G78: 1 | H78: 200 | I78: 1 | J78: 175 | L78: 1 | N78: 150 | W78: =(D78*F78)+(G78*H78)+(I78*J78)+(K78*L78)+(M78*N78) -> 1475 | X78: =(W78*5%) -> 73.75 | Y78: =SUM(W78+X78) -> 1548.75 | Z78: 16
A79: 42241 | D79: 1 | F79: 1100 | G79: 1 | H79: 200 | I79: 1 | J79: 175 | L79: 1 | N79: 150 | W79: =(D79*F79)+(G79*H79)+(I79*J79)+(K79*L79)+(M79*N79) -> 1475 | X79: =(W79*5%) -> 73.75 | Y79: =SUM(W79+X79) -> 1548.75 | Z79: 16
A80: 42242 | D80: 1 | F80: 1100 | G80: 1 | H80: 200 | I80: 1 | J80: 175 | L80: 1 | N80: 150 | W80: =(D80*F80)+(G80*H80)+(I80*J80)+(K80*L80)+(M80*N80) -> 1475 | X80: =(W80*5%) -> 73.75 | Y80: =SUM(W80+X80) -> 1548.75 | Z80: 16
A81: 42243 | D81: 1 | F81: 1100 | G81: 1 | H81: 200 | I81: 1 | J81: 175 | L81: 1 | N81: 150 | W81: =(D81*F81)+(G81*H81)+(I81*J81)+(K81*L81)+(M81*N81) -> 1475 | X81: =(W81*5%) -> 73.75 | Y81: =SUM(W81+X81) -> 1548.75 | Z81: 16
A82: 42244 | D82: 1 | F82: 1100 | G82: 1 | H82: 200 | I82: 1 | J82: 175 | L82: 1 | N82: 150 | W82: =(D82*F82)+(G82*H82)+(I82*J82)+(K82*L82)+(M82*N82) -> 1475 | X82: =(W82*5%) -> 73.75 | Y82: =SUM(W82+X82) -> 1548.75 | Z82: 16
A83: 42245 | D83: 1 | F83: 1100 | G83: 1 | H83: 200 | I83: 1 | J83: 175 | L83: 1 | N83: 150 | W83: =(D83*F83)+(G83*H83)+(I83*J83)+(K83*L83)+(M83*N83) -> 1475 | X83: =(W83*5%) -> 73.75 | Y83: =SUM(W83+X83) -> 1548.75 | Z83: 16
A84: 42246 | F84: 1100 | H84: 200 | I84: 1 | J84: 175 | L84: 1 | N84: 150 | W84: =(D84*F84)+(G84*H84)+(I84*J84)+(K84*L84)+(M84*N84) -> 175 | X84: =(W84*5%) -> 8.75 | Y84: =SUM(W84+X84) -> 183.75 | Z84: 16 | AB84: Invoice#16
A85: 42247 | D85: 1 | F85: 1100 | G85: 1 | H85: 200 | I85: 1 | J85: 175 | L85: 1 | N85: 150 | W85: =(D85*F85)+(G85*H85)+(I85*J85)+(K85*L85)+(M85*N85) -> 1475 | X85: =(W85*5%) -> 73.75 | Y85: =SUM(W85+X85) -> 1548.75 | Z85: 16
A86: 42248 | D86: 1 | F86: 1100 | G86: 1 | H86: 200 | I86: 1 | J86: 175 | L86: 1 | N86: 150 | W86: =(D86*F86)+(G86*H86)+(I86*J86)+(K86*L86)+(M86*N86) -> 1475 | X86: =(W86*5%) -> 73.75 | Y86: =SUM(W86+X86) -> 1548.75 | Z86: 17
A87: 42249 | D87: 1 | F87: 1100 | G87: 1 | H87: 200 | I87: 1 | J87: 175 | L87: 1 | N87: 150 | W87: =(D87*F87)+(G87*H87)+(I87*J87)+(K87*L87)+(M87*N87) -> 1475 | X87: =(W87*5%) -> 73.75 | Y87: =SUM(W87+X87) -> 1548.75 | Z87: 17
A88: 42250 | D88: 1 | F88: 1100 | G88: 1 | H88: 200 | I88: 1 | J88: 175 | L88: 1 | N88: 150 | W88: =(D88*F88)+(G88*H88)+(I88*J88)+(K88*L88)+(M88*N88) -> 1475 | X88: =(W88*5%) -> 73.75 | Y88: =SUM(W88+X88) -> 1548.75 | Z88: 17
A89: 42267 | D89: 1 | F89: 1100 | G89: 1 | H89: 200 | I89: 1 | J89: 175 | L89: 1 | N89: 150 | W89: =(D89*F89)+(G89*H89)+(I89*J89)+(K89*L89)+(M89*N89) -> 1475 | X89: =(W89*5%) -> 73.75 | Y89: =SUM(W89+X89) -> 1548.75 | Z89: 17
A90: 42268 | D90: 1 | F90: 1100 | G90: 1 | H90: 200 | I90: 1 | J90: 175 | L90: 1 | N90: 150 | W90: =(D90*F90)+(G90*H90)+(I90*J90)+(K90*L90)+(M90*N90) -> 1475 | X90: =(W90*5%) -> 73.75 | Y90: =SUM(W90+X90) -> 1548.75 | Z90: 17
A91: 42269 | D91: 1 | F91: 1100 | G91: 1 | H91: 200 | I91: 1 | J91: 175 | L91: 1 | N91: 150 | W91: =(D91*F91)+(G91*H91)+(I91*J91)+(K91*L91)+(M91*N91) -> 1475 | X91: =(W91*5%) -> 73.75 | Y91: =SUM(W91+X91) -> 1548.75 | Z91: 17
A92: 42270 | D92: 1 | F92: 1100 | G92: 1 | H92: 200 | I92: 1 | J92: 175 | L92: 1 | N92: 150 | W92: =(D92*F92)+(G92*H92)+(I92*J92)+(K92*L92)+(M92*N92) -> 1475 | X92: =(W92*5%) -> 73.75 | Y92: =SUM(W92+X92) -> 1548.75 | Z92: 17
A93: 42271 | D93: 1 | F93: 1100 | G93: 1 | H93: 200 | I93: 1 | J93: 175 | L93: 1 | N93: 150 | W93: =(D93*F93)+(G93*H93)+(I93*J93)+(K93*L93)+(M93*N93) -> 1475 | X93: =(W93*5%) -> 73.75 | Y93: =SUM(W93+X93) -> 1548.75 | Z93: 17
A94: 42272 | D94: 1 | F94: 1100 | G94: 1 | H94: 200 | I94: 1 | J94: 175 | L94: 1 | N94: 150 | W94: =(D94*F94)+(G94*H94)+(I94*J94)+(K94*L94)+(M94*N94) -> 1475 | X94: =(W94*5%) -> 73.75 | Y94: =SUM(W94+X94) -> 1548.75 | Z94: 17
A95: 42274 | D95: 0 | F95: 1100 | G95: 0 | H95: 200 | I95: 1 | J95: 175 | L95: 1 | N95: 150 | W95: =(D95*F95)+(G95*H95)+(I95*J95)+(K95*L95)+(M95*N95) -> 175 | X95: =(W95*5%) -> 8.75 | Y95: =SUM(W95+X95) -> 183.75 | Z95: 17
A96: 42276 | D96: 1 | F96: 1100 | G96: 1 | H96: 200 | I96: 1 | J96: 175 | L96: 1 | N96: 150 | W96: =(D96*F96)+(G96*H96)+(I96*J96)+(K96*L96)+(M96*N96) -> 1475 | X96: =(W96*5%) -> 73.75 | Y96: =SUM(W96+X96) -> 1548.75 | Z96: 17
A97: 42277 | D97: 1 | F97: 1100 | G97: 1 | H97: 200 | I97: 1 | J97: 175 | L97: 1 | N97: 150 | W97: =(D97*F97)+(G97*H97)+(I97*J97)+(K97*L97)+(M97*N97) -> 1475 | X97: =(W97*5%) -> 73.75 | Y97: =SUM(W97+X97) -> 1548.75 | Z97: 17
A98: 42278
A99: 42279
A100: 42280
A101: 42281
A102: 42282
A103: 42283
A104: 42284
A105: 42285
A106: 42286
...

Sheet Vendor #8
A2: Vendor #8
A4: Date | B4: Straight Hours Charged (ea.) | C4: Overtime Hours Charged (ea.) | D4: Vendor #8 | E4: Rate | F4: Vehicle | G4: Rate $200 | H4: Quad | I4: Rate $150 | J4: KM Over 180 | K4: Rate $1.00 | L4: Sub | M4: Rate $200 | N4: Labourer class | O4: Rate | P4: Labourer class | Q4: Rate | R4: Total Labour Rate per hr | S4: Total Hours Charged | T4: Equipment Detail | U4: Km's Charged | V4: Subtotal | W4: GST | X4: LEM Amount | Y4: Affiliating Invoice | Z4: Approved By | AA4: SUM OF ALL LEM'S (before GST)
AA5: =SUM(V6:V174) -> 193842
A6: 42124 | E6: 0 | G6: 0 | I6: 0 | K6: 0 | M6: 0 | O6: 0 | Q6: 0 | R6: =SUM(K6,I6,G6,E6) -> 0 | S6: =(B6+C6)*D6 -> 0 | T6: Invoice from April 16-30 | V6: 1360 | W6: =(V6*5%) -> 68 | X6: =SUM(V6+W6) -> 1428 | Y6: 2015-10
A7: 42139 | E7: 0 | G7: 0 | I7: 0 | K7: 0 | M7: 0 | O7: 0 | Q7: 0 | R7: =SUM(K7,I7,G7,E7) -> 0 | S7: =(B7+C7)*D7 -> 0 | T7: Invoice from May 1-15 | V7: 2980 | W7: =(V7*5%) -> 149 | X7: =V7+W7 -> 3129 | Y7: 2015-12
A8: 42155 | E8: 0 | G8: 0 | I8: 0 | K8: 0 | M8: 0 | O8: 0 | Q8: 0 | R8: =SUM(K8,I8,G8,E8) -> 0 | S8: =(B8+C8)*D8 -> 0 | T8: Invoice from May 16-31 | V8: 9400 | W8: =(V8*5%) -> 470 | X8: =SUM(V8+W8) -> 9870 | Y8: 2015-14
A9: 42156 | B9: 12 | C9: 0 | D9: 1 | E9: 1100 | F9: 1 | G9: 200 | I9: 150 | K9: 1 | L9: 1 | M9: 200 | O9: 0 | Q9: 0 | R9: =SUM(U9,I9,G9,E9) -> 1450 | S9: =(B9+C9)*D9 -> 12 | U9: =K9*J9 -> 0 | V9: =(D9*E9)+(F9*G9)+(H9*I9)+(J9*K9)+(L9*M9) -> 1500 | W9: =(V9*5%) -> 75 | X9: =SUM(V9+W9) -> 1575 | Y9: 2015-15
A10: 42157 | B10: 12 | C10: 0 | D10: 0.5 | E10: 1100 | F10: 0.5 | G10: 200 | I10: 150 | K10: 1 | L10: 1 | M10: 200 | O10: 0 | Q10: 0 | R10: =SUM(K10,I10,G10,E10) -> 1451 | S10: =(B10+C10)*D10 -> 6 | U10: =K10*J10 -> 0 | V10: =(D10*E10)+(F10*G10)+(H10*I10)+(J10*K10)+(L10*M10) -> 850 | W10: =(V10*5%) -> 42.5 | X10: =SUM(V10+W10) -> 892.5 | Y10: 2015-15
A11: 42158 | B11: 12 | C11: 0 | E11: 1100 | G11: 200 | I11: 150 | K11: 1 | L11: 1 | M11: 200 | O11: 0 | Q11: 0 | R11: =SUM(K11,I11,G11,E11) -> 1451 | S11: =(B11+C11)*D11 -> 0 | U11: =K11*J11 -> 0 | V11: =(D11*E11)+(F11*G11)+(H11*I11)+(J11*K11)+(L11*M11) -> 200 | W11: =(V11*5%) -> 10 | X11: =SUM(V11+W11) -> 210 | Y11: 2015-15
A12: 42159 | B12: 12 | C12: 0 | E12: 1100 | G12: 200 | I12: 150 | K12: 1 | L12: 1 | M12: 200 | O12: 0 | Q12: 0 | R12: =SUM(K12,I12,G12,E12) -> 1451 | S12: =(B12+C12)*D12 -> 0 | U12: =K12*J12 -> 0 | V12: =(D12*E12)+(F12*G12)+(H12*I12)+(J12*K12)+(L12*M12) -> 200 | W12: =(V12*5%) -> 10 | X12: =SUM(V12+W12) -> 210 | Y12: 2015-15
A13: 42160 | B13: 12 | C13: 0 | D13: 1 | E13: 1100 | F13: 1 | G13: 200 | I13: 150 | K13: 1 | L13: 1 | M13: 200 | O13: 0 | Q13: 0 | R13: =SUM(K13,I13,G13,E13) -> 1451 | S13: =(B13+C13)*D13 -> 12 | U13: =K13*J13 -> 0 | V13: =(D13*E13)+(F13*G13)+(H13*I13)+(J13*K13)+(L13*M13) -> 1500 | W13: =(V13*5%) -> 75 | X13: =SUM(V13+W13) -> 1575 | Y13: 2015-15
A14: 42163 | B14: 12 | C14: 0 | D14: 1 | E14: 1100 | F14: 1 | G14: 200 | I14: 150 | K14: 1 | L14: 1 | M14: 200 | O14: 0 | Q14: 0 | R14: =SUM(K14,I14,G14,E14) -> 1451 | S14: =(B14+C14)*D14 -> 12 | U14: =K14*J14 -> 0 | V14: =(D14*E14)+(F14*G14)+(H14*I14)+(J14*K14)+(L14*M14) -> 1500 | W14: =(V14*5%) -> 75 | X14: =SUM(V14+W14) -> 1575 | Y14: 2015-15
A15: 42164 | B15: 12 | C15: 0 | D15: 1 | E15: 1100 | F15: 1 | G15: 200 | I15: 150 | K15: 1 | L15: 1 | M15: 200 | O15: 0 | Q15: 0 | R15: =SUM(K15,I15,G15,E15) -> 1451 | S15: =(B15+C15)*D15 -> 12 | U15: =K15*J15 -> 0 | V15: =(D15*E15)+(F15*G15)+(H15*I15)+(J15*K15)+(L15*M15) -> 1500 | W15: =(V15*5%) -> 75 | X15: =SUM(V15+W15) -> 1575 | Y15: 2015-15 | Z15: =SUM(V9:V21) -> 14300
A16: 42165 | D16: 1 | E16: 1100 | F16: 1 | G16: 200 | I16: 150 | K16: 1 | L16: 1 | M16: 200 | O16: 0 | Q16: 0 | R16: =SUM(K16,I16,G16,E16) -> 1451 | S16: =(B16+C16)*D16 -> 0 | U16: =K16*J16 -> 0 | V16: =(D16*E16)+(F16*G16)+(H16*I16)+(J16*K16)+(L16*M16) -> 1500 | W16: =(V16*5%) -> 75 | X16: =SUM(V16+W16) -> 1575 | Y16: 2015-15
A17: 42166 | D17: 0.5 | E17: 1100 | F17: 0.5 | G17: 200 | I17: 150 | K17: 1 | L17: 1 | M17: 200 | O17: 0 | Q17: 0 | R17: =SUM(K17,I17,G17,E17) -> 1451 | S17: =(B17+C17)*D17 -> 0 | U17: =K17*J17 -> 0 | V17: =(D17*E17)+(F17*G17)+(H17*I17)+(J17*K17)+(L17*M17) -> 850 | W17: =(V17*5%) -> 42.5 | X17: =SUM(V17+W17) -> 892.5 | Y17: 2015-15
A18: 42167 | D18: 1 | E18: 1100 | F18: 1 | G18: 200 | I18: 150 | K18: 1 | L18: 1 | M18: 200 | O18: 0 | Q18: 0 | R18: =SUM(K18,I18,G18,E18) -> 1451 | S18: =(B18+C18)*D18 -> 0 | U18: =K18*J18 -> 0 | V18: =(D18*E18)+(F18*G18)+(H18*I18)+(J18*K18)+(L18*M18) -> 1500 | W18: =(V18*5%) -> 75 | X18: =SUM(V18+W18) -> 1575 | Y18: 2015-15
A19: 42168 | D19: 1 | E19: 1100 | F19: 1 | G19: 200 | I19: 150 | K19: 1 | L19: 1 | M19: 200 | O19: 0 | Q19: 0 | R19: =SUM(K19,I19,G19,E19) -> 1451 | S19: =(B19+C19)*D19 -> 0 | U19: =K19*J19 -> 0 | V19: =(D19*E19)+(F19*G19)+(H19*I19)+(J19*K19)+(L19*M19) -> 1500 | W19: =(V19*5%) -> 75 | X19: =SUM(V19+W19) -> 1575 | Y19: 2015-15
A20: 42169 | E20: 1100 | G20: 200 | I20: 150 | K20: 1 | L20: 1 | M20: 200 | O20: 0 | Q20: 0 | R20: =SUM(K20,I20,G20,E20) -> 1451 | S20: =(B20+C20)*D20 -> 0 | U20: =K20*J20 -> 0 | V20: =(D20*E20)+(F20*G20)+(H20*I20)+(J20*K20)+(L20*M20) -> 200 | W20: =(V20*5%) -> 10 | X20: =SUM(V20+W20) -> 210 | Y20: 2015-15
A21: 42170 | D21: 1 | E21: 1100 | F21: 1 | G21: 200 | I21: 150 | K21: 1 | L21: 1 | M21: 200 | O21: 0 | Q21: 0 | R21: =SUM(K21,I21,G21,E21) -> 1451 | S21: =(B21+C21)*D21 -> 0 | U21: =K21*J21 -> 0 | V21: =(D21*E21)+(F21*G21)+(H21*I21)+(J21*K21)+(L21*M21) -> 1500 | W21: =(V21*5%) -> 75 | X21: =SUM(V21+W21) -> 1575 | Y21: 2015-15
A22: 42171 | D22: 1 | E22: 1100 | F22: 1 | G22: 200 | I22: 150 | K22: 1 | L22: 1 | M22: 200 | O22: 0 | Q22: 0 | R22: =SUM(K22,I22,G22,E22) -> 1451 | S22: =(B22+C22)*D22 -> 0 | U22: =K22*J22 -> 0 | V22: =(D22*E22)+(F22*G22)+(H22*I22)+(J22*K22)+(L22*M22) -> 1500 | W22: =(V22*5%) -> 75 | X22: =SUM(V22+W22) -> 1575 | Y22: 2015-17
A23: 42172 | D23: 1 | E23: 1100 | F23: 1 | G23: 200 | H23: 1 | I23: 150 | K23: 1 | L23: 1 | M23: 200 | O23: 0 | Q23: 0 | R23: =SUM(K23,I23,G23,E23) -> 1451 | S23: =(B23+C23)*D23 -> 0 | U23: =K23*J23 -> 0 | V23: =(D23*E23)+(F23*G23)+(H23*I23)+(J23*K23)+(L23*M23) -> 1650 | W23: =(V23*5%) -> 82.5 | X23: =SUM(V23+W23) -> 1732.5 | Y23: 2015-17
A24: 42173 | D24: 1 | E24: 1100 | F24: 1 | G24: 200 | H24: 1 | I24: 150 | K24: 1 | L24: 1 | M24: 200 | O24: 0 | Q24: 0 | R24: =SUM(K24,I24,G24,E24) -> 1451 | S24: =(B24+C24)*D24 -> 0 | U24: =K24*J24 -> 0 | V24: =(D24*E24)+(F24*G24)+(H24*I24)+(J24*K24)+(L24*M24) -> 1650 | W24: =(V24*5%) -> 82.5 | X24: =SUM(V24+W24) -> 1732.5 | Y24: 2015-17 | Z24: =SUM(V22:V36) -> 19050
A25: 42174 | D25: 1 | E25: 1100 | F25: 1 | G25: 200 | I25: 150 | K25: 1 | L25: 1 | M25: 200 | O25: 0 | Q25: 0 | R25: =SUM(K25,I25,G25,E25) -> 1451 | S25: =(B25+C25)*D25 -> 0 | U25: =K25*J25 -> 0 | V25: =(D25*E25)+(F25*G25)+(H25*I25)+(J25*K25)+(L25*M25) -> 1500 | W25: =(V25*5%) -> 75 | X25: =SUM(V25+W25) -> 1575 | Y25: 2015-17
A26: 42175 | D26: 0.5 | E26: 1100 | F26: 0.5 | G26: 200 | I26: 150 | K26: 1 | L26: 1 | M26: 200 | O26: 0 | Q26: 0 | R26: =SUM(K26,I26,G26,E26) -> 1451 | S26: =(B26+C26)*D26 -> 0 | U26: =K26*J26 -> 0 | V26: =(D26*E26)+(F26*G26)+(H26*I26)+(J26*K26)+(L26*M26) -> 850 | W26: =(V26*5%) -> 42.5 | X26: =SUM(V26+W26) -> 892.5 | Y26: 2015-17
A27: 42176 | E27: 1100 | G27: 200 | I27: 150 | K27: 1 | L27: 1 | M27: 200 | O27: 0 | Q27: 0 | R27: =SUM(K27,I27,G27,E27) -> 1451 | S27: =(B27+C27)*D27 -> 0 | U27: =K27*J27 -> 0 | V27: =(D27*E27)+(F27*G27)+(H27*I27)+(J27*K27)+(L27*M27) -> 200 | W27: =(V27*5%) -> 10 | X27: =SUM(V27+W27) -> 210 | Y27: 2015-17
A28: 42177 | D28: 1 | E28: 1100 | F28: 1 | G28: 200 | H28: 1 | I28: 150 | K28: 1 | L28: 1 | M28: 200 | O28: 0 | Q28: 0 | R28: =SUM(K28,I28,G28,E28) -> 1451 | S28: =(B28+C28)*D28 -> 0 | U28: =K28*J28 -> 0 | V28: =(D28*E28)+(F28*G28)+(H28*I28)+(J28*K28)+(L28*M28) -> 1650 | W28: =(V28*5%) -> 82.5 | X28: =SUM(V28+W28) -> 1732.5 | Y28: 2015-17
A29: 42178 | D29: 1 | E29: 1100 | F29: 1 | G29: 200 | I29: 150 | K29: 1 | L29: 1 | M29: 200 | O29: 0 | Q29: 0 | R29: =SUM(K29,I29,G29,E29) -> 1451 | S29: =(B29+C29)*D29 -> 0 | U29: =K29*J29 -> 0 | V29: =(D29*E29)+(F29*G29)+(H29*I29)+(J29*K29)+(L29*M29) -> 1500 | W29: =(V29*5%) -> 75 | X29: =SUM(V29+W29) -> 1575 | Y29: 2015-17
A30: 42179 | D30: 1 | E30: 1100 | F30: 1 | G30: 200 | I30: 150 | K30: 1 | L30: 1 | M30: 200 | O30: 0 | Q30: 0 | R30: =SUM(K30,I30,G30,E30) -> 1451 | S30: =(B30+C30)*D30 -> 0 | U30: =K30*J30 -> 0 | V30: =(D30*E30)+(F30*G30)+(H30*I30)+(J30*K30)+(L30*M30) -> 1500 | W30: =(V30*5%) -> 75 | X30: =SUM(V30+W30) -> 1575 | Y30: 2015-17
A31: 42180 | D31: 1 | E31: 1100 | F31: 1 | G31: 200 | I31: 150 | K31: 1 | L31: 1 | M31: 200 | O31: 0 | Q31: 0 | R31: =SUM(K31,I31,G31,E31) -> 1451 | S31: =(B31+C31)*D31 -> 0 | U31: =K31*J31 -> 0 | V31: =(D31*E31)+(F31*G31)+(H31*I31)+(J31*K31)+(L31*M31) -> 1500 | W31: =(V31*5%) -> 75 | X31: =SUM(V31+W31) -> 1575 | Y31: 2015-17
A32: 42181 | D32: 0.5 | E32: 1100 | F32: .5 | G32: 200 | I32: 150 | K32: 1 | L32: 1 | M32: 200 | O32: 0 | Q32: 0 | R32: =SUM(K32,I32,G32,E32) -> 1451 | S32: =(B32+C32)*D32 -> 0 | U32: =K32*J32 -> 0 | V32: =(D32*E32)+(F32*G32)+(H32*I32)+(J32*K32)+(L32*M32) -> 850 | W32: =(V32*5%) -> 42.5 | X32: =SUM(V32+W32) -> 892.5 | Y32: 2015-17
A33: 42182 | D33: 1 | E33: 1100 | F33: 1 | G33: 200 | I33: 150 | K33: 1 | L33: 1 | M33: 200 | O33: 0 | Q33: 0 | R33: =SUM(K33,I33,G33,E33) -> 1451 | S33: =(B33+C33)*D33 -> 0 | U33: =K33*J33 -> 0 | V33: =(D33*E33)+(F33*G33)+(H33*I33)+(J33*K33)+(L33*M33) -> 1500 | W33: =(V33*5%) -> 75 | X33: =SUM(V33+W33) -> 1575 | Y33: 2015-17
A34: 42183 | E34: 1100 | G34: 200 | I34: 150 | K34: 1 | L34: 1 | M34: 200 | O34: 0 | Q34: 0 | R34: =SUM(K34,I34,G34,E34) -> 1451 | S34: =(B34+C34)*D34 -> 0 | U34: =K34*J34 -> 0 | V34: =(D34*E34)+(F34*G34)+(H34*I34)+(J34*K34)+(L34*M34) -> 200 | W34: =(V34*5%) -> 10 | X34: =SUM(V34+W34) -> 210 | Y34: 2015-17
A35: 42184 | D35: 1 | E35: 1100 | F35: 1 | G35: 200 | I35: 150 | K35: 1 | L35: 1 | M35: 200 | O35: 0 | Q35: 0 | R35: =SUM(K35,I35,G35,E35) -> 1451 | S35: =(B35+C35)*D35 -> 0 | U35: =K35*J35 -> 0 | V35: =(D35*E35)+(F35*G35)+(H35*I35)+(J35*K35)+(L35*M35) -> 1500 | W35: =(V35*5%) -> 75 | X35: =SUM(V35+W35) -> 1575 | Y35: 2015-17
A36: 42185 | D36: 1 | E36: 1100 | F36: 1 | G36: 200 | I36: 150 | K36: 1 | L36: 1 | M36: 200 | O36: 0 | Q36: 0 | R36: =SUM(K36,I36,G36,E36) -> 1451 | S36: =(B36+C36)*D36 -> 0 | U36: =K36*J36 -> 0 | V36: =(D36*E36)+(F36*G36)+(H36*I36)+(J36*K36)+(L36*M36) -> 1500 | W36: =(V36*5%) -> 75 | X36: =SUM(V36+W36) -> 1575 | Y36: 2015-17
A37: 42186 | D37: 1 | E37: 1100 | F37: 1 | G37: 200 | I37: 150 | K37: 1 | L37: 1 | M37: 200 | O37: 0 | Q37: 0 | R37: =SUM(K37,I37,G37,E37) -> 1451 | S37: =(B37+C37)*D37 -> 0 | U37: =K37*J37 -> 0 | V37: =(D37*E37)+(F37*G37)+(H37*I37)+(J37*K37)+(L37*M37) -> 1500 | W37: =(V37*5%) -> 75 | X37: =SUM(V37+W37) -> 1575 | Y37: 2015-18
A38: 42187 | D38: 1 | E38: 1100 | F38: 1 | G38: 200 | I38: 150 | K38: 1 | L38: 1 | M38: 200 | O38: 0 | Q38: 0 | R38: =SUM(K38,I38,G38,E38) -> 1451 | S38: =(B38+C38)*D38 -> 0 | U38: =K38*J38 -> 0 | V38: =(D38*E38)+(F38*G38)+(H38*I38)+(J38*K38)+(L38*M38) -> 1500 | W38: =(V38*5%) -> 75 | X38: =SUM(V38+W38) -> 1575 | Y38: 2015-18
A39: 42188 | D39: 1 | E39: 1100 | F39: 1 | G39: 200 | I39: 150 | K39: 1 | L39: 1 | M39: 200 | O39: 0 | Q39: 0 | R39: =SUM(K39,I39,G39,E39) -> 1451 | S39: =(B39+C39)*D39 -> 0 | U39: =K39*J39 -> 0 | V39: =(D39*E39)+(F39*G39)+(H39*I39)+(J39*K39)+(L39*M39) -> 1500 | W39: =(V39*5%) -> 75 | X39: =SUM(V39+W39) -> 1575 | Y39: 2015-18
A40: 42189 | D40: 1 | E40: 1100 | F40: 1 | G40: 200 | I40: 150 | K40: 1 | L40: 1 | M40: 200 | O40: 0 | Q40: 0 | R40: =SUM(K40,I40,G40,E40) -> 1451 | S40: =(B40+C40)*D40 -> 0 | U40: =K40*J40 -> 0 | V40: =(D40*E40)+(F40*G40)+(H40*I40)+(J40*K40)+(L40*M40) -> 1500 | W40: =(V40*5%) -> 75 | X40: =SUM(V40+W40) -> 1575 | Y40: 2015-18
A41: 42190 | E41: 1100 | G41: 200 | L41: 1 | M41: 200 | O41: 0 | Q41: 0 | R41: =SUM(K41,I41,G41,E41) -> 1300 | S41: =(B41+C41)*D41 -> 0 | U41: =K41*J41 -> 0 | V41: =(D41*E41)+(F41*G41)+(H41*I41)+(J41*K41)+(L41*M41) -> 200 | W41: =(V41*5%) -> 10 | X41: =SUM(V41+W41) -> 210 | Y41: 2015-18
A42: 42191 | D42: 1 | E42: 1100 | F42: 1 | G42: 200 | I42: 150 | K42: 1 | L42: 1 | M42: 200 | O42: 0 | Q42: 0 | R42: =SUM(K42,I42,G42,E42) -> 1451 | S42: =(B42+C42)*D42 -> 0 | U42: =K42*J42 -> 0 | V42: =(D42*E42)+(F42*G42)+(H42*I42)+(J42*K42)+(L42*M42) -> 1500 | W42: =(V42*5%) -> 75 | X42: =SUM(V42+W42) -> 1575 | Y42: 2015-18
A43: 42192 | D43: 1 | E43: 1100 | F43: 1 | G43: 200 | I43: 150 | K43: 1 | L43: 1 | M43: 200 | O43: 0 | Q43: 0 | R43: =SUM(K43,I43,G43,E43) -> 1451 | S43: =(B43+C43)*D43 -> 0 | U43: =K43*J43 -> 0 | V43: =(D43*E43)+(F43*G43)+(H43*I43)+(J43*K43)+(L43*M43) -> 1500 | W43: =(V43*5%) -> 75 | X43: =SUM(V43+W43) -> 1575 | Y43: 2015-18
A44: 42193 | D44: 1 | E44: 1100 | F44: 1 | G44: 200 | I44: 150 | K44: 1 | L44: 1 | M44: 200 | O44: 0 | Q44: 0 | R44: =SUM(K44,I44,G44,E44) -> 1451 | S44: =(B44+C44)*D44 -> 0 | U44: =K44*J44 -> 0 | V44: =(D44*E44)+(F44*G44)+(H44*I44)+(J44*K44)+(L44*M44) -> 1500 | W44: =(V44*5%) -> 75 | X44: =SUM(V44+W44) -> 1575 | Y44: 2015-18
A45: 42194 | D45: 1 | E45: 1100 | F45: 1 | G45: 200 | I45: 150 | K45: 1 | L45: 1 | M45: 200 | O45: 0 | Q45: 0 | R45: =SUM(K45,I45,G45,E45) -> 1451 | S45: =(B45+C45)*D45 -> 0 | U45: =K45*J45 -> 0 | V45: =(D45*E45)+(F45*G45)+(H45*I45)+(J45*K45)+(L45*M45) -> 1500 | W45: =(V45*5%) -> 75 | X45: =SUM(V45+W45) -> 1575 | Y45: 2015-18
A46: 42195 | D46: 1 | E46: 1100 | F46: 1 | G46: 200 | I46: 150 | K46: 1 | L46: 1 | M46: 200 | O46: 0 | Q46: 0 | R46: =SUM(K46,I46,G46,E46) -> 1451 | S46: =(B46+C46)*D46 -> 0 | U46: =K46*J46 -> 0 | V46: =(D46*E46)+(F46*G46)+(H46*I46)+(J46*K46)+(L46*M46) -> 1500 | W46: =(V46*5%) -> 75 | X46: =SUM(V46+W46) -> 1575 | Y46: 2015-18
A47: 42196 | D47: 1 | E47: 1100 | F47: 1 | G47: 200 | I47: 150 | K47: 1 | L47: 1 | M47: 200 | O47: 0 | Q47: 0 | R47: =SUM(K47,I47,G47,E47) -> 1451 | S47: =(B47+C47)*D47 -> 0 | U47: =K47*J47 -> 0 | V47: =(D47*E47)+(F47*G47)+(H47*I47)+(J47*K47)+(L47*M47) -> 1500 | W47: =(V47*5%) -> 75 | X47: =SUM(V47+W47) -> 1575 | Y47: 2015-18
A48: 42197 | E48: 1100 | G48: 200 | I48: 150 | K48: 1 | L48: 1 | M48: 200 | O48: 0 | Q48: 0 | R48: =SUM(K48,I48,G48,E48) -> 1451 | S48: =(B48+C48)*D48 -> 0 | U48: =K48*J48 -> 0 | V48: =(D48*E48)+(F48*G48)+(H48*I48)+(J48*K48)+(L48*M48) -> 200 | W48: =(V48*5%) -> 10 | X48: =SUM(V48+W48) -> 210 | Y48: 2015-18
A49: 42198 | D49: 1 | E49: 1100 | F49: 1 | G49: 200 | I49: 150 | K49: 1 | L49: 1 | M49: 200 | O49: 0 | Q49: 0 | R49: =SUM(K49,I49,G49,E49) -> 1451 | S49: =(B49+C49)*D49 -> 0 | U49: =K49*J49 -> 0 | V49: =(D49*E49)+(F49*G49)+(H49*I49)+(J49*K49)+(L49*M49) -> 1500 | W49: =(V49*5%) -> 75 | X49: =SUM(V49+W49) -> 1575 | Y49: 2015-18
A50: 42199 | D50: 1 | E50: 1100 | F50: 1 | G50: 200 | I50: 150 | K50: 1 | L50: 1 | M50: 200 | O50: 0 | Q50: 0 | R50: =SUM(K50,I50,G50,E50) -> 1451 | S50: =(B50+C50)*D50 -> 0 | U50: =K50*J50 -> 0 | V50: =(D50*E50)+(F50*G50)+(H50*I50)+(J50*K50)+(L50*M50) -> 1500 | W50: =(V50*5%) -> 75 | X50: =SUM(V50+W50) -> 1575 | Y50: 2015-18
A51: 42200 | D51: 1 | E51: 1100 | F51: 1 | G51: 200 | I51: 150 | K51: 1 | L51: 1 | M51: 200 | O51: 0 | Q51: 0 | R51: =SUM(K51,I51,G51,E51) -> 1451 | S51: =(B51+C51)*D51 -> 0 | U51: =K51*J51 -> 0 | V51: =(D51*E51)+(F51*G51)+(H51*I51)+(J51*K51)+(L51*M51) -> 1500 | W51: =(V51*5%) -> 75 | X51: =SUM(V51+W51) -> 1575 | Y51: 2015-18 | Z51: =SUM(V37:V51) -> 19900
A52: 42201 | D52: 1 | E52: 1100 | F52: 1 | G52: 200 | I52: 150 | K52: 1 | L52: 1 | M52: 200 | O52: 0 | Q52: 0 | R52: =SUM(K52,I52,G52,E52) -> 1451 | S52: =(B52+C52)*D52 -> 0 | U52: =K52*J52 -> 0 | V52: =(D52*E52)+(F52*G52)+(H52*I52)+(J52*K52)+(L52*M52) -> 1500 | W52: =(V52*5%) -> 75 | X52: =SUM(V52+W52) -> 1575 | Y52: 2015-19
A53: 42202 | D53: 1 | E53: 1100 | F53: 1 | G53: 200 | I53: 150 | K53: 1 | L53: 1 | M53: 200 | O53: 0 | Q53: 0 | R53: =SUM(K53,I53,G53,E53) -> 1451 | S53: =(B53+C53)*D53 -> 0 | U53: =K53*J53 -> 0 | V53: =(D53*E53)+(F53*G53)+(H53*I53)+(J53*K53)+(L53*M53) -> 1500 | W53: =(V53*5%) -> 75 | X53: =SUM(V53+W53) -> 1575 | Y53: 2015-19
A54: 42203 | C54: 425 | D54: 1 | E54: 1100 | F54: 1 | G54: 200 | I54: 150 | K54: 1 | L54: 1 | M54: 200 | O54: 0 | Q54: 0 | R54: =SUM(K54,I54,G54,E54) -> 1451 | S54: =(B54+C54)*D54 -> 425 | U54: =K54*J54 -> 0 | V54: =(D54*E54)+(F54*G54)+(H54*I54)+(J54*K54)+(L54*M54) -> 1500 | W54: =(V54*5%) -> 75 | X54: =SUM(V54+W54) -> 1575 | Y54: 2015-19
A55: 42204 | C55: 425 | D55: 1 | E55: 1100 | F55: 1 | G55: 200 | I55: 150 | K55: 1 | L55: 1 | M55: 200 | O55: 0 | Q55: 0 | R55: =SUM(K55,I55,G55,E55) -> 1451 | S55: =(B55+C55)*D55 -> 425 | U55: =K55*J55 -> 0 | V55: =(D55*E55)+(F55*G55)+(H55*I55)+(J55*K55)+(L55*M55) -> 1500 | W55: =(V55*5%) -> 75 | X55: =SUM(V55+W55) -> 1575 | Y55: 2015-19
A56: 42205 | C56: 425 | D56: 1 | E56: 1100 | F56: 1 | G56: 200 | I56: 150 | K56: 1 | L56: 1 | M56: 200 | O56: 0 | Q56: 0 | R56: =SUM(K56,I56,G56,E56) -> 1451 | S56: =(B56+C56)*D56 -> 425 | U56: =K56*J56 -> 0 | V56: =(D56*E56)+(F56*G56)+(H56*I56)+(J56*K56)+(L56*M56) -> 1500 | W56: =(V56*5%) -> 75 | X56: =SUM(V56+W56) -> 1575 | Y56: 2015-19
A57: 42206 | C57: 425 | D57: 1 | E57: 1100 | F57: 1 | G57: 200 | I57: 150 | K57: 1 | L57: 1 | M57: 200 | O57: 0 | Q57: 0 | R57: =SUM(K57,I57,G57,E57) -> 1451 | S57: =(B57+C57)*D57 -> 425 | U57: =K57*J57 -> 0 | V57: =(D57*E57)+(F57*G57)+(H57*I57)+(J57*K57)+(L57*M57) -> 1500 | W57: =(V57*5%) -> 75 | X57: =SUM(V57+W57) -> 1575 | Y57: 2015-19
A58: 42207 | C58: 425 | D58: 1 | E58: 1100 | F58: 1 | G58: 200 | I58: 150 | K58: 1 | L58: 1 | M58: 200 | O58: 0 | Q58: 0 | R58: =SUM(K58,I58,G58,E58) -> 1451 | S58: =(B58+C58)*D58 -> 425 | U58: =K58*J58 -> 0 | V58: =(D58*E58)+(F58*G58)+(H58*I58)+(J58*K58)+(L58*M58) -> 1500 | W58: =(V58*5%) -> 75 | X58: =SUM(V58+W58) -> 1575 | Y58: 2015-19
A59: 42208 | C59: 425 | D59: 1 | E59: 1100 | F59: 1 | G59: 200 | I59: 150 | K59: 1 | L59: 1 | M59: 200 | O59: 0 | Q59: 0 | R59: =SUM(K59,I59,G59,E59) -> 1451 | S59: =(B59+C59)*D59 -> 425 | U59: =K59*J59 -> 0 | V59: =(D59*E59)+(F59*G59)+(H59*I59)+(J59*K59)+(L59*M59) -> 1500 | W59: =(V59*5%) -> 75 | X59: =SUM(V59+W59) -> 1575 | Y59: 2015-19
A60: 42209 | C60: 425 | D60: 1 | E60: 1100 | F60: 1 | G60: 200 | I60: 150 | K60: 1 | L60: 1 | M60: 200 | O60: 0 | Q60: 0 | R60: =SUM(K60,I60,G60,E60) -> 1451 | S60: =(B60+C60)*D60 -> 425 | U60: =K60*J60 -> 0 | V60: =(D60*E60)+(F60*G60)+(H60*I60)+(J60*K60)+(L60*M60) -> 1500 | W60: =(V60*5%) -> 75 | X60: =SUM(V60+W60) -> 1575 | Y60: 2015-19
A61: 42210 | C61: 425 | D61: 1 | E61: 1100 | F61: 1 | G61: 200 | I61: 150 | K61: 1 | L61: 1 | M61: 200 | O61: 0 | Q61: 0 | R61: =SUM(K61,I61,G61,E61) -> 1451 | S61: =(B61+C61)*D61 -> 425 | U61: =K61*J61 -> 0 | V61: =(D61*E61)+(F61*G61)+(H61*I61)+(J61*K61)+(L61*M61) -> 1500 | W61: =(V61*5%) -> 75 | X61: =SUM(V61+W61) -> 1575 | Y61: 2015-19
A62: 42211 | C62: 425 | E62: 1100 | G62: 200 | I62: 150 | K62: 1 | L62: 1 | M62: 200 | O62: 0 | Q62: 0 | R62: =SUM(K62,I62,G62,E62) -> 1451 | S62: =(B62+C62)*D62 -> 0 | U62: =K62*J62 -> 0 | V62: =(D62*E62)+(F62*G62)+(H62*I62)+(J62*K62)+(L62*M62) -> 200 | W62: =(V62*5%) -> 10 | X62: =SUM(V62+W62) -> 210 | Y62: 2015-19
A63: 42212 | C63: 425 | D63: 1 | E63: 1100 | F63: 1 | G63: 200 | I63: 150 | K63: 1 | L63: 1 | M63: 200 | O63: 0 | Q63: 0 | R63: =SUM(K63,I63,G63,E63) -> 1451 | S63: =(B63+C63)*D63 -> 425 | U63: =K63*J63 -> 0 | V63: =(D63*E63)+(F63*G63)+(H63*I63)+(J63*K63)+(L63*M63) -> 1500 | W63: =(V63*5%) -> 75 | X63: =SUM(V63+W63) -> 1575 | Y63: 2015-19
A64: 42213 | C64: 425 | D64: 1 | E64: 1100 | F64: 1 | G64: 200 | I64: 150 | K64: 1 | L64: 1 | M64: 200 | O64: 0 | Q64: 0 | R64: =SUM(K64,I64,G64,E64) -> 1451 | S64: =(B64+C64)*D64 -> 425 | U64: =K64*J64 -> 0 | V64: =(D64*E64)+(F64*G64)+(H64*I64)+(J64*K64)+(L64*M64) -> 1500 | W64: =(V64*5%) -> 75 | X64: =SUM(V64+W64) -> 1575 | Y64: 2015-19
A65: 42214 | C65: 425 | D65: 1 | E65: 1100 | F65: 1 | G65: 200 | I65: 150 | K65: 1 | L65: 1 | M65: 200 | O65: 0 | Q65: 0 | R65: =SUM(K65,I65,G65,E65) -> 1451 | S65: =(B65+C65)*D65 -> 425 | U65: =K65*J65 -> 0 | V65: =(D65*E65)+(F65*G65)+(H65*I65)+(J65*K65)+(L65*M65) -> 1500 | W65: =(V65*5%) -> 75 | X65: =SUM(V65+W65) -> 1575 | Y65: 2015-19
A66: 42215 | C66: 425 | D66: 1 | E66: 1100 | F66: 1 | G66: 200 | I66: 150 | K66: 1 | L66: 1 | M66: 200 | O66: 0 | Q66: 0 | R66: =SUM(K66,I66,G66,E66) -> 1451 | S66: =(B66+C66)*D66 -> 425 | U66: =K66*J66 -> 0 | V66: =(D66*E66)+(F66*G66)+(H66*I66)+(J66*K66)+(L66*M66) -> 1500 | W66: =(V66*5%) -> 75 | X66: =SUM(V66+W66) -> 1575 | Y66: 2015-19
A67: 42216 | C67: 425 | D67: 1 | E67: 1100 | F67: 1 | G67: 200 | I67: 150 | K67: 1 | L67: 1 | M67: 200 | O67: 0 | Q67: 0 | R67: =SUM(K67,I67,G67,E67) -> 1451 | S67: =(B67+C67)*D67 -> 425 | U67: =K67*J67 -> 0 | V67: =(D67*E67)+(F67*G67)+(H67*I67)+(J67*K67)+(L67*M67) -> 1500 | W67: =(V67*5%) -> 75 | X67: =SUM(V67+W67) -> 1575 | Y67: 2015-19 | Z67: =SUM(V52:V67) -> 22700
A68: 42217 | C68: 425 | D68: 1 | E68: 1100 | F68: 1 | G68: 200 | I68: 150 | K68: 1 | L68: 1 | M68: 200 | O68: 0 | Q68: 0 | R68: =SUM(K68,I68,G68,E68) -> 1451 | S68: =(B68+C68)*D68 -> 425 | U68: =K68*J68 -> 0 | V68: =(D68*E68)+(F68*G68)+(H68*I68)+(J68*K68)+(L68*M68) -> 1500 | W68: =(V68*5%) -> 75 | X68: =SUM(V68+W68) -> 1575 | Y68: 2015-20
A69: 42218 | C69: 425 | E69: 1100 | G69: 200 | I69: 150 | K69: 1 | L69: 1 | M69: 200 | O69: 0 | Q69: 0 | R69: =SUM(K69,I69,G69,E69) -> 1451 | S69: =(B69+C69)*D69 -> 0 | U69: =K69*J69 -> 0 | V69: =(D69*E69)+(F69*G69)+(H69*I69)+(J69*K69)+(L69*M69) -> 200 | W69: =(V69*5%) -> 10 | X69: =SUM(V69+W69) -> 210 | Y69: 2015-20
A70: 42219 | C70: 425 | D70: 1 | E70: 1100 | F70: 1 | G70: 200 | I70: 150 | K70: 1 | L70: 1 | M70: 200 | O70: 0 | Q70: 0 | R70: =SUM(K70,I70,G70,E70) -> 1451 | S70: =(B70+C70)*D70 -> 425 | U70: =K70*J70 -> 0 | V70: =(D70*E70)+(F70*G70)+(H70*I70)+(J70*K70)+(L70*M70) -> 1500 | W70: =(V70*5%) -> 75 | X70: =SUM(V70+W70) -> 1575 | Y70: 2015-20
A71: 42220 | C71: 425 | D71: 1 | E71: 1100 | F71: 1 | G71: 200 | I71: 150 | K71: 1 | L71: 1 | M71: 200 | O71: 0 | Q71: 0 | R71: =SUM(K71,I71,G71,E71) -> 1451 | S71: =(B71+C71)*D71 -> 425 | U71: =K71*J71 -> 0 | V71: =(D71*E71)+(F71*G71)+(H71*I71)+(J71*K71)+(L71*M71) -> 1500 | W71: =(V71*5%) -> 75 | X71: =SUM(V71+W71) -> 1575 | Y71: 2015-20
A72: 42221 | C72: 425 | D72: 1 | E72: 1100 | F72: 1 | G72: 200 | I72: 150 | K72: 1 | L72: 1 | M72: 200 | O72: 0 | Q72: 0 | R72: =SUM(K72,I72,G72,E72) -> 1451 | S72: =(B72+C72)*D72 -> 425 | U72: =K72*J72 -> 0 | V72: =(D72*E72)+(F72*G72)+(H72*I72)+(J72*K72)+(L72*M72) -> 1500 | W72: =(V72*5%) -> 75 | X72: =SUM(V72+W72) -> 1575 | Y72: 2015-20
A73: 42222 | C73: 425 | D73: 1 | E73: 1100 | F73: 1 | G73: 200 | I73: 150 | K73: 1 | L73: 1 | M73: 200 | O73: 0 | Q73: 0 | R73: =SUM(K73,I73,G73,E73) -> 1451 | S73: =(B73+C73)*D73 -> 425 | U73: =K73*J73 -> 0 | V73: =(D73*E73)+(F73*G73)+(H73*I73)+(J73*K73)+(L73*M73) -> 1500 | W73: =(V73*5%) -> 75 | X73: =SUM(V73+W73) -> 1575 | Y73: 2015-20
A74: 42228 | C74: 426 | D74: 1 | E74: 1100 | F74: 1 | G74: 200 | I74: 150 | K74: 1 | L74: 1 | M74: 200 | O74: 0 | Q74: 0 | R74: =SUM(K74,I74,G74,E74) -> 1451 | S74: =(B74+C74)*D74 -> 426 | U74: =K74*J74 -> 0 | V74: =(D74*E74)+(F74*G74)+(H74*I74)+(J74*K74)+(L74*M74) -> 1500 | W74: =(V74*5%) -> 75 | X74: =SUM(V74+W74) -> 1575 | Y74: 2015-20
A75: 42229 | C75: 426 | D75: 1 | E75: 1100 | F75: 1 | G75: 200 | I75: 150 | K75: 1 | L75: 1 | M75: 200 | O75: 0 | Q75: 0 | R75: =SUM(K75,I75,G75,E75) -> 1451 | S75: =(B75+C75)*D75 -> 426 | U75: =K75*J75 -> 0 | V75: =(D75*E75)+(F75*G75)+(H75*I75)+(J75*K75)+(L75*M75) -> 1500 | W75: =(V75*5%) -> 75 | X75: =SUM(V75+W75) -> 1575 | Y75: 2015-20
A76: 42230 | C76: 426 | D76: 1 | E76: 1100 | F76: 1 | G76: 200 | I76: 150 | K76: 1 | L76: 1 | M76: 200 | O76: 0 | Q76: 0 | R76: =SUM(K76,I76,G76,E76) -> 1451 | S76: =(B76+C76)*D76 -> 426 | U76: =K76*J76 -> 0 | V76: =(D76*E76)+(F76*G76)+(H76*I76)+(J76*K76)+(L76*M76) -> 1500 | W76: =(V76*5%) -> 75 | X76: =SUM(V76+W76) -> 1575 | Y76: 2015-20 | AB76: 13700
A77: 42231 | C77: 426 | D77: 1 | E77: 1100 | F77: 1 | G77: 200 | I77: 150 | K77: 1 | L77: 1 | M77: 200 | O77: 0 | Q77: 0 | R77: =SUM(K77,I77,G77,E77) -> 1451 | S77: =(B77+C77)*D77 -> 426 | U77: =K77*J77 -> 0 | V77: =(D77*E77)+(F77*G77)+(H77*I77)+(J77*K77)+(L77*M77) -> 1500 | W77: =(V77*5%) -> 75 | X77: =SUM(V77+W77) -> 1575 | Y77: 2015-20 | Z77: =SUM(V68:V77) -> 13700 | AA77: Invoice#2015-20
A78: 42232 | C78: 426 | D78: 0 | E78: 1100 | G78: 200 | I78: 150 | K78: 1 | L78: 1 | M78: 200 | O78: 0 | Q78: 0 | R78: =SUM(K78,I78,G78,E78) -> 1451 | S78: =(B78+C78)*D78 -> 0 | U78: =K78*J78 -> 0 | V78: =(D78*E78)+(F78*G78)+(H78*I78)+(J78*K78)+(L78*M78) -> 200 | W78: =(V78*5%) -> 10 | X78: =SUM(V78+W78) -> 210 | Y78: 2015-21
A79: 42233 | C79: 427 | D79: 1 | E79: 1100 | F79: 1 | G79: 200 | I79: 150 | K79: 1 | L79: 1 | M79: 200 | O79: 0 | Q79: 0 | R79: =SUM(K79,I79,G79,E79) -> 1451 | S79: =(B79+C79)*D79 -> 427 | U79: =K79*J79 -> 0 | V79: =(D79*E79)+(F79*G79)+(H79*I79)+(J79*K79)+(L79*M79) -> 1500 | W79: =(V79*5%) -> 75 | X79: =SUM(V79+W79) -> 1575 | Y79: 2015-21
A80: 42234 | D80: 1 | E80: 1100 | F80: 1 | G80: 200 | I80: 150 | K80: 1 | L80: 1 | M80: 200 | O80: 0 | Q80: 0 | R80: =SUM(K80,I80,G80,E80) -> 1451 | S80: =(B80+C80)*D80 -> 0 | U80: =K80*J80 -> 0 | V80: =(D80*E80)+(F80*G80)+(H80*I80)+(J80*K80)+(L80*M80) -> 1500 | W80: =(V80*5%) -> 75 | X80: =SUM(V80+W80) -> 1575 | Y80: 2015-21
A81: 42235 | D81: 1 | E81: 1100 | F81: 1 | G81: 200 | I81: 150 | K81: 1 | L81: 1 | M81: 200 | O81: 0 | Q81: 0 | R81: =SUM(K81,I81,G81,E81) -> 1451 | S81: =(B81+C81)*D81 -> 0 | U81: =K81*J81 -> 0 | V81: =(D81*E81)+(F81*G81)+(H81*I81)+(J81*K81)+(L81*M81) -> 1500 | W81: =(V81*5%) -> 75 | X81: =SUM(V81+W81) -> 1575 | Y81: 2015-21
A82: 42236 | D82: 1 | E82: 1100 | F82: 1 | G82: 200 | I82: 150 | K82: 1 | L82: 1 | M82: 200 | O82: 0 | Q82: 0 | R82: =SUM(K82,I82,G82,E82) -> 1451 | S82: =(B82+C82)*D82 -> 0 | U82: =K82*J82 -> 0 | V82: =(D82*E82)+(F82*G82)+(H82*I82)+(J82*K82)+(L82*M82) -> 1500 | W82: =(V82*5%) -> 75 | X82: =SUM(V82+W82) -> 1575 | Y82: 2015-21
A83: 42237 | D83: 1 | E83: 1100 | F83: 1 | G83: 200 | I83: 150 | K83: 1 | L83: 1 | M83: 200 | O83: 0 | Q83: 0 | R83: =SUM(K83,I83,G83,E83) -> 1451 | S83: =(B83+C83)*D83 -> 0 | U83: =K83*J83 -> 0 | V83: =(D83*E83)+(F83*G83)+(H83*I83)+(J83*K83)+(L83*M83) -> 1500 | W83: =(V83*5%) -> 75 | X83: =SUM(V83+W83) -> 1575 | Y83: 2015-21
A84: 42238 | D84: 1 | E84: 1100 | F84: 1 | G84: 200 | I84: 150 | K84: 1 | L84: 1 | M84: 200 | R84: =SUM(K84,I84,G84,E84) -> 1451 | S84: =(B84+C84)*D84 -> 0 | U84: =K84*J84 -> 0 | V84: =(D84*E84)+(F84*G84)+(H84*I84)+(J84*K84)+(L84*M84) -> 1500 | W84: =(V84*5%) -> 75 | X84: =SUM(V84+W84) -> 1575 | Y84: 2015-21
A85: 42239 | D85: 0 | E85: 1100 | F85: 0 | G85: 200 | I85: 150 | K85: 1 | L85: 1 | M85: 200 | O85: 0 | Q85: 0 | R85: =SUM(K85,I85,G85,E85) -> 1451 | S85: =(B85+C85)*D85 -> 0 | U85: =K85*J85 -> 0 | V85: =(D85*E85)+(F85*G85)+(H85*I85)+(J85*K85)+(L85*M85) -> 200 | W85: =(V85*5%) -> 10 | X85: =SUM(V85+W85) -> 210 | Y85: 2015-21
A86: 42240 | D86: 1 | E86: 1100 | F86: 1 | G86: 200 | I86: 150 | K86: 1 | L86: 1 | M86: 200 | O86: 0 | Q86: 0 | R86: =SUM(K86,I86,G86,E86) -> 1451 | S86: =(B86+C86)*D86 -> 0 | U86: =K86*J86 -> 0 | V86: =(D86*E86)+(F86*G86)+(H86*I86)+(J86*K86)+(L86*M86) -> 1500 | W86: =(V86*5%) -> 75 | X86: =SUM(V86+W86) -> 1575 | Y86: 2015-21
A87: 42241 | D87: 1 | E87: 1100 | F87: 1 | G87: 200 | I87: 150 | K87: 1 | L87: 1 | M87: 200 | O87: 0 | Q87: 0 | R87: =SUM(K87,I87,G87,E87) -> 1451 | S87: =(B87+C87)*D87 -> 0 | U87: =K87*J87 -> 0 | V87: =(D87*E87)+(F87*G87)+(H87*I87)+(J87*K87)+(L87*M87) -> 1500 | W87: =(V87*5%) -> 75 | X87: =SUM(V87+W87) -> 1575 | Y87: 2015-21
A88: 42242 | D88: 1 | E88: 1100 | F88: 1 | G88: 200 | I88: 150 | K88: 1 | L88: 1 | M88: 200 | O88: 0 | Q88: 0 | R88: =SUM(K88,I88,G88,E88) -> 1451 | S88: =(B88+C88)*D88 -> 0 | U88: =K88*J88 -> 0 | V88: =(D88*E88)+(F88*G88)+(H88*I88)+(J88*K88)+(L88*M88) -> 1500 | W88: =(V88*5%) -> 75 | X88: =SUM(V88+W88) -> 1575 | Y88: 2015-21
A89: 42243 | D89: 1 | E89: 1100 | F89: 1 | G89: 200 | I89: 150 | K89: 1 | L89: 1 | M89: 200 | O89: 0 | Q89: 0 | R89: =SUM(K89,I89,G89,E89) -> 1451 | S89: =(B89+C89)*D89 -> 0 | U89: =K89*J89 -> 0 | V89: =(D89*E89)+(F89*G89)+(H89*I89)+(J89*K89)+(L89*M89) -> 1500 | W89: =(V89*5%) -> 75 | X89: =SUM(V89+W89) -> 1575 | Y89: 2015-21
A90: 42244 | D90: 1 | E90: 1100 | F90: 1 | G90: 200 | I90: 150 | K90: 1 | L90: 1 | M90: 200 | O90: 0 | Q90: 0 | R90: =SUM(K90,I90,G90,E90) -> 1451 | S90: =(B90+C90)*D90 -> 0 | U90: =K90*J90 -> 0 | V90: =(D90*E90)+(F90*G90)+(H90*I90)+(J90*K90)+(L90*M90) -> 1500 | W90: =(V90*5%) -> 75 | X90: =SUM(V90+W90) -> 1575 | Y90: 2015-21
A91: 42245 | D91: 1 | E91: 1100 | F91: 1 | G91: 200 | I91: 150 | K91: 1 | L91: 1 | M91: 200 | O91: 0 | Q91: 0 | R91: =SUM(K91,I91,G91,E91) -> 1451 | S91: =(B91+C91)*D91 -> 0 | U91: =K91*J91 -> 0 | V91: =(D91*E91)+(F91*G91)+(H91*I91)+(J91*K91)+(L91*M91) -> 1500 | W91: =(V91*5%) -> 75 | X91: =SUM(V91+W91) -> 1575 | Y91: 2015-21
A92: 42246 | D92: 0 | E92: 1100 | G92: 200 | I92: 150 | K92: 1 | L92: 1 | M92: 200 | O92: 0 | Q92: 0 | R92: =SUM(K92,I92,G92,E92) -> 1451 | S92: =(B92+C92)*D92 -> 0 | U92: =K92*J92 -> 0 | V92: =(D92*E92)+(F92*G92)+(H92*I92)+(J92*K92)+(L92*M92) -> 200 | W92: =(V92*5%) -> 10 | X92: =SUM(V92+W92) -> 210 | Y92: 2015-21 | AB92: 20100
A93: 42247 | D93: 1 | E93: 1100 | F93: 1 | G93: 200 | I93: 150 | K93: 1 | L93: 1 | M93: 200 | O93: 0 | Q93: 0 | R93: =SUM(K93,I93,G93,E93) -> 1451 | S93: =(B93+C93)*D93 -> 0 | U93: =K93*J93 -> 0 | V93: =(D93*E93)+(F93*G93)+(H93*I93)+(J93*K93)+(L93*M93) -> 1500 | W93: =(V93*5%) -> 75 | X93: =SUM(V93+W93) -> 1575 | Y93: 2015-21 | AA93: Invoice#2015-21
A94: 42248 | D94: 1 | E94: 1100 | F94: 1 | G94: 200 | I94: 150 | K94: 1 | L94: 1 | M94: 200 | O94: 0 | Q94: 0 | R94: =SUM(K94,I94,G94,E94) -> 1451 | S94: =(B94+C94)*D94 -> 0 | U94: =K94*J94 -> 0 | V94: =(D94*E94)+(F94*G94)+(H94*I94)+(J94*K94)+(L94*M94) -> 1500 | W94: =(V94*5%) -> 75 | X94: =SUM(V94+W94) -> 1575 | Y94: 2015-22
A95: 42249 | D95: 1 | E95: 1100 | F95: 1 | G95: 200 | I95: 150 | K95: 1 | L95: 1 | M95: 200 | O95: 0 | Q95: 0 | R95: =SUM(K95,I95,G95,E95) -> 1451 | S95: =(B95+C95)*D95 -> 0 | U95: =K95*J95 -> 0 | V95: =(D95*E95)+(F95*G95)+(H95*I95)+(J95*K95)+(L95*M95) -> 1500 | W95: =(V95*5%) -> 75 | X95: =SUM(V95+W95) -> 1575 | Y95: 2015-22
A96: 42250 | D96: 1 | E96: 1100 | F96: 1 | G96: 200 | I96: 150 | K96: 1 | L96: 1 | M96: 200 | O96: 0 | Q96: 0 | R96: =SUM(K96,I96,G96,E96) -> 1451 | S96: =(B96+C96)*D96 -> 0 | U96: =K96*J96 -> 0 | V96: =(D96*E96)+(F96*G96)+(H96*I96)+(J96*K96)+(L96*M96) -> 1500 | W96: =(V96*5%) -> 75 | X96: =SUM(V96+W96) -> 1575 | Y96: 2015-22
A97: 42251 | E97: 1100 | G97: 200 | I97: 150 | K97: 1 | M97: 200 | O97: 0 | Q97: 0 | R97: =SUM(K97,I97,G97,E97) -> 1451 | S97: =(B97+C97)*D97 -> 0 | U97: =K97*J97 -> 0 | V97: =(D97*E97)+(F97*G97)+(H97*I97)+(J97*K97)+(L97*M97) -> 0 | W97: =(V97*5%) -> 0 | X97: =SUM(V97+W97) -> 0 | Y97: 2015-22
A98: 42252 | E98: 1100 | G98: 200 | I98: 150 | K98: 1 | M98: 200 | O98: 0 | Q98: 0 | R98: =SUM(K98,I98,G98,E98) -> 1451 | S98: =(B98+C98)*D98 -> 0 | U98: =K98*J98 -> 0 | V98: =(D98*E98)+(F98*G98)+(H98*I98)+(J98*K98)+(L98*M98) -> 0 | W98: =(V98*5%) -> 0 | X98: =SUM(V98+W98) -> 0 | Y98: 2015-22
A99: 42253 | E99: 1100 | G99: 200 | I99: 150 | K99: 1 | M99: 200 | O99: 0 | Q99: 0 | R99: =SUM(K99,I99,G99,E99) -> 1451 | S99: =(B99+C99)*D99 -> 0 | U99: =K99*J99 -> 0 | V99: =(D99*E99)+(F99*G99)+(H99*I99)+(J99*K99)+(L99*M99) -> 0 | W99: =(V99*5%) -> 0 | X99: =SUM(V99+W99) -> 0 | Y99: 2015-22
A100: 42254 | E100: 1100 | G100: 200 | I100: 150 | K100: 1 | M100: 200 | O100: 0 | Q100: 0 | R100: =SUM(K100,I100,G100,E100) -> 1451 | S100: =(B100+C100)*D100 -> 0 | U100: =K100*J100 -> 0 | V100: =(D100*E100)+(F100*G100)+(H100*I100)+(J100*K100)+(L100*M100) -> 0 | W100: =(V100*5%) -> 0 | X100: =SUM(V100+W100) -> 0 | Y100: 2015-22
A101: 42255 | E101: 1100 | G101: 200 | I101: 150 | K101: 1 | M101: 200 | O101: 0 | Q101: 0 | R101: =SUM(K101,I101,G101,E101) -> 1451 | S101: =(B101+C101)*D101 -> 0 | U101: =K101*J101 -> 0 | V101: =(D101*E101)+(F101*G101)+(H101*I101)+(J101*K101)+(L101*M101) -> 0 | W101: =(V101*5%) -> 0 | X101: =SUM(V101+W101) -> 0 | Y101: 2015-22
A102: 42256 | E102: 1100 | G102: 200 | I102: 150 | K102: 1 | L102: 1 | M102: 200 | O102: 0 | Q102: 0 | R102: =SUM(K102,I102,G102,E102) -> 1451 | S102: =(B102+C102)*D102 -> 0 | U102: =K102*J102 -> 0 | V102: =(D102*E102)+(F102*G102)+(H102*I102)+(J102*K102)+(L102*M102) -> 200 | W102: =(V102*5%) -> 10 | X102: =SUM(V102+W102) -> 210 | Y102: 2015-22
...

Sheet Vendor #11
A2: Vendor #11
A4: Date | B4: Straight Hours Charged (ea.) | C4: Overtime Hours Charged (ea.) | D4: Vendor #11 | E4: Rate | F4: Truck | G4: Rate | H4: Km over 200 | I4: Rate | J4: Sub | K4: Rate | L4: Labourer class | M4: Rate | N4: Labourer class | O4: Rate | P4: Labourer class | Q4: Rate | R4: Total Labour Rate per hr | S4: Total Hours Charged | T4: Equipment Detail | U4: Km's Charged | V4: Subtotal | W4: GST | X4: LEM Amount | Y4: Affiliating Invoice | Z4: Approved By | AA4: SUM OF ALL LEM'S (before GST)
AA5: =SUM(V6:V221) -> 195250
A6: May 1-31 | E6: 1100 | G6: 200 | I6: 1 | K6: 175 | M6: 0 | O6: 0 | Q6: 0 | V6: 11250 | W6: =(V6*5%) -> 562.5 | X6: =SUM(V6+W6) -> 11812.5 | Y6: 48
A7: 42156 | B7: 1 | D7: 1 | E7: 1100 | F7: 1 | G7: 200 | I7: 1 | K7: 175 | M7: 0 | O7: 0 | Q7: 0 | R7: =(B7*#REF!)+(D7*E7)+(F7*G7) -> #REF! | U7: =H7*I7 -> 0 | V7: =(D7*E7)+(F7*G7)+(H7*I7)+(J7*K7) -> 1300 | W7: =(V7*5%) -> 65 | X7: =SUM(V7+W7) -> 1365 | Y7: 49
A8: 42157 | B8: 1 | D8: 1 | E8: 1100 | F8: 1 | G8: 200 | I8: 1 | K8: 175 | M8: 0 | O8: 0 | Q8: 0 | R8: =(B8*#REF!)+(D8*E8)+(F8*G8) -> #REF! | U8: =H8*I8 -> 0 | V8: =(D8*E8)+(F8*G8)+(H8*I8)+(J8*K8) -> 1300 | W8: =(V8*5%) -> 65 | X8: =SUM(V8+W8) -> 1365 | Y8: 49
A9: 42158 | B9: 1 | D9: 1 | E9: 1100 | F9: 1 | G9: 200 | I9: 1 | K9: 175 | M9: 0 | O9: 0 | Q9: 0 | R9: =(B9*#REF!)+(D9*E9)+(F9*G9) -> #REF! | U9: =H9*I9 -> 0 | V9: =(D9*E9)+(F9*G9)+(H9*I9)+(J9*K9) -> 1300 | W9: =(V9*5%) -> 65 | X9: =SUM(V9+W9) -> 1365 | Y9: 49
A10: 42159 | B10: 1 | D10: 1 | E10: 1100 | F10: 1 | G10: 200 | I10: 1 | K10: 175 | M10: 0 | O10: 0 | Q10: 0 | R10: =(B10*#REF!)+(D10*E10)+(F10*G10) -> #REF! | U10: =H10*I10 -> 0 | V10: =(D10*E10)+(F10*G10)+(H10*I10)+(J10*K10) -> 1300 | W10: =(V10*5%) -> 65 | X10: =SUM(V10+W10) -> 1365 | Y10: 49
A11: 42160 | B11: 1 | D11: 1 | E11: 1100 | F11: 1 | G11: 200 | I11: 1 | K11: 175 | M11: 0 | O11: 0 | Q11: 0 | R11: =(B11*#REF!)+(D11*E11)+(F11*G11) -> #REF! | U11: =H11*I11 -> 0 | V11: =(D11*E11)+(F11*G11)+(H11*I11)+(J11*K11) -> 1300 | W11: =(V11*5%) -> 65 | X11: =SUM(V11+W11) -> 1365 | Y11: 49
A12: 42161 | D12: 1 | E12: 1100 | F12: 1 | G12: 200 | I12: 1 | K12: 175 | U12: =H12*I12 -> 0 | V12: =(D12*E12)+(F12*G12)+(H12*I12)+(J12*K12) -> 1300 | W12: =(V12*5%) -> 65 | X12: =SUM(V12+W12) -> 1365 | Y12: 49
A13: 42162 | E13: 1100 | G13: 200 | I13: 1 | J13: 1 | K13: 175 | U13: =H13*I13 -> 0 | V13: =(D13*E13)+(F13*G13)+(H13*I13)+(J13*K13) -> 175 | W13: =(V13*5%) -> 8.75 | X13: =SUM(V13+W13) -> 183.75 | Y13: 49
A14: 42163 | B14: 1 | D14: 1 | E14: 1100 | F14: 1 | G14: 200 | I14: 1 | J14: 1 | K14: 175 | M14: 0 | O14: 0 | Q14: 0 | R14: =(B14*#REF!)+(D14*E14)+(F14*G14) -> #REF! | U14: =H14*I14 -> 0 | V14: =(D14*E14)+(F14*G14)+(H14*I14)+(J14*K14) -> 1475 | W14: =(V14*5%) -> 73.75 | X14: =SUM(V14+W14) -> 1548.75 | Y14: 49
A15: 42164 | B15: 1 | D15: 1 | E15: 1100 | F15: 1 | G15: 200 | I15: 1 | J15: 1 | K15: 175 | M15: 0 | O15: 0 | Q15: 0 | R15: =(B15*#REF!)+(D15*E15)+(F15*G15) -> #REF! | U15: =H15*I15 -> 0 | V15: =(D15*E15)+(F15*G15)+(H15*I15)+(J15*K15) -> 1475 | W15: =(V15*5%) -> 73.75 | X15: =SUM(V15+W15) -> 1548.75 | Y15: 49
A16: 42165 | B16: 1 | D16: 1 | E16: 1100 | F16: 1 | G16: 200 | I16: 1 | J16: 1 | K16: 175 | M16: 0 | O16: 0 | Q16: 0 | R16: =(B16*#REF!)+(D16*E16)+(F16*G16) -> #REF! | U16: =H16*I16 -> 0 | V16: =(D16*E16)+(F16*G16)+(H16*I16)+(J16*K16) -> 1475 | W16: =(V16*5%) -> 73.75 | X16: =SUM(V16+W16) -> 1548.75 | Y16: 49
A17: 42166 | B17: 1 | D17: 1 | E17: 1100 | F17: 1 | G17: 200 | I17: 1 | J17: 1 | K17: 175 | M17: 0 | O17: 0 | Q17: 0 | R17: =(B17*#REF!)+(D17*E17)+(F17*G17) -> #REF! | U17: =H17*I17 -> 0 | V17: =(D17*E17)+(F17*G17)+(H17*I17)+(J17*K17) -> 1475 | W17: =(V17*5%) -> 73.75 | X17: =SUM(V17+W17) -> 1548.75 | Y17: 49
A18: 42167 | B18: 1 | D18: 1 | E18: 1100 | F18: 1 | G18: 200 | I18: 1 | J18: 1 | K18: 175 | M18: 0 | O18: 0 | Q18: 0 | R18: =(B18*#REF!)+(D18*E18)+(F18*G18) -> #REF! | U18: =H18*I18 -> 0 | V18: =(D18*E18)+(F18*G18)+(H18*I18)+(J18*K18) -> 1475 | W18: =(V18*5%) -> 73.75 | X18: =SUM(V18+W18) -> 1548.75 | Y18: 49
A19: 42168 | B19: 1 | D19: 1 | E19: 1100 | F19: 1 | G19: 200 | I19: 1 | J19: 1 | K19: 175 | M19: 0 | O19: 0 | Q19: 0 | R19: =(B19*#REF!)+(D19*E19)+(F19*G19) -> #REF! | U19: =H19*I19 -> 0 | V19: =(D19*E19)+(F19*G19)+(H19*I19)+(J19*K19) -> 1475 | W19: =(V19*5%) -> 73.75 | X19: =SUM(V19+W19) -> 1548.75 | Y19: 49
A20: 42169 | B20: 0 | E20: 1100 | G20: 200 | I20: 1 | J20: 1 | K20: 175 | M20: 0 | O20: 0 | Q20: 0 | R20: =(B20*#REF!)+(D20*E20)+(F20*G20) -> #REF! | U20: =H20*I20 -> 0 | V20: =(D20*E20)+(F20*G20)+(H20*I20)+(J20*K20) -> 175 | W20: =(V20*5%) -> 8.75 | X20: =SUM(V20+W20) -> 183.75 | Y20: 49
A21: 42170 | B21: 1 | D21: 1 | E21: 1100 | F21: 1 | G21: 200 | I21: 1 | J21: 1 | K21: 175 | M21: 0 | O21: 0 | Q21: 0 | R21: =(B21*#REF!)+(D21*E21)+(F21*G21) -> #REF! | U21: =H21*I21 -> 0 | V21: =(D21*E21)+(F21*G21)+(H21*I21)+(J21*K21) -> 1475 | W21: =(V21*5%) -> 73.75 | X21: =SUM(V21+W21) -> 1548.75 | Y21: 49
A22: 42171 | B22: 1 | D22: 1 | E22: 1100 | F22: 1 | G22: 200 | I22: 1 | J22: 1 | K22: 175 | M22: 0 | O22: 0 | Q22: 0 | R22: =(B22*#REF!)+(D22*E22)+(F22*G22) -> #REF! | U22: =H22*I22 -> 0 | V22: =(D22*E22)+(F22*G22)+(H22*I22)+(J22*K22) -> 1475 | W22: =(V22*5%) -> 73.75 | X22: =SUM(V22+W22) -> 1548.75 | Y22: 49
A23: 42172 | D23: 1 | E23: 1100 | F23: 1 | G23: 200 | I23: 1 | J23: 1 | K23: 175 | M23: 0 | O23: 0 | Q23: 0 | R23: =(B23*#REF!)+(D23*E23)+(F23*G23) -> #REF! | U23: =H23*I23 -> 0 | V23: =(D23*E23)+(F23*G23)+(H23*I23)+(J23*K23) -> 1475 | W23: =(V23*5%) -> 73.75 | X23: =SUM(V23+W23) -> 1548.75 | Y23: 49
A24: 42173 | D24: 1 | E24: 1100 | F24: 1 | G24: 200 | I24: 1 | J24: 1 | K24: 175 | M24: 0 | O24: 0 | Q24: 0 | R24: =(B24*#REF!)+(D24*E24)+(F24*G24) -> #REF! | U24: =H24*I24 -> 0 | V24: =(D24*E24)+(F24*G24)+(H24*I24)+(J24*K24) -> 1475 | W24: =(V24*5%) -> 73.75 | X24: =SUM(V24+W24) -> 1548.75 | Y24: 49
A25: 42174 | D25: 1 | E25: 1100 | F25: 1 | G25: 200 | I25: 1 | J25: 1 | K25: 175 | M25: 0 | O25: 0 | Q25: 0 | R25: =(B25*#REF!)+(D25*E25)+(F25*G25) -> #REF! | U25: =H25*I25 -> 0 | V25: =(D25*E25)+(F25*G25)+(H25*I25)+(J25*K25) -> 1475 | W25: =(V25*5%) -> 73.75 | X25: =SUM(V25+W25) -> 1548.75 | Y25: 49
A26: 42175 | D26: 1 | E26: 1100 | F26: 1 | G26: 200 | I26: 1 | J26: 1 | K26: 175 | M26: 0 | O26: 0 | Q26: 0 | R26: =(B26*#REF!)+(D26*E26)+(F26*G26) -> #REF! | U26: =H26*I26 -> 0 | V26: =(D26*E26)+(F26*G26)+(H26*I26)+(J26*K26) -> 1475 | W26: =(V26*5%) -> 73.75 | X26: =SUM(V26+W26) -> 1548.75 | Y26: 49
A27: 42176 | E27: 1100 | G27: 200 | I27: 1 | J27: 1 | K27: 175 | M27: 0 | O27: 0 | Q27: 0 | R27: =(B27*#REF!)+(D27*E27)+(F27*G27) -> #REF! | U27: =H27*I27 -> 0 | V27: =(D27*E27)+(F27*G27)+(H27*I27)+(J27*K27) -> 175 | W27: =(V27*5%) -> 8.75 | X27: =SUM(V27+W27) -> 183.75 | Y27: 49
A28: 42177 | D28: 1 | E28: 1100 | F28: 1 | G28: 200 | I28: 1 | J28: 1 | K28: 175 | M28: 0 | O28: 0 | Q28: 0 | R28: =(B28*#REF!)+(D28*E28)+(F28*G28) -> #REF! | U28: =H28*I28 -> 0 | V28: =(D28*E28)+(F28*G28)+(H28*I28)+(J28*K28) -> 1475 | W28: =(V28*5%) -> 73.75 | X28: =SUM(V28+W28) -> 1548.75 | Y28: 49
A29: 42178 | D29: 1 | E29: 1100 | F29: 1 | G29: 200 | I29: 1 | J29: 1 | K29: 175 | M29: 0 | O29: 0 | Q29: 0 | R29: =(B29*#REF!)+(D29*E29)+(F29*G29) -> #REF! | U29: =H29*I29 -> 0 | V29: =(D29*E29)+(F29*G29)+(H29*I29)+(J29*K29) -> 1475 | W29: =(V29*5%) -> 73.75 | X29: =SUM(V29+W29) -> 1548.75 | Y29: 49
A30: 42179 | D30: 1 | E30: 1100 | F30: 1 | G30: 200 | I30: 1 | J30: 1 | K30: 175 | M30: 0 | O30: 0 | Q30: 0 | R30: =(B30*#REF!)+(D30*E30)+(F30*G30) -> #REF! | U30: =H30*I30 -> 0 | V30: =(D30*E30)+(F30*G30)+(H30*I30)+(J30*K30) -> 1475 | W30: =(V30*5%) -> 73.75 | X30: =SUM(V30+W30) -> 1548.75 | Y30: 49
A31: 42180 | D31: 1 | E31: 1100 | F31: 1 | G31: 200 | I31: 1 | J31: 1 | K31: 175 | M31: 0 | O31: 0 | Q31: 0 | R31: =(B31*#REF!)+(D31*E31)+(F31*G31) -> #REF! | U31: =H31*I31 -> 0 | V31: =(D31*E31)+(F31*G31)+(H31*I31)+(J31*K31) -> 1475 | W31: =(V31*5%) -> 73.75 | X31: =SUM(V31+W31) -> 1548.75 | Y31: 49
A32: 42181 | D32: 1 | E32: 1100 | F32: 1 | G32: 200 | I32: 1 | J32: 1 | K32: 175 | M32: 0 | O32: 0 | Q32: 0 | R32: =(B32*#REF!)+(D32*E32)+(F32*G32) -> #REF! | U32: =H32*I32 -> 0 | V32: =(D32*E32)+(F32*G32)+(H32*I32)+(J32*K32) -> 1475 | W32: =(V32*5%) -> 73.75 | X32: =SUM(V32+W32) -> 1548.75 | Y32: 49
A33: 42182 | D33: 1 | E33: 1100 | F33: 1 | G33: 200 | I33: 1 | J33: 1 | K33: 175 | M33: 0 | O33: 0 | Q33: 0 | R33: =SUM(K33,I33,G33,E33) -> 1476 | U33: =H33*I33 -> 0 | V33: =(D33*E33)+(F33*G33)+(H33*I33)+(J33*K33) -> 1475 | W33: =(V33*5%) -> 73.75 | X33: =SUM(V33+W33) -> 1548.75 | Y33: 49
A34: 42183 | E34: 1100 | G34: 200 | I34: 1 | J34: 1 | K34: 175 | M34: 0 | O34: 0 | Q34: 0 | R34: =SUM(K34,I34,G34,E34) -> 1476 | U34: =H34*I34 -> 0 | V34: =(D34*E34)+(F34*G34)+(H34*I34)+(J34*K34) -> 175 | W34: =(V34*5%) -> 8.75 | X34: =SUM(V34+W34) -> 183.75 | Y34: 49
A35: 42184 | D35: 1 | E35: 1100 | F35: 1 | G35: 200 | I35: 1 | J35: 1 | K35: 175 | U35: =H35*I35 -> 0 | V35: =(D35*E35)+(F35*G35)+(H35*I35)+(J35*K35) -> 1475 | W35: =(V35*5%) -> 73.75 | X35: =SUM(V35+W35) -> 1548.75 | Y35: 49
A36: 42185 | D36: 1 | E36: 1100 | F36: 1 | G36: 200 | I36: 1 | J36: 1 | K36: 175 | U36: =H36*I36 -> 0 | V36: =(D36*E36)+(F36*G36)+(H36*I36)+(J36*K36) -> 1475 | W36: =(V36*5%) -> 73.75 | X36: =SUM(V36+W36) -> 1548.75 | Y36: 49
A37: 42186 | D37: 1 | E37: 1100 | F37: 1 | G37: 200 | I37: 1 | J37: 1 | K37: 175 | U37: =H37*I37 -> 0 | V37: =(D37*E37)+(F37*G37)+(H37*I37)+(J37*K37) -> 1475 | W37: =(V37*5%) -> 73.75 | X37: =SUM(V37+W37) -> 1548.75 | Y37: 50
A38: 42187 | D38: 1 | E38: 1100 | F38: 1 | G38: 200 | I38: 1 | J38: 1 | K38: 175 | U38: =H38*I38 -> 0 | V38: =(D38*E38)+(F38*G38)+(H38*I38)+(J38*K38) -> 1475 | W38: =(V38*5%) -> 73.75 | X38: =SUM(V38+W38) -> 1548.75 | Y38: 50
A39: 42188 | D39: 1 | E39: 1100 | F39: 1 | G39: 200 | I39: 1 | J39: 1 | K39: 175 | U39: =H39*I39 -> 0 | V39: =(D39*E39)+(F39*G39)+(H39*I39)+(J39*K39) -> 1475 | W39: =(V39*5%) -> 73.75 | X39: =SUM(V39+W39) -> 1548.75 | Y39: 50
A40: 42189 | D40: 1 | E40: 1100 | F40: 1 | G40: 200 | I40: 1 | J40: 1 | K40: 175 | U40: =H40*I40 -> 0 | V40: =(D40*E40)+(F40*G40)+(H40*I40)+(J40*K40) -> 1475 | W40: =(V40*5%) -> 73.75 | X40: =SUM(V40+W40) -> 1548.75 | Y40: 50
A41: 42190 | J41: 1 | K41: 175 | U41: =H41*I41 -> 0 | V41: =(D41*E41)+(F41*G41)+(H41*I41)+(J41*K41) -> 175 | W41: =(V41*5%) -> 8.75 | X41: =SUM(V41+W41) -> 183.75 | Y41: 50
A42: 42191 | D42: 1 | E42: 1100 | F42: 1 | G42: 200 | I42: 1 | J42: 1 | K42: 175 | V42: =(D42*E42)+(F42*G42)+(H42*I42)+(J42*K42) -> 1475 | W42: =(V42*5%) -> 73.75 | X42: =SUM(V42+W42) -> 1548.75 | Y42: 50
A43: 42192 | D43: 1 | E43: 1100 | F43: 1 | G43: 200 | I43: 1 | J43: 1 | K43: 175 | V43: =(D43*E43)+(F43*G43)+(H43*I43)+(J43*K43) -> 1475 | W43: =(V43*5%) -> 73.75 | X43: =SUM(V43+W43) -> 1548.75 | Y43: 50
A44: 42193 | D44: 1 | E44: 1100 | F44: 1 | G44: 200 | I44: 1 | J44: 1 | K44: 175 | V44: =(D44*E44)+(F44*G44)+(H44*I44)+(J44*K44) -> 1475 | W44: =(V44*5%) -> 73.75 | X44: =SUM(V44+W44) -> 1548.75 | Y44: 50
A45: 42194 | D45: 1 | E45: 1100 | F45: 1 | G45: 200 | I45: 1 | J45: 1 | K45: 175 | V45: =(D45*E45)+(F45*G45)+(H45*I45)+(J45*K45) -> 1475 | W45: =(V45*5%) -> 73.75 | X45: =SUM(V45+W45) -> 1548.75 | Y45: 50
A46: 42195 | D46: 1 | E46: 1100 | F46: 1 | G46: 200 | I46: 1 | J46: 1 | K46: 175 | V46: =(D46*E46)+(F46*G46)+(H46*I46)+(J46*K46) -> 1475 | W46: =(V46*5%) -> 73.75 | X46: =SUM(V46+W46) -> 1548.75 | Y46: 50
A47: 42196 | D47: 1 | E47: 1100 | F47: 1 | G47: 200 | I47: 1 | J47: 1 | K47: 175 | V47: =(D47*E47)+(F47*G47)+(H47*I47)+(J47*K47) -> 1475 | W47: =(V47*5%) -> 73.75 | X47: =SUM(V47+W47) -> 1548.75 | Y47: 50
A48: 42197 | E48: 1100 | G48: 200 | I48: 1 | J48: 1 | K48: 175 | V48: =(D48*E48)+(F48*G48)+(H48*I48)+(J48*K48) -> 175 | W48: =(V48*5%) -> 8.75 | X48: =SUM(V48+W48) -> 183.75 | Y48: 50
A49: 42198 | D49: 1 | E49: 1100 | F49: 1 | G49: 200 | I49: 1 | J49: 1 | K49: 175 | V49: =(D49*E49)+(F49*G49)+(H49*I49)+(J49*K49) -> 1475 | W49: =(V49*5%) -> 73.75 | X49: =SUM(V49+W49) -> 1548.75 | Y49: 50
A50: 42199 | D50: 1 | E50: 1100 | F50: 1 | G50: 200 | I50: 1 | J50: 1 | K50: 175 | V50: =(D50*E50)+(F50*G50)+(H50*I50)+(J50*K50) -> 1475 | W50: =(V50*5%) -> 73.75 | X50: =SUM(V50+W50) -> 1548.75 | Y50: 50
A51: 42200 | D51: 1 | E51: 1100 | F51: 1 | G51: 200 | I51: 1 | J51: 1 | K51: 175 | V51: =(D51*E51)+(F51*G51)+(H51*I51)+(J51*K51) -> 1475 | W51: =(V51*5%) -> 73.75 | X51: =SUM(V51+W51) -> 1548.75 | Y51: 50
A52: 42201 | D52: 1 | E52: 1100 | F52: 1 | G52: 200 | I52: 1 | J52: 1 | K52: 175 | V52: =(D52*E52)+(F52*G52)+(H52*I52)+(J52*K52) -> 1475 | W52: =(V52*5%) -> 73.75 | X52: =SUM(V52+W52) -> 1548.75 | Y52: 50 | Z52: =SUM(V37:V63) -> 37225
A53: 42205 | C53: 427 | D53: 1 | E53: 1100 | F53: 1 | G53: 200 | I53: 1 | J53: 1 | K53: 175 | V53: =(D53*E53)+(F53*G53)+(H53*I53)+(J53*K53) -> 1475 | W53: =(V53*5%) -> 73.75 | X53: =SUM(V53+W53) -> 1548.75 | Y53: 50
A54: 42206 | C54: 427 | D54: 1 | E54: 1100 | F54: 1 | G54: 200 | I54: 1 | J54: 1 | K54: 175 | V54: =(D54*E54)+(F54*G54)+(H54*I54)+(J54*K54) -> 1475 | W54: =(V54*5%) -> 73.75 | X54: =SUM(V54+W54) -> 1548.75 | Y54: 50
A55: 42207 | C55: 427 | D55: 1 | E55: 1100 | F55: 1 | G55: 200 | I55: 1 | J55: 1 | K55: 175 | V55: =(D55*E55)+(F55*G55)+(H55*I55)+(J55*K55) -> 1475 | W55: =(V55*5%) -> 73.75 | X55: =SUM(V55+W55) -> 1548.75 | Y55: 50
A56: 42208 | C56: 427 | D56: 1 | E56: 1100 | F56: 1 | G56: 200 | I56: 1 | J56: 1 | K56: 175 | V56: =(D56*E56)+(F56*G56)+(H56*I56)+(J56*K56) -> 1475 | W56: =(V56*5%) -> 73.75 | X56: =SUM(V56+W56) -> 1548.75 | Y56: 50
A57: 42209 | C57: 427 | D57: 1 | E57: 1100 | F57: 1 | G57: 200 | I57: 1 | J57: 1 | K57: 175 | V57: =(D57*E57)+(F57*G57)+(H57*I57)+(J57*K57) -> 1475 | W57: =(V57*5%) -> 73.75 | X57: =SUM(V57+W57) -> 1548.75 | Y57: 50
A58: 42210 | C58: 427 | D58: 1 | E58: 1100 | F58: 1 | G58: 200 | I58: 1 | J58: 1 | K58: 175 | V58: =(D58*E58)+(F58*G58)+(H58*I58)+(J58*K58) -> 1475 | W58: =(V58*5%) -> 73.75 | X58: =SUM(V58+W58) -> 1548.75 | Y58: 50
A59: 42212 | C59: 427 | D59: 1 | E59: 1100 | F59: 1 | G59: 200 | I59: 1 | J59: 1 | K59: 175 | V59: =(D59*E59)+(F59*G59)+(H59*I59)+(J59*K59) -> 1475 | W59: =(V59*5%) -> 73.75 | X59: =SUM(V59+W59) -> 1548.75 | Y59: 50
A60: 42213 | C60: 427 | D60: 1 | E60: 1100 | F60: 1 | G60: 200 | I60: 1 | J60: 1 | K60: 175 | V60: =(D60*E60)+(F60*G60)+(H60*I60)+(J60*K60) -> 1475 | W60: =(V60*5%) -> 73.75 | X60: =SUM(V60+W60) -> 1548.75 | Y60: 50
A61: 42214 | C61: 427 | D61: 1 | E61: 1100 | F61: 1 | G61: 200 | I61: 1 | J61: 1 | K61: 175 | V61: =(D61*E61)+(F61*G61)+(H61*I61)+(J61*K61) -> 1475 | W61: =(V61*5%) -> 73.75 | X61: =SUM(V61+W61) -> 1548.75 | Y61: 50
A62: 42215 | C62: 427 | D62: 1 | E62: 1100 | F62: 1 | G62: 200 | I62: 1 | J62: 1 | K62: 175 | V62: =(D62*E62)+(F62*G62)+(H62*I62)+(J62*K62) -> 1475 | W62: =(V62*5%) -> 73.75 | X62: =SUM(V62+W62) -> 1548.75 | Y62: 50
A63: 42216 | C63: 427 | D63: 1 | E63: 1100 | F63: 1 | G63: 200 | I63: 1 | J63: 1 | K63: 175 | V63: =(D63*E63)+(F63*G63)+(H63*I63)+(J63*K63) -> 1475 | W63: =(V63*5%) -> 73.75 | X63: =SUM(V63+W63) -> 1548.75 | Y63: 50
A64: 42217 | C64: 427 | E64: 1100 | G64: 200 | I64: 1 | K64: 175 | V64: =(D64*E64)+(F64*G64)+(H64*I64)+(J64*K64) -> 0 | W64: =(V64*5%) -> 0 | X64: =SUM(V64+W64) -> 0 | Y64: 51
A65: 42218 | C65: 427 | E65: 1100 | G65: 200 | I65: 1 | J65: 0 | K65: 175 | V65: =(D65*E65)+(F65*G65)+(H65*I65)+(J65*K65) -> 0 | W65: =(V65*5%) -> 0 | X65: =SUM(V65+W65) -> 0 | Y65: 51
A66: 42219 | C66: 427 | D66: 1 | E66: 1100 | F66: 1 | G66: 200 | I66: 1 | J66: 1 | K66: 175 | V66: =(D66*E66)+(F66*G66)+(H66*I66)+(J66*K66) -> 1475 | W66: =(V66*5%) -> 73.75 | X66: =SUM(V66+W66) -> 1548.75 | Y66: 51
A67: 42220 | C67: 427 | D67: 1 | E67: 1100 | F67: 1 | G67: 200 | I67: 1 | J67: 1 | K67: 175 | V67: =(D67*E67)+(F67*G67)+(H67*I67)+(J67*K67) -> 1475 | W67: =(V67*5%) -> 73.75 | X67: =SUM(V67+W67) -> 1548.75 | Y67: 51
A68: 42221 | C68: 427 | D68: 1 | E68: 1100 | F68: 1 | G68: 200 | I68: 1 | J68: 1 | K68: 175 | V68: =(D68*E68)+(F68*G68)+(H68*I68)+(J68*K68) -> 1475 | W68: =(V68*5%) -> 73.75 | X68: =SUM(V68+W68) -> 1548.75 | Y68: 51
A69: 42222 | C69: 427 | E69: 1100 | G69: 200 | I69: 1 | K69: 175 | V69: =(D69*E69)+(F69*G69)+(H69*I69)+(J69*K69) -> 0 | W69: =(V69*5%) -> 0 | X69: =SUM(V69+W69) -> 0 | Y69: 51
A70: 42223 | C70: 428 | E70: 1100 | G70: 200 | I70: 1 | K70: 175 | V70: =(D70*E70)+(F70*G70)+(H70*I70)+(J70*K70) -> 0 | W70: =(V70*5%) -> 0 | X70: =SUM(V70+W70) -> 0 | Y70: 51
A71: 42224 | C71: 429 | E71: 1100 | G71: 200 | I71: 1 | K71: 175 | V71: =(D71*E71)+(F71*G71)+(H71*I71)+(J71*K71) -> 0 | W71: =(V71*5%) -> 0 | X71: =SUM(V71+W71) -> 0 | Y71: 51
A72: 42225 | C72: 430 | E72: 1100 | G72: 200 | I72: 1 | K72: 175 | V72: =(D72*E72)+(F72*G72)+(H72*I72)+(J72*K72) -> 0 | W72: =(V72*5%) -> 0 | X72: =SUM(V72+W72) -> 0 | Y72: 51
A73: 42226 | C73: 431 | D73: 1 | E73: 1100 | F73: 1 | G73: 200 | I73: 1 | J73: 1 | K73: 175 | V73: =(D73*E73)+(F73*G73)+(H73*I73)+(J73*K73) -> 1475 | W73: =(V73*5%) -> 73.75 | X73: =SUM(V73+W73) -> 1548.75 | Y73: 51
A74: 42227 | C74: 431 | D74: 1 | E74: 1100 | F74: 1 | G74: 200 | I74: 1 | J74: 1 | K74: 175 | V74: =(D74*E74)+(F74*G74)+(H74*I74)+(J74*K74) -> 1475 | W74: =(V74*5%) -> 73.75 | X74: =SUM(V74+W74) -> 1548.75 | Y74: 51
A75: 42228 | C75: 431 | D75: 1 | E75: 1100 | F75: 1 | G75: 200 | I75: 1 | J75: 1 | K75: 175 | V75: =(D75*E75)+(F75*G75)+(H75*I75)+(J75*K75) -> 1475 | W75: =(V75*5%) -> 73.75 | X75: =SUM(V75+W75) -> 1548.75 | Y75: 51
A76: 42229 | C76: 431 | D76: 1 | E76: 1100 | F76: 1 | G76: 200 | I76: 1 | J76: 1 | K76: 175 | V76: =(D76*E76)+(F76*G76)+(H76*I76)+(J76*K76) -> 1475 | W76: =(V76*5%) -> 73.75 | X76: =SUM(V76+W76) -> 1548.75 | Y76: 51
A77: 42230 | C77: 431 | D77: 1 | E77: 1100 | F77: 1 | G77: 200 | I77: 1 | J77: 1 | K77: 175 | V77: =(D77*E77)+(F77*G77)+(H77*I77)+(J77*K77) -> 1475 | W77: =(V77*5%) -> 73.75 | X77: =SUM(V77+W77) -> 1548.75 | Y77: 51
A78: 42231 | C78: 431 | D78: 1 | E78: 1100 | F78: 1 | G78: 200 | I78: 1 | J78: 1 | K78: 175 | V78: =(D78*E78)+(F78*G78)+(H78*I78)+(J78*K78) -> 1475 | W78: =(V78*5%) -> 73.75 | X78: =SUM(V78+W78) -> 1548.75 | Y78: 51
A79: 42232 | C79: 431 | D79: 1 | E79: 1100 | F79: 1 | G79: 200 | I79: 1 | J79: 1 | K79: 175 | V79: =(D79*E79)+(F79*G79)+(H79*I79)+(J79*K79) -> 1475 | W79: =(V79*5%) -> 73.75 | X79: =SUM(V79+W79) -> 1548.75 | Y79: 51
A80: 42233 | C80: 431 | D80: 1 | E80: 1100 | F80: 1 | G80: 200 | I80: 1 | J80: 1 | K80: 175 | V80: =(D80*E80)+(F80*G80)+(H80*I80)+(J80*K80) -> 1475 | W80: =(V80*5%) -> 73.75 | X80: =SUM(V80+W80) -> 1548.75 | Y80: 51
A81: 42234 | C81: 431 | D81: 1 | E81: 1100 | F81: 1 | G81: 200 | I81: 1 | J81: 1 | K81: 175 | V81: =(D81*E81)+(F81*G81)+(H81*I81)+(J81*K81) -> 1475 | W81: =(V81*5%) -> 73.75 | X81: =SUM(V81+W81) -> 1548.75 | Y81: 51
A82: 42235 | C82: 431 | D82: 1 | E82: 1100 | F82: 1 | G82: 200 | I82: 1 | J82: 1 | K82: 175 | V82: =(D82*E82)+(F82*G82)+(H82*I82)+(J82*K82) -> 1475 | W82: =(V82*5%) -> 73.75 | X82: =SUM(V82+W82) -> 1548.75 | Y82: 51
A83: 42236 | C83: 431 | D83: 1 | E83: 1100 | F83: 1 | G83: 200 | I83: 1 | J83: 1 | K83: 175 | V83: =(D83*E83)+(F83*G83)+(H83*I83)+(J83*K83) -> 1475 | W83: =(V83*5%) -> 73.75 | X83: =SUM(V83+W83) -> 1548.75 | Y83: 51
A84: 42237 | C84: 431 | D84: 1 | E84: 1100 | F84: 1 | G84: 200 | I84: 1 | J84: 1 | K84: 175 | V84: =(D84*E84)+(F84*G84)+(H84*I84)+(J84*K84) -> 1475 | W84: =(V84*5%) -> 73.75 | X84: =SUM(V84+W84) -> 1548.75 | Y84: 51
... A92: 42245 | C92: 431 | D92: 1 | E92: 1100 | F92: 1 | G92: 200 | I92: 1 | J92: 1 | K92: 175 | V92: =(D92*E92)+(F92*G92)+(H92*I92)+(J92*K92) -> 1475 | W92: =(V92*5%) -> 73.75 | X92: =SUM(V92+W92) -> 1548.75 | Y92: 51
A93: 42246 | C93: 431 | E93: 1100 | G93: 200 | I93: 1 | K93: 175 | V93: =(D93*E93)+(F93*G93)+(H93*I93)+(J93*K93) -> 0 | W93: =(V93*5%) -> 0 | X93: =SUM(V93+W93) -> 0 | Y93: 51
A94: 42247 | C94: 431 | D94: 1 | E94: 1100 | F94: 1 | G94: 200 | I94: 1 | J94: 1 | K94: 175 | V94: =(D94*E94)+(F94*G94)+(H94*I94)+(J94*K94) -> 1475 | W94: =(V94*5%) -> 73.75 | X94: =SUM(V94+W94) -> 1548.75 | Y94: 51 | Z94: 34072.5
A95: 42248 | C95: 431 | D95: 1 | E95: 1100 | F95: 1 | G95: 200 | I95: 1 | J95: 1 | K95: 175 | V95: =(D95*E95)+(F95*G95)+(H95*I95)+(J95*K95) -> 1475 | W95: =(V95*5%) -> 73.75 | X95: =SUM(V95+W95) -> 1548.75 | Y95: 52
A96: 42249 | C96: 431 | D96: 1 | E96: 1100 | F96: 1 | G96: 200 | I96: 1 | J96: 1 | K96: 175 | V96: =(D96*E96)+(F96*G96)+(H96*I96)+(J96*K96) -> 1475 | W96: =(V96*5%) -> 73.75 | X96: =SUM(V96+W96) -> 1548.75 | Y96: 52
A97: 42250 | C97: 431 | D97: 1 | E97: 1100 | F97: 1 | G97: 200 | I97: 1 | J97: 1 | K97: 175 | V97: =(D97*E97)+(F97*G97)+(H97*I97)+(J97*K97) -> 1475 | W97: =(V97*5%) -> 73.75 | X97: =SUM(V97+W97) -> 1548.75 | Y97: 52
A98: 42255 | D98: 1 | E98: 1100 | F98: 1 | G98: 200 | I98: 1 | J98: 1 | K98: 175 | V98: =(D98*E98)+(F98*G98)+(H98*I98)+(J98*K98) -> 1475 | W98: =(V98*5%) -> 73.75 | X98: =SUM(V98+W98) -> 1548.75 | Y98: 52
A99: 42256 | D99: 1 | E99: 1100 | F99: 1 | G99: 200 | I99: 1 | J99: 1 | K99: 175 | V99: =(D99*E99)+(F99*G99)+(H99*I99)+(J99*K99) -> 1475 | W99: =(V99*5%) -> 73.75 | X99: =SUM(V99+W99) -> 1548.75 | Y99: 52
A100: 42257 | D100: 1 | E100: 1100 | F100: 1 | G100: 200 | I100: 1 | J100: 1 | K100: 175 | V100: =(D100*E100)+(F100*G100)+(H100*I100)+(J100*K100) -> 1475 | W100: =(V100*5%) -> 73.75 | X100: =SUM(V100+W100) -> 1548.75 | Y100: 52
A101: 42258 | D101: 1 | E101: 1100 | F101: 1 | G101: 200 | I101: 1 | J101: 1 | K101: 175 | V101: =(D101*E101)+(F101*G101)+(H101*I101)+(J101*K101) -> 1475 | W101: =(V101*5%) -> 73.75 | X101: =SUM(V101+W101) -> 1548.75 | Y101: 52
A102: 42259 | D102: 1 | E102: 1100 | F102: 1 | G102: 200 | I102: 1 | J102: 1 | K102: 175 | V102: =(D102*E102)+(F102*G102)+(H102*I102)+(J102*K102) -> 1475 | W102: =(V102*5%) -> 73.75 | X102: =SUM(V102+W102) -> 1548.75 | Y102: 52
A103: 42260 | D103: 1 | E103: 1100 | F103: 1 | G103: 200 | I103: 1 | J103: 1 | K103: 175 | V103: =(D103*E103)+(F103*G103)+(H103*I103)+(J103*K103) -> 1475 | W103: =(V103*5%) -> 73.75 | X103: =SUM(V103+W103) -> 1548.75 | Y103: 52
A104: 42261 | D104: 1 | E104: 1100 | F104: 1 | G104: 200 | I104: 1 | J104: 1 | K104: 175 | V104: =(D104*E104)+(F104*G104)+(H104*I104)+(J104*K104) -> 1475 | W104: =(V104*5%) -> 73.75 | X104: =SUM(V104+W104) -> 1548.75 | Y104: 52
A105: 42262 | D105: 1 | E105: 1100 | F105: 1 | G105: 200 | I105: 1 | J105: 1 | K105: 175 | V105: =(D105*E105)+(F105*G105)+(H105*I105)+(J105*K105) -> 1475 | W105: =(V105*5%) -> 73.75 | X105: =SUM(V105+W105) -> 1548.75 | Y105: 52
A106: 42263 | D106: 1 | E106: 1100 | F106: 1 | G106: 200 | I106: 1 | J106: 1 | K106: 175 | V106: =(D106*E106)+(F106*G106)+(H106*I106)+(J106*K106) -> 1475 | W106: =(V106*5%) -> 73.75 | X106: =SUM(V106+W106) -> 1548.75 | Y106: 52
A107: 42264 | D107: 0 | E107: 1100 | F107: 0 | G107: 200 | I107: 1 | J107: 0 | K107: 175 | V107: =(D107*E107)+(F107*G107)+(H107*I107)+(J107*K107) -> 0 | W107: =(V107*5%) -> 0 | X107: =SUM(V107+W107) -> 0 | Y107: 52
A108: 42265 | D108: 0 | E108: 1100 | F108: 0 | G108: 200 | I108: 1 | J108: 0 | K108: 175 | V108: =(D108*E108)+(F108*G108)+(H108*I108)+(J108*K108) -> 0 | W108: =(V108*5%) -> 0 | X108: =SUM(V108+W108) -> 0 | Y108: 52
A109: 42266 | D109: 0 | E109: 1100 | F109: 0 | G109: 200 | I109: 1 | J109: 0 | K109: 175 | V109: =(D109*E109)+(F109*G109)+(H109*I109)+(J109*K109) -> 0 | W109: =(V109*5%) -> 0 | X109: =SUM(V109+W109) -> 0 | Y109: 52
...

Sheet Vendor #12
A2: Vendor #12
A4: Date | B4: LEM # | C4: Straight Hours Charged (ea.) | D4: Manpower | E4: Admin | F4: Rate | G4: Lead | H4: Rate | I4: KM | J4: Rate | K4: Build Spreadsheet | L4: Rate | M4: Titles | N4: Rate | O4: Pad Prep $105 | P4: Rate | Q4: Land title spin $32 | R4: Total Hours Charged | S4: Equipment Detail | T4: Km's Charged | U4: Subtotal | V4: GST | W4: LEM Amount | X4: Affiliating Invoice | Y4: SUM OF ALL LEM'S (before GST)
Y5: =SUM(U6:U74) -> 18298
A6: 42145 | B6: 5581 | C6: 8 | F6: 75 | G6: 8 | H6: 105 | I6: 70 | J6: 1 | L6: 0 | N6: 0 | P6: 0 | R6: =C6*F6 -> 600 | T6: =I6*J6 -> 70 | U6: =(E6*F6)+(G6*H6)+(I6*J6)+(K6*L6) -> 910 | V6: =(U6*5%) -> 45.5 | W6: =SUM(U6+V6) -> 955.5 | X6: 1192
A7: 42146 | B7: 5582 | C7: 2 | F7: 75 | G7: 2 | H7: 105 | I7: 20 | J7: 1 | L7: 0 | N7: 0 | P7: 0 | Q7: =SUM(N7,L7,J7,F7) -> 76 | R7: =C7*F7 -> 150 | T7: =I7*J7 -> 20 | U7: =(E7*F7)+(G7*H7)+(I7*J7)+(K7*L7) -> 230 | V7: =(U7*5%) -> 11.5 | W7: =SUM(U7+V7) -> 241.5 | X7: 1192
A8: 42149 | B8: 5421 | C8: 2 | E8: 2 | F8: 75 | H8: 105 | I8: 0 | J8: 1 | K8: 0.5 | L8: 75 | N8: 0 | P8: 0 | Q8: =SUM(N8,L8,J8,F8) -> 151 | R8: =(C8*F8)+(K8*L8) -> 187.5 | T8: =I8*J8 -> 0 | U8: =(E8*F8)+(G8*H8)+(I8*J8)+(K8*L8) -> 187.5 | V8: =(U8*5%) -> 9.375 | W8: =SUM(U8+V8) -> 196.875 | X8: 1192
A9: 42149 | B9: 5584 | C9: 2 | F9: 75 | G9: 2 | H9: 105 | I9: 0 | J9: 1 | L9: 0 | N9: 0 | P9: 0 | Q9: =SUM(N9,L9,J9,F9) -> 76 | R9: =C9*F9 -> 150 | T9: =I9*J9 -> 0 | U9: =(E9*F9)+(G9*H9)+(I9*J9)+(K9*L9) -> 210 | V9: =(U9*5%) -> 10.5 | W9: =SUM(U9+V9) -> 220.5 | X9: 1192
A10: 42150 | B10: 5370 | C10: 6 | E10: 6 | F10: 75 | H10: 105 | I10: 0 | J10: 1 | L10: 75 | N10: 0 | P10: 0 | Q10: =SUM(N10,L10,J10,F10) -> 151 | R10: =(C10*F10)+(K10*L10) -> 450 | T10: =I10*J10 -> 0 | U10: =(E10*F10)+(G10*H10)+(I10*J10)+(K10*L10) -> 450 | V10: =(U10*5%) -> 22.5 | W10: =SUM(U10+V10) -> 472.5 | X10: 1192
A11: 42150 | B11: 5372 | C11: 1.5 | E11: 1.5 | F11: 75 | H11: 105 | I11: 0 | J11: 1 | L11: 75 | N11: 0 | P11: 0 | Q11: =SUM(N11,L11,J11,F11) -> 151 | R11: =(C11*F11)+(K11*L11) -> 112.5 | T11: =I11*J11 -> 0 | U11: =(E11*F11)+(G11*H11)+(I11*J11)+(K11*L11) -> 112.5 | V11: =(U11*5%) -> 5.625 | W11: =SUM(U11+V11) -> 118.125 | X11: 1192
A12: 42150 | B12: 5426 | C12: 3 | E12: 3 | F12: 75 | H12: 105 | J12: 1 | K12: 1.5 | L12: 75 | N12: 0 | P12: 0 | Q12: =SUM(N12,L12,J12,F12) -> 151 | R12: =(C12*F12)+(K12*L12) -> 337.5 | T12: =I12*J12 -> 0 | U12: =(E12*F12)+(G12*H12)+(I12*J12)+(K12*L12) -> 337.5 | V12: =(U12*5%) -> 16.875 | W12: =SUM(U12+V12) -> 354.375 | X12: 1192
A13: 42151 | B13: 5427 | C13: 6 | E13: 6 | F13: 75 | H13: 105 | J13: 1 | L13: 75 | N13: 0 | P13: 0 | Q13: =SUM(N13,L13,J13,F13) -> 151 | R13: =(C13*F13)+(K13*L13) -> 450 | T13: =I13*J13 -> 0 | U13: =(E13*F13)+(G13*H13)+(I13*J13)+(K13*L13) -> 450 | V13: =(U13*5%) -> 22.5 | W13: =SUM(U13+V13) -> 472.5 | X13: 1192
A14: 42151 | B14: 5590 | C14: 6 | F14: 75 | G14: 6 | H14: 105 | I14: 22 | J14: 1 | L14: 75 | N14: 0 | P14: 0 | Q14: =SUM(N14,L14,J14,F14) -> 151 | R14: =(C14*F14)+(K14*L14) -> 450 | T14: =I14*J14 -> 22 | U14: =(E14*F14)+(G14*H14)+(I14*J14)+(K14*L14) -> 652 | V14: =(U14*5%) -> 32.6 | W14: =SUM(U14+V14) -> 684.6 | X14: 1192
A15: 42152 | B15: 5375 | C15: 4 | E15: 4 | F15: 75 | H15: 105 | J15: 1 | L15: 75 | N15: 140 | P15: 0 | Q15: =SUM(N15,L15,J15,F15) -> 291 | R15: =(C15*F15)+(K15*L15) -> 300 | T15: =I15*J15 -> 0 | U15: =(E15*F15)+(G15*H15)+(I15*J15)+(K15*L15) -> 300 | V15: =(U15*5%) -> 15 | W15: =SUM(U15+V15) -> 315 | X15: 1192
A16: 42153 | B16: 5376 | C16: 1 | E16: 1 | F16: 75 | H16: 105 | J16: 1 | L16: 75 | N16: 140 | P16: 0 | Q16: =SUM(N16,L16,J16,F16) -> 291 | R16: =(C16*F16)+(K16*L16) -> 75 | T16: =I16*J16 -> 0 | U16: =(E16*F16)+(G16*H16)+(I16*J16)+(K16*L16) -> 75 | V16: =(U16*5%) -> 3.75 | W16: =SUM(U16+V16) -> 78.75 | X16: 1192
A17: 42156 | B17: 5378 | C17: 0.5 | E17: 0.5 | F17: 75 | H17: 105 | J17: 1 | L17: 75 | N17: 140 | P17: 0 | Q17: =SUM(N17,L17,J17,F17) -> 291 | R17: =(C17*F17)+(K17*L17) -> 37.5 | T17: =I17*J17 -> 0 | U17: =(E17*F17)+(G17*H17)+(I17*J17)+(K17*L17) -> 37.5 | V17: =(U17*5%) -> 1.875 | W17: =SUM(U17+V17) -> 39.375 | X17: 1192
A18: 42157 | B18: 5380 | C18: 2 | E18: 2 | F18: 75 | H18: 105 | J18: 1 | L18: 75 | N18: 140 | P18: 0 | Q18: =SUM(N18,L18,J18,F18) -> 291 | R18: =(C18*F18)+(K18*L18) -> 150 | T18: =I18*J18 -> 0 | U18: =(E18*F18)+(G18*H18)+(I18*J18)+(K18*L18) -> 150 | V18: =(U18*5%) -> 7.5 | W18: =SUM(U18+V18) -> 157.5 | X18: 1192
A19: 42160 | B19: 5383 | C19: 3 | E19: 3 | F19: 75 | H19: 105 | J19: 1 | L19: 75 | N19: 140 | P19: 0 | Q19: =SUM(N19,L19,J19,F19) -> 291 | R19: =(C19*F19)+(K19*L19) -> 225 | T19: =I19*J19 -> 0 | U19: =(E19*F19)+(G19*H19)+(I19*J19)+(K19*L19) -> 225 | V19: =(U19*5%) -> 11.25 | W19: =SUM(U19+V19) -> 236.25 | X19: 1192
A20: 42163 | B20: 5386 | C20: 2 | E20: 2 | F20: 75 | H20: 105 | J20: 1 | L20: 75 | N20: 140 | P20: 0 | Q20: =SUM(N20,L20,J20,F20) -> 291 | R20: =(C20*F20)+(K20*L20) -> 150 | T20: =I20*J20 -> 0 | U20: =(E20*F20)+(G20*H20)+(I20*J20)+(K20*L20) -> 150 | V20: =(U20*5%) -> 7.5 | W20: =SUM(U20+V20) -> 157.5 | X20: 1192
A21: 42163 | B21: 5604 | C21: 5 | F21: 75 | G21: 5 | H21: 105 | I21: 123 | J21: 1 | L21: 75 | N21: 140 | P21: 0 | Q21: =SUM(N21,L21,J21,F21) -> 291 | R21: =(C21*F21)+(K21*L21) -> 375 | T21: =I21*J21 -> 123 | U21: =(E21*F21)+(G21*H21)+(I21*J21)+(K21*L21) -> 648 | V21: =(U21*5%) -> 32.4 | W21: =SUM(U21+V21) -> 680.4 | X21: 1192
A22: 42164 | B22: 5606 | C22: 9 | F22: 75 | G22: 9 | H22: 105 | I22: 167 | J22: 1 | L22: 75 | N22: 140 | P22: 0 | Q22: =SUM(N22,L22,J22,F22) -> 291 | R22: =(C22*F22)+(K22*L22) -> 675 | T22: =I22*J22 -> 167 | U22: =(E22*F22)+(G22*H22)+(I22*J22)+(K22*L22) -> 1112 | V22: =(U22*5%) -> 55.6 | W22: =SUM(U22+V22) -> 1167.6 | X22: 1192
A23: 42165 | B23: 5608 | C23: 4 | F23: 75 | G23: 4 | H23: 105 | I23: 93 | J23: 1 | L23: 75 | N23: 140 | U23: =(E23*F23)+(G23*H23)+(I23*J23)+(K23*L23)+(M23*N23) -> 513 | V23: =(U23*5%) -> 25.65 | W23: =SUM(U23+V23) -> 538.65 | X23: 1205
A24: 42166 | B24: 5390 | C24: 4 | E24: 4 | F24: 75 | H24: 105 | J24: 1 | L24: 75 | N24: 140 | P24: 0 | Q24: =SUM(N24,L24,J24,F24) -> 291 | R24: =(C24*F24)+(K24*L24) -> 300 | T24: =I24*J24 -> 0 | U24: =(E24*F24)+(G24*H24)+(I24*J24)+(K24*L24) -> 300 | V24: =(U24*5%) -> 15 | W24: =SUM(U24+V24) -> 315 | X24: 1194
A25: 42167 | B25: 5387 | C25: 4 | E25: 1 | F25: 75 | H25: 105 | J25: 1 | K25: 3 | L25: 75 | N25: 140 | P25: 0 | Q25: =SUM(N25,L25,J25,F25) -> 291 | R25: =(C25*F25)+(K25*L25) -> 525 | T25: =I25*J25 -> 0 | U25: =(E25*F25)+(G25*H25)+(I25*J25)+(K25*L25) -> 300 | V25: =(U25*5%) -> 15 | W25: =SUM(U25+V25) -> 315 | X25: 1194
A26: 42167 | B26: 5444 | C26: 1 | E26: 1 | F26: 75 | H26: 105 | J26: 1 | L26: 75 | N26: 140 | P26: 0 | Q26: =SUM(N26,L26,J26,F26) -> 291 | R26: =(C26*F26)+(K26*L26) -> 75 | T26: =I26*J26 -> 0 | U26: =(E26*F26)+(G26*H26)+(I26*J26)+(K26*L26) -> 75 | V26: =(U26*5%) -> 3.75 | W26: =SUM(U26+V26) -> 78.75 | X26: 1194
A27: 42167 | B27: 5613 | C27: 1.5 | F27: 75 | G27: 1.5 | H27: 105 | I27: 11 | J27: 1 | L27: 75 | N27: 140 | U27: =(E27*F27)+(G27*H27)+(I27*J27)+(K27*L27)+(M27*N27) -> 168.5 | V27: =(U27*5%) -> 8.425 | W27: =SUM(U27+V27) -> 176.925 | X27: 1205
A28: 42170 | B28: 5445 | C28: 2 | E28: 1 | F28: 75 | H28: 105 | J28: 1 | K28: 1 | L28: 75 | N28: 140 | P28: 0 | Q28: =SUM(N28,L28,J28,F28) -> 291 | R28: =(C28*F28)+(K28*L28) -> 225 | T28: =I28*J28 -> 0 | U28: =(E28*F28)+(G28*H28)+(I28*J28)+(K28*L28) -> 150 | V28: =(U28*5%) -> 7.5 | W28: =SUM(U28+V28) -> 157.5 | X28: 1194
A29: 42174 | B29: 5393 | C29: 2 | E29: 2 | F29: 75 | H29: 105 | J29: 1 | L29: 75 | M29: 1 | N29: 140 | U29: =(E29*F29)+(G29*H29)+(I29*J29)+(K29*L29)+(M29*N29) -> 290 | V29: =(U29*5%) -> 14.5 | W29: =SUM(U29+V29) -> 304.5 | X29: 1204
A30: 42177 | B30: 5397 | E30: 3 | F30: 75 | H30: 105 | J30: 1 | L30: 75 | N30: 140 | U30: =(E30*F30)+(G30*H30)+(I30*J30)+(K30*L30)+(M30*N30)+(105*O30) -> 225 | V30: =(U30*5%) -> 11.25 | W30: =SUM(U30+V30) -> 236.25 | X30: 1204
A31: 42177 | B31: 5615 | C31: 2 | F31: 75 | G31: 2 | H31: 105 | I31: 28 | J31: 1 | L31: 75 | N31: 140 | U31: =(E31*F31)+(G31*H31)+(I31*J31)+(K31*L31)+(M31*N31) -> 238 | V31: =(U31*5%) -> 11.9 | W31: =SUM(U31+V31) -> 249.9 | X31: 1205
A32: 42178 | B32: 5399 | C32: 2 | E32: 1 | F32: 75 | H32: 105 | J32: 1 | K32: 1 | L32: 75 | N32: 140 | P32: 0 | Q32: =SUM(N32,L32,J32,F32) -> 291 | R32: =(C32*F32)+(K32*L32) -> 225 | T32: =I32*J32 -> 0 | U32: =(E32*F32)+(G32*H32)+(I32*J32)+(K32*L32)+(M32*N32) -> 150 | V32: =(U32*5%) -> 7.5 | W32: =SUM(U32+V32) -> 157.5 | X32: 1209
A33: 42178 | B33: 5617 | C33: 2 | F33: 75 | G33: 2 | H33: 105 | J33: 1 | L33: 75 | N33: 140 | U33: =(E33*F33)+(G33*H33)+(I33*J33)+(K33*L33)+(M33*N33) -> 210 | V33: =(U33*5%) -> 10.5 | W33: =SUM(U33+V33) -> 220.5 | X33: 1205
A34: 42179 | B34: 5620 | C34: 2 | F34: 75 | G34: 2 | H34: 105 | I34: 11 | J34: 1 | L34: 75 | N34: 140 | U34: =(E34*F34)+(G34*H34)+(I34*J34)+(K34*L34)+(M34*N34) -> 221 | V34: =(U34*5%) -> 11.05 | W34: =SUM(U34+V34) -> 232.05 | X34: 1205
A35: 42180 | B35: 5622 | C35: 2 | F35: 75 | G35: 2 | H35: 105 | J35: 1 | L35: 75 | N35: 140 | U35: =(E35*F35)+(G35*H35)+(I35*J35)+(K35*L35)+(M35*N35) -> 210 | V35: =(U35*5%) -> 10.5 | W35: =SUM(U35+V35) -> 220.5 | X35: 1205
A36: 42180 | B36: 5701 | C36: 6 | E36: 6 | F36: 75 | H36: 105 | J36: 1 | L36: 75 | N36: 140 | U36: =(E36*F36)+(G36*H36)+(I36*J36)+(K36*L36)+(M36*N36) -> 450 | V36: =(U36*5%) -> 22.5 | W36: =SUM(U36+V36) -> 472.5 | X36: 1204
A37: 42181 | B37: 5626 | C37: 2 | F37: 75 | G37: 2 | H37: 105 | I37: 22 | J37: 1 | L37: 75 | N37: 140 | U37: =(E37*F37)+(G37*H37)+(I37*J37)+(K37*L37)+(M37*N37) -> 232 | V37: =(U37*5%) -> 11.6 | W37: =SUM(U37+V37) -> 243.6 | X37: 1205
A38: 42181 | B38: 5702 | C38: 3 | E38: 3 | F38: 75 | H38: 105 | J38: 1 | L38: 75 | N38: 140 | U38: =(E38*F38)+(G38*H38)+(I38*J38)+(K38*L38)+(M38*N38) -> 225 | V38: =(U38*5%) -> 11.25 | W38: =SUM(U38+V38) -> 236.25 | X38: 1204
A39: 42184 | B39: 5627 | C39: 8 | F39: 75 | G39: 8 | H39: 105 | I39: 56 | J39: 1 | L39: 75 | N39: 140 | U39: =(E39*F39)+(G39*H39)+(I39*J39)+(K39*L39)+(M39*N39) -> 896 | V39: =(U39*5%) -> 44.8 | W39: =SUM(U39+V39) -> 940.8 | X39: 1205
A40: 42184 | B40: 5704 | C40: 4 | E40: 4 | F40: 75 | H40: 105 | J40: 1 | L40: 75 | N40: 140 | U40: =(E40*F40)+(G40*H40)+(I40*J40)+(K40*L40)+(M40*N40) -> 300 | V40: =(U40*5%) -> 15 | W40: =SUM(U40+V40) -> 315 | X40: 1204
A41: 42185 | B41: 5629 | C41: 2 | F41: 75 | G41: 2 | H41: 105 | I41: 10 | J41: 1 | L41: 75 | N41: 140 | U41: =(E41*F41)+(G41*H41)+(I41*J41)+(K41*L41)+(M41*N41) -> 220 | V41: =(U41*5%) -> 11 | W41: =SUM(U41+V41) -> 231 | X41: 1205
A42: 42191 | B42: 5631 | C42: 4 | F42: 75 | G42: 4 | H42: 105 | I42: 32 | J42: 1 | L42: 75 | N42: 140 | U42: =(E42*F42)+(G42*H42)+(I42*J42)+(K42*L42)+(M42*N42) -> 452 | V42: =(U42*5%) -> 22.6 | W42: =SUM(U42+V42) -> 474.6 | X42: 1205
A43: 42192 | B43: 5633 | C43: 2 | F43: 75 | G43: 2 | H43: 105 | I43: 14 | J43: 1 | L43: 75 | N43: 140 | U43: =(E43*F43)+(G43*H43)+(I43*J43)+(K43*L43)+(M43*N43) -> 224 | V43: =(U43*5%) -> 11.2 | W43: =SUM(U43+V43) -> 235.2 | X43: 1219
A44: 42193 | B44: 5634 | C44: 2 | F44: 75 | G44: 2 | H44: 105 | I44: 0 | J44: 1 | L44: 75 | N44: 140 | U44: =(E44*F44)+(G44*H44)+(I44*J44)+(K44*L44)+(M44*N44) -> 210 | V44: =(U44*5%) -> 10.5 | W44: =SUM(U44+V44) -> 220.5 | X44: 1219
A45: 42194 | B45: 5635 | C45: 3 | F45: 75 | G45: 3 | H45: 105 | I45: 23 | J45: 1 | L45: 75 | N45: 140 | U45: =(E45*F45)+(G45*H45)+(I45*J45)+(K45*L45)+(M45*N45) -> 338 | V45: =(U45*5%) -> 16.9 | W45: =SUM(U45+V45) -> 354.9 | X45: 1219
A46: 42194 | B46: 7055 | C46: =1.5+1.5 -> 3 | F46: 75 | G46: =1.5+1.5 -> 3 | H46: 105 | I46: 26 | J46: 1 | L46: 75 | N46: 140 | U46: =(E46*F46)+(G46*H46)+(I46*J46)+(K46*L46)+(M46*N46) -> 341 | V46: =(U46*5%) -> 17.05 | W46: =SUM(U46+V46) -> 358.05 | X46: 1232
A47: 42198 | B47: 7058 | C47: 3 | F47: 75 | G47: 3 | H47: 105 | J47: 1 | L47: 75 | N47: 140 | U47: =(E47*F47)+(G47*H47)+(I47*J47)+(K47*L47)+(M47*N47) -> 315 | V47: =(U47*5%) -> 15.75 | W47: =SUM(U47+V47) -> 330.75 | X47: 1232
A48: 42200 | B48: 7063 | C48: 2 | F48: 75 | G48: 2 | H48: 105 | I48: 20 | J48: 1 | L48: 75 | N48: 140 | U48: =(E48*F48)+(G48*H48)+(I48*J48)+(K48*L48)+(M48*N48) -> 230 | V48: =(U48*5%) -> 11.5 | W48: =SUM(U48+V48) -> 241.5 | X48: 1232
A49: 42201 | B49: 7066 | C49: 1 | F49: 75 | G49: 1 | H49: 105 | J49: 1 | L49: 75 | N49: 140 | U49: =(E49*F49)+(G49*H49)+(I49*J49)+(K49*L49)+(M49*N49) -> 105 | V49: =(U49*5%) -> 5.25 | W49: =SUM(U49+V49) -> 110.25 | X49: 1232
A50: 42205 | B50: 7075 | C50: 2 | F50: 75 | G50: 2.5 | H50: 105 | I50: 10 | J50: 1 | L50: 75 | N50: 140 | U50: =(E50*F50)+(G50*H50)+(I50*J50)+(K50*L50)+(M50*N50) -> 272.5 | V50: =(U50*5%) -> 13.625 | W50: =SUM(U50+V50) -> 286.125 | X50: 1232
A51: 42206 | B51: 7078 | F51: 75 | G51: 3 | H51: 105 | I51: 63 | J51: 1 | L51: 75 | N51: 140 | O51: 1 | S51: 1 | T51: 63 | U51: =(E51*F51)+(G51*H51)+(I51*J51)+(K51*L51)+(M51*N51)+(105*O51) -> 483 | V51: =(U51*5%) -> 24.15 | W51: =SUM(U51+V51) -> 507.15 | X51: 1232
A52: 42228 | B52: 7110 | E52: 1 | F52: 75 | H52: 105 | J52: 1 | L52: 75 | N52: 140 | U52: =(E52*F52)+(G52*H52)+(I52*J52)+(K52*L52)+(M52*N52)+(105*O52) -> 75 | V52: =(U52*5%) -> 3.75 | W52: =SUM(U52+V52) -> 78.75 | X52: 1232
A53: 42207 | B53: 7081 | C53: 2 | F53: 75 | G53: 1.5 | H53: 105 | J53: 1 | L53: 75 | N53: 140 | U53: =(E53*F53)+(G53*H53)+(I53*J53)+(K53*L53)+(M53*N53) -> 157.5 | V53: =(U53*5%) -> 7.875 | W53: =SUM(U53+V53) -> 165.375 | X53: 1232
A54: 42208 | B54: 7083 | C54: 1 | F54: 75 | G54: 1 | H54: 105 | I54: 10 | J54: 1 | L54: 75 | N54: 140 | U54: =(E54*F54)+(G54*H54)+(I54*J54)+(K54*L54)+(M54*N54) -> 115 | V54: =(U54*5%) -> 5.75 | W54: =SUM(U54+V54) -> 120.75 | X54: 1232
A55: 42212 | B55: 7089 | F55: 75 | G55: 2 | H55: 105 | I55: 34 | J55: 1 | L55: 75 | N55: 140 | U55: =(E55*F55)+(G55*H55)+(I55*J55)+(K55*L55)+(M55*N55) -> 244 | V55: =(U55*5%) -> 12.2 | W55: =SUM(U55+V55) -> 256.2 | X55: 1232
A56: 42214 | B56: 7098 | F56: 75 | H56: 105 | I56: 34 | J56: 1 | L56: 75 | N56: 140 | O56: 3 | T56: 34 | U56: =(E56*F56)+(G56*H56)+(I56*J56)+(K56*L56)+(M56*N56)+(105*O56) -> 349 | V56: =(U56*5%) -> 17.45 | W56: =SUM(U56+V56) -> 366.45 | X56: 1232
A57: 42215 | B57: 7003 | C57: 4 | F57: 75 | H57: 105 | J57: 1 | K57: 4 | L57: 75 | N57: 140 | U57: =(E57*F57)+(G57*H57)+(I57*J57)+(K57*L57)+(M57*N57)+(105*O57) -> 300 | V57: =(U57*5%) -> 15 | W57: =SUM(U57+V57) -> 315 | X57: 1219
A58: 42215 | B58: 7135 | F58: 75 | G58: 2 | H58: 105 | J58: 1 | L58: 75 | N58: 140 | U58: =(E58*F58)+(G58*H58)+(I58*J58)+(K58*L58)+(M58*N58)+(105*O58) -> 210 | V58: =(U58*5%) -> 10.5 | W58: =SUM(U58+V58) -> 220.5 | X58: 1235
A59: 42216 | B59: 7005 | C59: 4 | F59: 75 | H59: 105 | J59: 1 | K59: 4 | L59: 75 | N59: 140 | U59: =(E59*F59)+(G59*H59)+(I59*J59)+(K59*L59)+(M59*N59)+(105*O59) -> 300 | V59: =(U59*5%) -> 15 | W59: =SUM(U59+V59) -> 315 | X59: 1219
A60: 42216 | B60: 7136 | F60: 75 | G60: 3 | H60: 105 | I60: 22 | J60: 1 | L60: 75 | N60: 140 | U60: =(E60*F60)+(G60*H60)+(I60*J60)+(K60*L60)+(M60*N60)+(105*O60) -> 337 | V60: =(U60*5%) -> 16.85 | W60: =SUM(U60+V60) -> 353.85 | X60: 1235
A61: 42220 | B61: 7139 | F61: 75 | G61: 2 | H61: 105 | I61: 17 | J61: 1 | L61: 75 | N61: 140 | U61: =(E61*F61)+(G61*H61)+(I61*J61)+(K61*L61)+(M61*N61)+(105*O61) -> 227 | V61: =(U61*5%) -> 11.35 | W61: =SUM(U61+V61) -> 238.35 | X61: 1235
A62: 42221 | B62: 7144 | F62: 75 | G62: 4 | H62: 105 | I62: 43 | J62: 1 | L62: 75 | N62: 140 | U62: =(E62*F62)+(G62*H62)+(I62*J62)+(K62*L62)+(M62*N62)+(105*O62)+(32*Q62) -> 463 | V62: =(U62*5%) -> 23.15 | W62: =SUM(U62+V62) -> 486.15 | X62: 1235
A63: 42226 | B63: 5481 | F63: 75 | H63: 105 | J63: 1 | L63: 75 | N63: 140 | Q63: 1 | U63: =(E63*F63)+(G63*H63)+(I63*J63)+(K63*L63)+(M63*N63)+(105*O63)+(32*Q63) -> 32 | V63: =(U63*5%) -> 1.6 | W63: =SUM(U63+V63) -> 33.6 | X63: 1232
A64: 42226 | B64: 7027 | E64: 1 | F64: 75 | H64: 105 | J64: 1 | L64: 75 | N64: 140 | U64: =(E64*F64)+(G64*H64)+(I64*J64)+(K64*L64)+(M64*N64)+(105*O64)+(32*Q64) -> 75 | V64: =(U64*5%) -> 3.75 | W64: =SUM(U64+V64) -> 78.75 | X64: 1232
A65: 42264 | B65: 7314 | F65: 75 | G65: 1 | H65: 105 | J65: 1 | L65: 75 | N65: 140 | U65: =(E65*F65)+(G65*H65)+(I65*J65)+(K65*L65)+(M65*N65)+(105*O65)+(32*Q65) -> 105 | V65: =(U65*5%) -> 5.25 | W65: =SUM(U65+V65) -> 110.25 | X65: 1271
A66: 42298 | B66: 7558 | F66: 75 | H66: 105 | J66: 1 | K66: 7 | L66: 75 | N66: 140 | U66: =(E66*F66)+(G66*H66)+(I66*J66)+(K66*L66)+(M66*N66)+(105*O66) -> 525 | V66: =(U66*5%) -> 26.25 | W66: =SUM(U66+V66) -> 551.25 | X66: 1301
A67: 42299 | B67: 7561 | F67: 75 | H67: 105 | J67: 1 | K67: 2 | L67: 75 | N67: 140 | U67: =(E67*F67)+(G67*H67)+(I67*J67)+(K67*L67)+(M67*N67)+(105*O67) -> 150 | V67: =(U67*5%) -> 7.5 | W67: =SUM(U67+V67) -> 157.5 | X67: 1301
A68: 42304 | B68: 7615 | F68: 75 | G68: 0.5 | H68: 105 | J68: 1 | L68: 75 | N68: 140 | U68: =(E68*F68)+(G68*H68)+(I68*J68)+(K68*L68)+(M68*N68)+(105*O68) -> 52.5 | V68: =(U68*5%) -> 2.625 | W68: =SUM(U68+V68) -> 55.125
F69: 75 | H69: 105 | J69: 1 | L69: 75 | N69: 140 | U69: =(E69*F69)+(G69*H69)+(I69*J69)+(K69*L69)+(M69*N69)+(105*O69) -> 0 | V69: =(U69*5%) -> 0 | W69: =SUM(U69+V69) -> 0
F70: 75 | H70: 105 | J70: 1 | L70: 75 | N70: 140 | U70: =(E70*F70)+(G70*H70)+(I70*J70)+(K70*L70)+(M70*N70)+(105*O70) -> 0 | V70: =(U70*5%) -> 0 | W70: =SUM(U70+V70) -> 0
F71: 75 | H71: 105 | J71: 1 | L71: 75 | N71: 140 | U71: =(E71*F71)+(G71*H71)+(I71*J71)+(K71*L71)+(M71*N71)+(105*O71) -> 0 | V71: =(U71*5%) -> 0 | W71: =SUM(U71+V71) -> 0
F72: 75 | H72: 105 | J72: 1 | L72: 75 | N72: 140 | U72: =(E72*F72)+(G72*H72)+(I72*J72)+(K72*L72)+(M72*N72)+(105*O72) -> 0 | V72: =(U72*5%) -> 0 | W72: =SUM(U72+V72) -> 0
F73: 75 | H73: 105 | J73: 1 | L73: 75 | N73: 140 | U73: =(E73*F73)+(G73*H73)+(I73*J73)+(K73*L73)+(M73*N73)+(105*O73) -> 0 | V73: =(U73*5%) -> 0 | W73: =SUM(U73+V73) -> 0
F74: 75 | H74: 105 | J74: 1 | L74: 75 | N74: 140 | U74: =(E74*F74)+(G74*H74)+(I74*J74)+(K74*L74)+(M74*N74)+(105*O74) -> 0 | V74: =(U74*5%) -> 0 | W74: =SUM(U74+V74) -> 0
F75: 75 | H75: 105 | J75: 1 | L75: 75 | N75: 140 | U75: =(E75*F75)+(G75*H75)+(I75*J75)+(K75*L75)+(M75*N75)+(105*O75) -> 0 | V75: =(U75*5%) -> 0 | W75: =SUM(U75+V75) -> 0
F76: 75 | H76: 105 | J76: 1 | L76: 75 | N76: 140 | U76: =(E76*F76)+(G76*H76)+(I76*J76)+(K76*L76)+(M76*N76)+(105*O76) -> 0 | V76: =(U76*5%) -> 0 | W76: =SUM(U76+V76) -> 0
F77: 75 | H77: 105 | J77: 1 | L77: 75 | N77: 140 | U77: =(E77*F77)+(G77*H77)+(I77*J77)+(K77*L77)+(M77*N77)+(105*O77) -> 0 | V77: =(U77*5%) -> 0 | W77: =SUM(U77+V77) -> 0
F78: 75 | H78: 105 | J78: 1 | L78: 75 | N78: 140 | U78: =(E78*F78)+(G78*H78)+(I78*J78)+(K78*L78)+(M78*N78)+(105*O78) -> 0 | V78: =(U78*5%) -> 0 | W78: =SUM(U78+V78) -> 0
F79: 75 | H79: 105 | J79: 1 | L79: 75 | N79: 140 | U79: =(E79*F79)+(G79*H79)+(I79*J79)+(K79*L79)+(M79*N79)+(105*O79) -> 0 | V79: =(U79*5%) -> 0 | W79: =SUM(U79+V79) -> 0
F80: 75 | H80: 105 | J80: 1 | L80: 75 | N80: 140 | U80: =(E80*F80)+(G80*H80)+(I80*J80)+(K80*L80)+(M80*N80)+(105*O80) -> 0 | V80: =(U80*5%) -> 0 | W80: =SUM(U80+V80) -> 0
... F82: 75 | H82: 105 | J82: 1 | L82: 75 | N82: 140 | U82: =(E82*F82)+(G82*H82)+(I82*J82)+(K82*L82)+(M82*N82)+(105*O82) -> 0 | V82: =(U82*5%) -> 0 | W82: =SUM(U82+V82) -> 0

Sheet Vendor #13
A2: Vendor #13
A4: Date | B4: Ticket Number | C4: Technician | D4: day Rate | E4: Blair | F4: Hr Rate | G4: Vehicle | H4: Rate | I4: KM >150 | J4: Rate | K4: Equipment package | L4: rate | M4: ATV | N4: Rate | O4: LOA | P4: Rate | Q4: KM's | R4: Rate | S4: 24" 11.1 | T4: 16" 9.5 | U4: 16" 7.1 | V4: Films | W4: Subtotal | X4: GST | Y4: LEM Amount | Z4: Affiliating Invoice | AA4: SUM OF ALL LEM'S (before GST)
AA5: =SUM(W6:W208) -> 131560.7
A6: 42163 | C6: 1 | D6: 1000 | F6: 125 | G6: 1 | H6: 150 | J6: 0.9 | K6: 1 | L6: 50 | M6: 1 | N6: 150 | W6: =(G6*H6)+(I6*J6)+(M6*N6)+(K6*L6)+(C6*D6)+(E6*F6) -> 1350 | X6: =(W6*5%) -> 67.5 | Y6: =SUM(W6+X6) -> 1417.5 | Z6: 5420
A7: 42164 | C7: 1 | D7: 1000 | F7: 125 | G7: 1 | H7: 150 | J7: 0.9 | K7: 1 | L7: 50 | M7: 1 | N7: 150 | W7: =(G7*H7)+(I7*J7)+(M7*N7)+(K7*L7)+(C7*D7)+(E7*F7) -> 1350 | X7: =(W7*5%) -> 67.5 | Y7: =SUM(W7+X7) -> 1417.5 | Z7: 5420
A8: 42165 | C8: 1 | D8: 1000 | F8: 125 | G8: 1 | H8: 150 | J8: 0.9 | K8: 1 | L8: 50 | M8: 1 | N8: 150 | W8: =(G8*H8)+(I8*J8)+(M8*N8)+(K8*L8)+(C8*D8)+(E8*F8) -> 1350 | X8: =(W8*5%) -> 67.5 | Y8: =SUM(W8+X8) -> 1417.5 | Z8: 5420
A9: 42170 | C9: 1 | D9: 1000 | F9: 125 | G9: 1 | H9: 150 | J9: 0.9 | K9: 1 | L9: 50 | M9: 1 | N9: 150 | W9: =(G9*H9)+(I9*J9)+(M9*N9)+(K9*L9)+(C9*D9)+(E9*F9) -> 1350 | X9: =(W9*5%) -> 67.5 | Y9: =SUM(W9+X9) -> 1417.5 | Z9: 5420
A10: 42171 | C10: 1 | D10: 1000 | F10: 125 | G10: 1 | H10: 150 | J10: 0.9 | K10: 1 | L10: 50 | M10: 1 | N10: 150 | W10: =(G10*H10)+(I10*J10)+(M10*N10)+(K10*L10)+(C10*D10)+(E10*F10) -> 1350 | X10: =(W10*5%) -> 67.5 | Y10: =SUM(W10+X10) -> 1417.5 | Z10: 5420
A11: 42172 | C11: 1 | D11: 1000 | F11: 125 | G11: 1 | H11: 150 | J11: 0.9 | K11: 1 | L11: 50 | M11: 1 | N11: 150 | W11: =(G11*H11)+(I11*J11)+(M11*N11)+(K11*L11)+(C11*D11)+(E11*F11) -> 1350 | X11: =(W11*5%) -> 67.5 | Y11: =SUM(W11+X11) -> 1417.5 | Z11: 5420
A12: 42173 | C12: 0.5 | D12: 1000 | F12: 125 | G12: 0.5 | H12: 150 | J12: 0.9 | K12: 0.5 | L12: 50 | M12: 0.5 | N12: 150 | W12: =(G12*H12)+(I12*J12)+(M12*N12)+(K12*L12)+(C12*D12)+(E12*F12) -> 675 | X12: =(W12*5%) -> 33.75 | Y12: =SUM(W12+X12) -> 708.75 | Z12: 5420
A13: 42174 | C13: 1 | D13: 1000 | F13: 125 | G13: 1 | H13: 150 | I13: 30 | J13: 0.9 | K13: 1 | L13: 50 | M13: 1 | N13: 150 | W13: =(G13*H13)+(I13*J13)+(M13*N13)+(K13*L13)+(C13*D13)+(E13*F13) -> 1377 | X13: =(W13*5%) -> 68.85 | Y13: =SUM(W13+X13) -> 1445.85 | Z13: 5420
A14: 42175 | C14: 1 | D14: 1000 | F14: 125 | G14: 1 | H14: 150 | I14: 30 | J14: 0.9 | K14: 1 | L14: 50 | M14: 1 | N14: 150 | W14: =(G14*H14)+(I14*J14)+(M14*N14)+(K14*L14)+(C14*D14)+(E14*F14) -> 1377 | X14: =(W14*5%) -> 68.85 | Y14: =SUM(W14+X14) -> 1445.85 | Z14: 5420
A15: 42177 | C15: 1 | D15: 1000 | F15: 125 | G15: 1 | H15: 150 | J15: 0.9 | K15: 1 | L15: 50 | M15: 1 | N15: 150 | W15: =(G15*H15)+(I15*J15)+(M15*N15)+(K15*L15)+(C15*D15)+(E15*F15) -> 1350 | X15: =(W15*5%) -> 67.5 | Y15: =SUM(W15+X15) -> 1417.5 | Z15: 5420
A16: 42178 | C16: 1 | D16: 1000 | F16: 125 | G16: 1 | H16: 150 | I16: 20 | J16: 0.9 | K16: 1 | L16: 50 | M16: 1 | N16: 150 | W16: =(G16*H16)+(I16*J16)+(M16*N16)+(K16*L16)+(C16*D16)+(E16*F16) -> 1368 | X16: =(W16*5%) -> 68.4 | Y16: =SUM(W16+X16) -> 1436.4 | Z16: 5420
A17: 42179 | C17: 1 | D17: 1000 | F17: 125 | G17: 1 | H17: 150 | I17: 7 | J17: 0.9 | K17: 1 | L17: 50 | M17: 1 | N17: 150 | W17: =(G17*H17)+(I17*J17)+(M17*N17)+(K17*L17)+(C17*D17)+(E17*F17) -> 1356.3 | X17: =(W17*5%) -> 67.815 | Y17: =SUM(W17+X17) -> 1424.115 | Z17: 5420
A18: 42180 | C18: 1 | D18: 1000 | F18: 125 | G18: 1 | H18: 150 | I18: 67 | J18: 0.9 | K18: 1 | L18: 50 | M18: 1 | N18: 150 | W18: =(G18*H18)+(I18*J18)+(M18*N18)+(K18*L18)+(C18*D18)+(E18*F18) -> 1410.3 | X18: =(W18*5%) -> 70.515 | Y18: =SUM(W18+X18) -> 1480.815 | Z18: 5420
A19: 42181 | C19: 1 | D19: 1000 | F19: 125 | G19: 1 | H19: 150 | I19: 10 | J19: 0.9 | K19: 1 | L19: 50 | M19: 1 | N19: 150 | W19: =(G19*H19)+(I19*J19)+(M19*N19)+(K19*L19)+(C19*D19)+(E19*F19) -> 1359 | X19: =(W19*5%) -> 67.95 | Y19: =SUM(W19+X19) -> 1426.95 | Z19: 5420
A20: 42182 | C20: 1 | D20: 1000 | F20: 125 | G20: 1 | H20: 150 | I20: 36 | J20: 0.9 | K20: 1 | L20: 50 | M20: 1 | N20: 150 | W20: =(G20*H20)+(I20*J20)+(M20*N20)+(K20*L20)+(C20*D20)+(E20*F20) -> 1382.4 | X20: =(W20*5%) -> 69.12 | Y20: =SUM(W20+X20) -> 1451.52 | Z20: 5420
A21: 42184 | C21: 1 | D21: 1000 | F21: 125 | G21: 1 | H21: 150 | I21: 15 | J21: 0.9 | K21: 1 | L21: 50 | M21: 1 | N21: 150 | W21: =(G21*H21)+(I21*J21)+(M21*N21)+(K21*L21)+(C21*D21)+(E21*F21) -> 1363.5 | X21: =(W21*5%) -> 68.175 | Y21: =SUM(W21+X21) -> 1431.675 | Z21: 5420
A22: 42185 | C22: 1 | D22: 1000 | F22: 125 | G22: 1 | H22: 150 | J22: 0.9 | K22: 1 | L22: 50 | M22: 1 | N22: 150 | W22: =(G22*H22)+(I22*J22)+(M22*N22)+(K22*L22)+(C22*D22)+(E22*F22) -> 1350 | X22: =(W22*5%) -> 67.5 | Y22: =SUM(W22+X22) -> 1417.5 | Z22: 5420
A23: 42186 | C23: 1 | D23: 1000 | F23: 125 | G23: 1 | H23: 150 | J23: 0.9 | K23: 1 | L23: 50 | M23: 1 | N23: 150 | W23: =(G23*H23)+(I23*J23)+(M23*N23)+(K23*L23)+(C23*D23)+(E23*F23) -> 1350 | X23: =(W23*5%) -> 67.5 | Y23: =SUM(W23+X23) -> 1417.5 | Z23: 5459
A24: 42187 | C24: 1 | D24: 1000 | F24: 125 | G24: 1 | H24: 150 | I24: 24 | J24: 0.9 | K24: 1 | L24: 50 | M24: 1 | N24: 150 | W24: =(G24*H24)+(I24*J24)+(M24*N24)+(K24*L24)+(C24*D24)+(E24*F24) -> 1371.6 | X24: =(W24*5%) -> 68.58 | Y24: =SUM(W24+X24) -> 1440.18 | Z24: 5459
A25: 42188 | C25: 1 | D25: 1000 | F25: 125 | G25: 1 | H25: 150 | J25: 0.9 | K25: 1 | L25: 50 | M25: 1 | N25: 150 | W25: =(G25*H25)+(I25*J25)+(M25*N25)+(K25*L25)+(C25*D25)+(E25*F25) -> 1350 | X25: =(W25*5%) -> 67.5 | Y25: =SUM(W25+X25) -> 1417.5 | Z25: 5459
A26: 42189 | C26: 1 | D26: 1000 | F26: 125 | G26: 1 | H26: 150 | J26: 0.9 | K26: 1 | L26: 50 | M26: 1 | N26: 150 | W26: =(G26*H26)+(I26*J26)+(M26*N26)+(K26*L26)+(C26*D26)+(E26*F26) -> 1350 | X26: =(W26*5%) -> 67.5 | Y26: =SUM(W26+X26) -> 1417.5 | Z26: 5459
A27: 42191 | C27: 1 | D27: 1000 | F27: 125 | G27: 1 | H27: 150 | I27: 10 | J27: 0.9 | K27: 1 | L27: 50 | M27: 1 | N27: 150 | W27: =(G27*H27)+(I27*J27)+(M27*N27)+(K27*L27)+(C27*D27)+(E27*F27) -> 1359 | X27: =(W27*5%) -> 67.95 | Y27: =SUM(W27+X27) -> 1426.95 | Z27: 5459
A28: 42192 | C28: 1 | D28: 1000 | F28: 125 | G28: 1 | H28: 150 | I28: 20 | J28: 0.9 | K28: 1 | L28: 50 | M28: 1 | N28: 150 | W28: =(G28*H28)+(I28*J28)+(M28*N28)+(K28*L28)+(C28*D28)+(E28*F28) -> 1368 | X28: =(W28*5%) -> 68.4 | Y28: =SUM(W28+X28) -> 1436.4 | Z28: 5459
A29: 42193 | C29: 1 | D29: 1000 | F29: 125 | G29: 1 | H29: 150 | J29: 0.9 | K29: 1 | L29: 50 | M29: 1 | N29: 150 | W29: =(G29*H29)+(I29*J29)+(M29*N29)+(K29*L29)+(C29*D29)+(E29*F29) -> 1350 | X29: =(W29*5%) -> 67.5 | Y29: =SUM(W29+X29) -> 1417.5 | Z29: 5459
A30: 42194 | C30: 1 | D30: 1000 | F30: 125 | G30: 1 | H30: 150 | I30: 10 | J30: 0.9 | K30: 1 | L30: 50 | M30: 1 | N30: 150 | W30: =(G30*H30)+(I30*J30)+(M30*N30)+(K30*L30)+(C30*D30)+(E30*F30) -> 1359 | X30: =(W30*5%) -> 67.95 | Y30: =SUM(W30+X30) -> 1426.95 | Z30: 5459
A31: 42195 | C31: 1 | D31: 1000 | F31: 125 | G31: 1 | H31: 150 | I31: 13 | J31: 0.9 | K31: 1 | L31: 50 | M31: 1 | N31: 150 | W31: =(G31*H31)+(I31*J31)+(M31*N31)+(K31*L31)+(C31*D31)+(E31*F31) -> 1361.7 | X31: =(W31*5%) -> 68.085 | Y31: =SUM(W31+X31) -> 1429.785 | Z31: 5459
A32: 42196 | C32: 1 | D32: 1000 | F32: 125 | G32: 1 | H32: 150 | I32: 10 | J32: 0.9 | K32: 1 | L32: 50 | M32: 1 | N32: 150 | W32: =(G32*H32)+(I32*J32)+(M32*N32)+(K32*L32)+(C32*D32)+(E32*F32) -> 1359 | X32: =(W32*5%) -> 67.95 | Y32: =SUM(W32+X32) -> 1426.95 | Z32: 5459
A33: 42199 | C33: 1 | D33: 1000 | F33: 125 | G33: 1 | H33: 150 | I33: 50 | J33: 0.9 | K33: 1 | L33: 50 | M33: 1 | N33: 150 | W33: =(G33*H33)+(I33*J33)+(M33*N33)+(K33*L33)+(C33*D33)+(E33*F33) -> 1395 | X33: =(W33*5%) -> 69.75 | Y33: =SUM(W33+X33) -> 1464.75 | Z33: 5459
A34: 42199 | D34: 1000 | E34: 10.5 | F34: 125 | G34: 1 | H34: 150 | J34: 0.9 | K34: 1 | L34: 50 | N34: 150 | W34: =(G34*H34)+(I34*J34)+(M34*N34)+(K34*L34)+(C34*D34)+(E34*F34) -> 1512.5 | X34: =(W34*5%) -> 75.625 | Y34: =SUM(W34+X34) -> 1588.125 | Z34: 5459
A35: 42200 | D35: 1000 | E35: 12 | F35: 125 | G35: 1 | H35: 150 | J35: 0.9 | K35: 1 | L35: 50 | N35: 150 | W35: =(G35*H35)+(I35*J35)+(M35*N35)+(K35*L35)+(C35*D35)+(E35*F35) -> 1700 | X35: =(W35*5%) -> 85 | Y35: =SUM(W35+X35) -> 1785 | Z35: 5459
A36: 42200 | C36: 1 | D36: 1000 | F36: 125 | G36: 1 | H36: 150 | J36: 0.9 | K36: 1 | L36: 50 | M36: 1 | N36: 150 | W36: =(G36*H36)+(I36*J36)+(M36*N36)+(K36*L36)+(C36*D36)+(E36*F36) -> 1350 | X36: =(W36*5%) -> 67.5 | Y36: =SUM(W36+X36) -> 1417.5 | Z36: 5459
A37: 42201 | C37: 0.5 | D37: 1000 | E37: 4 | F37: 125 | G37: 1 | H37: 150 | J37: 0.9 | K37: 1 | L37: 50 | M37: 0.5 | N37: 150 | W37: =(G37*H37)+(I37*J37)+(M37*N37)+(K37*L37)+(C37*D37)+(E37*F37) -> 1275 | X37: =(W37*5%) -> 63.75 | Y37: =SUM(W37+X37) -> 1338.75 | Z37: 5459
A38: 42205 | C38: 1 | D38: 1000 | E38: 1 | F38: 125 | G38: 1 | H38: 150 | I38: 17 | J38: 0.9 | K38: 1 | L38: 50 | M38: 1 | N38: 150 | W38: =(G38*H38)+(I38*J38)+(M38*N38)+(K38*L38)+(C38*D38)+(E38*F38) -> 1490.3 | X38: =(W38*5%) -> 74.515 | Y38: =SUM(W38+X38) -> 1564.815 | Z38: 5459
A39: 42206 | C39: 1 | D39: 1000 | F39: 125 | G39: 1 | H39: 150 | I39: 64 | J39: 0.9 | K39: 1 | L39: 50 | M39: 1 | N39: 150 | W39: =(G39*H39)+(I39*J39)+(M39*N39)+(K39*L39)+(C39*D39)+(E39*F39) -> 1407.6 | X39: =(W39*5%) -> 70.38 | Y39: =SUM(W39+X39) -> 1477.98 | Z39: 5459
A40: 42207 | C40: 1 | D40: 1000 | F40: 125 | G40: 1 | H40: 150 | I40: 94 | J40: 0.9 | K40: 1 | L40: 50 | M40: 1 | N40: 150 | W40: =(G40*H40)+(I40*J40)+(M40*N40)+(K40*L40)+(C40*D40)+(E40*F40) -> 1434.6 | X40: =(W40*5%) -> 71.73 | Y40: =SUM(W40+X40) -> 1506.33 | Z40: 5459
A41: 42208 | C41: 1 | D41: 1000 | F41: 125 | G41: 1 | H41: 150 | I41: 57 | J41: 0.9 | K41: 1 | L41: 50 | M41: 1 | N41: 150 | W41: =(G41*H41)+(I41*J41)+(M41*N41)+(K41*L41)+(C41*D41)+(E41*F41) -> 1401.3 | X41: =(W41*5%) -> 70.065 | Y41: =SUM(W41+X41) -> 1471.365 | Z41: 5459
A42: 42209 | C42: 1 | D42: 1000 | F42: 125 | G42: 1 | H42: 150 | I42: 47 | J42: 0.9 | K42: 1 | L42: 50 | M42: 1 | N42: 150 | W42: =(G42*H42)+(I42*J42)+(M42*N42)+(K42*L42)+(C42*D42)+(E42*F42) -> 1392.3 | X42: =(W42*5%) -> 69.615 | Y42: =SUM(W42+X42) -> 1461.915 | Z42: 5459
A43: 42210 | C43: 1 | D43: 1000 | F43: 125 | G43: 1 | H43: 150 | I43: 100 | J43: 0.9 | K43: 1 | L43: 50 | M43: 1 | N43: 150 | W43: =(G43*H43)+(I43*J43)+(M43*N43)+(K43*L43)+(C43*D43)+(E43*F43) -> 1440 | X43: =(W43*5%) -> 72 | Y43: =SUM(W43+X43) -> 1512 | Z43: 5459
A44: 42212 | C44: 1 | D44: 1000 | F44: 125 | G44: 1 | H44: 150 | I44: 50 | J44: 0.9 | K44: 1 | L44: 50 | M44: 1 | N44: 150 | W44: =(G44*H44)+(I44*J44)+(M44*N44)+(K44*L44)+(C44*D44)+(E44*F44) -> 1395 | X44: =(W44*5%) -> 69.75 | Y44: =SUM(W44+X44) -> 1464.75 | Z44: 5459
A45: 42213 | C45: 1 | D45: 1000 | F45: 125 | G45: 1 | H45: 150 | I45: 20 | J45: 0.9 | K45: 1 | L45: 50 | M45: 1 | N45: 150 | W45: =(G45*H45)+(I45*J45)+(M45*N45)+(K45*L45)+(C45*D45)+(E45*F45) -> 1368 | X45: =(W45*5%) -> 68.4 | Y45: =SUM(W45+X45) -> 1436.4 | Z45: 5459
A46: 42214 | C46: 1 | D46: 1000 | F46: 125 | G46: 1 | H46: 150 | I46: 0 | J46: 0.9 | K46: 1 | L46: 50 | M46: 1 | N46: 150 | W46: =(G46*H46)+(I46*J46)+(M46*N46)+(K46*L46)+(C46*D46)+(E46*F46) -> 1350 | X46: =(W46*5%) -> 67.5 | Y46: =SUM(W46+X46) -> 1417.5 | Z46: 5459
A47: 42215 | C47: 1 | D47: 1000 | F47: 125 | G47: 1 | H47: 150 | I47: 0 | J47: 0.9 | K47: 1 | L47: 50 | M47: 1 | N47: 150 | W47: =(G47*H47)+(I47*J47)+(M47*N47)+(K47*L47)+(C47*D47)+(E47*F47) -> 1350 | X47: =(W47*5%) -> 67.5 | Y47: =SUM(W47+X47) -> 1417.5 | Z47: 5459
A48: 42216 | C48: 1 | D48: 1000 | F48: 125 | G48: 1 | H48: 150 | I48: 26 | J48: 0.9 | K48: 1 | L48: 50 | M48: 1 | N48: 150 | W48: =(G48*H48)+(I48*J48)+(M48*N48)+(K48*L48)+(C48*D48)+(E48*F48) -> 1373.4 | X48: =(W48*5%) -> 68.67 | Y48: =SUM(W48+X48) -> 1442.07 | Z48: 5459
A49: 42217 | C49: 1 | D49: 1000 | F49: 125 | G49: 1 | H49: 150 | I49: 50 | J49: 0.9 | K49: 1 | L49: 50 | M49: 1 | N49: 150 | W49: =(G49*H49)+(I49*J49)+(M49*N49)+(K49*L49)+(C49*D49)+(E49*F49) -> 1395 | X49: =(W49*5%) -> 69.75 | Y49: =SUM(W49+X49) -> 1464.75 | Z49: 5502
A50: 42219 | C50: 1 | D50: 1000 | F50: 125 | G50: 1 | H50: 150 | I50: 61 | J50: 0.9 | K50: 1 | L50: 50 | M50: 1 | N50: 150 | W50: =(G50*H50)+(I50*J50)+(M50*N50)+(K50*L50)+(C50*D50)+(E50*F50) -> 1404.9 | X50: =(W50*5%) -> 70.245 | Y50: =SUM(W50+X50) -> 1475.145 | Z50: 5502
A51: 42243 | C51: 1 | D51: 1000 | F51: 125 | G51: 1 | H51: 150 | J51: 0.9 | K51: 1 | L51: 50 | M51: 1 | N51: 150 | W51: =(G51*H51)+(I51*J51)+(M51*N51)+(K51*L51)+(C51*D51)+(E51*F51) -> 1350 | X51: =(W51*5%) -> 67.5 | Y51: =SUM(W51+X51) -> 1417.5 | Z51: 5502
A52: 42244 | C52: 1 | D52: 1000 | F52: 125 | G52: 1 | H52: 150 | J52: 0.9 | K52: 1 | L52: 50 | M52: 1 | N52: 150 | W52: =(G52*H52)+(I52*J52)+(M52*N52)+(K52*L52)+(C52*D52)+(E52*F52) -> 1350 | X52: =(W52*5%) -> 67.5 | Y52: =SUM(W52+X52) -> 1417.5 | Z52: 5502
A53: 42245 | C53: 1 | D53: 1000 | F53: 125 | G53: 1 | H53: 150 | J53: 0.9 | K53: 1 | L53: 50 | M53: 1 | N53: 150 | W53: =(G53*H53)+(I53*J53)+(M53*N53)+(K53*L53)+(C53*D53)+(E53*F53) -> 1350 | X53: =(W53*5%) -> 67.5 | Y53: =SUM(W53+X53) -> 1417.5 | Z53: 5502
A54: 42246 | D54: 1000 | F54: 125 | H54: 150 | J54: 0.9 | L54: 50 | W54: =(G54*H54)+(I54*J54)+(M54*N54)+(K54*L54)+(C54*D54)+(E54*F54) -> 0 | X54: =(W54*5%) -> 0 | Y54: =SUM(W54+X54) -> 0 | Z54: 5502
A55: 42247 | C55: 1 | D55: 1000 | F55: 125 | G55: 1 | H55: 150 | J55: 0.9 | K55: 1 | L55: 50 | M55: 1 | N55: 150 | W55: =(G55*H55)+(I55*J55)+(M55*N55)+(K55*L55)+(C55*D55)+(E55*F55) -> 1350 | X55: =(W55*5%) -> 67.5 | Y55: =SUM(W55+X55) -> 1417.5 | Z55: 5502 | AA55: Invoice 5502 | AB55: 8199.9
A56: 42248 | C56: 1 | D56: 1000 | F56: 125 | G56: 1 | H56: 150 | J56: 0.9 | K56: 1 | L56: 50 | M56: 1 | N56: 150 | W56: =(G56*H56)+(I56*J56)+(M56*N56)+(K56*L56)+(C56*D56)+(E56*F56) -> 1350 | X56: =(W56*5%) -> 67.5 | Y56: =SUM(W56+X56) -> 1417.5 | Z56: 5582
A57: 42249 | C57: 1 | D57: 1000 | F57: 125 | G57: 1 | H57: 150 | J57: 0.9 | K57: 1 | L57: 50 | M57: 1 | N57: 150 | W57: =(G57*H57)+(I57*J57)+(M57*N57)+(K57*L57)+(C57*D57)+(E57*F57) -> 1350 | X57: =(W57*5%) -> 67.5 | Y57: =SUM(W57+X57) -> 1417.5 | Z57: 5582
A58: 42250 | C58: 1 | D58: 1000 | F58: 125 | G58: 1 | H58: 150 | J58: 0.9 | K58: 1 | L58: 50 | M58: 1 | N58: 150 | W58: =(G58*H58)+(I58*J58)+(M58*N58)+(K58*L58)+(C58*D58)+(E58*F58) -> 1350 | X58: =(W58*5%) -> 67.5 | Y58: =SUM(W58+X58) -> 1417.5 | Z58: 5582
A59: 42251 | H59: 0 | J59: 0 | N59: 0 | W59: =(G59*H59)+(I59*J59)+(M59*N59)+(K59*L59)+(C59*D59)+(E59*F59) -> 0 | X59: =(W59*5%) -> 0 | Y59: =SUM(W59+X59) -> 0
A60: 42252 | H60: 0 | J60: 0 | N60: 0 | W60: =(G60*H60)+(I60*J60)+(M60*N60)+(K60*L60)+(C60*D60)+(E60*F60) -> 0 | X60: =(W60*5%) -> 0 | Y60: =SUM(W60+X60) -> 0
A61: 42253 | H61: 0 | J61: 0 | N61: 0 | W61: =(G61*H61)+(I61*J61)+(M61*N61)+(K61*L61)+(C61*D61)+(E61*F61) -> 0 | X61: =(W61*5%) -> 0 | Y61: =SUM(W61+X61) -> 0
A62: 42254 | H62: 0 | J62: 0 | N62: 0 | W62: =(G62*H62)+(I62*J62)+(M62*N62)+(K62*L62)+(C62*D62)+(E62*F62) -> 0 | X62: =(W62*5%) -> 0 | Y62: =SUM(W62+X62) -> 0
A63: 42255 | H63: 0 | J63: 0 | N63: 0 | W63: =(G63*H63)+(I63*J63)+(M63*N63)+(K63*L63)+(C63*D63)+(E63*F63) -> 0 | X63: =(W63*5%) -> 0 | Y63: =SUM(W63+X63) -> 0
A64: 42256 | H64: 0 | J64: 0 | N64: 0 | W64: =(G64*H64)+(I64*J64)+(M64*N64)+(K64*L64)+(C64*D64)+(E64*F64) -> 0 | X64: =(W64*5%) -> 0 | Y64: =SUM(W64+X64) -> 0
A65: 42257 | H65: 0 | J65: 0 | N65: 0 | W65: =(G65*H65)+(I65*J65)+(M65*N65)+(K65*L65)+(C65*D65)+(E65*F65) -> 0 | X65: =(W65*5%) -> 0 | Y65: =SUM(W65+X65) -> 0
A66: 42258 | C66: 1 | D66: 1000 | F66: 125 | G66: 1 | H66: 150 | J66: 0.9 | K66: 1 | L66: 50 | M66: 1 | N66: 150 | W66: =(G66*H66)+(I66*J66)+(M66*N66)+(K66*L66)+(C66*D66)+(E66*F66) -> 1350 | X66: =(W66*5%) -> 67.5 | Y66: =SUM(W66+X66) -> 1417.5 | Z66: 5582
A67: 42259 | C67: 1 | D67: 1000 | F67: 125 | G67: 1 | H67: 150 | J67: 0.9 | K67: 1 | L67: 50 | M67: 1 | N67: 150 | W67: =(G67*H67)+(I67*J67)+(M67*N67)+(K67*L67)+(C67*D67)+(E67*F67) -> 1350 | X67: =(W67*5%) -> 67.5 | Y67: =SUM(W67+X67) -> 1417.5 | Z67: 5582
A68: 42260 | C68: 0.5 | D68: 1000 | F68: 125 | G68: 0.5 | H68: 150 | J68: 0.9 | K68: 1 | L68: 50 | M68: 1 | N68: 150 | W68: =(G68*H68)+(I68*J68)+(M68*N68)+(K68*L68)+(C68*D68)+(E68*F68) -> 775 | X68: =(W68*5%) -> 38.75 | Y68: =SUM(W68+X68) -> 813.75 | Z68: 5582
A69: 42261 | C69: 1 | D69: 1000 | F69: 125 | G69: 1 | H69: 150 | J69: 0.9 | K69: 1 | L69: 50 | M69: 1 | N69: 150 | W69: =(G69*H69)+(I69*J69)+(M69*N69)+(K69*L69)+(C69*D69)+(E69*F69) -> 1350 | X69: =(W69*5%) -> 67.5 | Y69: =SUM(W69+X69) -> 1417.5 | Z69: 5582
A70: 42262 | C70: 1 | D70: 1000 | F70: 125 | G70: 1 | H70: 150 | J70: 0.9 | K70: 1 | L70: 50 | M70: 1 | N70: 150 | W70: =(G70*H70)+(I70*J70)+(M70*N70)+(K70*L70)+(C70*D70)+(E70*F70) -> 1350 | X70: =(W70*5%) -> 67.5 | Y70: =SUM(W70+X70) -> 1417.5 | Z70: 5582
A71: 42263 | C71: 0 | D71: 0 | F71: 125 | G71: 0 | H71: 0 | J71: 0 | K71: 0 | L71: 0 | M71: 0 | N71: 0 | W71: =(G71*H71)+(I71*J71)+(M71*N71)+(K71*L71)+(C71*D71)+(E71*F71) -> 0 | X71: =(W71*5%) -> 0 | Y71: =SUM(W71+X71) -> 0
A72: 42264 | C72: 0 | D72: 0 | F72: 125 | G72: 0 | H72: 0 | J72: 0 | K72: 0 | L72: 0 | M72: 0 | N72: 0 | W72: =(G72*H72)+(I72*J72)+(M72*N72)+(K72*L72)+(C72*D72)+(E72*F72) -> 0 | X72: =(W72*5%) -> 0 | Y72: =SUM(W72+X72) -> 0
A73: 42265 | C73: 1 | D73: 1000 | F73: 125 | G73: 1 | H73: 150 | J73: 0.9 | K73: 1 | L73: 50 | M73: 1 | N73: 150 | W73: =(G73*H73)+(I73*J73)+(M73*N73)+(K73*L73)+(C73*D73)+(E73*F73) -> 1350 | X73: =(W73*5%) -> 67.5 | Y73: =SUM(W73+X73) -> 1417.5 | Z73: 5582
A74: 42266 | C74: 1 | D74: 1000 | F74: 125 | G74: 1 | H74: 150 | J74: 0.9 | K74: 1 | L74: 50 | M74: 1 | N74: 150 | W74: =(G74*H74)+(I74*J74)+(M74*N74)+(K74*L74)+(C74*D74)+(E74*F74) -> 1350 | X74: =(W74*5%) -> 67.5 | Y74: =SUM(W74+X74) -> 1417.5 | Z74: 5582
A75: 42267 | C75: 1 | D75: 1000 | F75: 125 | G75: 1 | H75: 150 | J75: 0.9 | K75: 1 | L75: 50 | M75: 1 | N75: 150 | W75: =(G75*H75)+(I75*J75)+(M75*N75)+(K75*L75)+(C75*D75)+(E75*F75) -> 1350 | X75: =(W75*5%) -> 67.5 | Y75: =SUM(W75+X75) -> 1417.5 | Z75: 5582
A76: 42268 | C76: 1 | D76: 1000 | F76: 125 | G76: 1 | H76: 150 | J76: 0.9 | K76: 1 | L76: 50 | M76: 1 | N76: 150 | W76: =(G76*H76)+(I76*J76)+(M76*N76)+(K76*L76)+(C76*D76)+(E76*F76) -> 1350 | X76: =(W76*5%) -> 67.5 | Y76: =SUM(W76+X76) -> 1417.5 | Z76: 5582
A77: 42269 | C77: 1 | D77: 1000 | F77: 125 | G77: 1 | H77: 150 | J77: 0.9 | K77: 1 | L77: 50 | M77: 1 | N77: 150 | W77: =(G77*H77)+(I77*J77)+(M77*N77)+(K77*L77)+(C77*D77)+(E77*F77) -> 1350 | X77: =(W77*5%) -> 67.5 | Y77: =SUM(W77+X77) -> 1417.5 | Z77: 5582
A78: 42270 | C78: 1 | D78: 1000 | F78: 125 | G78: 1 | H78: 150 | J78: 0.9 | K78: 1 | L78: 50 | M78: 1 | N78: 150 | W78: =(G78*H78)+(I78*J78)+(M78*N78)+(K78*L78)+(C78*D78)+(E78*F78) -> 1350 | X78: =(W78*5%) -> 67.5 | Y78: =SUM(W78+X78) -> 1417.5 | Z78: 5582
A79: 42271 | C79: 1 | D79: 1000 | F79: 125 | G79: 1 | H79: 150 | J79: 0.9 | K79: 1 | L79: 50 | M79: 1 | N79: 150 | W79: =(G79*H79)+(I79*J79)+(M79*N79)+(K79*L79)+(C79*D79)+(E79*F79) -> 1350 | X79: =(W79*5%) -> 67.5 | Y79: =SUM(W79+X79) -> 1417.5 | Z79: 5582
A80: 42272 | C80: 1 | D80: 1000 | F80: 125 | G80: 1 | H80: 150 | J80: 0.9 | K80: 1 | L80: 50 | M80: 1 | N80: 150 | W80: =(G80*H80)+(I80*J80)+(M80*N80)+(K80*L80)+(C80*D80)+(E80*F80) -> 1350 | X80: =(W80*5%) -> 67.5 | Y80: =SUM(W80+X80) -> 1417.5 | Z80: 5582
A81: 42273 | C81: 1 | D81: 1000 | F81: 125 | G81: 1 | H81: 150 | J81: 0.9 | K81: 1 | L81: 50 | M81: 1 | N81: 150 | W81: =(G81*H81)+(I81*J81)+(M81*N81)+(K81*L81)+(C81*D81)+(E81*F81) -> 1350 | X81: =(W81*5%) -> 67.5 | Y81: =SUM(W81+X81) -> 1417.5 | Z81: 5582
A82: 42274 | C82: 1 | D82: 1000 | F82: 125 | G82: 1 | H82: 150 | J82: 0.9 | K82: 1 | L82: 50 | M82: 1 | N82: 150 | W82: =(G82*H82)+(I82*J82)+(M82*N82)+(K82*L82)+(C82*D82)+(E82*F82) -> 1350 | X82: =(W82*5%) -> 67.5 | Y82: =SUM(W82+X82) -> 1417.5 | Z82: 5582
A83: 42275 | C83: 1 | D83: 1000 | F83: 125 | G83: 1 | H83: 150 | J83: 0.9 | K83: 1 | L83: 50 | M83: 1 | N83: 150 | W83: =(G83*H83)+(I83*J83)+(M83*N83)+(K83*L83)+(C83*D83)+(E83*F83) -> 1350 | X83: =(W83*5%) -> 67.5 | Y83: =SUM(W83+X83) -> 1417.5 | Z83: 5582
A84: 42276 | C84: 1 | D84: 1000 | F84: 125 | G84: 1 | H84: 150 | J84: 0.9 | K84: 1 | L84: 50 | M84: 1 | N84: 150 | W84: =(G84*H84)+(I84*J84)+(M84*N84)+(K84*L84)+(C84*D84)+(E84*F84) -> 1350 | X84: =(W84*5%) -> 67.5 | Y84: =SUM(W84+X84) -> 1417.5 | Z84: 5582
A85: 42277 | C85: 1 | D85: 1000 | F85: 125 | G85: 1 | H85: 150 | J85: 0.9 | K85: 1 | L85: 50 | M85: 1 | N85: 150 | W85: =(G85*H85)+(I85*J85)+(M85*N85)+(K85*L85)+(C85*D85)+(E85*F85) -> 1350 | X85: =(W85*5%) -> 67.5 | Y85: =SUM(W85+X85) -> 1417.5 | Z85: 5582 | AA85: Invoice 5582 29163.75
A86: 42278 | C86: 1 | D86: 1000 | F86: 125 | G86: 1 | H86: 150 | I86: 20 | J86: 0.9 | K86: 1 | L86: 50 | M86: 1 | N86: 150 | W86: =(G86*H86)+(I86*J86)+(M86*N86)+(K86*L86)+(C86*D86)+(E86*F86) -> 1368 | X86: =(W86*5%) -> 68.4 | Y86: =SUM(W86+X86) -> 1436.4 | Z86: 5687
A87: 42279 | C87: 1 | D87: 1000 | F87: 125 | G87: 1 | H87: 150 | J87: 0.9 | K87: 1 | L87: 50 | M87: 1 | N87: 150 | W87: =(G87*H87)+(I87*J87)+(M87*N87)+(K87*L87)+(C87*D87)+(E87*F87) -> 1350 | X87: =(W87*5%) -> 67.5 | Y87: =SUM(W87+X87) -> 1417.5 | Z87: 5687
A88: 42280 | C88: 1 | D88: 1000 | F88: 125 | G88: 1 | H88: 150 | I88: 10 | J88: 0.9 | K88: 1 | L88: 50 | M88: 1 | N88: 150 | W88: =(G88*H88)+(I88*J88)+(M88*N88)+(K88*L88)+(C88*D88)+(E88*F88) -> 1359 | X88: =(W88*5%) -> 67.95 | Y88: =SUM(W88+X88) -> 1426.95 | Z88: 5687
A89: 42281 | C89: 1 | D89: 1000 | F89: 125 | G89: 1 | H89: 150 | J89: 0.9 | K89: 1 | L89: 50 | M89: 1 | N89: 150 | W89: =(G89*H89)+(I89*J89)+(M89*N89)+(K89*L89)+(C89*D89)+(E89*F89) -> 1350 | X89: =(W89*5%) -> 67.5 | Y89: =SUM(W89+X89) -> 1417.5 | Z89: 5687
A90: 42282 | C90: 1 | D90: 1000 | F90: 125 | G90: 1 | H90: 150 | J90: 0.9 | K90: 1 | L90: 50 | M90: 1 | N90: 150 | W90: =(G90*H90)+(I90*J90)+(M90*N90)+(K90*L90)+(C90*D90)+(E90*F90) -> 1350 | X90: =(W90*5%) -> 67.5 | Y90: =SUM(W90+X90) -> 1417.5 | Z90: 5687
A91: 42283 | C91: 1 | D91: 1000 | F91: 125 | G91: 1 | H91: 150 | J91: 0.9 | K91: 1 | L91: 50 | M91: 1 | N91: 150 | W91: =(G91*H91)+(I91*J91)+(M91*N91)+(K91*L91)+(C91*D91)+(E91*F91) -> 1350 | X91: =(W91*5%) -> 67.5 | Y91: =SUM(W91+X91) -> 1417.5 | Z91: 5687
A92: 42284 | C92: 1 | D92: 1000 | F92: 125 | G92: 1 | H92: 150 | I92: 40 | J92: 0.9 | K92: 1 | L92: 50 | M92: 1 | N92: 150 | W92: =(G92*H92)+(I92*J92)+(M92*N92)+(K92*L92)+(C92*D92)+(E92*F92) -> 1386 | X92: =(W92*5%) -> 69.3 | Y92: =SUM(W92+X92) -> 1455.3 | Z92: 5687
A93: 42285 | C93: 1 | D93: 1000 | F93: 125 | G93: 1 | H93: 150 | J93: 0.9 | K93: 1 | L93: 50 | M93: 1 | N93: 150 | W93: =(G93*H93)+(I93*J93)+(M93*N93)+(K93*L93)+(C93*D93)+(E93*F93) -> 1350 | X93: =(W93*5%) -> 67.5 | Y93: =SUM(W93+X93) -> 1417.5 | Z93: 5687
A94: 42291 | C94: 1 | D94: 1000 | E94: 12 | F94: 125 | G94: 2 | H94: 150 | I94: 130 | J94: 0.9 | K94: 2 | L94: 50 | M94: 1 | N94: 150 | W94: =(G94*H94)+(I94*J94)+(M94*N94)+(K94*L94)+(C94*D94)+(E94*F94) -> 3167 | X94: =(W94*5%) -> 158.35 | Y94: =SUM(W94+X94) -> 3325.35 | Z94: 5687
A95: 42292 | C95: 1 | D95: 1000 | E95: 12 | F95: 125 | G95: 2 | H95: 150 | I95: 50 | J95: 0.9 | K95: 2 | L95: 50 | M95: 1 | N95: 150 | W95: =(G95*H95)+(I95*J95)+(M95*N95)+(K95*L95)+(C95*D95)+(E95*F95) -> 3095 | X95: =(W95*5%) -> 154.75 | Y95: =SUM(W95+X95) -> 3249.75 | Z95: 5687
A96: 42293 | C96: 1 | D96: 1000 | E96: 12 | F96: 125 | G96: 2 | H96: 150 | I96: 18 | J96: 0.9 | K96: 2 | L96: 50 | M96: 1 | N96: 150 | W96: =(G96*H96)+(I96*J96)+(M96*N96)+(K96*L96)+(C96*D96)+(E96*F96) -> 3066.2 | X96: =(W96*5%) -> 153.31 | Y96: =SUM(W96+X96) -> 3219.51 | Z96: 5687
A97: 42294 | C97: 1 | D97: 1000 | E97: 10 | F97: 125 | G97: 2 | H97: 150 | I97: 20 | J97: 0.9 | K97: 2 | L97: 50 | M97: 1 | N97: 150 | W97: =(G97*H97)+(I97*J97)+(M97*N97)+(K97*L97)+(C97*D97)+(E97*F97) -> 2818 | X97: =(W97*5%) -> 140.9 | Y97: =SUM(W97+X97) -> 2958.9 | Z97: 5687
A98: 42295 | C98: 1 | D98: 1000 | F98: 125 | G98: 1 | H98: 150 | J98: 0.9 | K98: 1 | L98: 50 | M98: 1 | N98: 150 | W98: =(G98*H98)+(I98*J98)+(M98*N98)+(K98*L98)+(C98*D98)+(E98*F98) -> 1350 | X98: =(W98*5%) -> 67.5 | Y98: =SUM(W98+X98) -> 1417.5 | Z98: 5687
A99: 42296 | C99: 1 | D99: 1000 | F99: 125 | G99: 1 | H99: 150 | J99: 0.9 | K99: 1 | L99: 50 | M99: 1 | N99: 150 | W99: =(G99*H99)+(I99*J99)+(M99*N99)+(K99*L99)+(C99*D99)+(E99*F99) -> 1350 | X99: =(W99*5%) -> 67.5 | Y99: =SUM(W99+X99) -> 1417.5 | Z99: 5687
A100: 42297 | C100: 1 | D100: 1000 | F100: 125 | G100: 1 | H100: 150 | J100: 0.9 | K100: 1 | L100: 50 | M100: 1 | N100: 150 | W100: =(G100*H100)+(I100*J100)+(M100*N100)+(K100*L100)+(C100*D100)+(E100*F100) -> 1350 | X100: =(W100*5%) -> 67.5 | Y100: =SUM(W100+X100) -> 1417.5 | Z100: 5687
A101: 42298 | C101: 1 | D101: 1000 | F101: 125 | G101: 1 | H101: 150 | I101: 20 | J101: 0.9 | K101: 1 | L101: 50 | M101: 1 | N101: 150 | W101: =(G101*H101)+(I101*J101)+(M101*N101)+(K101*L101)+(C101*D101)+(E101*F101) -> 1368 | X101: =(W101*5%) -> 68.4 | Y101: =SUM(W101+X101) -> 1436.4 | Z101: 5687
A102: 42299 | C102: 1 | D102: 1000 | F102: 125 | G102: 1 | H102: 150 | J102: 0.9 | K102: 1 | L102: 50 | M102: 1 | N102: 150 | W102: =(G102*H102)+(I102*J102)+(M102*N102)+(K102*L102)+(C102*D102)+(E102*F102) -> 1350 | X102: =(W102*5%) -> 67.5 | Y102: =SUM(W102+X102) -> 1417.5 | Z102: 5687
...

Sheet Vendor #14
A2: Vendor #14-Survey
A4: Date | B4: LEM # | C4: Pipeline Tech | D4: CAD Tech | E4: Field Supervisor | F4: 2 Man Survey Crew | G4: one man survey crew | H4: Additional Person | I4: GIS Tech | J4: Safety Officer | K4: Subsistance | L4: Project Manager | M4: ATV | N4: GPS | O4: additional GPS | P4: Vehicle | Q4: km | R4: Total Hours Charged | S4: Equipment Detail | T4: Km's Charged | U4: Invoicing coordinator | V4: Professional surveyor | W4: Misc. materials | Y4: Subtotal | Z4: GST | AA4: LEM Amount | AB4: Affiliating Invoice | AC4: Approved By | AD4: SUM OF ALL LEM'S (before GST)
C5: Per Hr | D5: Per Hr | E5: Per Hr | F5: Per Hr | G5: Per Hr | H5: Per Hr | I5: Per Hr | J5: Per Hr | K5: Per Day | L5: Per Hr | M5: Per Day | N5: Per Day | O5: Per Day | P5: Per Hr | Q5: Per Km | U5: Per Hr | V5: Per hr
C6: 94.5 | D6: 90 | E6: 103.5 | F6: 144 | G6: 90 | H6: 54 | I6: 94.5 | J6: 90 | K6: 250 | L6: 112.5 | M6: 150 | N6: 500 | O6: 250 | P6: 23 | Q6: 1.1 | R6: 0 | S6: 0 | T6: 0 | U6: 67.5 | V6: 135 | W6: 1
AD7: =SUM(Y8:Y351) -> 1224133.5
A8: 42166 | B8: May 20 to May 30 | D8: 0.5 | I8: 30 | L8: 25 | R8: =L8+J8+I8+H8+G8+F8+E8+D8+C8 -> 55.5 | T8: =Q8 -> 0 | Y8: =SUM(C8*$C$6+D8*$D$6+E8*$E$6+F8*$F$6+G8*$G$6+H8*$H$6+I8*$I$6+J8*$J$6+K8*$K$6+L8*$L$6+M8*$M$6+N8*$N$6+O8*$O$6+P8*$P$6+Q8*$Q$6+U8*$U$6+V8*$V$6+W8*$W$6+X8*$X$6) -> 5692.5 | Z8: =(Y8*5%) -> 284.625 | AA8: =SUM(Y8+Z8) -> 5977.125 | AB8: 33041
A9: 42166 | B9: June 1 to June 7 | C9: 8 | D9: 6 | E9: 22 | F9: 14 | I9: 20.5 | J9: 4 | L9: 8.5 | N9: 1 | P9: 28 | Q9: 225 | R9: =L9+J9+I9+H9+G9+F9+E9+D9+C9 -> 83 | T9: =Q9 -> 225 | Y9: =SUM(C9*$C$6+D9*$D$6+E9*$E$6+F9*$F$6+G9*$G$6+H9*$H$6+I9*$I$6+J9*$J$6+K9*$K$6+L9*$L$6+M9*$M$6+N9*$N$6+O9*$O$6+P9*$P$6+Q9*$Q$6+U9*$U$6+V9*$V$6+W9*$W$6+X9*$X$6) -> 10234 | Z9: =(Y9*5%) -> 511.7 | AA9: =SUM(Y9+Z9) -> 10745.7 | AB9: 33041
A10: 42226 | B10: May 20 to June 30 | D10: 8.5 | I10: 18 | L10: 8 | Q10: 700 | Y10: =SUM(C10*$C$6+D10*$D$6+E10*$E$6+F10*$F$6+G10*$G$6+H10*$H$6+I10*$I$6+J10*$J$6+K10*$K$6+L10*$L$6+M10*$M$6+N10*$N$6+O10*$O$6+P10*$P$6+Q10*$Q$6+U10*$U$6+V10*$V$6+W10*$W$6+X10*$X$6) -> 4136 | Z10: =(Y10*5%) -> 206.8 | AA10: =SUM(Y10+Z10) -> 4342.8 | AB10: 33041
A11: 42148 | B11: 10621 | Y11: 494.75 | Z11: =(Y11*5%) -> 24.7375 | AA11: =SUM(Y11+Z11) -> 519.4875 | AB11: 33041 | AC11: soup and sandwich
A12: 42164 | B12: 26367 | Y12: 10399 | Z12: =(Y12*5%) -> 519.95 | AA12: =SUM(Y12+Z12) -> 10918.95 | AB12: 33041 | AC12: stake and lath
A13: 42164 | B13: 28609518 | Y13: 10 | Z13: =(Y13*5%) -> 0.5 | AA13: =SUM(Y13+Z13) -> 10.5 | AB13: 33041
A14: 42164 | B14: 28611176 | Y14: 10 | Z14: =(Y14*5%) -> 0.5 | AA14: =SUM(Y14+Z14) -> 10.5 | AB14: 33041
A15: 42163 | B15: 1 | E15: 12 | F15: 21 | J15: 4 | M15: 0 | N15: 2 | P15: 33 | Q15: 84 | R15: =L15+J15+I15+H15+G15+F15+E15+D15+C15 -> 37 | T15: =Q15 -> 84 | Y15: =SUM(C15*$C$6+D15*$D$6+E15*$E$6+F15*$F$6+G15*$G$6+H15*$H$6+I15*$I$6+J15*$J$6+K15*$K$6+L15*$L$6+M15*$M$6+N15*$N$6+O15*$O$6+P15*$P$6+Q15*$Q$6+U15*$U$6+V15*$V$6+W15*$W$6+X15*$X$6) -> 6477.4 | Z15: =(Y15*5%) -> 323.87 | AA15: =SUM(Y15+Z15) -> 6801.27 | AB15: 33041 | AC15: Additioanl $630 added to LEM
A16: 42164 | B16: 2-Revised | D16: 8 | E16: 11 | F16: 23 | M16: 4 | N16: 2 | P16: 34 | Y16: =SUM(C16*$C$6+D16*$D$6+E16*$E$6+F16*$F$6+G16*$G$6+H16*$H$6+I16*$I$6+J16*$J$6+K16*$K$6+L16*$L$6+M16*$M$6+N16*$N$6+O16*$O$6+P16*$P$6+Q16*$Q$6+U16*$U$6+V16*$V$6+W16*$W$6+X16*$X$6) -> 7552.5 | Z16: =(Y16*5%) -> 377.625 | AA16: =SUM(Y16+Z16) -> 7930.125 | AB16: 33041
A17: 42165 | B17: 3-Revised | D17: 1 | E17: 12 | F17: 21 | L17: 3 | M17: 4 | N17: 2 | P17: 33 | Q17: 0 | R17: =L17+J17+I17+H17+G17+F17+E17+D17+C17 -> 37 | T17: =Q17 -> 0 | Y17: =SUM(C17*$C$6+D17*$D$6+E17*$E$6+F17*$F$6+G17*$G$6+H17*$H$6+I17*$I$6+J17*$J$6+K17*$K$6+L17*$L$6+M17*$M$6+N17*$N$6+O17*$O$6+P17*$P$6+Q17*$Q$6+U17*$U$6+V17*$V$6+W17*$W$6+X17*$X$6) -> 7052.5 | Z17: =(Y17*5%) -> 352.625 | AA17: =SUM(Y17+Z17) -> 7405.125 | AB17: 33041 | AC17: Additional $90 added to LEM
A18: 42166 | B18: 4 | C18: 6 | E18: 13 | F18: 22.5 | H18: 11.5 | L18: 2 | M18: 4 | N18: 2 | P18: 22.5 | Q18: 275 | R18: =L18+J18+I18+H18+G18+F18+E18+D18+C18 -> 55 | T18: =Q18 -> 275 | Y18: =SUM(C18*$C$6+D18*$D$6+E18*$E$6+F18*$F$6+G18*$G$6+H18*$H$6+I18*$I$6+J18*$J$6+K18*$K$6+L18*$L$6+M18*$M$6+N18*$N$6+O18*$O$6+P18*$P$6+Q18*$Q$6+U18*$U$6+V18*$V$6+W18*$W$6+X18*$X$6) -> 8418.5 | Z18: =(Y18*5%) -> 420.925 | AA18: =SUM(Y18+Z18) -> 8839.425 | AB18: 33041
A19: 42167 | B19: 5 | C19: 4 | E19: 11 | F19: 24 | L19: 2 | M19: 4 | N19: 2 | P19: 35 | R19: =L19+J19+I19+H19+G19+F19+E19+D19+C19 -> 41 | T19: =Q19 -> 0 | Y19: =SUM(C19*$C$6+D19*$D$6+E19*$E$6+F19*$F$6+G19*$G$6+H19*$H$6+I19*$I$6+J19*$J$6+K19*$K$6+L19*$L$6+M19*$M$6+N19*$N$6+O19*$O$6+P19*$P$6+Q19*$Q$6+U19*$U$6+V19*$V$6+W19*$W$6+X19*$X$6) -> 7602.5 | Z19: =(Y19*5%) -> 380.125 | AA19: =SUM(Y19+Z19) -> 7982.625 | AB19: 33041
A20: 42168 | B20: 6 | E20: 12 | F20: 20 | L20: 1 | M20: 4 | N20: 2 | P20: 32 | R20: =L20+J20+I20+H20+G20+F20+E20+D20+C20 -> 33 | T20: =Q20 -> 0 | Y20: =SUM(C20*$C$6+D20*$D$6+E20*$E$6+F20*$F$6+G20*$G$6+H20*$H$6+I20*$I$6+J20*$J$6+K20*$K$6+L20*$L$6+M20*$M$6+N20*$N$6+O20*$O$6+P20*$P$6+Q20*$Q$6+U20*$U$6+V20*$V$6+W20*$W$6+X20*$X$6) -> 6570.5 | Z20: =(Y20*5%) -> 328.525 | AA20: =SUM(Y20+Z20) -> 6899.025 | AB20: 33041
A21: 42170 | B21: 7 | C21: 2 | E21: 12 | F21: 32 | L21: 2 | M21: 4 | N21: 2 | P21: 44 | R21: =L21+J21+I21+H21+G21+F21+E21+D21+C21 -> 48 | T21: =Q21 -> 0 | Y21: =SUM(C21*$C$6+D21*$D$6+E21*$E$6+F21*$F$6+G21*$G$6+H21*$H$6+I21*$I$6+J21*$J$6+K21*$K$6+L21*$L$6+M21*$M$6+N21*$N$6+O21*$O$6+P21*$P$6+Q21*$Q$6+U21*$U$6+V21*$V$6+W21*$W$6+X21*$X$6) -> 8876 | Z21: =(Y21*5%) -> 443.8 | AA21: =SUM(Y21+Z21) -> 9319.8 | AB21: 33041
A22: 42171 | B22: 8 | C22: 2 | E22: 11 | F22: 33.5 | L22: 2 | M22: 4 | N22: 3 | P22: 44.5 | R22: =L22+J22+I22+H22+G22+F22+E22+D22+C22 -> 48.5 | T22: =Q22 -> 0 | Y22: =SUM(C22*$C$6+D22*$D$6+E22*$E$6+F22*$F$6+G22*$G$6+H22*$H$6+I22*$I$6+J22*$J$6+K22*$K$6+L22*$L$6+M22*$M$6+N22*$N$6+O22*$O$6+P22*$P$6+Q22*$Q$6+U22*$U$6+V22*$V$6+W22*$W$6+X22*$X$6) -> 9500 | Z22: =(Y22*5%) -> 475 | AA22: =SUM(Y22+Z22) -> 9975 | AB22: 33041
A23: 42172 | B23: 9 | C23: 2 | E23: 12 | F23: 33.5 | L23: 1 | M23: 4 | N23: 3 | P23: 45.5 | R23: =L23+J23+I23+H23+G23+F23+E23+D23+C23 -> 48.5 | T23: =Q23 -> 0 | Y23: =SUM(C23*$C$6+D23*$D$6+E23*$E$6+F23*$F$6+G23*$G$6+H23*$H$6+I23*$I$6+J23*$J$6+K23*$K$6+L23*$L$6+M23*$M$6+N23*$N$6+O23*$O$6+P23*$P$6+Q23*$Q$6+U23*$U$6+V23*$V$6+W23*$W$6+X23*$X$6) -> 9514 | Z23: =(Y23*5%) -> 475.7 | AA23: =SUM(Y23+Z23) -> 9989.7 | AB23: 33041 | AC23: Additional $135 added to LEM
A24: 42173 | B24: 10 | D24: 1 | E24: 12 | F24: 32.5 | G24: 5 | M24: 6 | N24: 3 | P24: 44.5 | Q24: 110 | R24: =L24+J24+I24+H24+G24+F24+E24+D24+C24 -> 50.5 | T24: =Q24 -> 110 | Y24: =SUM(C24*$C$6+D24*$D$6+E24*$E$6+F24*$F$6+G24*$G$6+H24*$H$6+I24*$I$6+J24*$J$6+K24*$K$6+L24*$L$6+M24*$M$6+N24*$N$6+O24*$O$6+P24*$P$6+Q24*$Q$6+U24*$U$6+V24*$V$6+W24*$W$6+X24*$X$6) -> 10006.5 | Z24: =(Y24*5%) -> 500.325 | AA24: =SUM(Y24+Z24) -> 10506.825 | AB24: 33041
A25: 42174 | B25: 11 | E25: 11 | F25: 22.5 | G25: 12 | H25: 5.5 | M25: 4 | N25: 2 | P25: 45.5 | R25: =L25+J25+I25+H25+G25+F25+E25+D25+C25 -> 51 | T25: =Q25 -> 0 | Y25: =SUM(C25*$C$6+D25*$D$6+E25*$E$6+F25*$F$6+G25*$G$6+H25*$H$6+I25*$I$6+J25*$J$6+K25*$K$6+L25*$L$6+M25*$M$6+N25*$N$6+O25*$O$6+P25*$P$6+Q25*$Q$6+U25*$U$6+V25*$V$6+W25*$W$6+X25*$X$6) -> 8402 | Z25: =(Y25*5%) -> 420.1 | AA25: =SUM(Y25+Z25) -> 8822.1 | AB25: 33041 | AC25: Additional $425.25 added to LEM
A26: 42174 | B26: 12 | C26: 6 | R26: =L26+J26+I26+H26+G26+F26+E26+D26+C26 -> 6 | T26: =Q26 -> 0 | Y26: =SUM(C26*$C$6+D26*$D$6+E26*$E$6+F26*$F$6+G26*$G$6+H26*$H$6+I26*$I$6+J26*$J$6+K26*$K$6+L26*$L$6+M26*$M$6+N26*$N$6+O26*$O$6+P26*$P$6+Q26*$Q$6+U26*$U$6+V26*$V$6+W26*$W$6+X26*$X$6) -> 567 | Z26: =(Y26*5%) -> 28.35 | AA26: =SUM(Y26+Z26) -> 595.35 | AB26: 33041
A27: 42175 | B27: 13 | E27: 12 | F27: 26.5 | M27: 6 | N27: 2 | O27: 1 | P27: 38.5 | R27: =L27+J27+I27+H27+G27+F27+E27+D27+C27 -> 38.5 | T27: =Q27 -> 0 | Y27: =SUM(C27*$C$6+D27*$D$6+E27*$E$6+F27*$F$6+G27*$G$6+H27*$H$6+I27*$I$6+J27*$J$6+K27*$K$6+L27*$L$6+M27*$M$6+N27*$N$6+O27*$O$6+P27*$P$6+Q27*$Q$6+U27*$U$6+V27*$V$6+W27*$W$6+X27*$X$6) -> 8093.5 | Z27: =(Y27*5%) -> 404.675 | AA27: =SUM(Y27+Z27) -> 8498.175 | AB27: 33041
A28: 42177 | B28: 14 | C28: 6 | E28: 11 | F28: 32 | L28: 8 | M28: 6 | N28: 2 | O28: 2 | P28: 43 | Q28: 440 | R28: =L28+J28+I28+H28+G28+F28+E28+D28+C28 -> 57 | T28: =Q28 -> 440 | Y28: =SUM(C28*$C$6+D28*$D$6+E28*$E$6+F28*$F$6+G28*$G$6+H28*$H$6+I28*$I$6+J28*$J$6+K28*$K$6+L28*$L$6+M28*$M$6+N28*$N$6+O28*$O$6+P28*$P$6+Q28*$Q$6+U28*$U$6+V28*$V$6+W28*$W$6+X28*$X$6) -> 11086.5 | Z28: =(Y28*5%) -> 554.325 | AA28: =SUM(Y28+Z28) -> 11640.825 | AB28: 33041
A29: 42178 | B29: 15 | C29: 8 | D29: 5 | E29: 11 | F29: 30 | I29: 0.5 | L29: 2 | M29: 6 | N29: 2 | O29: 1 | P29: 41 | R29: =L29+J29+I29+H29+G29+F29+E29+D29+C29 -> 56.5 | T29: 230 | Y29: =SUM(C29*$C$6+D29*$D$6+E29*$E$6+F29*$F$6+G29*$G$6+H29*$H$6+I29*$I$6+J29*$J$6+K29*$K$6+L29*$L$6+M29*$M$6+N29*$N$6+O29*$O$6+P29*$P$6+Q29*$Q$6+U29*$U$6+V29*$V$6+W29*$W$6+X29*$X$6) -> 10029.75 | Z29: =(Y29*5%) -> 501.4875 | AA29: =SUM(Y29+Z29) -> 10531.237 | AB29: 33041 | AC29: Additional $519 added to LEM
A30: 42179 | B30: 16 | C30: 10 | E30: 13 | F30: 30.5 | I30: 1 | M30: 4 | N30: 3 | P30: 33.5 | Q30: 230 | R30: =L30+J30+I30+H30+G30+F30+E30+D30+C30 -> 54.5 | T30: =Q30 -> 230 | Y30: =SUM(C30*$C$6+D30*$D$6+E30*$E$6+F30*$F$6+G30*$G$6+H30*$H$6+I30*$I$6+J30*$J$6+K30*$K$6+L30*$L$6+M30*$M$6+N30*$N$6+O30*$O$6+P30*$P$6+Q30*$Q$6+U30*$U$6+V30*$V$6+W30*$W$6+X30*$X$6) -> 9900.5 | Z30: =(Y30*5%) -> 495.025 | AA30: =SUM(Y30+Z30) -> 10395.525 | AB30: 33041 | AC30: Additional $330 added to LEM
A31: 42180 | B31: 17 | C31: 9 | E31: 12 | F31: 34 | L31: 1 | M31: 4 | N31: 3 | P31: 35 | Q31: 230 | R31: =L31+J31+I31+H31+G31+F31+E31+D31+C31 -> 56 | T31: =Q31 -> 230 | Y31: =SUM(C31*$C$6+D31*$D$6+E31*$E$6+F31*$F$6+G31*$G$6+H31*$H$6+I31*$I$6+J31*$J$6+K31*$K$6+L31*$L$6+M31*$M$6+N31*$N$6+O31*$O$6+P31*$P$6+Q31*$Q$6+U31*$U$6+V31*$V$6+W31*$W$6+X31*$X$6) -> 10259 | Z31: =(Y31*5%) -> 512.95 | AA31: =SUM(Y31+Z31) -> 10771.95 | AB31: 33041
A32: 42181 | B32: 18 | C32: 9 | F32: 36 | M32: 6 | N32: 3 | P32: 36 | R32: =L32+J32+I32+H32+G32+F32+E32+D32+C32 -> 45 | T32: =Q32 -> 0 | Y32: =SUM(C32*$C$6+D32*$D$6+E32*$E$6+F32*$F$6+G32*$G$6+H32*$H$6+I32*$I$6+J32*$J$6+K32*$K$6+L32*$L$6+M32*$M$6+N32*$N$6+O32*$O$6+P32*$P$6+Q32*$Q$6+U32*$U$6+V32*$V$6+W32*$W$6+X32*$X$6) -> 9262.5 | Z32: =(Y32*5%) -> 463.125 | AA32: =SUM(Y32+Z32) -> 9725.625 | AB32: 33041 | AC32: Additional $567 added to LEM
A33: 42182 | B33: 19 | F33: 24.5 | M33: 6 | N33: 2 | O33: 1 | P33: 24.5 | R33: =L33+J33+I33+H33+G33+F33+E33+D33+C33 -> 24.5 | T33: =Q33 -> 0 | Y33: =SUM(C33*$C$6+D33*$D$6+E33*$E$6+F33*$F$6+G33*$G$6+H33*$H$6+I33*$I$6+J33*$J$6+K33*$K$6+L33*$L$6+M33*$M$6+N33*$N$6+O33*$O$6+P33*$P$6+Q33*$Q$6+U33*$U$6+V33*$V$6+W33*$W$6+X33*$X$6) -> 6241.5 | Z33: =(Y33*5%) -> 312.075 | AA33: =SUM(Y33+Z33) -> 6553.575 | AB33: 33041
A34: 42184 | B34: 20 | C34: 11 | D34: 0.5 | E34: 12 | F34: 33.5 | L34: 3 | M34: 6 | N34: 2 | O34: 1 | P34: 45.5 | R34: =L34+J34+I34+H34+G34+F34+E34+D34+C34 -> 60 | T34: =Q34 -> 0 | Y34: =SUM(C34*$C$6+D34*$D$6+E34*$E$6+F34*$F$6+G34*$G$6+H34*$H$6+I34*$I$6+J34*$J$6+K34*$K$6+L34*$L$6+M34*$M$6+N34*$N$6+O34*$O$6+P34*$P$6+Q34*$Q$6+U34*$U$6+V34*$V$6+W34*$W$6+X34*$X$6) -> 10684.5 | Z34: =(Y34*5%) -> 534.225 | AA34: =SUM(Y34+Z34) -> 11218.725 | AB34: 33041
A35: 42185 | B35: 21 | C35: 11 | E35: 10 | F35: 15 | L35: 1 | O35: 3 | P35: 15 | Q35: 283 | R35: =L35+J35+I35+H35+G35+F35+E35+D35+C35 -> 37 | T35: =Q35 -> 283 | Y35: =SUM(C35*$C$6+D35*$D$6+E35*$E$6+F35*$F$6+G35*$G$6+H35*$H$6+I35*$I$6+J35*$J$6+K35*$K$6+L35*$L$6+M35*$M$6+N35*$N$6+O35*$O$6+P35*$P$6+Q35*$Q$6+U35*$U$6+V35*$V$6+W35*$W$6+X35*$X$6) -> 5753.3 | Z35: =(Y35*5%) -> 287.665 | AA35: =SUM(Y35+Z35) -> 6040.965 | AB35: 33041
A36: 42186 | B36: 22 | C36: 6 | E36: 6 | G36: 12 | Q36: 515 | R36: =L36+J36+I36+H36+G36+F36+E36+D36+C36 -> 24 | T36: =Q36 -> 515 | Y36: =SUM(C36*$C$6+D36*$D$6+E36*$E$6+F36*$F$6+G36*$G$6+H36*$H$6+I36*$I$6+J36*$J$6+K36*$K$6+L36*$L$6+M36*$M$6+N36*$N$6+O36*$O$6+P36*$P$6+Q36*$Q$6+U36*$U$6+V36*$V$6+W36*$W$6+X36*$X$6) -> 2834.5 | Z36: =(Y36*5%) -> 141.725 | AA36: =SUM(Y36+Z36) -> 2976.225 | AB36: 33272
A37: 42187 | B37: 23 Revised | C37: 3 | E37: 13 | F37: 33.5 | I37: 6 | L37: 6 | M37: 6 | N37: 2 | O37: 1 | P37: 35.5 | Q37: 280 | R37: =L37+J37+I37+H37+G37+F37+E37+D37+C37 -> 61.5 | T37: =Q37 -> 280 | Y37: =SUM(C37*$C$6+D37*$D$6+E37*$E$6+F37*$F$6+G37*$G$6+H37*$H$6+I37*$I$6+J37*$J$6+K37*$K$6+L37*$L$6+M37*$M$6+N37*$N$6+O37*$O$6+P37*$P$6+Q37*$Q$6+U37*$U$6+V37*$V$6+W37*$W$6+X37*$X$6) -> 10969.5 | Z37: =(Y37*5%) -> 548.475 | AA37: =SUM(Y37+Z37) -> 11517.975 | AB37: 33272
A38: 42188 | B38: 24 Revised | C38: 4 | D38: 1.5 | E38: 12 | F38: 36 | L38: 2 | M38: 4 | N38: 2 | O38: 1 | P38: 24 | Q38: 450 | R38: =L38+J38+I38+H38+G38+F38+E38+D38+C38 -> 55.5 | T38: =Q38 -> 450 | Y38: =SUM(C38*$C$6+D38*$D$6+E38*$E$6+F38*$F$6+G38*$G$6+H38*$H$6+I38*$I$6+J38*$J$6+K38*$K$6+L38*$L$6+M38*$M$6+N38*$N$6+O38*$O$6+P38*$P$6+Q38*$Q$6+U38*$U$6+V38*$V$6+W38*$W$6+X38*$X$6) -> 10061 | Z38: =(Y38*5%) -> 503.05 | AA38: =SUM(Y38+Z38) -> 10564.05 | AB38: 33272
A39: 42189 | B39: 25 | C39: 2 | E39: 12 | F39: 30 | M39: 2 | N39: 3 | P39: 30 | Q39: 220 | R39: =L39+J39+I39+H39+G39+F39+E39+D39+C39 -> 44 | T39: =Q39 -> 220 | Y39: =SUM(C39*$C$6+D39*$D$6+E39*$E$6+F39*$F$6+G39*$G$6+H39*$H$6+I39*$I$6+J39*$J$6+K39*$K$6+L39*$L$6+M39*$M$6+N39*$N$6+O39*$O$6+P39*$P$6+Q39*$Q$6+U39*$U$6+V39*$V$6+W39*$W$6+X39*$X$6) -> 8483 | Z39: =(Y39*5%) -> 424.15 | AA39: =SUM(Y39+Z39) -> 8907.15 | AB39: 33272
A40: 42191 | B40: 26 | E40: 12 | F40: 35.5 | M40: 4 | N40: 2 | O40: 1 | P40: 47.5 | R40: =L40+J40+I40+H40+G40+F40+E40+D40+C40 -> 47.5 | T40: =Q40 -> 0 | Y40: =SUM(C40*$C$6+D40*$D$6+E40*$E$6+F40*$F$6+G40*$G$6+H40*$H$6+I40*$I$6+J40*$J$6+K40*$K$6+L40*$L$6+M40*$M$6+N40*$N$6+O40*$O$6+P40*$P$6+Q40*$Q$6+U40*$U$6+V40*$V$6+W40*$W$6+X40*$X$6) -> 9296.5 | Z40: =(Y40*5%) -> 464.825 | AA40: =SUM(Y40+Z40) -> 9761.325 | AB40: 33272
A41: 42192 | B41: 27 Revised | D41: 2 | E41: 10 | F41: 33.5 | L41: 2 | M41: 4 | N41: 2 | O41: 1 | P41: 43.5 | R41: =L41+J41+I41+H41+G41+F41+E41+D41+C41 -> 47.5 | T41: =Q41 -> 0 | Y41: =SUM(C41*$C$6+D41*$D$6+E41*$E$6+F41*$F$6+G41*$G$6+H41*$H$6+I41*$I$6+J41*$J$6+K41*$K$6+L41*$L$6+M41*$M$6+N41*$N$6+O41*$O$6+P41*$P$6+Q41*$Q$6+U41*$U$6+V41*$V$6+W41*$W$6+X41*$X$6) -> 9114.5 | Z41: =(Y41*5%) -> 455.725 | AA41: =SUM(Y41+Z41) -> 9570.225 | AB41: 33272
A42: 42193 | B42: 28 | D42: 2.5 | E42: 11 | F42: 34 | M42: 4 | N42: 2 | O42: 1 | P42: 45 | R42: =L42+J42+I42+H42+G42+F42+E42+D42+C42 -> 47.5 | T42: =Q42 -> 0 | Y42: =SUM(C42*$C$6+D42*$D$6+E42*$E$6+F42*$F$6+G42*$G$6+H42*$H$6+I42*$I$6+J42*$J$6+K42*$K$6+L42*$L$6+M42*$M$6+N42*$N$6+O42*$O$6+P42*$P$6+Q42*$Q$6+U42*$U$6+V42*$V$6+W42*$W$6+X42*$X$6) -> 9144.5 | Z42: =(Y42*5%) -> 457.225 | AA42: =SUM(Y42+Z42) -> 9601.725 | AB42: 33272
A43: 42194 | B43: 29 Revised | D43: 5 | E43: 13 | F43: 35.5 | I43: 5 | L43: 2.5 | M43: 4 | N43: 3 | P43: 48.5 | R43: =L43+J43+I43+H43+G43+F43+E43+D43+C43 -> 61 | T43: =Q43 -> 0 | U43: 0.5 | Y43: =SUM(C43*$C$6+D43*$D$6+E43*$E$6+F43*$F$6+G43*$G$6+H43*$H$6+I43*$I$6+J43*$J$6+K43*$K$6+L43*$L$6+M43*$M$6+N43*$N$6+O43*$O$6+P43*$P$6+Q43*$Q$6+U43*$U$6+V43*$V$6+W43*$W$6+X43*$X$6) -> 10910.5 | Z43: =(Y43*5%) -> 545.525 | AA43: =SUM(Y43+Z43) -> 11456.025 | AB43: 33272
A44: 42195 | B44: 30 Revised | D44: 4 | E44: 10 | F44: 35 | L44: 2 | M44: 5 | N44: 3 | P44: 45 | R44: =L44+J44+I44+H44+G44+F44+E44+D44+C44 -> 51 | T44: =Q44 -> 0 | U44: 2.5 | Y44: =SUM(C44*$C$6+D44*$D$6+E44*$E$6+F44*$F$6+G44*$G$6+H44*$H$6+I44*$I$6+J44*$J$6+K44*$K$6+L44*$L$6+M44*$M$6+N44*$N$6+O44*$O$6+P44*$P$6+Q44*$Q$6+U44*$U$6+V44*$V$6+W44*$W$6+X44*$X$6) -> 10113.75 | Z44: =(Y44*5%) -> 505.6875 | AA44: =SUM(Y44+Z44) -> 10619.438 | AB44: 33272
A45: 42196 | B45: 31 | E45: 11 | F45: 32.5 | M45: 4 | N45: 2 | O45: 1 | P45: 43.5 | R45: =L45+J45+I45+H45+G45+F45+E45+D45+C45 -> 43.5 | T45: =Q45 -> 0 | Y45: =SUM(C45*$C$6+D45*$D$6+E45*$E$6+F45*$F$6+G45*$G$6+H45*$H$6+I45*$I$6+J45*$J$6+K45*$K$6+L45*$L$6+M45*$M$6+N45*$N$6+O45*$O$6+P45*$P$6+Q45*$Q$6+U45*$U$6+V45*$V$6+W45*$W$6+X45*$X$6) -> 8669 | Z45: =(Y45*5%) -> 433.45 | AA45: =SUM(Y45+Z45) -> 9102.45 | AB45: 33272
A46: 42198 | B46: 32 | C46: 8 | D46: 2 | L46: 3 | R46: =L46+J46+I46+H46+G46+F46+E46+D46+C46 -> 13 | T46: =Q46 -> 0 | Y46: =SUM(C46*$C$6+D46*$D$6+E46*$E$6+F46*$F$6+G46*$G$6+H46*$H$6+I46*$I$6+J46*$J$6+K46*$K$6+L46*$L$6+M46*$M$6+N46*$N$6+O46*$O$6+P46*$P$6+Q46*$Q$6+U46*$U$6+V46*$V$6+W46*$W$6+X46*$X$6) -> 1273.5 | Z46: =(Y46*5%) -> 63.675 | AA46: =SUM(Y46+Z46) -> 1337.175 | AB46: 33272
A47: 42199 | B47: 33 | C47: 8 | G47: 12 | L47: 1 | R47: =L47+J47+I47+H47+G47+F47+E47+D47+C47 -> 21 | T47: =Q47 -> 0 | Y47: =SUM(C47*$C$6+D47*$D$6+E47*$E$6+F47*$F$6+G47*$G$6+H47*$H$6+I47*$I$6+J47*$J$6+K47*$K$6+L47*$L$6+M47*$M$6+N47*$N$6+O47*$O$6+P47*$P$6+Q47*$Q$6+U47*$U$6+V47*$V$6+W47*$W$6+X47*$X$6) -> 1948.5 | Z47: =(Y47*5%) -> 97.425 | AA47: =SUM(Y47+Z47) -> 2045.925 | AB47: 33272
A48: 42200 | B48: 34 | D48: 0.5 | E48: 8 | F48: 35.5 | G48: 12 | L48: 1 | M48: 2 | N48: 3 | P48: 55.5 | R48: =L48+J48+I48+H48+G48+F48+E48+D48+C48 -> 57 | T48: =Q48 -> 0 | Y48: =SUM(C48*$C$6+D48*$D$6+E48*$E$6+F48*$F$6+G48*$G$6+H48*$H$6+I48*$I$6+J48*$J$6+K48*$K$6+L48*$L$6+M48*$M$6+N48*$N$6+O48*$O$6+P48*$P$6+Q48*$Q$6+U48*$U$6+V48*$V$6+W48*$W$6+X48*$X$6) -> 10254 | Z48: =(Y48*5%) -> 512.7 | AA48: =SUM(Y48+Z48) -> 10766.7 | AB48: 33272
A49: 42201 | B49: 35 | E49: 10 | F49: 17 | L49: 1.5 | N49: 1 | P49: 27 | R49: =L49+J49+I49+H49+G49+F49+E49+D49+C49 -> 28.5 | T49: =Q49 -> 0 | Y49: =SUM(C49*$C$6+D49*$D$6+E49*$E$6+F49*$F$6+G49*$G$6+H49*$H$6+I49*$I$6+J49*$J$6+K49*$K$6+L49*$L$6+M49*$M$6+N49*$N$6+O49*$O$6+P49*$P$6+Q49*$Q$6+U49*$U$6+V49*$V$6+W49*$W$6+X49*$X$6) -> 4772.75 | Z49: =(Y49*5%) -> 238.6375 | AA49: =SUM(Y49+Z49) -> 5011.3875 | AB49: 33272
A50: 42202 | B50: 36 | D50: 4.5 | L50: 1 | R50: =L50+J50+I50+H50+G50+F50+E50+D50+C50 -> 5.5 | T50: =Q50 -> 0 | Y50: =SUM(C50*$C$6+D50*$D$6+E50*$E$6+F50*$F$6+G50*$G$6+H50*$H$6+I50*$I$6+J50*$J$6+K50*$K$6+L50*$L$6+M50*$M$6+N50*$N$6+O50*$O$6+P50*$P$6+Q50*$Q$6+U50*$U$6+V50*$V$6+W50*$W$6+X50*$X$6) -> 517.5 | Z50: =(Y50*5%) -> 25.875 | AA50: =SUM(Y50+Z50) -> 543.375 | AB50: 33272
A51: 42205 | B51: 37 Revised | C51: 4 | D51: 5 | F51: 23 | G51: 12 | L51: 1 | M51: 4 | N51: 2 | P51: 23 | Q51: 260 | R51: =L51+J51+I51+H51+G51+F51+E51+D51+C51 -> 45 | T51: =Q51 -> 260 | Y51: =SUM(C51*$C$6+D51*$D$6+E51*$E$6+F51*$F$6+G51*$G$6+H51*$H$6+I51*$I$6+J51*$J$6+K51*$K$6+L51*$L$6+M51*$M$6+N51*$N$6+O51*$O$6+P51*$P$6+Q51*$Q$6+U51*$U$6+V51*$V$6+W51*$W$6+X51*$X$6) -> 7747.5 | Z51: =(Y51*5%) -> 387.375 | AA51: =SUM(Y51+Z51) -> 8134.875 | AB51: 33272
A52: 42206 | B52: 38 Revised | C52: 6 | D52: 4.5 | E52: 12 | F52: 32 | L52: 2 | M52: 2 | N52: 1 | P52: 34.5 | Q52: 200 | R52: =L52+J52+I52+H52+G52+F52+E52+D52+C52 -> 56.5 | T52: =Q52 -> 200 | Y52: =SUM(C52*$C$6+D52*$D$6+E52*$E$6+F52*$F$6+G52*$G$6+H52*$H$6+I52*$I$6+J52*$J$6+K52*$K$6+L52*$L$6+M52*$M$6+N52*$N$6+O52*$O$6+P52*$P$6+Q52*$Q$6+U52*$U$6+V52*$V$6+W52*$W$6+X52*$X$6) -> 8860.5 | Z52: =(Y52*5%) -> 443.025 | AA52: =SUM(Y52+Z52) -> 9303.525 | AB52: 33272
A53: 42207 | B53: 39 Revised | C53: 4 | D53: 7 | E53: 12 | F53: 34 | L53: 2 | M53: 2 | N53: 2 | P53: 46 | R53: =L53+J53+I53+H53+G53+F53+E53+D53+C53 -> 59 | T53: =Q53 -> 0 | Y53: =SUM(C53*$C$6+D53*$D$6+E53*$E$6+F53*$F$6+G53*$G$6+H53*$H$6+I53*$I$6+J53*$J$6+K53*$K$6+L53*$L$6+M53*$M$6+N53*$N$6+O53*$O$6+P53*$P$6+Q53*$Q$6+U53*$U$6+V53*$V$6+W53*$W$6+X53*$X$6) -> 9729 | Z53: =(Y53*5%) -> 486.45 | AA53: =SUM(Y53+Z53) -> 10215.45 | AB53: 33272
A54: 42208 | B54: 40 | C54: 6 | D54: 5.5 | E54: 12 | F54: 33 | L54: 1 | M54: 4 | N54: 2 | P54: 33 | Q54: 265 | R54: =L54+J54+I54+H54+G54+F54+E54+D54+C54 -> 57.5 | T54: =Q54 -> 265 | U54: 4 | Y54: =SUM(C54*$C$6+D54*$D$6+E54*$E$6+F54*$F$6+G54*$G$6+H54*$H$6+I54*$I$6+J54*$J$6+K54*$K$6+L54*$L$6+M54*$M$6+N54*$N$6+O54*$O$6+P54*$P$6+Q54*$Q$6+U54*$U$6+V54*$V$6+W54*$W$6+X54*$X$6) -> 10089 | Z54: =(Y54*5%) -> 504.45 | AA54: =SUM(Y54+Z54) -> 10593.45 | AB54: 33272
A55: 42209 | B55: 41 Revised | C55: 3 | D55: 4 | E55: 10 | F55: 36 | L55: 2 | M55: 4 | N55: 2 | P55: 36 | Q55: 250 | R55: =L55+J55+I55+H55+G55+F55+E55+D55+C55 -> 55 | T55: =Q55 -> 250 | Y55: =SUM(C55*$C$6+D55*$D$6+E55*$E$6+F55*$F$6+G55*$G$6+H55*$H$6+I55*$I$6+J55*$J$6+K55*$K$6+L55*$L$6+M55*$M$6+N55*$N$6+O55*$O$6+P55*$P$6+Q55*$Q$6+U55*$U$6+V55*$V$6+W55*$W$6+X55*$X$6) -> 9790.5 | Z55: =(Y55*5%) -> 489.525 | AA55: =SUM(Y55+Z55) -> 10280.025 | AB55: 33272
A56: 42210 | B56: 42 | C56: 2 | E56: 12 | F56: 33.5 | M56: 4 | N56: 2 | P56: 33.5 | Q56: 265 | R56: =L56+J56+I56+H56+G56+F56+E56+D56+C56 -> 47.5 | T56: =Q56 -> 265 | Y56: =SUM(C56*$C$6+D56*$D$6+E56*$E$6+F56*$F$6+G56*$G$6+H56*$H$6+I56*$I$6+J56*$J$6+K56*$K$6+L56*$L$6+M56*$M$6+N56*$N$6+O56*$O$6+P56*$P$6+Q56*$Q$6+U56*$U$6+V56*$V$6+W56*$W$6+X56*$X$6) -> 8917 | Z56: =(Y56*5%) -> 445.85 | AA56: =SUM(Y56+Z56) -> 9362.85 | AB56: 33272
A57: 42211 | B57: 43 Revised | G57: 8 | L57: 1.5 | R57: =L57+J57+I57+H57+G57+F57+E57+D57+C57 -> 9.5 | T57: =Q57 -> 0 | Y57: =SUM(C57*$C$6+D57*$D$6+E57*$E$6+F57*$F$6+G57*$G$6+H57*$H$6+I57*$I$6+J57*$J$6+K57*$K$6+L57*$L$6+M57*$M$6+N57*$N$6+O57*$O$6+P57*$P$6+Q57*$Q$6+U57*$U$6+V57*$V$6+W57*$W$6+X57*$X$6) -> 888.75 | Z57: =(Y57*5%) -> 44.4375 | AA57: =SUM(Y57+Z57) -> 933.1875 | AB57: 33272
A58: 42212 | B58: 44 Revised | C58: 7 | D58: 11 | E58: 12 | F58: 47 | G58: 12 | M58: 7 | N58: 3 | P58: 59 | Q58: 258 | R58: =L58+J58+I58+H58+G58+F58+E58+D58+C58 -> 89 | T58: =Q58 -> 258 | U58: 2 | Y58: =SUM(C58*$C$6+D58*$D$6+E58*$E$6+F58*$F$6+G58*$G$6+H58*$H$6+I58*$I$6+J58*$J$6+K58*$K$6+L58*$L$6+M58*$M$6+N58*$N$6+O58*$O$6+P58*$P$6+Q58*$Q$6+U58*$U$6+V58*$V$6+W58*$W$6+X58*$X$6) -> 15067.3 | Z58: =(Y58*5%) -> 753.365 | AA58: =SUM(Y58+Z58) -> 15820.665 | AB58: 33272
A59: 42213 | B59: 45 Revised | C59: 11 | D59: 7.75 | E59: 12 | F59: 46.5 | G59: 11 | L59: 1 | M59: 6 | N59: 2 | O59: 1 | P59: 69.5 | R59: =L59+J59+I59+H59+G59+F59+E59+D59+C59 -> 89.25 | T59: =Q59 -> 0 | Y59: =SUM(C59*$C$6+D59*$D$6+E59*$E$6+F59*$F$6+G59*$G$6+H59*$H$6+I59*$I$6+J59*$J$6+K59*$K$6+L59*$L$6+M59*$M$6+N59*$N$6+O59*$O$6+P59*$P$6+Q59*$Q$6+U59*$U$6+V59*$V$6+W59*$W$6+X59*$X$6) -> 14526 | Z59: =(Y59*5%) -> 726.3 | AA59: =SUM(Y59+Z59) -> 15252.3 | AB59: 33272
A60: 42214 | B60: 46 | C60: 10 | D60: 9.25 | E60: 12 | F60: 57 | L60: 1 | M60: 6 | N60: 2 | O60: 1 | P60: 57 | Q60: 293 | R60: =L60+J60+I60+H60+G60+F60+E60+D60+C60 -> 89.25 | T60: =Q60 -> 293 | Y60: =SUM(C60*$C$6+D60*$D$6+E60*$E$6+F60*$F$6+G60*$G$6+H60*$H$6+I60*$I$6+J60*$J$6+K60*$K$6+L60*$L$6+M60*$M$6+N60*$N$6+O60*$O$6+P60*$P$6+Q60*$Q$6+U60*$U$6+V60*$V$6+W60*$W$6+X60*$X$6) -> 15123.3 | Z60: =(Y60*5%) -> 756.165 | AA60: =SUM(Y60+Z60) -> 15879.465 | AB60: 33272
A61: 42215 | B61: 47 | C61: 10 | D61: 3 | E61: 11 | F61: 46.5 | L61: 3 | M61: 4 | N61: 1 | O61: 1 | P61: 45.5 | Q61: 268 | R61: =L61+J61+I61+H61+G61+F61+E61+D61+C61 -> 73.5 | T61: =Q61 -> 268 | Y61: =SUM(C61*$C$6+D61*$D$6+E61*$E$6+F61*$F$6+G61*$G$6+H61*$H$6+I61*$I$6+J61*$J$6+K61*$K$6+L61*$L$6+M61*$M$6+N61*$N$6+O61*$O$6+P61*$P$6+Q61*$Q$6+U61*$U$6+V61*$V$6+W61*$W$6+X61*$X$6) -> 12078.3 | Z61: =(Y61*5%) -> 603.915 | AA61: =SUM(Y61+Z61) -> 12682.215 | AB61: 33272
A62: 42216 | B62: 48 Revised | C62: 4 | E62: 10 | F62: 31.5 | L62: 2 | M62: 4 | N62: 2 | P62: 19.5 | Q62: 508 | R62: =L62+J62+I62+H62+G62+F62+E62+D62+C62 -> 47.5 | T62: =Q62 -> 508 | Y62: =SUM(C62*$C$6+D62*$D$6+E62*$E$6+F62*$F$6+G62*$G$6+H62*$H$6+I62*$I$6+J62*$J$6+K62*$K$6+L62*$L$6+M62*$M$6+N62*$N$6+O62*$O$6+P62*$P$6+Q62*$Q$6+U62*$U$6+V62*$V$6+W62*$W$6+X62*$X$6) -> 8781.3 | Z62: =(Y62*5%) -> 439.065 | AA62: =SUM(Y62+Z62) -> 9220.365 | AB62: 33272
A63: 42216 | B63: ipads | S63: 2400 | Y63: =SUM(C63*$C$6+D63*$D$6+E63*$E$6+F63*$F$6+G63*$G$6+H63*$H$6+I63*$I$6+J63*$J$6+K63*$K$6+L63*$L$6+M63*$M$6+N63*$N$6+O63*$O$6+P63*$P$6+Q63*$Q$6+U63*$U$6+V63*$V$6+W63*$W$6+X63*$X$6)+S63 -> 2400 | Z63: =(Y63*5%) -> 120 | AA63: =SUM(Y63+Z63) -> 2520 | AB63: 33272
A64: 42216 | B64: Expenses | S64: 124 | Y64: =SUM(C64*$C$6+D64*$D$6+E64*$E$6+F64*$F$6+G64*$G$6+H64*$H$6+I64*$I$6+J64*$J$6+K64*$K$6+L64*$L$6+M64*$M$6+N64*$N$6+O64*$O$6+P64*$P$6+Q64*$Q$6+U64*$U$6+V64*$V$6+W64*$W$6+X64*$X$6)+S64 -> 124 | Z64: =(Y64*5%) -> 6.2 | AA64: =SUM(Y64+Z64) -> 130.2 | AB64: 33272
A65: 42217 | B65: 49 | F65: 33 | M65: 4 | N65: 2 | P65: 12 | Q65: 513 | R65: =L65+J65+I65+H65+G65+F65+E65+D65+C65 -> 33 | T65: =Q65 -> 513 | Y65: =SUM(C65*$C$6+D65*$D$6+E65*$E$6+F65*$F$6+G65*$G$6+H65*$H$6+I65*$I$6+J65*$J$6+K65*$K$6+L65*$L$6+M65*$M$6+N65*$N$6+O65*$O$6+P65*$P$6+Q65*$Q$6+U65*$U$6+V65*$V$6+W65*$W$6+X65*$X$6) -> 7192.3 | Z65: =(Y65*5%) -> 359.615 | AA65: =SUM(Y65+Z65) -> 7551.915 | AB65: 33529
A66: 42218 | B66: 50 | G66: =12+9.5 -> 21.5 | R66: =L66+J66+I66+H66+G66+F66+E66+D66+C66 -> 21.5 | T66: =Q66 -> 0 | Y66: =SUM(C66*$C$6+D66*$D$6+E66*$E$6+F66*$F$6+G66*$G$6+H66*$H$6+I66*$I$6+J66*$J$6+K66*$K$6+L66*$L$6+M66*$M$6+N66*$N$6+O66*$O$6+P66*$P$6+Q66*$Q$6+U66*$U$6+V66*$V$6+W66*$W$6+X66*$X$6) -> 1935 | Z66: =(Y66*5%) -> 96.75 | AA66: =SUM(Y66+Z66) -> 2031.75 | AB66: 33529
A67: 42219 | B67: 51 | C67: 4 | E67: 8 | F67: =12+12+12 -> 36 | M67: 2 | N67: 2 | P67: 24 | Q67: 508 | R67: =L67+J67+I67+H67+G67+F67+E67+D67+C67 -> 48 | T67: =Q67 -> 508 | Y67: =SUM(C67*$C$6+D67*$D$6+E67*$E$6+F67*$F$6+G67*$G$6+H67*$H$6+I67*$I$6+J67*$J$6+K67*$K$6+L67*$L$6+M67*$M$6+N67*$N$6+O67*$O$6+P67*$P$6+Q67*$Q$6+U67*$U$6+V67*$V$6+W67*$W$6+X67*$X$6) -> 8800.8 | Z67: =(Y67*5%) -> 440.04 | AA67: =SUM(Y67+Z67) -> 9240.84 | AB67: 33529
A68: 42220 | B68: 52 | C68: 12 | D68: 2 | E68: 12 | F68: =12+13+11.5 -> 36.5 | L68: 1 | N68: 2 | P68: 11.5 | Q68: =299+280+280 -> 859 | R68: =L68+J68+I68+H68+G68+F68+E68+D68+C68 -> 63.5 | T68: =Q68 -> 859 | Y68: =SUM(C68*$C$6+D68*$D$6+E68*$E$6+F68*$F$6+G68*$G$6+H68*$H$6+I68*$I$6+J68*$J$6+K68*$K$6+L68*$L$6+M68*$M$6+N68*$N$6+O68*$O$6+P68*$P$6+Q68*$Q$6+U68*$U$6+V68*$V$6+W68*$W$6+X68*$X$6) -> 10133.9 | Z68: =(Y68*5%) -> 506.695 | AA68: =SUM(Y68+Z68) -> 10640.595 | AB68: 33529
A69: 42221 | B69: 53 | D69: 1 | E69: 12 | F69: =12+12+12+12.5 -> 48.5 | I69: 12 | L69: 2.5 | M69: 2 | N69: 2 | O69: 1 | P69: 48 | Q69: 331 | R69: =L69+J69+I69+H69+G69+F69+E69+D69+C69 -> 76 | T69: =Q69 -> 331 | Y69: =SUM(C69*$C$6+D69*$D$6+E69*$E$6+F69*$F$6+G69*$G$6+H69*$H$6+I69*$I$6+J69*$J$6+K69*$K$6+L69*$L$6+M69*$M$6+N69*$N$6+O69*$O$6+P69*$P$6+Q69*$Q$6+U69*$U$6+V69*$V$6+W69*$W$6+X69*$X$6) -> 12749.35 | Z69: =(Y69*5%) -> 637.4675 | AA69: =SUM(Y69+Z69) -> 13386.818 | AB69: 33529
A70: 42222 | B70: 54 | C70: 8 | D70: 3 | E70: 11 | F70: 47.5 | L70: 1 | M70: 2 | N70: 3 | P70: 58.5 | R70: =L70+J70+I70+H70+G70+F70+E70+D70+C70 -> 70.5 | T70: =Q70 -> 0 | Y70: =SUM(C70*$C$6+D70*$D$6+E70*$E$6+F70*$F$6+G70*$G$6+H70*$H$6+I70*$I$6+J70*$J$6+K70*$K$6+L70*$L$6+M70*$M$6+N70*$N$6+O70*$O$6+P70*$P$6+Q70*$Q$6+U70*$U$6+V70*$V$6+W70*$W$6+X70*$X$6) -> 12262.5 | Z70: =(Y70*5%) -> 613.125 | AA70: =SUM(Y70+Z70) -> 12875.625 | AB70: 33529
A71: 42223 | B71: 55 | D71: 3 | E71: 12 | F71: =9.5+12+12+11 -> 44.5 | I71: 6 | M71: 2 | N71: 2 | O71: 1 | P71: =9.5+12+12+11 -> 44.5 | Q71: 286 | R71: =L71+J71+I71+H71+G71+F71+E71+D71+C71 -> 65.5 | T71: =Q71 -> 286 | Y71: =SUM(C71*$C$6+D71*$D$6+E71*$E$6+F71*$F$6+G71*$G$6+H71*$H$6+I71*$I$6+J71*$J$6+K71*$K$6+L71*$L$6+M71*$M$6+N71*$N$6+O71*$O$6+P71*$P$6+Q71*$Q$6+U71*$U$6+V71*$V$6+W71*$W$6+X71*$X$6) -> 11375.1 | Z71: =(Y71*5%) -> 568.755 | AA71: =SUM(Y71+Z71) -> 11943.855 | AB71: 33529
A72: 42224 | B72: 56 | C72: 5 | E72: 11 | F72: 45.5 | N72: 2 | P72: 44.5 | Q72: 285 | R72: =L72+J72+I72+H72+G72+F72+E72+D72+C72 -> 61.5 | T72: =Q72 -> 285 | Y72: =SUM(C72*$C$6+D72*$D$6+E72*$E$6+F72*$F$6+G72*$G$6+H72*$H$6+I72*$I$6+J72*$J$6+K72*$K$6+L72*$L$6+M72*$M$6+N72*$N$6+O72*$O$6+P72*$P$6+Q72*$Q$6+U72*$U$6+V72*$V$6+W72*$W$6+X72*$X$6) -> 10500 | Z72: =(Y72*5%) -> 525 | AA72: =SUM(Y72+Z72) -> 11025 | AB72: 33529
A73: 42225 | B73: 57 | G73: 12 | R73: =L73+J73+I73+H73+G73+F73+E73+D73+C73 -> 12 | T73: =Q73 -> 0 | Y73: =SUM(C73*$C$6+D73*$D$6+E73*$E$6+F73*$F$6+G73*$G$6+H73*$H$6+I73*$I$6+J73*$J$6+K73*$K$6+L73*$L$6+M73*$M$6+N73*$N$6+O73*$O$6+P73*$P$6+Q73*$Q$6+U73*$U$6+V73*$V$6+W73*$W$6+X73*$X$6) -> 1080 | Z73: =(Y73*5%) -> 54 | AA73: =SUM(Y73+Z73) -> 1134 | AB73: 33529
A74: 42226 | B74: 58 | C74: 18 | D74: 1.5 | E74: 12 | F74: 45.5 | K74: 1 | L74: 6 | M74: 2 | N74: 2 | P74: 24 | Q74: 1358 | R74: =L74+J74+I74+H74+G74+F74+E74+D74+C74 -> 83 | T74: =Q74 -> 1358 | U74: 0.25 | Y74: =SUM(C74*$C$6+D74*$D$6+E74*$E$6+F74*$F$6+G74*$G$6+H74*$H$6+I74*$I$6+J74*$J$6+K74*$K$6+L74*$L$6+M74*$M$6+N74*$N$6+O74*$O$6+P74*$P$6+Q74*$Q$6+U74*$U$6+V74*$V$6+W74*$W$6+X74*$X$6) -> 13917.675 | Z74: =(Y74*5%) -> 695.88375 | AA74: =SUM(Y74+Z74) -> 14613.559 | AB74: 33529
A75: 42227 | B75: 59 | C75: 12 | D75: 4 | E75: 14 | F75: 37 | K75: 1 | N75: 2 | P75: 39 | Q75: 595 | R75: =L75+J75+I75+H75+G75+F75+E75+D75+C75 -> 67 | T75: =Q75 -> 595 | U75: 4 | Y75: =SUM(C75*$C$6+D75*$D$6+E75*$E$6+F75*$F$6+G75*$G$6+H75*$H$6+I75*$I$6+J75*$J$6+K75*$K$6+L75*$L$6+M75*$M$6+N75*$N$6+O75*$O$6+P75*$P$6+Q75*$Q$6+U75*$U$6+V75*$V$6+W75*$W$6+X75*$X$6) -> 11342.5 | Z75: =(Y75*5%) -> 567.125 | AA75: =SUM(Y75+Z75) -> 11909.625 | AB75: 33529
A76: 42228 | B76: 60 | C76: 12 | E76: 12 | F76: 51 | I76: 8 | L76: 5.5 | M76: 2 | N76: 2 | P76: 37 | Q76: 1676 | R76: =L76+J76+I76+H76+G76+F76+E76+D76+C76 -> 88.5 | T76: =Q76 -> 1676 | U76: 2 | Y76: =SUM(C76*$C$6+D76*$D$6+E76*$E$6+F76*$F$6+G76*$G$6+H76*$H$6+I76*$I$6+J76*$J$6+K76*$K$6+L76*$L$6+M76*$M$6+N76*$N$6+O76*$O$6+P76*$P$6+Q76*$Q$6+U76*$U$6+V76*$V$6+W76*$W$6+X76*$X$6) -> 15224.35 | Z76: =(Y76*5%) -> 761.2175 | AA76: =SUM(Y76+Z76) -> 15985.568 | AB76: 33529
A77: 42229 | B77: 61 | C77: 8 | D77: 6 | E77: 12 | F77: 36.5 | G77: 12 | I77: 4 | L77: 12 | M77: 2 | N77: 2 | P77: 35.5 | Q77: 1079 | R77: =L77+J77+I77+H77+G77+F77+E77+D77+C77 -> 90.5 | T77: =Q77 -> 1079 | Y77: =SUM(C77*$C$6+D77*$D$6+E77*$E$6+F77*$F$6+G77*$G$6+H77*$H$6+I77*$I$6+J77*$J$6+K77*$K$6+L77*$L$6+M77*$M$6+N77*$N$6+O77*$O$6+P77*$P$6+Q77*$Q$6+U77*$U$6+V77*$V$6+W77*$W$6+X77*$X$6) -> 13905.4 | Z77: =(Y77*5%) -> 695.27 | AA77: =SUM(Y77+Z77) -> 14600.67 | AB77: 33529
A78: 42230 | B78: 62 | C78: 9 | E78: 11 | F78: 33 | G78: 16.5 | M78: 2 | N78: 3 | P78: 44 | Q78: 474 | R78: =L78+J78+I78+H78+G78+F78+E78+D78+C78 -> 69.5 | T78: =Q78 -> 474 | Y78: =SUM(C78*$C$6+D78*$D$6+E78*$E$6+F78*$F$6+G78*$G$6+H78*$H$6+I78*$I$6+J78*$J$6+K78*$K$6+L78*$L$6+M78*$M$6+N78*$N$6+O78*$O$6+P78*$P$6+Q78*$Q$6+U78*$U$6+V78*$V$6+W78*$W$6+X78*$X$6) -> 11559.4 | Z78: =(Y78*5%) -> 577.97 | AA78: =SUM(Y78+Z78) -> 12137.37 | AB78: 33529
A79: 42231 | B79: 63 | E79: 10 | F79: 35 | G79: 11 | M79: 1 | N79: 3 | P79: 46 | Q79: 230 | R79: =L79+J79+I79+H79+G79+F79+E79+D79+C79 -> 56 | T79: =Q79 -> 230 | Y79: =SUM(C79*$C$6+D79*$D$6+E79*$E$6+F79*$F$6+G79*$G$6+H79*$H$6+I79*$I$6+J79*$J$6+K79*$K$6+L79*$L$6+M79*$M$6+N79*$N$6+O79*$O$6+P79*$P$6+Q79*$Q$6+U79*$U$6+V79*$V$6+W79*$W$6+X79*$X$6) -> 10026 | Z79: =(Y79*5%) -> 501.3 | AA79: =SUM(Y79+Z79) -> 10527.3 | AB79: 33529
A80: 42232 | R80: =L80+J80+I80+H80+G80+F80+E80+D80+C80 -> 0 | T80: =Q80 -> 0 | Y80: =SUM(C80*$C$6+D80*$D$6+E80*$E$6+F80*$F$6+G80*$G$6+H80*$H$6+I80*$I$6+J80*$J$6+K80*$K$6+L80*$L$6+M80*$M$6+N80*$N$6+O80*$O$6+P80*$P$6+Q80*$Q$6+U80*$U$6+V80*$V$6+W80*$W$6+X80*$X$6) -> 0 | Z80: =(Y80*5%) -> 0 | AA80: =SUM(Y80+Z80) -> 0 | AB80: 33529
A81: 42233 | B81: 64 | C81: 22 | E81: 12 | F81: 48.5 | N81: 3 | P81: 48 | Q81: 268 | R81: =L81+J81+I81+H81+G81+F81+E81+D81+C81 -> 82.5 | T81: =Q81 -> 268 | U81: 2 | Y81: =SUM(C81*$C$6+D81*$D$6+E81*$E$6+F81*$F$6+G81*$G$6+H81*$H$6+I81*$I$6+J81*$J$6+K81*$K$6+L81*$L$6+M81*$M$6+N81*$N$6+O81*$O$6+P81*$P$6+Q81*$Q$6+U81*$U$6+V81*$V$6+W81*$W$6+X81*$X$6) -> 13338.8 | Z81: =(Y81*5%) -> 666.94 | AA81: =SUM(Y81+Z81) -> 14005.74 | AB81: 33529
A82: 42234 | B82: 65 | C82: 5 | D82: 1 | E82: 12 | F82: =13+13+12+12 -> 50 | N82: 3 | P82: 49 | Q82: 277 | R82: =L82+J82+I82+H82+G82+F82+E82+D82+C82 -> 68 | T82: =Q82 -> 277 | Y82: =SUM(C82*$C$6+D82*$D$6+E82*$E$6+F82*$F$6+G82*$G$6+H82*$H$6+I82*$I$6+J82*$J$6+K82*$K$6+L82*$L$6+M82*$M$6+N82*$N$6+O82*$O$6+P82*$P$6+Q82*$Q$6+U82*$U$6+V82*$V$6+W82*$W$6+X82*$X$6) -> 11936.2 | Z82: =(Y82*5%) -> 596.81 | AA82: =SUM(Y82+Z82) -> 12533.01 | AB82: 33529
A83: 42235 | B83: 66 | C83: 10 | D83: 5.5 | E83: 12 | F83: =10.5+12+16 -> 38.5 | G83: =14+10.5 -> 24.5 | J83: 1 | N83: 3 | O83: 1 | P83: =10.5+14+12+16+10.5+1 -> 64 | Q83: 262 | R83: =L83+J83+I83+H83+G83+F83+E83+D83+C83 -> 91.5 | T83: =Q83 -> 262 | U83: 0.25 | Y83: =SUM(C83*$C$6+D83*$D$6+E83*$E$6+F83*$F$6+G83*$G$6+H83*$H$6+I83*$I$6+J83*$J$6+K83*$K$6+L83*$L$6+M83*$M$6+N83*$N$6+O83*$O$6+P83*$P$6+Q83*$Q$6+U83*$U$6+V83*$V$6+W83*$W$6+X83*$X$6) -> 14048.075 | Z83: =(Y83*5%) -> 702.40375 | AA83: =SUM(Y83+Z83) -> 14750.479 | AB83: 33529
A84: 42236 | B84: 67 | E84: 13 | F84: 46 | M84: 2 | N84: 3 | P84: =11+12.5+10.5+13 -> 47 | Q84: 261 | R84: =L84+J84+I84+H84+G84+F84+E84+D84+C84 -> 59 | T84: =Q84 -> 261 | Y84: =SUM(C84*$C$6+D84*$D$6+E84*$E$6+F84*$F$6+G84*$G$6+H84*$H$6+I84*$I$6+J84*$J$6+K84*$K$6+L84*$L$6+M84*$M$6+N84*$N$6+O84*$O$6+P84*$P$6+Q84*$Q$6+U84*$U$6+V84*$V$6+W84*$W$6+X84*$X$6) -> 11137.6 | Z84: =(Y84*5%) -> 556.88 | AA84: =SUM(Y84+Z84) -> 11694.48 | AB84: 33529
A85: 42237 | B85: 68 | D85: 1 | E85: 11 | F85: 47.5 | M85: 2 | N85: 3 | P85: 58.5 | Q85: 0 | R85: =L85+J85+I85+H85+G85+F85+E85+D85+C85 -> 59.5 | T85: =Q85 -> 0 | Y85: =SUM(C85*$C$6+D85*$D$6+E85*$E$6+F85*$F$6+G85*$G$6+H85*$H$6+I85*$I$6+J85*$J$6+K85*$K$6+L85*$L$6+M85*$M$6+N85*$N$6+O85*$O$6+P85*$P$6+Q85*$Q$6+U85*$U$6+V85*$V$6+W85*$W$6+X85*$X$6) -> 11214 | Z85: =(Y85*5%) -> 560.7 | AA85: =SUM(Y85+Z85) -> 11774.7 | AB85: 33529
A86: 42238 | B86: 69 | F86: 23 | G86: 21.5 | N86: 3 | P86: 22.5 | Q86: 531 | R86: =L86+J86+I86+H86+G86+F86+E86+D86+C86 -> 44.5 | T86: =Q86 -> 531 | Y86: =SUM(C86*$C$6+D86*$D$6+E86*$E$6+F86*$F$6+G86*$G$6+H86*$H$6+I86*$I$6+J86*$J$6+K86*$K$6+L86*$L$6+M86*$M$6+N86*$N$6+O86*$O$6+P86*$P$6+Q86*$Q$6+U86*$U$6+V86*$V$6+W86*$W$6+X86*$X$6) -> 7848.6 | Z86: =(Y86*5%) -> 392.43 | AA86: =SUM(Y86+Z86) -> 8241.03 | AB86: 33529
A87: 42239 | B87: 70 | G87: 15 | R87: =L87+J87+I87+H87+G87+F87+E87+D87+C87 -> 15 | T87: =Q87 -> 0 | Y87: =SUM(C87*$C$6+D87*$D$6+E87*$E$6+F87*$F$6+G87*$G$6+H87*$H$6+I87*$I$6+J87*$J$6+K87*$K$6+L87*$L$6+M87*$M$6+N87*$N$6+O87*$O$6+P87*$P$6+Q87*$Q$6+U87*$U$6+V87*$V$6+W87*$W$6+X87*$X$6) -> 1350 | Z87: =(Y87*5%) -> 67.5 | AA87: =SUM(Y87+Z87) -> 1417.5 | AB87: 33529
A88: 42240 | B88: 71 | C88: 10 | D88: 0.5 | E88: 12 | F88: 46.5 | G88: 10.5 | M88: 2 | N88: 3 | P88: 45.5 | Q88: 509 | R88: =L88+J88+I88+H88+G88+F88+E88+D88+C88 -> 79.5 | T88: =Q88 -> 509 | Y88: =SUM(C88*$C$6+D88*$D$6+E88*$E$6+F88*$F$6+G88*$G$6+H88*$H$6+I88*$I$6+J88*$J$6+K88*$K$6+L88*$L$6+M88*$M$6+N88*$N$6+O88*$O$6+P88*$P$6+Q88*$Q$6+U88*$U$6+V88*$V$6+W88*$W$6+X88*$X$6) -> 13279.4 | Z88: =(Y88*5%) -> 663.97 | AA88: =SUM(Y88+Z88) -> 13943.37 | AB88: 33529
A89: 42241 | B89: 72 | C89: 11 | E89: 11.5 | F89: 48.5 | G89: 10 | M89: 2 | N89: 1 | O89: 3 | P89: 59 | Q89: 263 | R89: =L89+J89+I89+H89+G89+F89+E89+D89+C89 -> 81 | T89: =Q89 -> 263 | Y89: =SUM(C89*$C$6+D89*$D$6+E89*$E$6+F89*$F$6+G89*$G$6+H89*$H$6+I89*$I$6+J89*$J$6+K89*$K$6+L89*$L$6+M89*$M$6+N89*$N$6+O89*$O$6+P89*$P$6+Q89*$Q$6+U89*$U$6+V89*$V$6+W89*$W$6+X89*$X$6) -> 13310.05 | Z89: =(Y89*5%) -> 665.5025 | AA89: =SUM(Y89+Z89) -> 13975.552 | AB89: 33529
A90: 42242 | B90: 73 | C90: 11 | E90: 13 | F90: 47 | G90: 8 | N90: 2 | O90: 1 | P90: 56 | Q90: 284 | R90: =L90+J90+I90+H90+G90+F90+E90+D90+C90 -> 79 | T90: =Q90 -> 284 | Y90: =SUM(C90*$C$6+D90*$D$6+E90*$E$6+F90*$F$6+G90*$G$6+H90*$H$6+I90*$I$6+J90*$J$6+K90*$K$6+L90*$L$6+M90*$M$6+N90*$N$6+O90*$O$6+P90*$P$6+Q90*$Q$6+U90*$U$6+V90*$V$6+W90*$W$6+X90*$X$6) -> 12723.4 | Z90: =(Y90*5%) -> 636.17 | AA90: =SUM(Y90+Z90) -> 13359.57 | AB90: 33529
A91: 42243 | B91: 74 | D91: 1.5 | E91: 12 | F91: =10+12+4+8+12 -> 46 | M91: 2 | N91: 2 | O91: 1 | P91: =46+12 -> 58 | R91: =L91+J91+I91+H91+G91+F91+E91+D91+C91 -> 59.5 | T91: =Q91 -> 0 | Y91: =SUM(C91*$C$6+D91*$D$6+E91*$E$6+F91*$F$6+G91*$G$6+H91*$H$6+I91*$I$6+J91*$J$6+K91*$K$6+L91*$L$6+M91*$M$6+N91*$N$6+O91*$O$6+P91*$P$6+Q91*$Q$6+U91*$U$6+V91*$V$6+W91*$W$6+X91*$X$6) -> 10885 | Z91: =(Y91*5%) -> 544.25 | AA91: =SUM(Y91+Z91) -> 11429.25 | AB91: 33529
A92: 42244 | B92: 75 | D92: 2 | E92: 12 | F92: =10.5+12+14+13 -> 49.5 | I92: 8 | M92: 1 | N92: 3 | P92: =49.5+12 -> 61.5 | R92: =L92+J92+I92+H92+G92+F92+E92+D92+C92 -> 71.5 | T92: =Q92 -> 0 | Y92: =SUM(C92*$C$6+D92*$D$6+E92*$E$6+F92*$F$6+G92*$G$6+H92*$H$6+I92*$I$6+J92*$J$6+K92*$K$6+L92*$L$6+M92*$M$6+N92*$N$6+O92*$O$6+P92*$P$6+Q92*$Q$6+U92*$U$6+V92*$V$6+W92*$W$6+X92*$X$6) -> 12370.5 | Z92: =(Y92*5%) -> 618.525 | AA92: =SUM(Y92+Z92) -> 12989.025 | AB92: 33529
A93: 42245 | B93: 76 | E93: 5 | F93: =11+12+12+11 -> 46 | I93: 12 | M93: 2 | N93: 2 | O93: 1 | P93: 46 | Q93: 175 | R93: =L93+J93+I93+H93+G93+F93+E93+D93+C93 -> 63 | T93: =Q93 -> 175 | Y93: =SUM(C93*$C$6+D93*$D$6+E93*$E$6+F93*$F$6+G93*$G$6+H93*$H$6+I93*$I$6+J93*$J$6+K93*$K$6+L93*$L$6+M93*$M$6+N93*$N$6+O93*$O$6+P93*$P$6+Q93*$Q$6+U93*$U$6+V93*$V$6+W93*$W$6+X93*$X$6) -> 11076 | Z93: =(Y93*5%) -> 553.8 | AA93: =SUM(Y93+Z93) -> 11629.8 | AB93: 33529
A94: 42246 | B94: 77 | G94: 10 | R94: =L94+J94+I94+H94+G94+F94+E94+D94+C94 -> 10 | T94: =Q94 -> 0 | Y94: =SUM(C94*$C$6+D94*$D$6+E94*$E$6+F94*$F$6+G94*$G$6+H94*$H$6+I94*$I$6+J94*$J$6+K94*$K$6+L94*$L$6+M94*$M$6+N94*$N$6+O94*$O$6+P94*$P$6+Q94*$Q$6+U94*$U$6+V94*$V$6+W94*$W$6+X94*$X$6) -> 900 | Z94: =(Y94*5%) -> 45 | AA94: =SUM(Y94+Z94) -> 945 | AB94: 33529
A95: 42247 | B95: 78 | D95: 1 | E95: 11 | F95: =12.5+12+12+10.5 -> 47 | I95: 12 | L95: 2 | N95: 2 | P95: =47+11 -> 58 | R95: =L95+J95+I95+H95+G95+F95+E95+D95+C95 -> 73 | T95: =Q95 -> 0 | U95: 2.25 | Y95: =SUM(C95*$C$6+D95*$D$6+E95*$E$6+F95*$F$6+G95*$G$6+H95*$H$6+I95*$I$6+J95*$J$6+K95*$K$6+L95*$L$6+M95*$M$6+N95*$N$6+O95*$O$6+P95*$P$6+Q95*$Q$6+U95*$U$6+V95*$V$6+W95*$W$6+X95*$X$6) -> 11841.375 | Z95: =(Y95*5%) -> 592.06875 | AA95: =SUM(Y95+Z95) -> 12433.444 | AB95: 33529
A96: 42247 | B96: iPads | S96: 2079.68 | Y96: =SUM(C96*$C$6+D96*$D$6+E96*$E$6+F96*$F$6+G96*$G$6+H96*$H$6+I96*$I$6+J96*$J$6+K96*$K$6+L96*$L$6+M96*$M$6+N96*$N$6+O96*$O$6+P96*$P$6+Q96*$Q$6+U96*$U$6+V96*$V$6+W96*$W$6+X96*$X$6)+S96 -> 2079.68 | Z96: =(Y96*5%) -> 103.984 | AA96: =SUM(Y96+Z96) -> 2183.664 | AB96: 33529
A97: 42248 | B97: 79 | C97: 12 | D97: 2.5 | E97: 10 | F97: =11+10+12+12 -> 45 | L97: 4 | N97: 3 | P97: 45 | Q97: 265 | R97: =L97+J97+I97+H97+G97+F97+E97+D97+C97 -> 73.5 | T97: =Q97 -> 265 | Y97: =SUM(C97*$C$6+D97*$D$6+E97*$E$6+F97*$F$6+G97*$G$6+H97*$H$6+I97*$I$6+J97*$J$6+K97*$K$6+L97*$L$6+M97*$M$6+N97*$N$6+O97*$O$6+P97*$P$6+Q97*$Q$6+U97*$U$6+V97*$V$6+W97*$W$6+X97*$X$6) -> 12150.5 | Z97: =(Y97*5%) -> 607.525 | AA97: =SUM(Y97+Z97) -> 12758.025 | AB97: 33794
A98: 42249 | B98: 80 | C98: 8 | D98: 1 | E98: 12 | F98: =11+12+10 -> 33 | G98: 10 | L98: 5 | N98: 3 | P98: 35 | Q98: 475 | R98: =L98+J98+I98+H98+G98+F98+E98+D98+C98 -> 69 | T98: =Q98 -> 475 | Y98: =SUM(C98*$C$6+D98*$D$6+E98*$E$6+F98*$F$6+G98*$G$6+H98*$H$6+I98*$I$6+J98*$J$6+K98*$K$6+L98*$L$6+M98*$M$6+N98*$N$6+O98*$O$6+P98*$P$6+Q98*$Q$6+U98*$U$6+V98*$V$6+W98*$W$6+X98*$X$6) -> 11130 | Z98: =(Y98*5%) -> 556.5 | AA98: =SUM(Y98+Z98) -> 11686.5 | AB98: 33794
A99: 42250 | B99: 81 | C99: 10 | E99: 12 | F99: =10.5+12+13 -> 35.5 | L99: 5 | N99: 2 | O99: 1 | P99: =35.5+12 -> 47.5 | R99: =L99+J99+I99+H99+G99+F99+E99+D99+C99 -> 62.5 | T99: =Q99 -> 0 | Y99: =SUM(C99*$C$6+D99*$D$6+E99*$E$6+F99*$F$6+G99*$G$6+H99*$H$6+I99*$I$6+J99*$J$6+K99*$K$6+L99*$L$6+M99*$M$6+N99*$N$6+O99*$O$6+P99*$P$6+Q99*$Q$6+U99*$U$6+V99*$V$6+W99*$W$6+X99*$X$6) -> 10204 | Z99: =(Y99*5%) -> 510.2 | AA99: =SUM(Y99+Z99) -> 10714.2 | AB99: 33794
A100: 42251 | B100: 82 | C100: 9 | L100: 5 | R100: =L100+J100+I100+H100+G100+F100+E100+D100+C100 -> 14 | T100: =Q100 -> 0 | Y100: =SUM(C100*$C$6+D100*$D$6+E100*$E$6+F100*$F$6+G100*$G$6+H100*$H$6+I100*$I$6+J100*$J$6+K100*$K$6+L100*$L$6+M100*$M$6+N100*$N$6+O100*$O$6+P100*$P$6+Q100*$Q$6+U100*$U$6+V100*$V$6+W100*$W$6+X100*$X$6) -> 1413 | Z100: =(Y100*5%) -> 70.65 | AA100: =SUM(Y100+Z100) -> 1483.65 | AB100: 33794
A101: 42252 | B101: 83 | C101: 10 | L101: 8 | R101: =L101+J101+I101+H101+G101+F101+E101+D101+C101 -> 18 | T101: =Q101 -> 0 | Y101: =SUM(C101*$C$6+D101*$D$6+E101*$E$6+F101*$F$6+G101*$G$6+H101*$H$6+I101*$I$6+J101*$J$6+K101*$K$6+L101*$L$6+M101*$M$6+N101*$N$6+O101*$O$6+P101*$P$6+Q101*$Q$6+U101*$U$6+V101*$V$6+W101*$W$6+X101*$X$6) -> 1845 | Z101: =(Y101*5%) -> 92.25 | AA101: =SUM(Y101+Z101) -> 1937.25 | AB101: 33794
A102: 42253 | B102: 84 | C102: 3 | R102: =L102+J102+I102+H102+G102+F102+E102+D102+C102 -> 3 | T102: =Q102 -> 0 | Y102: =SUM(C102*$C$6+D102*$D$6+E102*$E$6+F102*$F$6+G102*$G$6+H102*$H$6+I102*$I$6+J102*$J$6+K102*$K$6+L102*$L$6+M102*$M$6+N102*$N$6+O102*$O$6+P102*$P$6+Q102*$Q$6+U102*$U$6+V102*$V$6+W102*$W$6+X102*$X$6) -> 283.5 | Z102: =(Y102*5%) -> 14.175 | AA102: =SUM(Y102+Z102) -> 297.675 | AB102: 33794
...

Sheet Vendor #17
A2: Vendor #17
A4: Date | B4: LEM # | C4: Straight Hours Charged (ea.) | D4: Overtime Hours Charged (ea.) | E4: Manpower | F4: Locate crew hours | G4: Rate | H4: Quad | I4: Rate | J4: Side by side | K4: Rate | L4: Sub | M4: Rate | N4: Digital map | O4: Rate | P4: Labourer class | Q4: Rate | R4: Labourer class | S4: Rate | T4: Labourer class | U4: Rate | V4: Labourer class | W4: Rate | X4: Total Labour Rate per hr | Y4: Total Hours Charged | Z4: Equipment Detail | AA4: Km's Charged | AB4: Subtotal | AC4: GST | AD4: LEM Amount | AE4: Affiliating Invoice | AF4: Approved By | AG4: SUM OF ALL LEM'S (before GST)
AG5: =SUM(AB6:AB100) -> 89327
A6: 42170 | B6: 66960 | E6: 2 | F6: 4 | G6: 182 | I6: 138 | K6: 276 | L6: 2 | M6: 161 | O6: 42 | Q6: 0 | S6: 0 | U6: 0 | W6: 0 | X6: =SUM(Q6,O6,M6,G6) -> 385 | Y6: =(C6+D6)*E6 -> 0 | Z6: Locate crew | AB6: =(F6*G6)+(L6*M6) -> 1050 | AC6: =(AB6*5%) -> 52.5 | AD6: =SUM(AB6+AC6) -> 1102.5 | AE6: 27913
A7: 42171 | B7: 66962 | E7: 2 | F7: 12 | G7: 182 | H7: 2 | I7: 138 | K7: 276 | L7: 2 | M7: 161 | O7: 42 | Q7: 0 | S7: 0 | U7: 0 | W7: 0 | X7: =SUM(Q7,O7,M7,G7) -> 385 | Y7: =(C7+D7)*E7 -> 0 | Z7: Locate crew and quad | AB7: =(F7*G7)+(L7*M7)+(H7*I7) -> 2782 | AC7: =(AB7*5%) -> 139.1 | AD7: =SUM(AB7+AC7) -> 2921.1 | AE7: 27913
A8: 42172 | B8: 66966 | E8: 2 | F8: 4 | G8: 182 | H8: 2 | I8: 138 | K8: 276 | L8: 2 | M8: 161 | O8: 42 | Q8: 0 | S8: 0 | U8: 0 | W8: 0 | X8: =SUM(Q8,O8,M8,G8) -> 385 | Y8: =(C8+D8)*E8 -> 0 | Z8: Locate crew | AB8: =(F8*G8)+(L8*M8)+(H8*I8) -> 1326 | AC8: =(AB8*5%) -> 66.3 | AD8: =SUM(AB8+AC8) -> 1392.3 | AE8: 27913
A9: 42172 | B9: 66967 | E9: 2 | F9: 8 | G9: 182 | I9: 138 | K9: 276 | M9: 161 | N9: 2 | O9: 42 | Q9: 0 | S9: 0 | U9: 0 | W9: 0 | X9: =SUM(Q9,O9,M9,G9) -> 385 | Y9: =(C9+D9)*E9 -> 0 | Z9: Digital maps | AB9: =(F9*G9)+(L9*M9)+(H9*I9)+(N9*O9) -> 1540 | AC9: =(AB9*5%) -> 77 | AD9: =SUM(AB9+AC9) -> 1617 | AE9: 27913
A10: 42173 | B10: 66968 | E10: 2 | F10: 12 | G10: 182 | H10: 2 | I10: 138 | K10: 276 | L10: 2 | M10: 161 | N10: 2 | O10: 42 | Q10: 0 | S10: 0 | U10: 0 | W10: 0 | X10: =SUM(Q10,O10,M10,G10) -> 385 | Y10: =(C10+D10)*E10 -> 0 | Z10: locate crew and dig maps | AB10: =(F10*G10)+(L10*M10)+(H10*I10)+(N10*O10) -> 2866 | AC10: =(AB10*5%) -> 143.3 | AD10: =SUM(AB10+AC10) -> 3009.3 | AE10: 27913
A11: 42174 | B11: 66970 | E11: 2 | F11: 12 | G11: 182 | H11: 2 | I11: 138 | K11: 276 | L11: 2 | M11: 161 | N11: 1 | O11: 42 | Q11: 0 | S11: 0 | U11: 0 | W11: 0 | X11: =SUM(Q11,O11,M11,G11) -> 385 | Y11: =(C11+D11)*E11 -> 0 | Z11: locate crew and dig map | AB11: =(F11*G11)+(L11*M11)+(H11*I11)+(N11*O11) -> 2824 | AC11: =(AB11*5%) -> 141.2 | AD11: =SUM(AB11+AC11) -> 2965.2 | AE11: 27913
A12: 42175 | B12: 66971 | E12: 2 | F12: 12 | G12: 182 | H12: 2 | I12: 138 | K12: 276 | L12: 2 | M12: 161 | N12: 2 | O12: 42 | Q12: 0 | S12: 0 | U12: 0 | W12: 0 | X12: =SUM(Q12,O12,M12,G12) -> 385 | Y12: =(C12+D12)*E12 -> 0 | Z12: locate crew and dig maps | AB12: =(F12*G12)+(L12*M12)+(H12*I12)+(N12*O12) -> 2866 | AC12: =(AB12*5%) -> 143.3 | AD12: =SUM(AB12+AC12) -> 3009.3 | AE12: 27913
A13: 42176 | B13: 66972 | E13: 2 | F13: 12 | G13: 182 | H13: 2 | I13: 138 | K13: 276 | L13: 2 | M13: 161 | N13: 3 | O13: 42 | Q13: 0 | S13: 0 | U13: 0 | W13: 0 | X13: =SUM(Q13,O13,M13,G13) -> 385 | Y13: =(C13+D13)*E13 -> 0 | Z13: Locate crew and dig maps | AB13: =(F13*G13)+(L13*M13)+(H13*I13)+(N13*O13) -> 2908 | AC13: =(AB13*5%) -> 145.4 | AD13: =SUM(AB13+AC13) -> 3053.4 | AE13: 27913
A14: 42176 | B14: 55726 | E14: 2 | F14: 4 | G14: 182 | I14: 138 | K14: 276 | L14: 2 | M14: 161 | O14: 42 | Q14: 0 | S14: 0 | U14: 0 | W14: 0 | X14: =SUM(Q14,O14,M14,G14) -> 385 | Y14: =(C14+D14)*E14 -> 0 | Z14: crew 1 | AB14: =(F14*G14)+(L14*M14)+(H14*I14)+(N14*O14)+(J14*K14) -> 1050 | AC14: =(AB14*5%) -> 52.5 | AD14: =SUM(AB14+AC14) -> 1102.5 | AE14: 27913
A15: 42177 | B15: 66973 | E15: 2 | F15: 12 | G15: 182 | H15: 2 | I15: 138 | K15: 276 | L15: 2 | M15: 161 | N15: 2 | O15: 42 | Q15: 0 | S15: 0 | U15: 0 | W15: 0 | X15: =SUM(Q15,O15,M15,G15) -> 385 | Y15: =(C15+D15)*E15 -> 0 | Z15: crew 1 | AB15: =(F15*G15)+(L15*M15)+(H15*I15)+(N15*O15) -> 2866 | AC15: =(AB15*5%) -> 143.3 | AD15: =SUM(AB15+AC15) -> 3009.3 | AE15: 27913
A16: 42177 | B16: 55727 | E16: 2 | F16: 12 | G16: 182 | I16: 138 | J16: 1 | K16: 276 | L16: 2 | M16: 161 | N16: 1 | O16: 42 | Q16: 0 | S16: 0 | U16: 0 | W16: 0 | X16: =SUM(Q16,O16,M16,G16) -> 385 | Y16: =(C16+D16)*E16 -> 0 | Z16: crew 1 | AB16: =(F16*G16)+(L16*M16)+(H16*I16)+(N16*O16)+(J16*K16) -> 2824 | AC16: =(AB16*5%) -> 141.2 | AD16: =SUM(AB16+AC16) -> 2965.2 | AE16: 27913
A17: 42178 | B17: 66974 | E17: 2 | F17: 12 | G17: 182 | H17: 2 | I17: 138 | K17: 276 | L17: 2 | M17: 161 | N17: 2 | O17: 42 | Q17: 0 | S17: 0 | U17: 0 | W17: 0 | X17: =SUM(Q17,O17,M17,G17) -> 385 | Y17: =(C17+D17)*E17 -> 0 | Z17: crew 1 | AB17: =(F17*G17)+(L17*M17)+(H17*I17)+(N17*O17)+(J17*K17) -> 2866 | AC17: =(AB17*5%) -> 143.3 | AD17: =SUM(AB17+AC17) -> 3009.3 | AE17: 27913
A18: 42178 | B18: 55728 | E18: 2 | F18: 12 | G18: 182 | I18: 138 | J18: 1 | K18: 276 | L18: 2 | M18: 161 | N18: 3 | O18: 42 | Q18: 0 | S18: 0 | U18: 0 | W18: 0 | X18: =SUM(Q18,O18,M18,G18) -> 385 | Y18: =(C18+D18)*E18 -> 0 | Z18: crew 1 | AB18: =(F18*G18)+(L18*M18)+(H18*I18)+(N18*O18)+(J18*K18) -> 2908 | AC18: =(AB18*5%) -> 145.4 | AD18: =SUM(AB18+AC18) -> 3053.4 | AE18: 27913
A19: 42179 | B19: 50531 | E19: 2 | F19: 12 | G19: 182 | I19: 138 | J19: 1 | K19: 276 | L19: 2 | M19: 161 | N19: 2 | O19: 42 | Q19: 0 | S19: 0 | U19: 0 | W19: 0 | X19: =SUM(Q19,O19,M19,G19) -> 385 | Y19: =(C19+D19)*E19 -> 0 | Z19: crew 1 | AB19: =(F19*G19)+(L19*M19)+(H19*I19)+(N19*O19)+(J19*K19) -> 2866 | AC19: =(AB19*5%) -> 143.3 | AD19: =SUM(AB19+AC19) -> 3009.3 | AE19: 27913
A20: 42179 | B20: 66975 | E20: 2 | F20: 12 | G20: 182 | H20: 2 | I20: 138 | K20: 276 | L20: 2 | M20: 161 | N20: 2 | O20: 42 | Q20: 0 | S20: 0 | U20: 0 | W20: 0 | X20: =SUM(Q20,O20,M20,G20) -> 385 | Y20: =(C20+D20)*E20 -> 0 | Z20: crew 1 | AB20: =(F20*G20)+(L20*M20)+(H20*I20)+(N20*O20)+(J20*K20) -> 2866 | AC20: =(AB20*5%) -> 143.3 | AD20: =SUM(AB20+AC20) -> 3009.3 | AE20: 27913
A21: 42180 | B21: 50532 | E21: 2 | F21: 12 | G21: 182 | I21: 138 | J21: 1 | K21: 276 | L21: 2 | M21: 161 | N21: 1 | O21: 42 | Q21: 0 | S21: 0 | U21: 0 | W21: 0 | X21: =SUM(Q21,O21,M21,G21) -> 385 | Y21: =(C21+D21)*E21 -> 0 | Z21: crew 1 | AB21: =(F21*G21)+(L21*M21)+(H21*I21)+(N21*O21)+(J21*K21) -> 2824 | AC21: =(AB21*5%) -> 141.2 | AD21: =SUM(AB21+AC21) -> 2965.2 | AE21: 27913
