Workbook

Sheet Summary
A1: =G11 -> PIPELINE PROJECT
A3: Total Schedule C: | C3: CO | D3: Extra Work | F3: To | G3: 42505
F4: From | G4: 42491
A5: 1.0 Base Lay | B5: ='1.0 BaseLay'!I449 -> 205093.55 | C5: UPI Summary: | D5: =B45 -> 125158.18
A6: 2.1 | B6: ='2.1'!E230 -> 3271.42 | C6: CO 001 | D6: ='CO001'!I496 -> 4394.6202
A7: 2.2 | C7: CO 002 | E7: ='CO002'!C31 -> 50000
A8: 2.3 | B8: ='2.3'!F425 -> 66806.76 | C8: CO 012
A9: 2.11 | C9: CO 015 | D9: ='CO015'!C272 -> 2238.76 | F9: Contractor: | G9: Contractor
A10: 2.14 | C10: CO 017 | F10: Chief Inspector | G10: Construction Manager
A11: 2.18 | C11: CO 019 | F11: Project: | G11: PIPELINE PROJECT
A12: 2.22 | C12: CO 024
A13: 2.27 | C13: CO 027 | E13: ='2.27'!F29 -> 2751.84
A14: 2.29 | C14: CO 030
A15: 2.31 | C15: CO 033
A16: 2.35 | B16: ='2.35'!F32 -> 55080 | C16: CO 038 | D16: ='CO038'!C152 -> 1480.14
A17: 3.1.2-2A | C17: CO 039
A18: 3.2.2-2A | C18: CO 040
C19: CO 052 | D19: ='CO052'!C29 -> 325639.92
C20: CO 053 | D20: ='CO053'!C29 -> 13198.84
C21: CO 054 | D21: ='CO054'!C29 -> 5195.45
C22: CO 055 | D22: ='CO055'!C29 -> 69770.04
C23: CO 056
C24: CO 057
E28: 2770000
A31: Total | B31: =SUM(B5:B30) -> 330251.73 | C31: CO Total: | D31: =SUM(D6:D30) -> 421917.77
B34: Subtotal: | C34: =B31+D31 -> 752169.5
F42: Difference:
A44: 1) Base Lay Total: | B44: =B5 -> 205093.55 | F44: =B45-D45 -> 0
A45: 2) UPI Total: | B45: =SUM(B6:B17) -> 125158.18 | C45: UPI CO: | D45: =D5 -> 125158.18
A46: 3) Incremental LS Total: | B46: =SUM(B17:B18) -> 0
A47: 4) Extra Work Total: | B47: =D31 -> 421917.77
A49: Gross: | B49: =SUM(B44:B48) -> 752169.5
A50: Holdback: | B50: =B49*0.1 -> 75216.95
A51: Subtotal: | B51: =B49-B50 -> 676952.55
A52: GST | B52: =B51*0.05 -> 33847.628
A53: Total: | B53: =SUM(B51:B52) -> 710800.18
A58: Previous Billings To Date W/ COs: | B58: 44853184
A60: Total Accrual: | B60: =B58+B49 -> 45605354
A62: Previous Accrual: | B62: 47877000
A64: Difference For Week: | B64: =B60-B62 -> -2271646.1

Sheet 1.0 BaseLay
A1: PIPELINE PROJECT
A8: Schedule C
A9: 1.0 - BASE LAY PRICE
I10: Billing Date: | J10: 42323
C11: 69435 | D11: % | E11: 580.70546 | F11: Total To Date | G11: Previous | H11: This Period | I11: Amount This Period ($) | J11: Total Earned Previously ($) | K11: Amount Earned To Date ($)
A12: 1.1 | B12: Mobilization | C12: Per Lin. m | D12: 0.02 | E12: =$E$11*D12 -> 11.614109 | F12: =G12+H12 -> 34718 | H12: 34718 | I12: =H12*E12 -> 403218.64 | J12: =G12*E12 -> 0 | K12: =SUM(I12:J12) -> 403218.64
B13: Grade ROW | C13: Per Lin. m | D13: 0.08 | E13: =$E$11*D13 -> 46.456437 | F13: =G13+H13 -> 0 | I13: =H13*E13 -> 0 | J13: =G13*E13 -> 0 | K13: =SUM(I13:J13) -> 0
B14: Haul and String Ppipe | C14: Per Lin. m | D14: 0.07 | E14: =$E$11*D14 -> 40.649382 | F14: =G14+H14 -> 0 | I14: =H14*E14 -> 0 | J14: =G14*E14 -> 0 | K14: =SUM(I14:J14) -> 0
B15: Bending | C15: Per Lin. m | D15: 0.07 | E15: =$E$11*D15 -> 40.649382 | F15: =G15+H15 -> 0 | I15: =H15*E15 -> 0 | J15: =G15*E15 -> 0 | K15: =SUM(I15:J15) -> 0
B16: Welding | C16: Per Lin. m | D16: 0.17 | E16: =$E$11*D16 -> 98.719928 | F16: =G16+H16 -> 0 | I16: =H16*E16 -> 0 | J16: =G16*E16 -> 0 | K16: =SUM(I16:J16) -> 0
B17: Excavate Pipe Trench | C17: Per Lin. m | D17: 0.08 | E17: =$E$11*D17 -> 46.456437 | F17: =G17+H17 -> 0 | I17: =H17*E17 -> 0 | J17: =G17*E17 -> 0 | K17: =SUM(I17:J17) -> 0
B18: Lower-In Pipe | C18: Per Lin. m | D18: 0.07 | E18: =$E$11*D18 -> 40.649382 | F18: =G18+H18 -> 0 | I18: =H18*E18 -> 0 | J18: =G18*E18 -> 0 | K18: =SUM(I18:J18) -> 0
B19: Backfill | C19: Per Lin. m | D19: 0.08 | E19: =$E$11*D19 -> 46.456437 | F19: =G19+H19 -> 0 | I19: =H19*E19 -> 0 | J19: =G19*E19 -> 0 | K19: =SUM(I19:J19) -> 0
B20: Tie-Ins | C20: Per Lin. m | D20: 0.07 | E20: =$E$11*D20 -> 40.649382 | F20: =G20+H20 -> 0 | I20: =H20*E20 -> 0 | J20: =G20*E20 -> 0 | K20: =SUM(I20:J20) -> 0
B21: Testing | C21: Per Lin. m | D21: 0.07 | E21: =$E$11*D21 -> 40.649382 | F21: =G21+H21 -> 0 | I21: =H21*E21 -> 0 | J21: =G21*E21 -> 0 | K21: =SUM(I21:J21) -> 0
B22: Final Tie-Ins | C22: Per Lin. m | D22: 0.05 | E22: =$E$11*D22 -> 29.035273 | F22: =G22+H22 -> 0 | I22: =H22*E22 -> 0 | J22: =G22*E22 -> 0 | K22: =SUM(I22:J22) -> 0
B23: Cleanup/Reclamation/Seeding | C23: Per Lin. m | D23: 0.09 | E23: =$E$11*D23 -> 52.263491 | F23: =G23+H23 -> 0 | I23: =H23*E23 -> 0 | J23: =G23*E23 -> 0 | K23: =SUM(I23:J23) -> 0
B24: Demobilization | C24: Per Lin. m | D24: 0.02 | E24: =$E$11*D24 -> 11.614109 | F24: =G24+H24 -> 0 | I24: =H24*E24 -> 0 | J24: =G24*E24 -> 0 | K24: =SUM(I24:J24) -> 0
B25: Final Clean Up (one year later) | C25: Per Lin. m | D25: 0.06 | E25: =$E$11*D25 -> 34.842327 | F25: =G25+H25 -> 0 | I25: =H25*E25 -> 0 | J25: =G25*E25 -> 0 | K25: =SUM(I25:J25) -> 0
D26: =SUM(D12:D25) -> 1 | E26: =SUM(E12:E25) -> 580.70546 | H26: Total For Base Lay Price: | I26: =SUM(I12:I25) -> 403218.64 | J26: =SUM(J12:J25) -> 0 | K26: =SUM(K12:K25) -> 403218.64
A29: Contractor
I34: Chief Inspector
A36: PIPELINE PROJECT
A43: Schedule C
A44: 1.0 - BASE LAY PRICE
I45: Billing Date: | J45: 42338
C46: 69435 | D46: % | E46: 580.70546 | F46: Total To Date | G46: Previous | H46: This Period | I46: Amount This Period ($) | J46: Total Earned Previously ($) | K46: Amount Earned To Date ($)
A47: 1.1 | B47: Mobilization | C47: Per Lin. m | D47: 0.02 | E47: =$E$11*D47 -> 11.614109 | F47: =G47+H47 -> 69435 | G47: 34718 | H47: 34717 | I47: =H47*E47 -> 403207.03 | J47: =G47*E47 -> 403218.64 | K47: =SUM(I47:J47) -> 806425.67
B48: Grade ROW | C48: Per Lin. m | D48: 0.08 | E48: =$E$11*D48 -> 46.456437 | F48: =G48+H48 -> 5300 | H48: 5300 | I48: =H48*E48 -> 246219.11 | J48: =G48*E48 -> 0 | K48: =SUM(I48:J48) -> 246219.11
B49: Haul and String Ppipe | C49: Per Lin. m | D49: 0.07 | E49: =$E$11*D49 -> 40.649382 | F49: =G49+H49 -> 400 | H49: 400 | I49: =H49*E49 -> 16259.753 | J49: =G49*E49 -> 0 | K49: =SUM(I49:J49) -> 16259.753
B50: Bending | C50: Per Lin. m | D50: 0.07 | E50: =$E$11*D50 -> 40.649382 | F50: =G50+H50 -> 0 | I50: =H50*E50 -> 0 | J50: =G50*E50 -> 0 | K50: =SUM(I50:J50) -> 0
B51: Welding | C51: Per Lin. m | D51: 0.17 | E51: =$E$11*D51 -> 98.719928 | F51: =G51+H51 -> 0 | I51: =H51*E51 -> 0 | J51: =G51*E51 -> 0 | K51: =SUM(I51:J51) -> 0
B52: Excavate Pipe Trench | C52: Per Lin. m | D52: 0.08 | E52: =$E$11*D52 -> 46.456437 | F52: =G52+H52 -> 0 | I52: =H52*E52 -> 0 | J52: =G52*E52 -> 0 | K52: =SUM(I52:J52) -> 0
B53: Lower-In Pipe | C53: Per Lin. m | D53: 0.07 | E53: =$E$11*D53 -> 40.649382 | F53: =G53+H53 -> 0 | I53: =H53*E53 -> 0 | J53: =G53*E53 -> 0 | K53: =SUM(I53:J53) -> 0
B54: Backfill | C54: Per Lin. m | D54: 0.08 | E54: =$E$11*D54 -> 46.456437 | F54: =G54+H54 -> 0 | I54: =H54*E54 -> 0 | J54: =G54*E54 -> 0 | K54: =SUM(I54:J54) -> 0
B55: Tie-Ins | C55: Per Lin. m | D55: 0.07 | E55: =$E$11*D55 -> 40.649382 | F55: =G55+H55 -> 0 | I55: =H55*E55 -> 0 | J55: =G55*E55 -> 0 | K55: =SUM(I55:J55) -> 0
B56: Testing | C56: Per Lin. m | D56: 0.07 | E56: =$E$11*D56 -> 40.649382 | F56: =G56+H56 -> 0 | I56: =H56*E56 -> 0 | J56: =G56*E56 -> 0 | K56: =SUM(I56:J56) -> 0
B57: Final Tie-Ins | C57: Per Lin. m | D57: 0.05 | E57: =$E$11*D57 -> 29.035273 | F57: =G57+H57 -> 0 | I57: =H57*E57 -> 0 | J57: =G57*E57 -> 0 | K57: =SUM(I57:J57) -> 0
B58: Cleanup/Reclamation/Seeding | C58: Per Lin. m | D58: 0.09 | E58: =$E$11*D58 -> 52.263491 | F58: =G58+H58 -> 0 | I58: =H58*E58 -> 0 | J58: =G58*E58 -> 0 | K58: =SUM(I58:J58) -> 0
B59: Demobilization | C59: Per Lin. m | D59: 0.02 | E59: =$E$11*D59 -> 11.614109 | F59: =G59+H59 -> 0 | I59: =H59*E59 -> 0 | J59: =G59*E59 -> 0 | K59: =SUM(I59:J59) -> 0
B60: Final Clean Up (one year later) | C60: Per Lin. m | D60: 0.06 | E60: =$E$11*D60 -> 34.842327 | F60: =G60+H60 -> 0 | I60: =H60*E60 -> 0 | J60: =G60*E60 -> 0 | K60: =SUM(I60:J60) -> 0
D61: =SUM(D47:D60) -> 1 | E61: =SUM(E47:E60) -> 580.70546 | H61: Total For Base Lay Price: | I61: =SUM(I47:I60) -> 665685.89 | J61: =SUM(J47:J60) -> 403218.64 | K61: =SUM(K47:K60) -> 1068904.5
A64: Contractor
I69: Chief Inspector
A71: =Summary!$G$11 -> PIPELINE PROJECT
A78: Schedule C
A79: 1.0 - BASE LAY PRICE
I80: Billing Date: | J80: 42353
C81: 69435 | D81: % | E81: 580.70546 | F81: Total To Date | G81: Previous | H81: This Period | I81: Amount This Period ($) | J81: Total Earned Previously ($) | K81: Amount Earned To Date ($) | P81: Current | Q81: New
A82: 1.1 | B82: Mobilization | C82: Per Lin. m | D82: 0.02 | E82: =$E$81*D82 -> 11.614109 | F82: =G82+H82 -> 69435 | G82: 69435 | I82: =H82*E82 -> 0 | J82: 806425.67 | K82: =SUM(I82:J82) -> 806425.67 | L82: hardwire previous
B83: Grade ROW | C83: Per Lin. m | D83: 0.08 | E83: =$E$81*D83 -> 46.456437 | F83: =G83+H83 -> 25100 | G83: 5300 | H83: 19800 | I83: 919837.44 | J83: 246219.11 | K83: =SUM(I83:J83) -> 1166056.5 | L83: hardwire previous | O83: grade | P83: 25100 | Q83: =P83-G83 -> 19800
B84: Haul and String Pipe | C84: Per Lin. m | D84: 0.07 | E84: =$E$81*D84 -> 40.649382 | F84: =G84+H84 -> 16100 | G84: 400 | H84: 15700 | I84: 638195.3 | J84: 16259.75 | K84: =SUM(I84:J84) -> 654455.05 | L84: hardwire previous | O84: string | P84: 16100 | Q84: =P84-G84 -> 15700
B85: Bending | C85: Per Lin. m | D85: 0.07 | E85: =$E$81*D85 -> 40.649382 | F85: =G85+H85 -> 12000 | H85: 12000 | I85: 487792.58 | J85: =G85*E85 -> 0 | K85: =SUM(I85:J85) -> 487792.58 | L85: hardwire previous | O85: bend | P85: 12000 | Q85: =P85-G85 -> 12000
B86: Welding | C86: Per Lin. m | D86: 0.17 | E86: =$E$81*D86 -> 98.719928 | F86: =G86+H86 -> 9500 | H86: 9500 | I86: 937839.31 | J86: =G86*E86 -> 0 | K86: =SUM(I86:J86) -> 937839.31 | L86: hardwire previous | O86: weld | P86: 9500 | Q86: =P86-G86 -> 9500
B87: Excavate Pipe Trench | C87: Per Lin. m | D87: 0.08 | E87: =$E$81*D87 -> 46.456437 | F87: =G87+H87 -> 3700 | H87: 3700 | I87: 171888.82 | J87: =G87*E87 -> 0 | K87: =SUM(I87:J87) -> 171888.82 | L87: hardwire previous | O87: ditch | P87: 3700 | Q87: =P87-G87 -> 3700
B88: Lower-In Pipe | C88: Per Lin. m | D88: 0.07 | E88: =$E$81*D88 -> 40.649382 | F88: =G88+H88 -> 3700 | H88: 3700 | I88: 150402.71 | J88: =G88*E88 -> 0 | K88: =SUM(I88:J88) -> 150402.71 | L88: hardwire previous | O88: lower-in | P88: 3700 | Q88: =P88-G88 -> 3700
B89: Backfill | C89: Per Lin. m | D89: 0.08 | E89: =$E$81*D89 -> 46.456437 | F89: =G89+H89 -> 2800 | H89: 2800 | I89: 130078.02 | J89: =G89*E89 -> 0 | K89: =SUM(I89:J89) -> 130078.02 | L89: hardwire previous | O89: backfill | P89: 2800 | Q89: =P89-G89 -> 2800
B90: Tie-Ins | C90: Per Lin. m | D90: 0.07 | E90: =$E$81*D90 -> 40.649382 | F90: =G90+H90 -> 1500 | H90: 1500 | I90: 60974.07 | J90: =G90*E90 -> 0 | K90: =SUM(I90:J90) -> 60974.07 | L90: hardwire previous | O90: tie-ins | P90: 1500 | Q90: =P90-G90 -> 1500
B91: Testing | C91: Per Lin. m | D91: 0.07 | E91: =$E$81*D91 -> 40.649382 | F91: =G91+H91 -> 0 | I91: =H91*E91 -> 0 | J91: =G91*E91 -> 0 | K91: =SUM(I91:J91) -> 0
B92: Final Tie-Ins | C92: Per Lin. m | D92: 0.05 | E92: =$E$81*D92 -> 29.035273 | F92: =G92+H92 -> 0 | I92: =H92*E92 -> 0 | J92: =G92*E92 -> 0 | K92: =SUM(I92:J92) -> 0
B93: Cleanup/Reclamation/Seeding | C93: Per Lin. m | D93: 0.09 | E93: =$E$81*D93 -> 52.263491 | F93: =G93+H93 -> 0 | I93: =H93*E93 -> 0 | J93: =G93*E93 -> 0 | K93: =SUM(I93:J93) -> 0
B94: Demobilization | C94: Per Lin. m | D94: 0.02 | E94: =$E$81*D94 -> 11.614109 | F94: =G94+H94 -> 0 | I94: =H94*E94 -> 0 | J94: =G94*E94 -> 0 | K94: =SUM(I94:J94) -> 0
B95: Final Clean Up (one year later) | C95: Per Lin. m | D95: 0.06 | E95: =$E$81*D95 -> 34.842327 | F95: =G95+H95 -> 0 | I95: =H95*E95 -> 0 | J95: =G95*E95 -> 0 | K95: =SUM(I95:J95) -> 0
D96: =SUM(D82:D95) -> 1 | E96: =SUM(E82:E95) -> 580.70546 | H96: Total For Base Lay Price: | I96: =SUM(I82:I95) -> 3497008.2 | J96: =SUM(J82:J95) -> 1068904.5 | K96: =SUM(K82:K95) -> 4565912.8
A99: =Summary!$G$9 -> Contractor
I104: =Summary!$G$10 -> Construction Manager
A107: =Summary!$G$11 -> PIPELINE PROJECT
A114: Schedule C
A115: 1.0 - BASE LAY PRICE
I116: Billing Date: | J116: 42369
C117: 69435 | D117: % | E117: 580.70546 | F117: Total To Date | G117: Previous | H117: This Period | I117: Amount This Period ($) | J117: Total Earned Previously ($) | K117: Amount Earned To Date ($) | P117: Current | Q117: New
A118: 1.1 | B118: Mobilization | C118: Per Lin. m | D118: 0.02 | E118: =$E$81*D118 -> 11.614109 | F118: =G118+H118 -> 69435 | G118: 69435 | I118: =H118*E118 -> 0 | J118: 806425.67 | K118: =SUM(I118:J118) -> 806425.67
B119: Grade ROW | C119: Per Lin. m | D119: 0.08 | E119: =$E$81*D119 -> 46.456437 | F119: =G119+H119 -> 32600 | G119: 25100 | H119: 7500 | I119: =H119*E119 -> 348423.27 | J119: 1166056.5 | K119: =SUM(I119:J119) -> 1514479.8 | O119: grade | P119: 32600 | Q119: =P119-G119 -> 7500
B120: Haul and String Pipe | C120: Per Lin. m | D120: 0.07 | E120: =$E$81*D120 -> 40.649382 | F120: =G120+H120 -> 24400 | G120: 16100 | H120: 8300 | I120: =H120*E120 -> 337389.87 | J120: 654455.05 | K120: =SUM(I120:J120) -> 991844.92 | O120: string | P120: 24400 | Q120: =P120-G120 -> 8300
B121: Bending | C121: Per Lin. m | D121: 0.07 | E121: =$E$81*D121 -> 40.649382 | F121: =G121+H121 -> 16100 | G121: 12000 | H121: 4100 | I121: =H121*E121 -> 166662.47 | J121: 487792.58 | K121: =SUM(I121:J121) -> 654455.05 | O121: bend | P121: 16100 | Q121: =P121-G121 -> 4100
B122: Welding | C122: Per Lin. m | D122: 0.17 | E122: =$E$81*D122 -> 98.719928 | F122: =G122+H122 -> 12800 | G122: 9500 | H122: 3300 | I122: =H122*E122 -> 325775.76 | J122: 937839.31 | K122: =SUM(I122:J122) -> 1263615.1 | O122: weld | P122: 12800 | Q122: =P122-G122 -> 3300
B123: Excavate Pipe Trench | C123: Per Lin. m | D123: 0.08 | E123: =$E$81*D123 -> 46.456437 | F123: =G123+H123 -> 6900 | G123: 3700 | H123: 3200 | I123: =H123*E123 -> 148660.6 | J123: 171888.82 | K123: =SUM(I123:J123) -> 320549.42 | O123: ditch | P123: 6900 | Q123: =P123-G123 -> 3200
B124: Lower-In Pipe | C124: Per Lin. m | D124: 0.07 | E124: =$E$81*D124 -> 40.649382 | F124: =G124+H124 -> 6900 | G124: 3700 | H124: 3200 | I124: =H124*E124 -> 130078.02 | J124: 150402.71 | K124: =SUM(I124:J124) -> 280480.73 | O124: lower-in | P124: 6900 | Q124: =P124-G124 -> 3200
B125: Backfill | C125: Per Lin. m | D125: 0.08 | E125: =$E$81*D125 -> 46.456437 | F125: =G125+H125 -> 6900 | G125: 2800 | H125: 4100 | I125: =H125*E125 -> 190471.39 | J125: 130078.02 | K125: =SUM(I125:J125) -> 320549.41 | O125: backfill | P125: 6900 | Q125: =P125-G125 -> 4100
B126: Tie-Ins | C126: Per Lin. m | D126: 0.07 | E126: =$E$81*D126 -> 40.649382 | F126: =G126+H126 -> 3700 | G126: 1500 | H126: 2200 | I126: =H126*E126 -> 89428.64 | J126: 60974.07 | K126: =SUM(I126:J126) -> 150402.71 | O126: tie-ins | P126: 3700 | Q126: =P126-G126 -> 2200
B127: Testing | C127: Per Lin. m | D127: 0.07 | E127: =$E$81*D127 -> 40.649382 | F127: =G127+H127 -> 0 | I127: =H127*E127 -> 0 | J127: =G127*E127 -> 0 | K127: =SUM(I127:J127) -> 0
B128: Final Tie-Ins | C128: Per Lin. m | D128: 0.05 | E128: =$E$81*D128 -> 29.035273 | F128: =G128+H128 -> 0 | I128: =H128*E128 -> 0 | J128: =G128*E128 -> 0 | K128: =SUM(I128:J128) -> 0
B129: Cleanup/Reclamation/Seeding | C129: Per Lin. m | D129: 0.09 | E129: =$E$81*D129 -> 52.263491 | F129: =G129+H129 -> 0 | I129: =H129*E129 -> 0 | J129: =G129*E129 -> 0 | K129: =SUM(I129:J129) -> 0
B130: Demobilization | C130: Per Lin. m | D130: 0.02 | E130: =$E$81*D130 -> 11.614109 | F130: =G130+H130 -> 0 | I130: =H130*E130 -> 0 | J130: =G130*E130 -> 0 | K130: =SUM(I130:J130) -> 0
B131: Final Clean Up (one year later) | C131: Per Lin. m | D131: 0.06 | E131: =$E$81*D131 -> 34.842327 | F131: =G131+H131 -> 0 | I131: =H131*E131 -> 0 | J131: =G131*E131 -> 0 | K131: =SUM(I131:J131) -> 0
D132: =SUM(D118:D131) -> 1 | E132: =SUM(E118:E131) -> 580.70546 | H132: Total For Base Lay Price: | I132: =SUM(I118:I131) -> 1736890 | J132: =SUM(J118:J131) -> 4565912.8 | K132: =SUM(K118:K131) -> 6302802.8
A135: =Summary!$G$9 -> Contractor
I140: =Summary!$G$10 -> Construction Manager
A143: =Summary!$G$11 -> PIPELINE PROJECT
A150: Schedule C
A151: 1.0 - BASE LAY PRICE
I152: Billing Date: | J152: 42384
C153: 69435 | D153: % | E153: 580.70546 | F153: Total To Date | G153: Previous | H153: This Period | I153: Amount This Period ($) | J153: Total Earned Previously ($) | K153: Amount Earned To Date ($) | P153: Current | Q153: New
A154: 1.1 | B154: Mobilization | C154: Per Lin. m | D154: 0.02 | E154: =$E$81*D154 -> 11.614109 | F154: =G154+H154 -> 69435 | G154: 69435 | I154: =H154*E154 -> 0 | J154: 806425.67 | K154: =SUM(I154:J154) -> 806425.67
B155: Grade ROW | C155: Per Lin. m | D155: 0.08 | E155: =$E$81*D155 -> 46.456437 | F155: =G155+H155 -> 48600 | G155: 32600 | H155: 16000 | I155: =H155*E155 -> 743302.98 | J155: 1514479.8 | K155: =SUM(I155:J155) -> 2257782.8 | O155: grade | P155: 48600 | Q155: =P155-G155 -> 16000
B156: Haul and String Pipe | C156: Per Lin. m | D156: 0.07 | E156: =$E$81*D156 -> 40.649382 | F156: =G156+H156 -> 40800 | G156: 24400 | H156: 16400 | I156: =H156*E156 -> 666649.86 | J156: 991844.92 | K156: =SUM(I156:J156) -> 1658494.8 | O156: string | P156: 40800 | Q156: =P156-G156 -> 16400
B157: Bending | C157: Per Lin. m | D157: 0.07 | E157: =$E$81*D157 -> 40.649382 | F157: =G157+H157 -> 32200 | G157: 16100 | H157: 16100 | I157: =H157*E157 -> 654455.05 | J157: 654455.05 | K157: =SUM(I157:J157) -> 1308910.1 | O157: bend | P157: 32200 | Q157: =P157-G157 -> 16100
B158: Welding | C158: Per Lin. m | D158: 0.17 | E158: =$E$81*D158 -> 98.719928 | F158: =G158+H158 -> 29100 | G158: 12800 | H158: 16300 | I158: =H158*E158 -> 1609134.8 | J158: 1263615.1 | K158: =SUM(I158:J158) -> 2872749.9 | O158: weld | P158: 29100 | Q158: =P158-G158 -> 16300
B159: Excavate Pipe Trench | C159: Per Lin. m | D159: 0.08 | E159: =$E$81*D159 -> 46.456437 | F159: =G159+H159 -> 21200 | G159: 6900 | H159: 14300 | I159: =H159*E159 -> 664327.04 | J159: 320549.42 | K159: =SUM(I159:J159) -> 984876.46 | O159: ditch | P159: 21200 | Q159: =P159-G159 -> 14300
B160: Lower-In Pipe | C160: Per Lin. m | D160: 0.07 | E160: =$E$81*D160 -> 40.649382 | F160: =G160+H160 -> 20400 | G160: 6900 | H160: 13500 | I160: =H160*E160 -> 548766.66 | J160: 280480.73 | K160: =SUM(I160:J160) -> 829247.39 | O160: lower-in | P160: 20400 | Q160: =P160-G160 -> 13500
...

Sheet 2.1
A1: =Summary!$G$11 -> PIPELINE PROJECT
A13: UNIT PRICE ITEM SUMMARY
A16: Schedule C | B16: Commercial Terms | D16: Date: | E16: 42353
A17: Item | B17: 2.1 Rock Trench
A19: Description | C19: per | E19: Amount
A20: 2.1 | B20: Rock Trench
B21: a) by mechanical methods, when requested by Company | C21: Cost Plus | E21: 36802.67
B22: b) by drill and blasting methods, when requestd by Company | C22: Cost Plus
B23: c) within the wetted perimeter of named watercourses in accordance with the Contract Documents, when requested by Company | C23: Cost Plus
D26: Total | E26: =SUM(E20:E25) -> 36802.67
A28: =Summary!$G$9 -> Contractor
C32: =Summary!$G$10 -> Construction Manager
A34: =Summary!$G$11 -> PIPELINE PROJECT
A47: UNIT PRICE ITEM SUMMARY
A50: Schedule C | B50: Commercial Terms | D50: Date: | E50: 42384
A51: Item | B51: 2.1 Rock Trench
A53: Description | C53: per | E53: Amount
A54: 2.1 | B54: Rock Trench
B55: a) by mechanical methods, when requested by Company | C55: Cost Plus | E55: 19134.69
B56: b) by drill and blasting methods, when requestd by Company | C56: Cost Plus
B57: c) within the wetted perimeter of named watercourses in accordance with the Contract Documents, when requested by Company | C57: Cost Plus
D60: Total | E60: =SUM(E54:E59) -> 19134.69
A62: =Summary!$G$9 -> Contractor
C66: =Summary!$G$10 -> Construction Manager
A68: =Summary!$G$11 -> PIPELINE PROJECT
A81: UNIT PRICE ITEM SUMMARY
A84: Schedule C | B84: Commercial Terms | D84: Date: | E84: 42400
A85: Item | B85: 2.1 Rock Trench
A87: Description | C87: per | E87: Amount
A88: 2.1 | B88: Rock Trench
B89: a) by mechanical methods, when requested by Company | C89: Cost Plus | E89: 1914.8
B90: b) by drill and blasting methods, when requestd by Company | C90: Cost Plus
B91: c) within the wetted perimeter of named watercourses in accordance with the Contract Documents, when requested by Company | C91: Cost Plus
D94: Total | E94: =SUM(E88:E93) -> 1914.8
A96: =Summary!$G$9 -> Contractor
C100: =Summary!$G$10 -> Construction Manager
A102: =Summary!$G$11 -> PIPELINE PROJECT
A115: UNIT PRICE ITEM SUMMARY
A118: Schedule C | B118: Commercial Terms | D118: Date: | E118: 42415
A119: Item | B119: 2.1 Rock Trench
A121: Description | C121: per | E121: Amount
A122: 2.1 | B122: Rock Trench
B123: a) by mechanical methods, when requested by Company | C123: Cost Plus | E123: 4031.8
B124: b) by drill and blasting methods, when requestd by Company | C124: Cost Plus
B125: c) within the wetted perimeter of named watercourses in accordance with the Contract Documents, when requested by Company | C125: Cost Plus
D128: Total | E128: =SUM(E122:E127) -> 4031.8
A130: =Summary!$G$9 -> Contractor
C134: =Summary!$G$10 -> Construction Manager
A136: =Summary!$G$11 -> PIPELINE PROJECT
A149: UNIT PRICE ITEM SUMMARY
A152: Schedule C | B152: Commercial Terms | D152: Date: | E152: 42429
A153: Item | B153: 2.1 Rock Trench
A155: Description | C155: per | E155: Amount
A156: 2.1 | B156: Rock Trench
B157: a) by mechanical methods, when requested by Company | C157: Cost Plus | E157: 35207.68
B158: b) by drill and blasting methods, when requestd by Company | C158: Cost Plus
B159: c) within the wetted perimeter of named watercourses in accordance with the Contract Documents, when requested by Company | C159: Cost Plus
D162: Total | E162: =SUM(E156:E161) -> 35207.68
A164: =Summary!$G$9 -> Contractor
C168: =Summary!$G$10 -> Construction Manager
A170: =Summary!$G$11 -> PIPELINE PROJECT
A183: UNIT PRICE ITEM SUMMARY
A186: Schedule C | B186: Commercial Terms | D186: Date: | E186: 42444
A187: Item | B187: 2.1 Rock Trench
A189: Description | C189: per | E189: Amount
A190: 2.1 | B190: Rock Trench
B191: a) by mechanical methods, when requested by Company | C191: Cost Plus | E191: 3361.32
B192: b) by drill and blasting methods, when requestd by Company | C192: Cost Plus
B193: c) within the wetted perimeter of named watercourses in accordance with the Contract Documents, when requested by Company | C193: Cost Plus
D196: Total | E196: =SUM(E190:E195) -> 3361.32
A198: =Summary!$G$9 -> Contractor
C202: =Summary!$G$10 -> Construction Manager
A204: =Summary!$G$11 -> PIPELINE PROJECT
A217: UNIT PRICE ITEM SUMMARY
A220: Schedule C | B220: Commercial Terms | D220: Date: | E220: =Summary!$G$3 -> 42505
A221: Item | B221: 2.1 Rock Trench
A223: Description | C223: per | E223: Amount
A224: 2.1 | B224: Rock Trench
B225: a) by mechanical methods, when requested by Company | C225: Cost Plus | E225: 3271.42
B226: b) by drill and blasting methods, when requestd by Company | C226: Cost Plus
B227: c) within the wetted perimeter of named watercourses in accordance with the Contract Documents, when requested by Company | C227: Cost Plus
D230: Total | E230: =SUM(E224:E229) -> 3271.42
A232: =Summary!$G$9 -> Contractor
C236: =Summary!$G$10 -> Construction Manager

Sheet 2.2
A1: =Summary!$G$11 -> PIPELINE PROJECT
A13: UNIT PRICE ITEM SUMMARY
A16: Schedule C | E16: Date: | F16: 42353
A17: Item | B17: 2.2 Rockshield
A19: Description | C19: per | D19: Unit Price | E19: Units | F19: Amount
A20: 2.2 | B20: Rockshield (NPS 16)
B21: a) Owner supply rockshield material | C21: per lin. M | D21: 51.48
B22: b) Contractor supply rockshield material | C22: per lin. M | D22: 71.48 | E22: 318.98 | F22: =E22*D22 -> 22800.69
E24: Total | F24: =SUM(F20:F23) -> 22800.69
A26: =Summary!$G$9 -> Contractor
C30: =Summary!$G$10 -> Construction Manager
B35: Locations (KPs): | C35: From | D35: To | E35: Metres
B36: SITE UPI Report 0552 Dec. 9: | C36: 51804 | D36: 51835 | E36: =ABS(C36-D36) -> 31
C37: 51967.5 | D37: 51978 | E37: =ABS(C37-D37) -> 10.5
C38: 52144.4 | D38: 52154.7 | E38: =ABS(C38-D38) -> 10.3
C39: 52233.1 | D39: 52269.3 | E39: =ABS(C39-D39) -> 36.2
C40: 52269.3 | D40: 52280 | E40: =ABS(C40-D40) -> 10.7
C41: 52307 | D41: 52338.2 | E41: =ABS(C41-D41) -> 31.2
C42: 52746.9 | D42: 52756.3 | E42: =ABS(C42-D42) -> 9.4
C43: 52904.6 | D43: 52923 | E43: =ABS(C43-D43) -> 18.4 | F43: =SUM(E36:E43) -> 157.7
B45: SITE UPI Report 0552 Dec 13: | C45: 53113 | D45: 53166 | E45: =ABS(C45-D45) -> 53
C46: 52545 | D46: 52617 | E46: =ABS(C46-D46) -> 72 | F46: =SUM(E45:E46) -> 125
B48: SITE UPI Report 0554 Dec 15: | C48: 54697.62 | D48: 54724.37 | E48: =ABS(C48-D48) -> 26.75
C49: 54229.8 | D49: 54239.33 | E49: =ABS(C49-D49) -> 9.53 | F49: =SUM(E48:E49) -> 36.28
D51: Total: | E51: =SUM(E35:E50) -> 318.98 | F51: =SUM(F43:F50) -> 318.98
A53: =Summary!$G$11 -> PIPELINE PROJECT
A65: UNIT PRICE ITEM SUMMARY
A68: Schedule C | E68: Date: | F68: 42369
A69: Item | B69: 2.2 Rockshield
A71: Description | C71: per | D71: Unit Price | E71: Units | F71: Amount
A72: 2.2 | B72: Rockshield (NPS 16)
B73: a) Owner supply rockshield material | C73: per lin. M | D73: 51.48
B74: b) Contractor supply rockshield material | C74: per lin. M | D74: 71.48 | E74: =E97 -> 292.61 | F74: =E74*D74 -> 20915.763
E76: Total | F76: =SUM(F72:F75) -> 20915.763
A78: =Summary!$G$9 -> Contractor
C82: =Summary!$G$10 -> Construction Manager
B87: Locations (KPs): | C87: From | D87: To | E87: Metres | H87: LEM
B88: 42723 | C88: 54463 | D88: 54538 | E88: =ABS(C88-D88) -> 75 | F88: 75 | G88: Tim Lay | H88: 0326 | J88: should be 54+539
B89: 42722 | C89: 57556 | D89: 57574.84 | E89: =ABS(C89-D89) -> 18.84 | F89: 18.84 | G89: Dwayne P | H89: 0555
B90: 42722 | C90: 57595.16 | D90: 57604.41 | E90: =ABS(C90-D90) -> 9.25 | F90: 9.25 | G90: Dwayne P | H90: 0555
B91: 42722 | C91: 57622.16 | D91: 57631.44 | E91: =ABS(C91-D91) -> 9.28 | F91: 9.28 | G91: Dwayne P | H91: 0555
B92: 42724 | C92: 65267 | D92: 65411 | E92: =ABS(C92-D92) -> 144 | F92: 144 | G92: Dwayne P | H92: 0555
B94: 42723 | C94: 60007.19 | D94: 60043.43 | E94: =ABS(C94-D94) -> 36.24 | F94: 36.24 | G94: Dwayne P | H94: 0556
D97: Total: | E97: =SUM(E87:E96) -> 292.61 | F97: =SUM(F88:F96) -> 292.61
A99: =Summary!$G$11 -> PIPELINE PROJECT
A111: UNIT PRICE ITEM SUMMARY
A114: Schedule C | E114: Date: | F114: 42384
A115: Item | B115: 2.2 Rockshield
A117: Description | C117: per | D117: Unit Price | E117: Units | F117: Amount
A118: 2.2 | B118: Rockshield (NPS 16)
B119: a) Owner supply rockshield material | C119: per lin. M | D119: 51.48
B120: b) Contractor supply rockshield material | C120: per lin. M | D120: 71.48 | E120: =E141 -> 298.7 | F120: =E120*D120 -> 21351.076
E122: Total | F122: =SUM(F118:F121) -> 21351.076
A124: =Summary!$G$9 -> Contractor
C128: =Summary!$G$10 -> Construction Manager
B133: Locations (KPs): | C133: From | D133: To | E133: Metres | F133: Survey | H133: LEM
B135: 42376 | C135: 60496 | D135: 60536 | E135: 39 | F135: 33.4 | G135: Tim/Jerome | H135: 0328 | I135: off by 6m too much compared to survey
B136: 42377 | C136: 61258 | D136: 61213 | E136: 44.4 | F136: 44.4 | G136: Jerome | H136: 0329 | I136: survey had in the other direction 61+257.5 to 61+301.9
B137: 42380 | C137: 67299 | D137: 67471 | E137: =ABS(C137-D137) -> 172 | F137: 172.3 | G137: Dwayne | H137: 0557
B138: 42381 | C138: 67562.7 | D138: 67606 | E138: =ABS(C138-D138) -> 43.3 | F138: 44 | G138: Dwayne | H138: 0558
E139: =ABS(C139-D139) -> 0
D141: Total: | E141: =SUM(E133:E140) -> 298.7 | F141: =SUM(F134:F140) -> 294.1
A143: =Summary!$G$11 -> PIPELINE PROJECT
A155: UNIT PRICE ITEM SUMMARY
A158: Schedule C | E158: Date: | F158: 42400
A159: Item | B159: 2.2 Rockshield
A161: Description | C161: per | D161: Unit Price | E161: Units | F161: Amount
A162: 2.2 | B162: Rockshield (NPS 16)
B163: a) Owner supply rockshield material | C163: per lin. M | D163: 51.48
B164: b) Contractor supply rockshield material | C164: per lin. M | D164: 71.48 | E164: =E191 -> 319.2 | F164: =E164*D164 -> 22816.416
E166: Total | F166: =SUM(F162:F165) -> 22816.416
A168: =Summary!$G$9 -> Contractor
C172: =Summary!$G$10 -> Construction Manager
B177: Locations (KPs): | C177: From | D177: To | E177: Metres | F177: Survey | H177: LEM
B179: 42388 | C179: 6564 | D179: 6600 | E179: 35 | F179: 35.4 | G179: Dwayne | H179: 559
C180: 6749 | D180: 6802 | E180: 53.7 | F180: 53.7 | G180: Dwayne | H180: 559 | I180: =E180+E179 -> 88.7
B181: 42388 | C181: 64946 | D181: 64964 | E181: 17 | F181: 18 | G181: Clint | H181: 1176
B182: 42389 | C182: 67477 | D182: 67519 | E182: =ABS(C182-D182) -> 42 | F182: 42.6 | G182: Jerome | H182: 331
B183: 42390 | C183: 10848 | D183: 10902.4 | E183: =ABS(C183-D183) -> 54.4 | F183: 54.4 | G183: Dwayne | H183: 560
C184: 11031 | D184: 11040.3 | E184: =ABS(C184-D184) -> 9.3 | F184: 9.3 | G184: Dwayne | H184: 560
C185: 11132.4 | D185: 11141.7 | E185: =ABS(C185-D185) -> 9.3 | F185: 9.3 | G185: Dwayne | H185: 560
C186: 11687.8 | D186: 11731.9 | E186: =ABS(C186-D186) -> 44.1 | F186: 44.1 | G186: Dwayne | H186: 560 | I186: =SUM(E183:E186) -> 117.1
B187: 42397 | C187: 16901.6 | D187: 16929 | E187: =ABS(C187-D187) -> 27.4 | F187: 27.5 | G187: Dwayne | H187: 561
B188: 42398 | C188: 14747 | D188: 14774 | E188: =ABS(C188-D188) -> 27 | F188: 27.1 | G188: Clint | H188: 1177
E189: =ABS(C189-D189) -> 0
D191: Total: | E191: =SUM(E177:E190) -> 319.2 | F191: =SUM(F178:F190) -> 321.4
A193: =Summary!$G$11 -> PIPELINE PROJECT
A205: UNIT PRICE ITEM SUMMARY
A208: Schedule C | E208: Date: | F208: 42415
A209: Item | B209: 2.2 Rockshield
A211: Description | C211: per | D211: Unit Price | E211: Units | F211: Amount
A212: 2.2 | B212: Rockshield (NPS 16)
B213: a) Owner supply rockshield material | C213: per lin. M | D213: 51.48
B214: b) Contractor supply rockshield material | C214: per lin. M | D214: 71.48 | E214: =E250 -> 1117.7 | F214: =E214*D214 -> 79893.196
E216: Total | F216: =SUM(F212:F215) -> 79893.196
A218: =Summary!$G$9 -> Contractor
C222: =Summary!$G$10 -> Construction Manager
B230: Locations (KPs): | C230: From | D230: To | E230: Metres | F230: Survey | H230: LEM
B232: 42402 | C232: 22241.3 | D232: 22303.86 | E232: 62.6 | F232: 62.6 | G232: Dwayne | H232: 0562
B233: 42403 | C233: 6425 | D233: 6507 | E233: 83 | F233: 82.1 | G233: Jerome | H233: 0335
...

Sheet 2.3
A1: =Summary!$G$11 -> PIPELINE PROJECT
A13: UNIT PRICE ITEM SUMMARY
A14: Sand Bedding/Padding
A16: Schedule C | E16: Date: | F16: 42353
A17: Item | B17: 2.3 Sand Bedding/Padding From Borrow Pits
A19: Description | C19: per | D19: Unit Price | E19: Units | F19: Amount
A20: 2.3 | B20: Sand Bedding/Padding From Borrow Pits (Supply, load, haul, unload, place) | J20: LEM | K20: From | L20: To
B21: a) Bedding | C21: Per Lin. m | D21: 89.6 | E21: 80 | F21: =E21*D21 -> 7168 | J21: #0165 | K21: 54+380 | L21: 54+460 | M21: 80 m | P21: 18.89 | Q21: 18.99
B22: b) Padding (Top) | C22: Per Lin. m | D22: 114.67 | F22: =E22*D22 -> 0 | P22: 18.9 | Q22: 19.03
B23: c) Bedding and Padding Placed As One Operation | C23: Per Lin. m | D23: 166.57 | E23: 180 | F23: =E23*D23 -> 29982.6 | J23: #0167 | K23: 54+200 | L23: 54+380 | M23: 180 m | P23: 18.95 | Q23: 19.27
B24: d) Hauling (The cost of hauling to the ROW) | C24: m3/km | D24: 2.8 | E24: 15430.75 | F24: =E24*D24 -> 43206.1 | P24: 9.6
P25: 19.19
P26: 18.88
E27: Total | F27: =SUM(F20:F26) -> 80356.7 | P27: 19.51
P28: =SUM(P21:P27) -> 123.92 | Q28: =SUM(Q21:Q27) -> 57.29
A29: =Summary!$G$9 -> Contractor
C32: =Summary!$G$10 -> Construction Manager
A34: =Summary!$G$11 -> PIPELINE PROJECT
A46: UNIT PRICE ITEM SUMMARY
A47: Sand Bedding/Padding
A49: Schedule C | E49: Date: | F49: 42384
A50: Item | B50: 2.3 Sand Bedding/Padding From Borrow Pits
A52: Description | C52: per | D52: Unit Price | E52: Units | F52: Amount
A53: 2.3 | B53: Sand Bedding/Padding From Borrow Pits (Supply, load, haul, unload, place)
B54: a) Bedding | C54: Per Lin. m | D54: 89.6 | E54: 10 | F54: =E54*D54 -> 896
B55: b) Padding (Top) | C55: Per Lin. m | D55: 114.67 | F55: =E55*D55 -> 0
B56: c) Bedding and Padding Placed As One Operation | C56: Per Lin. m | D56: 166.57 | F56: =E56*D56 -> 0
B57: d) Hauling (The cost of hauling to the ROW) | C57: m3/km | D57: 2.8 | E57: =E76 -> 3360 | F57: =E57*D57 -> 9408
E60: Total | F60: =SUM(F53:F59) -> 10304
A62: =Summary!$G$9 -> Contractor
C65: =Summary!$G$10 -> Construction Manager
H72: LEM
B73: 42373 | C73: 21 | D73: km one way | F73: Josh | G73: Haul sand | H73: 0456
B74: 42383 | C74: 21 | F74: Harvey | G74: Haul sand | H74: 0465
C76: =SUM(C73:C74) -> 42 | D76: 80 | E76: =C76*D76 -> 3360
A78: =Summary!$G$11 -> PIPELINE PROJECT
A90: UNIT PRICE ITEM SUMMARY
A91: Sand Bedding/Padding
A93: Schedule C | E93: Date: | F93: 42400
A94: Item | B94: 2.3 Sand Bedding/Padding From Borrow Pits
A96: Description | C96: per | D96: Unit Price | E96: Units | F96: Amount
A97: 2.3 | B97: Sand Bedding/Padding From Borrow Pits (Supply, load, haul, unload, place)
B98: a) Bedding | C98: Per Lin. m | D98: 89.6 | E98: 10 | F98: =E98*D98 -> 896
B99: b) Padding (Top) | C99: Per Lin. m | D99: 114.67 | F99: =E99*D99 -> 0
B100: c) Bedding and Padding Placed As One Operation | C100: Per Lin. m | D100: 166.57 | F100: =E100*D100 -> 0
B101: d) Hauling (The cost of hauling to the ROW) | C101: m3/km | D101: 2.8 | E101: =E124 -> 5920 | F101: =E101*D101 -> 16576
E104: Total | F104: =SUM(F97:F103) -> 17472
A106: =Summary!$G$9 -> Contractor
C109: =Summary!$G$10 -> Construction Manager
C117: Cubes | H117: LEM
B118: 42388 | C118: 11 | E118: 10 | F118: Clint | G118: Bedding | H118: 1176
B119: 42391 | C119: 21 | F119: Doug | G119: Haul sand | H119: 0466
B120: 42399 | C120: 42 | F120: Shawn | G120: Haul Sand
D123: km 1 way
C124: =SUM(C118:C123) -> 74 | D124: 80 | E124: =C124*D124 -> 5920
A126: =Summary!$G$11 -> PIPELINE PROJECT
A138: UNIT PRICE ITEM SUMMARY
A139: Sand Bedding/Padding
A141: Schedule C | E141: Date: | F141: 42415
A142: Item | B142: 2.3 Sand Bedding/Padding From Borrow Pits
A144: Description | C144: per | D144: Unit Price | E144: Units | F144: Amount
A145: 2.3 | B145: Sand Bedding/Padding From Borrow Pits (Supply, load, haul, unload, place)
B146: a) Bedding | C146: Per Lin. m | D146: 89.6 | F146: =E146*D146 -> 0
B147: b) Padding (Top) | C147: Per Lin. m | D147: 114.67 | F147: =E147*D147 -> 0
B148: c) Bedding and Padding Placed As One Operation | C148: Per Lin. m | D148: 166.57 | F148: =E148*D148 -> 0
B149: d) Hauling (The cost of hauling to the ROW) | C149: m3/km | D149: 2.8 | E149: =G176 -> 9760 | F149: =E149*D149 -> 27328
E152: Total | F152: =SUM(F145:F151) -> 27328
A154: =Summary!$G$9 -> Contractor
C157: =Summary!$G$10 -> Construction Manager
C166: Cubes | H166: LEM
B167: 42400 | C167: 21 | E167: 80 | F167: Shawn | G167: Haul Sand | H167: 0704 | I167: missing Shawn's signature
B168: 42404 | C168: 11 | E168: 80 | F168: Jerome | G168: Haul Sand | H168: 0337
C169: =SUM(C167:C168) -> 32 | D169: 80 | E169: =C169*D169 -> 2560
B170: 42403 | C170: 15 | E170: 96 | F170: Shawn | G170: Haul Sand | H170: 0705
B171: 42403 | C171: 15 | E171: 96 | F171: Shawn | G171: Haul Sand | H171: 0706
B172: 42401 | C172: 15 | E172: 96 | F172: Jerome | G172: Haul Sand | H172: 0334
B173: 42412 | C173: 30 | D173: 2 loads | E173: 96 | F173: Jerome | G173: Haul Sand | H173: 0338
D175: km 1 way
C176: =SUM(C170:C175) -> 75 | D176: 96 | E176: =C176*D176 -> 7200 | F176: Total: | G176: =E176+E169 -> 9760
A178: =Summary!$G$11 -> PIPELINE PROJECT
A190: UNIT PRICE ITEM SUMMARY
A191: Sand Bedding/Padding
A193: Schedule C | E193: Date: | F193: 42429
A194: Item | B194: 2.3 Sand Bedding/Padding From Borrow Pits
A196: Description | C196: per | D196: Unit Price | E196: Units | F196: Amount
A197: 2.3 | B197: Sand Bedding/Padding From Borrow Pits (Supply, load, haul, unload, place)
B198: a) Bedding | C198: Per Lin. m | D198: 89.6 | E198: =M232 -> 269 | F198: =E198*D198 -> 24102.4
B199: b) Padding (Top) | C199: Per Lin. m | D199: 114.67 | E199: =U232 -> 233.4 | F199: =E199*D199 -> 26763.978
B200: c) Bedding and Padding Placed As One Operation | C200: Per Lin. m | D200: 166.57 | F200: =E200*D200 -> 0
B201: d) Hauling (The cost of hauling to the ROW) | C201: m3/km | D201: 2.8 | E201: =G233 -> 27072 | F201: =E201*D201 -> 75801.6
E204: Total | F204: =SUM(F197:F203) -> 126667.98
A206: =Summary!$G$9 -> Contractor
C209: =Summary!$G$10 -> Construction Manager
B218: d) | C218: Cubes | D218: Haul Sand | H218: LEM | J218: a) | K218: Bedding | R218: b) | S218: Padding (Top)
N219: Survey | V219: Survey
B220: 42417 | C220: 100 | F220: Dwayne | H220: 0531 | J220: 42417 | K220: 34654.9 | L220: 34830.9 | M220: 200 | N220: 176 | O220: Dwayne | P220: 0531 | R220: 42418 | S220: 34654.9 | T220: 34830.9 | U220: =ABS(S220-T220) -> 176 | V220: 176 | W220: Thomas | X220: 0141
B221: 42418 | C221: 145 | F221: Thomas | H221: 0141 | K221: 34876.4 | L221: 34933.8 | N221: 57.4 | O221: Dwayne | P221: 0531 | S221: 34876.4 | T221: 34933.8 | U221: =ABS(S221-T221) -> 57.4 | V221: 57.4 | W221: Thomas | X221: 0141
B222: 42419 | C222: 37 | F222: Thomas | H222: 0142 | J222: 42424 | K222: 32750 | L222: 32787 | M222: =ABS(K222-L222) -> 37 | N222: 37 | O222: Clint | P222: 1179 | U222: =ABS(R222-S222) -> 0
K223: 32861 | L223: 32893 | M223: =ABS(K223-L223) -> 32 | N223: 32 | O223: Clint | P223: 1179 | U223: =ABS(R223-S223) -> 0
M224: =ABS(K224-L224) -> 0 | U224: =ABS(S224-T224) -> 0
...

Sheet 2.11
A1: =Summary!$G$11 -> PIPELINE PROJECT
A13: UNIT PRICE ITEM SUMMARY
A16: Schedule C | D16: Date: | E16: 42475
A17: Item | B17: 2.11 Clean Washed Gravel
A19: Description | C19: Per | E19: Amount
A20: 2.11 | B20: Clean Washed Gravel
B21: To supply load and place well graded, clean, washed gravel with particle size between 25 mm and 50 mm from contractor sourced borrow pits and pre-approved by the company, as requested by Company. | C21: Cost Plus | E21: 7658.4 | I21: Ticket: 1468, 1469 | L21: =8876.4-1218 -> 7658.4
B22: Haul (The cost of hauling to the ROW. Pits and haul distance approved by the Company) | C22: Cost Plus | E22: 1218 | L22: 8876.4
D24: Total | E24: =SUM(E20:E23) -> 8876.4
A26: =Summary!$G$9 -> Contractor
C30: =Summary!G10 -> Construction Manager
A32: =Summary!$G$11 -> PIPELINE PROJECT
A44: UNIT PRICE ITEM SUMMARY
A47: Schedule C | D47: Date: | E47: =Summary!$G$3 -> 42505
A48: Item | B48: 2.11 Clean Washed Gravel
A50: Description | C50: Per | E50: Amount
A51: 2.11 | B51: Clean Washed Gravel
B52: To supply load and place well graded, clean, washed gravel with particle size between 25 mm and 50 mm from contractor sourced borrow pits and pre-approved by the company, as requested by Company. | C52: Cost Plus | E52: 0 | I52: Ticket:
B53: Haul (The cost of hauling to the ROW. Pits and haul distance approved by the Company) | C53: Cost Plus | E53: 0
D55: Total | E55: =SUM(E51:E54) -> 0
A57: =Summary!$G$9 -> Contractor
C61: =Summary!$G$10 -> Construction Manager

Sheet 2.14
A1: =Summary!$G$11 -> PIPELINE PROJECT
A13: UNIT PRICE ITEM SUMMARY
A16: Schedule C | E16: Billing Date: | F16: 42353
A17: Item | B17: 2.14 Install Pipe To Extra Depth
A19: Description | C19: per | D19: Unit Price | E19: Units | F19: Billing Amount
A20: 2.14 | B20: Install Pipe To Extra Depth
B21: a) 0.30 m total extra depth | C21: per lin. M. | D21: 10
B22: b) 0.60 m total extra depth | C22: per lin. M. | D22: 14 | E22: 60 | F22: =E22*D22 -> 840
B23: C) 0.90 m total extra depth | C23: per lin. M. | D23: 19
B24: d) 1.20 m total extra depth | C24: per lin. M. | D24: 24
B25: e) 1.50 m total extra depth | C25: per lin. M. | D25: 39
E29: Total | F29: =SUM(F20:F28) -> 840
A31: =Summary!$G$9 -> Contractor
C35: =Summary!$G$10 -> Construction Manager
A37: =Summary!$G$11 -> PIPELINE PROJECT
A49: UNIT PRICE ITEM SUMMARY
A52: Schedule C | E52: Billing Date: | F52: 42369
A53: Item | B53: 2.14 Install Pipe To Extra Depth
A55: Description | C55: per | D55: Unit Price | E55: Units | F55: Billing Amount
A56: 2.14 | B56: Install Pipe To Extra Depth
B57: a) 0.30 m total extra depth | C57: per lin. M. | D57: 10
B58: b) 0.60 m total extra depth | C58: per lin. M. | D58: 14
B59: C) 0.90 m total extra depth | C59: per lin. M. | D59: 19
B60: d) 1.20 m total extra depth | C60: per lin. M. | D60: 24
B61: e) 1.50 m total extra depth | C61: per lin. M. | D61: 39 | E61: 12 | F61: =E61*D61 -> 468
E65: Total | F65: =SUM(F56:F64) -> 468
A67: =Summary!$G$9 -> Contractor
C71: =Summary!$G$10 -> Construction Manager
A73: =Summary!$G$11 -> PIPELINE PROJECT
A85: UNIT PRICE ITEM SUMMARY
A88: Schedule C | E88: Billing Date: | F88: 42490
A89: Item | B89: 2.14 Install Pipe To Extra Depth
A91: Description | C91: per | D91: Unit Price | E91: Units | F91: Billing Amount
A92: 2.14 | B92: Install Pipe To Extra Depth
B93: a) 0.30 m total extra depth | C93: per lin. M. | D93: 10 | E93: =L93 -> 23.606 | F93: =E93*D93 -> 236.06 | H93: 5.99 | I93: 10.069 | J93: 3.447 | K93: 4.1 | L93: =SUM(H93:K93) -> 23.606
B94: b) 0.60 m total extra depth | C94: per lin. M. | D94: 14 | E94: =L94 -> 3.449 | F94: =E94*D94 -> 48.286 | H94: 1.259 | I94: 2.19 | L94: =SUM(H94:K94) -> 3.449
B95: C) 0.90 m total extra depth | C95: per lin. M. | D95: 19
B96: d) 1.20 m total extra depth | C96: per lin. M. | D96: 24
B97: e) 1.50 m total extra depth | C97: per lin. M. | D97: 39
D99: Total: | E99: =SUM(E93:E98) -> 27.055
E101: Total | F101: =SUM(F92:F100) -> 284.346
A103: =Summary!$G$9 -> Contractor
C107: =Summary!$G$10 -> Construction Manager
A109: =Summary!$G$11 -> PIPELINE PROJECT
A121: UNIT PRICE ITEM SUMMARY
A124: Schedule C | E124: Billing Date: | F124: =Summary!$G$3 -> 42505
A125: Item | B125: 2.14 Install Pipe To Extra Depth
A127: Description | C127: per | D127: Unit Price | E127: Units | F127: Billing Amount
A128: 2.14 | B128: Install Pipe To Extra Depth
B129: a) 0.30 m total extra depth | C129: per lin. M. | D129: 10 | F129: =E129*D129 -> 0
B130: b) 0.60 m total extra depth | C130: per lin. M. | D130: 14 | F130: =E130*D130 -> 0
B131: C) 0.90 m total extra depth | C131: per lin. M. | D131: 19
B132: d) 1.20 m total extra depth | C132: per lin. M. | D132: 24
B133: e) 1.50 m total extra depth | C133: per lin. M. | D133: 39
D135: Total: | E135: =SUM(E129:E134) -> 0
E137: Total | F137: =SUM(F128:F136) -> 0
A139: =Summary!$G$9 -> Contractor
C143: =Summary!$G$10 -> Construction Manager

Sheet 2.18
A1: =Summary!$G$11 -> PIPELINE PROJECT
A13: UNIT PRICE ITEM SUMMARY
A16: Schedule C | E16: Date: | F16: 42353
A17: Item | B17: 2.18 Vehicle & Equipment Wash Stations
A19: Description | C19: per | D19: Unit Price | E19: Units | F19: Amount
A20: 2.18 | B20: b) Winter Wash
B21: i) Operating the wash station (Hot Steamer) | C21: Per Day | D21: 1625 | E21: 5 | F21: =E21*D21 -> 8125
B22: ii) Installation of wash stations (load, haul, assemble) | C22: Per Station | D22: 7785 | E22: 0.333333 | F22: =E22*D22 -> 2594.9974
B23: iii) Removal of wash station (load, haul, take down) | C23: Per Station | D23: 3960 | F23: =E23*D23 -> 0
E26: Total | F26: =SUM(F20:F25) -> 10719.997
A28: =Summary!$G$9 -> Contractor
C32: =Summary!$G$10 -> Construction Manager
A38: =Summary!$G$11 -> PIPELINE PROJECT
A50: UNIT PRICE ITEM SUMMARY
A53: Schedule C | E53: Date: | F53: =Summary!$G$3 -> 42505
A54: Item | B54: 2.18 Vehicle & Equipment Wash Stations
A56: Description | C56: per | D56: Unit Price | E56: Units | F56: Amount
A57: 2.18 | B57: b) Winter Wash
B58: i) Operating the wash station (Hot Steamer) | C58: Per Day | D58: 1625 | F58: =E58*D58 -> 0
B59: ii) Installation of wash stations (load, haul, assemble) | C59: Per Station | D59: 7785 | F59: =E59*D59 -> 0
B60: iii) Removal of wash station (load, haul, take down) | C60: Per Station | D60: 3960 | F60: =E60*D60 -> 0
E63: Total | F63: =SUM(F57:F62) -> 0
A65: =Summary!$G$9 -> Contractor
C69: =Summary!$G$10 -> Construction Manager

Sheet 2.22
A1: =Summary!$G$11 -> PIPELINE PROJECT
A13: UNIT PRICE ITEM SUMMARY
A16: Schedule C | E16: Date: | F16: 42415
A17: Item | B17: 2.22 Cut Out And Replace Welds
A19: Description | C19: per | D19: Unit Price | E19: Units | F19: Billing Amount
A20: 2.22 | B20: To cut out and replace welds rings, including | C20: per weld | D20: 3890 | E20: 2 | F20: =E20*D20 -> 7780
B21: re-bevelling of two (2) pipe ends at request of
B22: Company
E29: Total | F29: =SUM(F20:F28) -> 7780
A31: =Summary!$G$9 -> Contractor
C35: =Summary!$G$10 -> Construction Manager
D38: UPI Report
C39: KP 26+027 | D39: 0563 | E39: Lorne
C40: KP 54+510 | D40: 1152 | E40: Cliff
A42: =Summary!$G$11 -> PIPELINE PROJECT
A54: UNIT PRICE ITEM SUMMARY
A57: Schedule C | E57: Date: | F57: 42429
A58: Item | B58: 2.22 Cut Out And Replace Welds
A60: Description | C60: per | D60: Unit Price | E60: Units | F60: Billing Amount
A61: 2.22 | B61: To cut out and replace welds rings, including | C61: per weld | D61: 3890 | E61: 1 | F61: =E61*D61 -> 3890 | I61: KP 46+890- TICKET 1302
B62: re-bevelling of two (2) pipe ends at request of
B63: Company
E70: Total | F70: =SUM(F61:F69) -> 3890
A72: =Summary!$G$9 -> Contractor
C76: =Summary!$G$10 -> Construction Manager
A78: =Summary!$G$11 -> PIPELINE PROJECT
A90: UNIT PRICE ITEM SUMMARY
A93: Schedule C | E93: Date: | F93: =Summary!$G$3 -> 42505
A94: Item | B94: 2.22 Cut Out And Replace Welds
A96: Description | C96: per | D96: Unit Price | E96: Units | F96: Billing Amount
A97: 2.22 | B97: To cut out and replace welds rings, including | C97: per weld | D97: 3890 | F97: =E97*D97 -> 0
B98: re-bevelling of two (2) pipe ends at request of
B99: Company
E106: Total | F106: =SUM(F97:F105) -> 0
A108: =Summary!$G$9 -> Contractor
C112: =Summary!$G$10 -> Construction Manager

Sheet 2.27
A1: =Summary!$G$11 -> PIPELINE PROJECT
A13: UNIT PRICE ITEM SUMMARY
A16: Schedule C | E16: Date: | F16: =Summary!$G$3 -> 42505
A17: Item | B17: 2.27 Erosion Control Mat
A19: Description | C19: per | D19: Unit Price | E19: Units | F19: Billing Amount
A20: 2.27 | B20: Supply & Install Erosion Control Mat When | C20: per m2 | D20: 13.23 | E20: 208 | F20: =E20*D20 -> 2751.84
B21: Requested By The Company
B23: SITE UPI Report# 0477
E29: Total | F29: =SUM(F20:F28) -> 2751.84
A31: =Summary!$G$9 -> Contractor
C35: =Summary!$G$10 -> Construction Manager

Sheet 2.29
A1: =Summary!$G$11 -> PIPELINE PROJECT
A13: UNIT PRICE ITEM SUMMARY
A16: Schedule C | E16: Date: | F16: 42369
A17: Item | B17: 2.29 Rig Mats
A19: Description | C19: per | D19: Unit Price | E19: Units | F19: Amount
A20: 2.29 | B20: Rig Mats | K20: 42735 | L20: 42379
B21: Oak Interlocking Mats | C21: per mat | D21: 4.5 | E21: 15876 | F21: =E21*D21 -> 71442 | K21: 15876 | L21: 21276
B22: Rig mats complete with metal frame (appox. 8' x 20') | C22: per mat | D22: 45 | F22: =E22*D22 -> 0
E26: Total | F26: =SUM(F20:F25) -> 71442
A28: =Summary!$G$9 -> Contractor
C32: =Summary!$G$10 -> Construction Manager
A34: =Summary!$G$11 -> PIPELINE PROJECT
A46: UNIT PRICE ITEM SUMMARY
A49: Schedule C | E49: Date: | F49: 42384 | K49: Need to enter the difference:
A50: Item | B50: 2.29 Rig Mats
A52: Description | C52: per | D52: Unit Price | E52: Units | F52: Amount | K52: Previous
A53: 2.29 | B53: Rig Mats | K53: 42735 | L53: 42384
B54: Oak Interlocking Mats | C54: per mat | D54: 4.5 | E54: 8100 | F54: =E54*D54 -> 36450 | K54: 15876 | L54: 8100
B55: Rig mats complete with metal frame (appox. 8' x 20') | C55: per mat | D55: 45 | F55: =E55*D55 -> 0
E59: Total | F59: =SUM(F53:F58) -> 36450
A61: =Summary!$G$9 -> Contractor
C65: =Summary!$G$10 -> Construction Manager
A67: =Summary!$G$11 -> PIPELINE PROJECT
A79: UNIT PRICE ITEM SUMMARY
A82: Schedule C | E82: Date: | F82: 42400 | K82: Need to enter the difference:
A83: Item | B83: 2.29 Rig Mats
A85: Description | C85: per | D85: Unit Price | E85: Units | F85: Amount | K85: Previous
A86: 2.29 | B86: Rig Mats | K86: 42735 | L86: 42384 | M86: 42400 | N86: 42415 | O86: To Date:
B87: Oak Interlocking Mats | C87: per mat | D87: 4.5 | E87: 8640 | F87: =E87*D87 -> 38880 | K87: 15876 | L87: 8100 | M87: 8640 | O87: =SUM(K87:N87) -> 32616
B88: Rig mats complete with metal frame (appox. 8' x 20') | C88: per mat | D88: 45 | F88: =E88*D88 -> 0 | K88: 71442 | L88: 36450 | M88: 38880 | O88: =SUM(K88:N88) -> 146772
E92: Total | F92: =SUM(F86:F91) -> 38880
A94: =Summary!$G$9 -> Contractor
C98: =Summary!$G$10 -> Construction Manager
A100: =Summary!$G$11 -> PIPELINE PROJECT
A112: UNIT PRICE ITEM SUMMARY
A115: Schedule C | E115: Date: | F115: 42415 | K115: Need to enter the difference:
A116: Item | B116: 2.29 Rig Mats
A118: Description | C118: per | D118: Unit Price | E118: Units | F118: Amount | K118: Previous
A119: 2.29 | B119: Rig Mats | K119: 42735 | L119: 42384 | M119: 42400 | N119: 42415 | O119: To Date:
B120: Oak Interlocking Mats | C120: per mat | D120: 4.5 | E120: 2700 | F120: =E120*D120 -> 12150 | K120: 15876 | L120: 8100 | M120: 8640 | N120: 2700 | O120: =SUM(K120:N120) -> 35316
B121: Rig mats complete with metal frame (appox. 8' x 20') | C121: per mat | D121: 45 | F121: =E121*D121 -> 0 | K121: 71442 | L121: 36450 | M121: 38880 | N121: 12150 | O121: =SUM(K121:N121) -> 158922
N124: Pulled out on the 6th.
E125: Total | F125: =SUM(F119:F124) -> 12150
A127: =Summary!$G$9 -> Contractor
C131: =Summary!$G$10 -> Construction Manager
A133: =Summary!$G$11 -> PIPELINE PROJECT
A145: UNIT PRICE ITEM SUMMARY
A148: Schedule C | E148: Date: | F148: 42460 | K148: Need to enter the difference:
A149: Item | B149: 2.29 Rig Mats
L150: 42460
A151: Description | C151: per | D151: Unit Price | E151: Units | F151: Amount | I151: CNRL | K151: 1237 & 1238: | L151: 1350
A152: 2.29 | B152: Rig Mats
B153: Oak Interlocking Mats | C153: per mat | D153: 4.5 | E153: 1398 | F153: =E153*D153 -> 6291 | I153: 30+551 Frac | K153: 2980,0982,0984,0986: | L153: 48
B154: Rig mats complete with metal frame (appox. 8' x 20') | C154: per mat | D154: 45 | F154: =E154*D154 -> 0 | L154: =SUM(L151:L153) -> 1398
E158: Total | F158: =SUM(F152:F157) -> 6291
A160: =Summary!$G$9 -> Contractor
C164: =Summary!$G$10 -> Construction Manager
A166: =Summary!$G$11 -> PIPELINE PROJECT
A178: UNIT PRICE ITEM SUMMARY
A181: Schedule C | E181: Date: | F181: 42475
A182: Item | B182: 2.29 Rig Mats
L183: 42475
A184: Description | C184: per | D184: Unit Price | E184: Units | F184: Amount | I184: CNRL | L184: 1275
A185: 2.29 | B185: Rig Mats
B186: Oak Interlocking Mats | C186: per mat | D186: 4.5 | E186: 1275 | F186: =E186*D186 -> 5737.5
B187: Rig mats complete with metal frame (appox. 8' x 20') | C187: per mat | D187: 45 | F187: =E187*D187 -> 0 | L187: =SUM(L184:L186) -> 1275
E191: Total | F191: =SUM(F185:F190) -> 5737.5
A193: =Summary!$G$9 -> Contractor
C197: =Summary!$G$10 -> Construction Manager
A199: =Summary!$G$11 -> PIPELINE PROJECT
A211: UNIT PRICE ITEM SUMMARY
A214: Schedule C | E214: Date: | F214: 42490
A215: Item | B215: 2.29 Rig Mats
L216: 42490
A217: Description | C217: per | D217: Unit Price | E217: Units | F217: Amount | I217: CNRL
A218: 2.29 | B218: Rig Mats
B219: Oak Interlocking Mats | C219: per mat | D219: 4.5 | E219: 340 | F219: =E219*D219 -> 1530
B220: Rig mats complete with metal frame (appox. 8' x 20') | C220: per mat | D220: 45 | F220: =E220*D220 -> 0 | L220: =SUM(L217:L219) -> 0
E224: Total | F224: =SUM(F218:F223) -> 1530
A226: =Summary!$G$9 -> Contractor
C230: =Summary!$G$10 -> Construction Manager
A232: =Summary!$G$11 -> PIPELINE PROJECT
A244: UNIT PRICE ITEM SUMMARY
A247: Schedule C | E247: Date: | F247: =Summary!$G$3 -> 42505
A248: Item | B248: 2.29 Rig Mats
L249: 42490
A250: Description | C250: per | D250: Unit Price | E250: Units | F250: Amount | I250: CNRL
A251: 2.29 | B251: Rig Mats
B252: Oak Interlocking Mats | C252: per mat | D252: 4.5 | F252: =E252*D252 -> 0
B253: Rig mats complete with metal frame (appox. 8' x 20') | C253: per mat | D253: 45 | F253: =E253*D253 -> 0 | L253: =SUM(L250:L252) -> 0
E257: Total | F257: =SUM(F251:F256) -> 0
A259: =Summary!$G$9 -> Contractor
C263: =Summary!$G$10 -> Construction Manager

Sheet 2.31
A1: =Summary!$G$11 -> PIPELINE PROJECT
A13: UNIT PRICE ITEM SUMMARY
A16: Schedule C | E16: Date: | F16: 42400
A17: Item | B17: 2.31 Move Around
A19: Description | C19: per | D19: Unit Price | E19: Units | F19: Amount
A20: 2.31 | B20: Move Around- Bending
B21: a) Within 10 km of ROW | C21: Crew | D21: 4500 | E21: 1 | F21: =E21*D21 -> 4500 | I21: 42716 | J21: 56+109- Bending Part crew move around so within 10 km of ROW used
B22: b) 10 to -25 km of ROW | C22: Crew | D22: 8200 | J22: KP 51+500 to 61+800 area
E29: Total | F29: =SUM(F20:F28) -> 4500
A31: =Summary!$G$9 -> Contractor
C35: =Summary!$G$10 -> Construction Manager
A37: =Summary!$G$11 -> PIPELINE PROJECT
A49: UNIT PRICE ITEM SUMMARY
A52: Schedule C | E52: Date: | F52: 42429
A53: Item | B53: 2.31 Move Around
I54: 42409 | J54: 48+800-Grade- Move Around Bear Den | N54: 0763 | P54: 3400
A55: Description | C55: per | D55: Unit Price | E55: Units | F55: Amount | I55: 42424 | J55: 48+800-Bending- Move Around Bear Den | N55: 0229/0229 | P55: 4500 | Q55: =P55 -> 4500
A56: 2.31 | B56: Move Around- Bending | I56: 42425 | J56: 48+800-Welding- Move Around Bear Den | P56: 11050 | Q56: =P56 -> 11050
B57: a) Within 10 km of ROW | C57: Crew | D57: 4500 | E57: 1 | F57: =E57*D57 -> 4500 | I57: 42426 | J57: 48+800-Coating- Move Around Bear Den | N57: 0281 | P57: 4500 | Q57: =P57 -> 4500
B58: b) 10 to -25 km of ROW | C58: Crew | D58: 8200 | F58: =E58*D58 -> 0 | I58: 42429 | J58: 48+800-Ditching- Move Around Bear Den | N58: 0765 | P58: 10500
B59: Move Around- Welding | I59: 42429 | J59: 48+800-Lower-In- Move Around Bear Den | N59: 0766 | P59: 9000
B60: a) Within 10 km of ROW | C60: Crew | D60: 11050 | E60: 1 | F60: =E60*D60 -> 11050 | I60: 42430 | J60: 48+800-Backfill- Move Around Bear Den | N60: 0144 | P60: 9000
B61: b) 10 to -25 km of ROW | C61: Crew | D61: 17600 | F61: =E61*D61 -> 0 | K61: test | P61: 4500
B62: Move Around- Coating | K62: Tie-ins | L62: 4 crew- 9,000 | P62: 27000
B63: a) Within 10 km of ROW | C63: Crew | D63: 4500 | E63: 1 | F63: =E63*D63 -> 4500 | K63: Initial clean up | P63: 12000
B64: b) 10 to -25 km of ROW | C64: Crew | D64: 8200 | F64: =E64*D64 -> 0 | K64: final Clean up | P64: 12000
E65: Total | F65: =SUM(F56:F64) -> 20050 | P65: =SUM(P54:P64) -> 107450 | Q65: =SUM(Q54:Q64) -> 20050
A67: =Summary!$G$9 -> Contractor
C71: =Summary!$G$10 -> Construction Manager
A73: =Summary!$G$11 -> PIPELINE PROJECT
A85: UNIT PRICE ITEM SUMMARY
A88: Schedule C | E88: Date: | F88: 42444
A89: Item | B89: 2.31 Move Around
I90: 42409 | J90: 48+800-Grade- Move Around Bear Den | N90: 0763 | P90: 3400 | Q90: 3400
A91: Description | C91: per | D91: Unit Price | E91: Units | F91: Amount | I91: 42424 | J91: 48+800-Bending- Move Around Bear Den | N91: 0229/0229 | P91: 4500 | R91: paid Feb 29
A92: 2.31 | B92: Move Around- Grading | I92: 42425 | J92: 48+800-Welding- Move Around Bear Den | P92: 11050 | R92: paid Feb 29
B93: a) Within 10 km of ROW | C93: Crew | D93: 10500 | E93: 0.3238094 | F93: =E93*D93 -> 3399.9987 | I93: 42426 | J93: 48+800-Coating- Move Around Bear Den | N93: 0281 | P93: 4500 | R93: paid Feb 29
B94: b) 10 to -25 km of ROW | C94: Crew | D94: 16400 | F94: =E94*D94 -> 0 | I94: 42429 | J94: 48+800-Ditching- Move Around Bear Den | N94: 0765 | P94: 10500 | Q94: 10500
B95: Move Around- Trenching | I95: 42429 | J95: 48+800-Lower-In- Move Around Bear Den | N95: 0766 | P95: 9000 | Q95: 9000
B96: a) Within 10 km of ROW | C96: Crew | D96: 10500 | E96: 1 | F96: =E96*D96 -> 10500 | I96: 42430 | J96: 48+800-Backfill- Move Around Bear Den | N96: 0144 | P96: 9000 | Q96: 9000
B97: b) 10 to -25 km of ROW | C97: Crew | D97: 16400 | F97: =E97*D97 -> 0 | K97: test | P97: 4500
B98: Move Around- Lower-In | K98: Tie-ins | L98: 4 crew- 9,000 | P98: 27000
B99: a) Within 10 km of ROW | C99: Crew | D99: 9000 | E99: 1 | F99: =E99*D99 -> 9000 | K99: Initial clean up | P99: 12000
B100: b) 10 to -25 km of ROW | C100: Crew | D100: 15200 | F100: =E100*D100 -> 0 | K100: final Clean up | P100: 12000
B101: Move Around- Backfill | P101: =SUM(P90:P100) -> 107450 | Q101: =SUM(Q90:Q100) -> 31900
B102: a) Within 10 km of ROW | C102: Crew | D102: 9000 | E102: 1 | F102: =E102*D102 -> 9000
B103: b) 10 to -25 km of ROW | C103: Crew | D103: 15200 | F103: =E103*D103 -> 0
E104: Total | F104: =SUM(F92:F103) -> 31899.999
A106: =Summary!$G$9 -> Contractor
C110: =Summary!$G$10 -> Construction Manager
A112: =Summary!$G$11 -> PIPELINE PROJECT
A124: UNIT PRICE ITEM SUMMARY
A127: Schedule C | E127: Date: | F127: 42490
A128: Item | B128: 2.31 Move Around
I129: 42409 | J129: 48+800-Grade- Move Around Bear Den | N129: 0763 | P129: 3400 | Q129: 3400 | R129: paid Mar 15
A130: Description | C130: per | D130: Unit Price | E130: Units | F130: Amount | I130: 42424 | J130: 48+800-Bending- Move Around Bear Den | N130: 0229/0229 | P130: 4500 | R130: paid Feb 29
A131: 2.31 | B131: Move Around- Tie-Ins | I131: 42425 | J131: 48+800-Welding- Move Around Bear Den | P131: 11050 | R131: paid Feb 29
B132: a) Within 10 km of ROW | C132: Crew | D132: 9000 | E132: 2 | F132: =E132*D132 -> 18000 | I132: 42426 | J132: 48+800-Coating- Move Around Bear Den | N132: 0281 | P132: 4500 | R132: paid Feb 29
B133: b) 10 to -25 km of ROW | C133: Crew | D133: 15200 | F133: =E133*D133 -> 0 | I133: 42429 | J133: 48+800-Ditching- Move Around Bear Den | N133: 0765 | P133: 10500 | Q133: 10500 | R133: paid Mar 15
I134: 42429 | J134: 48+800-Lower-In- Move Around Bear Den | N134: 0766 | P134: 9000 | Q134: 9000 | R134: paid Mar 15
I135: 42430 | J135: 48+800-Backfill- Move Around Bear Den | N135: 0144 | P135: 9000 | Q135: 9000 | R135: paid Mar 15
K136: test | P136: 4500
I137: 42442 | K137: Tie-ins | L137: 4 crew- 9,000 | N137: 1454 | P137: 27000 | Q137: 18000
K138: Initial clean up | P138: 12000
K139: final Clean up | P139: 12000
P140: =SUM(P129:P139) -> 107450 | Q140: =SUM(Q129:Q139) -> 49900
E143: Total | F143: =SUM(F131:F142) -> 18000
A145: =Summary!$G$9 -> Contractor
C149: =Summary!$G$10 -> Construction Manager
A151: =Summary!$G$11 -> PIPELINE PROJECT
A163: UNIT PRICE ITEM SUMMARY
A166: Schedule C | E166: Date: | F166: =Summary!$G$3 -> 42505
A167: Item | B167: 2.31 Move Around
I168: 42409 | J168: 48+800-Grade- Move Around Bear Den | N168: 0763 | P168: 3400 | Q168: 3400 | R168: paid Mar 15
A169: Description | C169: per | D169: Unit Price | E169: Units | F169: Amount | I169: 42424 | J169: 48+800-Bending- Move Around Bear Den | N169: 0229/0229 | P169: 4500 | R169: paid Feb 29
A170: 2.31 | B170: Move Around- Tie-Ins | I170: 42425 | J170: 48+800-Welding- Move Around Bear Den | P170: 11050 | R170: paid Feb 29
B171: a) Within 10 km of ROW | C171: Crew | D171: 9000 | F171: =E171*D171 -> 0 | I171: 42426 | J171: 48+800-Coating- Move Around Bear Den | N171: 0281 | P171: 4500 | R171: paid Feb 29
B172: b) 10 to -25 km of ROW | C172: Crew | D172: 15200 | F172: =E172*D172 -> 0 | I172: 42429 | J172: 48+800-Ditching- Move Around Bear Den | N172: 0765 | P172: 10500 | Q172: 10500 | R172: paid Mar 15
I173: 42429 | J173: 48+800-Lower-In- Move Around Bear Den | N173: 0766 | P173: 9000 | Q173: 9000 | R173: paid Mar 15
I174: 42430 | J174: 48+800-Backfill- Move Around Bear Den | N174: 0144 | P174: 9000 | Q174: 9000 | R174: paid Mar 15
K175: test | P175: 4500
I176: 42442 | K176: Tie-ins | L176: 4 crew- 9,000 | N176: 1454 | P176: 27000 | Q176: 18000
K177: Initial clean up | P177: 12000
K178: final Clean up | P178: 12000
P179: =SUM(P168:P178) -> 107450 | Q179: =SUM(Q168:Q178) -> 49900
E182: Total | F182: =SUM(F170:F181) -> 0
A184: =Summary!$G$9 -> Contractor
C188: =Summary!$G$10 -> Construction Manager

Sheet 2.35
A1: =Summary!$G$11 -> PIPELINE PROJECT
A13: UNIT PRICE ITEM SUMMARY
A16: Schedule C | E16: Date: | F16: =Summary!$G$3 -> 42505
A17: Item | B17: 2.35 Crossings Under Existing Buried Pipelines
A19: Description | C19: per | D19: Unit Price | E19: Units | F19: Amount
A20: 2.35 | B20: Crossings Under Existing Buried Pipelines
B21: Add per crossing | C21: Crossing | D21: 18360 | E21: 3 | F21: =E21*D21 -> 55080
E32: Total | F32: =SUM(F20:F31) -> 55080
A34: =Summary!$G$9 -> Contractor
C38: =Summary!$G$10 -> Construction Manager

Sheet 3.2.2-2A
A1: =Summary!G11 -> PIPELINE PROJECT
A13: 3.0 INCREMENTAL LUMP SUM
A15: Schedule C | F15: Billing Date: | G15: =Summary!G3 -> 42505
A16: Item | B16: HDD and Brored Crossing Lump Sum Prices for 12" Oil Line Segment
A18: Description | C18: per | D18: Unit Price | E18: Previous | F18: Units | G18: Billing Amount
A19: 2A-C.1 | B19: NPS 12 HDD Crossing Installation- Bow River | C19: Lump Sum | D19: 344650 | E19: 1 | G19: =F19*D19 -> 0
A20: 2A-C.2 | B20: NPS 12 HDD Crossing Installation- Irrigation Canal & Reservoir | C20: Lump Sum | D20: 286300 | E20: 1
A21: 2A-C.3 | B21: NPS 12 HDD Crossing Installation- Secondary Hwy 524 | C21: Lump Sum | D21: 18000 | E21: 1
A22: 2A-C.4 | B22: NPS 12 HDD Crossing Installation- Secondary Hwy 875 | C22: Lump Sum | D22: 18000 | E22: 1
A23: 2A-C.5 | B23: NPS 12 HDD Crossing Installation- Old Man River | C23: Lump Sum | D23: 386350 | E23: 1
F27: Total | G27: =SUM(G19:G26) -> 0
A29: =Summary!G9 -> Contractor
D33: =Summary!G10 -> Construction Manager

Sheet 3.1.2-2A
A1: =Summary!G11 -> PIPELINE PROJECT
A13: 3.0 INCREMENTAL LUMP SUM
A15: Schedule C | E15: Billing Date: | F15: =Summary!G3 -> 42505
A16: Item | B16: Fabricated Assembly Lump Sum Prices For 12" Oil Line Segment
A18: Description | C18: per | D18: Unit Price | E18: Previous | F18: Units | G18: Billing Amount
A19: 2A-B.1 | B19: Fabricate Test & Install NPS 12 Mainline Block Valve Assembly | C19: Lump Sum | D19: 25050 | E19: 1 | G19: =F19*D19 -> 0
A20: 2A-B.2 | B20: Fabricate Test & Install NPS 12 Mainline Block Valve & Check Valve Assembly | C20: Lump Sum | D20: 28650 | E20: 1 | G20: =F20*D20 -> 0
F27: Total | G27: =SUM(G19:G26) -> 0
A29: =Summary!G9 -> Contractor
D33: =Summary!G10 -> Construction Manager

Sheet 4.1
A1: =Summary!G11 -> PIPELINE PROJECT
A13: UNIT PRICE ITEM SUMMARY
A14: Topsoil Stripping & Replacement
A16: Schedule C | G16: Billing Date: | H16: =Summary!G3 -> 42505
A17: Item | B17: 4.1
A19: Description | C19: per | D19: Unit Price | E19: Units Stripped | F19: Units Replaced | G19: Total Units | H19: Amount This Period
A20: 4.1 | B20: Topsoil Stripping And Replacement
A21: 4.1.1 | B21: Removal and restoration of topsoil over trench area (blade width stripping)
B22: a) 0 to 40 cm in depth | C22: Per Lin. m | D22: 3.5 | G22: =SUM(E22:F22) -> 0 | H22: =(F22*D22/2)+(E22*D22/2) -> 0
B23: b) 40 cm and greater | C23: Per Lin. m | D23: 4.5 | G23: =SUM(E23:F23) -> 0 | H23: =(F23*D23/2)+(E23*D23/2) -> 0
A24: 4.1.2 | B24: Removal and restoration of topsoil over trench and spoil side area
B25: a) 0 to 40 cm in depth | C25: Per Lin. m | D25: 6.5 | G25: =SUM(E25:F25) -> 0 | H25: =(F25*D25/2)+(E25*D25/2) -> 0
B26: b) 40 cm and greater | C26: Per Lin. m | D26: 9.5 | G26: =SUM(E26:F26) -> 0 | H26: =(F26*D26/2)+(E26*D26/2) -> 0
A27: 4.1.3 | B27: Removal and restoration of topsoil over the entire Construction Right of Way
B28: a) 0 to 40 cm in depth | C28: Per Lin. m | D28: 9.5 | G28: =SUM(E28:F28) -> 0 | H28: =(F28*D28/2)+(E28*D28/2) -> 0
B29: b) 40 cm and greater | C29: Per Lin. m | D29: 12.5 | G29: =SUM(E29:F29) -> 0 | H29: =(F29*D29/2)+(E29*D29/2) -> 0
E31: Total | G31: =SUM(G20:G30) -> 0 | H31: =SUM(H20:H30) -> 0
A33: =Summary!G9 -> Contractor
E36: =Summary!G10 -> Construction Manager

Sheet RFI's
A1: RFI Log
A3: Expansion Pipeline Project | F3: Date: | G3: =Summary!G3 -> 42505
A4: Request for Information (RFI)
A5: RFI # | B5: Description | C5: Originator | D5: Date Issued | E5: Reply Date Required | F5: Status | G5: Cost Impact | H5: Change Order Request | I5: Change Order (if applicable) | J5: RFI Complete
A6: W2K-RFI-0001 | B6: Additional HDD Location | C6: Mark Ringrose | D6: 42311 | E6: 42311 | F6: Approved | J6: Complete
A7: W2K-RFI-0002 | B7: Harvest Crossing and Road Use Agreements | C7: Mark Ringrose | D7: 42311 | E7: 42317 | F7: Approved | J7: Complete
A8: W2K-RFI-0003 | B8: Road Allowance Workspace | C8: Mark Ringrose | D8: 42312 | E8: 42318 | F8: Approved | J8: Complete
A9: W2K-RFI-0004 | B9: Corinthian Access Roads & Pipeline Crossings- Crossing & Proximity Agreements | C9: Mark Ringrose | D9: 42312 | E9: 42324 | F9: Approved | J9: Complete
A10: W2K-RFI-0005 | B10: Depth of Cover at Ephemeral Draws and Intermittent Creek Crossings | C10: Mark Ringrose | D10: 42314 | E10: 42318 | F10: Approved | J10: Complete
A11: W2K-RFI-0006 | B11: Slashing Standby | C11: Kendall O'Regan | D11: 42314 | E11: 42317 | F11: N/A | G11: 12805 | J11: Complete
A12: W2K-RFI-0007 | B12: Purchase Of Two-Way Radios | C12: Kendall O'Regan | D12: 42314 | E12: 42317 | F12: Approved | G12: 6751 | I12: CO2 | J12: Complete
A13: W2K-RFI-0008 | B13: Weather Conditions & Winter Welding | C13: Andrew Elash | D13: 42314 | E13: 42318 | F13: Not Approved | J13: Complete
A14: W2K-RFI-0009 | B14: Typical Construction Drawings | C14: Andrew Elash | D14: 42314 | E14: 42318 | F14: Approved | J14: Complete
A15: W2K-RFI-0010 | B15: Additional TFA For ROW Access | C15: Mark Ringrose | D15: 42314 | E15: 42318 | F15: Approved | J15: Complete
A16: W2K-RFI-0011 | B16: Welder Testing- Line Up Clamps | C16: Andrew Elash | D16: 42314 | E16: 42318 | F16: Approved | J16: Complete
A17: W2K-RFI-0012R1 | B17: Removal Of Pipe Clamps During Hot Pass | C17: Andrew Elash | D17: 42361 | E17: 42369 | F17: Responded | J17: Complete
A18: W2K-RFI-0013 | B18: Minimum Tie Install Temperature | C18: Andrew Elash | D18: 42314 | E18: 42318 | F18: Approved | J18: Complete
A19: W2K-RFI-0014 | B19: Pipe & Bend MTRs | C19: Andrew Elash | D19: 42314 | E19: 42318 | F19: Approved | J19: Complete
A20: W2K-RFI-0015R3 | B20: Project Delay Indirect Costs, Equipment Costs & Foremen Retention | C20: Kendall O'Regan | D20: 42318 | E20: 42320 | F20: Approved | G20: 555229.22 | I20: CO5 | J20: Complete
A21: W2K-RFI-0016 | B21: Combine Typical Drills #6 (38+390) & #7 (38+606) | C21: Andrew Elash | D21: 42319 | E21: 42324 | F21: Approved | J21: Complete
A22: W2K-RFI-0017R1 | B22: Extend Bore At KP 22+821 | C22: Andrew Elash | D22: 42319 | E22: 42324 | F22: Approved | J22: Complete
A23: W2K-RFI-0018 | B23: Extra Work Space Required For HDD At KP 26+759 | C23: Andrew Elash | D23: 42319 | E23: 42324 | F23: Approved | J23: Complete
A24: W2K-RFI-0019R1 | B24: Husky Road Use Agreement Required For Husky Roads | C24: Andrew Elash | D24: 42320 | E24: 42324 | F24: Approved | J24: Complete
A25: W2K-RFI-0020 | B25: Clearing Support: Change Request CR-0001 Proposal | C25: Mark Ringrose | D25: 42327 | E25: 42329 | F25: Approved | I25: CO3 | J25: Complete
A26: W2K-RFI-0021 | B26: Sand Blasting Abrasive | C26: Andrew Elash | D26: 42327 | E26: 42328 | F26: Approved | J26: Complete
A27: W2K-RFI-0022 | B27: Hydro Test Pressure | C27: Andrew Elash | D27: 42327 | E27: 42328 | F27: Approved | J27: Complete
A28: W2K-RFI-0023 | B28: CNRL Pipeline Crossings | C28: Kristen Jones | D28: 42327 | E28: 42332 | F28: Approved | J28: Complete
A29: W2K-RFI-0024 | B29: Hauling Of Stripped Topsoil | C29: Mark Ringrose | D29: 42328 | E29: 42332 | F29: Not Approved | G29: 34974.24 | J29: Complete
A30: W2K-RFI-0025 | B30: Extended Bore KP 57+204 | C30: Mark Ringrose | D30: 42328 | E30: 42332 | F30: Approved | J30: Complete
A31: W2K-RFI-0026R1 | B31: 24Hr Medic Coverage | C31: Mark Ringrose | D31: 42331 | E31: 42333 | F31: Approved | G31: 103635 | I31: CO4 | J31: Complete
A32: W2K-RFI-0027
A33: W2K-RFI-0028 | B33: River Pull Back (Over Bend Radius) | C33: Mark Ringrose | D33: 42331 | E33: 42333 | F33: Approved | J33: Complete
A34: W2K-RFI-0029 | B34: Approval To Use Methanol For HDD Pre-Tests | C34: Mark Ringrose | D34: 42331 | E34: 42333 | F34: Approved | J34: Complete
A35: W2K-RFI-0030R1 | B35: Atco Power Pole At 8+221 | C35: Mark Ringrose | D35: 42331 | E35: 42333 | F35: Approved | J35: Complete
A36: W2K-RFI-0031 | B36: Removal Of USM & Topsoil | C36: Mark Ringrose | D36: 42331 | E36: 42333 | F36: Approved | J36: Complete
A37: W2K-RFI-0032 | B37: Sump Pit Excavation- Test Holes | C37: Mark Ringrose | D37: 42334 | E37: 42335 | F37: Approved | G37: 20000 | I37: CO9 | J37: Complete
A38: W2K-RFI-0033 | B38: Minimum Separation During HDD | C38: Mark Ringrose | D38: 42338 | E38: 42339 | F38: Reviewed | J38: Complete
A39: W2K-RFI-0034 | B39: Trucking Mats To Cutbank HDD | C39: Mark Ringrose | D39: 42339 | E39: 42341 | F39: Approved | G39: 76820 | I39: CO10 | J39: Complete
A40: W2K-RFI-0035 | B40: Atco Power Pole At 14+157 | C40: Mark Ringrose | D40: 42339 | E40: 42342 | F40: Approved | J40: Complete
A41: W2K-RFI-0036 | B41: Proposed Ditch Line KP 52+445 | C41: Mark Ringrose | D41: 42340 | E41: 42341 | F41: Approved | J41: Complete
A42: W2K-RFI-0037 | B42: HD Bore Live Line Separations | C42: Mark Ringrose | D42: 42341 | E42: 42343 | F42: Approved | J42: Complete
A43: W2K-RFI-0038R2 | B43: NuVista Riser | C43: Mark Ringrose | D43: 42339 | E43: 42342 | F43: No Response | G43: 9586.06 | J43: Complete
A44: W2K-RFI-0039 | B44: Red One Rock Shield In Lieu of Tuff-N-Nuff | C44: Mark Ringrose | D44: 42341 | E44: 42345 | F44: Approved | J44: Complete
A45: W2K-RFI-0040 | B45: Crossing Agreement SE-11-68-8 W6M | C45: Mark Ringrose | D45: 42343 | E45: 42343 | F45: Approved | J45: Complete
A46: W2K-RFI-0041 | B46: Direct Drilling Support (440 Rig) | C46: Mark Ringrose | D46: 42345 | E46: 42352 | F46: Not Approved | J46: Complete
A47: W2K-RFI-0042 | B47: Digging Sumps | C47: Mark Ringrose | D47: 42712 | E47: 42715 | F47: Approved | I47: CO11 & CO43 | J47: Complete
A48: W2K-RFI-0043 | B48: Lowering In Deviation | C48: Mark Ringrose | D48: 42346 | E48: 42348 | F48: Approved | J48: Complete
A49: W2K-RFI-0044 | B49: Unload Pembina Owned Mats | C49: Mark Ringrose | D49: 42388 | E49: 42389 | F49: Approved | G49: 19408 | I49: CO17 | J49: Complete | L49: 19.41/mat
A50: W2K-RFI-0045 | B50: Bentonite | C50: Mark Ringrose | D50: 42346 | E50: 42348 | F50: Not Approved | J50: Complete
A51: W2K-RFI-0046 | B51: Performance Vac- Mud Disposal | C51: Mark Ringrose | D51: 42348 | E51: 42350 | F51: Not Approved | G51: 50000 | I51: CO12 | J51: Complete
A52: W2K-RFI-0047
A53: W2K-RFI-0048 | B53: Rework Due To Survey Error | C53: Mark Ringrose | D53: 42350 | E53: 42351 | F53: Approved | G53: 4250.2 | I53: CO13 | J53: Complete
A54: W2K-RFI-0049 | B54: Cost Estimate Holiday Support | C54: Mark Ringrose | D54: 42359 | E54: 42361 | F54: No Response From SITE | G54: 175603.32 | J54: Complete
A55: W2K-RFI-0050 | B55: Miscellaneous Extra Works | C55: Mark Ringrose | D55: 42354 | E55: 42356 | F55: Approved | I55: CO14 | J55: Ongoing
A56: W2K-RFI-0051 | B56: New Weld Procedure | C56: Mark Ringrose | D56: 42354 | E56: 42356 | F56: Approved | J56: Complete
A57: W2K-RFI-0052 | B57: Extended Bore KP 67+800 | C57: Mark Ringrose | D57: 42355 | E57: 42359 | F57: Approved | J57: Complete
A58: W2K-RFI-0053R2 | B58: Extended Bore KP 24+539 to 24+942 | C58: Mark Ringrose | D58: 42356 | E58: 42359 | F58: Partly Approved | J58: Complete
A59: W2K-RFI-0054 | B59: Grade Crew Delays | C59: Mark Ringrose | D59: 42375 | E59: 42377 | F59: Approved | J59: Complete
A60: W2K-RFI-0055R1 | B60: Replace 8.4 mm Bore Pipe With 9.5 mm | C60: Mark Ringrose | D60: 42375 | E60: 42376 | F60: Approved | G60: 42835.64 | J60: Complete
A61: W2K-RFI-0056 | B61: Coating No-Productive Time | C61: Mark Ringrose | D61: 42376 | E61: 42378 | F61: Not Approved | J61: Complete
A62: W2K-RFI-0057 | B62: Access Around Beaver Dam (KP 17+772) | C62: Mark Ringrose | D62: 42376 | E62: 42377 | F62: Not Approved | J62: Complete
A63: W2K-RFI-0058 | B63: Remob to HDD | C63: Mark Ringrose | D63: 42378 | E63: 42379 | F63: Approved | J63: Complete
A64: W2K-RFI-0059 | B64: Haul Water ROW Freezing | C64: Mark Ringrose | D64: 42377 | E64: 42378 | F64: Approved | G64: 23684.06 | I64: CO18 | J64: Complete
A65: W2K-RFI-0060
A66: W2K-RFI-0061 | B66: Crossing Agreement- Station (Conoco Phillips) | C66: Mark Ringrose | D66: 42382 | E66: 42383 | F66: Approved | J66: Complete
A67: W2K-RFI-0062 | B67: Long Run Exploration Rep | C67: Mark Ringrose | D67: 42383 | E67: 42384 | F67: Approved | G67: 5040 | I67: CO19 | J67: Complete
A68: W2K-RFI-0063 | B68: Hydrovac Truck Supply | C68: Mark Ringrose | D68: 42383 | E68: 42384 | F68: Not Approved | G68: 15000 | J68: Complete
A69: W2K-RFI-0064 | B69: Additional RT Trucks | C69: Mark Ringrose | D69: 42383 | E69: 42384 | F69: Approved | J69: Complete
A70: W2K-RFI-0065 | B70: Combine Bore 15+920 to 16+010/16+043 to 16+097 | C70: Mark Ringrose | D70: 42383 | E70: 42387 | F70: Approved | J70: Complete
A71: W2K-RFI-0066 | B71: Bore @ 69+397 | C71: Mark Ringrose | D71: 42383 | E71: 42387 | F71: Approved | J71: Complete
A72: W2K-RFI-0067 | B72: River Additional Rig Support | C72: Mark Ringrose | D72: 42383 | E72: 42384 | F72: Approved | G72: 66500.64 | I72: CO20 | J72: Complete
A73: W2K-RFI-0068 | B73: Addition Of 60 m On Drag Section At KP 0+000 | C73: Mark Ringrose | D73: 42384 | E73: 42387 | F73: Approved | J73: Complete
A74: W2K-RFI-0069 | B74: Nova Line Crossing At 39+400 | C74: Mark Ringrose | D74: 42385 | E74: 42387 | F74: Not Approved | J74: Complete
A75: W2K-RFI-0070R1 | B75: Hydrovac Support | C75: Mark Ringrose | D75: 42389 | E75: 42391 | F75: Approved | G75: 359953.32 | I75: CO23 | J75: Complete
A76: W2K-RFI-0071 | B76: Additional Tie-In Support | C76: Mark Ringrose | D76: 42396 | E76: 42398 | F76: Approved | G76: 763439.04 | I76: CO24 | J76: Complete
A77: W2K-RFI-0072 | B77: HDD Support Crews | C77: Mark Ringrose | D77: 42397 | E77: 42400 | F77: Approved | G77: 1201072.3 | I77: CO24 | J77: Complete
A78: W2K-RFI-0073 | B78: Deviation From Pre Testing Drag Sections | C78: Mark Ringrose | D78: 42390 | E78: 42393 | F78: Not Approved | J78: Complete
A79: W2K-RFI-0074 | B79: Deviation From Pre Testing Drag Sections- Cleaning Pig Tech. Info | C79: Mark Ringrose | D79: 42391 | E79: 42395 | F79: Approved | J79: Complete
A80: W2K-RFI-0075 | B80: Tracked HydroVac Truck Supply | C80: Mark Ringrose | D80: 42391 | E80: 42392 | F80: Approved | G80: 118900 | I80: C044 | J80: Complete
A81: W2K-RFI-0076 | B81: Husky Crossing At 28+221 | C81: Mark Ringrose | D81: 42392 | E81: 42395 | F81: Replied | J81: Complete
A82: W2K-RFI-0077 | B82: Hot Bend @ 10+711 | C82: Mark Ringrose | D82: 42392 | E82: 42395 | F82: Approved | J82: Complete
A83: W2K-RFI-0078 | B83: Combine Bores 34+139 & 34+228 | C83: Mark Ringrose | D83: 42395 | E83: 42399 | F83: Not Approved | J83: Complete
A84: W2K-RFI-0079R1 | B84: Extend Bore 35+273 To 35+327 | C84: Mark Ringrose | D84: 42395 | E84: 42399 | F84: Approved | J84: Complete
A85: W2K-RFI-0080 | B85: Extend HDD 35+668 To 35+886 | C85: Mark Ringrose | D85: 42395 | E85: 42399 | F85: Approved | J85: Complete
A86: W2K-RFI-0081R1 | B86: Open Cut To Trenchless Crossings | C86: Mark Ringrose | D86: 42395 | E86: 42399 | F86: Partly Approved | J86: Complete
A87: W2K-RFI-0082 | B87: Hydrotest Water Source | C87: Mark Ringrose | D87: 42396 | E87: 42399 | F87: Responded | J87: Complete
A88: W2K-RFI-0083 | B88: Additional Grade Through Crossings | C88: Mark Ringrose | D88: 42398 | E88: 42401 | F88: Responded | J88: Complete
A89: W2K-RFI-0084 | B89: Safety Stand Down Jan 18th | C89: Mark Ringrose | D89: 42399 | E89: 42401 | F89: Approved | G89: 215855.08 | I89: CO22 | J89: Complete
A90: W2K-RFI-0085 | B90: Clean Up Release | C90: Mark Ringrose | D90: 42399 | E90: 42401 | F90: Approved | G90: 60808.38 | I90: CO21 | J90: Complete
A91: W2K-RFI-0086 | B91: Miscellaneous Extra Works | C91: Mark Ringrose | D91: 42399 | E91: 42401 | F91: Not Approved | J91: Complete
A92: W2K-RFI-0087R1 | B92: Open Cut To Trenchless Crossings | C92: Mark Ringrose | D92: 42400 | E92: 42404 | F92: Approved | J92: Complete
A93: W2K-RFI-0088 | B93: Drag Section At KP 63+700 To Be Tested In Two Sections | C93: Mark Ringrose | D93: 42406 | E93: 42410 | F93: Approved | J93: Complete
A94: W2K-RFI-0089 | B94: Drag Section At KP 12+500 To Be Tested In Two Sections | C94: Mark Ringrose | D94: 42411 | E94: 42415 | F94: Approved | J94: Complete
A95: W2K-RFI-0090 | B95: Drag Sections At KP 30+115 & 10+608- Add Tested Pipe To Section | C95: Mark Ringrose | D95: 42416 | E95: 42418 | F95: Not Approved | J95: Complete
A96: W2K-RFI-0091 | B96: Water Trucks To Support HDD Rigs | C96: Mark Ringrose | D96: 42416 | E96: 42418 | F96: Approved | G96: 38750 | I96: CO36 | J96: Complete
A97: W2K-RFI-0092 | B97: Backfill Sumps Along ROW | C97: Mark Ringrose | D97: 42417 | E97: 42419 | F97: Approved | G97: 165080.96 | I97: CO33 | J97: Complete
A98: W2K-RFI-0093 | B98: 24Hr Medic Coverage | C98: Mark Ringrose | D98: 42419 | E98: 42421 | F98: Approved | G98: 151000 | I98: CO30 | J98: Complete
A99: W2K-RFI-0094 | B99: Stumping & Grubbing Support | C99: Mark Ringrose | D99: 42419 | E99: 42421 | F99: Approved | G99: 22069.31 | I99: CO29 | J99: Complete
A100: W2K-RFI-0095 | B100: Move Around Bear Den At KP 48+800 | C100: Mark Ringrose | D100: 42420 | E100: 42423 | F100: Approved | I100: UPI | J100: Complete
A101: W2K-RFI-0096 | B101: Clean Up Crew Move Around HDD Drills | C101: Jeremy Manning | D101: 42420 | E101: 42423 | F101: Not Approved | J101: Complete
...

Sheet SI Log
D1: SI Log
A2: Expansion Pipeline Project | D2: Energy Services | I2: Progress Period | J2: =Summary!G4 -> 42491 | K2: To | L2: =Summary!G3 -> 42505
B5: CO | C5: Description | D5: Type | E5: Approved | F5: Forecast | G5: Date | H5: Change | I5: Work
A6: SI | B6: Number | D6: SI | E6: Value | F6: Value | G6: Approved | H6: Order | I6: Status
A7: Number | B7: If Applic. | D7: Change Request | E7: $ | F7: $ | H7: Status | J7: This | K7: Previous | L7: To Date
D8: Change Order | J8: Period
A10: 1 | E10: 0 | F10: 0 | J10: 0 | K10: 0 | L10: =J10+K10 -> 0
A11: 2 | C11: Overnight Hold on Welds | D11: SI | E11: 0 | F11: 0 | J11: 0 | K11: 0 | L11: =J11+K11 -> 0
A12: 3 | C12: Theoretical Road Crossing Depth | D12: SI | E12: 0 | F12: 0 | J12: 0 | K12: 0 | L12: =J12+K12 -> 0
A13: 4 | C13: Minimum Depth Of Cover For Watercourses | D13: SI | E13: 0 | F13: 0 | J13: 0 | K13: 0 | L13: =J13+K13 -> 0
A14: 5 | E14: 0 | F14: 0 | J14: 0 | K14: 0 | L14: =J14+K14 -> 0
A15: 6 | E15: 0 | F15: 0 | J15: 0 | K15: 0 | L15: =J15+K15 -> 0
A16: 7 | E16: 0 | F16: 0 | J16: 0 | K16: 0 | L16: =J16+K16 -> 0
A17: 8 | E17: 0 | F17: 0 | J17: 0 | K17: 0 | L17: =J17+K17 -> 0
A18: 9 | E18: 0 | F18: 0 | J18: 0 | K18: 0 | L18: =J18+K18 -> 0
A19: 10 | E19: 0 | F19: 0 | J19: 0 | K19: 0 | L19: =J19+K19 -> 0
A20: 11 | E20: 0 | F20: 0 | J20: 0 | K20: 0 | L20: =J20+K20 -> 0
A21: 12 | E21: 0 | F21: 0 | J21: 0 | K21: 0 | L21: =J21+K21 -> 0
A22: 13 | E22: 0 | F22: 0 | J22: 0 | K22: 0 | L22: =J22+K22 -> 0
A23: 14 | E23: 0 | F23: 0 | J23: 0 | K23: 0 | L23: =J23+K23 -> 0
A24: 15 | E24: 0 | F24: 0 | J24: 0 | K24: 0 | L24: =J24+K24 -> 0
A25: 16 | E25: 0 | F25: 0 | J25: 0 | K25: 0 | L25: =J25+K25 -> 0
... A39: 30 | E39: 0 | F39: 0 | J39: 0 | K39: 0 | L39: =J39+K39 -> 0
E40: 0 | F40: 0 | J40: 0 | K40: 0 | L40: =J40+K40 -> 0
E41: =J41*1.11 -> 0 | F41: =K41*1.11 -> 0 | J41: 0 | K41: 0 | L41: =J41+K41 -> 0
E42: 0 | F42: 0 | J42: 0 | K42: 0 | L42: =J42+K42 -> 0
C43: Accumulated Value | E43: =SUM(E10:E42) -> 0 | F43: =SUM(F10:F42) -> 0 | I43: Subtotal: | J43: =SUM(J10:J42) -> 0 | K43: =SUM(K10:K42) -> 0 | L43: =SUM(L10:L42) -> 0
I44: Total: | J44: =SUM(J43:J43) -> 0 | K44: =SUM(K43:K43) -> 0 | L44: =SUM(L43:L43) -> 0

Sheet CO Log
D1: Change Order Log
A2: Expansion Pipeline Project | D2: Contractor | I2: Progress Period | J2: =Summary!G4 -> 42491 | K2: To | L2: =Summary!G3 -> 42505
A5: Change | B5: RFI | C5: Description | D5: Type | E5: Approved | F5: Forecast | G5: Date | H5: Change | I5: Work
A6: Order | B6: Number | D6: RFI | E6: Value | F6: Value | G6: Approved | H6: Order | I6: Status
A7: Number | B7: If Applic. | D7: Change Request | E7: $ | F7: $ | H7: Status | J7: This | K7: Previous | L7: To Date
D8: Change Order | J8: Period | N8: 40321283 | R8: If Negative then CO is Over | S8: Pending | T8: Difference
A10: 1 | B10: N/A | C10: Additional Right-of-Way Stripping (Add $12.44 To Base Lay Price) | D10: Change Order | E10: 863980 | F10: 863980 | G10: 42313 | H10: Executed | I10: Ongoing | J10: 4394.62 | K10: 790957.11 | L10: =J10+K10 -> 795351.73 | N10: =E10+N8 -> 41185263 | R10: =F10-L10 -> 68628.27
A11: 2 | B11: 007 | C11: Additional Two Way Radios For Inspection | D11: Change Order | E11: 7088.55 | F11: 7088.55 | G11: 42317 | H11: Executed | I11: Ongoing | J11: 0 | K11: 0 | L11: =J11+K11 -> 0 | N11: =E11+N10 -> 41192352 | R11: =F11-L11 -> 7088.55
A12: 3 | B12: 020 | C12: Clearing Support | D12: Change Order | E12: 670085.52 | F12: 438132.84 | G12: 42340 | H12: Executed | I12: Complete | J12: 0 | K12: 438132.84 | L12: =J12+K12 -> 438132.84 | N12: =E12+N11 -> 41862437 | R12: =F12-L12 -> 0
A13: 4 | B13: 026R1 | C13: 24Hr Medic Coverage | D13: Change Order | E13: 103635 | F13: 103635 | G13: 42340 | H13: Executed | I13: Complete | J13: 0 | K13: 103635 | L13: =J13+K13 -> 103635 | N13: =E13+N12 -> 41966072 | R13: =F13-L13 -> 0
A14: 5 | B14: 015R3 | C14: Delayed Start Due To Weather- Cost Impacts | D14: Change Order | E14: 555229.22 | F14: 555229.22 | G14: 42345 | H14: Executed | I14: Complete | J14: 0 | K14: 555229.22 | L14: =J14+K14 -> 555229.22 | N14: =E14+N13 -> 42521302 | R14: =F14-L14 -> 0
A15: 6 | B15: N/A | C15: UPIs For Progress Payments Dec 15 & Dec 31 2015 | D15: Change Order | E15: 244345.82 | F15: =L15 -> 244345.82 | G15: 42373 | H15: Executed | I15: Complete | J15: 0 | K15: 244345.82 | L15: =J15+K15 -> 244345.82 | N15: =E15+N14 -> 42765647 | O15: PO added 3 cents On CO 6. | R15: =F15-L15 -> 0
A16: 7 | B16: N/A | C16: UPIs For Progress Payment Jan 15 2016 | D16: Change Order | E16: 86343.77 | F16: 86343.77 | G16: 42388 | H16: Executed | I16: Complete | J16: 0 | K16: 86343.77 | L16: =J16+K16 -> 86343.77 | N16: =E16+N15 -> 42851991 | R16: =F16-L16 -> 0
A17: 8 | B17: N/A | C17: VOID | D17: VOID | E17: 0 | F17: 0 | I17: Complete | J17: 0 | K17: 0 | L17: =J17+K17 -> 0 | N17: =E17+N16 -> 42851991 | R17: =F17-L17 -> 0
A18: 9 | B18: 032 | C18: Digging Test Holes | D18: Change Order | E18: 20000 | F18: 18809.25 | G18: 42390 | H18: Executed | I18: Complete | J18: 0 | K18: 18809.25 | L18: =J18+K18 -> 18809.25 | N18: =E18+N17 -> 42871991 | R18: =F18-L18 -> 0
A19: 10 | B19: 034 | C19: Installation/Removal & Trucking Of Access Mats To The River | D19: Change Order | E19: 80000 | F19: 80000 | G19: 42390 | H19: Executed | I19: Complete | J19: 0 | K19: 80000 | L19: =J19+K19 -> 80000 | N19: =E19+N18 -> 42951991 | R19: =F19-L19 -> 0
A20: 11 | B20: 042 | C20: Digging Sumps | D20: Change Order | E20: 60000 | F20: 59756.38 | G20: 42390 | H20: Executed | I20: Complete | J20: 0 | K20: 59756.38 | L20: =J20+K20 -> 59756.38 | N20: =E20+N19 -> 43011991 | R20: =F20-L20 -> 0
A21: 12 | B21: 046 | C21: Performance Vac- Mud Disposal | D21: Change Order | E21: 25000 | F21: 25000 | G21: 42390 | H21: Executed | I21: Ongoing | J21: 0 | K21: 0 | L21: =J21+K21 -> 0 | N21: =E21+N20 -> 43036991 | R21: =F21-L21 -> 25000
A22: 13 | B22: 048 | C22: Rework Due To Survey Error | D22: Change Order | E22: 4250.2 | F22: 3397.2 | G22: 42390 | H22: Executed | I22: Complete | J22: 0 | K22: 3397.2 | L22: =J22+K22 -> 3397.2 | N22: =E22+N21 -> 43041241 | R22: =F22-L22 -> 0
A23: 14 | B23: 050 | C23: Paragon Soils Test Holes & Repair Factory Holidays | D23: Change Order | E23: 2070.78 | F23: 686.9 | G23: 42390 | H23: Executed | I23: Complete | J23: 0 | K23: 686.9 | L23: =J23+K23 -> 686.9 | N23: =E23+N22 -> 43043312 | R23: =F23-L23 -> 0
A24: 15 | B24: N/A | C24: Miscellaneous Additional Costs | D24: Change Order | E24: 50000 | F24: 50000 | G24: 42390 | H24: Executed | I24: Ongoing | J24: 2238.76 | K24: 29808.89 | L24: =J24+K24 -> 32047.65 | N24: =E24+N23 -> 43093312 | R24: =F24-L24 -> 17952.35
A25: 16 | B25: N/A | C25: Damage To Irrigation Pipe | D25: Change Order | E25: 5991.3 | F25: 5991.3 | G25: 42390 | H25: Executed | I25: Complete | J25: 0 | K25: 5991.3 | L25: =J25+K25 -> 5991.3 | N25: =E25+N24 -> 43099304 | R25: =F25-L25 -> 0
A26: 17 | B26: 044 | C26: Unloading Mats | D26: Change Order | E26: 19408 | F26: 19410 | G26: 42395 | H26: Executed | I26: Ongoing | J26: 0 | K26: 5958.87 | L26: =J26+K26 -> 5958.87 | N26: =E26+N25 -> 43118712 | R26: =F26-L26 -> 13451.13
A27: 18 | B27: 059 | C27: Haul Water For ROW Freezing | D27: Change Order | E27: 23684.06 | F27: 23684.06 | G27: 42396 | H27: Executed | I27: Complete | J27: 0 | K27: 23684.06 | L27: =J27+K27 -> 23684.06 | N27: =E27+N26 -> 43142396 | R27: =F27-L27 -> 0
A28: 19 | B28: 062 | C28: Consultant For Long Run Crossing | D28: Change Order | E28: 5040 | F28: 4410 | G28: 42396 | H28: Executed | I28: Complete | J28: 0 | K28: 4410 | L28: =J28+K28 -> 4410 | N28: =E28+N27 -> 43147436 | R28: =F28-L28 -> 0
A29: 20 | B29: 067 | C29: Drilling Support- Extended Schedule At River | D29: Change Order | E29: 88667.52 | F29: 88667.52 | G29: 42396 | H29: Executed | I29: Complete | J29: 0 | K29: 88667.52 | L29: =J29+K29 -> 88667.52 | N29: =E29+N28 -> 43236103 | R29: =F29-L29 -> 0
... A33: 24 | B33: 071 & 072 | C33: Additional Tie-In Support And HDD Support Crews | D33: Change Order | E33: 1964511.4 | F33: 1964511.4 | G33: 42403 | H33: Executed | I33: Complete | J33: 0 | K33: 1964511.4 | L33: =J33+K33 -> 1964511.4 | N33: =E33+N32 -> 45842231 | R33: =F33-L33 -> 0
A34: 25 | B34: N/A | C34: VOID | D34: VOID | E34: 0 | F34: 0 | I34: Complete | J34: 0 | K34: 0 | L34: =J34+K34 -> 0 | N34: =E34+N33 -> 45842231 | R34: =F34-L34 -> 0
A35: 26 | B35: N/A | C35: UPIs For Progress Payment Jan 31 2016 | D35: Change Order | E35: 85583.22 | F35: 85583.22 | G35: 42403 | H35: Executed | I35: Complete | J35: 0 | K35: 85583.22 | L35: =J35+K35 -> 85583.22 | N35: =E35+N34 -> 45927814 | R35: =F35-L35 -> 0
A36: 27 | B36: N/A | C36: Existing Piping Removal At Station | D36: Change Order | E36: 200000 | F36: 85020.86 | G36: 42416 | H36: Executed | I36: Complete | J36: 0 | K36: 85020.86 | L36: =J36+K36 -> 85020.86 | N36: =E36+N35 -> 46127814 | R36: =F36-L36 -> 0
A37: 28 | B37: N/A | C37: UPIs For Progress Payment Feb 15 2016 | D37: Change Order | E37: 131183 | F37: 131183 | G37: 42422 | H37: Executed | I37: Complete | J37: 0 | K37: 131183 | L37: =J37+K37 -> 131183 | N37: =E37+N36 -> 46258997 | R37: =F37-L37 -> 0
A38: 29 | B38: 094 | C38: Stumping & Grubbing Not Completed By Clearing Contractor | D38: Change Order | E38: 22069.31 | F38: 22059.31 | G38: 42424 | H38: Executed | I38: Complete | J38: 0 | K38: 22059.31 | L38: =J38+K38 -> 22059.31 | N38: =E38+N37 -> 46281067 | R38: =F38-L38 -> 0
A39: 30 | B39: 093 | C39: 24Hr Medic Coverage (Additional To C004) | D39: Change Order | E39: 150785.25 | F39: 137550 | G39: 42424 | H39: Executed | I39: Complete | J39: 0 | K39: 137550 | L39: =J39+K39 -> 137550 | N39: =E39+N38 -> 46431852 | R39: =F39-L39 -> 0
A40: 31 | B40: 034 | C40: Installation/Removal & Trucking Of Access Mats To The Cutbank River (Addit. To C010) | D40: Change Order | E40: 2965.6 | F40: 2965.6 | G40: 42424 | H40: Executed | I40: Complete | J40: 0 | K40: 2965.6 | L40: =J40+K40 -> 2965.6 | N40: =E40+N39 -> 46434818 | R40: =F40-L40 -> 0
A41: 32 | B41: N/A | C41: Additional Force Account Equipment Rates | D41: Change Order | E41: 0 | F41: 0 | G41: 42424 | H41: Executed | I41: Complete | J41: 0 | K41: 0 | L41: =J41+K41 -> 0 | N41: =E41+N40 -> 46434818 | R41: =F41-L41 -> 0
A42: 33 | B42: 092 | C42: Mix And Backfill HDD Mud Sump Pits | D42: Change Order | E42: 165080.96 | F42: 165041.2 | G42: 42424 | H42: Executed | I42: Complete | J42: 0 | K42: 165041.2 | L42: =J42+K42 -> 165041.2 | N42: =E42+N41 -> 46599899 | R42: =F42-L42 -> 0 | S42: 137519.85 | T42: =S42-R42 -> 137519.85
A43: 34 | B43: N/A | C43: Remove Merchantable Timber When Mills Were Closed | D43: Change Order | E43: 5512.5 | F43: 5512.5 | G43: 42438 | H43: Executed | I43: Complete | J43: 0 | K43: 5512.5 | L43: =J43+K43 -> 5512.5 | N43: =E43+N42 -> 46605411 | R43: =F43-L43 -> 0
A44: 35 | B44: N/A | C44: UPIs For Progress Payment Feb 29 2016 | D44: Change Order | E44: 645875.24 | F44: 645875.24 | G44: 42438 | H44: Executed | I44: Complete | J44: 0 | K44: 645875.24 | L44: =J44+K44 -> 645875.24 | N44: =E44+N43 -> 47251286 | R44: =F44-L44 -> 0
A45: 36 | B45: N/A | C45: UPIs For Progress Payment Mar 15 2016 | D45: Change Order | E45: 284494.98 | F45: 284494.98 | G45: 42452 | H45: Executed | I45: Complete | J45: 0 | K45: 284494.98 | L45: =J45+K45 -> 284494.98 | N45: =E45+N44 -> 47535781 | R45: =F45-L45 -> 0
A46: 37 | B46: 091 | C46: Water Trucks To Support HDD Rigs | D46: Change Order | E46: 67500 | F46: 42875.6 | G46: 42452 | H46: Executed | I46: Complete | J46: 0 | K46: 42875.6 | L46: =J46+K46 -> 42875.6 | N46: =E46+N45 -> 47603281 | R46: =F46-L46 -> 0
A47: 38 | B47: 110 | C47: Other Drill IMR Clean Up | D47: Change Order | E47: 197366.91 | F47: 197366.91 | G47: 42452 | H47: Executed | I47: Ongoing | J47: 1480.14 | K47: 195710.53 | L47: =J47+K47 -> 197190.67 | N47: =E47+N46 -> 47800648 | P47: =E47-L47 -> 176.24 | R47: =F47-L47 -> 176.24 | S47: 14188.92 | T47: =S47-R47 -> 14012.68
A48: 39 | B48: 114 | C48: X-Ray Auditor Call Backs | D48: Change Order | E48: 9805.78 | F48: 9805.78 | G48: 42452 | H48: Executed | I48: Ongoing | J48: 0 | K48: 5805.78 | L48: =J48+K48 -> 5805.78 | N48: =E48+N47 -> 47810454 | R48: =F48-L48 -> 4000
A49: 40 | B49: 111 | C49: Delays Due To Clearing, Reps & Miscellaneous Causes | D49: Change Order | E49: 104077.7 | F49: 104077.7 | G49: 42474 | H49: Executed | I49: Ongoing | J49: 0 | K49: 84077.7 | L49: =J49+K49 -> 84077.7 | N49: =E49+N48 -> 47914532 | R49: =F49-L49 -> 20000
A50: 41 | B50: 121 | C50: Purchase Of Seed Mix | D50: Change Order | E50: 10000 | F50: 10000 | G50: 42474 | H50: Executed | I50: Ongoing | J50: 0 | K50: 8923.6 | L50: =J50+K50 -> 8923.6 | N50: =E50+N49 -> 47924532 | R50: =F50-L50 -> 1076.4
A51: 42 | B51: N/A | C51: UPIs For Progress Payment Mar 31 2016 | D51: Change Order | E51: 66053.28 | F51: 66053.28 | G51: 42474 | H51: Executed | I51: Complete | J51: 0 | K51: 66053.28 | L51: =J51+K51 -> 66053.28 | N51: =E51+N50 -> 47990585 | R51: =F51-L51 -> 0
A52: 43 | B52: 042 | C52: Digging Sumps Additional To C011 | D52: Change Order | E52: 80000 | F52: 66369.92 | G52: 42474 | H52: Executed | I52: Complete | J52: 0 | K52: 66369.92 | L52: =J52+K52 -> 66369.92 | N52: =E52+N51 -> 48070585 | R52: =F52-L52 -> 0 | T52: =S52-R52 -> 0
A53: 44 | B53: 075 & 104 | C53: Daylighting CNRL Pipelines At KP 24+804 | D53: Change Order | E53: 122491.4 | F53: 101151.91 | G53: 42474 | H53: Executed | I53: Ongoing | J53: 0 | K53: 101151.91 | L53: =J53+K53 -> 101151.91 | N53: =E53+N52 -> 48193076 | R53: =F53-L53 -> 0
A54: 45 | B54: 070R1 | C54: Hydrovac Support Additional to C023 | D54: Change Order | E54: 54750.6 | F54: 32090.76 | G54: 42474 | H54: Executed | I54: Complete | J54: 0 | K54: 32090.76 | L54: =J54+K54 -> 32090.76 | N54: =E54+N53 -> 48247827 | R54: =F54-L54 -> 0 | S54: 8670.08 | T54: =S54-R54 -> 8670.08
A55: 46 | B55: N/A | C55: UPIs For Progress Payment Apr 15 2016 | D55: Change Order | E55: 155239.62 | F55: 155239.62 | G55: 42482 | H55: Executed | I55: Complete | J55: 0 | K55: 155239.62 | L55: =J55+K55 -> 155239.62 | N55: =E55+N54 -> 48403067 | R55: =F55-L55 -> 0
A56: 47 | B56: 118 | C56: Light Towers For HDD Sumps | D56: Change Order | E56: 62260 | F56: 62260 | G56: 42482 | H56: Executed | I56: Complete | J56: 0 | K56: 62260 | L56: =J56+K56 -> 62260 | N56: =E56+N55 -> 48465327 | R56: =F56-L56 -> 0
A57: 48 | B57: 067 | C57: Drilling Support- Extended Schedule At River Additional To C020 | D57: Change Order | E57: 169946.08 | F57: 169946.08 | G57: 42482 | H57: Executed | I57: Complete | J57: 0 | K57: 169946.08 | L57: =J57+K57 -> 169946.08 | N57: =E57+N56 -> 48635273 | R57: =F57-L57 -> 0
A58: 49 | B58: N/A | C58: UPIs For Progress Payment Apr 30 2016 | D58: Change Order | E58: 95648.31 | F58: 95648.31 | G58: 42501 | H58: Executed | I58: Complete | J58: 0 | K58: 95648.31 | L58: =J58+K58 -> 95648.31 | N58: =E58+N57 -> 48730921 | R58: =F58-L58 -> 0
A59: 50 | B59: 062 | C59: Consultant For Long Run Exploration Crossing Additional To C019 | D59: Change Order | E59: 5040 | F59: 5040 | G59: 42501 | H59: Executed | I59: Complete | J59: 0 | K59: 5040 | L59: =J59+K59 -> 5040 | N59: =E59+N58 -> 48735961 | R59: =F59-L59 -> 0
A60: 51 | B60: 092 | C60: Mix And Backfill HDD Mud Sump Pits Additional To C033 | D60: Change Order | E60: 143330.98 | F60: 143330.98 | G60: 42501 | H60: Executed | I60: Complete | J60: 0 | K60: 143330.98 | L60: =J60+K60 -> 143330.98 | N60: =E60+N59 -> 48879292 | R60: =F60-L60 -> 0
A61: 52 | B61: 113 | C61: Additional Work Associated With Bear Den At KP 48+800 | D61: Change Order | E61: 366773.29 | F61: 366773.29 | I61: Complete | J61: 325639.92 | K61: 0 | L61: =J61+K61 -> 325639.92 | N61: =E61+N60 -> 49246065 | R61: =F61-L61 -> 41133.37
A62: 53 | B62: 110 | C62: Inadvertent Mud Release Clean Up In Addition To C038 | D62: Change Order | E62: 13198.84 | F62: 13198.84 | I62: Complete | J62: 13198.84 | K62: 0 | L62: =J62+K62 -> 13198.84 | N62: =E62+N61 -> 49259264 | R62: =F62-L62 -> 0
A63: 54 | B63: 119 | C63: Access Road Repairs & Maintenance | D63: Change Order | E63: 100000 | F63: 100000 | I63: Ongoing | J63: 5195.45 | K63: 0 | L63: =J63+K63 -> 5195.45 | N63: =E63+N62 -> 49359264 | R63: =F63-L63 -> 94804.55
A64: 55 | B64: 127 | C64: All Conditions Equipment Use During Spring Break Up | D64: Change Order | E64: 69770.04 | F64: 69770.04 | I64: Complete | J64: 69770.04 | K64: 0 | L64: =J64+K64 -> 69770.04 | N64: =E64+N63 -> 49429034 | R64: =F64-L64 -> 0
A65: 56 | B65: N/A | C65: UPIs For Progress Payment May 15 2016 | D65: Change Order | E65: 125158.18 | F65: 125158.18 | I65: Complete | J65: 125158.18 | K65: 0 | L65: =J65+K65 -> 125158.18 | N65: =E65+N64 -> 49554192 | R65: =F65-L65 -> 0
A66: 57 | B66: 134 | C66: Caliper Pig Contractor Change | D66: Change Order | E66: 55529.82 | F66: 55529.82 | J66: 0 | K66: 0 | L66: =J66+K66 -> 0 | N66: =E66+N65 -> 49609722 | R66: =F66-L66 -> 55529.82
A67: 58 | B67: 101 | C67: Tow Equipment To Access Drilling Rigs | D67: Change Order | E67: 155203.98 | F67: 155203.98 | J67: 0 | K67: 0 | L67: =J67+K67 -> 0 | N67: =E67+N66 -> 49764926 | R67: =F67-L67 -> 155203.98
A68: 59 | E68: 0 | F68: 0 | J68: 0 | K68: 0 | L68: =J68+K68 -> 0 | N68: =E68+N67 -> 49764926 | O68: CO total should be 3 cents more | R68: =F68-L68 -> 0
C69: Accumulated Value | E69: =SUM(E10:E68) -> 9443642.8 | F69: =SUM(F10:F68) -> 8990943.9 | I69: Subtotal: | J69: =SUM(J10:J68) -> 547075.95 | K69: =SUM(K10:K68) -> 7939823.3 | L69: =SUM(L10:L68) -> 8486899.2
I70: Total: | J70: =SUM(J69:J69) -> 547075.95 | K70: =SUM(K69:K69) -> 7939823.3 | L70: =SUM(L69:L69) -> 8486899.2

Sheet CO001
A1: WAPITI EXPANSION PIPELINE PROJECT
A6: EXTRA WORK SUMMARY
A7: CO# | B7: 001
A9: Item | B9: Additional Right-Of-Way Stripping: Add $12.44/m To Base Lay Price
I10: Billing Date: | J10: 42323
C11: 69435 | D11: % | E11: 12.443004 | F11: Total To Date | G11: Previous | H11: This Period | I11: Amount This Period ($) | J11: Total Earned Previously ($) | K11: Amount Earned To Date ($)
A12: 1.1 | B12: Mobilization | C12: Per Lin. m | D12: 0.02 | E12: =$E$11*D12 -> 0.24886008 | F12: =G12+H12 -> 34718 | H12: 34718 | I12: =H12*E12 -> 8639.9244 | J12: =G12*E12 -> 0 | K12: =SUM(I12:J12) -> 8639.9244
B13: Grade ROW | C13: Per Lin. m | D13: 0.08 | E13: =$E$11*D13 -> 0.99544034 | F13: =G13+H13 -> 0 | I13: =H13*E13 -> 0 | J13: =G13*E13 -> 0 | K13: =SUM(I13:J13) -> 0
B14: Haul and String Ppipe | C14: Per Lin. m | D14: 0.07 | E14: =$E$11*D14 -> 0.8710103 | F14: =G14+H14 -> 0 | I14: =H14*E14 -> 0 | J14: =G14*E14 -> 0 | K14: =SUM(I14:J14) -> 0
B15: Bending | C15: Per Lin. m | D15: 0.07 | E15: =$E$11*D15 -> 0.8710103 | F15: =G15+H15 -> 0 | I15: =H15*E15 -> 0 | J15: =G15*E15 -> 0 | K15: =SUM(I15:J15) -> 0
B16: Welding | C16: Per Lin. m | D16: 0.17 | E16: =$E$11*D16 -> 2.1153107 | F16: =G16+H16 -> 0 | I16: =H16*E16 -> 0 | J16: =G16*E16 -> 0 | K16: =SUM(I16:J16) -> 0
B17: Excavate Pipe Trench | C17: Per Lin. m | D17: 0.08 | E17: =$E$11*D17 -> 0.99544034 | F17: =G17+H17 -> 0 | I17: =H17*E17 -> 0 | J17: =G17*E17 -> 0 | K17: =SUM(I17:J17) -> 0
B18: Lower-In Pipe | C18: Per Lin. m | D18: 0.07 | E18: =$E$11*D18 -> 0.8710103 | F18: =G18+H18 -> 0 | I18: =H18*E18 -> 0 | J18: =G18*E18 -> 0 | K18: =SUM(I18:J18) -> 0
B19: Backfill | C19: Per Lin. m | D19: 0.08 | E19: =$E$11*D19 -> 0.99544034 | F19: =G19+H19 -> 0 | I19: =H19*E19 -> 0 | J19: =G19*E19 -> 0 | K19: =SUM(I19:J19) -> 0
B20: Tie-Ins | C20: Per Lin. m | D20: 0.07 | E20: =$E$11*D20 -> 0.8710103 | F20: =G20+H20 -> 0 | I20: =H20*E20 -> 0 | J20: =G20*E20 -> 0 | K20: =SUM(I20:J20) -> 0
B21: Testing | C21: Per Lin. m | D21: 0.07 | E21: =$E$11*D21 -> 0.8710103 | F21: =G21+H21 -> 0 | I21: =H21*E21 -> 0 | J21: =G21*E21 -> 0 | K21: =SUM(I21:J21) -> 0
B22: Final Tie-Ins | C22: Per Lin. m | D22: 0.05 | E22: =$E$11*D22 -> 0.62215021 | F22: =G22+H22 -> 0 | I22: =H22*E22 -> 0 | J22: =G22*E22 -> 0 | K22: =SUM(I22:J22) -> 0
B23: Cleanup/Reclamation/Seeding | C23: Per Lin. m | D23: 0.09 | E23: =$E$11*D23 -> 1.1198704 | F23: =G23+H23 -> 0 | I23: =H23*E23 -> 0 | J23: =G23*E23 -> 0 | K23: =SUM(I23:J23) -> 0
B24: Demobilization | C24: Per Lin. m | D24: 0.02 | E24: =$E$11*D24 -> 0.24886008 | F24: =G24+H24 -> 0 | I24: =H24*E24 -> 0 | J24: =G24*E24 -> 0 | K24: =SUM(I24:J24) -> 0
B25: Final Clean Up (one year later) | C25: Per Lin. m | D25: 0.06 | E25: =$E$11*D25 -> 0.74658025 | F25: =G25+H25 -> 0 | I25: =H25*E25 -> 0 | J25: =G25*E25 -> 0 | K25: =SUM(I25:J25) -> 0
D26: =SUM(D12:D25) -> 1 | E26: =SUM(E12:E25) -> 12.443004 | H26: Total For Base Lay Price: | I26: =SUM(I12:I25) -> 8639.9244 | J26: =SUM(J12:J25) -> 0 | K26: =SUM(K12:K25) -> 8639.9244
A29: Contractor
I33: Chief Inspector
H37: Approved CO Value ($) | J37: CO To Date ($)
H38: 863980 | J38: =K26 -> 8639.9244
A41: WAPITI EXPANSION PIPELINE PROJECT
A46: EXTRA WORK SUMMARY
A47: CO# | B47: 001
A49: Item | B49: Additional Right-Of-Way Stripping: Add $12.44/m To Base Lay Price
I50: Billing Date: | J50: 42338
C51: 69435 | D51: % | E51: 12.443004 | F51: Total To Date | G51: Previous | H51: This Period | I51: Amount This Period ($) | J51: Total Earned Previously ($) | K51: Amount Earned To Date ($)
A52: 1.1 | B52: Mobilization | C52: Per Lin. m | D52: 0.02 | E52: =$E$51*D52 -> 0.24886008 | F52: =G52+H52 -> 69435 | G52: 34718 | H52: 34717 | I52: =H52*E52 -> 8639.6756 | J52: =G52*E52 -> 8639.9244 | K52: 17279.6
B53: Grade ROW | C53: Per Lin. m | D53: 0.08 | E53: =$E$51*D53 -> 0.99544034 | F53: =G53+H53 -> 5300 | H53: 5300 | I53: =H53*E53 -> 5275.8338 | J53: =G53*E53 -> 0 | K53: 5275.83
B54: Haul and String Pipe | C54: Per Lin. m | D54: 0.07 | E54: =$E$51*D54 -> 0.8710103 | F54: =G54+H54 -> 400 | H54: 400 | I54: =H54*E54 -> 348.40412 | J54: =G54*E54 -> 0 | K54: 348.4
B55: Bending | C55: Per Lin. m | D55: 0.07 | E55: =$E$51*D55 -> 0.8710103 | F55: =G55+H55 -> 0 | I55: =H55*E55 -> 0 | J55: =G55*E55 -> 0 | K55: =SUM(I55:J55) -> 0
B56: Welding | C56: Per Lin. m | D56: 0.17 | E56: =$E$51*D56 -> 2.1153107 | F56: =G56+H56 -> 0 | I56: =H56*E56 -> 0 | J56: =G56*E56 -> 0 | K56: =SUM(I56:J56) -> 0
B57: Excavate Pipe Trench | C57: Per Lin. m | D57: 0.08 | E57: =$E$51*D57 -> 0.99544034 | F57: =G57+H57 -> 0 | I57: =H57*E57 -> 0 | J57: =G57*E57 -> 0 | K57: =SUM(I57:J57) -> 0
B58: Lower-In Pipe | C58: Per Lin. m | D58: 0.07 | E58: =$E$51*D58 -> 0.8710103 | F58: =G58+H58 -> 0 | I58: =H58*E58 -> 0 | J58: =G58*E58 -> 0 | K58: =SUM(I58:J58) -> 0
B59: Backfill | C59: Per Lin. m | D59: 0.08 | E59: =$E$51*D59 -> 0.99544034 | F59: =G59+H59 -> 0 | I59: =H59*E59 -> 0 | J59: =G59*E59 -> 0 | K59: =SUM(I59:J59) -> 0
B60: Tie-Ins | C60: Per Lin. m | D60: 0.07 | E60: =$E$51*D60 -> 0.8710103 | F60: =G60+H60 -> 0 | I60: =H60*E60 -> 0 | J60: =G60*E60 -> 0 | K60: =SUM(I60:J60) -> 0
B61: Testing | C61: Per Lin. m | D61: 0.07 | E61: =$E$51*D61 -> 0.8710103 | F61: =G61+H61 -> 0 | I61: =H61*E61 -> 0 | J61: =G61*E61 -> 0 | K61: =SUM(I61:J61) -> 0
B62: Final Tie-Ins | C62: Per Lin. m | D62: 0.05 | E62: =$E$51*D62 -> 0.62215021 | F62: =G62+H62 -> 0 | I62: =H62*E62 -> 0 | J62: =G62*E62 -> 0 | K62: =SUM(I62:J62) -> 0
B63: Cleanup/Reclamation/Seeding | C63: Per Lin. m | D63: 0.09 | E63: =$E$51*D63 -> 1.1198704 | F63: =G63+H63 -> 0 | I63: =H63*E63 -> 0 | J63: =G63*E63 -> 0 | K63: =SUM(I63:J63) -> 0
B64: Demobilization | C64: Per Lin. m | D64: 0.02 | E64: =$E$51*D64 -> 0.24886008 | F64: =G64+H64 -> 0 | I64: =H64*E64 -> 0 | J64: =G64*E64 -> 0 | K64: =SUM(I64:J64) -> 0
B65: Final Clean Up (one year later) | C65: Per Lin. m | D65: 0.06 | E65: =$E$51*D65 -> 0.74658025 | F65: =G65+H65 -> 0 | I65: =H65*E65 -> 0 | J65: =G65*E65 -> 0 | K65: =SUM(I65:J65) -> 0
D66: =SUM(D52:D65) -> 1 | E66: =SUM(E52:E65) -> 12.443004 | H66: Total For Base Lay Price: | I66: =SUM(I52:I65) -> 14263.913 | J66: =SUM(J52:J65) -> 8639.9244 | K66: =SUM(K52:K65) -> 22903.83
A69: Contractor
I73: Chief Inspector
H77: Approved CO Value ($) | J77: CO To Date ($)
H78: 863980 | J78: =K66 -> 22903.83
A81: =Summary!$G$11 -> PIPELINE PROJECT
A86: EXTRA WORK SUMMARY
A87: CO# | B87: 001
A89: Item | B89: Additional Right-Of-Way Stripping: Add $12.44/m To Base Lay Price
I90: Billing Date: | J90: 42353
C91: 69435 | D91: % | E91: 12.443004 | F91: Total To Date | G91: Previous | H91: This Period | I91: Amount This Period ($) | J91: Total Earned Previously ($) | K91: Amount Earned To Date ($)
A92: 1.1 | B92: Mobilization | C92: Per Lin. m | D92: 0.02 | E92: =$E$91*D92 -> 0.24886008 | F92: =G92+H92 -> 69435 | G92: 69435 | I92: =H92*E92 -> 0 | J92: 17279.6 | K92: 17279.6
B93: Grade ROW | C93: Per Lin. m | D93: 0.08 | E93: =$E$91*D93 -> 0.99544034 | F93: =G93+H93 -> 25100 | G93: 5300 | H93: 19800 | I93: 19709.72 | J93: 5275.83 | K93: =SUM(I93:J93) -> 24985.55
B94: Haul and String Pipe | C94: Per Lin. m | D94: 0.07 | E94: =$E$91*D94 -> 0.8710103 | F94: =G94+H94 -> 16100 | G94: 400 | H94: 15700 | I94: 13674.86 | J94: 348.4 | K94: =SUM(I94:J94) -> 14023.26
B95: Bending | C95: Per Lin. m | D95: 0.07 | E95: =$E$91*D95 -> 0.8710103 | F95: =G95+H95 -> 12000 | H95: 12000 | I95: 10452.12 | J95: =G95*E95 -> 0 | K95: =SUM(I95:J95) -> 10452.12
B96: Welding | C96: Per Lin. m | D96: 0.17 | E96: =$E$91*D96 -> 2.1153107 | F96: =G96+H96 -> 9500 | H96: 9500 | I96: 20095.45 | J96: =G96*E96 -> 0 | K96: =SUM(I96:J96) -> 20095.45
B97: Excavate Pipe Trench | C97: Per Lin. m | D97: 0.08 | E97: =$E$91*D97 -> 0.99544034 | F97: =G97+H97 -> 3700 | H97: 3700 | I97: 3683.13 | J97: =G97*E97 -> 0 | K97: =SUM(I97:J97) -> 3683.13
B98: Lower-In Pipe | C98: Per Lin. m | D98: 0.07 | E98: =$E$91*D98 -> 0.8710103 | F98: =G98+H98 -> 3700 | H98: 3700 | I98: 3222.74 | J98: =G98*E98 -> 0 | K98: =SUM(I98:J98) -> 3222.74
B99: Backfill | C99: Per Lin. m | D99: 0.08 | E99: =$E$91*D99 -> 0.99544034 | F99: =G99+H99 -> 2800 | H99: 2800 | I99: 2787.23 | J99: =G99*E99 -> 0 | K99: =SUM(I99:J99) -> 2787.23
B100: Tie-Ins | C100: Per Lin. m | D100: 0.07 | E100: =$E$91*D100 -> 0.8710103 | F100: =G100+H100 -> 1500 | H100: 1500 | I100: 1306.52 | J100: =G100*E100 -> 0 | K100: =SUM(I100:J100) -> 1306.52
B101: Testing | C101: Per Lin. m | D101: 0.07 | E101: =$E$91*D101 -> 0.8710103 | F101: =G101+H101 -> 0 | I101: =H101*E101 -> 0 | J101: =G101*E101 -> 0 | K101: =SUM(I101:J101) -> 0
B102: Final Tie-Ins | C102: Per Lin. m | D102: 0.05 | E102: =$E$91*D102 -> 0.62215021 | F102: =G102+H102 -> 0 | I102: =H102*E102 -> 0 | J102: =G102*E102 -> 0 | K102: =SUM(I102:J102) -> 0
B103: Cleanup/Reclamation/Seeding | C103: Per Lin. m | D103: 0.09 | E103: =$E$91*D103 -> 1.1198704 | F103: =G103+H103 -> 0 | I103: =H103*E103 -> 0 | J103: =G103*E103 -> 0 | K103: =SUM(I103:J103) -> 0
B104: Demobilization | C104: Per Lin. m | D104: 0.02 | E104: =$E$91*D104 -> 0.24886008 | F104: =G104+H104 -> 0 | I104: =H104*E104 -> 0 | J104: =G104*E104 -> 0 | K104: =SUM(I104:J104) -> 0
B105: Final Clean Up (one year later) | C105: Per Lin. m | D105: 0.06 | E105: =$E$91*D105 -> 0.74658025 | F105: =G105+H105 -> 0 | I105: =H105*E105 -> 0 | J105: =G105*E105 -> 0 | K105: =SUM(I105:J105) -> 0
D106: =SUM(D92:D105) -> 1 | E106: =SUM(E92:E105) -> 12.443004 | H106: Total For Base Lay Price: | I106: =SUM(I92:I105) -> 74931.77 | J106: =SUM(J92:J105) -> 22903.83 | K106: =SUM(K92:K105) -> 97835.6
A109: =Summary!$G$9 -> Contractor
I113: =Summary!$G$10 -> Construction Manager
H117: Approved CO Value ($) | J117: CO To Date ($)
H118: ='CO Log'!E10 -> 863980 | J118: =K106 -> 97835.6
A120: =Summary!$G$11 -> PIPELINE PROJECT
A125: EXTRA WORK SUMMARY
A126: CO# | B126: C01
A128: Item | B128: Additional Right-Of-Way Stripping: Add $12.44/m To Base Lay Price
I129: Billing Date: | J129: 42369
C130: 69435 | D130: % | E130: 12.443004 | F130: Total To Date | G130: Previous | H130: This Period | I130: Amount This Period ($) | J130: Total Earned Previously ($) | K130: Amount Earned To Date ($)
A131: 1.1 | B131: Mobilization | C131: Per Lin. m | D131: 0.02 | E131: =$E$91*D131 -> 0.24886008 | F131: =G131+H131 -> 69435 | G131: 69435 | I131: =H131*E131 -> 0 | J131: 17279.6 | K131: 17279.6
B132: Grade ROW | C132: Per Lin. m | D132: 0.08 | E132: =$E$91*D132 -> 0.99544034 | F132: =G132+H132 -> 32600 | G132: 25100 | H132: 7500 | I132: =H132*E132 -> 7465.8025 | J132: 24985.55 | K132: =SUM(I132:J132) -> 32451.353
B133: Haul and String Pipe | C133: Per Lin. m | D133: 0.07 | E133: =$E$91*D133 -> 0.8710103 | F133: =G133+H133 -> 24400 | G133: 16100 | H133: 8300 | I133: =H133*E133 -> 7229.3855 | J133: 14023.26 | K133: =SUM(I133:J133) -> 21252.645
B134: Bending | C134: Per Lin. m | D134: 0.07 | E134: =$E$91*D134 -> 0.8710103 | F134: =G134+H134 -> 16100 | G134: 12000 | H134: 4100 | I134: =H134*E134 -> 3571.1422 | J134: 10452.12 | K134: =SUM(I134:J134) -> 14023.262
B135: Welding | C135: Per Lin. m | D135: 0.17 | E135: =$E$91*D135 -> 2.1153107 | F135: =G135+H135 -> 12800 | G135: 9500 | H135: 3300 | I135: =H135*E135 -> 6980.5254 | J135: 20095.45 | K135: =SUM(I135:J135) -> 27075.975
B136: Excavate Pipe Trench | C136: Per Lin. m | D136: 0.08 | E136: =$E$91*D136 -> 0.99544034 | F136: =G136+H136 -> 6900 | G136: 3700 | H136: 3200 | I136: =H136*E136 -> 3185.4091 | J136: 3683.13 | K136: =SUM(I136:J136) -> 6868.5391
B137: Lower-In Pipe | C137: Per Lin. m | D137: 0.07 | E137: =$E$91*D137 -> 0.8710103 | F137: =G137+H137 -> 6900 | G137: 3700 | H137: 3200 | I137: =H137*E137 -> 2787.233 | J137: 3222.74 | K137: =SUM(I137:J137) -> 6009.973
B138: Backfill | C138: Per Lin. m | D138: 0.08 | E138: =$E$91*D138 -> 0.99544034 | F138: =G138+H138 -> 6900 | G138: 2800 | H138: 4100 | I138: =H138*E138 -> 4081.3054 | J138: 2787.23 | K138: =SUM(I138:J138) -> 6868.5354
B139: Tie-Ins | C139: Per Lin. m | D139: 0.07 | E139: =$E$91*D139 -> 0.8710103 | F139: =G139+H139 -> 3700 | G139: 1500 | H139: 2200 | I139: =H139*E139 -> 1916.2227 | J139: 1306.52 | K139: =SUM(I139:J139) -> 3222.7427
B140: Testing | C140: Per Lin. m | D140: 0.07 | E140: =$E$91*D140 -> 0.8710103 | F140: =G140+H140 -> 0 | I140: =H140*E140 -> 0 | J140: =G140*E140 -> 0 | K140: =SUM(I140:J140) -> 0
B141: Final Tie-Ins | C141: Per Lin. m | D141: 0.05 | E141: =$E$91*D141 -> 0.62215021 | F141: =G141+H141 -> 0 | I141: =H141*E141 -> 0 | J141: =G141*E141 -> 0 | K141: =SUM(I141:J141) -> 0
B142: Cleanup/Reclamation/Seeding | C142: Per Lin. m | D142: 0.09 | E142: =$E$91*D142 -> 1.1198704 | F142: =G142+H142 -> 0 | I142: =H142*E142 -> 0 | J142: =G142*E142 -> 0 | K142: =SUM(I142:J142) -> 0
B143: Demobilization | C143: Per Lin. m | D143: 0.02 | E143: =$E$91*D143 -> 0.24886008 | F143: =G143+H143 -> 0 | I143: =H143*E143 -> 0 | J143: =G143*E143 -> 0 | K143: =SUM(I143:J143) -> 0
B144: Final Clean Up (one year later) | C144: Per Lin. m | D144: 0.06 | E144: =$E$91*D144 -> 0.74658025 | F144: =G144+H144 -> 0 | I144: =H144*E144 -> 0 | J144: =G144*E144 -> 0 | K144: =SUM(I144:J144) -> 0
D145: =SUM(D131:D144) -> 1 | E145: =SUM(E131:E144) -> 12.443004 | H145: Total For Base Lay Price: | I145: =SUM(I131:I144) -> 37217.026 | J145: =SUM(J131:J144) -> 97835.6 | K145: =SUM(K131:K144) -> 135052.63
A148: =Summary!$G$9 -> Contractor
I152: =Summary!$G$10 -> Construction Manager
H156: Approved CO Value ($) | J156: CO To Date ($)
H157: 863980 | J157: =K145 -> 135052.63
...

Sheet CO002
A1: =Summary!G11 -> PIPELINE PROJECT
A13: EXTRA WORK SUMMARY
A14: CO# | B14: 002
D16: Billing Date: | E16: =Summary!G3 -> 42505
A17: Item | B17: Additional Two Way Radios For Inspection
A19: Date | B19: Description | C19: This Period | D19: Previous | E19: Total To Date
E20: =C20+D20 -> 0
C21: 25000 | E21: =C21+D21 -> 25000
C22: 25000 | E22: =C22+D22 -> 25000
E23: =C23+D23 -> 0
E24: =C24+D24 -> 0
E25: =C25+D25 -> 0
E26: =C26+D26 -> 0
E27: =C27+D27 -> 0
E28: =C28+D28 -> 0
E29: =C29+D29 -> 0
E30: =C30+D30 -> 0
B31: Total | C31: =SUM(C20:C30) -> 50000 | D31: =SUM(D20:D30) -> 0 | E31: =SUM(E20:E30) -> 50000
A33: =Summary!G9 -> Contractor
C37: =Summary!G10 -> Construction Manager
D42: Approved CO Value ($) | E42: CO To Date ($)
D43: 7088.55 | E43: =E31 -> 50000

Sheet CO003
A1: =Summary!$G$11 -> PIPELINE PROJECT
A13: EXTRA WORK SUMMARY
A14: CO# | B14: C03
D16: Date: | E16: 42384
A17: Item | B17: Clearing Support
A19: Date | B19: Description | C19: This Period | D19: Previous | E19: Total To Date | J19: Dec 4- Dec 15 | K19: 8590.84 | L19: 12 | N19: =K19*L19 -> 103090.08
A20: Nov 25- Dec 15 | B20: Support Crew #2 & #3 (30 Days) | C20: 257725.2 | E20: =C20+D20 -> 257725.2 | J20: Nov 25-Dec 13 | K20: 8590.84 | L20: 18 | N20: =K20*L20 -> 154635.12
A21: Dec 16- Dec 21 | B21: Support Crew #2 (6 Days) | C21: 51545.04 | E21: =C21+D21 -> 51545.04 | J21: Dec 16- Dec 21 | K21: 8590.84 | L21: 6 | N21: =K21*L21 -> 51545.04
A22: Jan 3- Jan 12 | B22: Support Crew (9 Days) | C22: 77317.56 | E22: =C22+D22 -> 77317.56 | J22: Jan 3- Jan 12 | K22: 8590.84 | L22: 9 | N22: =K22*L22 -> 77317.56
N23: =SUM(N19:N22) -> 386587.8
B29: Total | C29: =SUM(C20:C28) -> 386587.8 | D29: =SUM(D20:D28) -> 0 | E29: =SUM(E20:E28) -> 386587.8
A31: =Summary!$G$9 -> Contractor
C35: =Summary!$G$10 -> Construction Manager
D42: Approved CO Value ($) | E42: CO To Date ($)
D43: 670085.52 | E43: =E29 -> 386587.8
A45: =Summary!$G$11 -> PIPELINE PROJECT
A57: EXTRA WORK SUMMARY
A58: CO# | B58: C03
D60: Date: | E60: 42400
A61: Item | B61: Clearing Support
A63: Date | B63: Description | C63: This Period | D63: Previous | E63: Total To Date | J63: Dec 4- Dec 15 | K63: 8590.84 | L63: 12 | N63: =K63*L63 -> 103090.08
A64: Nov 25- Dec 15 | B64: Support Crew #2 & #3 (30 Days) | D64: 257725.2 | E64: =C64+D64 -> 257725.2 | J64: Nov 25-Dec 13 | K64: 8590.84 | L64: 18 | N64: =K64*L64 -> 154635.12
A65: Dec 16- Dec 21 | B65: Support Crew #2 (6 Days) | D65: 51545.04 | E65: =C65+D65 -> 51545.04 | J65: Dec 16- Dec 21 | K65: 8590.84 | L65: 6 | N65: =K65*L65 -> 51545.04
A66: Jan 3- Jan 12 | B66: Support Crew (9 Days) | D66: 77317.56 | E66: =C66+D66 -> 77317.56 | J66: Jan 3- Jan 12 | K66: 8590.84 | L66: 9 | N66: =K66*L66 -> 77317.56
A67: Jan 14- Jan 21 | B67: Support Crew (6 Days) | C67: 51545.04 | E67: =C67+D67 -> 51545.04 | J67: Jan 14- Jan 21 | K67: 8590.84 | L67: 6 | N67: =K67*L67 -> 51545.04
N69: =SUM(N63:N68) -> 438132.84
B73: Total | C73: =SUM(C64:C72) -> 51545.04 | D73: =SUM(D64:D72) -> 386587.8 | E73: =SUM(E64:E72) -> 438132.84
A75: =Summary!$G$9 -> Contractor
C79: =Summary!$G$10 -> Construction Manager
D86: Approved CO Value ($) | E86: CO To Date ($)
D87: 670085.52 | E87: =E73 -> 438132.84
A89: =Summary!$G$11 -> PIPELINE PROJECT
A101: EXTRA WORK SUMMARY
A102: CO# | B102: C03
D104: Date: | E104: =Summary!$G$3 -> 42505
A105: Item | B105: Clearing Support
A107: Date | B107: Description | C107: This Period | D107: Previous | E107: Total To Date
A108: Nov 25- Dec 15 | B108: Support Crew #2 & #3 (30 Days) | D108: 257725.2 | E108: =C108+D108 -> 257725.2
A109: Dec 16- Dec 21 | B109: Support Crew #2 (6 Days) | D109: 51545.04 | E109: =C109+D109 -> 51545.04
A110: Jan 3- Jan 12 | B110: Support Crew (9 Days) | D110: 77317.56 | E110: =C110+D110 -> 77317.56
A111: Jan 14- Jan 21 | B111: Support Crew (6 Days) | D111: 51545.04 | E111: =C111+D111 -> 51545.04
B117: Total | C117: =SUM(C108:C116) -> 0 | D117: =SUM(D108:D116) -> 438132.84 | E117: =SUM(E108:E116) -> 438132.84
A119: =Summary!$G$9 -> Contractor
C123: =Summary!$G$10 -> Construction Manager
D130: Approved CO Value ($) | E130: CO To Date ($)
D131: 670085.52 | E131: =E117 -> 438132.84
E132: Complete

Sheet CO004
A1: =Summary!$G$11 -> PIPELINE PROJECT
A13: EXTRA WORK SUMMARY
A14: CO# | B14: C04
D16: Date: | E16: 42353
A17: Item | B17: 24 Hour Medic Coverage
A19: Date | B19: Description | C19: This Period | D19: Previous | E19: Total To Date
A21: 42353 | B21: 24 Hour Medic for HDD & Burning Crew | C21: 25357.5 | E21: =C21+D21 -> 25357.5
B29: Total | C29: =SUM(C20:C28) -> 25357.5 | D29: =SUM(D20:D28) -> 0 | E29: =SUM(E20:E28) -> 25357.5
A31: =Summary!$G$9 -> Contractor
C35: =Summary!$G$10 -> Construction Manager
A37: =Summary!$G$11 -> PIPELINE PROJECT
A49: EXTRA WORK SUMMARY
A50: CO# | B50: C04
D52: Date: | E52: 42369
A53: Item | B53: 24 Hour Medic Coverage
A55: Date | B55: Description | C55: This Period | D55: Previous | E55: Total To Date
A57: 42353 | B57: 24 Hour Medic for HDD & Burning Crew | D57: 25357.5 | E57: =C57+D57 -> 25357.5
A58: =E52 -> 42369 | B58: 25 Hour Medic for HDD & Burning Crew | C58: 8820 | E58: =C58+D58 -> 8820
B65: Total | C65: =SUM(C56:C64) -> 8820 | D65: =SUM(D56:D64) -> 25357.5 | E65: =SUM(E56:E64) -> 34177.5
A67: =Summary!$G$9 -> Contractor
C71: =Summary!$G$10 -> Construction Manager
D78: Approved CO Value ($) | E78: CO To Date ($)
D79: 103635 | E79: =E65 -> 34177.5
A81: =Summary!$G$11 -> PIPELINE PROJECT
A93: EXTRA WORK SUMMARY
A94: CO# | B94: C04
D96: Date: | E96: 42384
A97: Item | B97: 24 Hour Medic Coverage
A99: Date | B99: Description | C99: This Period | D99: Previous | E99: Total To Date
A101: 42353 | B101: 24 Hour Medic for HDD & Burning Crew (Nov 25-Dec 15) | D101: 25357.5 | E101: =C101+D101 -> 25357.5
A102: 42369 | B102: 25 Hour Medic for HDD & Burning Crew (Dec 16-31) | D102: 8820 | E102: =C102+D102 -> 8820
A103: 42384 | B103: 26 Hour Medic for HDD & Burning Crew (Jan 1-14) | C103: 23152.5 | E103: =C103+D103 -> 23152.5
B109: Total | C109: =SUM(C100:C108) -> 23152.5 | D109: =SUM(D100:D108) -> 34177.5 | E109: =SUM(E100:E108) -> 57330
A111: =Summary!$G$9 -> Contractor
C115: =Summary!$G$10 -> Construction Manager
D122: Approved CO Value ($) | E122: CO To Date ($)
D123: 103635 | E123: =E109 -> 57330
A125: =Summary!$G$11 -> PIPELINE PROJECT
A137: EXTRA WORK SUMMARY
A138: CO# | B138: C04
D140: Date: | E140: 42400
A141: Item | B141: 24 Hour Medic Coverage
A143: Date | B143: Description | C143: This Period | D143: Previous | E143: Total To Date
A145: 42353 | B145: 24 Hour Medic for HDD & Burning Crew (Nov 25-Dec 15) | D145: 25357.5 | E145: =C145+D145 -> 25357.5
A146: 42369 | B146: 24 Hour Medic for HDD & Burning Crew (Dec 16-31) | D146: 8820 | E146: =C146+D146 -> 8820
A147: 42384 | B147: 24 Hour Medic for HDD & Burning Crew (Jan 1-14) | D147: 23152.5 | E147: =C147+D147 -> 23152.5
A148: 42393 | B148: 24 Hour Medic for HDD & Burning Crew (Jan 14-24) | C148: 31972.5 | E148: =C148+D148 -> 31972.5
B153: Total | C153: =SUM(C144:C152) -> 31972.5 | D153: =SUM(D144:D152) -> 57330 | E153: =SUM(E144:E152) -> 89302.5
A155: =Summary!$G$9 -> Contractor
C159: =Summary!$G$10 -> Construction Manager
D166: Approved CO Value ($) | E166: CO To Date ($)
D167: 103635 | E167: =E153 -> 89302.5
A169: =Summary!$G$11 -> PIPELINE PROJECT
A181: EXTRA WORK SUMMARY
A182: CO# | B182: C04
D184: Date: | E184: 42415
A185: Item | B185: 24 Hour Medic Coverage
A187: Date | B187: Description | C187: This Period | D187: Previous | E187: Total To Date
A189: 42353 | B189: 24 Hour Medic for HDD & Burning Crew (Nov 25-Dec 15) | D189: 25357.5 | E189: =C189+D189 -> 25357.5
A190: 42369 | B190: 24 Hour Medic for HDD & Burning Crew (Dec 16-31) | D190: 8820 | E190: =C190+D190 -> 8820
A191: 42384 | B191: 24 Hour Medic for HDD & Burning Crew (Jan 1-14) | D191: 23152.5 | E191: =C191+D191 -> 23152.5
A192: 42393 | B192: 24 Hour Medic for HDD & Burning Crew (Jan 14-24) | D192: 31972.5 | E192: =C192+D192 -> 31972.5
A193: 42415 | B193: 25 Hour Medic for HDD & Burning Crew (Jan 30-Feb 4) | C193: 14332.5 | E193: =C193+D193 -> 14332.5
B197: Total | C197: =SUM(C188:C196) -> 14332.5 | D197: =SUM(D188:D196) -> 89302.5 | E197: =SUM(E188:E196) -> 103635
A199: =Summary!$G$9 -> Contractor
C203: =Summary!$G$10 -> Construction Manager
D210: Approved CO Value ($) | E210: CO To Date ($)
D211: 103635 | E211: =E197 -> 103635
A213: =Summary!$G$11 -> PIPELINE PROJECT
A225: EXTRA WORK SUMMARY
A226: CO# | B226: C04
D228: Date: | E228: =Summary!$G$3 -> 42505
A229: Item | B229: 24 Hour Medic Coverage
A231: Date | B231: Description | C231: This Period | D231: Previous | E231: Total To Date
A233: 42353 | B233: 24 Hour Medic for HDD & Burning Crew (Nov 25-Dec 15) | D233: 25357.5 | E233: =C233+D233 -> 25357.5
A234: 42369 | B234: 24 Hour Medic for HDD & Burning Crew (Dec 16-31) | D234: 8820 | E234: =C234+D234 -> 8820
A235: 42384 | B235: 24 Hour Medic for HDD & Burning Crew (Jan 1-14) | D235: 23152.5 | E235: =C235+D235 -> 23152.5
A236: 42393 | B236: 24 Hour Medic for HDD & Burning Crew (Jan 14-24) | D236: 31972.5 | E236: =C236+D236 -> 31972.5
A237: 42415 | B237: 25 Hour Medic for HDD & Burning Crew (Jan 30-Feb 4) | D237: 14332.5 | E237: =C237+D237 -> 14332.5
B241: Total | C241: =SUM(C232:C240) -> 0 | D241: =SUM(D232:D240) -> 103635 | E241: =SUM(E232:E240) -> 103635
A243: =Summary!$G$9 -> Contractor
C247: =Summary!$G$10 -> Construction Manager
D254: Approved CO Value ($) | E254: CO To Date ($)
D255: 103635 | E255: =E241 -> 103635
E256: Complete

Sheet CO005
A1: =Summary!$G$11 -> PIPELINE PROJECT
A13: EXTRA WORK SUMMARY
A14: CO# | B14: CO5
D16: Billing Date: | E16: 42353
A17: Item | B17: RFI-015-R3 Cost Impacts
A19: Date | B19: Description | C19: This Period | D19: Previous | E19: Total To Date
A20: 42353 | B20: Cost Impacts Due To Start Delay | C20: 555229.22 | E20: =C20+D20 -> 555229.22
B29: Total | C29: =SUM(C20:C28) -> 555229.22 | D29: =SUM(D20:D28) -> 0 | E29: =SUM(E20:E28) -> 555229.22
A31: =Summary!$G$9 -> Contractor
C35: =Summary!$G$10 -> Construction Manager
A37: =Summary!$G$11 -> PIPELINE PROJECT
A49: EXTRA WORK SUMMARY
A50: CO# | B50: CO5
D52: Billing Date: | E52: =Summary!$G$3 -> 42505
A53: Item | B53: W2K-RFI-015-R3 Cost Impacts
A55: Date | B55: Description | C55: This Period | D55: Previous | E55: Total To Date
A56: 42369 | B56: Cost Impacts Due To Start Delay | D56: 555229.22 | E56: =C56+D56 -> 555229.22
B65: Total | C65: =SUM(C56:C64) -> 0 | D65: =SUM(D56:D64) -> 555229.22 | E65: =SUM(E56:E64) -> 555229.22
A67: =Summary!$G$9 -> Contractor
C71: =Summary!$G$10 -> Construction Manager
E72: Complete

Sheet CO006
A1: =Summary!$G$11 -> PIPELINE PROJECT
A13: UNIT PRICE SUMMARY
A14: CO# | B14: CO6
E16: Billing Date: | F16: =Summary!$G$3 -> 42505
A17: Item | B17: UPI SUMMARY
A19: Date | B19: UPI | C19: Description | D19: This Period | E19: Previous | F19: Total To Date
F20: =D20+E20 -> 0
A21: 42353 | B21: 2.1 a) | C21: Rock Trench | D21: 36802.67 | F21: =D21+E21 -> 36802.67
B22: 2.2 b) | C22: Rockshield | D22: 22800.69 | F22: =D22+E22 -> 22800.69
B23: 2.3 a) c) d) | C23: Sand Bedding/Padding From Borrow Pits | D23: 80356.7 | F23: =D23+E23 -> 80356.7
B24: 2.14 b) | C24: Install Pipe To Extra Depth | D24: 840 | F24: =D24+E24 -> 840
B25: 2.18 b) | C25: Vehicle & Equipment Wash Stations | D25: 10720 | F25: =D25+E25 -> 10720
F26: =D26+E26 -> 0
F27: =D27+E27 -> 0
F28: =D28+E28 -> 0
F29: =D29+E29 -> 0
F30: =D30+E30 -> 0
F31: =D31+E31 -> 0
F32: =D32+E32 -> 0
F33: =D33+E33 -> 0
F34: =D34+E34 -> 0
C35: Total | D35: =SUM(D20:D34) -> 151520.06 | E35: =SUM(E20:E34) -> 0 | F35: =SUM(F20:F34) -> 151520.06
A37: =Summary!$G$9 -> Contractor
A39: =Summary!$G$11 -> PIPELINE PROJECT
A51: UNIT PRICE SUMMARY
A52: CO# | B52: CO6
E54: Billing Date: | F54: 42369
A55: Item | B55: UPI SUMMARY
A57: Date | B57: UPI | C57: Description | D57: This Period | E57: Previous | F57: Total To Date
F58: =D58+E58 -> 0
A59: =F54 -> 42369 | B59: 2.1 a) | C59: Rock Trench | E59: 36802.67 | F59: =D59+E59 -> 36802.67
B60: 2.2 b) | C60: Rockshield | D60: 20915.763 | E60: 22800.69 | F60: =D60+E60 -> 43716.453
B61: 2.3 a) c) d) | C61: Sand Bedding/Padding From Borrow Pits | E61: 80356.7 | F61: =D61+E61 -> 80356.7
B62: 2.14 b) | C62: Install Pipe To Extra Depth | D62: 468 | E62: 840 | F62: =D62+E62 -> 1308
B63: 2.18 b) | C63: Vehicle & Equipment Wash Stations | E63: 10720 | F63: =D63+E63 -> 10720
B64: 2.29 | C64: Rig Mats | D64: 71442 | F64: =D64+E64 -> 71442
F65: =D65+E65 -> 0
F66: =D66+E66 -> 0
F67: =D67+E67 -> 0
F68: =D68+E68 -> 0
F69: =D69+E69 -> 0
F70: =D70+E70 -> 0
F71: =D71+E71 -> 0
F72: =D72+E72 -> 0
C73: Total | D73: =SUM(D58:D72) -> 92825.763 | E73: =SUM(E58:E72) -> 151520.06 | F73: =SUM(F58:F72) -> 244345.82
A75: =Summary!$G$9 -> Contractor

Sheet CO007
A1: =Summary!$G$11 -> PIPELINE PROJECT
A13: UNIT PRICE SUMMARY
A14: CO# | B14: CO7
E16: Billing Date: | F16: 42384
A17: Item | B17: UPI SUMMARY
A19: Date | B19: UPI | C19: Description | D19: This Period | E19: Previous | F19: Total To Date
A21: =F16 -> 42384 | B21: 2.1 a) | C21: Rock Trench | D21: 19134.69 | F21: =D21+E21 -> 19134.69
B22: 2.2 b) | C22: Rockshield | D22: 21351.076 | F22: =D22+E22 -> 21351.076
B23: 2.3 a) c) d) | C23: Sand Bedding/Padding From Borrow Pits | D23: 9408 | F23: =D23+E23 -> 9408
B24: 2.14 b) | C24: Install Pipe To Extra Depth | F24: =D24+E24 -> 0
B25: 2.18 b) | C25: Vehicle & Equipment Wash Stations | F25: =D25+E25 -> 0
B26: 2.29 | C26: Rig Mats | D26: 36450 | F26: =D26+E26 -> 36450
F27: =D27+E27 -> 0
F28: =D28+E28 -> 0
F29: =D29+E29 -> 0
F30: =D30+E30 -> 0
F31: =D31+E31 -> 0
F32: =D32+E32 -> 0
F33: =D33+E33 -> 0
F34: =D34+E34 -> 0
C35: Total | D35: =SUM(D20:D34) -> 86343.766 | E35: =SUM(E20:E34) -> 0 | F35: =SUM(F20:F34) -> 86343.766
A37: =Summary!$G$9 -> Contractor

Sheet CO009
A1: =Summary!$G$11 -> PIPELINE PROJECT
A13: EXTRA WORK SUMMARY
A14: CO# | B14: CO9
D16: Billing Date: | E16: 42400
A17: Item | B17: Digging Test Holes For Sump Suitability
A19: Date | B19: Description | C19: This Period | D19: Previous | E19: Total To Date
A20: 42400 | B20: Digging Test Holes | C20: 4889.75 | E20: =C20+D20 -> 4889.75
B21: Tickets 0153, 0401, 0426, 0430, 0431, 0432
B29: Total | C29: =SUM(C20:C28) -> 4889.75 | D29: =SUM(D20:D28) -> 0 | E29: =SUM(E20:E28) -> 4889.75
A31: =Summary!$G$9 -> Contractor
C35: =Summary!$G$10 -> Construction Manager
D39: Approved CO Value ($) | E39: CO To Date ($)
D40: 20000 | E40: =E29 -> 4889.75
A42: =Summary!$G$11 -> PIPELINE PROJECT
A54: EXTRA WORK SUMMARY
A55: CO# | B55: CO9
D57: Billing Date: | E57: 42415
A58: Item | B58: Digging Test Holes For Sump Suitability
A60: Date | B60: Description | C60: This Period | D60: Previous | E60: Total To Date
A61: 42415 | B61: Digging Test Holes | D61: 4889.75 | E61: =C61+D61 -> 4889.75
B62: Tickets 0677, 0678 | C62: 10369.43 | E62: =D62+C62 -> 10369.43
B70: Total | C70: =SUM(C61:C69) -> 10369.43 | D70: =SUM(D61:D69) -> 4889.75 | E70: =SUM(E61:E69) -> 15259.18
A72: =Summary!$G$9 -> Contractor
C76: =Summary!$G$10 -> Construction Manager
D80: Approved CO Value ($) | E80: CO To Date ($)
D81: 20000 | E81: =E70 -> 15259.18
A83: =Summary!$G$11 -> PIPELINE PROJECT
A95: EXTRA WORK SUMMARY
A96: CO# | B96: CO9
D98: Billing Date: | E98: 42460
A99: Item | B99: Digging Test Holes For Sump Suitability
A101: Date | B101: Description | C101: This Period | D101: Previous | E101: Total To Date
A102: 42400 | B102: Digging Test Holes | D102: 4889.75 | E102: =C102+D102 -> 4889.75
B103: Tickets 0153, 0401, 0426, 0430, 0431, 0432
A104: 42429 | B104: Digging Test Holes | D104: 10369.43 | E104: =D104+C104 -> 10369.43
B105: Tickets 0677, 0678
A106: 42460 | B106: Digging Test Holes | C106: 3550.07 | E106: =D106+C106 -> 3550.07
B107: Ticket 1439
B111: Total | C111: =SUM(C102:C110) -> 3550.07 | D111: =SUM(D102:D110) -> 15259.18 | E111: =SUM(E102:E110) -> 18809.25
A113: =Summary!$G$9 -> Contractor
C117: =Summary!$G$10 -> Construction Manager
D121: Approved CO Value ($) | E121: CO To Date ($)
D122: 20000 | E122: =E111 -> 18809.25
A124: =Summary!$G$11 -> PIPELINE PROJECT
A136: EXTRA WORK SUMMARY
A137: CO# | B137: CO9
D139: Billing Date: | E139: =Summary!$G$3 -> 42505
A140: Item | B140: Digging Test Holes For Sump Suitability
A142: Date | B142: Description | C142: This Period | D142: Previous | E142: Total To Date
A143: 42400 | B143: Digging Test Holes | D143: 4889.75 | E143: =C143+D143 -> 4889.75
B144: Tickets 0153, 0401, 0426, 0430, 0431, 0432
A145: 42429 | B145: Digging Test Holes | D145: 10369.43 | E145: =D145+C145 -> 10369.43
B146: Tickets 0677, 0678
A147: 42460 | B147: Digging Test Holes | D147: 3550.07 | E147: =D147+C147 -> 3550.07
B148: Ticket 1439
B152: Total | C152: =SUM(C143:C151) -> 0 | D152: =SUM(D143:D151) -> 18809.25 | E152: =SUM(E143:E151) -> 18809.25
A154: =Summary!$G$9 -> Contractor
C158: =Summary!$G$10 -> Construction Manager
D162: Approved CO Value ($) | E162: CO To Date ($)
D163: 20000 | E163: =E152 -> 18809.25
E164: Complete

Sheet CO010
A1: =Summary!$G$11 -> PIPELINE PROJECT
A13: EXTRA WORK SUMMARY
A14: CO# | B14: CO10
D16: Billing Date: | E16: 42400
A17: Item | B17: Installation & Removal Of Access Mats At River 56+109
A19: Date | B19: Description | C19: This Period | D19: Previous | E19: Total To Date
A20: 42400 | B20: Installation & Trucking Of Mats For HDD Pad | C20: 41482.8 | E20: =C20+D20 -> 41482.8
B21: Total is 540 mats @ $153.64 per mat:
B22: 50% For Installation; Remaining 50% Upon Removal
B29: Total | C29: =SUM(C20:C28) -> 41482.8 | D29: =SUM(D20:D28) -> 0 | E29: =SUM(E20:E28) -> 41482.8
A31: =Summary!$G$9 -> Contractor
C35: =Summary!$G$10 -> Construction Manager
D39: Approved CO Value ($) | E39: CO To Date ($)
D40: 80000 | E40: =E29 -> 41482.8
A42: =Summary!$G$11 -> PIPELINE PROJECT
A54: EXTRA WORK SUMMARY
A55: CO# | B55: CO10
D57: Billing Date: | E57: 42415
A58: Item | B58: Installation & Removal Of Access Mats At River 56+109
A60: Date | B60: Description | C60: This Period | D60: Previous | E60: Total To Date
A61: 42400 | B61: Installation & Trucking Of Mats For HDD Pad | D61: 41482.8 | E61: =C61+D61 -> 41482.8
B62: Total is 540 mats @ $153.64 per mat:
B63: 50% For Installation; Remaining 50% Upon Removal
A64: 42415 | B64: Installation & Trucking Of Mats For HDD Pad | C64: 38517.2 | E64: =D64+C64 -> 38517.2
B65: 50% For Removal
B66: Note: Balance of work ($2,965.60) to be issued in
B67: another Change Order
B70: Total | C70: =SUM(C61:C69) -> 38517.2 | D70: =SUM(D61:D69) -> 41482.8 | E70: =SUM(E61:E69) -> 80000
A72: =Summary!$G$9 -> Contractor
C76: =Summary!$G$10 -> Construction Manager
D80: Approved CO Value ($) | E80: CO To Date ($)
D81: 80000 | E81: =E70 -> 80000
A83: =Summary!$G$11 -> PIPELINE PROJECT
A95: EXTRA WORK SUMMARY
A96: CO# | B96: CO10
D98: Billing Date: | E98: =Summary!$G$3 -> 42505
A99: Item | B99: Installation & Removal Of Access Mats At River 56+109
A101: Date | B101: Description | C101: This Period | D101: Previous | E101: Total To Date
A102: 42400 | B102: Installation & Trucking Of Mats For HDD Pad | D102: 41482.8 | E102: =C102+D102 -> 41482.8
B103: Total is 540 mats @ $153.64 per mat:
B104: 50% For Installation; Remaining 50% Upon Removal
A105: 42415 | B105: Installation & Trucking Of Mats For HDD Pad | D105: 38517.2 | E105: =D105+C105 -> 38517.2
B106: 50% For Removal
B107: Note: Balance of work ($2,965.60) to be issued in
B108: another Change Order
B111: Total | C111: =SUM(C102:C110) -> 0 | D111: =SUM(D102:D110) -> 80000 | E111: =SUM(E102:E110) -> 80000
A113: =Summary!$G$9 -> Contractor
C117: =Summary!$G$10 -> Construction Manager
D121: Approved CO Value ($) | E121: CO To Date ($)
D122: 80000 | E122: =E111 -> 80000
E123: Complete

Sheet CO011
A1: =Summary!$G$11 -> PIPELINE PROJECT
A13: EXTRA WORK SUMMARY
A14: CO# | B14: CO11
D16: Billing Date: | E16: 42400
A17: Item | B17: Digging Sumps For Mud Containment
A19: Date | B19: Description | C19: This Period | D19: Previous | E19: Total To Date
A20: 42400 | B20: Digging Sumps | C20: 18307.84 | E20: =C20+D20 -> 18307.84
B21: Tickets 0157, 0168, 0169
B29: Total | C29: =SUM(C20:C28) -> 18307.84 | D29: =SUM(D20:D28) -> 0 | E29: =SUM(E20:E28) -> 18307.84
A31: =Summary!$G$9 -> Contractor
C35: =Summary!$G$10 -> Construction Manager
D39: Approved CO Value ($) | E39: CO To Date ($)
D40: 60000 | E40: =E29 -> 18307.84
A42: =Summary!$G$11 -> PIPELINE PROJECT
A54: EXTRA WORK SUMMARY
A55: CO# | B55: CO11
D57: Billing Date: | E57: 42415
A58: Item | B58: Digging Sumps For Mud Containment
A60: Date | B60: Description | C60: This Period | D60: Previous | E60: Total To Date
A61: 42415 | B61: Digging Sumps | D61: 18307.84 | E61: =C61+D61 -> 18307.84
B62: Tickets 0679, 0680, 0681, 0682, 0683, 0684, 0685, | C62: 28369.24 | E62: =D62+C62 -> 28369.24
B63: 0686, 0688
B70: Total | C70: =SUM(C61:C69) -> 28369.24 | D70: =SUM(D61:D69) -> 18307.84 | E70: =SUM(E61:E69) -> 46677.08
A72: =Summary!$G$9 -> Contractor
C76: =Summary!$G$10 -> Construction Manager
D80: Approved CO Value ($) | E80: CO To Date ($)
D81: 60000 | E81: =E70 -> 46677.08
A83: =Summary!$G$11 -> PIPELINE PROJECT
A95: EXTRA WORK SUMMARY
A96: CO# | B96: CO11
D98: Billing Date: | E98: 42429
A99: Item | B99: Digging Sumps For Mud Containment
A101: Date | B101: Description | C101: This Period | D101: Previous | E101: Total To Date
A102: 42400 | B102: Digging Sumps- Tickets 0157, 0168, 0169 | D102: 18307.84 | E102: =C102+D102 -> 18307.84
A103: 42415 | B103: Digging Sumps- Tickets 0679, 0680, 0681, 0682, | D103: 28369.24 | E103: =D103+C103 -> 28369.24
B104: 0683, 0684, 0685,0686, 0688
A105: 42429 | B105: Digging Sumps- Tickets 0687, 0689, 0699, 1426 | C105: 13079.3 | E105: =D105+C105 -> 13079.3
B111: Total | C111: =SUM(C102:C110) -> 13079.3 | D111: =SUM(D102:D110) -> 46677.08 | E111: =SUM(E102:E110) -> 59756.38
A113: =Summary!$G$9 -> Contractor
C117: =Summary!$G$10 -> Construction Manager
D121: Approved CO Value ($) | E121: CO To Date ($)
D122: 60000 | E122: =E111 -> 59756.38
A124: =Summary!$G$11 -> PIPELINE PROJECT
A136: EXTRA WORK SUMMARY
A137: CO# | B137: CO11
D139: Billing Date: | E139: =Summary!$G$3 -> 42505
A140: Item | B140: Digging Sumps For Mud Containment
A142: Date | B142: Description | C142: This Period | D142: Previous | E142: Total To Date
A143: 42400 | B143: Digging Sumps- Tickets 0157, 0168, 0169 | D143: 18307.84 | E143: =C143+D143 -> 18307.84
A144: 42415 | B144: Digging Sumps- Tickets 0679, 0680, 0681, 0682, | D144: 28369.24 | E144: =D144+C144 -> 28369.24
B145: 0683, 0684, 0685,0686, 0688
A146: 42429 | B146: Digging Sumps- Tickets 0687, 0689, 0699, 1426 | D146: 13079.3 | E146: =D146+C146 -> 13079.3
B152: Total | C152: =SUM(C143:C151) -> 0 | D152: =SUM(D143:D151) -> 59756.38 | E152: =SUM(E143:E151) -> 59756.38
A154: =Summary!$G$9 -> Contractor
C158: =Summary!$G$10 -> Construction Manager
D162: Approved CO Value ($) | E162: CO To Date ($)
D163: 60000 | E163: =E152 -> 59756.38
E164: Complete

Sheet CO012
A1: =Summary!$G$11 -> PIPELINE PROJECT
A13: EXTRA WORK SUMMARY
A14: CO# | B14: C012
D16: Billing Date: | E16: =Summary!$G$3 -> 42505
A17: Item | B17: Performance Vac- Mud Disposal
A19: Date | B19: Description | C19: This Period | D19: Previous | E19: Total To Date
E20: =C20+D20 -> 0
B29: Total | C29: =SUM(C20:C28) -> 0 | D29: =SUM(D20:D28) -> 0 | E29: =SUM(E20:E28) -> 0
A31: =Summary!$G$9 -> Contractor
C35: =Summary!$G$10 -> Construction Manager
D39: Approved CO Value ($) | E39: CO To Date ($)
D40: 25000 | E40: =E29 -> 0

Sheet CO013
A1: =Summary!$G$11 -> PIPELINE PROJECT
A13: EXTRA WORK SUMMARY
A14: CO# | B14: CO13
D16: Billing Date: | E16: 42400
A17: Item | B17: Rework Due To Survey Error
A19: Date | B19: Description | C19: This Period | D19: Previous | E19: Total To Date
A20: 42400 | B20: Rework Due To Survey Error (Estimate Revised) | C20: 3397.2 | E20: =C20+D20 -> 3397.2
B21: Ticket 0226
B29: Total | C29: =SUM(C20:C28) -> 3397.2 | D29: =SUM(D20:D28) -> 0 | E29: =SUM(E20:E28) -> 3397.2
A31: =Summary!$G$9 -> Contractor
C35: =Summary!$G$10 -> Construction Manager
D39: Approved CO Value ($) | E39: CO To Date ($)
D40: 4250.2 | E40: =E29 -> 3397.2
A42: =Summary!$G$11 -> PIPELINE PROJECT
A54: EXTRA WORK SUMMARY
A55: CO# | B55: CO-13
D57: Billing Date: | E57: =Summary!$G$3 -> 42505
A58: Item | B58: Rework Due To Survey Error
A60: Date | B60: Description | C60: This Period | D60: Previous | E60: Total To Date
A61: 42400 | B61: Rework Due To Survey Error (Estimate Revised) | D61: 3397.2 | E61: =C61+D61 -> 3397.2
B62: Ticket 0226
B70: Total | C70: =SUM(C61:C69) -> 0 | D70: =SUM(D61:D69) -> 3397.2 | E70: =SUM(E61:E69) -> 3397.2
A72: =Summary!$G$9 -> Contractor
C76: =Summary!$G$10 -> Construction Manager
D80: Approved CO Value ($) | E80: CO To Date ($)
D81: 4250.2 | E81: =E70 -> 3397.2
E82: Complete

Sheet CO014
A1: =Summary!$G$11 -> PIPELINE PROJECT
A13: EXTRA WORK SUMMARY
A14: CO# | B14: CO14
D16: Billing Date: | E16: 42400
A17: Item | B17: Paragon Soil Test Holes & Sandblast Defective Repairs
A19: Date | B19: Description | C19: This Period | D19: Previous | E19: Total To Date
A20: 42400 | B20: Paragon Test Holes Ticket 0437 | C20: 686.9 | E20: =C20+D20 -> 686.9
B29: Total | C29: =SUM(C20:C28) -> 686.9 | D29: =SUM(D20:D28) -> 0 | E29: =SUM(E20:E28) -> 686.9
A31: =Summary!$G$9 -> Contractor
C35: =Summary!$G$10 -> Construction Manager
D39: Approved CO Value ($) | E39: CO To Date ($)
D40: 2070.78 | E40: =E29 -> 686.9
A42: =Summary!$G$11 -> PIPELINE PROJECT
A54: EXTRA WORK SUMMARY
A55: CO# | B55: CO14
D57: Billing Date: | E57: =Summary!$G$3 -> 42505
A58: Item | B58: Paragon Soil Test Holes & Sandblast Defective Repairs
A60: Date | B60: Description | C60: This Period | D60: Previous | E60: Total To Date
A61: 42400 | B61: Paragon Test Holes Ticket 0437 | D61: 686.9 | E61: =C61+D61 -> 686.9
B62: Sandblast Defective Repairs Ticket 0176
B63: (Ticket 0176 was $483.30 over the CO so I put it in | C63: 1867.18
B64: the Miscellaneous CO15)
B70: Total | C70: =SUM(C61:C69) -> 1867.18 | D70: =SUM(D61:D69) -> 686.9 | E70: =SUM(E61:E69) -> 686.9
A72: =Summary!$G$9 -> Contractor
C76: =Summary!$G$10 -> Construction Manager
D80: Approved CO Value ($) | E80: CO To Date ($)
D81: 2070.78 | E81: =E70 -> 686.9
E82: Complete

Sheet CO015
A1: =Summary!$G$11 -> PIPELINE PROJECT
A13: EXTRA WORK SUMMARY
A14: CO# | B14: C015
D16: Billing Date: | E16: 42415
A17: Item | B17: Miscellaneous Additional Costs
A19: Date | B19: Description | C19: This Period | D19: Previous | E19: Total To Date
A20: 42382 | B20: 0128- Pull Out Badger Hydrovac | C20: 1985.36 | E20: =C20+D20 -> 1985.36
A21: 42359 | B21: TKT00160522- Badger Water Haul- No TDL Available | C21: 1978.2 | E21: =C21+D21 -> 1978.2
A22: 42358 | B22: TKT00160521- Badger Water Haul- No TDL Available | C22: 2167.2 | E22: =C22+D22 -> 2167.2
A23: 42358 | B23: TKT00226429- Badger Water Haul- No TDL Available | C23: 2167.2 | E23: =C23+D23 -> 2167.2
A24: 42411 | B24: 0181-Repair Coating After Buffing Due To Defect | C24: 231.94 | E24: =C24+D24 -> 231.94
A25: 42341 | B25: Badger Hydrovac Mud Disposal To Secure | C25: 945 | E25: =C25+D25 -> 945
B29: Total | C29: =SUM(C20:C28) -> 9474.9 | D29: =SUM(D20:D28) -> 0 | E29: =SUM(E20:E28) -> 9474.9
A31: =Summary!$G$9 -> Contractor
C35: =Summary!$G$10 -> Construction Manager
D39: Approved CO Value ($) | E39: CO To Date ($)
D40: 50000 | E40: =E29 -> 9474.9
A42: =Summary!$G$11 -> PIPELINE PROJECT
A54: EXTRA WORK SUMMARY
A55: CO# | B55: C015
D57: Billing Date: | E57: 42444
A58: Item | B58: Miscellaneous Additional Costs
A60: Date | B60: Description | C60: This Period | D60: Previous | E60: Total To Date
A61: 42382 | B61: 0128- Pull Out Badger Hydrovac | D61: 1985.36 | E61: =C61+D61 -> 1985.36
A62: 42359 | B62: TKT00160522- Badger Water Haul- No TDL Available | D62: 1978.2 | E62: =C62+D62 -> 1978.2
A63: 42358 | B63: TKT00160521- Badger Water Haul- No TDL Available | D63: 2167.2 | E63: =C63+D63 -> 2167.2
A64: 42358 | B64: TKT00226429- Badger Water Haul- No TDL Available | D64: 2167.2 | E64: =C64+D64 -> 2167.2
A65: 42411 | B65: 0181-Repair Coating After Buffing Due To Defect | D65: 231.94 | E65: =C65+D65 -> 231.94
A66: 42341 | B66: Badger Hydrovac Mud Disposal To Secure 0618 | D66: 945 | E66: =C66+D66 -> 945
B67: TKT00210800
A68: 42444 | B68: Sandblast Defective Repairs Ticket 0176 | C68: 1867.18 | E68: =C68+D68 -> 1867.18
B69: (Ticket 0176 was $483.30 over the C014 limit so it
B70: will be placed in C015)
B72: Total | C72: =SUM(C61:C71) -> 1867.18 | D72: =SUM(D61:D71) -> 9474.9 | E72: =SUM(E61:E71) -> 11342.08
A74: =Summary!$G$9 -> Contractor
C78: =Summary!$G$10 -> Construction Manager
D82: Approved CO Value ($) | E82: CO To Date ($)
D83: 50000 | E83: =E72 -> 11342.08
A85: =Summary!$G$11 -> PIPELINE PROJECT
A97: EXTRA WORK SUMMARY
A98: CO#
B99: C015
D100: Billing Date: | E100: 42460
A101: Item | B101: Miscellaneous Additional Costs
A103: Date | B103: Description | C103: This Period | D103: Previous | E103: Total To Date
A104: 42382 | B104: 0128- Pull Out Badger Hydrovac | D104: 1985.36 | E104: =C104+D104 -> 1985.36
A105: 42359 | B105: TKT00160522- Badger Water Haul- No TDL Available | D105: 1978.2 | E105: =C105+D105 -> 1978.2
A106: 42358 | B106: TKT00160521- Badger Water Haul- No TDL Available | D106: 2167.2 | E106: =C106+D106 -> 2167.2
A107: 42358 | B107: TKT00226429- Badger Water Haul- No TDL Available | D107: 2167.2 | E107: =C107+D107 -> 2167.2
A108: 42411 | B108: 0181-Repair Coating After Buffing Due To Defect | D108: 231.94 | E108: =C108+D108 -> 231.94
A109: 42341 | B109: Badger Hydrovac Mud Disposal To Secure 0618 | D109: 945 | E109: =C109+D109 -> 945
B110: TKT00210800
A111: 42444 | B111: Sandblast Defective Repairs Ticket 0176 | D111: 1867.18 | E111: =C111+D111 -> 1867.18
A112: 42460 | B112: Digging Test Holes- 0697 | C112: 3195.16 | E112: =C112+D112 -> 3195.16
B113: (Would have put C009 over by $2,004.41 so it will be
B114: placed in C015)
B117: Total | C117: =SUM(C104:C116) -> 3195.16 | D117: =SUM(D104:D116) -> 11342.08 | E117: =SUM(E104:E116) -> 14537.24
A119: =Summary!$G$9 -> Contractor
C123: =Summary!$G$10 -> Construction Manager
D127: Approved CO Value ($) | E127: CO To Date ($)
D128: 50000 | E128: =E117 -> 14537.24
A130: =Summary!$G$11 -> PIPELINE PROJECT
A142: EXTRA WORK SUMMARY
A143: CO# | B143: C015
D145: Billing Date: | E145: 42475
A146: Item | B146: Miscellaneous Additional Costs
A148: Date | B148: Description | C148: This Period | D148: Previous | E148: Total To Date
A149: 42382 | B149: 0128- Pull Out Badger Hydrovac | D149: 1985.36 | E149: =C149+D149 -> 1985.36
A150: 42359 | B150: TKT00160522- Badger Water Haul- No TDL Available | D150: 1978.2 | E150: =C150+D150 -> 1978.2
A151: 42358 | B151: TKT00160521- Badger Water Haul- No TDL Available | D151: 2167.2 | E151: =C151+D151 -> 2167.2
A152: 42358 | B152: TKT00226429- Badger Water Haul- No TDL Available | D152: 2167.2 | E152: =C152+D152 -> 2167.2
A153: 42411 | B153: 0181-Repair Coating After Buffing Due To Defect | D153: 231.94 | E153: =C153+D153 -> 231.94
A154: 42341 | B154: Badger Hydrovac Mud Disposal To Secure 0618 | D154: 945 | E154: =C154+D154 -> 945
B155: TKT00210800
A156: 42444 | B156: Sandblast Defective Repairs Ticket 0176 | D156: 1867.18 | E156: =C156+D156 -> 1867.18
A157: 42460 | B157: Digging Test Holes- 0697 | D157: 3195.16 | E157: =C157+D157 -> 3195.16
B158: (Would have put C009 over by $2,004.41 so it will be
B159: placed in C015)
A160: 42475 | B160: Badger Hydrovac Expose For Secure TKT00228896 | C160: 1829.63 | E160: =C160+D160 -> 1829.63
B161: Conoco Rep Request Invoice #16-0089 | C161: 850.5 | E161: =C161+D161 -> 850.5
B162: Remove Ribbons From Cutbank- 1470 | C162: 1639.92 | E162: =C162+D162 -> 1639.92
B165: Total | C165: =SUM(C149:C164) -> 4320.05 | D165: =SUM(D149:D164) -> 14537.24 | E165: =SUM(E149:E164) -> 18857.29
A167: =Summary!$G$9 -> Contractor
C171: =Summary!$G$10 -> Construction Manager
D175: Approved CO Value ($) | E175: CO To Date ($)
D176: 50000 | E176: =E165 -> 18857.29
A178: =Summary!$G$11 -> PIPELINE PROJECT
A190: EXTRA WORK SUMMARY
A191: CO# | B191: C015
D193: Billing Date: | E193: 42490
A194: Item | B194: Miscellaneous Additional Costs
A196: Date | B196: Description | C196: This Period | D196: Previous | E196: Total To Date
A197: 42382 | B197: 0128- Pull Out Badger Hydrovac | D197: 1985.36 | E197: =C197+D197 -> 1985.36
A198: 42359 | B198: TKT00160522- Badger Water Haul- No TDL Available | D198: 1978.2 | E198: =C198+D198 -> 1978.2
A199: 42358 | B199: TKT00160521- Badger Water Haul- No TDL Available | D199: 2167.2 | E199: =C199+D199 -> 2167.2
A200: 42358 | B200: TKT00226429- Badger Water Haul- No TDL Available | D200: 2167.2 | E200: =C200+D200 -> 2167.2
A201: 42411 | B201: 0181-Repair Coating After Buffing Due To Defect | D201: 231.94 | E201: =C201+D201 -> 231.94
A202: 42341 | B202: Badger Hydrovac Mud Disposal To Secure 0618 | D202: 945 | E202: =C202+D202 -> 945
B203: TKT00210800
A204: 42444 | B204: Sandblast Defective Repairs Ticket 0176 | D204: 1867.18 | E204: =C204+D204 -> 1867.18
...

Sheet CO016
A1: =Summary!$G$11 -> PIPELINE PROJECT
A13: EXTRA WORK SUMMARY
A14: CO# | B14: CO16
D16: Billing Date: | E16: 42400
A17: Item | B17: Damage To Irrigation Pipe
A19: Date | B19: Description | C19: This Period | D19: Previous | E19: Total To Date
A20: 42350 | B20: Energy Fluid Service: Invoice #2015-0032 | C20: 5706 | E20: =C20+D20 -> 5706
B21: Handling Fee/Mark Up @ 5%: | C21: =C20*0.05 -> 285.3 | E21: =C21+D21 -> 285.3
B29: Total | C29: =SUM(C20:C28) -> 5991.3 | D29: =SUM(D20:D28) -> 0 | E29: =SUM(E20:E28) -> 5991.3
A31: =Summary!$G$9 -> Contractor
C35: =Summary!$G$10 -> Construction Manager
D39: Approved CO Value ($) | E39: CO To Date ($)
D40: 5991.3 | E40: =E29 -> 5991.3
A42: =Summary!$G$11 -> PIPELINE PROJECT
A54: EXTRA WORK SUMMARY
A55: CO# | B55: CO16
D57: Billing Date: | E57: =Summary!$G$3 -> 42505
A58: Item | B58: Damage To Irrigation Pipe
A60: Date | B60: Description | C60: This Period | D60: Previous | E60: Total To Date
A61: 42350 | B61: Energy Fluid Service: Invoice #2015-0032 | D61: 5706 | E61: =C61+D61 -> 5706
B62: Handling Fee/Mark Up @ 5%: | D62: =D61*0.05 -> 285.3 | E62: =C62+D62 -> 285.3
B70: Total | C70: =SUM(C61:C69) -> 0 | D70: =SUM(D61:D69) -> 5991.3 | E70: =SUM(E61:E69) -> 5991.3
A72: =Summary!$G$9 -> Contractor
C76: =Summary!$G$10 -> Construction Manager
D80: Approved CO Value ($) | E80: CO To Date ($)
D81: 5991.3 | E81: =E70 -> 5991.3
E82: Complete

Sheet CO017
A1: =Summary!$G$11 -> PIPELINE PROJECT
A13: EXTRA WORK SUMMARY
A14: CO# | B14: CO17
D16: Billing Date: | E16: 42400
A17: Item | B17: Unloading Mats- $19.41 Per Mat
A19: Date | B19: Description | C19: This Period | D19: Previous | E19: Total To Date
A20: 42400 | B20: Offload Company Supplied Mats | C20: 5027.19 | E20: =C20+D20 -> 5027.19
B21: 259 Mats @ $19.41/mat To Dec 19, 2015
B29: Total | C29: =SUM(C20:C28) -> 5027.19 | D29: =SUM(D20:D28) -> 0 | E29: =SUM(E20:E28) -> 5027.19
A31: =Summary!$G$9 -> Contractor
C35: =Summary!$G$10 -> Construction Manager
D39: Approved CO Value ($) | E39: CO To Date ($)
D40: 19408 | E40: =E29 -> 5027.19
A42: =Summary!$G$11 -> PIPELINE PROJECT
A54: EXTRA WORK SUMMARY
A55: CO# | B55: CO17
D57: Billing Date: | E57: 42429
A58: Item | B58: Unloading Mats- $19.41 Per Mat
A60: Date | B60: Description | C60: This Period | D60: Previous | E60: Total To Date
A61: 42400 | B61: Offload Company Supplied Mats | D61: 5027.19 | E61: =C61+D61 -> 5027.19
B62: 259 Mats @ $19.41/mat To Dec 19, 2015
A64: 42424 | B64: Offload Company Supplied Mats- NTL 6826 | C64: 562.89 | E64: =C64+D64 -> 562.89
B65: 29 Mats @ $19.41/mat
A66: 42425 | B66: Offload Company Supplied Mats- NTL 6826 | C66: 368.79 | E66: =C66+D66 -> 368.79
B67: 19 Mats @ $19.41/mat
B68: Total: 307 Mats To Date
B70: Total | C70: =SUM(C61:C69) -> 931.68 | D70: =SUM(D61:D69) -> 5027.19 | E70: =SUM(E61:E69) -> 5958.87
A72: =Summary!$G$9 -> Contractor
C76: =Summary!$G$10 -> Construction Manager
D80: Approved CO Value ($) | E80: CO To Date ($)
D81: 19408 | E81: =E70 -> 5958.87
A83: =Summary!$G$11 -> PIPELINE PROJECT
A95: EXTRA WORK SUMMARY
A96: CO# | B96: CO17
D98: Billing Date: | E98: =Summary!$G$3 -> 42505
A99: Item | B99: Unloading Mats- $19.41 Per Mat
A101: Date | B101: Description | C101: This Period | D101: Previous | E101: Total To Date
A102: 42400 | B102: Offload Company Supplied Mats | D102: 5027.19 | E102: =C102+D102 -> 5027.19
B103: 259 Mats @ $19.41/mat To Dec 19, 2015
A104: 42424 | B104: Offload Company Supplied Mats- NTL 6826 | D104: 562.89 | E104: =C104+D104 -> 562.89
B105: 29 Mats @ $19.41/mat
A106: 42425 | B106: Offload Company Supplied Mats- NTL 6826 | D106: 368.79 | E106: =C106+D106 -> 368.79
B107: 19 Mats @ $19.41/mat
B113: Total: 307 Mats To Date
B115: Total | C115: =SUM(C102:C114) -> 0 | D115: =SUM(D102:D114) -> 5958.87 | E115: =SUM(E102:E114) -> 5958.87
A117: =Summary!$G$9 -> Contractor
C121: =Summary!$G$10 -> Construction Manager
D125: Approved CO Value ($) | E125: CO To Date ($)
D126: 19408 | E126: =E115 -> 5958.87

Sheet CO018
A1: =Summary!$G$11 -> PIPELINE PROJECT
A13: EXTRA WORK SUMMARY
A14: CO# | B14: CO18
D16: Billing Date: | E16: 42429
A17: Item | B17: Water Haul- ROW Freezing
A19: Date | B19: Description | C19: This Period | D19: Previous | E19: Total To Date
A20: 42376 | B20: Haul Water For ROW Freezing (No TDLs In Place) | C20: 23684.06 | E20: =C20+D20 -> 23684.06
B29: Total | C29: =SUM(C20:C28) -> 23684.06 | D29: =SUM(D20:D28) -> 0 | E29: =SUM(E20:E28) -> 23684.06
A31: =Summary!$G$9 -> Contractor
C35: =Summary!$G$10 -> Construction Manager
D39: Approved CO Value ($) | E39: CO To Date ($)
D40: 23684.06 | E40: =E29 -> 23684.06
A42: =Summary!$G$11 -> PIPELINE PROJECT
A54: EXTRA WORK SUMMARY
A55: CO# | B55: CO18
D57: Billing Date: | E57: =Summary!$G$3 -> 42505
A58: Item | B58: Water Haul- ROW Freezing
A60: Date | B60: Description | C60: This Period | D60: Previous | E60: Total To Date
A61: 42376 | B61: Haul Water For ROW Freezing (No TDLs In Place) | D61: 23684.06 | E61: =C61+D61 -> 23684.06
B70: Total | C70: =SUM(C61:C69) -> 0 | D70: =SUM(D61:D69) -> 23684.06 | E70: =SUM(E61:E69) -> 23684.06
A72: =Summary!$G$9 -> Contractor
C76: =Summary!$G$10 -> Construction Manager
D80: Approved CO Value ($) | E80: CO To Date ($)
D81: 23684.06 | E81: =E70 -> 23684.06
E82: Complete

Sheet CO019
A1: =Summary!$G$11 -> PIPELINE PROJECT
A13: EXTRA WORK SUMMARY
A14: CO# | B14: CO19
D16: Billing Date: | E16: 42444
A17: Item | B17: Consultant For Long Run Crossing
A19: Date | B19: Description | C19: This Period | D19: Previous | E19: Total To Date
A21: 42444 | B21: Avid Resource Management Jan 11-14 | C21: 4410 | E21: =C21+D21 -> 4410
B22: Invoices 1362, 1363, 1366, 1367
B29: Total | C29: =SUM(C20:C28) -> 4410 | D29: =SUM(D20:D28) -> 0 | E29: =SUM(E20:E28) -> 4410
A31: =Summary!$G$9 -> Contractor
C35: =Summary!$G$10 -> Construction Manager
D39: Approved CO Value ($) | E39: CO To Date ($)
D40: 5040 | E40: =E29 -> 4410
A42: =Summary!$G$11 -> PIPELINE PROJECT
A54: EXTRA WORK SUMMARY
A55: CO# | B55: CO19
D57: Billing Date: | E57: =Summary!$G$3 -> 42505
A58: Item | B58: Consultant For Long Run Crossing
A60: Date | B60: Description | C60: This Period | D60: Previous | E60: Total To Date
A62: 42444 | B62: Avid Resource Management Jan 11-14 | D62: 4410 | E62: =C62+D62 -> 4410
B63: Invoices 1362, 1363, 1366, 1367 | E63: =C63+D63 -> 0
B70: Total | C70: =SUM(C61:C69) -> 0 | D70: =SUM(D61:D69) -> 4410 | E70: =SUM(E61:E69) -> 4410
A72: =Summary!$G$9 -> Contractor
C76: =Summary!$G$10 -> Construction Manager
D80: Approved CO Value ($) | E80: CO To Date ($)
D81: 5040 | E81: =E70 -> 4410

Sheet CO020
A1: =Summary!$G$11 -> PIPELINE PROJECT
A13: EXTRA WORK SUMMARY
A14: CO# | B14: CO20
D16: Billing Date: | E16: 42400
A17: Item | B17: Drilling Support- Extended Schedule At River
A19: Date | B19: Description | C19: This Period | D19: Previous | E19: Total To Date
A20: 42400 | B20: 24 Additional Shifts @ $3,694.48 | C20: 88667.52 | E20: =C20+D20 -> 88667.52
B21: 12 Days: Jan 10 to Jan 21, 2016
B29: Total | C29: =SUM(C20:C28) -> 88667.52 | D29: =SUM(D20:D28) -> 0 | E29: =SUM(E20:E28) -> 88667.52
A31: =Summary!$G$9 -> Contractor
C35: =Summary!$G$10 -> Construction Manager
D39: Approved CO Value ($) | E39: CO To Date ($)
D40: 88667.52 | E40: =E29 -> 88667.52
A42: =Summary!$G$11 -> PIPELINE PROJECT
A54: EXTRA WORK SUMMARY
A55: CO# | B55: CO20
D57: Billing Date: | E57: =Summary!$G$3 -> 42505
A58: Item | B58: Drilling Support- Extended Schedule At River
A60: Date | B60: Description | C60: This Period | D60: Previous | E60: Total To Date
A61: 42400 | B61: 24 Additional Shifts @ $3,694.48 | D61: 88667.52 | E61: =C61+D61 -> 88667.52
B62: 12 Days: Jan 10 to Jan 21, 2016
B70: Total | C70: =SUM(C61:C69) -> 0 | D70: =SUM(D61:D69) -> 88667.52 | E70: =SUM(E61:E69) -> 88667.52
A72: =Summary!$G$9 -> Contractor
C76: =Summary!$G$10 -> Construction Manager
D80: Approved CO Value ($) | E80: CO To Date ($)
D81: 88667.52 | E81: =E70 -> 88667.52
E82: Complete

Sheet CO021
A1: =Summary!$G$11 -> PIPELINE PROJECT
A13: EXTRA WORK SUMMARY
A14: CO# | B14: CO21
D16: Billing Date: | E16: 42415
A17: Item | B17: Inadvertant Mud Release Clean Up
A19: Date | B19: Description | C19: This Period | D19: Previous | E19: Total To Date
A20: 42357 | B20: 0580- IMR Clean Up | C20: 21412.1 | E20: =C20+D20 -> 21412.1
A21: 42358 | B21: 0276- IMR Clean Up | C21: 32413.12 | E21: =C21+D21 -> 32413.12
A22: 42359 | B22: 0277- IMR Clean Up | C22: 6407.16 | E22: =C22+D22 -> 6407.16
B29: Total | C29: =SUM(C20:C28) -> 60232.38 | D29: =SUM(D20:D28) -> 0 | E29: =SUM(E20:E28) -> 60232.38
A31: =Summary!$G$9 -> Contractor
C35: =Summary!$G$10 -> Construction Manager
D39: Approved CO Value ($) | E39: CO To Date ($)
D40: 65808.36 | E40: =E29 -> 60232.38
A42: =Summary!$G$11 -> PIPELINE PROJECT
A54: EXTRA WORK SUMMARY
A55: CO# | B55: CO21
D57: Billing Date: | E57: =Summary!$G$3 -> 42505
A58: Item | B58: Inadvertant Mud Release Clean Up
A60: Date | B60: Description | C60: This Period | D60: Previous | E60: Total To Date
A61: 42357 | B61: 0580- IMR Clean Up | D61: 21412.1 | E61: =C61+D61 -> 21412.1
A62: 42358 | B62: 0276- IMR Clean Up | D62: 32413.12 | E62: =C62+D62 -> 32413.12
A63: 42359 | B63: 0277- IMR Clean Up | D63: 6407.16 | E63: =C63+D63 -> 6407.16
B70: Total | C70: =SUM(C61:C69) -> 0 | D70: =SUM(D61:D69) -> 60232.38 | E70: =SUM(E61:E69) -> 60232.38
A72: =Summary!$G$9 -> Contractor
C76: =Summary!$G$10 -> Construction Manager
D80: Approved CO Value ($) | E80: CO To Date ($)
D81: 65808.36 | E81: =E70 -> 60232.38
E82: Complete

Sheet CO022
A1: =Summary!$G$11 -> PIPELINE PROJECT
A13: EXTRA WORK SUMMARY
A14: CO# | B14: CO22
D16: Billing Date: | E16: 42415
A17: Item | B17: Safety Stand Down
A19: Date | B19: Description | C19: This Period | D19: Previous | E19: Total To Date
A20: 42387 | B20: Safety Stand Down | C20: 215562.16 | E20: =C20+D20 -> 215562.16
B29: Total | C29: =SUM(C20:C28) -> 215562.16 | D29: =SUM(D20:D28) -> 0 | E29: =SUM(E20:E28) -> 215562.16
A31: =Summary!$G$9 -> Contractor
C35: =Summary!$G$10 -> Construction Manager
D39: Approved CO Value ($) | E39: CO To Date ($)
D40: 215855.08 | E40: =E29 -> 215562.16
A42: =Summary!$G$11 -> PIPELINE PROJECT
A54: EXTRA WORK SUMMARY
A55: CO# | B55: CO22
D57: Billing Date: | E57: =Summary!$G$3 -> 42505
A58: Item | B58: Safety Stand Down
A60: Date | B60: Description | C60: This Period | D60: Previous | E60: Total To Date
A61: 42387 | B61: Safety Stand Down | D61: 215562.16 | E61: =C61+D61 -> 215562.16
B70: Total | C70: =SUM(C61:C69) -> 0 | D70: =SUM(D61:D69) -> 215562.16 | E70: =SUM(E61:E69) -> 215562.16
A72: =Summary!$G$9 -> Contractor
C76: =Summary!$G$10 -> Construction Manager
D80: Approved CO Value ($) | E80: CO To Date ($)
D81: 215855.08 | E81: =E70 -> 215562.16
E82: Complete

Sheet CO023
A1: =Summary!$G$11 -> PIPELINE PROJECT
A13: EXTRA WORK SUMMARY
A14: CO# | B14: CO23
D16: Billing Date: | E16: 42444
A17: Item | B17: Additional Hydrovac Support
A19: Date | B19: Description | C19: This Period | D19: Previous | E19: Total To Date
A20: 42444 | B20: Additional Hydrovac Support | C20: 76263.46 | E20: =C20+D20 -> 76263.46
B29: Total | C29: =SUM(C20:C28) -> 76263.46 | D29: =SUM(D20:D28) -> 0 | E29: =SUM(E20:E28) -> 76263.46
A31: =Summary!$G$9 -> Contractor
C35: =Summary!$G$10 -> Construction Manager
D39: Approved CO Value ($) | E39: CO To Date ($)
D40: 359953.32 | E40: =E29 -> 76263.46
A42: =Summary!$G$11 -> PIPELINE PROJECT
A54: EXTRA WORK SUMMARY
A55: CO# | B55: CO23
D57: Billing Date: | E57: 42460
A58: Item | B58: Additional Hydrovac Support
A60: Date | B60: Description | C60: This Period | D60: Previous | E60: Total To Date
A61: 42444 | B61: Additional Hydrovac Support | D61: 76263.46 | E61: =C61+D61 -> 76263.46
A62: 42460 | B62: Additional Hydrovac Support | C62: 283629.82 | E62: =D62+C62 -> 283629.82
B70: Total | C70: =SUM(C61:C69) -> 283629.82 | D70: =SUM(D61:D69) -> 76263.46 | E70: =SUM(E61:E69) -> 359893.28
A72: =Summary!$G$9 -> Contractor
C76: =Summary!$G$10 -> Construction Manager
D80: Approved CO Value ($) | E80: CO To Date ($)
D81: 359953.32 | E81: =E70 -> 359893.28
A83: =Summary!$G$11 -> PIPELINE PROJECT
A95: EXTRA WORK SUMMARY
A96: CO# | B96: CO23
D98: Billing Date: | E98: =Summary!$G$3 -> 42505
A99: Item | B99: Additional Hydrovac Support
A101: Date | B101: Description | C101: This Period | D101: Previous | E101: Total To Date
A102: 42444 | B102: Additional Hydrovac Support | D102: 76263.46 | E102: =C102+D102 -> 76263.46
A103: 42460 | B103: Additional Hydrovac Support | D103: 283629.82 | E103: =D103+C103 -> 283629.82
B111: Total | C111: =SUM(C102:C110) -> 0 | D111: =SUM(D102:D110) -> 359893.28 | E111: =SUM(E102:E110) -> 359893.28
A113: =Summary!$G$9 -> Contractor
C117: =Summary!$G$10 -> Construction Manager
D121: Approved CO Value ($) | E121: CO To Date ($)
D122: 359953.32 | E122: =E111 -> 359893.28
E123: Complete

Sheet CO024
A1: =Summary!$G$11 -> PIPELINE PROJECT
A13: EXTRA WORK SUMMARY
A14: CO# | B14: CO-24
D16: Billing Date: | E16: 42460
A17: Item | B17: Additional Tie-In Support & HDD Crews
A19: Date | B19: Description | C19: This Period | D19: Previous | E19: Total To Date
A20: 42460 | B20: Additional Tie-In Support: W2K-RFI-071
B21: March 31 Payment (25% of $763,439.04) | C21: 190859.76 | E21: =D21+C21 -> 190859.76
B22: April 15 Payment (50% of $763,439.04) | E22: =D22+C22 -> 0
B23: April 31 Payment (25% of $763,439.04) | E23: =D23+C23 -> 0
A25: 42460 | B25: HDD Support Crews To March 31: W2K-RFI-072 | C25: 1201072.3 | E25: =D25+C25 -> 1201072.3
B26: March 31 Payment (100% of $1,201,072.32)
B29: Total | C29: =SUM(C20:C28) -> 1391932.1 | D29: =SUM(D20:D28) -> 0 | E29: =SUM(E20:E28) -> 1391932.1
A31: =Summary!$G$9 -> Contractor
C35: =Summary!$G$10 -> Construction Manager
D39: Approved CO Value ($) | E39: CO To Date ($)
D40: 1964511.4 | E40: =E29 -> 1391932.1
A42: =Summary!$G$11 -> PIPELINE PROJECT
A54: EXTRA WORK SUMMARY
A55: CO# | B55: CO-24
D57: Billing Date: | E57: 42475
A58: Item | B58: Additional Tie-In Support & HDD Crews
A60: Date | B60: Description | C60: This Period | D60: Previous | E60: Total To Date
A61: 42460 | B61: Additional Tie-In Support: W2K-RFI-071
B62: March 31 Payment (25% of $763,439.04) | D62: 190859.76 | E62: =D62+C62 -> 190859.76
B63: April 31 Payment (25% of $763,439.04)
A65: 42460 | B65: HDD Support Crews To March 31: W2K-RFI-072 | D65: 1201072.3 | E65: =D65+C65 -> 1201072.3
B66: March 31 Payment (100% of $1,201,072.32)
A68: 42475 | B68: Additional Tie-In Support: W2K-RFI-071
B69: April 15 Payment (50% of $763,439.04) | C69: 381719.52 | E69: =C69+D69 -> 381719.52
B71: Total | C71: =SUM(C61:C70) -> 381719.52 | D71: =SUM(D61:D70) -> 1391932.1 | E71: =SUM(E61:E70) -> 1773651.6
A73: =Summary!$G$9 -> Contractor
C77: =Summary!$G$10 -> Construction Manager
D81: Approved CO Value ($) | E81: CO To Date ($)
D82: 1964511.4 | E82: =E71 -> 1773651.6
A84: =Summary!$G$11 -> PIPELINE PROJECT
A96: EXTRA WORK SUMMARY
A97: CO# | B97: CO-24
D99: Billing Date: | E99: 42490
A100: Item | B100: Additional Tie-In Support & HDD Crews
A102: Date | B102: Description | C102: This Period | D102: Previous | E102: Total To Date
A103: 42460 | B103: Additional Tie-In Support: W2K-RFI-071
B104: March 31 Payment (25% of $763,439.04) | D104: 190859.76 | E104: =D104+C104 -> 190859.76
A106: 42460 | B106: HDD Support Crews To March 31: W2K-RFI-072
B107: March 31 Payment (100% of $1,201,072.32) | D107: 1201072.3 | E107: =D107+C107 -> 1201072.3
A109: 42475 | B109: Additional Tie-In Support: W2K-RFI-071
B110: April 15 Payment (50% of $763,439.04) | D110: 381719.52 | E110: =C110+D110 -> 381719.52
A112: 42490 | B112: Additional Tie-In Support: W2K-RFI-071 | C112: 190859.76 | E112: =C112+D112 -> 190859.76
B113: April 30 Payment (25% of $763,439.04)
B115: Total | C115: =SUM(C103:C114) -> 190859.76 | D115: =SUM(D103:D114) -> 1773651.6 | E115: =SUM(E103:E114) -> 1964511.4
A117: =Summary!$G$9 -> Contractor
C121: =Summary!$G$10 -> Construction Manager
D125: Approved CO Value ($) | E125: CO To Date ($)
D126: 1964511.4 | E126: =E115 -> 1964511.4
A128: =Summary!$G$11 -> PIPELINE PROJECT
A140: EXTRA WORK SUMMARY
A141: CO# | B141: CO-24
D143: Billing Date: | E143: =Summary!$G$3 -> 42505
A144: Item | B144: Additional Tie-In Support & HDD Crews
A146: Date | B146: Description | C146: This Period | D146: Previous | E146: Total To Date
A147: 42460 | B147: Additional Tie-In Support: W2K-RFI-071
B148: March 31 Payment (25% of $763,439.04) | D148: 190859.76 | E148: =D148+C148 -> 190859.76
A150: 42460 | B150: HDD Support Crews To March 31: W2K-RFI-072
B151: March 31 Payment (100% of $1,201,072.32) | D151: 1201072.3 | E151: =D151+C151 -> 1201072.3
A153: 42475 | B153: Additional Tie-In Support: W2K-RFI-071
B154: April 15 Payment (50% of $763,439.04) | D154: 381719.52 | E154: =C154+D154 -> 381719.52
A156: 42490 | B156: Additional Tie-In Support: W2K-RFI-071 | D156: 190859.76 | E156: =C156+D156 -> 190859.76
B157: April 30 Payment (25% of $763,439.04)
B159: Total | C159: =SUM(C147:C158) -> 0 | D159: =SUM(D147:D158) -> 1964511.4 | E159: =SUM(E147:E158) -> 1964511.4
A161: =Summary!$G$9 -> Contractor
C165: =Summary!$G$10 -> Construction Manager
D169: Approved CO Value ($) | E169: CO To Date ($)
D170: 1964511.4 | E170: =E159 -> 1964511.4
E171: Complete

Sheet CO026UPI
A1: =Summary!$G$11 -> PIPELINE PROJECT
A13: UNIT PRICE SUMMARY
A14: CO# | B14: CO26
E16: Billing Date: | F16: 42400
A17: Item | B17: UPI SUMMARY
A19: Date | B19: UPI | C19: Description | D19: This Period | E19: Previous | F19: Total To Date
A21: 42400 | B21: 2.1 a) | C21: Rock Trench | D21: 1914.8 | F21: =D21+E21 -> 1914.8
B22: 2.2 b) | C22: Rockshield | D22: 22816.42 | F22: =D22+E22 -> 22816.42
B23: 2.3 a) b) c) d) | C23: Sand Bedding/Padding From Borrow Pits | D23: 17472 | F23: =D23+E23 -> 17472
B24: 2.29 | C24: Rig Mats | D24: 38880 | F24: =D24+E24 -> 38880
B25: 2.31 | C25: Move Around | D25: 4500 | F25: =D25+E25 -> 4500
F26: =D26+E26 -> 0
F27: =D27+E27 -> 0
F28: =D28+E28 -> 0
F29: =D29+E29 -> 0
F30: =D30+E30 -> 0
F31: =D31+E31 -> 0
F32: =D32+E32 -> 0
F33: =D33+E33 -> 0
F34: =D34+E34 -> 0
C35: Total | D35: =SUM(D20:D34) -> 85583.22 | E35: =SUM(E20:E34) -> 0 | F35: =SUM(F20:F34) -> 85583.22
A37: =Summary!$G$9 -> Contractor

Sheet CO027
A1: =Summary!$G$11 -> PIPELINE PROJECT
A13: EXTRA WORK SUMMARY
A14: CO# | B14: CO027
D16: Billing Date: | E16: 42429
A17: Item | B17: Existing Piping Removal At Station
A19: Date | B19: Description | C19: This Period | D19: Previous | E19: Total To Date
A20: 42429 | B20: Existing Piping Removal At Bald Mountain Station
B21: Tickets 0753 to 0760 | C21: 78334.63 | E21: =C21+D21 -> 78334.63
B29: Total | C29: =SUM(C20:C28) -> 78334.63 | D29: =SUM(D20:D28) -> 0 | E29: =SUM(E20:E28) -> 78334.63
A31: =Summary!$G$9 -> Contractor
C35: =Summary!$G$10 -> Construction Manager
D39: Approved CO Value ($) | E39: CO To Date ($)
D40: 200000 | E40: =E29 -> 78334.63
A42: =Summary!$G$11 -> PIPELINE PROJECT
A54: EXTRA WORK SUMMARY
A55: CO# | B55: CO027
D57: Billing Date: | E57: 42444
A58: Item | B58: Existing Piping Removal At Station
A60: Date | B60: Description | C60: This Period | D60: Previous | E60: Total To Date
A61: 42429 | B61: Existing Piping Removal At Station | D61: 78334.63 | E61: =C61+D61 -> 78334.63
A62: 42444 | B62: Badger Ticket: TKT00232464 plus 5% mark up | C62: 3649.1 | E62: =C62+D62 -> 3649.1
B63: Badger Ticket: TKT00233225 plus 5% mark up | C63: 3037.13 | E63: =C63+D63 -> 3037.13
B70: Total | C70: =SUM(C61:C69) -> 6686.23 | D70: =SUM(D61:D69) -> 78334.63 | E70: =SUM(E61:E69) -> 85020.86
A72: =Summary!$G$9 -> Contractor
C76: =Summary!$G$10 -> Construction Manager
D80: Approved CO Value ($) | E80: CO To Date ($)
D81: 200000 | E81: =E70 -> 85020.86
A83: =Summary!$G$11 -> PIPELINE PROJECT
A95: EXTRA WORK SUMMARY
A96: CO# | B96: CO027
D98: Billing Date: | E98: =Summary!$G$3 -> 42505
A99: Item | B99: Existing Piping Removal At Station
A101: Date | B101: Description | C101: This Period | D101: Previous | E101: Total To Date
A102: 42429 | B102: Existing Piping Removal At Station | D102: 78334.63 | E102: =C102+D102 -> 78334.63
A103: 42444 | B103: Badger Ticket: TKT00232464 plus 5% mark up | D103: 3649.1 | E103: =C103+D103 -> 3649.1
B104: Badger Ticket: TKT00233225 plus 5% mark up | D104: 3037.13 | E104: =C104+D104 -> 3037.13
B111: Total | C111: =SUM(C102:C110) -> 0 | D111: =SUM(D102:D110) -> 85020.86 | E111: =SUM(E102:E110) -> 85020.86
A113: =Summary!$G$9 -> Contractor
C117: =Summary!$G$10 -> Construction Manager
D121: Approved CO Value ($) | E121: CO To Date ($)
D122: 200000 | E122: =E111 -> 85020.86
E123: Complete

Sheet CO028UPI
A1: =Summary!$G$11 -> PIPELINE PROJECT
A13: UNIT PRICE SUMMARY
A14: CO# | B14: CO028
E16: Billing Date: | F16: 42415
A17: Item | B17: UPI SUMMARY
A19: Date | B19: UPI | C19: Description | D19: This Period | E19: Previous | F19: Total To Date
A21: 42415 | B21: 2.1 a) | C21: Rock Trench | D21: 4031.8 | F21: =D21+E21 -> 4031.8
B22: 2.2 b) | C22: Rockshield | D22: 79893.2 | F22: =D22+E22 -> 79893.2
B23: 2.3 d) | C23: Sand Bedding/Padding From Borrow Pits | D23: 27328 | F23: =D23+E23 -> 27328
B24: 2.22 | C24: Cut Out And Replace Welds | D24: 7780 | F24: =D24+E24 -> 7780
B25: 2.29 | C25: Rig Mats | D25: 12150 | F25: =D25+E25 -> 12150
F26: =D26+E26 -> 0
F27: =D27+E27 -> 0
F28: =D28+E28 -> 0
F29: =D29+E29 -> 0
F30: =D30+E30 -> 0
F31: =D31+E31 -> 0
F32: =D32+E32 -> 0
F33: =D33+E33 -> 0
F34: =D34+E34 -> 0
C35: Total | D35: =SUM(D20:D34) -> 131183 | E35: =SUM(E20:E34) -> 0 | F35: =SUM(F20:F34) -> 131183
A37: =Summary!$G$9 -> Contractor

Sheet CO029
A1: =Summary!$G$11 -> PIPELINE PROJECT
A13: EXTRA WORK SUMMARY
A14: CO# | B14: CO029
D16: Billing Date: | E16: 42429
A17: Item | B17: Stumping & Grubbing Not Completed By Clearing Contractor
A19: Date | B19: Description | C19: This Period | D19: Previous | E19: Total To Date
A20: 42429 | B20: Stumping & Grubbing Not Completed By Clearing
B21: Tickets 0601, 0602 | C21: 22059.31 | E21: =C21+D21 -> 22059.31
B29: Total | C29: =SUM(C20:C28) -> 22059.31 | D29: =SUM(D20:D28) -> 0 | E29: =SUM(E20:E28) -> 22059.31
A31: =Summary!$G$9 -> Contractor
C35: =Summary!$G$10 -> Construction Manager
D39: Approved CO Value ($) | E39: CO To Date ($)
D40: 22069.31 | E40: =E29 -> 22059.31
A42: =Summary!$G$11 -> PIPELINE PROJECT
A54: EXTRA WORK SUMMARY
A55: CO# | B55: CO029
D57: Billing Date: | E57: =Summary!$G$3 -> 42505
A58: Item | B58: Stumping & Grubbing Not Completed By Clearing Contractor
A60: Date | B60: Description | C60: This Period | D60: Previous | E60: Total To Date
A61: 42429 | B61: Stumping & Grubbing Not Completed By Clearing
B62: Tickets 0601, 0602 | D62: 22059.31 | E62: =C62+D62 -> 22059.31
B70: Total | C70: =SUM(C61:C69) -> 0 | D70: =SUM(D61:D69) -> 22059.31 | E70: =SUM(E61:E69) -> 22059.31
A72: =Summary!$G$9 -> Contractor
C76: =Summary!$G$10 -> Construction Manager
D80: Approved CO Value ($) | E80: CO To Date ($)
D81: 22069.31 | E81: =E70 -> 22059.31
E82: Complete

Sheet CO030
A1: =Summary!$G$11 -> PIPELINE PROJECT
A13: EXTRA WORK SUMMARY
A14: CO# | B14: CO030
D16: Billing Date: | E16: 42429
A17: Item | B17: 24 Hr Medic Coverage Additional To C004
A19: Date | B19: Description | C19: This Period | D19: Previous | E19: Total To Date
A20: 42429 | B20: 24 Hr Medic Coverage Additional To C004
B21: (Feb 5-Feb 29) | C21: 55125 | E21: =C21+D21 -> 55125
B29: Total | C29: =SUM(C20:C28) -> 55125 | D29: =SUM(D20:D28) -> 0 | E29: =SUM(E20:E28) -> 55125
A31: =Summary!$G$9 -> Contractor
C35: =Summary!$G$10 -> Construction Manager
D39: Approved CO Value ($) | E39: CO To Date ($)
D40: 150785.25 | E40: =E29 -> 55125
A42: =Summary!$G$11 -> PIPELINE PROJECT
A54: EXTRA WORK SUMMARY
A55: CO# | B55: CO030
D57: Billing Date: | E57: 42444
A58: Item | B58: 24 Hr Medic Coverage Additional To C004
A60: Date | B60: Description | C60: This Period | D60: Previous | E60: Total To Date
A61: 42429 | B61: 24 Hr Medic Coverage Additional To C004 | D61: 55125 | E61: =C61+D61 -> 55125
B62: (Feb 5-Feb 29)
A63: 42444 | B63: 24 Hr Medic Coverage Additional To C004 | C63: 34177.5 | E63: =C63+D63 -> 34177.5
B64: (Mar 1-15)
B70: Total | C70: =SUM(C61:C69) -> 34177.5 | D70: =SUM(D61:D69) -> 55125 | E70: =SUM(E61:E69) -> 89302.5
A72: =Summary!$G$9 -> Contractor
C76: =Summary!$G$10 -> Construction Manager
D80: Approved CO Value ($) | E80: CO To Date ($)
D81: 150785.25 | E81: =E70 -> 89302.5
A83: =Summary!$G$11 -> PIPELINE PROJECT
A95: EXTRA WORK SUMMARY
A96: CO# | B96: CO030
D98: Billing Date: | E98: 42460
A99: Item | B99: 24 Hr Medic Coverage Additional To C004
A101: Date | B101: Description | C101: This Period | D101: Previous | E101: Total To Date
A102: 42429 | B102: 24 Hr Medic Coverage Additional To C004 | D102: 55125 | E102: =C102+D102 -> 55125
B103: (Feb 5-Feb 29)
A104: 42444 | B104: 24 Hr Medic Coverage Additional To C004 | D104: 34177.5 | E104: =C104+D104 -> 34177.5
B105: (Mar 1-15)
A106: 42460 | B106: 24 Hr Medic Coverage Additional To C004 | C106: 31710 | E106: =C106+D106 -> 31710
B107: (Mar 16-31)
B111: Total | C111: =SUM(C102:C110) -> 31710 | D111: =SUM(D102:D110) -> 89302.5 | E111: =SUM(E102:E110) -> 121012.5
A113: =Summary!$G$9 -> Contractor
C117: =Summary!$G$10 -> Construction Manager
D121: Approved CO Value ($) | E121: CO To Date ($)
D122: 150785.25 | E122: =E111 -> 121012.5
A124: =Summary!$G$11 -> PIPELINE PROJECT
A136: EXTRA WORK SUMMARY
A137: CO# | B137: CO030
D139: Billing Date: | E139: 42475
A140: Item | B140: 24 Hr Medic Coverage Additional To C004
A142: Date | B142: Description | C142: This Period | D142: Previous | E142: Total To Date
A143: 42429 | B143: 24 Hr Medic Coverage Additional To C004 | D143: 55125 | E143: =C143+D143 -> 55125
B144: (Feb 5-Feb 29)
A145: 42444 | B145: 24 Hr Medic Coverage Additional To C004 | D145: 34177.5 | E145: =C145+D145 -> 34177.5
B146: (Mar 1-15)
A147: 42460 | B147: 24 Hr Medic Coverage Additional To C004 | D147: 31710 | E147: =C147+D147 -> 31710
B148: (Mar 16-31)
A149: 42475 | B149: 24 Hr Medic Coverage Additional To C004 | C149: 16537.5 | E149: =D149+C149 -> 16537.5
B150: (Mar 1-8)
B152: Total | C152: =SUM(C143:C151) -> 16537.5 | D152: =SUM(D143:D151) -> 121012.5 | E152: =SUM(E143:E151) -> 137550
A154: =Summary!$G$9 -> Contractor
C158: =Summary!$G$10 -> Construction Manager
D162: Approved CO Value ($) | E162: CO To Date ($)
D163: 150785.25 | E163: =E152 -> 137550
A165: =Summary!$G$11 -> PIPELINE PROJECT
A177: EXTRA WORK SUMMARY
A178: CO# | B178: CO030
D180: Billing Date: | E180: =Summary!$G$3 -> 42505
A181: Item | B181: 24 Hr Medic Coverage Additional To C004
A183: Date | B183: Description | C183: This Period | D183: Previous | E183: Total To Date
A184: 42429 | B184: 24 Hr Medic Coverage Additional To C004 | D184: 55125 | E184: =C184+D184 -> 55125
B185: (Feb 5-Feb 29)
A186: 42444 | B186: 24 Hr Medic Coverage Additional To C004 | D186: 34177.5 | E186: =C186+D186 -> 34177.5
B187: (Mar 1-15)
A188: 42460 | B188: 24 Hr Medic Coverage Additional To C004 | D188: 31710 | E188: =C188+D188 -> 31710
B189: (Mar 16-31)
A190: 42475 | B190: 24 Hr Medic Coverage Additional To C004 | D190: 16537.5 | E190: =D190+C190 -> 16537.5
B191: (Mar 1-8)
A192: 42490 | B192: 24 Hr Medic Coverage Additional To C004 | E192: =D192+C192 -> 0
B193: (Mar ?-?)
B195: Total | C195: =SUM(C184:C194) -> 0 | D195: =SUM(D184:D194) -> 137550 | E195: =SUM(E184:E194) -> 137550
A197: =Summary!$G$9 -> Contractor
C201: =Summary!$G$10 -> Construction Manager
D205: Approved CO Value ($) | E205: CO To Date ($)
D206: 150785.25 | E206: =E195 -> 137550
E207: Complete

Sheet CO031
A1: =Summary!$G$11 -> PIPELINE PROJECT
A13: EXTRA WORK SUMMARY
A14: CO# | B14: CO031
D16: Billing Date: | E16: 42429
A17: Item | B17: Install/Remove/Truck Access Mats- Addit. To C010
A19: Date | B19: Description | C19: This Period | D19: Previous | E19: Total To Date
A20: 42429 | B20: Install/Remove/Truck Access Mats- Addit. To C010
B21: Note: This is balance of work ($2,965.60) from | C21: 2965.6 | E21: =C21+D21 -> 2965.6
B22: Change Order C010
B29: Total | C29: =SUM(C20:C28) -> 2965.6 | D29: =SUM(D20:D28) -> 0 | E29: =SUM(E20:E28) -> 2965.6
A31: =Summary!$G$9 -> Contractor
C35: =Summary!$G$10 -> Construction Manager
D39: Approved CO Value ($) | E39: CO To Date ($)
D40: 2965.6 | E40: =E29 -> 2965.6
A42: =Summary!$G$11 -> PIPELINE PROJECT
A54: EXTRA WORK SUMMARY
A55: CO# | B55: CO031
D57: Billing Date: | E57: =Summary!$G$3 -> 42505
A58: Item | B58: Install/Remove/Truck Access Mats- Addit. To C010
A60: Date | B60: Description | C60: This Period | D60: Previous | E60: Total To Date
A61: 42429 | B61: Install/Remove/Truck Access Mats- Addit. To C010
B62: Note: This is balance of work ($2,965.60) from | D62: 2965.6 | E62: =C62+D62 -> 2965.6
B63: Change Order C010
B70: Total | C70: =SUM(C61:C69) -> 0 | D70: =SUM(D61:D69) -> 2965.6 | E70: =SUM(E61:E69) -> 2965.6
A72: =Summary!$G$9 -> Contractor
C76: =Summary!$G$10 -> Construction Manager
D80: Approved CO Value ($) | E80: CO To Date ($)
D81: 2965.6 | E81: =E70 -> 2965.6
E82: Complete

Sheet CO033
A1: =Summary!$G$11 -> PIPELINE PROJECT
A13: EXTRA WORK SUMMARY
A14: CO# | B14: CO033
D16: Billing Date: | E16: 42429
A17: Item | B17: Mix & Backfill HDD Mud Sump Pits
A19: Date | B19: Description | C19: This Period | D19: Previous | E19: Total To Date
A20: 42429 | B20: Mix & Backfill HDD Mud Sump Pits
B21: Tickets 0436, 0437, 0438, 0439 | C21: 14188.83 | E21: =C21+D21 -> 14188.83
B29: Total | C29: =SUM(C20:C28) -> 14188.83 | D29: =SUM(D20:D28) -> 0 | E29: =SUM(E20:E28) -> 14188.83
A31: =Summary!$G$9 -> Contractor
C35: =Summary!$G$10 -> Construction Manager
D39: Approved CO Value ($) | E39: CO To Date ($)
D40: 165080.96 | E40: =E29 -> 14188.83
A42: =Summary!$G$11 -> PIPELINE PROJECT
A54: EXTRA WORK SUMMARY
A55: CO# | B55: CO033
D57: Billing Date: | E57: 42460
A58: Item | B58: Mix & Backfill HDD Mud Sump Pits
A60: Date | B60: Description | C60: This Period | D60: Previous | E60: Total To Date
A61: 42429 | B61: Mix & Backfill HDD Mud Sump Pits
B62: Tickets: 0436, 0437, 0438, 0439 | D62: 14188.83 | E62: =C62+D62 -> 14188.83
A63: 42460 | B63: Mix & Backfill HDD Mud Sump Pits | C63: 66930.13 | E63: =C63+D63 -> 66930.13
B64: Tickets: 0446, 0449, 0450, 1455, 1456, 1458, 1457,
B65: 1459, 1462, 0150, 1463, 1026, 1464, 1443, 1027,
B66: 1444, 1445
B70: Total | C70: =SUM(C61:C69) -> 66930.13 | D70: =SUM(D61:D69) -> 14188.83 | E70: =SUM(E61:E69) -> 81118.96
A72: =Summary!$G$9 -> Contractor
C76: =Summary!$G$10 -> Construction Manager
D80: Approved CO Value ($) | E80: CO To Date ($)
D81: 165080.96 | E81: =E70 -> 81118.96
A83: =Summary!$G$11 -> PIPELINE PROJECT
A95: EXTRA WORK SUMMARY
A96: CO# | B96: CO033
D98: Billing Date: | E98: 42475
A99: Item | B99: Mix & Backfill HDD Mud Sump Pits
A101: Date | B101: Description | C101: This Period | D101: Previous | E101: Total To Date
A102: 42429 | B102: Mix & Backfill HDD Mud Sump Pits | D102: 14188.83 | E102: =C102+D102 -> 14188.83
B103: Tickets: 0436, 0437, 0438, 0439
A104: 42460 | B104: Mix & Backfill HDD Mud Sump Pits | D104: 66930.13 | E104: =C104+D104 -> 66930.13
B105: Tickets: 0446, 0449, 0450, 1455, 1456, 1458, 1457,
B106: 1459, 1462, 0150, 1463, 1026, 1464, 1443, 1027,
B107: 1444, 1445
A108: 42475 | B108: Mix & Backfill HDD Mud Sump Pits | C108: 47362.37 | E108: =D108+C108 -> 47362.37
B109: Tickets: 1031, 0539, 1446, 0953, 0540, 0541, 0954,
B110: 1447, 1467, 0957, 1450
B111: Total | C111: =SUM(C102:C110) -> 47362.37 | D111: =SUM(D102:D110) -> 81118.96 | E111: =SUM(E102:E110) -> 128481.33
A113: =Summary!$G$9 -> Contractor
C117: =Summary!$G$10 -> Construction Manager
D121: Approved CO Value ($) | E121: CO To Date ($)
D122: 165080.96 | E122: =E111 -> 128481.33
A124: =Summary!$G$11 -> PIPELINE PROJECT
A136: EXTRA WORK SUMMARY
A137: CO# | B137: CO033
D139: Billing Date: | E139: 42490
A140: Item | B140: Mix & Backfill HDD Mud Sump Pits
A142: Date | B142: Description | C142: This Period | D142: Previous | E142: Total To Date
A143: 42429 | B143: Mix & Backfill HDD Mud Sump Pits | D143: 14188.83 | E143: =C143+D143 -> 14188.83
B144: Tickets: 0436, 0437, 0438, 0439
A145: 42460 | B145: Mix & Backfill HDD Mud Sump Pits | D145: 66930.13 | E145: =C145+D145 -> 66930.13
B146: Tickets: 0446, 0449, 0450, 1455, 1456, 1458, 1457,
B147: 1459, 1462, 0150, 1463, 1026, 1464, 1443, 1027,
B148: 1444, 1445
A149: 42475 | B149: Mix & Backfill HDD Mud Sump Pits | D149: 47362.37 | E149: =D149+C149 -> 47362.37
B150: Tickets: 1031, 0539, 1446, 0953, 0540, 0541, 0954,
B151: 1447, 1467, 0957, 1450
A152: 42490 | B152: Mix & Backfill HDD Mud Sump Pits | C152: 36559.87 | E152: =D152+C152 -> 36559.87
B153: Tickets: 0964, 0965, 0969, 0970, 0973
B155: Total | C155: =SUM(C143:C154) -> 36559.87 | D155: =SUM(D143:D154) -> 128481.33 | E155: =SUM(E143:E154) -> 165041.2
A157: =Summary!$G$9 -> Contractor
C161: =Summary!$G$10 -> Construction Manager
D165: Approved CO Value ($) | E165: CO To Date ($)
D166: 165080.96 | E166: =E155 -> 165041.2
A168: =Summary!$G$11 -> PIPELINE PROJECT
A180: EXTRA WORK SUMMARY
A181: CO# | B181: CO033
D183: Billing Date: | E183: =Summary!$G$3 -> 42505
A184: Item | B184: Mix & Backfill HDD Mud Sump Pits
A186: Date | B186: Description | C186: This Period | D186: Previous | E186: Total To Date
A187: 42429 | B187: Mix & Backfill HDD Mud Sump Pits | D187: 14188.83 | E187: =C187+D187 -> 14188.83
B188: Tickets: 0436, 0437, 0438, 0439
A189: 42460 | B189: Mix & Backfill HDD Mud Sump Pits | D189: 66930.13 | E189: =C189+D189 -> 66930.13
B190: Tickets: 0446, 0449, 0450, 1455, 1456, 1458, 1457,
B191: 1459, 1462, 0150, 1463, 1026, 1464, 1443, 1027,
B192: 1444, 1445
A193: 42475 | B193: Mix & Backfill HDD Mud Sump Pits | D193: 47362.37 | E193: =D193+C193 -> 47362.37
B194: Tickets: 1031, 0539, 1446, 0953, 0540, 0541, 0954,
B195: 1447, 1467, 0957, 1450
A196: 42490 | B196: Mix & Backfill HDD Mud Sump Pits | D196: 36559.87 | E196: =D196+C196 -> 36559.87
B197: Tickets: 0964, 0965, 0969, 0970, 0973
B199: Total | C199: =SUM(C187:C198) -> 0 | D199: =SUM(D187:D198) -> 165041.2 | E199: =SUM(E187:E198) -> 165041.2
A201: =Summary!$G$9 -> Contractor
C205: =Summary!$G$10 -> Construction Manager
D209: Approved CO Value ($) | E209: CO To Date ($)
D210: 165080.96 | E210: =E199 -> 165041.2
E211: Complete

Sheet CO034
A1: =Summary!$G$11 -> PIPELINE PROJECT
A13: EXTRA WORK SUMMARY
A14: CO# | B14: CO034
D16: Billing Date: | E16: 42444
A17: Item | B17: Remove Merchantable Timber When Mills Were Closed
A19: Date | B19: Description | C19: This Period | D19: Previous | E19: Total To Date
A20: 42444 | B20: Remove Merchatable Timber
B21: 1701747 Alberta Ltd Invoice: #242 | C21: 5512.5 | E21: =C21+D21 -> 5512.5
B29: Total | C29: =SUM(C20:C28) -> 5512.5 | D29: =SUM(D20:D28) -> 0 | E29: =SUM(E20:E28) -> 5512.5
A31: =Summary!$G$9 -> Contractor
C35: =Summary!$G$10 -> Construction Manager
D39: Approved CO Value ($) | E39: CO To Date ($)
D40: 5512.5 | E40: =E29 -> 5512.5
A42: =Summary!$G$11 -> PIPELINE PROJECT
A54: EXTRA WORK SUMMARY
A55: CO# | B55: CO034
D57: Billing Date: | E57: =Summary!$G$3 -> 42505
A58: Item | B58: Remove Merchantable Timber When Mills Were Closed
A60: Date | B60: Description | C60: This Period | D60: Previous | E60: Total To Date
A61: 42444 | B61: Remove Merchatable Timber
B62: 1701747 Alberta Ltd Invoice: #242 | D62: 5512.5 | E62: =C62+D62 -> 5512.5
B70: Total | C70: =SUM(C61:C69) -> 0 | D70: =SUM(D61:D69) -> 5512.5 | E70: =SUM(E61:E69) -> 5512.5
A72: =Summary!$G$9 -> Contractor
C76: =Summary!$G$10 -> Construction Manager
D80: Approved CO Value ($) | E80: CO To Date ($)
D81: 5512.5 | E81: =E70 -> 5512.5
E82: Complete

Sheet CO035UPI
A1: =Summary!$G$11 -> PIPELINE PROJECT
A13: UNIT PRICE SUMMARY
A14: CO# | B14: CO035
E16: Billing Date: | F16: 42429
A17: Item | B17: UPI SUMMARY
A19: Date | B19: UPI | C19: Description | D19: This Period | E19: Previous | F19: Total To Date
A21: =F16 -> 42429 | B21: 2.1 a) | C21: Rock Trench | D21: 35207.68 | F21: =D21+E21 -> 35207.68
B22: 2.2 b) | C22: Rockshield | D22: 460059.58 | F22: =D22+E22 -> 460059.58
B23: 2.3 a) | C23: Sand Bedding From Borrow Pits | D23: 24102.4 | F23: =D23+E23 -> 24102.4
B24: 2.3 b) | C24: Sand Padding (Top) From Borrow Pits | D24: 26763.98 | F24: =D24+E24 -> 26763.98
B25: 2.3 d) | C25: Sand Hauling From Borrow Pits | D25: 75801.6 | F25: =D25+E25 -> 75801.6
B26: 2.22 | C26: Cut Out And Replace Welds | D26: 3890 | F26: =D26+E26 -> 3890
B27: 2.31 | C27: Move Around (Bear Den At KP 48+800) | D27: 20050 | F27: =D27+E27 -> 20050
C28: (Bending, Welding, Coating) | F28: =D28+E28 -> 0
F29: =D29+E29 -> 0
F30: =D30+E30 -> 0
F31: =D31+E31 -> 0
F32: =D32+E32 -> 0
F33: =D33+E33 -> 0
F34: =D34+E34 -> 0
C35: Total | D35: =SUM(D20:D34) -> 645875.24 | E35: =SUM(E20:E34) -> 0 | F35: =SUM(F20:F34) -> 645875.24
A37: =Summary!$G$9 -> Contractor

Sheet CO036UPI
A1: =Summary!$G$11 -> PIPELINE PROJECT
A13: UNIT PRICE SUMMARY
A14: CO# | B14: CO036
E16: Billing Date: | F16: 42444
A17: Item | B17: UPI SUMMARY
A19: Date | B19: UPI | C19: Description | D19: This Period | E19: Previous | F19: Total To Date
A21: 42444 | B21: 2.1 a) | C21: Rock Trench | D21: 3361.32 | F21: =D21+E21 -> 3361.32
B22: 2.2 b) | C22: Rockshield | D22: 243353.66 | F22: =D22+E22 -> 243353.66
B23: 2.3 d) | C23: Sand Hauling From Borrow Pits | D23: 5880 | F23: =D23+E23 -> 5880
B24: 2.31 | C24: Move Around (Bear Den At KP 48+800) | D24: 31899.999 | F24: =D24+E24 -> 31899.999
C25: (Part of Grade, Trenching, Lower-In & Backfill) | F25: =D25+E25 -> 0
F26: =D26+E26 -> 0
F27: =D27+E27 -> 0
F28: =D28+E28 -> 0
F29: =D29+E29 -> 0
F30: =D30+E30 -> 0
F31: =D31+E31 -> 0
F32: =D32+E32 -> 0
F33: =D33+E33 -> 0
F34: =D34+E34 -> 0
C35: Total | D35: =SUM(D20:D34) -> 284494.98 | E35: =SUM(E20:E34) -> 0 | F35: =SUM(F20:F34) -> 284494.98
A37: =Summary!$G$9 -> Contractor

Sheet CO037
A1: =Summary!$G$11 -> PIPELINE PROJECT
A13: EXTRA WORK SUMMARY
A14: CO# | B14: CO037
D16: Billing Date: | E16: 42444
A17: Item | B17: Water Trucks To Support HDD Rigs
A19: Date | B19: Description | C19: This Period | D19: Previous | E19: Total To Date
A20: 42444 | B20: Water Trucks (Feb 16-23) | C20: 42875.6 | E20: =C20+D20 -> 42875.6
B29: Total | C29: =SUM(C20:C28) -> 42875.6 | D29: =SUM(D20:D28) -> 0 | E29: =SUM(E20:E28) -> 42875.6
A31: =Summary!$G$9 -> Contractor
C35: =Summary!$G$10 -> Construction Manager
D39: Approved CO Value ($) | E39: CO To Date ($)
D40: 67500 | E40: =E29 -> 42875.6
A42: =Summary!$G$11 -> PIPELINE PROJECT
A54: EXTRA WORK SUMMARY
A55: CO# | B55: CO037
D57: Billing Date: | E57: =Summary!$G$3 -> 42505
A58: Item | B58: Water Trucks To Support HDD Rigs
A60: Date | B60: Description | C60: This Period | D60: Previous | E60: Total To Date
A61: 42444 | B61: Water Trucks (Feb 16-23) | D61: 42875.6 | E61: =C61+D61 -> 42875.6
B70: Total | C70: =SUM(C61:C69) -> 0 | D70: =SUM(D61:D69) -> 42875.6 | E70: =SUM(E61:E69) -> 42875.6
A72: =Summary!$G$9 -> Contractor
C76: =Summary!$G$10 -> Construction Manager
D80: Approved CO Value ($) | E80: CO To Date ($)
D81: 67500 | E81: =E70 -> 42875.6
E82: Complete

Sheet CO038
A1: =Summary!$G$11 -> PIPELINE PROJECT
A13: EXTRA WORK SUMMARY
A14: CO# | B14: CO038
D16: Billing Date: | E16: 42444
A17: Item | B17: Other Drill IMR Clean Up
A19: Date | B19: Description | C19: This Period | D19: Previous | E19: Total To Date
A20: 42444 | B20: River & KP 64+445 IMR Clean Up | C20: 122366.91 | E20: =C20+D20 -> 122366.91
B29: Total | C29: =SUM(C20:C28) -> 122366.91 | D29: =SUM(D20:D28) -> 0 | E29: =SUM(E20:E28) -> 122366.91
A31: =Summary!$G$9 -> Contractor
C35: =Summary!$G$10 -> Construction Manager
D39: Approved CO Value ($) | E39: CO To Date ($)
D40: 197366.91 | E40: =E29 -> 122366.91
A42: =Summary!$G$11 -> PIPELINE PROJECT
A54: EXTRA WORK SUMMARY
A55: CO# | B55: CO038
D57: Billing Date: | E57: 42460
A58: Item | B58: Other Drill IMR Clean Up
A60: Date | B60: Description | C60: This Period | D60: Previous | E60: Total To Date
A61: 42444 | B61: River & KP 64+445 IMR Clean Up | D61: 122366.91 | E61: =C61+D61 -> 122366.91
A62: 42460 | B62: KP 30+551 IMR Clean Up | C62: 67863.74 | E62: =D62+C62 -> 67863.74
B70: Total | C70: =SUM(C61:C69) -> 67863.74 | D70: =SUM(D61:D69) -> 122366.91 | E70: =SUM(E61:E69) -> 190230.65
A72: =Summary!$G$9 -> Contractor
C76: =Summary!$G$10 -> Construction Manager
D80: Approved CO Value ($) | E80: CO To Date ($)
D81: 197366.91 | E81: =E70 -> 190230.65
A83: =Summary!$G$11 -> PIPELINE PROJECT
A95: EXTRA WORK SUMMARY
A96: CO# | B96: CO038
D98: Billing Date: | E98: 42475
A99: Item | B99: Other Drill IMR Clean Up
A101: Date | B101: Description | C101: This Period | D101: Previous | E101: Total To Date
A102: 42444 | B102: River & KP 64+445 IMR Clean Up | D102: 122366.91 | E102: =C102+D102 -> 122366.91
A103: 42460 | B103: KP 30+551 IMR Clean Up | D103: 67863.74 | E103: =D103+C103 -> 67863.74
A104: 42475 | B104: River IMR Clean Up | C104: 5479.88 | E104: =D104+C104 -> 5479.88
B111: Total | C111: =SUM(C102:C110) -> 5479.88 | D111: =SUM(D102:D110) -> 190230.65 | E111: =SUM(E102:E110) -> 195710.53
A113: =Summary!$G$9 -> Contractor
C117: =Summary!$G$10 -> Construction Manager
D121: Approved CO Value ($) | E121: CO To Date ($)
D122: 197366.91 | E122: =E111 -> 195710.53
A124: =Summary!$G$11 -> PIPELINE PROJECT
A136: EXTRA WORK SUMMARY
A137: CO# | B137: CO038
D139: Billing Date: | E139: =Summary!$G$3 -> 42505
A140: Item | B140: Other Drill IMR Clean Up
A142: Date | B142: Description | C142: This Period | D142: Previous | E142: Total To Date
A143: 42444 | B143: River & KP 64+445 IMR Clean Up | D143: 122366.91 | E143: =C143+D143 -> 122366.91
A144: 42460 | B144: KP 30+551 IMR Clean Up | D144: 67863.74 | E144: =D144+C144 -> 67863.74
A145: 42475 | B145: River IMR Clean Up | D145: 5479.88 | E145: =D145+C145 -> 5479.88
A146: 42505 | B146: KP 39+600 Mud Clean Up | C146: 1480.14 | E146: =D146+C146 -> 1480.14
B152: Total | C152: =SUM(C143:C151) -> 1480.14 | D152: =SUM(D143:D151) -> 195710.53 | E152: =SUM(E143:E151) -> 197190.67
A154: =Summary!$G$9 -> Contractor
C158: =Summary!$G$10 -> Construction Manager
D162: Approved CO Value ($) | E162: CO To Date ($)
D163: 197366.91 | E163: =E152 -> 197190.67

Sheet CO039
A1: =Summary!$G$11 -> PIPELINE PROJECT
A13: EXTRA WORK SUMMARY
A14: CO# | B14: CO039
D16: Billing Date: | E16: 42444
A17: Item | B17: X-Ray Auditor Call Backs
A19: Date | B19: Description | C19: This Period | D19: Previous | E19: Total To Date
A20: 42444 | B20: X-Ray Auditor Call Back | C20: 5805.78 | E20: =C20+D20 -> 5805.78
B21: Tickets: 0178, 0332, 0179, 0180, 0278
B29: Total | C29: =SUM(C20:C28) -> 5805.78 | D29: =SUM(D20:D28) -> 0 | E29: =SUM(E20:E28) -> 5805.78
A31: =Summary!$G$9 -> Contractor
C35: =Summary!$G$10 -> Construction Manager
D39: Approved CO Value ($) | E39: CO To Date ($)
D40: 9805.78 | E40: =E29 -> 5805.78
A42: =Summary!$G$11 -> PIPELINE PROJECT
A54: EXTRA WORK SUMMARY
A55: CO# | B55: CO039
D57: Billing Date: | E57: =Summary!$G$3 -> 42505
A58: Item | B58: X-Ray Auditor Call Backs
A60: Date | B60: Description | C60: This Period | D60: Previous | E60: Total To Date
A61: 42444 | B61: X-Ray Auditor Call Back | D61: 5805.78 | E61: =C61+D61 -> 5805.78
B62: Tickets: 0178, 0332, 0179, 0180, 0278
B70: Total | C70: =SUM(C61:C69) -> 0 | D70: =SUM(D61:D69) -> 5805.78 | E70: =SUM(E61:E69) -> 5805.78
A72: =Summary!$G$9 -> Contractor
C76: =Summary!$G$10 -> Construction Manager
D80: Approved CO Value ($) | E80: CO To Date ($)
D81: 9805.78 | E81: =E70 -> 5805.78

Sheet CO040
A1: =Summary!$G$11 -> PIPELINE PROJECT
A13: EXTRA WORK SUMMARY
A14: CO# | B14: CO040
D16: Billing Date: | E16: 42460
A17: Item | B17: Delays Due To Clearing, Reps & Misc. Causes
A19: Date | B19: Description | C19: This Period | D19: Previous | E19: Total To Date
A20: 42460 | B20: Delays Due to Clearing, Reps & Misc. Causes | C20: 84077.7 | E20: =C20+D20 -> 84077.7
B21: Tickets: 0604, 0617, 0606, 0330, 0613, 0707, 0708
B22: 0710, 0712
B29: Total | C29: =SUM(C20:C28) -> 84077.7 | D29: =SUM(D20:D28) -> 0 | E29: =SUM(E20:E28) -> 84077.7
A31: =Summary!$G$9 -> Contractor
C35: =Summary!$G$10 -> Construction Manager
D39: Approved CO Value ($) | E39: CO To Date ($)
D40: 104077.7 | E40: =E29 -> 84077.7
A42: =Summary!$G$11 -> PIPELINE PROJECT
A54: EXTRA WORK SUMMARY
A55: CO# | B55: C0040
D57: Billing Date: | E57: =Summary!$G$3 -> 42505
A58: Item | B58: Delays Due To Clearing, Reps & Misc. Causes
A60: Date | B60: Description | C60: This Period | D60: Previous | E60: Total To Date
A61: 42460 | B61: Delays Due to Clearing, Reps & Misc. Causes | D61: 84077.7 | E61: =C61+D61 -> 84077.7
B62: Tickets: 0604, 0617, 0606, 0330, 0613, 0707, 0708
B63: 0710, 0712
B70: Total | C70: =SUM(C61:C69) -> 0 | D70: =SUM(D61:D69) -> 84077.7 | E70: =SUM(E61:E69) -> 84077.7
A72: =Summary!$G$9 -> Contractor
C76: =Summary!$G$10 -> Construction Manager
D80: Approved CO Value ($) | E80: CO To Date ($)
D81: 104077.7 | E81: =E70 -> 84077.7

Sheet CO041
A1: =Summary!$G$11 -> PIPELINE PROJECT
A13: EXTRA WORK SUMMARY
A14: CO# | B14: CO041
D16: Billing Date: | E16: 42460
A17: Item | B17: Purchase Of Seed Mix
A19: Date | B19: Description | C19: This Period | D19: Previous | E19: Total To Date
A20: 42460 | B20: Purchase of Seed Mix | C20: 8411.63 | E20: =C20+D20 -> 8411.63
B21: Invoice: Foster's Seed & Feed #230164
B29: Total | C29: =SUM(C20:C28) -> 8411.63 | D29: =SUM(D20:D28) -> 0 | E29: =SUM(E20:E28) -> 8411.63
A31: =Summary!$G$9 -> Contractor
C35: =Summary!$G$10 -> Construction Manager
D39: Approved CO Value ($) | E39: CO To Date ($)
D40: 10000 | E40: =E29 -> 8411.63
A42: =Summary!$G$11 -> PIPELINE PROJECT
A54: EXTRA WORK SUMMARY
A55: CO# | B55: CO041
D57: Billing Date: | E57: 42490
A58: Item | B58: Purchase Of Seed Mix
A60: Date | B60: Description | C60: This Period | D60: Previous | E60: Total To Date
A61: 42460 | B61: Purchase of Seed Mix | D61: 8411.63 | E61: =C61+D61 -> 8411.63
B62: Invoice: Foster's Seed & Feed #230164
A63: 42490 | B63: Purchase of Seed Mix | C63: 511.97 | E63: =D63+C63 -> 511.97
B64: Invoice: Foster's Seed & Feed #230295
B70: Total | C70: =SUM(C61:C69) -> 511.97 | D70: =SUM(D61:D69) -> 8411.63 | E70: =SUM(E61:E69) -> 8923.6
A72: =Summary!$G$9 -> Contractor
C76: =Summary!$G$10 -> Construction Manager
D80: Approved CO Value ($) | E80: CO To Date ($)
D81: 10000 | E81: =E70 -> 8923.6
A83: =Summary!$G$11 -> PIPELINE PROJECT
A95: EXTRA WORK SUMMARY
A96: CO# | B96: CO041
D98: Billing Date: | E98: =Summary!$G$3 -> 42505
A99: Item | B99: Purchase Of Seed Mix
A101: Date | B101: Description | C101: This Period | D101: Previous | E101: Total To Date
A102: 42460 | B102: Purchase of Seed Mix | D102: 8411.63 | E102: =C102+D102 -> 8411.63
B103: Invoice: Foster's Seed & Feed #230164
A104: 42490 | B104: Purchase of Seed Mix | D104: 511.97 | E104: =D104+C104 -> 511.97
B105: Invoice: Foster's Seed & Feed #230295
B111: Total | C111: =SUM(C102:C110) -> 0 | D111: =SUM(D102:D110) -> 8923.6 | E111: =SUM(E102:E110) -> 8923.6
A113: =Summary!$G$9 -> Contractor
C117: =Summary!$G$10 -> Construction Manager
D121: Approved CO Value ($) | E121: CO To Date ($)
D122: 10000 | E122: =E111 -> 8923.6

Sheet CO042UPI
A1: =Summary!$G$11 -> PIPELINE PROJECT
A13: UNIT PRICE SUMMARY
A14: CO# | B14: CO042
E16: Billing Date: | F16: 42460
A17: Item | B17: UPI SUMMARY
A19: Date | B19: UPI | C19: Description | D19: This Period | E19: Previous | F19: Total To Date
A21: 42460 | B21: 2.2 b) | C21: Rockshield | D21: 59762.28 | F21: =D21+E21 -> 59762.28
B22: 2.29 | C22: Rig Mats | D22: 6291 | F22: =D22+E22 -> 6291
F23: =D23+E23 -> 0
F24: =D24+E24 -> 0
F25: =D25+E25 -> 0
F26: =D26+E26 -> 0
F27: =D27+E27 -> 0
F28: =D28+E28 -> 0
F29: =D29+E29 -> 0
F30: =D30+E30 -> 0
F31: =D31+E31 -> 0
F32: =D32+E32 -> 0
F33: =D33+E33 -> 0
F34: =D34+E34 -> 0
C35: Total | D35: =SUM(D20:D34) -> 66053.28 | E35: =SUM(E20:E34) -> 0 | F35: =SUM(F20:F34) -> 66053.28
A37: =Summary!$G$9 -> Contractor

Sheet CO043
A1: =Summary!$G$11 -> PIPELINE PROJECT
A13: EXTRA WORK SUMMARY
A14: CO# | B14: CO043
D16: Billing Date: | E16: 42460
A17: Item | B17: Digging Sumps Additional To C011
A19: Date | B19: Description | C19: This Period | D19: Previous | E19: Total To Date
A20: 42460 | B20: Digging Sumps Additional To C011 | C20: 9370.55 | E20: =C20+D20 -> 9370.55
B21: Tickets: 1440, 1441, 1442
B29: Total | C29: =SUM(C20:C28) -> 9370.55 | D29: =SUM(D20:D28) -> 0 | E29: =SUM(E20:E28) -> 9370.55
A31: =Summary!$G$9 -> Contractor
C35: =Summary!$G$10 -> Construction Manager
D39: Approved CO Value ($) | E39: CO To Date ($)
D40: 80000 | E40: =E29 -> 9370.55
A42: =Summary!$G$11 -> PIPELINE PROJECT
A54: EXTRA WORK SUMMARY
A55: CO# | B55: CO043
D57: Billing Date: | E57: 42475
A58: Item | B58: Digging Sumps Additional To C011
A60: Date | B60: Description | C60: This Period | D60: Previous | E60: Total To Date
A61: 42460 | B61: Digging Sumps Additional To C011 | D61: 9370.55 | E61: =C61+D61 -> 9370.55
A63: 42475 | B63: Digging Sumps Additional To C011 | C63: 56999.37 | E63: =C63+D63 -> 56999.37
B70: Total | C70: =SUM(C61:C69) -> 56999.37 | D70: =SUM(D61:D69) -> 9370.55 | E70: =SUM(E61:E69) -> 66369.92
A72: =Summary!$G$9 -> Contractor
C76: =Summary!$G$10 -> Construction Manager
D80: Approved CO Value ($) | E80: CO To Date ($)
D81: 80000 | E81: =E70 -> 66369.92
A83: =Summary!$G$11 -> PIPELINE PROJECT
A95: EXTRA WORK SUMMARY
A96: CO# | B96: CO043
D98: Billing Date: | E98: =Summary!$G$3 -> 42505
A99: Item | B99: Digging Sumps Additional To C011
A101: Date | B101: Description | C101: This Period | D101: Previous | E101: Total To Date
A102: 42460 | B102: Digging Sumps Additional To C011 | D102: 9370.55 | E102: =C102+D102 -> 9370.55
A104: 42475 | B104: Digging Sumps Additional To C011 | D104: 56999.37 | E104: =C104+D104 -> 56999.37
B111: Total | C111: =SUM(C102:C110) -> 0 | D111: =SUM(D102:D110) -> 66369.92 | E111: =SUM(E102:E110) -> 66369.92
A113: =Summary!$G$9 -> Contractor
C117: =Summary!$G$10 -> Construction Manager
D121: Approved CO Value ($) | E121: CO To Date ($)
D122: 80000 | E122: =E111 -> 66369.92
E123: Complete

Sheet CO044
A1: =Summary!$G$11 -> PIPELINE PROJECT
A13: EXTRA WORK SUMMARY
A14: CO# | B14: CO044
D16: Billing Date: | E16: 42460
A17: Item | B17: Daylighting CNRL Pipelines At KP 24+804
A19: Date | B19: Description | C19: This Period | D19: Previous | E19: Total To Date
A20: 42460 | B20: Daylighting CNRL Pipelines At KP 24+804 | C20: 94936.83 | E20: =C20+D20 -> 94936.83
B21: Tickets: 2010062, 0634, 0635, 0636, 0637, 0638
B29: Total | C29: =SUM(C20:C28) -> 94936.83 | D29: =SUM(D20:D28) -> 0 | E29: =SUM(E20:E28) -> 94936.83
A31: =Summary!$G$9 -> Contractor
C35: =Summary!$G$10 -> Construction Manager
D39: Approved CO Value ($) | E39: CO To Date ($)
D40: 122491.4 | E40: =E29 -> 94936.83
A42: =Summary!$G$11 -> PIPELINE PROJECT
A54: EXTRA WORK SUMMARY
A55: CO# | B55: CO044
D57: Billing Date: | E57: 42475
A58: Item | B58: Daylighting CNRL Pipelines At KP 24+804
A60: Date | B60: Description | C60: This Period | D60: Previous | E60: Total To Date
A61: 42460 | B61: Daylighting CNRL Pipelines At KP 24+804 | D61: 94936.83 | E61: =C61+D61 -> 94936.83
B62: Tickets: 2010062, 0634, 0635, 0636, 0637, 0638
A63: 42475 | B63: Daylighting CNRL Pipelines At KP 24+804 | C63: 6215.08 | E63: =C63+D63 -> 6215.08
B64: Tickets: 0768, 0220, 0219
B70: Total | C70: =SUM(C61:C69) -> 6215.08 | D70: =SUM(D61:D69) -> 94936.83 | E70: =SUM(E61:E69) -> 101151.91
A72: =Summary!$G$9 -> Contractor
C76: =Summary!$G$10 -> Construction Manager
D80: Approved CO Value ($) | E80: CO To Date ($)
D81: 122491.4 | E81: =E70 -> 101151.91
A83: =Summary!$G$11 -> PIPELINE PROJECT
A95: EXTRA WORK SUMMARY
A96: CO# | B96: CO044
D98: Billing Date: | E98: =Summary!$G$3 -> 42505
A99: Item | B99: Daylighting CNRL Pipelines At KP 24+804
A101: Date | B101: Description | C101: This Period | D101: Previous | E101: Total To Date
A102: 42460 | B102: Daylighting CNRL Pipelines At KP 24+804 | D102: 94936.83 | E102: =C102+D102 -> 94936.83
B103: Tickets: 2010062, 0634, 0635, 0636, 0637, 0638
A104: 42475 | B104: Daylighting CNRL Pipelines At KP 24+804 | D104: 6215.08 | E104: =C104+D104 -> 6215.08
B105: Tickets: 0768, 0220, 0219
B111: Total | C111: =SUM(C102:C110) -> 0 | D111: =SUM(D102:D110) -> 101151.91 | E111: =SUM(E102:E110) -> 101151.91
A113: =Summary!$G$9 -> Contractor
C117: =Summary!$G$10 -> Construction Manager
D121: Approved CO Value ($) | E121: CO To Date ($)
D122: 122491.4 | E122: =E111 -> 101151.91
E123: Complete

Sheet CO045
A1: =Summary!$G$11 -> PIPELINE PROJECT
A13: EXTRA WORK SUMMARY
A14: CO# | B14: CO045
D16: Billing Date: | E16: 42460
A17: Item | B17: Hydrovac Support Additional To C023
A19: Date | B19: Description | C19: This Period | D19: Previous | E19: Total To Date
A20: 42460 | B20: Hydrovac Support Additional To C023 | C20: 23420.68 | E20: =C20+D20 -> 23420.68
B21: Tickets: 0807, 0808, 1242, 0809, 0810, 0772, 0771
B29: Total | C29: =SUM(C20:C28) -> 23420.68 | D29: =SUM(D20:D28) -> 0 | E29: =SUM(E20:E28) -> 23420.68
A31: =Summary!$G$9 -> Contractor
C35: =Summary!$G$10 -> Construction Manager
D39: Approved CO Value ($) | E39: CO To Date ($)
D40: 54750.6 | E40: =E29 -> 23420.68
A42: =Summary!$G$11 -> PIPELINE PROJECT
A54: EXTRA WORK SUMMARY
A55: CO# | B55: CO045
D57: Billing Date: | E57: 42475
A58: Item | B58: Hydrovac Support Additional To C023
A60: Date | B60: Description | C60: This Period | D60: Previous | E60: Total To Date
A61: 42460 | B61: Hydrovac Support Additional To C023 | D61: 23420.68 | E61: =C61+D61 -> 23420.68
B62: Tickets: 0807, 0808, 1242, 0809, 0810, 0772, 0771
A63: 42475 | B63: Hydrovac Support Additional To C023 | C63: 8670.08 | E63: =C63+D63 -> 8670.08
B64: Tickets: 0770, 0769
B70: Total | C70: =SUM(C61:C69) -> 8670.08 | D70: =SUM(D61:D69) -> 23420.68 | E70: =SUM(E61:E69) -> 32090.76
A72: =Summary!$G$9 -> Contractor
C76: =Summary!$G$10 -> Construction Manager
D80: Approved CO Value ($) | E80: CO To Date ($)
D81: 54750.6 | E81: =E70 -> 32090.76
A83: =Summary!$G$11 -> PIPELINE PROJECT
A95: EXTRA WORK SUMMARY
A96: CO# | B96: CO045
D98: Billing Date: | E98: =Summary!$G$3 -> 42505
A99: Item | B99: Hydrovac Support Additional To C023
A101: Date | B101: Description | C101: This Period | D101: Previous | E101: Total To Date
A102: 42460 | B102: Hydrovac Support Additional To C023 | D102: 23420.68 | E102: =C102+D102 -> 23420.68
B103: Tickets: 0807, 0808, 1242, 0809, 0810, 0772, 0771
A104: 42475 | B104: Hydrovac Support Additional To C023 | D104: 8670.08 | E104: =C104+D104 -> 8670.08
B105: Tickets: 0770, 0769
B111: Total | C111: =SUM(C102:C110) -> 0 | D111: =SUM(D102:D110) -> 32090.76 | E111: =SUM(E102:E110) -> 32090.76
A113: =Summary!$G$9 -> Contractor
C117: =Summary!$G$10 -> Construction Manager
D121: Approved CO Value ($) | E121: CO To Date ($)
D122: 54750.6 | E122: =E111 -> 32090.76

Sheet CO046UPI
A1: =Summary!$G$11 -> PIPELINE PROJECT
A13: UNIT PRICE SUMMARY
A14: CO# | B14: CO046
E16: Billing Date: | F16: 42475
A17: Item | B17: UPI SUMMARY
A19: Date | B19: UPI | C19: Description | D19: This Period | E19: Previous | F19: Total To Date
A21: 42475 | B21: 2.2 b) | C21: Rockshield | D21: 39456.96 | F21: =D21+E21 -> 39456.96
B22: 2.3 d) | C22: Sand Hauling From Borrow Pits | D22: 101168.76 | F22: =D22+E22 -> 101168.76
B23: 2.11 | C23: Clean Washed Gravel | D23: 8876.4 | F23: =D23+E23 -> 8876.4
B24: 2.29 | C24: Rig Mats | D24: 5737.5 | F24: =D24+E24 -> 5737.5
F25: =D25+E25 -> 0
F26: =D26+E26 -> 0
F27: =D27+E27 -> 0
F28: =D28+E28 -> 0
F29: =D29+E29 -> 0
F30: =D30+E30 -> 0
F31: =D31+E31 -> 0
F32: =D32+E32 -> 0
F33: =D33+E33 -> 0
F34: =D34+E34 -> 0
C35: Total | D35: =SUM(D20:D34) -> 155239.62 | E35: =SUM(E20:E34) -> 0 | F35: =SUM(F20:F34) -> 155239.62
A37: =Summary!$G$9 -> Contractor

Sheet CO047
A1: =Summary!$G$11 -> PIPELINE PROJECT
A13: EXTRA WORK SUMMARY
A14: CO# | B14: CO047
D16: Billing Date: | E16: 42475
A17: Item | B17: Light Towers For HDD Sumps
A19: Date | B19: Description | C19: This Period | D19: Previous | E19: Total To Date
A20: 42475 | B20: Light Towers For HDD Sumps | C20: 62260 | E20: =C20+D20 -> 62260
B29: Total | C29: =SUM(C20:C28) -> 62260 | D29: =SUM(D20:D28) -> 0 | E29: =SUM(E20:E28) -> 62260
A31: =Summary!$G$9 -> Contractor
C35: =Summary!$G$10 -> Construction Manager
D39: Approved CO Value ($) | E39: CO To Date ($)
D40: 62260 | E40: =E29 -> 62260
A42: =Summary!$G$11 -> PIPELINE PROJECT
A54: EXTRA WORK SUMMARY
A55: CO# | B55: CO047
D57: Billing Date: | E57: =Summary!$G$3 -> 42505
A58: Item | B58: Light Towers For HDD Sumps
A60: Date | B60: Description | C60: This Period | D60: Previous | E60: Total To Date
A61: 42475 | B61: Light Towers For HDD Sumps | D61: 62260 | E61: =C61+D61 -> 62260
B70: Total | C70: =SUM(C61:C69) -> 0 | D70: =SUM(D61:D69) -> 62260 | E70: =SUM(E61:E69) -> 62260
A72: =Summary!$G$9 -> Contractor
C76: =Summary!$G$10 -> Construction Manager
D80: Approved CO Value ($) | E80: CO To Date ($)
D81: 62260 | E81: =E70 -> 62260
E82: Complete

Sheet CO048
A1: =Summary!$G$11 -> PIPELINE PROJECT
A13: EXTRA WORK SUMMARY
A14: CO# | B14: CO-048
D16: Billing Date: | E16: 42475
A17: Item | B17: Drilling Support- Extended Schedule At River Additional To C020
A19: Date | B19: Description | C19: This Period | D19: Previous | E19: Total To Date
A20: 42475 | B20: Drilling Support At River | C20: 169946.08 | E20: =C20+D20 -> 169946.08
B29: Total | C29: =SUM(C20:C28) -> 169946.08 | D29: =SUM(D20:D28) -> 0 | E29: =SUM(E20:E28) -> 169946.08
A31: =Summary!$G$9 -> Contractor
C35: =Summary!$G$10 -> Construction Manager
D39: Approved CO Value ($) | E39: CO To Date ($)
D40: 169946.08 | E40: =E29 -> 169946.08
A42: =Summary!$G$11 -> PIPELINE PROJECT
A54: EXTRA WORK SUMMARY
A55: CO# | B55: CO048
D57: Billing Date: | E57: =Summary!$G$3 -> 42505
A58: Item | B58: Drilling Support- Extended Schedule AtRiver Additional To C020
A60: Date | B60: Description | C60: This Period | D60: Previous | E60: Total To Date
A61: 42475 | B61: Drilling Support At River | D61: 169946.08 | E61: =C61+D61 -> 169946.08
B70: Total | C70: =SUM(C61:C69) -> 0 | D70: =SUM(D61:D69) -> 169946.08 | E70: =SUM(E61:E69) -> 169946.08
A72: =Summary!$G$9 -> Contractor
C76: =Summary!$G$10 -> Construction Manager
D80: Approved CO Value ($) | E80: CO To Date ($)
D81: 169946.08 | E81: =E70 -> 169946.08
E82: Complete

Sheet CO049UPIs
A1: =Summary!$G$11 -> PIPELINE PROJECT
A13: UNIT PRICE SUMMARY
A14: CO# | B14: CO049
E16: Billing Date: | F16: 42490
A17: Item | B17: UPI SUMMARY
A19: Date | B19: UPI | C19: Description | D19: This Period | E19: Previous | F19: Total To Date
A21: 42490 | B21: 2.3 c), d) | C21: Sand Bedding, Padding and Hauling | D21: 75833.96 | F21: =D21+E21 -> 75833.96
B22: 2.14 | C22: Extra Depth Ditch | D22: 284.346 | F22: =D22+E22 -> 284.346
B23: 2.29 | C23: Rig Mats | D23: 1530 | F23: =D23+E23 -> 1530
B24: 2.31 | C24: Move Arounds | D24: 18000 | F24: =D24+E24 -> 18000
F25: =D25+E25 -> 0
F26: =D26+E26 -> 0
F27: =D27+E27 -> 0
F28: =D28+E28 -> 0
F29: =D29+E29 -> 0
F30: =D30+E30 -> 0
F31: =D31+E31 -> 0
F32: =D32+E32 -> 0
F33: =D33+E33 -> 0
F34: =D34+E34 -> 0
C35: Total | D35: =SUM(D20:D34) -> 95648.306 | E35: =SUM(E20:E34) -> 0 | F35: =SUM(F20:F34) -> 95648.306
A37: =Summary!$G$9 -> Contractor

Sheet CO050
A1: =Summary!$G$11 -> PIPELINE PROJECT
A13: EXTRA WORK SUMMARY
A14: CO# | B14: CO050
D16: Billing Date: | E16: 42490
A17: Item | B17: Consultant For Long Run Crossing Additional To C019
A19: Date | B19: Description | C19: This Period | D19: Previous | E19: Total To Date
A21: 42490 | B21: Avid Resource Management Ltd. Feb 15-19 | C21: 5040 | E21: =C21+D21 -> 5040
B22: Invoices 1371, 1372, 1373, 1374
B29: Total | C29: =SUM(C20:C28) -> 5040 | D29: =SUM(D20:D28) -> 0 | E29: =SUM(E20:E28) -> 5040
A31: =Summary!$G$9 -> Contractor
C35: =Summary!$G$10 -> Construction Manager
D39: Approved CO Value ($) | E39: CO To Date ($)
D40: 5040 | E40: =E29 -> 5040
A42: =Summary!$G$11 -> PIPELINE PROJECT
A54: EXTRA WORK SUMMARY
A55: CO# | B55: CO050
D57: Billing Date: | E57: =Summary!$G$3 -> 42505
A58: Item | B58: Consultant For Long Run Crossing Additional To C019
