Workbook

Sheet Field Log (50)
J1: Date:
G6: Field Log ID: | J6: Status:
A7: Address: | G7: Account #: | J7: Account:
G8: Foreman:
A10: Employee ID | B10: Labor Type | C10: Employee | D10: RT Hours | E10: RT Rate | F10: OT Hours | G10: OT Rate | H10: DT Hours | I10: DT Rate | J10: Sub. | K10: Total | M10: Additional Hours
B11: =VLOOKUP($C$11:$C$24,Personnel!$A$1:$B$1234,2,FALSE) -> 0 | E11: =VLOOKUP($B$11:$B$24,'Constr. Wage Rate Calculations'!$A$19:$Z$288,22,FALSE) -> 0 | G11: =VLOOKUP($B$11:$B$24,'Constr. Wage Rate Calculations'!$A$19:$Z$288,23,FALSE) -> 0 | I11: =VLOOKUP($B$11:$B$24,'Constr. Wage Rate Calculations'!$A$19:$Z$288,24,FALSE) -> 0 | J11: =VLOOKUP($B$11:$B$25,'Constr. Wage Rate Calculations'!$A$19:$Z$288,25,FALSE) -> 0 | K11: =IF($D11>=1,$J11+(D11*E11)+(F11*G11)+(H11*I11),IF($F11>=1,$J11+(D11*E11)+(F11*G11)+(H11*I11),IF($H11>=1,$J11+(D11*E11)+(F11*G11)+(H11*I11),"")))
B12: =VLOOKUP($C$11:$C$24,Personnel!$A$1:$B$1234,2,FALSE) -> 0 | E12: =VLOOKUP($B$11:$B$24,'Constr. Wage Rate Calculations'!$A$19:$Z$288,22,FALSE) -> 0 | G12: =VLOOKUP($B$11:$B$24,'Constr. Wage Rate Calculations'!$A$19:$Z$288,23,FALSE) -> 0 | I12: =VLOOKUP($B$11:$B$24,'Constr. Wage Rate Calculations'!$A$19:$Z$288,24,FALSE) -> 0 | J12: =VLOOKUP($B$11:$B$25,'Constr. Wage Rate Calculations'!$A$19:$Z$288,25,FALSE) -> 0 | K12: =IF($D12>=1,$J12+(D12*E12)+(F12*G12)+(H12*I12),IF($F12>=1,$J12+(D12*E12)+(F12*G12)+(H12*I12),IF($H12>=1,$J12+(D12*E12)+(F12*G12)+(H12*I12),"")))
B13: =VLOOKUP($C$11:$C$24,Personnel!$A$1:$B$1234,2,FALSE) -> 0 | E13: =VLOOKUP($B$11:$B$24,'Constr. Wage Rate Calculations'!$A$19:$Z$288,22,FALSE) -> 0 | G13: =VLOOKUP($B$11:$B$24,'Constr. Wage Rate Calculations'!$A$19:$Z$288,23,FALSE) -> 0 | I13: =VLOOKUP($B$11:$B$24,'Constr. Wage Rate Calculations'!$A$19:$Z$288,24,FALSE) -> 0 | J13: =VLOOKUP($B$11:$B$25,'Constr. Wage Rate Calculations'!$A$19:$Z$288,25,FALSE) -> 0 | K13: =IF($D13>=1,$J13+(D13*E13)+(F13*G13)+(H13*I13),IF($F13>=1,$J13+(D13*E13)+(F13*G13)+(H13*I13),IF($H13>=1,$J13+(D13*E13)+(F13*G13)+(H13*I13),"")))
B14: =VLOOKUP($C$11:$C$24,Personnel!$A$1:$B$1234,2,FALSE) -> 0 | E14: =VLOOKUP($B$11:$B$24,'Constr. Wage Rate Calculations'!$A$19:$Z$288,22,FALSE) -> 0 | G14: =VLOOKUP($B$11:$B$24,'Constr. Wage Rate Calculations'!$A$19:$Z$288,23,FALSE) -> 0 | I14: =VLOOKUP($B$11:$B$24,'Constr. Wage Rate Calculations'!$A$19:$Z$288,24,FALSE) -> 0 | J14: =VLOOKUP($B$11:$B$25,'Constr. Wage Rate Calculations'!$A$19:$Z$288,25,FALSE) -> 0 | K14: =IF($D14>=1,$J14+(D14*E14)+(F14*G14)+(H14*I14),IF($F14>=1,$J14+(D14*E14)+(F14*G14)+(H14*I14),IF($H14>=1,$J14+(D14*E14)+(F14*G14)+(H14*I14),"")))
B15: =VLOOKUP($C$11:$C$24,Personnel!$A$1:$B$1234,2,FALSE) -> 0 | E15: =VLOOKUP($B$11:$B$24,'Constr. Wage Rate Calculations'!$A$19:$Z$288,22,FALSE) -> 0 | G15: =VLOOKUP($B$11:$B$24,'Constr. Wage Rate Calculations'!$A$19:$Z$288,23,FALSE) -> 0 | I15: =VLOOKUP($B$11:$B$24,'Constr. Wage Rate Calculations'!$A$19:$Z$288,24,FALSE) -> 0 | J15: =VLOOKUP($B$11:$B$25,'Constr. Wage Rate Calculations'!$A$19:$Z$288,25,FALSE) -> 0 | K15: =IF($D15>=1,$J15+(D15*E15)+(F15*G15)+(H15*I15),IF($F15>=1,$J15+(D15*E15)+(F15*G15)+(H15*I15),IF($H15>=1,$J15+(D15*E15)+(F15*G15)+(H15*I15),"")))
B16: =VLOOKUP($C$11:$C$24,Personnel!$A$1:$B$1234,2,FALSE) -> 0 | E16: =VLOOKUP($B$11:$B$24,'Constr. Wage Rate Calculations'!$A$19:$Z$288,22,FALSE) -> 0 | G16: =VLOOKUP($B$11:$B$24,'Constr. Wage Rate Calculations'!$A$19:$Z$288,23,FALSE) -> 0 | I16: =VLOOKUP($B$11:$B$24,'Constr. Wage Rate Calculations'!$A$19:$Z$288,24,FALSE) -> 0 | J16: =VLOOKUP($B$11:$B$25,'Constr. Wage Rate Calculations'!$A$19:$Z$288,25,FALSE) -> 0 | K16: =IF($D16>=1,$J16+(D16*E16)+(F16*G16)+(H16*I16),IF($F16>=1,$J16+(D16*E16)+(F16*G16)+(H16*I16),IF($H16>=1,$J16+(D16*E16)+(F16*G16)+(H16*I16),"")))
B17: =VLOOKUP($C$11:$C$24,Personnel!$A$1:$B$1234,2,FALSE) -> 0 | E17: =VLOOKUP($B$11:$B$24,'Constr. Wage Rate Calculations'!$A$19:$Z$288,22,FALSE) -> 0 | G17: =VLOOKUP($B$11:$B$24,'Constr. Wage Rate Calculations'!$A$19:$Z$288,23,FALSE) -> 0 | I17: =VLOOKUP($B$11:$B$24,'Constr. Wage Rate Calculations'!$A$19:$Z$288,24,FALSE) -> 0 | J17: =VLOOKUP($B$11:$B$25,'Constr. Wage Rate Calculations'!$A$19:$Z$288,25,FALSE) -> 0 | K17: =IF($D17>=1,$J17+(D17*E17)+(F17*G17)+(H17*I17),IF($F17>=1,$J17+(D17*E17)+(F17*G17)+(H17*I17),IF($H17>=1,$J17+(D17*E17)+(F17*G17)+(H17*I17),"")))
B18: =VLOOKUP($C$11:$C$24,Personnel!$A$1:$B$1234,2,FALSE) -> 0 | E18: =VLOOKUP($B$11:$B$24,'Constr. Wage Rate Calculations'!$A$19:$Z$288,22,FALSE) -> 0 | G18: =VLOOKUP($B$11:$B$24,'Constr. Wage Rate Calculations'!$A$19:$Z$288,23,FALSE) -> 0 | I18: =VLOOKUP($B$11:$B$24,'Constr. Wage Rate Calculations'!$A$19:$Z$288,24,FALSE) -> 0 | J18: =VLOOKUP($B$11:$B$25,'Constr. Wage Rate Calculations'!$A$19:$Z$288,25,FALSE) -> 0 | K18: =IF($D18>=1,$J18+(D18*E18)+(F18*G18)+(H18*I18),IF($F18>=1,$J18+(D18*E18)+(F18*G18)+(H18*I18),IF($H18>=1,$J18+(D18*E18)+(F18*G18)+(H18*I18),"")))
B19: =VLOOKUP($C$11:$C$24,Personnel!$A$1:$B$1234,2,FALSE) -> 0 | E19: =VLOOKUP($B$11:$B$24,'Constr. Wage Rate Calculations'!$A$19:$Z$288,22,FALSE) -> 0 | G19: =VLOOKUP($B$11:$B$24,'Constr. Wage Rate Calculations'!$A$19:$Z$288,23,FALSE) -> 0 | I19: =VLOOKUP($B$11:$B$24,'Constr. Wage Rate Calculations'!$A$19:$Z$288,24,FALSE) -> 0 | J19: =VLOOKUP($B$11:$B$25,'Constr. Wage Rate Calculations'!$A$19:$Z$288,25,FALSE) -> 0 | K19: =IF($D19>=1,$J19+(D19*E19)+(F19*G19)+(H19*I19),IF($F19>=1,$J19+(D19*E19)+(F19*G19)+(H19*I19),IF($H19>=1,$J19+(D19*E19)+(F19*G19)+(H19*I19),"")))
B20: =VLOOKUP($C$11:$C$24,Personnel!$A$1:$B$1234,2,FALSE) -> 0 | E20: =VLOOKUP($B$11:$B$24,'Constr. Wage Rate Calculations'!$A$19:$Z$288,22,FALSE) -> 0 | G20: =VLOOKUP($B$11:$B$24,'Constr. Wage Rate Calculations'!$A$19:$Z$288,23,FALSE) -> 0 | I20: =VLOOKUP($B$11:$B$24,'Constr. Wage Rate Calculations'!$A$19:$Z$288,24,FALSE) -> 0 | J20: =VLOOKUP($B$11:$B$25,'Constr. Wage Rate Calculations'!$A$19:$Z$288,25,FALSE) -> 0 | K20: =IF($D20>=1,$J20+(D20*E20)+(F20*G20)+(H20*I20),IF($F20>=1,$J20+(D20*E20)+(F20*G20)+(H20*I20),IF($H20>=1,$J20+(D20*E20)+(F20*G20)+(H20*I20),"")))
B21: =VLOOKUP($C$11:$C$24,Personnel!$A$1:$B$1234,2,FALSE) -> 0 | E21: =VLOOKUP($B$11:$B$24,'Constr. Wage Rate Calculations'!$A$19:$Z$288,22,FALSE) -> 0 | G21: =VLOOKUP($B$11:$B$24,'Constr. Wage Rate Calculations'!$A$19:$Z$288,23,FALSE) -> 0 | I21: =VLOOKUP($B$11:$B$24,'Constr. Wage Rate Calculations'!$A$19:$Z$288,24,FALSE) -> 0 | J21: =VLOOKUP($B$11:$B$25,'Constr. Wage Rate Calculations'!$A$19:$Z$288,25,FALSE) -> 0 | K21: =IF($D21>=1,$J21+(D21*E21)+(F21*G21)+(H21*I21),IF($F21>=1,$J21+(D21*E21)+(F21*G21)+(H21*I21),IF($H21>=1,$J21+(D21*E21)+(F21*G21)+(H21*I21),"")))
B22: =VLOOKUP($C$11:$C$24,Personnel!$A$1:$B$1234,2,FALSE) -> 0 | E22: =VLOOKUP($B$11:$B$24,'Constr. Wage Rate Calculations'!$A$19:$Z$288,22,FALSE) -> 0 | G22: =VLOOKUP($B$11:$B$24,'Constr. Wage Rate Calculations'!$A$19:$Z$288,23,FALSE) -> 0 | I22: =VLOOKUP($B$11:$B$24,'Constr. Wage Rate Calculations'!$A$19:$Z$288,24,FALSE) -> 0 | J22: =VLOOKUP($B$11:$B$25,'Constr. Wage Rate Calculations'!$A$19:$Z$288,25,FALSE) -> 0 | K22: =IF($D22>=1,$J22+(D22*E22)+(F22*G22)+(H22*I22),IF($F22>=1,$J22+(D22*E22)+(F22*G22)+(H22*I22),IF($H22>=1,$J22+(D22*E22)+(F22*G22)+(H22*I22),"")))
B23: =VLOOKUP($C$11:$C$24,Personnel!$A$1:$B$1234,2,FALSE) -> 0 | E23: =VLOOKUP($B$11:$B$24,'Constr. Wage Rate Calculations'!$A$19:$Z$288,22,FALSE) -> 0 | G23: =VLOOKUP($B$11:$B$24,'Constr. Wage Rate Calculations'!$A$19:$Z$288,23,FALSE) -> 0 | I23: =VLOOKUP($B$11:$B$24,'Constr. Wage Rate Calculations'!$A$19:$Z$288,24,FALSE) -> 0 | J23: =VLOOKUP($B$11:$B$25,'Constr. Wage Rate Calculations'!$A$19:$Z$288,25,FALSE) -> 0 | K23: =IF($D23>=1,$J23+(D23*E23)+(F23*G23)+(H23*I23),IF($F23>=1,$J23+(D23*E23)+(F23*G23)+(H23*I23),IF($H23>=1,$J23+(D23*E23)+(F23*G23)+(H23*I23),"")))
B24: =VLOOKUP($C$11:$C$24,Personnel!$A$1:$B$1234,2,FALSE) -> 0 | E24: =VLOOKUP($B$11:$B$24,'Constr. Wage Rate Calculations'!$A$19:$Z$288,22,FALSE) -> 0 | G24: =VLOOKUP($B$11:$B$24,'Constr. Wage Rate Calculations'!$A$19:$Z$288,23,FALSE) -> 0 | I24: =VLOOKUP($B$11:$B$24,'Constr. Wage Rate Calculations'!$A$19:$Z$288,24,FALSE) -> 0 | J24: =VLOOKUP($B$11:$B$25,'Constr. Wage Rate Calculations'!$A$19:$Z$288,25,FALSE) -> 0 | K24: =IF($D24>=1,$J24+(D24*E24)+(F24*G24)+(H24*I24),IF($F24>=1,$J24+(D24*E24)+(F24*G24)+(H24*I24),IF($H24>=1,$J24+(D24*E24)+(F24*G24)+(H24*I24),""))) | M24: =SUM(M11:M23) -> 0
I25: TOTAL LABOUR | K25: =SUM(K11:K24) -> 0 | M25: =SUMIFS(D11:D24,D11:D24,"<3",D11:D24,"<5") -> 0 | N25: =SUMIFS(D11:D24,D11:D24,">3",D11:D24,">5") -> 0 | O25: =SUM(F11:F24,H11:H24,M25,N25)-M24 -> 0
A27: Equipment ID | B27: Equipment | H27: Days | I27: Hrs. | J27: Rate | K27: Total
B28: =VLOOKUP($C$28:$C$49,Equipment!$A$1:$B$2322,2,FALSE) -> 0 | J28: =VLOOKUP($B$28:$B$49,'Alberta Equip. Rates Year 3'!$B$13:$K$314,10,FALSE) -> 0 | K28: =(H28+I28)*J28 -> 0
B29: =VLOOKUP($C$28:$C$49,Equipment!$A$1:$B$2322,2,FALSE) -> 0 | J29: =VLOOKUP($B$28:$B$49,'Alberta Equip. Rates Year 3'!$B$13:$K$314,10,FALSE) -> 0 | K29: =(H29+I29)*J29 -> 0
B30: =VLOOKUP($C$28:$C$49,Equipment!$A$1:$B$2322,2,FALSE) -> 0 | J30: =VLOOKUP($B$28:$B$49,'Alberta Equip. Rates Year 3'!$B$13:$K$314,10,FALSE) -> 0 | K30: =(H30+I30)*J30 -> 0
B31: =VLOOKUP($C$28:$C$49,Equipment!$A$1:$B$2322,2,FALSE) -> 0 | J31: =VLOOKUP($B$28:$B$49,'Alberta Equip. Rates Year 3'!$B$13:$K$314,10,FALSE) -> 0 | K31: =(H31+I31)*J31 -> 0
B32: =VLOOKUP($C$28:$C$49,Equipment!$A$1:$B$2322,2,FALSE) -> 0 | J32: =VLOOKUP($B$28:$B$49,'Alberta Equip. Rates Year 3'!$B$13:$K$314,10,FALSE) -> 0 | K32: =(H32+I32)*J32 -> 0
B33: =VLOOKUP($C$28:$C$49,Equipment!$A$1:$B$2322,2,FALSE) -> 0 | J33: =VLOOKUP($B$28:$B$49,'Alberta Equip. Rates Year 3'!$B$13:$K$314,10,FALSE) -> 0 | K33: =(H33+I33)*J33 -> 0
B34: =VLOOKUP($C$28:$C$49,Equipment!$A$1:$B$2322,2,FALSE) -> 0 | J34: =VLOOKUP($B$28:$B$49,'Alberta Equip. Rates Year 3'!$B$13:$K$314,10,FALSE) -> 0 | K34: =(H34+I34)*J34 -> 0
B35: =VLOOKUP($C$28:$C$49,Equipment!$A$1:$B$2322,2,FALSE) -> 0 | J35: =VLOOKUP($B$28:$B$49,'Alberta Equip. Rates Year 3'!$B$13:$K$314,10,FALSE) -> 0 | K35: =(H35+I35)*J35 -> 0
B36: =VLOOKUP($C$28:$C$49,Equipment!$A$1:$B$2322,2,FALSE) -> 0 | J36: =VLOOKUP($B$28:$B$49,'Alberta Equip. Rates Year 3'!$B$13:$K$314,10,FALSE) -> 0 | K36: =(H36+I36)*J36 -> 0
B37: =VLOOKUP($C$28:$C$49,Equipment!$A$1:$B$2322,2,FALSE) -> 0 | J37: =VLOOKUP($B$28:$B$49,'Alberta Equip. Rates Year 3'!$B$13:$K$314,10,FALSE) -> 0 | K37: =(H37+I37)*J37 -> 0
B38: =VLOOKUP($C$28:$C$49,Equipment!$A$1:$B$2322,2,FALSE) -> 0 | J38: =VLOOKUP($B$28:$B$49,'Alberta Equip. Rates Year 3'!$B$13:$K$314,10,FALSE) -> 0 | K38: =(H38+I38)*J38 -> 0
B39: =VLOOKUP($C$28:$C$49,Equipment!$A$1:$B$2322,2,FALSE) -> 0 | J39: =VLOOKUP($B$28:$B$49,'Alberta Equip. Rates Year 3'!$B$13:$K$314,10,FALSE) -> 0 | K39: =(H39+I39)*J39 -> 0
... B49: =VLOOKUP($C$28:$C$49,Equipment!$A$1:$B$2322,2,FALSE) -> 0 | J49: =VLOOKUP($B$28:$B$49,'Alberta Equip. Rates Year 3'!$B$13:$K$314,10,FALSE) -> 0 | K49: =(H49+I49)*J49 -> 0
I50: TOTAL EQUIPMENT | K50: =SUM(K28:K49) -> 0
A52: Scope of Work: | I52: LABOUR | K52: =K25 -> 0
I53: EQUIPMENT | K53: =K50 -> 0
I54: SMALL TOOLS | K54: =(O25)*14.15 -> 0
I55: MATERIALS
I56: TRUCKING
I57: SUBCONTRACTORS
I58: FIELD LOG TOTAL* | K58: =SUM(K52:K57) -> 0
A60: Client: | H60: Company Representitive:
A62: * Field Log Total does no include markups
A63: 41218.479

Sheet Field Log (49)
J1: Date:
G6: Field Log ID: | J6: Status:
A7: Address: | G7: Account #: | J7: Account:
G8: Foreman:
A10: Employee ID | B10: Labor Type | C10: Employee | D10: RT Hours | E10: RT Rate | F10: OT Hours | G10: OT Rate | H10: DT Hours | I10: DT Rate | J10: Sub. | K10: Total | M10: Additional Hours
B11: =VLOOKUP($C$11:$C$24,Personnel!$A$1:$B$1234,2,FALSE) -> 0 | E11: =VLOOKUP($B$11:$B$24,'Constr. Wage Rate Calculations'!$A$19:$Z$288,22,FALSE) -> 0 | G11: =VLOOKUP($B$11:$B$24,'Constr. Wage Rate Calculations'!$A$19:$Z$288,23,FALSE) -> 0 | I11: =VLOOKUP($B$11:$B$24,'Constr. Wage Rate Calculations'!$A$19:$Z$288,24,FALSE) -> 0 | J11: =VLOOKUP($B$11:$B$25,'Constr. Wage Rate Calculations'!$A$19:$Z$288,25,FALSE) -> 0 | K11: =IF($D11>=1,$J11+(D11*E11)+(F11*G11)+(H11*I11),IF($F11>=1,$J11+(D11*E11)+(F11*G11)+(H11*I11),IF($H11>=1,$J11+(D11*E11)+(F11*G11)+(H11*I11),"")))
B12: =VLOOKUP($C$11:$C$24,Personnel!$A$1:$B$1234,2,FALSE) -> 0 | E12: =VLOOKUP($B$11:$B$24,'Constr. Wage Rate Calculations'!$A$19:$Z$288,22,FALSE) -> 0 | G12: =VLOOKUP($B$11:$B$24,'Constr. Wage Rate Calculations'!$A$19:$Z$288,23,FALSE) -> 0 | I12: =VLOOKUP($B$11:$B$24,'Constr. Wage Rate Calculations'!$A$19:$Z$288,24,FALSE) -> 0 | J12: =VLOOKUP($B$11:$B$25,'Constr. Wage Rate Calculations'!$A$19:$Z$288,25,FALSE) -> 0 | K12: =IF($D12>=1,$J12+(D12*E12)+(F12*G12)+(H12*I12),IF($F12>=1,$J12+(D12*E12)+(F12*G12)+(H12*I12),IF($H12>=1,$J12+(D12*E12)+(F12*G12)+(H12*I12),"")))
B13: =VLOOKUP($C$11:$C$24,Personnel!$A$1:$B$1234,2,FALSE) -> 0 | E13: =VLOOKUP($B$11:$B$24,'Constr. Wage Rate Calculations'!$A$19:$Z$288,22,FALSE) -> 0 | G13: =VLOOKUP($B$11:$B$24,'Constr. Wage Rate Calculations'!$A$19:$Z$288,23,FALSE) -> 0 | I13: =VLOOKUP($B$11:$B$24,'Constr. Wage Rate Calculations'!$A$19:$Z$288,24,FALSE) -> 0 | J13: =VLOOKUP($B$11:$B$25,'Constr. Wage Rate Calculations'!$A$19:$Z$288,25,FALSE) -> 0 | K13: =IF($D13>=1,$J13+(D13*E13)+(F13*G13)+(H13*I13),IF($F13>=1,$J13+(D13*E13)+(F13*G13)+(H13*I13),IF($H13>=1,$J13+(D13*E13)+(F13*G13)+(H13*I13),"")))
B14: =VLOOKUP($C$11:$C$24,Personnel!$A$1:$B$1234,2,FALSE) -> 0 | E14: =VLOOKUP($B$11:$B$24,'Constr. Wage Rate Calculations'!$A$19:$Z$288,22,FALSE) -> 0 | G14: =VLOOKUP($B$11:$B$24,'Constr. Wage Rate Calculations'!$A$19:$Z$288,23,FALSE) -> 0 | I14: =VLOOKUP($B$11:$B$24,'Constr. Wage Rate Calculations'!$A$19:$Z$288,24,FALSE) -> 0 | J14: =VLOOKUP($B$11:$B$25,'Constr. Wage Rate Calculations'!$A$19:$Z$288,25,FALSE) -> 0 | K14: =IF($D14>=1,$J14+(D14*E14)+(F14*G14)+(H14*I14),IF($F14>=1,$J14+(D14*E14)+(F14*G14)+(H14*I14),IF($H14>=1,$J14+(D14*E14)+(F14*G14)+(H14*I14),"")))
B15: =VLOOKUP($C$11:$C$24,Personnel!$A$1:$B$1234,2,FALSE) -> 0 | E15: =VLOOKUP($B$11:$B$24,'Constr. Wage Rate Calculations'!$A$19:$Z$288,22,FALSE) -> 0 | G15: =VLOOKUP($B$11:$B$24,'Constr. Wage Rate Calculations'!$A$19:$Z$288,23,FALSE) -> 0 | I15: =VLOOKUP($B$11:$B$24,'Constr. Wage Rate Calculations'!$A$19:$Z$288,24,FALSE) -> 0 | J15: =VLOOKUP($B$11:$B$25,'Constr. Wage Rate Calculations'!$A$19:$Z$288,25,FALSE) -> 0 | K15: =IF($D15>=1,$J15+(D15*E15)+(F15*G15)+(H15*I15),IF($F15>=1,$J15+(D15*E15)+(F15*G15)+(H15*I15),IF($H15>=1,$J15+(D15*E15)+(F15*G15)+(H15*I15),"")))
B16: =VLOOKUP($C$11:$C$24,Personnel!$A$1:$B$1234,2,FALSE) -> 0 | E16: =VLOOKUP($B$11:$B$24,'Constr. Wage Rate Calculations'!$A$19:$Z$288,22,FALSE) -> 0 | G16: =VLOOKUP($B$11:$B$24,'Constr. Wage Rate Calculations'!$A$19:$Z$288,23,FALSE) -> 0 | I16: =VLOOKUP($B$11:$B$24,'Constr. Wage Rate Calculations'!$A$19:$Z$288,24,FALSE) -> 0 | J16: =VLOOKUP($B$11:$B$25,'Constr. Wage Rate Calculations'!$A$19:$Z$288,25,FALSE) -> 0 | K16: =IF($D16>=1,$J16+(D16*E16)+(F16*G16)+(H16*I16),IF($F16>=1,$J16+(D16*E16)+(F16*G16)+(H16*I16),IF($H16>=1,$J16+(D16*E16)+(F16*G16)+(H16*I16),"")))
B17: =VLOOKUP($C$11:$C$24,Personnel!$A$1:$B$1234,2,FALSE) -> 0 | E17: =VLOOKUP($B$11:$B$24,'Constr. Wage Rate Calculations'!$A$19:$Z$288,22,FALSE) -> 0 | G17: =VLOOKUP($B$11:$B$24,'Constr. Wage Rate Calculations'!$A$19:$Z$288,23,FALSE) -> 0 | I17: =VLOOKUP($B$11:$B$24,'Constr. Wage Rate Calculations'!$A$19:$Z$288,24,FALSE) -> 0 | J17: =VLOOKUP($B$11:$B$25,'Constr. Wage Rate Calculations'!$A$19:$Z$288,25,FALSE) -> 0 | K17: =IF($D17>=1,$J17+(D17*E17)+(F17*G17)+(H17*I17),IF($F17>=1,$J17+(D17*E17)+(F17*G17)+(H17*I17),IF($H17>=1,$J17+(D17*E17)+(F17*G17)+(H17*I17),"")))
B18: =VLOOKUP($C$11:$C$24,Personnel!$A$1:$B$1234,2,FALSE) -> 0 | E18: =VLOOKUP($B$11:$B$24,'Constr. Wage Rate Calculations'!$A$19:$Z$288,22,FALSE) -> 0 | G18: =VLOOKUP($B$11:$B$24,'Constr. Wage Rate Calculations'!$A$19:$Z$288,23,FALSE) -> 0 | I18: =VLOOKUP($B$11:$B$24,'Constr. Wage Rate Calculations'!$A$19:$Z$288,24,FALSE) -> 0 | J18: =VLOOKUP($B$11:$B$25,'Constr. Wage Rate Calculations'!$A$19:$Z$288,25,FALSE) -> 0 | K18: =IF($D18>=1,$J18+(D18*E18)+(F18*G18)+(H18*I18),IF($F18>=1,$J18+(D18*E18)+(F18*G18)+(H18*I18),IF($H18>=1,$J18+(D18*E18)+(F18*G18)+(H18*I18),"")))
B19: =VLOOKUP($C$11:$C$24,Personnel!$A$1:$B$1234,2,FALSE) -> 0 | E19: =VLOOKUP($B$11:$B$24,'Constr. Wage Rate Calculations'!$A$19:$Z$288,22,FALSE) -> 0 | G19: =VLOOKUP($B$11:$B$24,'Constr. Wage Rate Calculations'!$A$19:$Z$288,23,FALSE) -> 0 | I19: =VLOOKUP($B$11:$B$24,'Constr. Wage Rate Calculations'!$A$19:$Z$288,24,FALSE) -> 0 | J19: =VLOOKUP($B$11:$B$25,'Constr. Wage Rate Calculations'!$A$19:$Z$288,25,FALSE) -> 0 | K19: =IF($D19>=1,$J19+(D19*E19)+(F19*G19)+(H19*I19),IF($F19>=1,$J19+(D19*E19)+(F19*G19)+(H19*I19),IF($H19>=1,$J19+(D19*E19)+(F19*G19)+(H19*I19),"")))
B20: =VLOOKUP($C$11:$C$24,Personnel!$A$1:$B$1234,2,FALSE) -> 0 | E20: =VLOOKUP($B$11:$B$24,'Constr. Wage Rate Calculations'!$A$19:$Z$288,22,FALSE) -> 0 | G20: =VLOOKUP($B$11:$B$24,'Constr. Wage Rate Calculations'!$A$19:$Z$288,23,FALSE) -> 0 | I20: =VLOOKUP($B$11:$B$24,'Constr. Wage Rate Calculations'!$A$19:$Z$288,24,FALSE) -> 0 | J20: =VLOOKUP($B$11:$B$25,'Constr. Wage Rate Calculations'!$A$19:$Z$288,25,FALSE) -> 0 | K20: =IF($D20>=1,$J20+(D20*E20)+(F20*G20)+(H20*I20),IF($F20>=1,$J20+(D20*E20)+(F20*G20)+(H20*I20),IF($H20>=1,$J20+(D20*E20)+(F20*G20)+(H20*I20),"")))
B21: =VLOOKUP($C$11:$C$24,Personnel!$A$1:$B$1234,2,FALSE) -> 0 | E21: =VLOOKUP($B$11:$B$24,'Constr. Wage Rate Calculations'!$A$19:$Z$288,22,FALSE) -> 0 | G21: =VLOOKUP($B$11:$B$24,'Constr. Wage Rate Calculations'!$A$19:$Z$288,23,FALSE) -> 0 | I21: =VLOOKUP($B$11:$B$24,'Constr. Wage Rate Calculations'!$A$19:$Z$288,24,FALSE) -> 0 | J21: =VLOOKUP($B$11:$B$25,'Constr. Wage Rate Calculations'!$A$19:$Z$288,25,FALSE) -> 0 | K21: =IF($D21>=1,$J21+(D21*E21)+(F21*G21)+(H21*I21),IF($F21>=1,$J21+(D21*E21)+(F21*G21)+(H21*I21),IF($H21>=1,$J21+(D21*E21)+(F21*G21)+(H21*I21),"")))
B22: =VLOOKUP($C$11:$C$24,Personnel!$A$1:$B$1234,2,FALSE) -> 0 | E22: =VLOOKUP($B$11:$B$24,'Constr. Wage Rate Calculations'!$A$19:$Z$288,22,FALSE) -> 0 | G22: =VLOOKUP($B$11:$B$24,'Constr. Wage Rate Calculations'!$A$19:$Z$288,23,FALSE) -> 0 | I22: =VLOOKUP($B$11:$B$24,'Constr. Wage Rate Calculations'!$A$19:$Z$288,24,FALSE) -> 0 | J22: =VLOOKUP($B$11:$B$25,'Constr. Wage Rate Calculations'!$A$19:$Z$288,25,FALSE) -> 0 | K22: =IF($D22>=1,$J22+(D22*E22)+(F22*G22)+(H22*I22),IF($F22>=1,$J22+(D22*E22)+(F22*G22)+(H22*I22),IF($H22>=1,$J22+(D22*E22)+(F22*G22)+(H22*I22),"")))
B23: =VLOOKUP($C$11:$C$24,Personnel!$A$1:$B$1234,2,FALSE) -> 0 | E23: =VLOOKUP($B$11:$B$24,'Constr. Wage Rate Calculations'!$A$19:$Z$288,22,FALSE) -> 0 | G23: =VLOOKUP($B$11:$B$24,'Constr. Wage Rate Calculations'!$A$19:$Z$288,23,FALSE) -> 0 | I23: =VLOOKUP($B$11:$B$24,'Constr. Wage Rate Calculations'!$A$19:$Z$288,24,FALSE) -> 0 | J23: =VLOOKUP($B$11:$B$25,'Constr. Wage Rate Calculations'!$A$19:$Z$288,25,FALSE) -> 0 | K23: =IF($D23>=1,$J23+(D23*E23)+(F23*G23)+(H23*I23),IF($F23>=1,$J23+(D23*E23)+(F23*G23)+(H23*I23),IF($H23>=1,$J23+(D23*E23)+(F23*G23)+(H23*I23),"")))
B24: =VLOOKUP($C$11:$C$24,Personnel!$A$1:$B$1234,2,FALSE) -> 0 | E24: =VLOOKUP($B$11:$B$24,'Constr. Wage Rate Calculations'!$A$19:$Z$288,22,FALSE) -> 0 | G24: =VLOOKUP($B$11:$B$24,'Constr. Wage Rate Calculations'!$A$19:$Z$288,23,FALSE) -> 0 | I24: =VLOOKUP($B$11:$B$24,'Constr. Wage Rate Calculations'!$A$19:$Z$288,24,FALSE) -> 0 | J24: =VLOOKUP($B$11:$B$25,'Constr. Wage Rate Calculations'!$A$19:$Z$288,25,FALSE) -> 0 | K24: =IF($D24>=1,$J24+(D24*E24)+(F24*G24)+(H24*I24),IF($F24>=1,$J24+(D24*E24)+(F24*G24)+(H24*I24),IF($H24>=1,$J24+(D24*E24)+(F24*G24)+(H24*I24),""))) | M24: =SUM(M11:M23) -> 0
I25: TOTAL LABOUR | K25: =SUM(K11:K24) -> 0 | M25: =SUMIFS(D11:D24,D11:D24,"<3",D11:D24,"<5") -> 0 | N25: =SUMIFS(D11:D24,D11:D24,">3",D11:D24,">5") -> 0 | O25: =SUM(F11:F24,H11:H24,M25,N25)-M24 -> 0
A27: Equipment ID | B27: Equipment | H27: Days | I27: Hrs. | J27: Rate | K27: Total
B28: =VLOOKUP($C$28:$C$49,Equipment!$A$1:$B$2322,2,FALSE) -> 0 | J28: =VLOOKUP($B$28:$B$49,'Alberta Equip. Rates Year 3'!$B$13:$K$314,10,FALSE) -> 0 | K28: =(H28+I28)*J28 -> 0
B29: =VLOOKUP($C$28:$C$49,Equipment!$A$1:$B$2322,2,FALSE) -> 0 | J29: =VLOOKUP($B$28:$B$49,'Alberta Equip. Rates Year 3'!$B$13:$K$314,10,FALSE) -> 0 | K29: =(H29+I29)*J29 -> 0
B30: =VLOOKUP($C$28:$C$49,Equipment!$A$1:$B$2322,2,FALSE) -> 0 | J30: =VLOOKUP($B$28:$B$49,'Alberta Equip. Rates Year 3'!$B$13:$K$314,10,FALSE) -> 0 | K30: =(H30+I30)*J30 -> 0
B31: =VLOOKUP($C$28:$C$49,Equipment!$A$1:$B$2322,2,FALSE) -> 0 | J31: =VLOOKUP($B$28:$B$49,'Alberta Equip. Rates Year 3'!$B$13:$K$314,10,FALSE) -> 0 | K31: =(H31+I31)*J31 -> 0
B32: =VLOOKUP($C$28:$C$49,Equipment!$A$1:$B$2322,2,FALSE) -> 0 | J32: =VLOOKUP($B$28:$B$49,'Alberta Equip. Rates Year 3'!$B$13:$K$314,10,FALSE) -> 0 | K32: =(H32+I32)*J32 -> 0
B33: =VLOOKUP($C$28:$C$49,Equipment!$A$1:$B$2322,2,FALSE) -> 0 | J33: =VLOOKUP($B$28:$B$49,'Alberta Equip. Rates Year 3'!$B$13:$K$314,10,FALSE) -> 0 | K33: =(H33+I33)*J33 -> 0
B34: =VLOOKUP($C$28:$C$49,Equipment!$A$1:$B$2322,2,FALSE) -> 0 | J34: =VLOOKUP($B$28:$B$49,'Alberta Equip. Rates Year 3'!$B$13:$K$314,10,FALSE) -> 0 | K34: =(H34+I34)*J34 -> 0
B35: =VLOOKUP($C$28:$C$49,Equipment!$A$1:$B$2322,2,FALSE) -> 0 | J35: =VLOOKUP($B$28:$B$49,'Alberta Equip. Rates Year 3'!$B$13:$K$314,10,FALSE) -> 0 | K35: =(H35+I35)*J35 -> 0
B36: =VLOOKUP($C$28:$C$49,Equipment!$A$1:$B$2322,2,FALSE) -> 0 | J36: =VLOOKUP($B$28:$B$49,'Alberta Equip. Rates Year 3'!$B$13:$K$314,10,FALSE) -> 0 | K36: =(H36+I36)*J36 -> 0
B37: =VLOOKUP($C$28:$C$49,Equipment!$A$1:$B$2322,2,FALSE) -> 0 | J37: =VLOOKUP($B$28:$B$49,'Alberta Equip. Rates Year 3'!$B$13:$K$314,10,FALSE) -> 0 | K37: =(H37+I37)*J37 -> 0
B38: =VLOOKUP($C$28:$C$49,Equipment!$A$1:$B$2322,2,FALSE) -> 0 | J38: =VLOOKUP($B$28:$B$49,'Alberta Equip. Rates Year 3'!$B$13:$K$314,10,FALSE) -> 0 | K38: =(H38+I38)*J38 -> 0
B39: =VLOOKUP($C$28:$C$49,Equipment!$A$1:$B$2322,2,FALSE) -> 0 | J39: =VLOOKUP($B$28:$B$49,'Alberta Equip. Rates Year 3'!$B$13:$K$314,10,FALSE) -> 0 | K39: =(H39+I39)*J39 -> 0
... B49: =VLOOKUP($C$28:$C$49,Equipment!$A$1:$B$2322,2,FALSE) -> 0 | J49: =VLOOKUP($B$28:$B$49,'Alberta Equip. Rates Year 3'!$B$13:$K$314,10,FALSE) -> 0 | K49: =(H49+I49)*J49 -> 0
I50: TOTAL EQUIPMENT | K50: =SUM(K28:K49) -> 0
A52: Scope of Work: | I52: LABOUR | K52: =K25 -> 0
I53: EQUIPMENT | K53: =K50 -> 0
I54: SMALL TOOLS | K54: =(O25)*14.15 -> 0
I55: MATERIALS
I56: TRUCKING
I57: SUBCONTRACTORS
I58: FIELD LOG TOTAL* | K58: =SUM(K52:K57) -> 0
A60: Client: | H60: Company Representitive:
A62: * Field Log Total does no include markups
A63: 41218.479

Sheet Field Log (48)
J1: Date:
G6: Field Log ID: | J6: Status:
A7: Address: | G7: Account #: | J7: Account:
G8: Foreman:
A10: Employee ID | B10: Labor Type | C10: Employee | D10: RT Hours | E10: RT Rate | F10: OT Hours | G10: OT Rate | H10: DT Hours | I10: DT Rate | J10: Sub. | K10: Total | M10: Additional Hours
B11: =VLOOKUP($C$11:$C$24,Personnel!$A$1:$B$1234,2,FALSE) -> 0 | E11: =VLOOKUP($B$11:$B$24,'Constr. Wage Rate Calculations'!$A$19:$Z$288,22,FALSE) -> 0 | G11: =VLOOKUP($B$11:$B$24,'Constr. Wage Rate Calculations'!$A$19:$Z$288,23,FALSE) -> 0 | I11: =VLOOKUP($B$11:$B$24,'Constr. Wage Rate Calculations'!$A$19:$Z$288,24,FALSE) -> 0 | J11: =VLOOKUP($B$11:$B$25,'Constr. Wage Rate Calculations'!$A$19:$Z$288,25,FALSE) -> 0 | K11: =IF($D11>=1,$J11+(D11*E11)+(F11*G11)+(H11*I11),IF($F11>=1,$J11+(D11*E11)+(F11*G11)+(H11*I11),IF($H11>=1,$J11+(D11*E11)+(F11*G11)+(H11*I11),"")))
B12: =VLOOKUP($C$11:$C$24,Personnel!$A$1:$B$1234,2,FALSE) -> 0 | E12: =VLOOKUP($B$11:$B$24,'Constr. Wage Rate Calculations'!$A$19:$Z$288,22,FALSE) -> 0 | G12: =VLOOKUP($B$11:$B$24,'Constr. Wage Rate Calculations'!$A$19:$Z$288,23,FALSE) -> 0 | I12: =VLOOKUP($B$11:$B$24,'Constr. Wage Rate Calculations'!$A$19:$Z$288,24,FALSE) -> 0 | J12: =VLOOKUP($B$11:$B$25,'Constr. Wage Rate Calculations'!$A$19:$Z$288,25,FALSE) -> 0 | K12: =IF($D12>=1,$J12+(D12*E12)+(F12*G12)+(H12*I12),IF($F12>=1,$J12+(D12*E12)+(F12*G12)+(H12*I12),IF($H12>=1,$J12+(D12*E12)+(F12*G12)+(H12*I12),"")))
B13: =VLOOKUP($C$11:$C$24,Personnel!$A$1:$B$1234,2,FALSE) -> 0 | E13: =VLOOKUP($B$11:$B$24,'Constr. Wage Rate Calculations'!$A$19:$Z$288,22,FALSE) -> 0 | G13: =VLOOKUP($B$11:$B$24,'Constr. Wage Rate Calculations'!$A$19:$Z$288,23,FALSE) -> 0 | I13: =VLOOKUP($B$11:$B$24,'Constr. Wage Rate Calculations'!$A$19:$Z$288,24,FALSE) -> 0 | J13: =VLOOKUP($B$11:$B$25,'Constr. Wage Rate Calculations'!$A$19:$Z$288,25,FALSE) -> 0 | K13: =IF($D13>=1,$J13+(D13*E13)+(F13*G13)+(H13*I13),IF($F13>=1,$J13+(D13*E13)+(F13*G13)+(H13*I13),IF($H13>=1,$J13+(D13*E13)+(F13*G13)+(H13*I13),"")))
B14: =VLOOKUP($C$11:$C$24,Personnel!$A$1:$B$1234,2,FALSE) -> 0 | E14: =VLOOKUP($B$11:$B$24,'Constr. Wage Rate Calculations'!$A$19:$Z$288,22,FALSE) -> 0 | G14: =VLOOKUP($B$11:$B$24,'Constr. Wage Rate Calculations'!$A$19:$Z$288,23,FALSE) -> 0 | I14: =VLOOKUP($B$11:$B$24,'Constr. Wage Rate Calculations'!$A$19:$Z$288,24,FALSE) -> 0 | J14: =VLOOKUP($B$11:$B$25,'Constr. Wage Rate Calculations'!$A$19:$Z$288,25,FALSE) -> 0 | K14: =IF($D14>=1,$J14+(D14*E14)+(F14*G14)+(H14*I14),IF($F14>=1,$J14+(D14*E14)+(F14*G14)+(H14*I14),IF($H14>=1,$J14+(D14*E14)+(F14*G14)+(H14*I14),"")))
B15: =VLOOKUP($C$11:$C$24,Personnel!$A$1:$B$1234,2,FALSE) -> 0 | E15: =VLOOKUP($B$11:$B$24,'Constr. Wage Rate Calculations'!$A$19:$Z$288,22,FALSE) -> 0 | G15: =VLOOKUP($B$11:$B$24,'Constr. Wage Rate Calculations'!$A$19:$Z$288,23,FALSE) -> 0 | I15: =VLOOKUP($B$11:$B$24,'Constr. Wage Rate Calculations'!$A$19:$Z$288,24,FALSE) -> 0 | J15: =VLOOKUP($B$11:$B$25,'Constr. Wage Rate Calculations'!$A$19:$Z$288,25,FALSE) -> 0 | K15: =IF($D15>=1,$J15+(D15*E15)+(F15*G15)+(H15*I15),IF($F15>=1,$J15+(D15*E15)+(F15*G15)+(H15*I15),IF($H15>=1,$J15+(D15*E15)+(F15*G15)+(H15*I15),"")))
B16: =VLOOKUP($C$11:$C$24,Personnel!$A$1:$B$1234,2,FALSE) -> 0 | E16: =VLOOKUP($B$11:$B$24,'Constr. Wage Rate Calculations'!$A$19:$Z$288,22,FALSE) -> 0 | G16: =VLOOKUP($B$11:$B$24,'Constr. Wage Rate Calculations'!$A$19:$Z$288,23,FALSE) -> 0 | I16: =VLOOKUP($B$11:$B$24,'Constr. Wage Rate Calculations'!$A$19:$Z$288,24,FALSE) -> 0 | J16: =VLOOKUP($B$11:$B$25,'Constr. Wage Rate Calculations'!$A$19:$Z$288,25,FALSE) -> 0 | K16: =IF($D16>=1,$J16+(D16*E16)+(F16*G16)+(H16*I16),IF($F16>=1,$J16+(D16*E16)+(F16*G16)+(H16*I16),IF($H16>=1,$J16+(D16*E16)+(F16*G16)+(H16*I16),"")))
B17: =VLOOKUP($C$11:$C$24,Personnel!$A$1:$B$1234,2,FALSE) -> 0 | E17: =VLOOKUP($B$11:$B$24,'Constr. Wage Rate Calculations'!$A$19:$Z$288,22,FALSE) -> 0 | G17: =VLOOKUP($B$11:$B$24,'Constr. Wage Rate Calculations'!$A$19:$Z$288,23,FALSE) -> 0 | I17: =VLOOKUP($B$11:$B$24,'Constr. Wage Rate Calculations'!$A$19:$Z$288,24,FALSE) -> 0 | J17: =VLOOKUP($B$11:$B$25,'Constr. Wage Rate Calculations'!$A$19:$Z$288,25,FALSE) -> 0 | K17: =IF($D17>=1,$J17+(D17*E17)+(F17*G17)+(H17*I17),IF($F17>=1,$J17+(D17*E17)+(F17*G17)+(H17*I17),IF($H17>=1,$J17+(D17*E17)+(F17*G17)+(H17*I17),"")))
B18: =VLOOKUP($C$11:$C$24,Personnel!$A$1:$B$1234,2,FALSE) -> 0 | E18: =VLOOKUP($B$11:$B$24,'Constr. Wage Rate Calculations'!$A$19:$Z$288,22,FALSE) -> 0 | G18: =VLOOKUP($B$11:$B$24,'Constr. Wage Rate Calculations'!$A$19:$Z$288,23,FALSE) -> 0 | I18: =VLOOKUP($B$11:$B$24,'Constr. Wage Rate Calculations'!$A$19:$Z$288,24,FALSE) -> 0 | J18: 0 | K18: =IF($D18>=1,$J18+(D18*E18)+(F18*G18)+(H18*I18),IF($F18>=1,$J18+(D18*E18)+(F18*G18)+(H18*I18),IF($H18>=1,$J18+(D18*E18)+(F18*G18)+(H18*I18),"")))
B19: =VLOOKUP($C$11:$C$24,Personnel!$A$1:$B$1234,2,FALSE) -> 0 | E19: =VLOOKUP($B$11:$B$24,'Constr. Wage Rate Calculations'!$A$19:$Z$288,22,FALSE) -> 0 | G19: =VLOOKUP($B$11:$B$24,'Constr. Wage Rate Calculations'!$A$19:$Z$288,23,FALSE) -> 0 | I19: =VLOOKUP($B$11:$B$24,'Constr. Wage Rate Calculations'!$A$19:$Z$288,24,FALSE) -> 0 | J19: =VLOOKUP($B$11:$B$25,'Constr. Wage Rate Calculations'!$A$19:$Z$288,25,FALSE) -> 0 | K19: =IF($D19>=1,$J19+(D19*E19)+(F19*G19)+(H19*I19),IF($F19>=1,$J19+(D19*E19)+(F19*G19)+(H19*I19),IF($H19>=1,$J19+(D19*E19)+(F19*G19)+(H19*I19),"")))
B20: =VLOOKUP($C$11:$C$24,Personnel!$A$1:$B$1234,2,FALSE) -> 0 | E20: =VLOOKUP($B$11:$B$24,'Constr. Wage Rate Calculations'!$A$19:$Z$288,22,FALSE) -> 0 | G20: =VLOOKUP($B$11:$B$24,'Constr. Wage Rate Calculations'!$A$19:$Z$288,23,FALSE) -> 0 | I20: =VLOOKUP($B$11:$B$24,'Constr. Wage Rate Calculations'!$A$19:$Z$288,24,FALSE) -> 0 | J20: =VLOOKUP($B$11:$B$25,'Constr. Wage Rate Calculations'!$A$19:$Z$288,25,FALSE) -> 0 | K20: =IF($D20>=1,$J20+(D20*E20)+(F20*G20)+(H20*I20),IF($F20>=1,$J20+(D20*E20)+(F20*G20)+(H20*I20),IF($H20>=1,$J20+(D20*E20)+(F20*G20)+(H20*I20),"")))
B21: =VLOOKUP($C$11:$C$24,Personnel!$A$1:$B$1234,2,FALSE) -> 0 | E21: =VLOOKUP($B$11:$B$24,'Constr. Wage Rate Calculations'!$A$19:$Z$288,22,FALSE) -> 0 | G21: =VLOOKUP($B$11:$B$24,'Constr. Wage Rate Calculations'!$A$19:$Z$288,23,FALSE) -> 0 | I21: =VLOOKUP($B$11:$B$24,'Constr. Wage Rate Calculations'!$A$19:$Z$288,24,FALSE) -> 0 | J21: =VLOOKUP($B$11:$B$25,'Constr. Wage Rate Calculations'!$A$19:$Z$288,25,FALSE) -> 0 | K21: =IF($D21>=1,$J21+(D21*E21)+(F21*G21)+(H21*I21),IF($F21>=1,$J21+(D21*E21)+(F21*G21)+(H21*I21),IF($H21>=1,$J21+(D21*E21)+(F21*G21)+(H21*I21),"")))
B22: =VLOOKUP($C$11:$C$24,Personnel!$A$1:$B$1234,2,FALSE) -> 0 | E22: =VLOOKUP($B$11:$B$24,'Constr. Wage Rate Calculations'!$A$19:$Z$288,22,FALSE) -> 0 | G22: =VLOOKUP($B$11:$B$24,'Constr. Wage Rate Calculations'!$A$19:$Z$288,23,FALSE) -> 0 | I22: =VLOOKUP($B$11:$B$24,'Constr. Wage Rate Calculations'!$A$19:$Z$288,24,FALSE) -> 0 | J22: =VLOOKUP($B$11:$B$25,'Constr. Wage Rate Calculations'!$A$19:$Z$288,25,FALSE) -> 0 | K22: =IF($D22>=1,$J22+(D22*E22)+(F22*G22)+(H22*I22),IF($F22>=1,$J22+(D22*E22)+(F22*G22)+(H22*I22),IF($H22>=1,$J22+(D22*E22)+(F22*G22)+(H22*I22),"")))
B23: =VLOOKUP($C$11:$C$24,Personnel!$A$1:$B$1234,2,FALSE) -> 0 | E23: =VLOOKUP($B$11:$B$24,'Constr. Wage Rate Calculations'!$A$19:$Z$288,22,FALSE) -> 0 | G23: =VLOOKUP($B$11:$B$24,'Constr. Wage Rate Calculations'!$A$19:$Z$288,23,FALSE) -> 0 | I23: =VLOOKUP($B$11:$B$24,'Constr. Wage Rate Calculations'!$A$19:$Z$288,24,FALSE) -> 0 | J23: =VLOOKUP($B$11:$B$25,'Constr. Wage Rate Calculations'!$A$19:$Z$288,25,FALSE) -> 0 | K23: =IF($D23>=1,$J23+(D23*E23)+(F23*G23)+(H23*I23),IF($F23>=1,$J23+(D23*E23)+(F23*G23)+(H23*I23),IF($H23>=1,$J23+(D23*E23)+(F23*G23)+(H23*I23),"")))
B24: =VLOOKUP($C$11:$C$24,Personnel!$A$1:$B$1234,2,FALSE) -> 0 | E24: =VLOOKUP($B$11:$B$24,'Constr. Wage Rate Calculations'!$A$19:$Z$288,22,FALSE) -> 0 | G24: =VLOOKUP($B$11:$B$24,'Constr. Wage Rate Calculations'!$A$19:$Z$288,23,FALSE) -> 0 | I24: =VLOOKUP($B$11:$B$24,'Constr. Wage Rate Calculations'!$A$19:$Z$288,24,FALSE) -> 0 | J24: =VLOOKUP($B$11:$B$25,'Constr. Wage Rate Calculations'!$A$19:$Z$288,25,FALSE) -> 0 | K24: =IF($D24>=1,$J24+(D24*E24)+(F24*G24)+(H24*I24),IF($F24>=1,$J24+(D24*E24)+(F24*G24)+(H24*I24),IF($H24>=1,$J24+(D24*E24)+(F24*G24)+(H24*I24),""))) | M24: =SUM(M11:M23) -> 0
I25: TOTAL LABOUR | K25: =SUM(K11:K24) -> 0 | M25: =SUMIFS(D11:D24,D11:D24,"<3",D11:D24,"<5") -> 0 | N25: =SUMIFS(D11:D24,D11:D24,">3",D11:D24,">5") -> 0 | O25: =SUM(F11:F24,H11:H24,M25,N25)-M24 -> 0
A27: Equipment ID | B27: Equipment | H27: Days | I27: Hrs. | J27: Rate | K27: Total
B28: =VLOOKUP($C$28:$C$49,Equipment!$A$1:$B$2322,2,FALSE) -> 0 | J28: =VLOOKUP($B$28:$B$49,'Alberta Equip. Rates Year 3'!$B$13:$K$314,10,FALSE) -> 0 | K28: =(H28+I28)*J28 -> 0
B29: =VLOOKUP($C$28:$C$49,Equipment!$A$1:$B$2322,2,FALSE) -> 0 | J29: =VLOOKUP($B$28:$B$49,'Alberta Equip. Rates Year 3'!$B$13:$K$314,10,FALSE) -> 0 | K29: =(H29+I29)*J29 -> 0
B30: =VLOOKUP($C$28:$C$49,Equipment!$A$1:$B$2322,2,FALSE) -> 0 | J30: =VLOOKUP($B$28:$B$49,'Alberta Equip. Rates Year 3'!$B$13:$K$314,10,FALSE) -> 0 | K30: =(H30+I30)*J30 -> 0
B31: =VLOOKUP($C$28:$C$49,Equipment!$A$1:$B$2322,2,FALSE) -> 0 | J31: =VLOOKUP($B$28:$B$49,'Alberta Equip. Rates Year 3'!$B$13:$K$314,10,FALSE) -> 0 | K31: =(H31+I31)*J31 -> 0
B32: =VLOOKUP($C$28:$C$49,Equipment!$A$1:$B$2322,2,FALSE) -> 0 | J32: =VLOOKUP($B$28:$B$49,'Alberta Equip. Rates Year 3'!$B$13:$K$314,10,FALSE) -> 0 | K32: =(H32+I32)*J32 -> 0
B33: =VLOOKUP($C$28:$C$49,Equipment!$A$1:$B$2322,2,FALSE) -> 0 | J33: =VLOOKUP($B$28:$B$49,'Alberta Equip. Rates Year 3'!$B$13:$K$314,10,FALSE) -> 0 | K33: =(H33+I33)*J33 -> 0
B34: =VLOOKUP($C$28:$C$49,Equipment!$A$1:$B$2322,2,FALSE) -> 0 | J34: =VLOOKUP($B$28:$B$49,'Alberta Equip. Rates Year 3'!$B$13:$K$314,10,FALSE) -> 0 | K34: =(H34+I34)*J34 -> 0
B35: =VLOOKUP($C$28:$C$49,Equipment!$A$1:$B$2322,2,FALSE) -> 0 | J35: =VLOOKUP($B$28:$B$49,'Alberta Equip. Rates Year 3'!$B$13:$K$314,10,FALSE) -> 0 | K35: =(H35+I35)*J35 -> 0
B36: =VLOOKUP($C$28:$C$49,Equipment!$A$1:$B$2322,2,FALSE) -> 0 | J36: =VLOOKUP($B$28:$B$49,'Alberta Equip. Rates Year 3'!$B$13:$K$314,10,FALSE) -> 0 | K36: =(H36+I36)*J36 -> 0
B37: =VLOOKUP($C$28:$C$49,Equipment!$A$1:$B$2322,2,FALSE) -> 0 | J37: =VLOOKUP($B$28:$B$49,'Alberta Equip. Rates Year 3'!$B$13:$K$314,10,FALSE) -> 0 | K37: =(H37+I37)*J37 -> 0
B38: =VLOOKUP($C$28:$C$49,Equipment!$A$1:$B$2322,2,FALSE) -> 0 | J38: =VLOOKUP($B$28:$B$49,'Alberta Equip. Rates Year 3'!$B$13:$K$314,10,FALSE) -> 0 | K38: =(H38+I38)*J38 -> 0
B39: =VLOOKUP($C$28:$C$49,Equipment!$A$1:$B$2322,2,FALSE) -> 0 | J39: =VLOOKUP($B$28:$B$49,'Alberta Equip. Rates Year 3'!$B$13:$K$314,10,FALSE) -> 0 | K39: =(H39+I39)*J39 -> 0
... B49: =VLOOKUP($C$28:$C$49,Equipment!$A$1:$B$2322,2,FALSE) -> 0 | J49: =VLOOKUP($B$28:$B$49,'Alberta Equip. Rates Year 3'!$B$13:$K$314,10,FALSE) -> 0 | K49: =(H49+I49)*J49 -> 0
I50: TOTAL EQUIPMENT | K50: =SUM(K28:K49) -> 0
A52: Scope of Work: | I52: LABOUR | K52: =K25 -> 0
I53: EQUIPMENT | K53: =K50 -> 0
I54: SMALL TOOLS | K54: =(O25)*14.15 -> 0
I55: MATERIALS
I56: TRUCKING
I57: SUBCONTRACTORS
I58: FIELD LOG TOTAL* | K58: =SUM(K52:K57) -> 0
A60: Client: | H60: Company Representitive:
A62: * Field Log Total does no include markups
A63: 41218.479

Sheet Field Log (47)
J1: Date:
G6: Field Log ID: | J6: Status:
A7: Address: | G7: Account #: | J7: Account:
G8: Foreman:
A10: Employee ID | B10: Labor Type | C10: Employee | D10: RT Hours | E10: RT Rate | F10: OT Hours | G10: OT Rate | H10: DT Hours | I10: DT Rate | J10: Sub. | K10: Total | M10: Additional Hours
B11: =VLOOKUP($C$11:$C$24,Personnel!$A$1:$B$1234,2,FALSE) -> 0 | E11: =VLOOKUP($B$11:$B$24,'Constr. Wage Rate Calculations'!$A$19:$Z$288,22,FALSE) -> 0 | G11: =VLOOKUP($B$11:$B$24,'Constr. Wage Rate Calculations'!$A$19:$Z$288,23,FALSE) -> 0 | I11: =VLOOKUP($B$11:$B$24,'Constr. Wage Rate Calculations'!$A$19:$Z$288,24,FALSE) -> 0 | J11: =VLOOKUP($B$11:$B$25,'Constr. Wage Rate Calculations'!$A$19:$Z$288,25,FALSE) -> 0 | K11: =IF($D11>=1,$J11+(D11*E11)+(F11*G11)+(H11*I11),IF($F11>=1,$J11+(D11*E11)+(F11*G11)+(H11*I11),IF($H11>=1,$J11+(D11*E11)+(F11*G11)+(H11*I11),"")))
B12: =VLOOKUP($C$11:$C$24,Personnel!$A$1:$B$1234,2,FALSE) -> 0 | E12: =VLOOKUP($B$11:$B$24,'Constr. Wage Rate Calculations'!$A$19:$Z$288,22,FALSE) -> 0 | G12: =VLOOKUP($B$11:$B$24,'Constr. Wage Rate Calculations'!$A$19:$Z$288,23,FALSE) -> 0 | I12: =VLOOKUP($B$11:$B$24,'Constr. Wage Rate Calculations'!$A$19:$Z$288,24,FALSE) -> 0 | J12: =VLOOKUP($B$11:$B$25,'Constr. Wage Rate Calculations'!$A$19:$Z$288,25,FALSE) -> 0 | K12: =IF($D12>=1,$J12+(D12*E12)+(F12*G12)+(H12*I12),IF($F12>=1,$J12+(D12*E12)+(F12*G12)+(H12*I12),IF($H12>=1,$J12+(D12*E12)+(F12*G12)+(H12*I12),"")))
B13: =VLOOKUP($C$11:$C$24,Personnel!$A$1:$B$1234,2,FALSE) -> 0 | E13: =VLOOKUP($B$11:$B$24,'Constr. Wage Rate Calculations'!$A$19:$Z$288,22,FALSE) -> 0 | G13: =VLOOKUP($B$11:$B$24,'Constr. Wage Rate Calculations'!$A$19:$Z$288,23,FALSE) -> 0 | I13: =VLOOKUP($B$11:$B$24,'Constr. Wage Rate Calculations'!$A$19:$Z$288,24,FALSE) -> 0 | J13: =VLOOKUP($B$11:$B$25,'Constr. Wage Rate Calculations'!$A$19:$Z$288,25,FALSE) -> 0 | K13: =IF($D13>=1,$J13+(D13*E13)+(F13*G13)+(H13*I13),IF($F13>=1,$J13+(D13*E13)+(F13*G13)+(H13*I13),IF($H13>=1,$J13+(D13*E13)+(F13*G13)+(H13*I13),"")))
B14: =VLOOKUP($C$11:$C$24,Personnel!$A$1:$B$1234,2,FALSE) -> 0 | E14: =VLOOKUP($B$11:$B$24,'Constr. Wage Rate Calculations'!$A$19:$Z$288,22,FALSE) -> 0 | G14: =VLOOKUP($B$11:$B$24,'Constr. Wage Rate Calculations'!$A$19:$Z$288,23,FALSE) -> 0 | I14: =VLOOKUP($B$11:$B$24,'Constr. Wage Rate Calculations'!$A$19:$Z$288,24,FALSE) -> 0 | J14: =VLOOKUP($B$11:$B$25,'Constr. Wage Rate Calculations'!$A$19:$Z$288,25,FALSE) -> 0 | K14: =IF($D14>=1,$J14+(D14*E14)+(F14*G14)+(H14*I14),IF($F14>=1,$J14+(D14*E14)+(F14*G14)+(H14*I14),IF($H14>=1,$J14+(D14*E14)+(F14*G14)+(H14*I14),"")))
B15: =VLOOKUP($C$11:$C$24,Personnel!$A$1:$B$1234,2,FALSE) -> 0 | E15: =VLOOKUP($B$11:$B$24,'Constr. Wage Rate Calculations'!$A$19:$Z$288,22,FALSE) -> 0 | G15: =VLOOKUP($B$11:$B$24,'Constr. Wage Rate Calculations'!$A$19:$Z$288,23,FALSE) -> 0 | I15: =VLOOKUP($B$11:$B$24,'Constr. Wage Rate Calculations'!$A$19:$Z$288,24,FALSE) -> 0 | J15: =VLOOKUP($B$11:$B$25,'Constr. Wage Rate Calculations'!$A$19:$Z$288,25,FALSE) -> 0 | K15: =IF($D15>=1,$J15+(D15*E15)+(F15*G15)+(H15*I15),IF($F15>=1,$J15+(D15*E15)+(F15*G15)+(H15*I15),IF($H15>=1,$J15+(D15*E15)+(F15*G15)+(H15*I15),"")))
B16: =VLOOKUP($C$11:$C$24,Personnel!$A$1:$B$1234,2,FALSE) -> 0 | E16: =VLOOKUP($B$11:$B$24,'Constr. Wage Rate Calculations'!$A$19:$Z$288,22,FALSE) -> 0 | G16: =VLOOKUP($B$11:$B$24,'Constr. Wage Rate Calculations'!$A$19:$Z$288,23,FALSE) -> 0 | I16: =VLOOKUP($B$11:$B$24,'Constr. Wage Rate Calculations'!$A$19:$Z$288,24,FALSE) -> 0 | J16: =VLOOKUP($B$11:$B$25,'Constr. Wage Rate Calculations'!$A$19:$Z$288,25,FALSE) -> 0 | K16: =IF($D16>=1,$J16+(D16*E16)+(F16*G16)+(H16*I16),IF($F16>=1,$J16+(D16*E16)+(F16*G16)+(H16*I16),IF($H16>=1,$J16+(D16*E16)+(F16*G16)+(H16*I16),"")))
B17: =VLOOKUP($C$11:$C$24,Personnel!$A$1:$B$1234,2,FALSE) -> 0 | E17: =VLOOKUP($B$11:$B$24,'Constr. Wage Rate Calculations'!$A$19:$Z$288,22,FALSE) -> 0 | G17: =VLOOKUP($B$11:$B$24,'Constr. Wage Rate Calculations'!$A$19:$Z$288,23,FALSE) -> 0 | I17: =VLOOKUP($B$11:$B$24,'Constr. Wage Rate Calculations'!$A$19:$Z$288,24,FALSE) -> 0 | J17: =VLOOKUP($B$11:$B$25,'Constr. Wage Rate Calculations'!$A$19:$Z$288,25,FALSE) -> 0 | K17: =IF($D17>=1,$J17+(D17*E17)+(F17*G17)+(H17*I17),IF($F17>=1,$J17+(D17*E17)+(F17*G17)+(H17*I17),IF($H17>=1,$J17+(D17*E17)+(F17*G17)+(H17*I17),"")))
B18: =VLOOKUP($C$11:$C$24,Personnel!$A$1:$B$1234,2,FALSE) -> 0 | E18: =VLOOKUP($B$11:$B$24,'Constr. Wage Rate Calculations'!$A$19:$Z$288,22,FALSE) -> 0 | G18: =VLOOKUP($B$11:$B$24,'Constr. Wage Rate Calculations'!$A$19:$Z$288,23,FALSE) -> 0 | I18: =VLOOKUP($B$11:$B$24,'Constr. Wage Rate Calculations'!$A$19:$Z$288,24,FALSE) -> 0 | J18: =VLOOKUP($B$11:$B$25,'Constr. Wage Rate Calculations'!$A$19:$Z$288,25,FALSE) -> 0 | K18: =IF($D18>=1,$J18+(D18*E18)+(F18*G18)+(H18*I18),IF($F18>=1,$J18+(D18*E18)+(F18*G18)+(H18*I18),IF($H18>=1,$J18+(D18*E18)+(F18*G18)+(H18*I18),"")))
B19: =VLOOKUP($C$11:$C$24,Personnel!$A$1:$B$1234,2,FALSE) -> 0 | E19: =VLOOKUP($B$11:$B$24,'Constr. Wage Rate Calculations'!$A$19:$Z$288,22,FALSE) -> 0 | G19: =VLOOKUP($B$11:$B$24,'Constr. Wage Rate Calculations'!$A$19:$Z$288,23,FALSE) -> 0 | I19: =VLOOKUP($B$11:$B$24,'Constr. Wage Rate Calculations'!$A$19:$Z$288,24,FALSE) -> 0 | J19: =VLOOKUP($B$11:$B$25,'Constr. Wage Rate Calculations'!$A$19:$Z$288,25,FALSE) -> 0 | K19: =IF($D19>=1,$J19+(D19*E19)+(F19*G19)+(H19*I19),IF($F19>=1,$J19+(D19*E19)+(F19*G19)+(H19*I19),IF($H19>=1,$J19+(D19*E19)+(F19*G19)+(H19*I19),"")))
B20: =VLOOKUP($C$11:$C$24,Personnel!$A$1:$B$1234,2,FALSE) -> 0 | E20: =VLOOKUP($B$11:$B$24,'Constr. Wage Rate Calculations'!$A$19:$Z$288,22,FALSE) -> 0 | G20: =VLOOKUP($B$11:$B$24,'Constr. Wage Rate Calculations'!$A$19:$Z$288,23,FALSE) -> 0 | I20: =VLOOKUP($B$11:$B$24,'Constr. Wage Rate Calculations'!$A$19:$Z$288,24,FALSE) -> 0 | J20: =VLOOKUP($B$11:$B$25,'Constr. Wage Rate Calculations'!$A$19:$Z$288,25,FALSE) -> 0 | K20: =IF($D20>=1,$J20+(D20*E20)+(F20*G20)+(H20*I20),IF($F20>=1,$J20+(D20*E20)+(F20*G20)+(H20*I20),IF($H20>=1,$J20+(D20*E20)+(F20*G20)+(H20*I20),"")))
B21: =VLOOKUP($C$11:$C$24,Personnel!$A$1:$B$1234,2,FALSE) -> 0 | E21: =VLOOKUP($B$11:$B$24,'Constr. Wage Rate Calculations'!$A$19:$Z$288,22,FALSE) -> 0 | G21: =VLOOKUP($B$11:$B$24,'Constr. Wage Rate Calculations'!$A$19:$Z$288,23,FALSE) -> 0 | I21: =VLOOKUP($B$11:$B$24,'Constr. Wage Rate Calculations'!$A$19:$Z$288,24,FALSE) -> 0 | J21: =VLOOKUP($B$11:$B$25,'Constr. Wage Rate Calculations'!$A$19:$Z$288,25,FALSE) -> 0 | K21: =IF($D21>=1,$J21+(D21*E21)+(F21*G21)+(H21*I21),IF($F21>=1,$J21+(D21*E21)+(F21*G21)+(H21*I21),IF($H21>=1,$J21+(D21*E21)+(F21*G21)+(H21*I21),"")))
B22: =VLOOKUP($C$11:$C$24,Personnel!$A$1:$B$1234,2,FALSE) -> 0 | E22: =VLOOKUP($B$11:$B$24,'Constr. Wage Rate Calculations'!$A$19:$Z$288,22,FALSE) -> 0 | G22: =VLOOKUP($B$11:$B$24,'Constr. Wage Rate Calculations'!$A$19:$Z$288,23,FALSE) -> 0 | I22: =VLOOKUP($B$11:$B$24,'Constr. Wage Rate Calculations'!$A$19:$Z$288,24,FALSE) -> 0 | J22: =VLOOKUP($B$11:$B$25,'Constr. Wage Rate Calculations'!$A$19:$Z$288,25,FALSE) -> 0 | K22: =IF($D22>=1,$J22+(D22*E22)+(F22*G22)+(H22*I22),IF($F22>=1,$J22+(D22*E22)+(F22*G22)+(H22*I22),IF($H22>=1,$J22+(D22*E22)+(F22*G22)+(H22*I22),"")))
B23: =VLOOKUP($C$11:$C$24,Personnel!$A$1:$B$1234,2,FALSE) -> 0 | E23: =VLOOKUP($B$11:$B$24,'Constr. Wage Rate Calculations'!$A$19:$Z$288,22,FALSE) -> 0 | G23: =VLOOKUP($B$11:$B$24,'Constr. Wage Rate Calculations'!$A$19:$Z$288,23,FALSE) -> 0 | I23: =VLOOKUP($B$11:$B$24,'Constr. Wage Rate Calculations'!$A$19:$Z$288,24,FALSE) -> 0 | J23: =VLOOKUP($B$11:$B$25,'Constr. Wage Rate Calculations'!$A$19:$Z$288,25,FALSE) -> 0 | K23: =IF($D23>=1,$J23+(D23*E23)+(F23*G23)+(H23*I23),IF($F23>=1,$J23+(D23*E23)+(F23*G23)+(H23*I23),IF($H23>=1,$J23+(D23*E23)+(F23*G23)+(H23*I23),"")))
B24: =VLOOKUP($C$11:$C$24,Personnel!$A$1:$B$1234,2,FALSE) -> 0 | E24: =VLOOKUP($B$11:$B$24,'Constr. Wage Rate Calculations'!$A$19:$Z$288,22,FALSE) -> 0 | G24: =VLOOKUP($B$11:$B$24,'Constr. Wage Rate Calculations'!$A$19:$Z$288,23,FALSE) -> 0 | I24: =VLOOKUP($B$11:$B$24,'Constr. Wage Rate Calculations'!$A$19:$Z$288,24,FALSE) -> 0 | J24: =VLOOKUP($B$11:$B$25,'Constr. Wage Rate Calculations'!$A$19:$Z$288,25,FALSE) -> 0 | K24: =IF($D24>=1,$J24+(D24*E24)+(F24*G24)+(H24*I24),IF($F24>=1,$J24+(D24*E24)+(F24*G24)+(H24*I24),IF($H24>=1,$J24+(D24*E24)+(F24*G24)+(H24*I24),""))) | M24: =SUM(M11:M23) -> 0
I25: TOTAL LABOUR | K25: =SUM(K11:K24) -> 0 | M25: =SUMIFS(D11:D24,D11:D24,"<3",D11:D24,"<5") -> 0 | N25: =SUMIFS(D11:D24,D11:D24,">3",D11:D24,">5") -> 0 | O25: =SUM(F11:F24,H11:H24,M25,N25)-M24 -> 0
A27: Equipment ID | B27: Equipment | H27: Days | I27: Hrs. | J27: Rate | K27: Total
B28: =VLOOKUP($C$28:$C$49,Equipment!$A$1:$B$2322,2,FALSE) -> 0 | J28: =VLOOKUP($B$28:$B$49,'Alberta Equip. Rates Year 3'!$B$13:$K$314,10,FALSE) -> 0 | K28: =(H28+I28)*J28 -> 0
B29: =VLOOKUP($C$28:$C$49,Equipment!$A$1:$B$2322,2,FALSE) -> 0 | J29: =VLOOKUP($B$28:$B$49,'Alberta Equip. Rates Year 3'!$B$13:$K$314,10,FALSE) -> 0 | K29: =(H29+I29)*J29 -> 0
B30: =VLOOKUP($C$28:$C$49,Equipment!$A$1:$B$2322,2,FALSE) -> 0 | J30: =VLOOKUP($B$28:$B$49,'Alberta Equip. Rates Year 3'!$B$13:$K$314,10,FALSE) -> 0 | K30: =(H30+I30)*J30 -> 0
B31: =VLOOKUP($C$28:$C$49,Equipment!$A$1:$B$2322,2,FALSE) -> 0 | J31: =VLOOKUP($B$28:$B$49,'Alberta Equip. Rates Year 3'!$B$13:$K$314,10,FALSE) -> 0 | K31: =(H31+I31)*J31 -> 0
B32: =VLOOKUP($C$28:$C$49,Equipment!$A$1:$B$2322,2,FALSE) -> 0 | J32: =VLOOKUP($B$28:$B$49,'Alberta Equip. Rates Year 3'!$B$13:$K$314,10,FALSE) -> 0 | K32: =(H32+I32)*J32 -> 0
B33: =VLOOKUP($C$28:$C$49,Equipment!$A$1:$B$2322,2,FALSE) -> 0 | J33: =VLOOKUP($B$28:$B$49,'Alberta Equip. Rates Year 3'!$B$13:$K$314,10,FALSE) -> 0 | K33: =(H33+I33)*J33 -> 0
B34: =VLOOKUP($C$28:$C$49,Equipment!$A$1:$B$2322,2,FALSE) -> 0 | J34: =VLOOKUP($B$28:$B$49,'Alberta Equip. Rates Year 3'!$B$13:$K$314,10,FALSE) -> 0 | K34: =(H34+I34)*J34 -> 0
B35: =VLOOKUP($C$28:$C$49,Equipment!$A$1:$B$2322,2,FALSE) -> 0 | J35: =VLOOKUP($B$28:$B$49,'Alberta Equip. Rates Year 3'!$B$13:$K$314,10,FALSE) -> 0 | K35: =(H35+I35)*J35 -> 0
B36: =VLOOKUP($C$28:$C$49,Equipment!$A$1:$B$2322,2,FALSE) -> 0 | J36: =VLOOKUP($B$28:$B$49,'Alberta Equip. Rates Year 3'!$B$13:$K$314,10,FALSE) -> 0 | K36: =(H36+I36)*J36 -> 0
B37: =VLOOKUP($C$28:$C$49,Equipment!$A$1:$B$2322,2,FALSE) -> 0 | J37: =VLOOKUP($B$28:$B$49,'Alberta Equip. Rates Year 3'!$B$13:$K$314,10,FALSE) -> 0 | K37: =(H37+I37)*J37 -> 0
B38: =VLOOKUP($C$28:$C$49,Equipment!$A$1:$B$2322,2,FALSE) -> 0 | J38: =VLOOKUP($B$28:$B$49,'Alberta Equip. Rates Year 3'!$B$13:$K$314,10,FALSE) -> 0 | K38: =(H38+I38)*J38 -> 0
B39: =VLOOKUP($C$28:$C$49,Equipment!$A$1:$B$2322,2,FALSE) -> 0 | J39: =VLOOKUP($B$28:$B$49,'Alberta Equip. Rates Year 3'!$B$13:$K$314,10,FALSE) -> 0 | K39: =(H39+I39)*J39 -> 0
... B49: =VLOOKUP($C$28:$C$49,Equipment!$A$1:$B$2322,2,FALSE) -> 0 | J49: =VLOOKUP($B$28:$B$49,'Alberta Equip. Rates Year 3'!$B$13:$K$314,10,FALSE) -> 0 | K49: =(H49+I49)*J49 -> 0
I50: TOTAL EQUIPMENT | K50: =SUM(K28:K49) -> 0
A52: Scope of Work: | I52: LABOUR | K52: =K25 -> 0
I53: EQUIPMENT | K53: =K50 -> 0
I54: SMALL TOOLS | K54: =(O25)*14.15 -> 0
I55: MATERIALS
I56: TRUCKING
I57: SUBCONTRACTORS
I58: FIELD LOG TOTAL* | K58: =SUM(K52:K57) -> 0
A60: Client: | H60: Company Representitive:
A62: * Field Log Total does no include markups
A63: 41218.479

Sheet Field Log (46)
J1: Date:
G6: Field Log ID: | J6: Status:
A7: Address: | G7: Account #: | J7: Account:
G8: Foreman:
A10: Employee ID | B10: Labor Type | C10: Employee | D10: RT Hours | E10: RT Rate | F10: OT Hours | G10: OT Rate | H10: DT Hours | I10: DT Rate | J10: Sub. | K10: Total | M10: Additional Hours
B11: =VLOOKUP($C$11:$C$24,Personnel!$A$1:$B$1234,2,FALSE) -> 0 | E11: =VLOOKUP($B$11:$B$24,'Constr. Wage Rate Calculations'!$A$19:$Z$288,22,FALSE) -> 0 | G11: =VLOOKUP($B$11:$B$24,'Constr. Wage Rate Calculations'!$A$19:$Z$288,23,FALSE) -> 0 | I11: =VLOOKUP($B$11:$B$24,'Constr. Wage Rate Calculations'!$A$19:$Z$288,24,FALSE) -> 0 | J11: =VLOOKUP($B$11:$B$25,'Constr. Wage Rate Calculations'!$A$19:$Z$288,25,FALSE) -> 0 | K11: =IF($D11>=1,$J11+(D11*E11)+(F11*G11)+(H11*I11),IF($F11>=1,$J11+(D11*E11)+(F11*G11)+(H11*I11),IF($H11>=1,$J11+(D11*E11)+(F11*G11)+(H11*I11),"")))
B12: =VLOOKUP($C$11:$C$24,Personnel!$A$1:$B$1234,2,FALSE) -> 0 | E12: =VLOOKUP($B$11:$B$24,'Constr. Wage Rate Calculations'!$A$19:$Z$288,22,FALSE) -> 0 | G12: =VLOOKUP($B$11:$B$24,'Constr. Wage Rate Calculations'!$A$19:$Z$288,23,FALSE) -> 0 | I12: =VLOOKUP($B$11:$B$24,'Constr. Wage Rate Calculations'!$A$19:$Z$288,24,FALSE) -> 0 | J12: =VLOOKUP($B$11:$B$25,'Constr. Wage Rate Calculations'!$A$19:$Z$288,25,FALSE) -> 0 | K12: =IF($D12>=1,$J12+(D12*E12)+(F12*G12)+(H12*I12),IF($F12>=1,$J12+(D12*E12)+(F12*G12)+(H12*I12),IF($H12>=1,$J12+(D12*E12)+(F12*G12)+(H12*I12),"")))
B13: =VLOOKUP($C$11:$C$24,Personnel!$A$1:$B$1234,2,FALSE) -> 0 | E13: =VLOOKUP($B$11:$B$24,'Constr. Wage Rate Calculations'!$A$19:$Z$288,22,FALSE) -> 0 | G13: =VLOOKUP($B$11:$B$24,'Constr. Wage Rate Calculations'!$A$19:$Z$288,23,FALSE) -> 0 | I13: =VLOOKUP($B$11:$B$24,'Constr. Wage Rate Calculations'!$A$19:$Z$288,24,FALSE) -> 0 | J13: =VLOOKUP($B$11:$B$25,'Constr. Wage Rate Calculations'!$A$19:$Z$288,25,FALSE) -> 0 | K13: =IF($D13>=1,$J13+(D13*E13)+(F13*G13)+(H13*I13),IF($F13>=1,$J13+(D13*E13)+(F13*G13)+(H13*I13),IF($H13>=1,$J13+(D13*E13)+(F13*G13)+(H13*I13),"")))
B14: =VLOOKUP($C$11:$C$24,Personnel!$A$1:$B$1234,2,FALSE) -> 0 | E14: =VLOOKUP($B$11:$B$24,'Constr. Wage Rate Calculations'!$A$19:$Z$288,22,FALSE) -> 0 | G14: =VLOOKUP($B$11:$B$24,'Constr. Wage Rate Calculations'!$A$19:$Z$288,23,FALSE) -> 0 | I14: =VLOOKUP($B$11:$B$24,'Constr. Wage Rate Calculations'!$A$19:$Z$288,24,FALSE) -> 0 | J14: =VLOOKUP($B$11:$B$25,'Constr. Wage Rate Calculations'!$A$19:$Z$288,25,FALSE) -> 0 | K14: =IF($D14>=1,$J14+(D14*E14)+(F14*G14)+(H14*I14),IF($F14>=1,$J14+(D14*E14)+(F14*G14)+(H14*I14),IF($H14>=1,$J14+(D14*E14)+(F14*G14)+(H14*I14),"")))
B15: =VLOOKUP($C$11:$C$24,Personnel!$A$1:$B$1234,2,FALSE) -> 0 | E15: =VLOOKUP($B$11:$B$24,'Constr. Wage Rate Calculations'!$A$19:$Z$288,22,FALSE) -> 0 | G15: =VLOOKUP($B$11:$B$24,'Constr. Wage Rate Calculations'!$A$19:$Z$288,23,FALSE) -> 0 | I15: =VLOOKUP($B$11:$B$24,'Constr. Wage Rate Calculations'!$A$19:$Z$288,24,FALSE) -> 0 | J15: =VLOOKUP($B$11:$B$25,'Constr. Wage Rate Calculations'!$A$19:$Z$288,25,FALSE) -> 0 | K15: =IF($D15>=1,$J15+(D15*E15)+(F15*G15)+(H15*I15),IF($F15>=1,$J15+(D15*E15)+(F15*G15)+(H15*I15),IF($H15>=1,$J15+(D15*E15)+(F15*G15)+(H15*I15),"")))
B16: =VLOOKUP($C$11:$C$24,Personnel!$A$1:$B$1234,2,FALSE) -> 0 | E16: =VLOOKUP($B$11:$B$24,'Constr. Wage Rate Calculations'!$A$19:$Z$288,22,FALSE) -> 0 | G16: =VLOOKUP($B$11:$B$24,'Constr. Wage Rate Calculations'!$A$19:$Z$288,23,FALSE) -> 0 | I16: =VLOOKUP($B$11:$B$24,'Constr. Wage Rate Calculations'!$A$19:$Z$288,24,FALSE) -> 0 | J16: =VLOOKUP($B$11:$B$25,'Constr. Wage Rate Calculations'!$A$19:$Z$288,25,FALSE) -> 0 | K16: =IF($D16>=1,$J16+(D16*E16)+(F16*G16)+(H16*I16),IF($F16>=1,$J16+(D16*E16)+(F16*G16)+(H16*I16),IF($H16>=1,$J16+(D16*E16)+(F16*G16)+(H16*I16),"")))
B17: =VLOOKUP($C$11:$C$24,Personnel!$A$1:$B$1234,2,FALSE) -> 0 | E17: =VLOOKUP($B$11:$B$24,'Constr. Wage Rate Calculations'!$A$19:$Z$288,22,FALSE) -> 0 | G17: =VLOOKUP($B$11:$B$24,'Constr. Wage Rate Calculations'!$A$19:$Z$288,23,FALSE) -> 0 | I17: =VLOOKUP($B$11:$B$24,'Constr. Wage Rate Calculations'!$A$19:$Z$288,24,FALSE) -> 0 | J17: =VLOOKUP($B$11:$B$25,'Constr. Wage Rate Calculations'!$A$19:$Z$288,25,FALSE) -> 0 | K17: =IF($D17>=1,$J17+(D17*E17)+(F17*G17)+(H17*I17),IF($F17>=1,$J17+(D17*E17)+(F17*G17)+(H17*I17),IF($H17>=1,$J17+(D17*E17)+(F17*G17)+(H17*I17),"")))
B18: =VLOOKUP($C$11:$C$24,Personnel!$A$1:$B$1234,2,FALSE) -> 0 | E18: =VLOOKUP($B$11:$B$24,'Constr. Wage Rate Calculations'!$A$19:$Z$288,22,FALSE) -> 0 | G18: =VLOOKUP($B$11:$B$24,'Constr. Wage Rate Calculations'!$A$19:$Z$288,23,FALSE) -> 0 | I18: =VLOOKUP($B$11:$B$24,'Constr. Wage Rate Calculations'!$A$19:$Z$288,24,FALSE) -> 0 | J18: =VLOOKUP($B$11:$B$25,'Constr. Wage Rate Calculations'!$A$19:$Z$288,25,FALSE) -> 0 | K18: =IF($D18>=1,$J18+(D18*E18)+(F18*G18)+(H18*I18),IF($F18>=1,$J18+(D18*E18)+(F18*G18)+(H18*I18),IF($H18>=1,$J18+(D18*E18)+(F18*G18)+(H18*I18),"")))
B19: =VLOOKUP($C$11:$C$24,Personnel!$A$1:$B$1234,2,FALSE) -> 0 | E19: =VLOOKUP($B$11:$B$24,'Constr. Wage Rate Calculations'!$A$19:$Z$288,22,FALSE) -> 0 | G19: =VLOOKUP($B$11:$B$24,'Constr. Wage Rate Calculations'!$A$19:$Z$288,23,FALSE) -> 0 | I19: =VLOOKUP($B$11:$B$24,'Constr. Wage Rate Calculations'!$A$19:$Z$288,24,FALSE) -> 0 | J19: =VLOOKUP($B$11:$B$25,'Constr. Wage Rate Calculations'!$A$19:$Z$288,25,FALSE) -> 0 | K19: =IF($D19>=1,$J19+(D19*E19)+(F19*G19)+(H19*I19),IF($F19>=1,$J19+(D19*E19)+(F19*G19)+(H19*I19),IF($H19>=1,$J19+(D19*E19)+(F19*G19)+(H19*I19),"")))
B20: =VLOOKUP($C$11:$C$24,Personnel!$A$1:$B$1234,2,FALSE) -> 0 | E20: =VLOOKUP($B$11:$B$24,'Constr. Wage Rate Calculations'!$A$19:$Z$288,22,FALSE) -> 0 | G20: =VLOOKUP($B$11:$B$24,'Constr. Wage Rate Calculations'!$A$19:$Z$288,23,FALSE) -> 0 | I20: =VLOOKUP($B$11:$B$24,'Constr. Wage Rate Calculations'!$A$19:$Z$288,24,FALSE) -> 0 | J20: =VLOOKUP($B$11:$B$25,'Constr. Wage Rate Calculations'!$A$19:$Z$288,25,FALSE) -> 0 | K20: =IF($D20>=1,$J20+(D20*E20)+(F20*G20)+(H20*I20),IF($F20>=1,$J20+(D20*E20)+(F20*G20)+(H20*I20),IF($H20>=1,$J20+(D20*E20)+(F20*G20)+(H20*I20),"")))
B21: =VLOOKUP($C$11:$C$24,Personnel!$A$1:$B$1234,2,FALSE) -> 0 | E21: =VLOOKUP($B$11:$B$24,'Constr. Wage Rate Calculations'!$A$19:$Z$288,22,FALSE) -> 0 | G21: =VLOOKUP($B$11:$B$24,'Constr. Wage Rate Calculations'!$A$19:$Z$288,23,FALSE) -> 0 | I21: =VLOOKUP($B$11:$B$24,'Constr. Wage Rate Calculations'!$A$19:$Z$288,24,FALSE) -> 0 | J21: =VLOOKUP($B$11:$B$25,'Constr. Wage Rate Calculations'!$A$19:$Z$288,25,FALSE) -> 0 | K21: =IF($D21>=1,$J21+(D21*E21)+(F21*G21)+(H21*I21),IF($F21>=1,$J21+(D21*E21)+(F21*G21)+(H21*I21),IF($H21>=1,$J21+(D21*E21)+(F21*G21)+(H21*I21),"")))
B22: =VLOOKUP($C$11:$C$24,Personnel!$A$1:$B$1234,2,FALSE) -> 0 | E22: =VLOOKUP($B$11:$B$24,'Constr. Wage Rate Calculations'!$A$19:$Z$288,22,FALSE) -> 0 | G22: =VLOOKUP($B$11:$B$24,'Constr. Wage Rate Calculations'!$A$19:$Z$288,23,FALSE) -> 0 | I22: =VLOOKUP($B$11:$B$24,'Constr. Wage Rate Calculations'!$A$19:$Z$288,24,FALSE) -> 0 | J22: =VLOOKUP($B$11:$B$25,'Constr. Wage Rate Calculations'!$A$19:$Z$288,25,FALSE) -> 0 | K22: =IF($D22>=1,$J22+(D22*E22)+(F22*G22)+(H22*I22),IF($F22>=1,$J22+(D22*E22)+(F22*G22)+(H22*I22),IF($H22>=1,$J22+(D22*E22)+(F22*G22)+(H22*I22),"")))
B23: =VLOOKUP($C$11:$C$24,Personnel!$A$1:$B$1234,2,FALSE) -> 0 | E23: =VLOOKUP($B$11:$B$24,'Constr. Wage Rate Calculations'!$A$19:$Z$288,22,FALSE) -> 0 | G23: =VLOOKUP($B$11:$B$24,'Constr. Wage Rate Calculations'!$A$19:$Z$288,23,FALSE) -> 0 | I23: =VLOOKUP($B$11:$B$24,'Constr. Wage Rate Calculations'!$A$19:$Z$288,24,FALSE) -> 0 | J23: =VLOOKUP($B$11:$B$25,'Constr. Wage Rate Calculations'!$A$19:$Z$288,25,FALSE) -> 0 | K23: =IF($D23>=1,$J23+(D23*E23)+(F23*G23)+(H23*I23),IF($F23>=1,$J23+(D23*E23)+(F23*G23)+(H23*I23),IF($H23>=1,$J23+(D23*E23)+(F23*G23)+(H23*I23),"")))
B24: =VLOOKUP($C$11:$C$24,Personnel!$A$1:$B$1234,2,FALSE) -> 0 | E24: =VLOOKUP($B$11:$B$24,'Constr. Wage Rate Calculations'!$A$19:$Z$288,22,FALSE) -> 0 | G24: =VLOOKUP($B$11:$B$24,'Constr. Wage Rate Calculations'!$A$19:$Z$288,23,FALSE) -> 0 | I24: =VLOOKUP($B$11:$B$24,'Constr. Wage Rate Calculations'!$A$19:$Z$288,24,FALSE) -> 0 | J24: =VLOOKUP($B$11:$B$25,'Constr. Wage Rate Calculations'!$A$19:$Z$288,25,FALSE) -> 0 | K24: =IF($D24>=1,$J24+(D24*E24)+(F24*G24)+(H24*I24),IF($F24>=1,$J24+(D24*E24)+(F24*G24)+(H24*I24),IF($H24>=1,$J24+(D24*E24)+(F24*G24)+(H24*I24),""))) | M24: =SUM(M11:M23) -> 0
I25: TOTAL LABOUR | K25: =SUM(K11:K24) -> 0 | M25: =SUMIFS(D11:D24,D11:D24,"<3",D11:D24,"<5") -> 0 | N25: =SUMIFS(D11:D24,D11:D24,">3",D11:D24,">5") -> 0 | O25: =SUM(F11:F24,H11:H24,M25,N25)-M24 -> 0
A27: Equipment ID | B27: Equipment | H27: Days | I27: Hrs. | J27: Rate | K27: Total
B28: =VLOOKUP($C$28:$C$49,Equipment!$A$1:$B$2322,2,FALSE) -> 0 | J28: =VLOOKUP($B$28:$B$49,'Alberta Equip. Rates Year 3'!$B$13:$K$314,10,FALSE) -> 0 | K28: =(H28+I28)*J28 -> 0
B29: =VLOOKUP($C$28:$C$49,Equipment!$A$1:$B$2322,2,FALSE) -> 0 | J29: =VLOOKUP($B$28:$B$49,'Alberta Equip. Rates Year 3'!$B$13:$K$314,10,FALSE) -> 0 | K29: =(H29+I29)*J29 -> 0
B30: =VLOOKUP($C$28:$C$49,Equipment!$A$1:$B$2322,2,FALSE) -> 0 | J30: =VLOOKUP($B$28:$B$49,'Alberta Equip. Rates Year 3'!$B$13:$K$314,10,FALSE) -> 0 | K30: =(H30+I30)*J30 -> 0
B31: =VLOOKUP($C$28:$C$49,Equipment!$A$1:$B$2322,2,FALSE) -> 0 | J31: =VLOOKUP($B$28:$B$49,'Alberta Equip. Rates Year 3'!$B$13:$K$314,10,FALSE) -> 0 | K31: =(H31+I31)*J31 -> 0
B32: =VLOOKUP($C$28:$C$49,Equipment!$A$1:$B$2322,2,FALSE) -> 0 | J32: =VLOOKUP($B$28:$B$49,'Alberta Equip. Rates Year 3'!$B$13:$K$314,10,FALSE) -> 0 | K32: =(H32+I32)*J32 -> 0
B33: =VLOOKUP($C$28:$C$49,Equipment!$A$1:$B$2322,2,FALSE) -> 0 | J33: =VLOOKUP($B$28:$B$49,'Alberta Equip. Rates Year 3'!$B$13:$K$314,10,FALSE) -> 0 | K33: =(H33+I33)*J33 -> 0
B34: =VLOOKUP($C$28:$C$49,Equipment!$A$1:$B$2322,2,FALSE) -> 0 | J34: =VLOOKUP($B$28:$B$49,'Alberta Equip. Rates Year 3'!$B$13:$K$314,10,FALSE) -> 0 | K34: =(H34+I34)*J34 -> 0
B35: =VLOOKUP($C$28:$C$49,Equipment!$A$1:$B$2322,2,FALSE) -> 0 | J35: =VLOOKUP($B$28:$B$49,'Alberta Equip. Rates Year 3'!$B$13:$K$314,10,FALSE) -> 0 | K35: =(H35+I35)*J35 -> 0
B36: =VLOOKUP($C$28:$C$49,Equipment!$A$1:$B$2322,2,FALSE) -> 0 | J36: =VLOOKUP($B$28:$B$49,'Alberta Equip. Rates Year 3'!$B$13:$K$314,10,FALSE) -> 0 | K36: =(H36+I36)*J36 -> 0
B37: =VLOOKUP($C$28:$C$49,Equipment!$A$1:$B$2322,2,FALSE) -> 0 | J37: =VLOOKUP($B$28:$B$49,'Alberta Equip. Rates Year 3'!$B$13:$K$314,10,FALSE) -> 0 | K37: =(H37+I37)*J37 -> 0
B38: =VLOOKUP($C$28:$C$49,Equipment!$A$1:$B$2322,2,FALSE) -> 0 | J38: =VLOOKUP($B$28:$B$49,'Alberta Equip. Rates Year 3'!$B$13:$K$314,10,FALSE) -> 0 | K38: =(H38+I38)*J38 -> 0
B39: =VLOOKUP($C$28:$C$49,Equipment!$A$1:$B$2322,2,FALSE) -> 0 | J39: =VLOOKUP($B$28:$B$49,'Alberta Equip. Rates Year 3'!$B$13:$K$314,10,FALSE) -> 0 | K39: =(H39+I39)*J39 -> 0
... B49: =VLOOKUP($C$28:$C$49,Equipment!$A$1:$B$2322,2,FALSE) -> 0 | J49: =VLOOKUP($B$28:$B$49,'Alberta Equip. Rates Year 3'!$B$13:$K$314,10,FALSE) -> 0 | K49: =(H49+I49)*J49 -> 0
I50: TOTAL EQUIPMENT | K50: =SUM(K28:K49) -> 0
A52: Scope of Work: | I52: LABOUR | K52: =K25 -> 0
I53: EQUIPMENT | K53: =K50 -> 0
I54: SMALL TOOLS | K54: =(O25)*14.15 -> 0
I55: MATERIALS
I56: TRUCKING
I57: SUBCONTRACTORS
I58: FIELD LOG TOTAL* | K58: =SUM(K52:K57) -> 0
A60: Client: | H60: Company Representitive:
A62: * Field Log Total does no include markups
A63: 41218.479

Sheet Field Log (45)
J1: Date:
G6: Field Log ID: | J6: Status:
A7: Address: | G7: Account #: | J7: Account:
G8: Foreman:
A10: Employee ID | B10: Labor Type | C10: Employee | D10: RT Hours | E10: RT Rate | F10: OT Hours | G10: OT Rate | H10: DT Hours | I10: DT Rate | J10: Sub. | K10: Total | M10: Additional Hours
B11: =VLOOKUP($C$11:$C$25,Personnel!$A$1:$B$1234,2,FALSE) -> 0 | E11: =VLOOKUP($B$11:$B$25,'Constr. Wage Rate Calculations'!$A$19:$Z$288,22,FALSE) -> 0 | G11: =VLOOKUP($B$11:$B$25,'Constr. Wage Rate Calculations'!$A$19:$Z$288,23,FALSE) -> 0 | I11: =VLOOKUP($B$11:$B$25,'Constr. Wage Rate Calculations'!$A$19:$Z$288,24,FALSE) -> 0 | J11: =VLOOKUP($B$11:$B$25,'Constr. Wage Rate Calculations'!$A$19:$Z$288,25,FALSE) -> 0 | K11: =IF($D11>=1,$J11+(D11*E11)+(F11*G11)+(H11*I11),IF($F11>=1,$J11+(D11*E11)+(F11*G11)+(H11*I11),IF($H11>=1,$J11+(D11*E11)+(F11*G11)+(H11*I11),"")))
B12: =VLOOKUP($C$11:$C$25,Personnel!$A$1:$B$1234,2,FALSE) -> 0 | E12: =VLOOKUP($B$11:$B$25,'Constr. Wage Rate Calculations'!$A$19:$Z$288,22,FALSE) -> 0 | G12: =VLOOKUP($B$11:$B$25,'Constr. Wage Rate Calculations'!$A$19:$Z$288,23,FALSE) -> 0 | I12: =VLOOKUP($B$11:$B$25,'Constr. Wage Rate Calculations'!$A$19:$Z$288,24,FALSE) -> 0 | J12: =VLOOKUP($B$11:$B$25,'Constr. Wage Rate Calculations'!$A$19:$Z$288,25,FALSE) -> 0 | K12: =IF($D12>=1,$J12+(D12*E12)+(F12*G12)+(H12*I12),IF($F12>=1,$J12+(D12*E12)+(F12*G12)+(H12*I12),IF($H12>=1,$J12+(D12*E12)+(F12*G12)+(H12*I12),"")))
B13: =VLOOKUP($C$11:$C$25,Personnel!$A$1:$B$1234,2,FALSE) -> 0 | E13: =VLOOKUP($B$11:$B$25,'Constr. Wage Rate Calculations'!$A$19:$Z$288,22,FALSE) -> 0 | G13: =VLOOKUP($B$11:$B$25,'Constr. Wage Rate Calculations'!$A$19:$Z$288,23,FALSE) -> 0 | I13: =VLOOKUP($B$11:$B$25,'Constr. Wage Rate Calculations'!$A$19:$Z$288,24,FALSE) -> 0 | J13: =VLOOKUP($B$11:$B$25,'Constr. Wage Rate Calculations'!$A$19:$Z$288,25,FALSE) -> 0 | K13: =IF($D13>=1,$J13+(D13*E13)+(F13*G13)+(H13*I13),IF($F13>=1,$J13+(D13*E13)+(F13*G13)+(H13*I13),IF($H13>=1,$J13+(D13*E13)+(F13*G13)+(H13*I13),"")))
B14: =VLOOKUP($C$11:$C$25,Personnel!$A$1:$B$1234,2,FALSE) -> 0 | E14: =VLOOKUP($B$11:$B$25,'Constr. Wage Rate Calculations'!$A$19:$Z$288,22,FALSE) -> 0 | G14: =VLOOKUP($B$11:$B$25,'Constr. Wage Rate Calculations'!$A$19:$Z$288,23,FALSE) -> 0 | I14: =VLOOKUP($B$11:$B$25,'Constr. Wage Rate Calculations'!$A$19:$Z$288,24,FALSE) -> 0 | J14: =VLOOKUP($B$11:$B$25,'Constr. Wage Rate Calculations'!$A$19:$Z$288,25,FALSE) -> 0 | K14: =IF($D14>=1,$J14+(D14*E14)+(F14*G14)+(H14*I14),IF($F14>=1,$J14+(D14*E14)+(F14*G14)+(H14*I14),IF($H14>=1,$J14+(D14*E14)+(F14*G14)+(H14*I14),"")))
B15: =VLOOKUP($C$11:$C$25,Personnel!$A$1:$B$1234,2,FALSE) -> 0 | E15: =VLOOKUP($B$11:$B$25,'Constr. Wage Rate Calculations'!$A$19:$Z$288,22,FALSE) -> 0 | G15: =VLOOKUP($B$11:$B$25,'Constr. Wage Rate Calculations'!$A$19:$Z$288,23,FALSE) -> 0 | I15: =VLOOKUP($B$11:$B$25,'Constr. Wage Rate Calculations'!$A$19:$Z$288,24,FALSE) -> 0 | J15: =VLOOKUP($B$11:$B$25,'Constr. Wage Rate Calculations'!$A$19:$Z$288,25,FALSE) -> 0 | K15: =IF($D15>=1,$J15+(D15*E15)+(F15*G15)+(H15*I15),IF($F15>=1,$J15+(D15*E15)+(F15*G15)+(H15*I15),IF($H15>=1,$J15+(D15*E15)+(F15*G15)+(H15*I15),"")))
B16: =VLOOKUP($C$11:$C$25,Personnel!$A$1:$B$1234,2,FALSE) -> 0 | E16: =VLOOKUP($B$11:$B$25,'Constr. Wage Rate Calculations'!$A$19:$Z$288,22,FALSE) -> 0 | G16: =VLOOKUP($B$11:$B$25,'Constr. Wage Rate Calculations'!$A$19:$Z$288,23,FALSE) -> 0 | I16: =VLOOKUP($B$11:$B$25,'Constr. Wage Rate Calculations'!$A$19:$Z$288,24,FALSE) -> 0 | J16: =VLOOKUP($B$11:$B$25,'Constr. Wage Rate Calculations'!$A$19:$Z$288,25,FALSE) -> 0 | K16: =IF($D16>=1,$J16+(D16*E16)+(F16*G16)+(H16*I16),IF($F16>=1,$J16+(D16*E16)+(F16*G16)+(H16*I16),IF($H16>=1,$J16+(D16*E16)+(F16*G16)+(H16*I16),"")))
B17: =VLOOKUP($C$11:$C$25,Personnel!$A$1:$B$1234,2,FALSE) -> 0 | E17: =VLOOKUP($B$11:$B$25,'Constr. Wage Rate Calculations'!$A$19:$Z$288,22,FALSE) -> 0 | G17: =VLOOKUP($B$11:$B$25,'Constr. Wage Rate Calculations'!$A$19:$Z$288,23,FALSE) -> 0 | I17: =VLOOKUP($B$11:$B$25,'Constr. Wage Rate Calculations'!$A$19:$Z$288,24,FALSE) -> 0 | J17: =VLOOKUP($B$11:$B$25,'Constr. Wage Rate Calculations'!$A$19:$Z$288,25,FALSE) -> 0 | K17: =IF($D17>=1,$J17+(D17*E17)+(F17*G17)+(H17*I17),IF($F17>=1,$J17+(D17*E17)+(F17*G17)+(H17*I17),IF($H17>=1,$J17+(D17*E17)+(F17*G17)+(H17*I17),"")))
B18: =VLOOKUP($C$11:$C$25,Personnel!$A$1:$B$1234,2,FALSE) -> 0 | E18: =VLOOKUP($B$11:$B$25,'Constr. Wage Rate Calculations'!$A$19:$Z$288,22,FALSE) -> 0 | G18: =VLOOKUP($B$11:$B$25,'Constr. Wage Rate Calculations'!$A$19:$Z$288,23,FALSE) -> 0 | I18: =VLOOKUP($B$11:$B$25,'Constr. Wage Rate Calculations'!$A$19:$Z$288,24,FALSE) -> 0 | J18: =VLOOKUP($B$11:$B$25,'Constr. Wage Rate Calculations'!$A$19:$Z$288,25,FALSE) -> 0 | K18: =IF($D18>=1,$J18+(D18*E18)+(F18*G18)+(H18*I18),IF($F18>=1,$J18+(D18*E18)+(F18*G18)+(H18*I18),IF($H18>=1,$J18+(D18*E18)+(F18*G18)+(H18*I18),"")))
B19: =VLOOKUP($C$11:$C$25,Personnel!$A$1:$B$1234,2,FALSE) -> 0 | E19: =VLOOKUP($B$11:$B$25,'Constr. Wage Rate Calculations'!$A$19:$Z$288,22,FALSE) -> 0 | G19: =VLOOKUP($B$11:$B$25,'Constr. Wage Rate Calculations'!$A$19:$Z$288,23,FALSE) -> 0 | I19: =VLOOKUP($B$11:$B$25,'Constr. Wage Rate Calculations'!$A$19:$Z$288,24,FALSE) -> 0 | J19: =VLOOKUP($B$11:$B$25,'Constr. Wage Rate Calculations'!$A$19:$Z$288,25,FALSE) -> 0 | K19: =IF($D19>=1,$J19+(D19*E19)+(F19*G19)+(H19*I19),IF($F19>=1,$J19+(D19*E19)+(F19*G19)+(H19*I19),IF($H19>=1,$J19+(D19*E19)+(F19*G19)+(H19*I19),"")))
B20: =VLOOKUP($C$11:$C$25,Personnel!$A$1:$B$1234,2,FALSE) -> 0 | E20: =VLOOKUP($B$11:$B$25,'Constr. Wage Rate Calculations'!$A$19:$Z$288,22,FALSE) -> 0 | G20: =VLOOKUP($B$11:$B$25,'Constr. Wage Rate Calculations'!$A$19:$Z$288,23,FALSE) -> 0 | I20: =VLOOKUP($B$11:$B$25,'Constr. Wage Rate Calculations'!$A$19:$Z$288,24,FALSE) -> 0 | J20: =VLOOKUP($B$11:$B$25,'Constr. Wage Rate Calculations'!$A$19:$Z$288,25,FALSE) -> 0 | K20: =IF($D20>=1,$J20+(D20*E20)+(F20*G20)+(H20*I20),IF($F20>=1,$J20+(D20*E20)+(F20*G20)+(H20*I20),IF($H20>=1,$J20+(D20*E20)+(F20*G20)+(H20*I20),"")))
B21: =VLOOKUP($C$11:$C$25,Personnel!$A$1:$B$1234,2,FALSE) -> 0 | E21: =VLOOKUP($B$11:$B$25,'Constr. Wage Rate Calculations'!$A$19:$Z$288,22,FALSE) -> 0 | G21: =VLOOKUP($B$11:$B$25,'Constr. Wage Rate Calculations'!$A$19:$Z$288,23,FALSE) -> 0 | I21: =VLOOKUP($B$11:$B$25,'Constr. Wage Rate Calculations'!$A$19:$Z$288,24,FALSE) -> 0 | J21: =VLOOKUP($B$11:$B$25,'Constr. Wage Rate Calculations'!$A$19:$Z$288,25,FALSE) -> 0 | K21: =IF($D21>=1,$J21+(D21*E21)+(F21*G21)+(H21*I21),IF($F21>=1,$J21+(D21*E21)+(F21*G21)+(H21*I21),IF($H21>=1,$J21+(D21*E21)+(F21*G21)+(H21*I21),"")))
B22: =VLOOKUP($C$11:$C$25,Personnel!$A$1:$B$1234,2,FALSE) -> 0 | E22: =VLOOKUP($B$11:$B$25,'Constr. Wage Rate Calculations'!$A$19:$Z$288,22,FALSE) -> 0 | G22: =VLOOKUP($B$11:$B$25,'Constr. Wage Rate Calculations'!$A$19:$Z$288,23,FALSE) -> 0 | I22: =VLOOKUP($B$11:$B$25,'Constr. Wage Rate Calculations'!$A$19:$Z$288,24,FALSE) -> 0 | J22: =VLOOKUP($B$11:$B$25,'Constr. Wage Rate Calculations'!$A$19:$Z$288,25,FALSE) -> 0 | K22: =IF($D22>=1,$J22+(D22*E22)+(F22*G22)+(H22*I22),IF($F22>=1,$J22+(D22*E22)+(F22*G22)+(H22*I22),IF($H22>=1,$J22+(D22*E22)+(F22*G22)+(H22*I22),"")))
... B24: =VLOOKUP($C$11:$C$25,Personnel!$A$1:$B$1234,2,FALSE) -> 0 | E24: =VLOOKUP($B$11:$B$25,'Constr. Wage Rate Calculations'!$A$19:$Z$288,22,FALSE) -> 0 | G24: =VLOOKUP($B$11:$B$25,'Constr. Wage Rate Calculations'!$A$19:$Z$288,23,FALSE) -> 0 | I24: =VLOOKUP($B$11:$B$25,'Constr. Wage Rate Calculations'!$A$19:$Z$288,24,FALSE) -> 0 | J24: =VLOOKUP($B$11:$B$25,'Constr. Wage Rate Calculations'!$A$19:$Z$288,25,FALSE) -> 0 | K24: =IF($D24>=1,$J24+(D24*E24)+(F24*G24)+(H24*I24),IF($F24>=1,$J24+(D24*E24)+(F24*G24)+(H24*I24),IF($H24>=1,$J24+(D24*E24)+(F24*G24)+(H24*I24),"")))
B25: =VLOOKUP($C$11:$C$25,Personnel!$A$1:$B$1234,2,FALSE) -> 0 | E25: =VLOOKUP($B$11:$B$25,'Constr. Wage Rate Calculations'!$A$19:$Z$288,22,FALSE) -> 0 | G25: =VLOOKUP($B$11:$B$25,'Constr. Wage Rate Calculations'!$A$19:$Z$288,23,FALSE) -> 0 | I25: =VLOOKUP($B$11:$B$25,'Constr. Wage Rate Calculations'!$A$19:$Z$288,24,FALSE) -> 0 | J25: =VLOOKUP($B$11:$B$25,'Constr. Wage Rate Calculations'!$A$19:$Z$288,25,FALSE) -> 0 | K25: =IF($D25>=1,$J25+(D25*E25)+(F25*G25)+(H25*I25),IF($F25>=1,$J25+(D25*E25)+(F25*G25)+(H25*I25),IF($H25>=1,$J25+(D25*E25)+(F25*G25)+(H25*I25),""))) | M25: =SUM(M11:M24) -> 0
I26: TOTAL LABOUR | K26: =SUM(K11:K25) -> 0 | M26: =SUMIFS(D11:D25,D11:D25,"<3",D11:D25,"<5") -> 0 | N26: =SUMIFS(D11:D25,D11:D25,">3",D11:D25,">5") -> 0 | O26: =SUM(F11:F25,H11:H25,M26,N26)-M25 -> 0
A28: Equipment ID | B28: Equipment | H28: Days | I28: Hrs. | J28: Rate | K28: Total
B29: =VLOOKUP($C$29:$C$42,Equipment!$A$1:$B$2322,2,FALSE) -> 0 | J29: =VLOOKUP($B$29:$B$42,'Alberta Equip. Rates Year 3'!$B$13:$K$314,10,FALSE) -> 0 | K29: =(H29+I29)*J29 -> 0
B30: =VLOOKUP($C$29:$C$42,Equipment!$A$1:$B$2322,2,FALSE) -> 0 | J30: =VLOOKUP($B$29:$B$42,'Alberta Equip. Rates Year 3'!$B$13:$K$314,10,FALSE) -> 0 | K30: =(H30+I30)*J30 -> 0
B31: =VLOOKUP($C$29:$C$42,Equipment!$A$1:$B$2322,2,FALSE) -> 0 | J31: =VLOOKUP($B$29:$B$42,'Alberta Equip. Rates Year 3'!$B$13:$K$314,10,FALSE) -> 0 | K31: =(H31+I31)*J31 -> 0
B32: =VLOOKUP($C$29:$C$42,Equipment!$A$1:$B$2322,2,FALSE) -> 0 | J32: =VLOOKUP($B$29:$B$42,'Alberta Equip. Rates Year 3'!$B$13:$K$314,10,FALSE) -> 0 | K32: =(H32+I32)*J32 -> 0
B33: =VLOOKUP($C$29:$C$42,Equipment!$A$1:$B$2322,2,FALSE) -> 0 | J33: =VLOOKUP($B$29:$B$42,'Alberta Equip. Rates Year 3'!$B$13:$K$314,10,FALSE) -> 0 | K33: =(H33+I33)*J33 -> 0
B34: =VLOOKUP($C$29:$C$42,Equipment!$A$1:$B$2322,2,FALSE) -> 0 | J34: =VLOOKUP($B$29:$B$42,'Alberta Equip. Rates Year 3'!$B$13:$K$314,10,FALSE) -> 0 | K34: =(H34+I34)*J34 -> 0
B35: =VLOOKUP($C$29:$C$42,Equipment!$A$1:$B$2322,2,FALSE) -> 0 | J35: =VLOOKUP($B$29:$B$42,'Alberta Equip. Rates Year 3'!$B$13:$K$314,10,FALSE) -> 0 | K35: =(H35+I35)*J35 -> 0
B36: =VLOOKUP($C$29:$C$42,Equipment!$A$1:$B$2322,2,FALSE) -> 0 | J36: =VLOOKUP($B$29:$B$42,'Alberta Equip. Rates Year 3'!$B$13:$K$314,10,FALSE) -> 0 | K36: =(H36+I36)*J36 -> 0
B37: =VLOOKUP($C$29:$C$42,Equipment!$A$1:$B$2322,2,FALSE) -> 0 | J37: =VLOOKUP($B$29:$B$42,'Alberta Equip. Rates Year 3'!$B$13:$K$314,10,FALSE) -> 0 | K37: =(H37+I37)*J37 -> 0
B38: =VLOOKUP($C$29:$C$42,Equipment!$A$1:$B$2322,2,FALSE) -> 0 | J38: =VLOOKUP($B$29:$B$42,'Alberta Equip. Rates Year 3'!$B$13:$K$314,10,FALSE) -> 0 | K38: =(H38+I38)*J38 -> 0
B39: =VLOOKUP($C$29:$C$42,Equipment!$A$1:$B$2322,2,FALSE) -> 0 | J39: =VLOOKUP($B$29:$B$42,'Alberta Equip. Rates Year 3'!$B$13:$K$314,10,FALSE) -> 0 | K39: =(H39+I39)*J39 -> 0
B40: =VLOOKUP($C$29:$C$42,Equipment!$A$1:$B$2322,2,FALSE) -> 0 | J40: =VLOOKUP($B$29:$B$42,'Alberta Equip. Rates Year 3'!$B$13:$K$314,10,FALSE) -> 0 | K40: =(H40+I40)*J40 -> 0
... B42: =VLOOKUP($C$29:$C$42,Equipment!$A$1:$B$2322,2,FALSE) -> 0 | J42: =VLOOKUP($B$29:$B$42,'Alberta Equip. Rates Year 3'!$B$13:$K$314,10,FALSE) -> 0 | K42: =(H42+I42)*J42 -> 0
I43: TOTAL EQUIPMENT | K43: =SUM(K29:K42) -> 0
A45: Scope of Work: | I45: LABOUR | K45: =K26 -> 0
I46: EQUIPMENT | K46: =K43 -> 0
I47: SMALL TOOLS | K47: =(O26)*14.15 -> 0
I48: MATERIALS
I49: TRUCKING
I50: SUBCONTRACTORS
I51: FIELD LOG TOTAL* | K51: =SUM(K45:K50) -> 0
A53: Client: | H53: Company Representitive:
A55: * Field Log Total does no include markups
A56: 41218.479

Sheet Field Log (44)
J1: Date:
G6: Field Log ID: | J6: Status:
A7: Address: | G7: Account #: | J7: Account:
G8: Foreman:
A10: Employee ID | B10: Labor Type | C10: Employee | D10: RT Hours | E10: RT Rate | F10: OT Hours | G10: OT Rate | H10: DT Hours | I10: DT Rate | J10: Sub. | K10: Total | M10: Additional Hours
B11: =VLOOKUP($C$11:$C$25,Personnel!$A$1:$B$1234,2,FALSE) -> 0 | E11: =VLOOKUP($B$11:$B$25,'Constr. Wage Rate Calculations'!$A$19:$Z$288,22,FALSE) -> 0 | G11: =VLOOKUP($B$11:$B$25,'Constr. Wage Rate Calculations'!$A$19:$Z$288,23,FALSE) -> 0 | I11: =VLOOKUP($B$11:$B$25,'Constr. Wage Rate Calculations'!$A$19:$Z$288,24,FALSE) -> 0 | J11: =VLOOKUP($B$11:$B$25,'Constr. Wage Rate Calculations'!$A$19:$Z$288,25,FALSE) -> 0 | K11: =IF($D11>=1,$J11+(D11*E11)+(F11*G11)+(H11*I11),IF($F11>=1,$J11+(D11*E11)+(F11*G11)+(H11*I11),IF($H11>=1,$J11+(D11*E11)+(F11*G11)+(H11*I11),"")))
B12: =VLOOKUP($C$11:$C$25,Personnel!$A$1:$B$1234,2,FALSE) -> 0 | E12: =VLOOKUP($B$11:$B$25,'Constr. Wage Rate Calculations'!$A$19:$Z$288,22,FALSE) -> 0 | G12: =VLOOKUP($B$11:$B$25,'Constr. Wage Rate Calculations'!$A$19:$Z$288,23,FALSE) -> 0 | I12: =VLOOKUP($B$11:$B$25,'Constr. Wage Rate Calculations'!$A$19:$Z$288,24,FALSE) -> 0 | J12: =VLOOKUP($B$11:$B$25,'Constr. Wage Rate Calculations'!$A$19:$Z$288,25,FALSE) -> 0 | K12: =IF($D12>=1,$J12+(D12*E12)+(F12*G12)+(H12*I12),IF($F12>=1,$J12+(D12*E12)+(F12*G12)+(H12*I12),IF($H12>=1,$J12+(D12*E12)+(F12*G12)+(H12*I12),"")))
B13: =VLOOKUP($C$11:$C$25,Personnel!$A$1:$B$1234,2,FALSE) -> 0 | E13: =VLOOKUP($B$11:$B$25,'Constr. Wage Rate Calculations'!$A$19:$Z$288,22,FALSE) -> 0 | G13: =VLOOKUP($B$11:$B$25,'Constr. Wage Rate Calculations'!$A$19:$Z$288,23,FALSE) -> 0 | I13: =VLOOKUP($B$11:$B$25,'Constr. Wage Rate Calculations'!$A$19:$Z$288,24,FALSE) -> 0 | J13: =VLOOKUP($B$11:$B$25,'Constr. Wage Rate Calculations'!$A$19:$Z$288,25,FALSE) -> 0 | K13: =IF($D13>=1,$J13+(D13*E13)+(F13*G13)+(H13*I13),IF($F13>=1,$J13+(D13*E13)+(F13*G13)+(H13*I13),IF($H13>=1,$J13+(D13*E13)+(F13*G13)+(H13*I13),"")))
B14: =VLOOKUP($C$11:$C$25,Personnel!$A$1:$B$1234,2,FALSE) -> 0 | E14: =VLOOKUP($B$11:$B$25,'Constr. Wage Rate Calculations'!$A$19:$Z$288,22,FALSE) -> 0 | G14: =VLOOKUP($B$11:$B$25,'Constr. Wage Rate Calculations'!$A$19:$Z$288,23,FALSE) -> 0 | I14: =VLOOKUP($B$11:$B$25,'Constr. Wage Rate Calculations'!$A$19:$Z$288,24,FALSE) -> 0 | J14: =VLOOKUP($B$11:$B$25,'Constr. Wage Rate Calculations'!$A$19:$Z$288,25,FALSE) -> 0 | K14: =IF($D14>=1,$J14+(D14*E14)+(F14*G14)+(H14*I14),IF($F14>=1,$J14+(D14*E14)+(F14*G14)+(H14*I14),IF($H14>=1,$J14+(D14*E14)+(F14*G14)+(H14*I14),"")))
B15: =VLOOKUP($C$11:$C$25,Personnel!$A$1:$B$1234,2,FALSE) -> 0 | E15: =VLOOKUP($B$11:$B$25,'Constr. Wage Rate Calculations'!$A$19:$Z$288,22,FALSE) -> 0 | G15: =VLOOKUP($B$11:$B$25,'Constr. Wage Rate Calculations'!$A$19:$Z$288,23,FALSE) -> 0 | I15: =VLOOKUP($B$11:$B$25,'Constr. Wage Rate Calculations'!$A$19:$Z$288,24,FALSE) -> 0 | J15: =VLOOKUP($B$11:$B$25,'Constr. Wage Rate Calculations'!$A$19:$Z$288,25,FALSE) -> 0 | K15: =IF($D15>=1,$J15+(D15*E15)+(F15*G15)+(H15*I15),IF($F15>=1,$J15+(D15*E15)+(F15*G15)+(H15*I15),IF($H15>=1,$J15+(D15*E15)+(F15*G15)+(H15*I15),"")))
B16: =VLOOKUP($C$11:$C$25,Personnel!$A$1:$B$1234,2,FALSE) -> 0 | E16: =VLOOKUP($B$11:$B$25,'Constr. Wage Rate Calculations'!$A$19:$Z$288,22,FALSE) -> 0 | G16: =VLOOKUP($B$11:$B$25,'Constr. Wage Rate Calculations'!$A$19:$Z$288,23,FALSE) -> 0 | I16: =VLOOKUP($B$11:$B$25,'Constr. Wage Rate Calculations'!$A$19:$Z$288,24,FALSE) -> 0 | J16: =VLOOKUP($B$11:$B$25,'Constr. Wage Rate Calculations'!$A$19:$Z$288,25,FALSE) -> 0 | K16: =IF($D16>=1,$J16+(D16*E16)+(F16*G16)+(H16*I16),IF($F16>=1,$J16+(D16*E16)+(F16*G16)+(H16*I16),IF($H16>=1,$J16+(D16*E16)+(F16*G16)+(H16*I16),"")))
B17: =VLOOKUP($C$11:$C$25,Personnel!$A$1:$B$1234,2,FALSE) -> 0 | E17: =VLOOKUP($B$11:$B$25,'Constr. Wage Rate Calculations'!$A$19:$Z$288,22,FALSE) -> 0 | G17: =VLOOKUP($B$11:$B$25,'Constr. Wage Rate Calculations'!$A$19:$Z$288,23,FALSE) -> 0 | I17: =VLOOKUP($B$11:$B$25,'Constr. Wage Rate Calculations'!$A$19:$Z$288,24,FALSE) -> 0 | J17: =VLOOKUP($B$11:$B$25,'Constr. Wage Rate Calculations'!$A$19:$Z$288,25,FALSE) -> 0 | K17: =IF($D17>=1,$J17+(D17*E17)+(F17*G17)+(H17*I17),IF($F17>=1,$J17+(D17*E17)+(F17*G17)+(H17*I17),IF($H17>=1,$J17+(D17*E17)+(F17*G17)+(H17*I17),"")))
B18: =VLOOKUP($C$11:$C$25,Personnel!$A$1:$B$1234,2,FALSE) -> 0 | E18: =VLOOKUP($B$11:$B$25,'Constr. Wage Rate Calculations'!$A$19:$Z$288,22,FALSE) -> 0 | G18: =VLOOKUP($B$11:$B$25,'Constr. Wage Rate Calculations'!$A$19:$Z$288,23,FALSE) -> 0 | I18: =VLOOKUP($B$11:$B$25,'Constr. Wage Rate Calculations'!$A$19:$Z$288,24,FALSE) -> 0 | J18: =VLOOKUP($B$11:$B$25,'Constr. Wage Rate Calculations'!$A$19:$Z$288,25,FALSE) -> 0 | K18: =IF($D18>=1,$J18+(D18*E18)+(F18*G18)+(H18*I18),IF($F18>=1,$J18+(D18*E18)+(F18*G18)+(H18*I18),IF($H18>=1,$J18+(D18*E18)+(F18*G18)+(H18*I18),"")))
B19: =VLOOKUP($C$11:$C$25,Personnel!$A$1:$B$1234,2,FALSE) -> 0 | E19: =VLOOKUP($B$11:$B$25,'Constr. Wage Rate Calculations'!$A$19:$Z$288,22,FALSE) -> 0 | G19: =VLOOKUP($B$11:$B$25,'Constr. Wage Rate Calculations'!$A$19:$Z$288,23,FALSE) -> 0 | I19: =VLOOKUP($B$11:$B$25,'Constr. Wage Rate Calculations'!$A$19:$Z$288,24,FALSE) -> 0 | J19: =VLOOKUP($B$11:$B$25,'Constr. Wage Rate Calculations'!$A$19:$Z$288,25,FALSE) -> 0 | K19: =IF($D19>=1,$J19+(D19*E19)+(F19*G19)+(H19*I19),IF($F19>=1,$J19+(D19*E19)+(F19*G19)+(H19*I19),IF($H19>=1,$J19+(D19*E19)+(F19*G19)+(H19*I19),"")))
B20: =VLOOKUP($C$11:$C$25,Personnel!$A$1:$B$1234,2,FALSE) -> 0 | E20: =VLOOKUP($B$11:$B$25,'Constr. Wage Rate Calculations'!$A$19:$Z$288,22,FALSE) -> 0 | G20: =VLOOKUP($B$11:$B$25,'Constr. Wage Rate Calculations'!$A$19:$Z$288,23,FALSE) -> 0 | I20: =VLOOKUP($B$11:$B$25,'Constr. Wage Rate Calculations'!$A$19:$Z$288,24,FALSE) -> 0 | J20: =VLOOKUP($B$11:$B$25,'Constr. Wage Rate Calculations'!$A$19:$Z$288,25,FALSE) -> 0 | K20: =IF($D20>=1,$J20+(D20*E20)+(F20*G20)+(H20*I20),IF($F20>=1,$J20+(D20*E20)+(F20*G20)+(H20*I20),IF($H20>=1,$J20+(D20*E20)+(F20*G20)+(H20*I20),"")))
B21: =VLOOKUP($C$11:$C$25,Personnel!$A$1:$B$1234,2,FALSE) -> 0 | E21: =VLOOKUP($B$11:$B$25,'Constr. Wage Rate Calculations'!$A$19:$Z$288,22,FALSE) -> 0 | G21: =VLOOKUP($B$11:$B$25,'Constr. Wage Rate Calculations'!$A$19:$Z$288,23,FALSE) -> 0 | I21: =VLOOKUP($B$11:$B$25,'Constr. Wage Rate Calculations'!$A$19:$Z$288,24,FALSE) -> 0 | J21: =VLOOKUP($B$11:$B$25,'Constr. Wage Rate Calculations'!$A$19:$Z$288,25,FALSE) -> 0 | K21: =IF($D21>=1,$J21+(D21*E21)+(F21*G21)+(H21*I21),IF($F21>=1,$J21+(D21*E21)+(F21*G21)+(H21*I21),IF($H21>=1,$J21+(D21*E21)+(F21*G21)+(H21*I21),"")))
B22: =VLOOKUP($C$11:$C$25,Personnel!$A$1:$B$1234,2,FALSE) -> 0 | E22: =VLOOKUP($B$11:$B$25,'Constr. Wage Rate Calculations'!$A$19:$Z$288,22,FALSE) -> 0 | G22: =VLOOKUP($B$11:$B$25,'Constr. Wage Rate Calculations'!$A$19:$Z$288,23,FALSE) -> 0 | I22: =VLOOKUP($B$11:$B$25,'Constr. Wage Rate Calculations'!$A$19:$Z$288,24,FALSE) -> 0 | J22: =VLOOKUP($B$11:$B$25,'Constr. Wage Rate Calculations'!$A$19:$Z$288,25,FALSE) -> 0 | K22: =IF($D22>=1,$J22+(D22*E22)+(F22*G22)+(H22*I22),IF($F22>=1,$J22+(D22*E22)+(F22*G22)+(H22*I22),IF($H22>=1,$J22+(D22*E22)+(F22*G22)+(H22*I22),"")))
... B24: =VLOOKUP($C$11:$C$25,Personnel!$A$1:$B$1234,2,FALSE) -> 0 | E24: =VLOOKUP($B$11:$B$25,'Constr. Wage Rate Calculations'!$A$19:$Z$288,22,FALSE) -> 0 | G24: =VLOOKUP($B$11:$B$25,'Constr. Wage Rate Calculations'!$A$19:$Z$288,23,FALSE) -> 0 | I24: =VLOOKUP($B$11:$B$25,'Constr. Wage Rate Calculations'!$A$19:$Z$288,24,FALSE) -> 0 | J24: =VLOOKUP($B$11:$B$25,'Constr. Wage Rate Calculations'!$A$19:$Z$288,25,FALSE) -> 0 | K24: =IF($D24>=1,$J24+(D24*E24)+(F24*G24)+(H24*I24),IF($F24>=1,$J24+(D24*E24)+(F24*G24)+(H24*I24),IF($H24>=1,$J24+(D24*E24)+(F24*G24)+(H24*I24),"")))
B25: =VLOOKUP($C$11:$C$25,Personnel!$A$1:$B$1234,2,FALSE) -> 0 | E25: =VLOOKUP($B$11:$B$25,'Constr. Wage Rate Calculations'!$A$19:$Z$288,22,FALSE) -> 0 | G25: =VLOOKUP($B$11:$B$25,'Constr. Wage Rate Calculations'!$A$19:$Z$288,23,FALSE) -> 0 | I25: =VLOOKUP($B$11:$B$25,'Constr. Wage Rate Calculations'!$A$19:$Z$288,24,FALSE) -> 0 | J25: =VLOOKUP($B$11:$B$25,'Constr. Wage Rate Calculations'!$A$19:$Z$288,25,FALSE) -> 0 | K25: =IF($D25>=1,$J25+(D25*E25)+(F25*G25)+(H25*I25),IF($F25>=1,$J25+(D25*E25)+(F25*G25)+(H25*I25),IF($H25>=1,$J25+(D25*E25)+(F25*G25)+(H25*I25),""))) | M25: =SUM(M11:M24) -> 0
I26: TOTAL LABOUR | K26: =SUM(K11:K25) -> 0 | M26: =SUMIFS(D11:D25,D11:D25,"<3",D11:D25,"<5") -> 0 | N26: =SUMIFS(D11:D25,D11:D25,">3",D11:D25,">5") -> 0 | O26: =SUM(F11:F25,H11:H25,M26,N26)-M25 -> 0
A28: Equipment ID | B28: Equipment | H28: Days | I28: Hrs. | J28: Rate | K28: Total
B29: =VLOOKUP($C$29:$C$42,Equipment!$A$1:$B$2322,2,FALSE) -> 0 | J29: =VLOOKUP($B$29:$B$42,'Alberta Equip. Rates Year 3'!$B$13:$K$314,10,FALSE) -> 0 | K29: =(H29+I29)*J29 -> 0
B30: =VLOOKUP($C$29:$C$42,Equipment!$A$1:$B$2322,2,FALSE) -> 0 | J30: =VLOOKUP($B$29:$B$42,'Alberta Equip. Rates Year 3'!$B$13:$K$314,10,FALSE) -> 0 | K30: =(H30+I30)*J30 -> 0
B31: =VLOOKUP($C$29:$C$42,Equipment!$A$1:$B$2322,2,FALSE) -> 0 | J31: =VLOOKUP($B$29:$B$42,'Alberta Equip. Rates Year 3'!$B$13:$K$314,10,FALSE) -> 0 | K31: =(H31+I31)*J31 -> 0
B32: =VLOOKUP($C$29:$C$42,Equipment!$A$1:$B$2322,2,FALSE) -> 0 | J32: =VLOOKUP($B$29:$B$42,'Alberta Equip. Rates Year 3'!$B$13:$K$314,10,FALSE) -> 0 | K32: =(H32+I32)*J32 -> 0
B33: =VLOOKUP($C$29:$C$42,Equipment!$A$1:$B$2322,2,FALSE) -> 0 | J33: =VLOOKUP($B$29:$B$42,'Alberta Equip. Rates Year 3'!$B$13:$K$314,10,FALSE) -> 0 | K33: =(H33+I33)*J33 -> 0
B34: =VLOOKUP($C$29:$C$42,Equipment!$A$1:$B$2322,2,FALSE) -> 0 | J34: =VLOOKUP($B$29:$B$42,'Alberta Equip. Rates Year 3'!$B$13:$K$314,10,FALSE) -> 0 | K34: =(H34+I34)*J34 -> 0
B35: =VLOOKUP($C$29:$C$42,Equipment!$A$1:$B$2322,2,FALSE) -> 0 | J35: =VLOOKUP($B$29:$B$42,'Alberta Equip. Rates Year 3'!$B$13:$K$314,10,FALSE) -> 0 | K35: =(H35+I35)*J35 -> 0
B36: =VLOOKUP($C$29:$C$42,Equipment!$A$1:$B$2322,2,FALSE) -> 0 | J36: =VLOOKUP($B$29:$B$42,'Alberta Equip. Rates Year 3'!$B$13:$K$314,10,FALSE) -> 0 | K36: =(H36+I36)*J36 -> 0
B37: =VLOOKUP($C$29:$C$42,Equipment!$A$1:$B$2322,2,FALSE) -> 0 | J37: =VLOOKUP($B$29:$B$42,'Alberta Equip. Rates Year 3'!$B$13:$K$314,10,FALSE) -> 0 | K37: =(H37+I37)*J37 -> 0
B38: =VLOOKUP($C$29:$C$42,Equipment!$A$1:$B$2322,2,FALSE) -> 0 | J38: =VLOOKUP($B$29:$B$42,'Alberta Equip. Rates Year 3'!$B$13:$K$314,10,FALSE) -> 0 | K38: =(H38+I38)*J38 -> 0
B39: =VLOOKUP($C$29:$C$42,Equipment!$A$1:$B$2322,2,FALSE) -> 0 | J39: =VLOOKUP($B$29:$B$42,'Alberta Equip. Rates Year 3'!$B$13:$K$314,10,FALSE) -> 0 | K39: =(H39+I39)*J39 -> 0
B40: =VLOOKUP($C$29:$C$42,Equipment!$A$1:$B$2322,2,FALSE) -> 0 | J40: =VLOOKUP($B$29:$B$42,'Alberta Equip. Rates Year 3'!$B$13:$K$314,10,FALSE) -> 0 | K40: =(H40+I40)*J40 -> 0
... B42: =VLOOKUP($C$29:$C$42,Equipment!$A$1:$B$2322,2,FALSE) -> 0 | J42: =VLOOKUP($B$29:$B$42,'Alberta Equip. Rates Year 3'!$B$13:$K$314,10,FALSE) -> 0 | K42: =(H42+I42)*J42 -> 0
I43: TOTAL EQUIPMENT | K43: =SUM(K29:K42) -> 0
A45: Scope of Work: | I45: LABOUR | K45: =K26 -> 0
I46: EQUIPMENT | K46: =K43 -> 0
I47: SMALL TOOLS | K47: =(O26)*14.15 -> 0
I48: MATERIALS
I49: TRUCKING
I50: SUBCONTRACTORS
I51: FIELD LOG TOTAL* | K51: =SUM(K45:K50) -> 0
A53: Client: | H53: Company Representitive:
A55: * Field Log Total does no include markups
A56: 41218.479

Sheet Field Log (43)
J1: Date:
G6: Field Log ID: | J6: Status:
A7: Address: | G7: Account #: | J7: Account:
G8: Foreman:
A10: Employee ID | B10: Labor Type | C10: Employee | D10: RT Hours | E10: RT Rate | F10: OT Hours | G10: OT Rate | H10: DT Hours | I10: DT Rate | J10: Sub. | K10: Total | M10: Additional Hours
B11: =VLOOKUP($C$11:$C$25,Personnel!$A$1:$B$1234,2,FALSE) -> 0 | E11: =VLOOKUP($B$11:$B$25,'Constr. Wage Rate Calculations'!$A$19:$Z$288,22,FALSE) -> 0 | G11: =VLOOKUP($B$11:$B$25,'Constr. Wage Rate Calculations'!$A$19:$Z$288,23,FALSE) -> 0 | I11: =VLOOKUP($B$11:$B$25,'Constr. Wage Rate Calculations'!$A$19:$Z$288,24,FALSE) -> 0 | J11: =VLOOKUP($B$11:$B$25,'Constr. Wage Rate Calculations'!$A$19:$Z$288,25,FALSE) -> 0 | K11: =IF($D11>=1,$J11+(D11*E11)+(F11*G11)+(H11*I11),IF($F11>=1,$J11+(D11*E11)+(F11*G11)+(H11*I11),IF($H11>=1,$J11+(D11*E11)+(F11*G11)+(H11*I11),"")))
B12: =VLOOKUP($C$11:$C$25,Personnel!$A$1:$B$1234,2,FALSE) -> 0 | E12: =VLOOKUP($B$11:$B$25,'Constr. Wage Rate Calculations'!$A$19:$Z$288,22,FALSE) -> 0 | G12: =VLOOKUP($B$11:$B$25,'Constr. Wage Rate Calculations'!$A$19:$Z$288,23,FALSE) -> 0 | I12: =VLOOKUP($B$11:$B$25,'Constr. Wage Rate Calculations'!$A$19:$Z$288,24,FALSE) -> 0 | K12: =IF($D12>=1,$J12+(D12*E12)+(F12*G12)+(H12*I12),IF($F12>=1,$J12+(D12*E12)+(F12*G12)+(H12*I12),IF($H12>=1,$J12+(D12*E12)+(F12*G12)+(H12*I12),"")))
B13: =VLOOKUP($C$11:$C$25,Personnel!$A$1:$B$1234,2,FALSE) -> 0 | E13: =VLOOKUP($B$11:$B$25,'Constr. Wage Rate Calculations'!$A$19:$Z$288,22,FALSE) -> 0 | G13: =VLOOKUP($B$11:$B$25,'Constr. Wage Rate Calculations'!$A$19:$Z$288,23,FALSE) -> 0 | I13: =VLOOKUP($B$11:$B$25,'Constr. Wage Rate Calculations'!$A$19:$Z$288,24,FALSE) -> 0 | J13: =VLOOKUP($B$11:$B$25,'Constr. Wage Rate Calculations'!$A$19:$Z$288,25,FALSE) -> 0 | K13: =IF($D13>=1,$J13+(D13*E13)+(F13*G13)+(H13*I13),IF($F13>=1,$J13+(D13*E13)+(F13*G13)+(H13*I13),IF($H13>=1,$J13+(D13*E13)+(F13*G13)+(H13*I13),"")))
B14: =VLOOKUP($C$11:$C$25,Personnel!$A$1:$B$1234,2,FALSE) -> 0 | E14: =VLOOKUP($B$11:$B$25,'Constr. Wage Rate Calculations'!$A$19:$Z$288,22,FALSE) -> 0 | G14: =VLOOKUP($B$11:$B$25,'Constr. Wage Rate Calculations'!$A$19:$Z$288,23,FALSE) -> 0 | I14: =VLOOKUP($B$11:$B$25,'Constr. Wage Rate Calculations'!$A$19:$Z$288,24,FALSE) -> 0 | J14: =VLOOKUP($B$11:$B$25,'Constr. Wage Rate Calculations'!$A$19:$Z$288,25,FALSE) -> 0 | K14: =IF($D14>=1,$J14+(D14*E14)+(F14*G14)+(H14*I14),IF($F14>=1,$J14+(D14*E14)+(F14*G14)+(H14*I14),IF($H14>=1,$J14+(D14*E14)+(F14*G14)+(H14*I14),"")))
B15: =VLOOKUP($C$11:$C$25,Personnel!$A$1:$B$1234,2,FALSE) -> 0 | E15: =VLOOKUP($B$11:$B$25,'Constr. Wage Rate Calculations'!$A$19:$Z$288,22,FALSE) -> 0 | G15: =VLOOKUP($B$11:$B$25,'Constr. Wage Rate Calculations'!$A$19:$Z$288,23,FALSE) -> 0 | I15: =VLOOKUP($B$11:$B$25,'Constr. Wage Rate Calculations'!$A$19:$Z$288,24,FALSE) -> 0 | J15: =VLOOKUP($B$11:$B$25,'Constr. Wage Rate Calculations'!$A$19:$Z$288,25,FALSE) -> 0 | K15: =IF($D15>=1,$J15+(D15*E15)+(F15*G15)+(H15*I15),IF($F15>=1,$J15+(D15*E15)+(F15*G15)+(H15*I15),IF($H15>=1,$J15+(D15*E15)+(F15*G15)+(H15*I15),"")))
B16: =VLOOKUP($C$11:$C$25,Personnel!$A$1:$B$1234,2,FALSE) -> 0 | E16: =VLOOKUP($B$11:$B$25,'Constr. Wage Rate Calculations'!$A$19:$Z$288,22,FALSE) -> 0 | G16: =VLOOKUP($B$11:$B$25,'Constr. Wage Rate Calculations'!$A$19:$Z$288,23,FALSE) -> 0 | I16: =VLOOKUP($B$11:$B$25,'Constr. Wage Rate Calculations'!$A$19:$Z$288,24,FALSE) -> 0 | J16: =VLOOKUP($B$11:$B$25,'Constr. Wage Rate Calculations'!$A$19:$Z$288,25,FALSE) -> 0 | K16: =IF($D16>=1,$J16+(D16*E16)+(F16*G16)+(H16*I16),IF($F16>=1,$J16+(D16*E16)+(F16*G16)+(H16*I16),IF($H16>=1,$J16+(D16*E16)+(F16*G16)+(H16*I16),"")))
B17: =VLOOKUP($C$11:$C$25,Personnel!$A$1:$B$1234,2,FALSE) -> 0 | E17: =VLOOKUP($B$11:$B$25,'Constr. Wage Rate Calculations'!$A$19:$Z$288,22,FALSE) -> 0 | G17: =VLOOKUP($B$11:$B$25,'Constr. Wage Rate Calculations'!$A$19:$Z$288,23,FALSE) -> 0 | I17: =VLOOKUP($B$11:$B$25,'Constr. Wage Rate Calculations'!$A$19:$Z$288,24,FALSE) -> 0 | J17: =VLOOKUP($B$11:$B$25,'Constr. Wage Rate Calculations'!$A$19:$Z$288,25,FALSE) -> 0 | K17: =IF($D17>=1,$J17+(D17*E17)+(F17*G17)+(H17*I17),IF($F17>=1,$J17+(D17*E17)+(F17*G17)+(H17*I17),IF($H17>=1,$J17+(D17*E17)+(F17*G17)+(H17*I17),"")))
B18: =VLOOKUP($C$11:$C$25,Personnel!$A$1:$B$1234,2,FALSE) -> 0 | E18: =VLOOKUP($B$11:$B$25,'Constr. Wage Rate Calculations'!$A$19:$Z$288,22,FALSE) -> 0 | G18: =VLOOKUP($B$11:$B$25,'Constr. Wage Rate Calculations'!$A$19:$Z$288,23,FALSE) -> 0 | I18: =VLOOKUP($B$11:$B$25,'Constr. Wage Rate Calculations'!$A$19:$Z$288,24,FALSE) -> 0 | J18: =VLOOKUP($B$11:$B$25,'Constr. Wage Rate Calculations'!$A$19:$Z$288,25,FALSE) -> 0 | K18: =IF($D18>=1,$J18+(D18*E18)+(F18*G18)+(H18*I18),IF($F18>=1,$J18+(D18*E18)+(F18*G18)+(H18*I18),IF($H18>=1,$J18+(D18*E18)+(F18*G18)+(H18*I18),"")))
B19: =VLOOKUP($C$11:$C$25,Personnel!$A$1:$B$1234,2,FALSE) -> 0 | E19: =VLOOKUP($B$11:$B$25,'Constr. Wage Rate Calculations'!$A$19:$Z$288,22,FALSE) -> 0 | G19: =VLOOKUP($B$11:$B$25,'Constr. Wage Rate Calculations'!$A$19:$Z$288,23,FALSE) -> 0 | I19: =VLOOKUP($B$11:$B$25,'Constr. Wage Rate Calculations'!$A$19:$Z$288,24,FALSE) -> 0 | J19: =VLOOKUP($B$11:$B$25,'Constr. Wage Rate Calculations'!$A$19:$Z$288,25,FALSE) -> 0 | K19: =IF($D19>=1,$J19+(D19*E19)+(F19*G19)+(H19*I19),IF($F19>=1,$J19+(D19*E19)+(F19*G19)+(H19*I19),IF($H19>=1,$J19+(D19*E19)+(F19*G19)+(H19*I19),"")))
B20: =VLOOKUP($C$11:$C$25,Personnel!$A$1:$B$1234,2,FALSE) -> 0 | E20: =VLOOKUP($B$11:$B$25,'Constr. Wage Rate Calculations'!$A$19:$Z$288,22,FALSE) -> 0 | G20: =VLOOKUP($B$11:$B$25,'Constr. Wage Rate Calculations'!$A$19:$Z$288,23,FALSE) -> 0 | I20: =VLOOKUP($B$11:$B$25,'Constr. Wage Rate Calculations'!$A$19:$Z$288,24,FALSE) -> 0 | J20: =VLOOKUP($B$11:$B$25,'Constr. Wage Rate Calculations'!$A$19:$Z$288,25,FALSE) -> 0 | K20: =IF($D20>=1,$J20+(D20*E20)+(F20*G20)+(H20*I20),IF($F20>=1,$J20+(D20*E20)+(F20*G20)+(H20*I20),IF($H20>=1,$J20+(D20*E20)+(F20*G20)+(H20*I20),"")))
B21: =VLOOKUP($C$11:$C$25,Personnel!$A$1:$B$1234,2,FALSE) -> 0 | E21: =VLOOKUP($B$11:$B$25,'Constr. Wage Rate Calculations'!$A$19:$Z$288,22,FALSE) -> 0 | G21: =VLOOKUP($B$11:$B$25,'Constr. Wage Rate Calculations'!$A$19:$Z$288,23,FALSE) -> 0 | I21: =VLOOKUP($B$11:$B$25,'Constr. Wage Rate Calculations'!$A$19:$Z$288,24,FALSE) -> 0 | J21: =VLOOKUP($B$11:$B$25,'Constr. Wage Rate Calculations'!$A$19:$Z$288,25,FALSE) -> 0 | K21: =IF($D21>=1,$J21+(D21*E21)+(F21*G21)+(H21*I21),IF($F21>=1,$J21+(D21*E21)+(F21*G21)+(H21*I21),IF($H21>=1,$J21+(D21*E21)+(F21*G21)+(H21*I21),"")))
B22: =VLOOKUP($C$11:$C$25,Personnel!$A$1:$B$1234,2,FALSE) -> 0 | E22: =VLOOKUP($B$11:$B$25,'Constr. Wage Rate Calculations'!$A$19:$Z$288,22,FALSE) -> 0 | G22: =VLOOKUP($B$11:$B$25,'Constr. Wage Rate Calculations'!$A$19:$Z$288,23,FALSE) -> 0 | I22: =VLOOKUP($B$11:$B$25,'Constr. Wage Rate Calculations'!$A$19:$Z$288,24,FALSE) -> 0 | J22: =VLOOKUP($B$11:$B$25,'Constr. Wage Rate Calculations'!$A$19:$Z$288,25,FALSE) -> 0 | K22: =IF($D22>=1,$J22+(D22*E22)+(F22*G22)+(H22*I22),IF($F22>=1,$J22+(D22*E22)+(F22*G22)+(H22*I22),IF($H22>=1,$J22+(D22*E22)+(F22*G22)+(H22*I22),"")))
B23: =VLOOKUP($C$11:$C$25,Personnel!$A$1:$B$1234,2,FALSE) -> 0 | E23: =VLOOKUP($B$11:$B$25,'Constr. Wage Rate Calculations'!$A$19:$Z$288,22,FALSE) -> 0 | G23: =VLOOKUP($B$11:$B$25,'Constr. Wage Rate Calculations'!$A$19:$Z$288,23,FALSE) -> 0 | I23: =VLOOKUP($B$11:$B$25,'Constr. Wage Rate Calculations'!$A$19:$Z$288,24,FALSE) -> 0 | J23: =VLOOKUP($B$11:$B$25,'Constr. Wage Rate Calculations'!$A$19:$Z$288,25,FALSE) -> 0 | K23: =IF($D23>=1,$J23+(D23*E23)+(F23*G23)+(H23*I23),IF($F23>=1,$J23+(D23*E23)+(F23*G23)+(H23*I23),IF($H23>=1,$J23+(D23*E23)+(F23*G23)+(H23*I23),"")))
B24: =VLOOKUP($C$11:$C$25,Personnel!$A$1:$B$1234,2,FALSE) -> 0 | E24: =VLOOKUP($B$11:$B$25,'Constr. Wage Rate Calculations'!$A$19:$Z$288,22,FALSE) -> 0 | G24: =VLOOKUP($B$11:$B$25,'Constr. Wage Rate Calculations'!$A$19:$Z$288,23,FALSE) -> 0 | I24: =VLOOKUP($B$11:$B$25,'Constr. Wage Rate Calculations'!$A$19:$Z$288,24,FALSE) -> 0 | J24: =VLOOKUP($B$11:$B$25,'Constr. Wage Rate Calculations'!$A$19:$Z$288,25,FALSE) -> 0 | K24: =IF($D24>=1,$J24+(D24*E24)+(F24*G24)+(H24*I24),IF($F24>=1,$J24+(D24*E24)+(F24*G24)+(H24*I24),IF($H24>=1,$J24+(D24*E24)+(F24*G24)+(H24*I24),"")))
B25: =VLOOKUP($C$11:$C$25,Personnel!$A$1:$B$1234,2,FALSE) -> 0 | E25: =VLOOKUP($B$11:$B$25,'Constr. Wage Rate Calculations'!$A$19:$Z$288,22,FALSE) -> 0 | G25: =VLOOKUP($B$11:$B$25,'Constr. Wage Rate Calculations'!$A$19:$Z$288,23,FALSE) -> 0 | I25: =VLOOKUP($B$11:$B$25,'Constr. Wage Rate Calculations'!$A$19:$Z$288,24,FALSE) -> 0 | J25: =VLOOKUP($B$11:$B$25,'Constr. Wage Rate Calculations'!$A$19:$Z$288,25,FALSE) -> 0 | K25: =IF($D25>=1,$J25+(D25*E25)+(F25*G25)+(H25*I25),IF($F25>=1,$J25+(D25*E25)+(F25*G25)+(H25*I25),IF($H25>=1,$J25+(D25*E25)+(F25*G25)+(H25*I25),""))) | M25: =SUM(M11:M24) -> 0
I26: TOTAL LABOUR | K26: =SUM(K11:K25) -> 0 | M26: =SUMIFS(D11:D25,D11:D25,"<3",D11:D25,"<5") -> 0 | N26: =SUMIFS(D11:D25,D11:D25,">3",D11:D25,">5") -> 0 | O26: =SUM(F11:F25,H11:H25,M26,N26)-M25 -> 0
A28: Equipment ID | B28: Equipment | H28: Days | I28: Hrs. | J28: Rate | K28: Total
B29: =VLOOKUP($C$29:$C$42,Equipment!$A$1:$B$2322,2,FALSE) -> 0 | J29: =VLOOKUP($B$29:$B$42,'Alberta Equip. Rates Year 3'!$B$13:$K$314,10,FALSE) -> 0 | K29: =(H29+I29)*J29 -> 0
B30: =VLOOKUP($C$29:$C$42,Equipment!$A$1:$B$2322,2,FALSE) -> 0 | J30: =VLOOKUP($B$29:$B$42,'Alberta Equip. Rates Year 3'!$B$13:$K$314,10,FALSE) -> 0 | K30: =(H30+I30)*J30 -> 0
B31: =VLOOKUP($C$29:$C$42,Equipment!$A$1:$B$2322,2,FALSE) -> 0 | J31: =VLOOKUP($B$29:$B$42,'Alberta Equip. Rates Year 3'!$B$13:$K$314,10,FALSE) -> 0 | K31: =(H31+I31)*J31 -> 0
B32: =VLOOKUP($C$29:$C$42,Equipment!$A$1:$B$2322,2,FALSE) -> 0 | J32: =VLOOKUP($B$29:$B$42,'Alberta Equip. Rates Year 3'!$B$13:$K$314,10,FALSE) -> 0 | K32: =(H32+I32)*J32 -> 0
B33: =VLOOKUP($C$29:$C$42,Equipment!$A$1:$B$2322,2,FALSE) -> 0 | J33: =VLOOKUP($B$29:$B$42,'Alberta Equip. Rates Year 3'!$B$13:$K$314,10,FALSE) -> 0 | K33: =(H33+I33)*J33 -> 0
B34: =VLOOKUP($C$29:$C$42,Equipment!$A$1:$B$2322,2,FALSE) -> 0 | J34: =VLOOKUP($B$29:$B$42,'Alberta Equip. Rates Year 3'!$B$13:$K$314,10,FALSE) -> 0 | K34: =(H34+I34)*J34 -> 0
B35: =VLOOKUP($C$29:$C$42,Equipment!$A$1:$B$2322,2,FALSE) -> 0 | J35: =VLOOKUP($B$29:$B$42,'Alberta Equip. Rates Year 3'!$B$13:$K$314,10,FALSE) -> 0 | K35: =(H35+I35)*J35 -> 0
B36: =VLOOKUP($C$29:$C$42,Equipment!$A$1:$B$2322,2,FALSE) -> 0 | J36: =VLOOKUP($B$29:$B$42,'Alberta Equip. Rates Year 3'!$B$13:$K$314,10,FALSE) -> 0 | K36: =(H36+I36)*J36 -> 0
B37: =VLOOKUP($C$29:$C$42,Equipment!$A$1:$B$2322,2,FALSE) -> 0 | J37: =VLOOKUP($B$29:$B$42,'Alberta Equip. Rates Year 3'!$B$13:$K$314,10,FALSE) -> 0 | K37: =(H37+I37)*J37 -> 0
B38: =VLOOKUP($C$29:$C$42,Equipment!$A$1:$B$2322,2,FALSE) -> 0 | J38: =VLOOKUP($B$29:$B$42,'Alberta Equip. Rates Year 3'!$B$13:$K$314,10,FALSE) -> 0 | K38: =(H38+I38)*J38 -> 0
B39: =VLOOKUP($C$29:$C$42,Equipment!$A$1:$B$2322,2,FALSE) -> 0 | J39: =VLOOKUP($B$29:$B$42,'Alberta Equip. Rates Year 3'!$B$13:$K$314,10,FALSE) -> 0 | K39: =(H39+I39)*J39 -> 0
B40: =VLOOKUP($C$29:$C$42,Equipment!$A$1:$B$2322,2,FALSE) -> 0 | J40: =VLOOKUP($B$29:$B$42,'Alberta Equip. Rates Year 3'!$B$13:$K$314,10,FALSE) -> 0 | K40: =(H40+I40)*J40 -> 0
... B42: =VLOOKUP($C$29:$C$42,Equipment!$A$1:$B$2322,2,FALSE) -> 0 | J42: =VLOOKUP($B$29:$B$42,'Alberta Equip. Rates Year 3'!$B$13:$K$314,10,FALSE) -> 0 | K42: =(H42+I42)*J42 -> 0
I43: TOTAL EQUIPMENT | K43: =SUM(K29:K42) -> 0
A45: Scope of Work: | I45: LABOUR | K45: =K26 -> 0
I46: EQUIPMENT | K46: =K43 -> 0
I47: SMALL TOOLS | K47: =(O26)*14.15 -> 0
I48: MATERIALS
I49: TRUCKING
I50: SUBCONTRACTORS
I51: FIELD LOG TOTAL* | K51: =SUM(K45:K50) -> 0
A53: Client: | H53: Company Representitive:
A55: * Field Log Total does no include markups
A56: 41218.479

Sheet Field Log (42)
J1: Date:
G6: Field Log ID: | J6: Status:
A7: Address: | G7: Account #: | J7: Account:
G8: Foreman:
A10: Employee ID | B10: Labor Type | C10: Employee | D10: RT Hours | E10: RT Rate | F10: OT Hours | G10: OT Rate | H10: DT Hours | I10: DT Rate | J10: Sub. | K10: Total | M10: Additional Hours
B11: =VLOOKUP($C$11:$C$25,Personnel!$A$1:$B$1234,2,FALSE) -> 0 | E11: =VLOOKUP($B$11:$B$25,'Constr. Wage Rate Calculations'!$A$19:$Z$288,22,FALSE) -> 0 | G11: =VLOOKUP($B$11:$B$25,'Constr. Wage Rate Calculations'!$A$19:$Z$288,23,FALSE) -> 0 | I11: =VLOOKUP($B$11:$B$25,'Constr. Wage Rate Calculations'!$A$19:$Z$288,24,FALSE) -> 0 | J11: =VLOOKUP($B$11:$B$25,'Constr. Wage Rate Calculations'!$A$19:$Z$288,25,FALSE) -> 0 | K11: =IF($D11>=1,$J11+(D11*E11)+(F11*G11)+(H11*I11),IF($F11>=1,$J11+(D11*E11)+(F11*G11)+(H11*I11),IF($H11>=1,$J11+(D11*E11)+(F11*G11)+(H11*I11),"")))
B12: =VLOOKUP($C$11:$C$25,Personnel!$A$1:$B$1234,2,FALSE) -> 0 | E12: =VLOOKUP($B$11:$B$25,'Constr. Wage Rate Calculations'!$A$19:$Z$288,22,FALSE) -> 0 | G12: =VLOOKUP($B$11:$B$25,'Constr. Wage Rate Calculations'!$A$19:$Z$288,23,FALSE) -> 0 | I12: =VLOOKUP($B$11:$B$25,'Constr. Wage Rate Calculations'!$A$19:$Z$288,24,FALSE) -> 0 | J12: =VLOOKUP($B$11:$B$25,'Constr. Wage Rate Calculations'!$A$19:$Z$288,25,FALSE) -> 0 | K12: =IF($D12>=1,$J12+(D12*E12)+(F12*G12)+(H12*I12),IF($F12>=1,$J12+(D12*E12)+(F12*G12)+(H12*I12),IF($H12>=1,$J12+(D12*E12)+(F12*G12)+(H12*I12),"")))
B13: =VLOOKUP($C$11:$C$25,Personnel!$A$1:$B$1234,2,FALSE) -> 0 | E13: =VLOOKUP($B$11:$B$25,'Constr. Wage Rate Calculations'!$A$19:$Z$288,22,FALSE) -> 0 | G13: =VLOOKUP($B$11:$B$25,'Constr. Wage Rate Calculations'!$A$19:$Z$288,23,FALSE) -> 0 | I13: =VLOOKUP($B$11:$B$25,'Constr. Wage Rate Calculations'!$A$19:$Z$288,24,FALSE) -> 0 | J13: =VLOOKUP($B$11:$B$25,'Constr. Wage Rate Calculations'!$A$19:$Z$288,25,FALSE) -> 0 | K13: =IF($D13>=1,$J13+(D13*E13)+(F13*G13)+(H13*I13),IF($F13>=1,$J13+(D13*E13)+(F13*G13)+(H13*I13),IF($H13>=1,$J13+(D13*E13)+(F13*G13)+(H13*I13),"")))
B14: =VLOOKUP($C$11:$C$25,Personnel!$A$1:$B$1234,2,FALSE) -> 0 | E14: =VLOOKUP($B$11:$B$25,'Constr. Wage Rate Calculations'!$A$19:$Z$288,22,FALSE) -> 0 | G14: =VLOOKUP($B$11:$B$25,'Constr. Wage Rate Calculations'!$A$19:$Z$288,23,FALSE) -> 0 | I14: =VLOOKUP($B$11:$B$25,'Constr. Wage Rate Calculations'!$A$19:$Z$288,24,FALSE) -> 0 | J14: =VLOOKUP($B$11:$B$25,'Constr. Wage Rate Calculations'!$A$19:$Z$288,25,FALSE) -> 0 | K14: =IF($D14>=1,$J14+(D14*E14)+(F14*G14)+(H14*I14),IF($F14>=1,$J14+(D14*E14)+(F14*G14)+(H14*I14),IF($H14>=1,$J14+(D14*E14)+(F14*G14)+(H14*I14),"")))
B15: =VLOOKUP($C$11:$C$25,Personnel!$A$1:$B$1234,2,FALSE) -> 0 | E15: =VLOOKUP($B$11:$B$25,'Constr. Wage Rate Calculations'!$A$19:$Z$288,22,FALSE) -> 0 | G15: =VLOOKUP($B$11:$B$25,'Constr. Wage Rate Calculations'!$A$19:$Z$288,23,FALSE) -> 0 | I15: =VLOOKUP($B$11:$B$25,'Constr. Wage Rate Calculations'!$A$19:$Z$288,24,FALSE) -> 0 | J15: =VLOOKUP($B$11:$B$25,'Constr. Wage Rate Calculations'!$A$19:$Z$288,25,FALSE) -> 0 | K15: =IF($D15>=1,$J15+(D15*E15)+(F15*G15)+(H15*I15),IF($F15>=1,$J15+(D15*E15)+(F15*G15)+(H15*I15),IF($H15>=1,$J15+(D15*E15)+(F15*G15)+(H15*I15),"")))
B16: =VLOOKUP($C$11:$C$25,Personnel!$A$1:$B$1234,2,FALSE) -> 0 | E16: =VLOOKUP($B$11:$B$25,'Constr. Wage Rate Calculations'!$A$19:$Z$288,22,FALSE) -> 0 | G16: =VLOOKUP($B$11:$B$25,'Constr. Wage Rate Calculations'!$A$19:$Z$288,23,FALSE) -> 0 | I16: =VLOOKUP($B$11:$B$25,'Constr. Wage Rate Calculations'!$A$19:$Z$288,24,FALSE) -> 0 | J16: =VLOOKUP($B$11:$B$25,'Constr. Wage Rate Calculations'!$A$19:$Z$288,25,FALSE) -> 0 | K16: =IF($D16>=1,$J16+(D16*E16)+(F16*G16)+(H16*I16),IF($F16>=1,$J16+(D16*E16)+(F16*G16)+(H16*I16),IF($H16>=1,$J16+(D16*E16)+(F16*G16)+(H16*I16),"")))
B17: =VLOOKUP($C$11:$C$25,Personnel!$A$1:$B$1234,2,FALSE) -> 0 | E17: =VLOOKUP($B$11:$B$25,'Constr. Wage Rate Calculations'!$A$19:$Z$288,22,FALSE) -> 0 | G17: =VLOOKUP($B$11:$B$25,'Constr. Wage Rate Calculations'!$A$19:$Z$288,23,FALSE) -> 0 | I17: =VLOOKUP($B$11:$B$25,'Constr. Wage Rate Calculations'!$A$19:$Z$288,24,FALSE) -> 0 | J17: =VLOOKUP($B$11:$B$25,'Constr. Wage Rate Calculations'!$A$19:$Z$288,25,FALSE) -> 0 | K17: =IF($D17>=1,$J17+(D17*E17)+(F17*G17)+(H17*I17),IF($F17>=1,$J17+(D17*E17)+(F17*G17)+(H17*I17),IF($H17>=1,$J17+(D17*E17)+(F17*G17)+(H17*I17),"")))
B18: =VLOOKUP($C$11:$C$25,Personnel!$A$1:$B$1234,2,FALSE) -> 0 | E18: =VLOOKUP($B$11:$B$25,'Constr. Wage Rate Calculations'!$A$19:$Z$288,22,FALSE) -> 0 | G18: =VLOOKUP($B$11:$B$25,'Constr. Wage Rate Calculations'!$A$19:$Z$288,23,FALSE) -> 0 | I18: =VLOOKUP($B$11:$B$25,'Constr. Wage Rate Calculations'!$A$19:$Z$288,24,FALSE) -> 0 | J18: =VLOOKUP($B$11:$B$25,'Constr. Wage Rate Calculations'!$A$19:$Z$288,25,FALSE) -> 0 | K18: =IF($D18>=1,$J18+(D18*E18)+(F18*G18)+(H18*I18),IF($F18>=1,$J18+(D18*E18)+(F18*G18)+(H18*I18),IF($H18>=1,$J18+(D18*E18)+(F18*G18)+(H18*I18),"")))
B19: =VLOOKUP($C$11:$C$25,Personnel!$A$1:$B$1234,2,FALSE) -> 0 | E19: =VLOOKUP($B$11:$B$25,'Constr. Wage Rate Calculations'!$A$19:$Z$288,22,FALSE) -> 0 | G19: =VLOOKUP($B$11:$B$25,'Constr. Wage Rate Calculations'!$A$19:$Z$288,23,FALSE) -> 0 | I19: =VLOOKUP($B$11:$B$25,'Constr. Wage Rate Calculations'!$A$19:$Z$288,24,FALSE) -> 0 | J19: =VLOOKUP($B$11:$B$25,'Constr. Wage Rate Calculations'!$A$19:$Z$288,25,FALSE) -> 0 | K19: =IF($D19>=1,$J19+(D19*E19)+(F19*G19)+(H19*I19),IF($F19>=1,$J19+(D19*E19)+(F19*G19)+(H19*I19),IF($H19>=1,$J19+(D19*E19)+(F19*G19)+(H19*I19),"")))
B20: =VLOOKUP($C$11:$C$25,Personnel!$A$1:$B$1234,2,FALSE) -> 0 | E20: =VLOOKUP($B$11:$B$25,'Constr. Wage Rate Calculations'!$A$19:$Z$288,22,FALSE) -> 0 | G20: =VLOOKUP($B$11:$B$25,'Constr. Wage Rate Calculations'!$A$19:$Z$288,23,FALSE) -> 0 | I20: =VLOOKUP($B$11:$B$25,'Constr. Wage Rate Calculations'!$A$19:$Z$288,24,FALSE) -> 0 | J20: =VLOOKUP($B$11:$B$25,'Constr. Wage Rate Calculations'!$A$19:$Z$288,25,FALSE) -> 0 | K20: =IF($D20>=1,$J20+(D20*E20)+(F20*G20)+(H20*I20),IF($F20>=1,$J20+(D20*E20)+(F20*G20)+(H20*I20),IF($H20>=1,$J20+(D20*E20)+(F20*G20)+(H20*I20),"")))
B21: =VLOOKUP($C$11:$C$25,Personnel!$A$1:$B$1234,2,FALSE) -> 0 | E21: =VLOOKUP($B$11:$B$25,'Constr. Wage Rate Calculations'!$A$19:$Z$288,22,FALSE) -> 0 | G21: =VLOOKUP($B$11:$B$25,'Constr. Wage Rate Calculations'!$A$19:$Z$288,23,FALSE) -> 0 | I21: =VLOOKUP($B$11:$B$25,'Constr. Wage Rate Calculations'!$A$19:$Z$288,24,FALSE) -> 0 | J21: =VLOOKUP($B$11:$B$25,'Constr. Wage Rate Calculations'!$A$19:$Z$288,25,FALSE) -> 0 | K21: =IF($D21>=1,$J21+(D21*E21)+(F21*G21)+(H21*I21),IF($F21>=1,$J21+(D21*E21)+(F21*G21)+(H21*I21),IF($H21>=1,$J21+(D21*E21)+(F21*G21)+(H21*I21),"")))
B22: =VLOOKUP($C$11:$C$25,Personnel!$A$1:$B$1234,2,FALSE) -> 0 | E22: =VLOOKUP($B$11:$B$25,'Constr. Wage Rate Calculations'!$A$19:$Z$288,22,FALSE) -> 0 | G22: =VLOOKUP($B$11:$B$25,'Constr. Wage Rate Calculations'!$A$19:$Z$288,23,FALSE) -> 0 | I22: =VLOOKUP($B$11:$B$25,'Constr. Wage Rate Calculations'!$A$19:$Z$288,24,FALSE) -> 0 | J22: =VLOOKUP($B$11:$B$25,'Constr. Wage Rate Calculations'!$A$19:$Z$288,25,FALSE) -> 0 | K22: =IF($D22>=1,$J22+(D22*E22)+(F22*G22)+(H22*I22),IF($F22>=1,$J22+(D22*E22)+(F22*G22)+(H22*I22),IF($H22>=1,$J22+(D22*E22)+(F22*G22)+(H22*I22),"")))
... B24: =VLOOKUP($C$11:$C$25,Personnel!$A$1:$B$1234,2,FALSE) -> 0 | E24: =VLOOKUP($B$11:$B$25,'Constr. Wage Rate Calculations'!$A$19:$Z$288,22,FALSE) -> 0 | G24: =VLOOKUP($B$11:$B$25,'Constr. Wage Rate Calculations'!$A$19:$Z$288,23,FALSE) -> 0 | I24: =VLOOKUP($B$11:$B$25,'Constr. Wage Rate Calculations'!$A$19:$Z$288,24,FALSE) -> 0 | J24: =VLOOKUP($B$11:$B$25,'Constr. Wage Rate Calculations'!$A$19:$Z$288,25,FALSE) -> 0 | K24: =IF($D24>=1,$J24+(D24*E24)+(F24*G24)+(H24*I24),IF($F24>=1,$J24+(D24*E24)+(F24*G24)+(H24*I24),IF($H24>=1,$J24+(D24*E24)+(F24*G24)+(H24*I24),"")))
B25: =VLOOKUP($C$11:$C$25,Personnel!$A$1:$B$1234,2,FALSE) -> 0 | E25: =VLOOKUP($B$11:$B$25,'Constr. Wage Rate Calculations'!$A$19:$Z$288,22,FALSE) -> 0 | G25: =VLOOKUP($B$11:$B$25,'Constr. Wage Rate Calculations'!$A$19:$Z$288,23,FALSE) -> 0 | I25: =VLOOKUP($B$11:$B$25,'Constr. Wage Rate Calculations'!$A$19:$Z$288,24,FALSE) -> 0 | J25: =VLOOKUP($B$11:$B$25,'Constr. Wage Rate Calculations'!$A$19:$Z$288,25,FALSE) -> 0 | K25: =IF($D25>=1,$J25+(D25*E25)+(F25*G25)+(H25*I25),IF($F25>=1,$J25+(D25*E25)+(F25*G25)+(H25*I25),IF($H25>=1,$J25+(D25*E25)+(F25*G25)+(H25*I25),""))) | M25: =SUM(M11:M24) -> 0
I26: TOTAL LABOUR | K26: =SUM(K11:K25) -> 0 | M26: =SUMIFS(D11:D25,D11:D25,"<3",D11:D25,"<5") -> 0 | N26: =SUMIFS(D11:D25,D11:D25,">3",D11:D25,">5") -> 0 | O26: =SUM(F11:F25,H11:H25,M26,N26)-M25 -> 0
A28: Equipment ID | B28: Equipment | H28: Days | I28: Hrs. | J28: Rate | K28: Total
B29: =VLOOKUP($C$29:$C$42,Equipment!$A$1:$B$2322,2,FALSE) -> 0 | J29: =VLOOKUP($B$29:$B$42,'Alberta Equip. Rates Year 3'!$B$13:$K$314,10,FALSE) -> 0 | K29: =(H29+I29)*J29 -> 0
B30: =VLOOKUP($C$29:$C$42,Equipment!$A$1:$B$2322,2,FALSE) -> 0 | J30: =VLOOKUP($B$29:$B$42,'Alberta Equip. Rates Year 3'!$B$13:$K$314,10,FALSE) -> 0 | K30: =(H30+I30)*J30 -> 0
B31: =VLOOKUP($C$29:$C$42,Equipment!$A$1:$B$2322,2,FALSE) -> 0 | J31: =VLOOKUP($B$29:$B$42,'Alberta Equip. Rates Year 3'!$B$13:$K$314,10,FALSE) -> 0 | K31: =(H31+I31)*J31 -> 0
B32: =VLOOKUP($C$29:$C$42,Equipment!$A$1:$B$2322,2,FALSE) -> 0 | J32: =VLOOKUP($B$29:$B$42,'Alberta Equip. Rates Year 3'!$B$13:$K$314,10,FALSE) -> 0 | K32: =(H32+I32)*J32 -> 0
B33: =VLOOKUP($C$29:$C$42,Equipment!$A$1:$B$2322,2,FALSE) -> 0 | J33: =VLOOKUP($B$29:$B$42,'Alberta Equip. Rates Year 3'!$B$13:$K$314,10,FALSE) -> 0 | K33: =(H33+I33)*J33 -> 0
B34: =VLOOKUP($C$29:$C$42,Equipment!$A$1:$B$2322,2,FALSE) -> 0 | J34: =VLOOKUP($B$29:$B$42,'Alberta Equip. Rates Year 3'!$B$13:$K$314,10,FALSE) -> 0 | K34: =(H34+I34)*J34 -> 0
B35: =VLOOKUP($C$29:$C$42,Equipment!$A$1:$B$2322,2,FALSE) -> 0 | J35: =VLOOKUP($B$29:$B$42,'Alberta Equip. Rates Year 3'!$B$13:$K$314,10,FALSE) -> 0 | K35: =(H35+I35)*J35 -> 0
B36: =VLOOKUP($C$29:$C$42,Equipment!$A$1:$B$2322,2,FALSE) -> 0 | J36: =VLOOKUP($B$29:$B$42,'Alberta Equip. Rates Year 3'!$B$13:$K$314,10,FALSE) -> 0 | K36: =(H36+I36)*J36 -> 0
B37: =VLOOKUP($C$29:$C$42,Equipment!$A$1:$B$2322,2,FALSE) -> 0 | J37: =VLOOKUP($B$29:$B$42,'Alberta Equip. Rates Year 3'!$B$13:$K$314,10,FALSE) -> 0 | K37: =(H37+I37)*J37 -> 0
B38: =VLOOKUP($C$29:$C$42,Equipment!$A$1:$B$2322,2,FALSE) -> 0 | J38: =VLOOKUP($B$29:$B$42,'Alberta Equip. Rates Year 3'!$B$13:$K$314,10,FALSE) -> 0 | K38: =(H38+I38)*J38 -> 0
B39: =VLOOKUP($C$29:$C$42,Equipment!$A$1:$B$2322,2,FALSE) -> 0 | J39: =VLOOKUP($B$29:$B$42,'Alberta Equip. Rates Year 3'!$B$13:$K$314,10,FALSE) -> 0 | K39: =(H39+I39)*J39 -> 0
B40: =VLOOKUP($C$29:$C$42,Equipment!$A$1:$B$2322,2,FALSE) -> 0 | J40: =VLOOKUP($B$29:$B$42,'Alberta Equip. Rates Year 3'!$B$13:$K$314,10,FALSE) -> 0 | K40: =(H40+I40)*J40 -> 0
... B42: =VLOOKUP($C$29:$C$42,Equipment!$A$1:$B$2322,2,FALSE) -> 0 | J42: =VLOOKUP($B$29:$B$42,'Alberta Equip. Rates Year 3'!$B$13:$K$314,10,FALSE) -> 0 | K42: =(H42+I42)*J42 -> 0
I43: TOTAL EQUIPMENT | K43: =SUM(K29:K42) -> 0
A45: Scope of Work: | I45: LABOUR | K45: =K26 -> 0
I46: EQUIPMENT | K46: =K43 -> 0
I47: SMALL TOOLS | K47: =(O26)*14.15 -> 0
I48: MATERIALS
I49: TRUCKING
I50: SUBCONTRACTORS
I51: FIELD LOG TOTAL* | K51: =SUM(K45:K50) -> 0
A53: Client: | H53: Company Representitive:
A55: * Field Log Total does no include markups
A56: 41218.479

Sheet Field Log (41)
J1: Date:
G6: Field Log ID: | J6: Status:
A7: Address: | G7: Account #: | J7: Account:
G8: Foreman:
A10: Employee ID | B10: Labor Type | C10: Employee | D10: RT Hours | E10: RT Rate | F10: OT Hours | G10: OT Rate | H10: DT Hours | I10: DT Rate | J10: Sub. | K10: Total | M10: Additional Hours
B11: =VLOOKUP($C$11:$C$25,Personnel!$A$1:$B$1234,2,FALSE) -> 0 | E11: =VLOOKUP($B$11:$B$25,'Constr. Wage Rate Calculations'!$A$19:$Z$288,22,FALSE) -> 0 | G11: =VLOOKUP($B$11:$B$25,'Constr. Wage Rate Calculations'!$A$19:$Z$288,23,FALSE) -> 0 | I11: =VLOOKUP($B$11:$B$25,'Constr. Wage Rate Calculations'!$A$19:$Z$288,24,FALSE) -> 0 | J11: =VLOOKUP($B$11:$B$25,'Constr. Wage Rate Calculations'!$A$19:$Z$288,25,FALSE) -> 0 | K11: =IF($D11>=1,$J11+(D11*E11)+(F11*G11)+(H11*I11),IF($F11>=1,$J11+(D11*E11)+(F11*G11)+(H11*I11),IF($H11>=1,$J11+(D11*E11)+(F11*G11)+(H11*I11),"")))
B12: =VLOOKUP($C$11:$C$25,Personnel!$A$1:$B$1234,2,FALSE) -> 0 | E12: =VLOOKUP($B$11:$B$25,'Constr. Wage Rate Calculations'!$A$19:$Z$288,22,FALSE) -> 0 | G12: =VLOOKUP($B$11:$B$25,'Constr. Wage Rate Calculations'!$A$19:$Z$288,23,FALSE) -> 0 | I12: =VLOOKUP($B$11:$B$25,'Constr. Wage Rate Calculations'!$A$19:$Z$288,24,FALSE) -> 0 | J12: =VLOOKUP($B$11:$B$25,'Constr. Wage Rate Calculations'!$A$19:$Z$288,25,FALSE) -> 0 | K12: =IF($D12>=1,$J12+(D12*E12)+(F12*G12)+(H12*I12),IF($F12>=1,$J12+(D12*E12)+(F12*G12)+(H12*I12),IF($H12>=1,$J12+(D12*E12)+(F12*G12)+(H12*I12),"")))
B13: =VLOOKUP($C$11:$C$25,Personnel!$A$1:$B$1234,2,FALSE) -> 0 | E13: =VLOOKUP($B$11:$B$25,'Constr. Wage Rate Calculations'!$A$19:$Z$288,22,FALSE) -> 0 | G13: =VLOOKUP($B$11:$B$25,'Constr. Wage Rate Calculations'!$A$19:$Z$288,23,FALSE) -> 0 | I13: =VLOOKUP($B$11:$B$25,'Constr. Wage Rate Calculations'!$A$19:$Z$288,24,FALSE) -> 0 | J13: =VLOOKUP($B$11:$B$25,'Constr. Wage Rate Calculations'!$A$19:$Z$288,25,FALSE) -> 0 | K13: =IF($D13>=1,$J13+(D13*E13)+(F13*G13)+(H13*I13),IF($F13>=1,$J13+(D13*E13)+(F13*G13)+(H13*I13),IF($H13>=1,$J13+(D13*E13)+(F13*G13)+(H13*I13),"")))
B14: =VLOOKUP($C$11:$C$25,Personnel!$A$1:$B$1234,2,FALSE) -> 0 | E14: =VLOOKUP($B$11:$B$25,'Constr. Wage Rate Calculations'!$A$19:$Z$288,22,FALSE) -> 0 | G14: =VLOOKUP($B$11:$B$25,'Constr. Wage Rate Calculations'!$A$19:$Z$288,23,FALSE) -> 0 | I14: =VLOOKUP($B$11:$B$25,'Constr. Wage Rate Calculations'!$A$19:$Z$288,24,FALSE) -> 0 | J14: =VLOOKUP($B$11:$B$25,'Constr. Wage Rate Calculations'!$A$19:$Z$288,25,FALSE) -> 0 | K14: =IF($D14>=1,$J14+(D14*E14)+(F14*G14)+(H14*I14),IF($F14>=1,$J14+(D14*E14)+(F14*G14)+(H14*I14),IF($H14>=1,$J14+(D14*E14)+(F14*G14)+(H14*I14),"")))
B15: =VLOOKUP($C$11:$C$25,Personnel!$A$1:$B$1234,2,FALSE) -> 0 | E15: =VLOOKUP($B$11:$B$25,'Constr. Wage Rate Calculations'!$A$19:$Z$288,22,FALSE) -> 0 | G15: =VLOOKUP($B$11:$B$25,'Constr. Wage Rate Calculations'!$A$19:$Z$288,23,FALSE) -> 0 | I15: =VLOOKUP($B$11:$B$25,'Constr. Wage Rate Calculations'!$A$19:$Z$288,24,FALSE) -> 0 | J15: =VLOOKUP($B$11:$B$25,'Constr. Wage Rate Calculations'!$A$19:$Z$288,25,FALSE) -> 0 | K15: =IF($D15>=1,$J15+(D15*E15)+(F15*G15)+(H15*I15),IF($F15>=1,$J15+(D15*E15)+(F15*G15)+(H15*I15),IF($H15>=1,$J15+(D15*E15)+(F15*G15)+(H15*I15),"")))
B16: =VLOOKUP($C$11:$C$25,Personnel!$A$1:$B$1234,2,FALSE) -> 0 | E16: =VLOOKUP($B$11:$B$25,'Constr. Wage Rate Calculations'!$A$19:$Z$288,22,FALSE) -> 0 | G16: =VLOOKUP($B$11:$B$25,'Constr. Wage Rate Calculations'!$A$19:$Z$288,23,FALSE) -> 0 | I16: =VLOOKUP($B$11:$B$25,'Constr. Wage Rate Calculations'!$A$19:$Z$288,24,FALSE) -> 0 | J16: =VLOOKUP($B$11:$B$25,'Constr. Wage Rate Calculations'!$A$19:$Z$288,25,FALSE) -> 0 | K16: =IF($D16>=1,$J16+(D16*E16)+(F16*G16)+(H16*I16),IF($F16>=1,$J16+(D16*E16)+(F16*G16)+(H16*I16),IF($H16>=1,$J16+(D16*E16)+(F16*G16)+(H16*I16),"")))
B17: =VLOOKUP($C$11:$C$25,Personnel!$A$1:$B$1234,2,FALSE) -> 0 | E17: =VLOOKUP($B$11:$B$25,'Constr. Wage Rate Calculations'!$A$19:$Z$288,22,FALSE) -> 0 | G17: =VLOOKUP($B$11:$B$25,'Constr. Wage Rate Calculations'!$A$19:$Z$288,23,FALSE) -> 0 | I17: =VLOOKUP($B$11:$B$25,'Constr. Wage Rate Calculations'!$A$19:$Z$288,24,FALSE) -> 0 | J17: =VLOOKUP($B$11:$B$25,'Constr. Wage Rate Calculations'!$A$19:$Z$288,25,FALSE) -> 0 | K17: =IF($D17>=1,$J17+(D17*E17)+(F17*G17)+(H17*I17),IF($F17>=1,$J17+(D17*E17)+(F17*G17)+(H17*I17),IF($H17>=1,$J17+(D17*E17)+(F17*G17)+(H17*I17),"")))
B18: =VLOOKUP($C$11:$C$25,Personnel!$A$1:$B$1234,2,FALSE) -> 0 | E18: =VLOOKUP($B$11:$B$25,'Constr. Wage Rate Calculations'!$A$19:$Z$288,22,FALSE) -> 0 | G18: =VLOOKUP($B$11:$B$25,'Constr. Wage Rate Calculations'!$A$19:$Z$288,23,FALSE) -> 0 | I18: =VLOOKUP($B$11:$B$25,'Constr. Wage Rate Calculations'!$A$19:$Z$288,24,FALSE) -> 0 | J18: =VLOOKUP($B$11:$B$25,'Constr. Wage Rate Calculations'!$A$19:$Z$288,25,FALSE) -> 0 | K18: =IF($D18>=1,$J18+(D18*E18)+(F18*G18)+(H18*I18),IF($F18>=1,$J18+(D18*E18)+(F18*G18)+(H18*I18),IF($H18>=1,$J18+(D18*E18)+(F18*G18)+(H18*I18),"")))
B19: =VLOOKUP($C$11:$C$25,Personnel!$A$1:$B$1234,2,FALSE) -> 0 | E19: =VLOOKUP($B$11:$B$25,'Constr. Wage Rate Calculations'!$A$19:$Z$288,22,FALSE) -> 0 | G19: =VLOOKUP($B$11:$B$25,'Constr. Wage Rate Calculations'!$A$19:$Z$288,23,FALSE) -> 0 | I19: =VLOOKUP($B$11:$B$25,'Constr. Wage Rate Calculations'!$A$19:$Z$288,24,FALSE) -> 0 | J19: =VLOOKUP($B$11:$B$25,'Constr. Wage Rate Calculations'!$A$19:$Z$288,25,FALSE) -> 0 | K19: =IF($D19>=1,$J19+(D19*E19)+(F19*G19)+(H19*I19),IF($F19>=1,$J19+(D19*E19)+(F19*G19)+(H19*I19),IF($H19>=1,$J19+(D19*E19)+(F19*G19)+(H19*I19),"")))
B20: =VLOOKUP($C$11:$C$25,Personnel!$A$1:$B$1234,2,FALSE) -> 0 | E20: =VLOOKUP($B$11:$B$25,'Constr. Wage Rate Calculations'!$A$19:$Z$288,22,FALSE) -> 0 | G20: =VLOOKUP($B$11:$B$25,'Constr. Wage Rate Calculations'!$A$19:$Z$288,23,FALSE) -> 0 | I20: =VLOOKUP($B$11:$B$25,'Constr. Wage Rate Calculations'!$A$19:$Z$288,24,FALSE) -> 0 | J20: =VLOOKUP($B$11:$B$25,'Constr. Wage Rate Calculations'!$A$19:$Z$288,25,FALSE) -> 0 | K20: =IF($D20>=1,$J20+(D20*E20)+(F20*G20)+(H20*I20),IF($F20>=1,$J20+(D20*E20)+(F20*G20)+(H20*I20),IF($H20>=1,$J20+(D20*E20)+(F20*G20)+(H20*I20),"")))
B21: =VLOOKUP($C$11:$C$25,Personnel!$A$1:$B$1234,2,FALSE) -> 0 | E21: =VLOOKUP($B$11:$B$25,'Constr. Wage Rate Calculations'!$A$19:$Z$288,22,FALSE) -> 0 | G21: =VLOOKUP($B$11:$B$25,'Constr. Wage Rate Calculations'!$A$19:$Z$288,23,FALSE) -> 0 | I21: =VLOOKUP($B$11:$B$25,'Constr. Wage Rate Calculations'!$A$19:$Z$288,24,FALSE) -> 0 | J21: =VLOOKUP($B$11:$B$25,'Constr. Wage Rate Calculations'!$A$19:$Z$288,25,FALSE) -> 0 | K21: =IF($D21>=1,$J21+(D21*E21)+(F21*G21)+(H21*I21),IF($F21>=1,$J21+(D21*E21)+(F21*G21)+(H21*I21),IF($H21>=1,$J21+(D21*E21)+(F21*G21)+(H21*I21),"")))
B22: =VLOOKUP($C$11:$C$25,Personnel!$A$1:$B$1234,2,FALSE) -> 0 | E22: =VLOOKUP($B$11:$B$25,'Constr. Wage Rate Calculations'!$A$19:$Z$288,22,FALSE) -> 0 | G22: =VLOOKUP($B$11:$B$25,'Constr. Wage Rate Calculations'!$A$19:$Z$288,23,FALSE) -> 0 | I22: =VLOOKUP($B$11:$B$25,'Constr. Wage Rate Calculations'!$A$19:$Z$288,24,FALSE) -> 0 | J22: =VLOOKUP($B$11:$B$25,'Constr. Wage Rate Calculations'!$A$19:$Z$288,25,FALSE) -> 0 | K22: =IF($D22>=1,$J22+(D22*E22)+(F22*G22)+(H22*I22),IF($F22>=1,$J22+(D22*E22)+(F22*G22)+(H22*I22),IF($H22>=1,$J22+(D22*E22)+(F22*G22)+(H22*I22),"")))
... B24: =VLOOKUP($C$11:$C$25,Personnel!$A$1:$B$1234,2,FALSE) -> 0 | E24: =VLOOKUP($B$11:$B$25,'Constr. Wage Rate Calculations'!$A$19:$Z$288,22,FALSE) -> 0 | G24: =VLOOKUP($B$11:$B$25,'Constr. Wage Rate Calculations'!$A$19:$Z$288,23,FALSE) -> 0 | I24: =VLOOKUP($B$11:$B$25,'Constr. Wage Rate Calculations'!$A$19:$Z$288,24,FALSE) -> 0 | J24: =VLOOKUP($B$11:$B$25,'Constr. Wage Rate Calculations'!$A$19:$Z$288,25,FALSE) -> 0 | K24: =IF($D24>=1,$J24+(D24*E24)+(F24*G24)+(H24*I24),IF($F24>=1,$J24+(D24*E24)+(F24*G24)+(H24*I24),IF($H24>=1,$J24+(D24*E24)+(F24*G24)+(H24*I24),"")))
B25: =VLOOKUP($C$11:$C$25,Personnel!$A$1:$B$1234,2,FALSE) -> 0 | E25: =VLOOKUP($B$11:$B$25,'Constr. Wage Rate Calculations'!$A$19:$Z$288,22,FALSE) -> 0 | G25: =VLOOKUP($B$11:$B$25,'Constr. Wage Rate Calculations'!$A$19:$Z$288,23,FALSE) -> 0 | I25: =VLOOKUP($B$11:$B$25,'Constr. Wage Rate Calculations'!$A$19:$Z$288,24,FALSE) -> 0 | J25: =VLOOKUP($B$11:$B$25,'Constr. Wage Rate Calculations'!$A$19:$Z$288,25,FALSE) -> 0 | K25: =IF($D25>=1,$J25+(D25*E25)+(F25*G25)+(H25*I25),IF($F25>=1,$J25+(D25*E25)+(F25*G25)+(H25*I25),IF($H25>=1,$J25+(D25*E25)+(F25*G25)+(H25*I25),""))) | M25: =SUM(M11:M24) -> 0
I26: TOTAL LABOUR | K26: =SUM(K11:K25) -> 0 | M26: =SUMIFS(D11:D25,D11:D25,"<3",D11:D25,"<5") -> 0 | N26: =SUMIFS(D11:D25,D11:D25,">3",D11:D25,">5") -> 0 | O26: =SUM(F11:F25,H11:H25,M26,N26)-M25 -> 0
A28: Equipment ID | B28: Equipment | H28: Days | I28: Hrs. | J28: Rate | K28: Total
B29: =VLOOKUP($C$29:$C$42,Equipment!$A$1:$B$2322,2,FALSE) -> 0 | J29: =VLOOKUP($B$29:$B$42,'Alberta Equip. Rates Year 3'!$B$13:$K$314,10,FALSE) -> 0 | K29: =(H29+I29)*J29 -> 0
B30: =VLOOKUP($C$29:$C$42,Equipment!$A$1:$B$2322,2,FALSE) -> 0 | J30: =VLOOKUP($B$29:$B$42,'Alberta Equip. Rates Year 3'!$B$13:$K$314,10,FALSE) -> 0 | K30: =(H30+I30)*J30 -> 0
B31: =VLOOKUP($C$29:$C$42,Equipment!$A$1:$B$2322,2,FALSE) -> 0 | J31: =VLOOKUP($B$29:$B$42,'Alberta Equip. Rates Year 3'!$B$13:$K$314,10,FALSE) -> 0 | K31: =(H31+I31)*J31 -> 0
B32: =VLOOKUP($C$29:$C$42,Equipment!$A$1:$B$2322,2,FALSE) -> 0 | J32: =VLOOKUP($B$29:$B$42,'Alberta Equip. Rates Year 3'!$B$13:$K$314,10,FALSE) -> 0 | K32: =(H32+I32)*J32 -> 0
B33: =VLOOKUP($C$29:$C$42,Equipment!$A$1:$B$2322,2,FALSE) -> 0 | J33: =VLOOKUP($B$29:$B$42,'Alberta Equip. Rates Year 3'!$B$13:$K$314,10,FALSE) -> 0 | K33: =(H33+I33)*J33 -> 0
B34: =VLOOKUP($C$29:$C$42,Equipment!$A$1:$B$2322,2,FALSE) -> 0 | J34: =VLOOKUP($B$29:$B$42,'Alberta Equip. Rates Year 3'!$B$13:$K$314,10,FALSE) -> 0 | K34: =(H34+I34)*J34 -> 0
B35: =VLOOKUP($C$29:$C$42,Equipment!$A$1:$B$2322,2,FALSE) -> 0 | J35: =VLOOKUP($B$29:$B$42,'Alberta Equip. Rates Year 3'!$B$13:$K$314,10,FALSE) -> 0 | K35: =(H35+I35)*J35 -> 0
B36: =VLOOKUP($C$29:$C$42,Equipment!$A$1:$B$2322,2,FALSE) -> 0 | J36: =VLOOKUP($B$29:$B$42,'Alberta Equip. Rates Year 3'!$B$13:$K$314,10,FALSE) -> 0 | K36: =(H36+I36)*J36 -> 0
B37: =VLOOKUP($C$29:$C$42,Equipment!$A$1:$B$2322,2,FALSE) -> 0 | J37: =VLOOKUP($B$29:$B$42,'Alberta Equip. Rates Year 3'!$B$13:$K$314,10,FALSE) -> 0 | K37: =(H37+I37)*J37 -> 0
B38: =VLOOKUP($C$29:$C$42,Equipment!$A$1:$B$2322,2,FALSE) -> 0 | J38: =VLOOKUP($B$29:$B$42,'Alberta Equip. Rates Year 3'!$B$13:$K$314,10,FALSE) -> 0 | K38: =(H38+I38)*J38 -> 0
B39: =VLOOKUP($C$29:$C$42,Equipment!$A$1:$B$2322,2,FALSE) -> 0 | J39: =VLOOKUP($B$29:$B$42,'Alberta Equip. Rates Year 3'!$B$13:$K$314,10,FALSE) -> 0 | K39: =(H39+I39)*J39 -> 0
B40: =VLOOKUP($C$29:$C$42,Equipment!$A$1:$B$2322,2,FALSE) -> 0 | J40: =VLOOKUP($B$29:$B$42,'Alberta Equip. Rates Year 3'!$B$13:$K$314,10,FALSE) -> 0 | K40: =(H40+I40)*J40 -> 0
... B42: =VLOOKUP($C$29:$C$42,Equipment!$A$1:$B$2322,2,FALSE) -> 0 | J42: =VLOOKUP($B$29:$B$42,'Alberta Equip. Rates Year 3'!$B$13:$K$314,10,FALSE) -> 0 | K42: =(H42+I42)*J42 -> 0
I43: TOTAL EQUIPMENT | K43: =SUM(K29:K42) -> 0
A45: Scope of Work: | I45: LABOUR | K45: =K26 -> 0
I46: EQUIPMENT | K46: =K43 -> 0
I47: SMALL TOOLS | K47: =(O26)*14.15 -> 0
I48: MATERIALS
I49: TRUCKING
I50: SUBCONTRACTORS
I51: FIELD LOG TOTAL* | K51: =SUM(K45:K50) -> 0
A53: Client: | H53: Company Representitive:
A55: * Field Log Total does no include markups
A56: 41218.479

Sheet Field Log (40)
J1: Date:
G6: Field Log ID: | J6: Status:
A7: Address: | G7: Account #: | J7: Account:
G8: Foreman:
A10: Employee ID | B10: Labor Type | C10: Employee | D10: RT Hours | E10: RT Rate | F10: OT Hours | G10: OT Rate | H10: DT Hours | I10: DT Rate | J10: Sub. | K10: Total | M10: Additional Hours
B11: =VLOOKUP($C$11:$C$25,Personnel!$A$1:$B$1234,2,FALSE) -> 0 | E11: =VLOOKUP($B$11:$B$25,'Constr. Wage Rate Calculations'!$A$19:$Z$288,22,FALSE) -> 0 | G11: =VLOOKUP($B$11:$B$25,'Constr. Wage Rate Calculations'!$A$19:$Z$288,23,FALSE) -> 0 | I11: =VLOOKUP($B$11:$B$25,'Constr. Wage Rate Calculations'!$A$19:$Z$288,24,FALSE) -> 0 | J11: =VLOOKUP($B$11:$B$25,'Constr. Wage Rate Calculations'!$A$19:$Z$288,25,FALSE) -> 0 | K11: =IF($D11>=1,$J11+(D11*E11)+(F11*G11)+(H11*I11),IF($F11>=1,$J11+(D11*E11)+(F11*G11)+(H11*I11),IF($H11>=1,$J11+(D11*E11)+(F11*G11)+(H11*I11),"")))
B12: =VLOOKUP($C$11:$C$25,Personnel!$A$1:$B$1234,2,FALSE) -> 0 | E12: =VLOOKUP($B$11:$B$25,'Constr. Wage Rate Calculations'!$A$19:$Z$288,22,FALSE) -> 0 | G12: =VLOOKUP($B$11:$B$25,'Constr. Wage Rate Calculations'!$A$19:$Z$288,23,FALSE) -> 0 | I12: =VLOOKUP($B$11:$B$25,'Constr. Wage Rate Calculations'!$A$19:$Z$288,24,FALSE) -> 0 | J12: =VLOOKUP($B$11:$B$25,'Constr. Wage Rate Calculations'!$A$19:$Z$288,25,FALSE) -> 0 | K12: =IF($D12>=1,$J12+(D12*E12)+(F12*G12)+(H12*I12),IF($F12>=1,$J12+(D12*E12)+(F12*G12)+(H12*I12),IF($H12>=1,$J12+(D12*E12)+(F12*G12)+(H12*I12),"")))
B13: =VLOOKUP($C$11:$C$25,Personnel!$A$1:$B$1234,2,FALSE) -> 0 | E13: =VLOOKUP($B$11:$B$25,'Constr. Wage Rate Calculations'!$A$19:$Z$288,22,FALSE) -> 0 | G13: =VLOOKUP($B$11:$B$25,'Constr. Wage Rate Calculations'!$A$19:$Z$288,23,FALSE) -> 0 | I13: =VLOOKUP($B$11:$B$25,'Constr. Wage Rate Calculations'!$A$19:$Z$288,24,FALSE) -> 0 | J13: =VLOOKUP($B$11:$B$25,'Constr. Wage Rate Calculations'!$A$19:$Z$288,25,FALSE) -> 0 | K13: =IF($D13>=1,$J13+(D13*E13)+(F13*G13)+(H13*I13),IF($F13>=1,$J13+(D13*E13)+(F13*G13)+(H13*I13),IF($H13>=1,$J13+(D13*E13)+(F13*G13)+(H13*I13),"")))
B14: =VLOOKUP($C$11:$C$25,Personnel!$A$1:$B$1234,2,FALSE) -> 0 | E14: =VLOOKUP($B$11:$B$25,'Constr. Wage Rate Calculations'!$A$19:$Z$288,22,FALSE) -> 0 | G14: =VLOOKUP($B$11:$B$25,'Constr. Wage Rate Calculations'!$A$19:$Z$288,23,FALSE) -> 0 | I14: =VLOOKUP($B$11:$B$25,'Constr. Wage Rate Calculations'!$A$19:$Z$288,24,FALSE) -> 0 | J14: =VLOOKUP($B$11:$B$25,'Constr. Wage Rate Calculations'!$A$19:$Z$288,25,FALSE) -> 0 | K14: =IF($D14>=1,$J14+(D14*E14)+(F14*G14)+(H14*I14),IF($F14>=1,$J14+(D14*E14)+(F14*G14)+(H14*I14),IF($H14>=1,$J14+(D14*E14)+(F14*G14)+(H14*I14),"")))
B15: =VLOOKUP($C$11:$C$25,Personnel!$A$1:$B$1234,2,FALSE) -> 0 | E15: =VLOOKUP($B$11:$B$25,'Constr. Wage Rate Calculations'!$A$19:$Z$288,22,FALSE) -> 0 | G15: =VLOOKUP($B$11:$B$25,'Constr. Wage Rate Calculations'!$A$19:$Z$288,23,FALSE) -> 0 | I15: =VLOOKUP($B$11:$B$25,'Constr. Wage Rate Calculations'!$A$19:$Z$288,24,FALSE) -> 0 | J15: =VLOOKUP($B$11:$B$25,'Constr. Wage Rate Calculations'!$A$19:$Z$288,25,FALSE) -> 0 | K15: =IF($D15>=1,$J15+(D15*E15)+(F15*G15)+(H15*I15),IF($F15>=1,$J15+(D15*E15)+(F15*G15)+(H15*I15),IF($H15>=1,$J15+(D15*E15)+(F15*G15)+(H15*I15),"")))
B16: =VLOOKUP($C$11:$C$25,Personnel!$A$1:$B$1234,2,FALSE) -> 0 | E16: =VLOOKUP($B$11:$B$25,'Constr. Wage Rate Calculations'!$A$19:$Z$288,22,FALSE) -> 0 | G16: =VLOOKUP($B$11:$B$25,'Constr. Wage Rate Calculations'!$A$19:$Z$288,23,FALSE) -> 0 | I16: =VLOOKUP($B$11:$B$25,'Constr. Wage Rate Calculations'!$A$19:$Z$288,24,FALSE) -> 0 | J16: =VLOOKUP($B$11:$B$25,'Constr. Wage Rate Calculations'!$A$19:$Z$288,25,FALSE) -> 0 | K16: =IF($D16>=1,$J16+(D16*E16)+(F16*G16)+(H16*I16),IF($F16>=1,$J16+(D16*E16)+(F16*G16)+(H16*I16),IF($H16>=1,$J16+(D16*E16)+(F16*G16)+(H16*I16),"")))
B17: =VLOOKUP($C$11:$C$25,Personnel!$A$1:$B$1234,2,FALSE) -> 0 | E17: =VLOOKUP($B$11:$B$25,'Constr. Wage Rate Calculations'!$A$19:$Z$288,22,FALSE) -> 0 | G17: =VLOOKUP($B$11:$B$25,'Constr. Wage Rate Calculations'!$A$19:$Z$288,23,FALSE) -> 0 | I17: =VLOOKUP($B$11:$B$25,'Constr. Wage Rate Calculations'!$A$19:$Z$288,24,FALSE) -> 0 | J17: =VLOOKUP($B$11:$B$25,'Constr. Wage Rate Calculations'!$A$19:$Z$288,25,FALSE) -> 0 | K17: =IF($D17>=1,$J17+(D17*E17)+(F17*G17)+(H17*I17),IF($F17>=1,$J17+(D17*E17)+(F17*G17)+(H17*I17),IF($H17>=1,$J17+(D17*E17)+(F17*G17)+(H17*I17),"")))
B18: =VLOOKUP($C$11:$C$25,Personnel!$A$1:$B$1234,2,FALSE) -> 0 | E18: =VLOOKUP($B$11:$B$25,'Constr. Wage Rate Calculations'!$A$19:$Z$288,22,FALSE) -> 0 | G18: =VLOOKUP($B$11:$B$25,'Constr. Wage Rate Calculations'!$A$19:$Z$288,23,FALSE) -> 0 | I18: =VLOOKUP($B$11:$B$25,'Constr. Wage Rate Calculations'!$A$19:$Z$288,24,FALSE) -> 0 | J18: =VLOOKUP($B$11:$B$25,'Constr. Wage Rate Calculations'!$A$19:$Z$288,25,FALSE) -> 0 | K18: =IF($D18>=1,$J18+(D18*E18)+(F18*G18)+(H18*I18),IF($F18>=1,$J18+(D18*E18)+(F18*G18)+(H18*I18),IF($H18>=1,$J18+(D18*E18)+(F18*G18)+(H18*I18),"")))
B19: =VLOOKUP($C$11:$C$25,Personnel!$A$1:$B$1234,2,FALSE) -> 0 | E19: =VLOOKUP($B$11:$B$25,'Constr. Wage Rate Calculations'!$A$19:$Z$288,22,FALSE) -> 0 | G19: =VLOOKUP($B$11:$B$25,'Constr. Wage Rate Calculations'!$A$19:$Z$288,23,FALSE) -> 0 | I19: =VLOOKUP($B$11:$B$25,'Constr. Wage Rate Calculations'!$A$19:$Z$288,24,FALSE) -> 0 | J19: =VLOOKUP($B$11:$B$25,'Constr. Wage Rate Calculations'!$A$19:$Z$288,25,FALSE) -> 0 | K19: =IF($D19>=1,$J19+(D19*E19)+(F19*G19)+(H19*I19),IF($F19>=1,$J19+(D19*E19)+(F19*G19)+(H19*I19),IF($H19>=1,$J19+(D19*E19)+(F19*G19)+(H19*I19),"")))
B20: =VLOOKUP($C$11:$C$25,Personnel!$A$1:$B$1234,2,FALSE) -> 0 | E20: =VLOOKUP($B$11:$B$25,'Constr. Wage Rate Calculations'!$A$19:$Z$288,22,FALSE) -> 0 | G20: =VLOOKUP($B$11:$B$25,'Constr. Wage Rate Calculations'!$A$19:$Z$288,23,FALSE) -> 0 | I20: =VLOOKUP($B$11:$B$25,'Constr. Wage Rate Calculations'!$A$19:$Z$288,24,FALSE) -> 0 | J20: =VLOOKUP($B$11:$B$25,'Constr. Wage Rate Calculations'!$A$19:$Z$288,25,FALSE) -> 0 | K20: =IF($D20>=1,$J20+(D20*E20)+(F20*G20)+(H20*I20),IF($F20>=1,$J20+(D20*E20)+(F20*G20)+(H20*I20),IF($H20>=1,$J20+(D20*E20)+(F20*G20)+(H20*I20),"")))
B21: =VLOOKUP($C$11:$C$25,Personnel!$A$1:$B$1234,2,FALSE) -> 0 | E21: =VLOOKUP($B$11:$B$25,'Constr. Wage Rate Calculations'!$A$19:$Z$288,22,FALSE) -> 0 | G21: =VLOOKUP($B$11:$B$25,'Constr. Wage Rate Calculations'!$A$19:$Z$288,23,FALSE) -> 0 | I21: =VLOOKUP($B$11:$B$25,'Constr. Wage Rate Calculations'!$A$19:$Z$288,24,FALSE) -> 0 | J21: =VLOOKUP($B$11:$B$25,'Constr. Wage Rate Calculations'!$A$19:$Z$288,25,FALSE) -> 0 | K21: =IF($D21>=1,$J21+(D21*E21)+(F21*G21)+(H21*I21),IF($F21>=1,$J21+(D21*E21)+(F21*G21)+(H21*I21),IF($H21>=1,$J21+(D21*E21)+(F21*G21)+(H21*I21),"")))
B22: =VLOOKUP($C$11:$C$25,Personnel!$A$1:$B$1234,2,FALSE) -> 0 | E22: =VLOOKUP($B$11:$B$25,'Constr. Wage Rate Calculations'!$A$19:$Z$288,22,FALSE) -> 0 | G22: =VLOOKUP($B$11:$B$25,'Constr. Wage Rate Calculations'!$A$19:$Z$288,23,FALSE) -> 0 | I22: =VLOOKUP($B$11:$B$25,'Constr. Wage Rate Calculations'!$A$19:$Z$288,24,FALSE) -> 0 | J22: =VLOOKUP($B$11:$B$25,'Constr. Wage Rate Calculations'!$A$19:$Z$288,25,FALSE) -> 0 | K22: =IF($D22>=1,$J22+(D22*E22)+(F22*G22)+(H22*I22),IF($F22>=1,$J22+(D22*E22)+(F22*G22)+(H22*I22),IF($H22>=1,$J22+(D22*E22)+(F22*G22)+(H22*I22),"")))
... B24: =VLOOKUP($C$11:$C$25,Personnel!$A$1:$B$1234,2,FALSE) -> 0 | E24: =VLOOKUP($B$11:$B$25,'Constr. Wage Rate Calculations'!$A$19:$Z$288,22,FALSE) -> 0 | G24: =VLOOKUP($B$11:$B$25,'Constr. Wage Rate Calculations'!$A$19:$Z$288,23,FALSE) -> 0 | I24: =VLOOKUP($B$11:$B$25,'Constr. Wage Rate Calculations'!$A$19:$Z$288,24,FALSE) -> 0 | J24: =VLOOKUP($B$11:$B$25,'Constr. Wage Rate Calculations'!$A$19:$Z$288,25,FALSE) -> 0 | K24: =IF($D24>=1,$J24+(D24*E24)+(F24*G24)+(H24*I24),IF($F24>=1,$J24+(D24*E24)+(F24*G24)+(H24*I24),IF($H24>=1,$J24+(D24*E24)+(F24*G24)+(H24*I24),"")))
B25: =VLOOKUP($C$11:$C$25,Personnel!$A$1:$B$1234,2,FALSE) -> 0 | E25: =VLOOKUP($B$11:$B$25,'Constr. Wage Rate Calculations'!$A$19:$Z$288,22,FALSE) -> 0 | G25: =VLOOKUP($B$11:$B$25,'Constr. Wage Rate Calculations'!$A$19:$Z$288,23,FALSE) -> 0 | I25: =VLOOKUP($B$11:$B$25,'Constr. Wage Rate Calculations'!$A$19:$Z$288,24,FALSE) -> 0 | J25: =VLOOKUP($B$11:$B$25,'Constr. Wage Rate Calculations'!$A$19:$Z$288,25,FALSE) -> 0 | K25: =IF($D25>=1,$J25+(D25*E25)+(F25*G25)+(H25*I25),IF($F25>=1,$J25+(D25*E25)+(F25*G25)+(H25*I25),IF($H25>=1,$J25+(D25*E25)+(F25*G25)+(H25*I25),""))) | M25: =SUM(M11:M24) -> 0
I26: TOTAL LABOUR | K26: =SUM(K11:K25) -> 0 | M26: =SUMIFS(D11:D25,D11:D25,"<3",D11:D25,"<5") -> 0 | N26: =SUMIFS(D11:D25,D11:D25,">3",D11:D25,">5") -> 0 | O26: =SUM(F11:F25,H11:H25,M26,N26)-M25 -> 0
A28: Equipment ID | B28: Equipment | H28: Days | I28: Hrs. | J28: Rate | K28: Total
B29: =VLOOKUP($C$29:$C$42,Equipment!$A$1:$B$2322,2,FALSE) -> 0 | J29: =VLOOKUP($B$29:$B$42,'Alberta Equip. Rates Year 3'!$B$13:$K$314,10,FALSE) -> 0 | K29: =(H29+I29)*J29 -> 0
B30: =VLOOKUP($C$29:$C$42,Equipment!$A$1:$B$2322,2,FALSE) -> 0 | J30: =VLOOKUP($B$29:$B$42,'Alberta Equip. Rates Year 3'!$B$13:$K$314,10,FALSE) -> 0 | K30: =(H30+I30)*J30 -> 0
B31: =VLOOKUP($C$29:$C$42,Equipment!$A$1:$B$2322,2,FALSE) -> 0 | J31: =VLOOKUP($B$29:$B$42,'Alberta Equip. Rates Year 3'!$B$13:$K$314,10,FALSE) -> 0 | K31: =(H31+I31)*J31 -> 0
B32: =VLOOKUP($C$29:$C$42,Equipment!$A$1:$B$2322,2,FALSE) -> 0 | J32: =VLOOKUP($B$29:$B$42,'Alberta Equip. Rates Year 3'!$B$13:$K$314,10,FALSE) -> 0 | K32: =(H32+I32)*J32 -> 0
B33: =VLOOKUP($C$29:$C$42,Equipment!$A$1:$B$2322,2,FALSE) -> 0 | J33: =VLOOKUP($B$29:$B$42,'Alberta Equip. Rates Year 3'!$B$13:$K$314,10,FALSE) -> 0 | K33: =(H33+I33)*J33 -> 0
B34: =VLOOKUP($C$29:$C$42,Equipment!$A$1:$B$2322,2,FALSE) -> 0 | J34: =VLOOKUP($B$29:$B$42,'Alberta Equip. Rates Year 3'!$B$13:$K$314,10,FALSE) -> 0 | K34: =(H34+I34)*J34 -> 0
B35: =VLOOKUP($C$29:$C$42,Equipment!$A$1:$B$2322,2,FALSE) -> 0 | J35: =VLOOKUP($B$29:$B$42,'Alberta Equip. Rates Year 3'!$B$13:$K$314,10,FALSE) -> 0 | K35: =(H35+I35)*J35 -> 0
B36: =VLOOKUP($C$29:$C$42,Equipment!$A$1:$B$2322,2,FALSE) -> 0 | J36: =VLOOKUP($B$29:$B$42,'Alberta Equip. Rates Year 3'!$B$13:$K$314,10,FALSE) -> 0 | K36: =(H36+I36)*J36 -> 0
B37: =VLOOKUP($C$29:$C$42,Equipment!$A$1:$B$2322,2,FALSE) -> 0 | J37: =VLOOKUP($B$29:$B$42,'Alberta Equip. Rates Year 3'!$B$13:$K$314,10,FALSE) -> 0 | K37: =(H37+I37)*J37 -> 0
B38: =VLOOKUP($C$29:$C$42,Equipment!$A$1:$B$2322,2,FALSE) -> 0 | J38: =VLOOKUP($B$29:$B$42,'Alberta Equip. Rates Year 3'!$B$13:$K$314,10,FALSE) -> 0 | K38: =(H38+I38)*J38 -> 0
B39: =VLOOKUP($C$29:$C$42,Equipment!$A$1:$B$2322,2,FALSE) -> 0 | J39: =VLOOKUP($B$29:$B$42,'Alberta Equip. Rates Year 3'!$B$13:$K$314,10,FALSE) -> 0 | K39: =(H39+I39)*J39 -> 0
B40: =VLOOKUP($C$29:$C$42,Equipment!$A$1:$B$2322,2,FALSE) -> 0 | J40: =VLOOKUP($B$29:$B$42,'Alberta Equip. Rates Year 3'!$B$13:$K$314,10,FALSE) -> 0 | K40: =(H40+I40)*J40 -> 0
... B42: =VLOOKUP($C$29:$C$42,Equipment!$A$1:$B$2322,2,FALSE) -> 0 | J42: =VLOOKUP($B$29:$B$42,'Alberta Equip. Rates Year 3'!$B$13:$K$314,10,FALSE) -> 0 | K42: =(H42+I42)*J42 -> 0
I43: TOTAL EQUIPMENT | K43: =SUM(K29:K42) -> 0
A45: Scope of Work: | I45: LABOUR | K45: =K26 -> 0
I46: EQUIPMENT | K46: =K43 -> 0
I47: SMALL TOOLS | K47: =(O26)*14.15 -> 0
I48: MATERIALS
I49: TRUCKING
I50: SUBCONTRACTORS
I51: FIELD LOG TOTAL* | K51: =SUM(K45:K50) -> 0
A53: Client: | H53: Company Representitive:
A55: * Field Log Total does no include markups
A56: 41218.479

Sheet Field Log (39)
J1: Date:
G6: Field Log ID: | J6: Status:
A7: Address: | G7: Account #: | J7: Account:
G8: Foreman:
A10: Employee ID | B10: Labor Type | C10: Employee | D10: RT Hours | E10: RT Rate | F10: OT Hours | G10: OT Rate | H10: DT Hours | I10: DT Rate | J10: Sub. | K10: Total | M10: Additional Hours
B11: =VLOOKUP($C$11:$C$25,Personnel!$A$1:$B$1234,2,FALSE) -> 0 | E11: =VLOOKUP($B$11:$B$25,'Constr. Wage Rate Calculations'!$A$19:$Z$288,22,FALSE) -> 0 | G11: =VLOOKUP($B$11:$B$25,'Constr. Wage Rate Calculations'!$A$19:$Z$288,23,FALSE) -> 0 | I11: =VLOOKUP($B$11:$B$25,'Constr. Wage Rate Calculations'!$A$19:$Z$288,24,FALSE) -> 0 | J11: =VLOOKUP($B$11:$B$25,'Constr. Wage Rate Calculations'!$A$19:$Z$288,25,FALSE) -> 0 | K11: =IF($D11>=1,$J11+(D11*E11)+(F11*G11)+(H11*I11),IF($F11>=1,$J11+(D11*E11)+(F11*G11)+(H11*I11),IF($H11>=1,$J11+(D11*E11)+(F11*G11)+(H11*I11),"")))
B12: =VLOOKUP($C$11:$C$25,Personnel!$A$1:$B$1234,2,FALSE) -> 0 | E12: =VLOOKUP($B$11:$B$25,'Constr. Wage Rate Calculations'!$A$19:$Z$288,22,FALSE) -> 0 | G12: =VLOOKUP($B$11:$B$25,'Constr. Wage Rate Calculations'!$A$19:$Z$288,23,FALSE) -> 0 | I12: =VLOOKUP($B$11:$B$25,'Constr. Wage Rate Calculations'!$A$19:$Z$288,24,FALSE) -> 0 | J12: =VLOOKUP($B$11:$B$25,'Constr. Wage Rate Calculations'!$A$19:$Z$288,25,FALSE) -> 0 | K12: =IF($D12>=1,$J12+(D12*E12)+(F12*G12)+(H12*I12),IF($F12>=1,$J12+(D12*E12)+(F12*G12)+(H12*I12),IF($H12>=1,$J12+(D12*E12)+(F12*G12)+(H12*I12),"")))
B13: =VLOOKUP($C$11:$C$25,Personnel!$A$1:$B$1234,2,FALSE) -> 0 | E13: =VLOOKUP($B$11:$B$25,'Constr. Wage Rate Calculations'!$A$19:$Z$288,22,FALSE) -> 0 | G13: =VLOOKUP($B$11:$B$25,'Constr. Wage Rate Calculations'!$A$19:$Z$288,23,FALSE) -> 0 | I13: =VLOOKUP($B$11:$B$25,'Constr. Wage Rate Calculations'!$A$19:$Z$288,24,FALSE) -> 0 | J13: =VLOOKUP($B$11:$B$25,'Constr. Wage Rate Calculations'!$A$19:$Z$288,25,FALSE) -> 0 | K13: =IF($D13>=1,$J13+(D13*E13)+(F13*G13)+(H13*I13),IF($F13>=1,$J13+(D13*E13)+(F13*G13)+(H13*I13),IF($H13>=1,$J13+(D13*E13)+(F13*G13)+(H13*I13),"")))
B14: =VLOOKUP($C$11:$C$25,Personnel!$A$1:$B$1234,2,FALSE) -> 0 | E14: =VLOOKUP($B$11:$B$25,'Constr. Wage Rate Calculations'!$A$19:$Z$288,22,FALSE) -> 0 | G14: =VLOOKUP($B$11:$B$25,'Constr. Wage Rate Calculations'!$A$19:$Z$288,23,FALSE) -> 0 | I14: =VLOOKUP($B$11:$B$25,'Constr. Wage Rate Calculations'!$A$19:$Z$288,24,FALSE) -> 0 | J14: =VLOOKUP($B$11:$B$25,'Constr. Wage Rate Calculations'!$A$19:$Z$288,25,FALSE) -> 0 | K14: =IF($D14>=1,$J14+(D14*E14)+(F14*G14)+(H14*I14),IF($F14>=1,$J14+(D14*E14)+(F14*G14)+(H14*I14),IF($H14>=1,$J14+(D14*E14)+(F14*G14)+(H14*I14),"")))
B15: =VLOOKUP($C$11:$C$25,Personnel!$A$1:$B$1234,2,FALSE) -> 0 | E15: =VLOOKUP($B$11:$B$25,'Constr. Wage Rate Calculations'!$A$19:$Z$288,22,FALSE) -> 0 | G15: =VLOOKUP($B$11:$B$25,'Constr. Wage Rate Calculations'!$A$19:$Z$288,23,FALSE) -> 0 | I15: =VLOOKUP($B$11:$B$25,'Constr. Wage Rate Calculations'!$A$19:$Z$288,24,FALSE) -> 0 | J15: =VLOOKUP($B$11:$B$25,'Constr. Wage Rate Calculations'!$A$19:$Z$288,25,FALSE) -> 0 | K15: =IF($D15>=1,$J15+(D15*E15)+(F15*G15)+(H15*I15),IF($F15>=1,$J15+(D15*E15)+(F15*G15)+(H15*I15),IF($H15>=1,$J15+(D15*E15)+(F15*G15)+(H15*I15),"")))
B16: =VLOOKUP($C$11:$C$25,Personnel!$A$1:$B$1234,2,FALSE) -> 0 | E16: =VLOOKUP($B$11:$B$25,'Constr. Wage Rate Calculations'!$A$19:$Z$288,22,FALSE) -> 0 | G16: =VLOOKUP($B$11:$B$25,'Constr. Wage Rate Calculations'!$A$19:$Z$288,23,FALSE) -> 0 | I16: =VLOOKUP($B$11:$B$25,'Constr. Wage Rate Calculations'!$A$19:$Z$288,24,FALSE) -> 0 | J16: =VLOOKUP($B$11:$B$25,'Constr. Wage Rate Calculations'!$A$19:$Z$288,25,FALSE) -> 0 | K16: =IF($D16>=1,$J16+(D16*E16)+(F16*G16)+(H16*I16),IF($F16>=1,$J16+(D16*E16)+(F16*G16)+(H16*I16),IF($H16>=1,$J16+(D16*E16)+(F16*G16)+(H16*I16),"")))
B17: =VLOOKUP($C$11:$C$25,Personnel!$A$1:$B$1234,2,FALSE) -> 0 | E17: =VLOOKUP($B$11:$B$25,'Constr. Wage Rate Calculations'!$A$19:$Z$288,22,FALSE) -> 0 | G17: =VLOOKUP($B$11:$B$25,'Constr. Wage Rate Calculations'!$A$19:$Z$288,23,FALSE) -> 0 | I17: =VLOOKUP($B$11:$B$25,'Constr. Wage Rate Calculations'!$A$19:$Z$288,24,FALSE) -> 0 | J17: =VLOOKUP($B$11:$B$25,'Constr. Wage Rate Calculations'!$A$19:$Z$288,25,FALSE) -> 0 | K17: =IF($D17>=1,$J17+(D17*E17)+(F17*G17)+(H17*I17),IF($F17>=1,$J17+(D17*E17)+(F17*G17)+(H17*I17),IF($H17>=1,$J17+(D17*E17)+(F17*G17)+(H17*I17),"")))
B18: =VLOOKUP($C$11:$C$25,Personnel!$A$1:$B$1234,2,FALSE) -> 0 | E18: =VLOOKUP($B$11:$B$25,'Constr. Wage Rate Calculations'!$A$19:$Z$288,22,FALSE) -> 0 | G18: =VLOOKUP($B$11:$B$25,'Constr. Wage Rate Calculations'!$A$19:$Z$288,23,FALSE) -> 0 | I18: =VLOOKUP($B$11:$B$25,'Constr. Wage Rate Calculations'!$A$19:$Z$288,24,FALSE) -> 0 | J18: =VLOOKUP($B$11:$B$25,'Constr. Wage Rate Calculations'!$A$19:$Z$288,25,FALSE) -> 0 | K18: =IF($D18>=1,$J18+(D18*E18)+(F18*G18)+(H18*I18),IF($F18>=1,$J18+(D18*E18)+(F18*G18)+(H18*I18),IF($H18>=1,$J18+(D18*E18)+(F18*G18)+(H18*I18),"")))
B19: =VLOOKUP($C$11:$C$25,Personnel!$A$1:$B$1234,2,FALSE) -> 0 | E19: =VLOOKUP($B$11:$B$25,'Constr. Wage Rate Calculations'!$A$19:$Z$288,22,FALSE) -> 0 | G19: =VLOOKUP($B$11:$B$25,'Constr. Wage Rate Calculations'!$A$19:$Z$288,23,FALSE) -> 0 | I19: =VLOOKUP($B$11:$B$25,'Constr. Wage Rate Calculations'!$A$19:$Z$288,24,FALSE) -> 0 | J19: =VLOOKUP($B$11:$B$25,'Constr. Wage Rate Calculations'!$A$19:$Z$288,25,FALSE) -> 0 | K19: =IF($D19>=1,$J19+(D19*E19)+(F19*G19)+(H19*I19),IF($F19>=1,$J19+(D19*E19)+(F19*G19)+(H19*I19),IF($H19>=1,$J19+(D19*E19)+(F19*G19)+(H19*I19),"")))
B20: =VLOOKUP($C$11:$C$25,Personnel!$A$1:$B$1234,2,FALSE) -> 0 | E20: =VLOOKUP($B$11:$B$25,'Constr. Wage Rate Calculations'!$A$19:$Z$288,22,FALSE) -> 0 | G20: =VLOOKUP($B$11:$B$25,'Constr. Wage Rate Calculations'!$A$19:$Z$288,23,FALSE) -> 0 | I20: =VLOOKUP($B$11:$B$25,'Constr. Wage Rate Calculations'!$A$19:$Z$288,24,FALSE) -> 0 | J20: =VLOOKUP($B$11:$B$25,'Constr. Wage Rate Calculations'!$A$19:$Z$288,25,FALSE) -> 0 | K20: =IF($D20>=1,$J20+(D20*E20)+(F20*G20)+(H20*I20),IF($F20>=1,$J20+(D20*E20)+(F20*G20)+(H20*I20),IF($H20>=1,$J20+(D20*E20)+(F20*G20)+(H20*I20),"")))
B21: =VLOOKUP($C$11:$C$25,Personnel!$A$1:$B$1234,2,FALSE) -> 0 | E21: =VLOOKUP($B$11:$B$25,'Constr. Wage Rate Calculations'!$A$19:$Z$288,22,FALSE) -> 0 | G21: =VLOOKUP($B$11:$B$25,'Constr. Wage Rate Calculations'!$A$19:$Z$288,23,FALSE) -> 0 | I21: =VLOOKUP($B$11:$B$25,'Constr. Wage Rate Calculations'!$A$19:$Z$288,24,FALSE) -> 0 | J21: =VLOOKUP($B$11:$B$25,'Constr. Wage Rate Calculations'!$A$19:$Z$288,25,FALSE) -> 0 | K21: =IF($D21>=1,$J21+(D21*E21)+(F21*G21)+(H21*I21),IF($F21>=1,$J21+(D21*E21)+(F21*G21)+(H21*I21),IF($H21>=1,$J21+(D21*E21)+(F21*G21)+(H21*I21),"")))
B22: =VLOOKUP($C$11:$C$25,Personnel!$A$1:$B$1234,2,FALSE) -> 0 | E22: =VLOOKUP($B$11:$B$25,'Constr. Wage Rate Calculations'!$A$19:$Z$288,22,FALSE) -> 0 | G22: =VLOOKUP($B$11:$B$25,'Constr. Wage Rate Calculations'!$A$19:$Z$288,23,FALSE) -> 0 | I22: =VLOOKUP($B$11:$B$25,'Constr. Wage Rate Calculations'!$A$19:$Z$288,24,FALSE) -> 0 | J22: =VLOOKUP($B$11:$B$25,'Constr. Wage Rate Calculations'!$A$19:$Z$288,25,FALSE) -> 0 | K22: =IF($D22>=1,$J22+(D22*E22)+(F22*G22)+(H22*I22),IF($F22>=1,$J22+(D22*E22)+(F22*G22)+(H22*I22),IF($H22>=1,$J22+(D22*E22)+(F22*G22)+(H22*I22),"")))
... B24: =VLOOKUP($C$11:$C$25,Personnel!$A$1:$B$1234,2,FALSE) -> 0 | E24: =VLOOKUP($B$11:$B$25,'Constr. Wage Rate Calculations'!$A$19:$Z$288,22,FALSE) -> 0 | G24: =VLOOKUP($B$11:$B$25,'Constr. Wage Rate Calculations'!$A$19:$Z$288,23,FALSE) -> 0 | I24: =VLOOKUP($B$11:$B$25,'Constr. Wage Rate Calculations'!$A$19:$Z$288,24,FALSE) -> 0 | J24: =VLOOKUP($B$11:$B$25,'Constr. Wage Rate Calculations'!$A$19:$Z$288,25,FALSE) -> 0 | K24: =IF($D24>=1,$J24+(D24*E24)+(F24*G24)+(H24*I24),IF($F24>=1,$J24+(D24*E24)+(F24*G24)+(H24*I24),IF($H24>=1,$J24+(D24*E24)+(F24*G24)+(H24*I24),"")))
B25: =VLOOKUP($C$11:$C$25,Personnel!$A$1:$B$1234,2,FALSE) -> 0 | E25: =VLOOKUP($B$11:$B$25,'Constr. Wage Rate Calculations'!$A$19:$Z$288,22,FALSE) -> 0 | G25: =VLOOKUP($B$11:$B$25,'Constr. Wage Rate Calculations'!$A$19:$Z$288,23,FALSE) -> 0 | I25: =VLOOKUP($B$11:$B$25,'Constr. Wage Rate Calculations'!$A$19:$Z$288,24,FALSE) -> 0 | J25: =VLOOKUP($B$11:$B$25,'Constr. Wage Rate Calculations'!$A$19:$Z$288,25,FALSE) -> 0 | K25: =IF($D25>=1,$J25+(D25*E25)+(F25*G25)+(H25*I25),IF($F25>=1,$J25+(D25*E25)+(F25*G25)+(H25*I25),IF($H25>=1,$J25+(D25*E25)+(F25*G25)+(H25*I25),""))) | M25: =SUM(M11:M24) -> 0
I26: TOTAL LABOUR | K26: =SUM(K11:K25) -> 0 | M26: =SUMIFS(D11:D25,D11:D25,"<3",D11:D25,"<5") -> 0 | N26: =SUMIFS(D11:D25,D11:D25,">3",D11:D25,">5") -> 0 | O26: =SUM(F11:F25,H11:H25,M26,N26)-M25 -> 0
A28: Equipment ID | B28: Equipment | H28: Days | I28: Hrs. | J28: Rate | K28: Total
B29: =VLOOKUP($C$29:$C$42,Equipment!$A$1:$B$2322,2,FALSE) -> 0 | J29: =VLOOKUP($B$29:$B$42,'Alberta Equip. Rates Year 3'!$B$13:$K$314,10,FALSE) -> 0 | K29: =(H29+I29)*J29 -> 0
B30: =VLOOKUP($C$29:$C$42,Equipment!$A$1:$B$2322,2,FALSE) -> 0 | J30: =VLOOKUP($B$29:$B$42,'Alberta Equip. Rates Year 3'!$B$13:$K$314,10,FALSE) -> 0 | K30: =(H30+I30)*J30 -> 0
B31: =VLOOKUP($C$29:$C$42,Equipment!$A$1:$B$2322,2,FALSE) -> 0 | J31: =VLOOKUP($B$29:$B$42,'Alberta Equip. Rates Year 3'!$B$13:$K$314,10,FALSE) -> 0 | K31: =(H31+I31)*J31 -> 0
B32: =VLOOKUP($C$29:$C$42,Equipment!$A$1:$B$2322,2,FALSE) -> 0 | J32: =VLOOKUP($B$29:$B$42,'Alberta Equip. Rates Year 3'!$B$13:$K$314,10,FALSE) -> 0 | K32: =(H32+I32)*J32 -> 0
B33: =VLOOKUP($C$29:$C$42,Equipment!$A$1:$B$2322,2,FALSE) -> 0 | J33: =VLOOKUP($B$29:$B$42,'Alberta Equip. Rates Year 3'!$B$13:$K$314,10,FALSE) -> 0 | K33: =(H33+I33)*J33 -> 0
B34: =VLOOKUP($C$29:$C$42,Equipment!$A$1:$B$2322,2,FALSE) -> 0 | J34: =VLOOKUP($B$29:$B$42,'Alberta Equip. Rates Year 3'!$B$13:$K$314,10,FALSE) -> 0 | K34: =(H34+I34)*J34 -> 0
B35: =VLOOKUP($C$29:$C$42,Equipment!$A$1:$B$2322,2,FALSE) -> 0 | J35: =VLOOKUP($B$29:$B$42,'Alberta Equip. Rates Year 3'!$B$13:$K$314,10,FALSE) -> 0 | K35: =(H35+I35)*J35 -> 0
B36: =VLOOKUP($C$29:$C$42,Equipment!$A$1:$B$2322,2,FALSE) -> 0 | J36: =VLOOKUP($B$29:$B$42,'Alberta Equip. Rates Year 3'!$B$13:$K$314,10,FALSE) -> 0 | K36: =(H36+I36)*J36 -> 0
B37: =VLOOKUP($C$29:$C$42,Equipment!$A$1:$B$2322,2,FALSE) -> 0 | J37: =VLOOKUP($B$29:$B$42,'Alberta Equip. Rates Year 3'!$B$13:$K$314,10,FALSE) -> 0 | K37: =(H37+I37)*J37 -> 0
B38: =VLOOKUP($C$29:$C$42,Equipment!$A$1:$B$2322,2,FALSE) -> 0 | J38: =VLOOKUP($B$29:$B$42,'Alberta Equip. Rates Year 3'!$B$13:$K$314,10,FALSE) -> 0 | K38: =(H38+I38)*J38 -> 0
B39: =VLOOKUP($C$29:$C$42,Equipment!$A$1:$B$2322,2,FALSE) -> 0 | J39: =VLOOKUP($B$29:$B$42,'Alberta Equip. Rates Year 3'!$B$13:$K$314,10,FALSE) -> 0 | K39: =(H39+I39)*J39 -> 0
B40: =VLOOKUP($C$29:$C$42,Equipment!$A$1:$B$2322,2,FALSE) -> 0 | J40: =VLOOKUP($B$29:$B$42,'Alberta Equip. Rates Year 3'!$B$13:$K$314,10,FALSE) -> 0 | K40: =(H40+I40)*J40 -> 0
... B42: =VLOOKUP($C$29:$C$42,Equipment!$A$1:$B$2322,2,FALSE) -> 0 | J42: =VLOOKUP($B$29:$B$42,'Alberta Equip. Rates Year 3'!$B$13:$K$314,10,FALSE) -> 0 | K42: =(H42+I42)*J42 -> 0
I43: TOTAL EQUIPMENT | K43: =SUM(K29:K42) -> 0
A45: Scope of Work: | I45: LABOUR | K45: =K26 -> 0
I46: EQUIPMENT | K46: =K43 -> 0
I47: SMALL TOOLS | K47: =(O26)*14.15 -> 0
I48: MATERIALS
I49: TRUCKING
I50: SUBCONTRACTORS
I51: FIELD LOG TOTAL* | K51: =SUM(K45:K50) -> 0
A53: Client: | H53: Company Representitive:
A55: * Field Log Total does no include markups
A56: 41218.479

Sheet Field Log (38)
J1: Date:
G6: Field Log ID: | J6: Status:
A7: Address: | G7: Account #: | J7: Account:
G8: Foreman:
A10: Employee ID | B10: Labor Type | C10: Employee | D10: RT Hours | E10: RT Rate | F10: OT Hours | G10: OT Rate | H10: DT Hours | I10: DT Rate | J10: Sub. | K10: Total | M10: Additional Hours
B11: =VLOOKUP($C$11:$C$36,Personnel!$A$1:$B$1234,2,FALSE) -> 0 | E11: =VLOOKUP($B$11:$B$36,'Constr. Wage Rate Calculations'!$A$19:$Z$288,22,FALSE) -> 0 | G11: =VLOOKUP($B$11:$B$36,'Constr. Wage Rate Calculations'!$A$19:$Z$288,23,FALSE) -> 0 | I11: =VLOOKUP($B$11:$B$36,'Constr. Wage Rate Calculations'!$A$19:$Z$288,24,FALSE) -> 0 | J11: =VLOOKUP($B$11:$B$36,'Constr. Wage Rate Calculations'!$A$19:$Z$288,25,FALSE) -> 0 | K11: =IF($D11>=1,$J11+(D11*E11)+(F11*G11)+(H11*I11),IF($F11>=1,$J11+(D11*E11)+(F11*G11)+(H11*I11),IF($H11>=1,$J11+(D11*E11)+(F11*G11)+(H11*I11),"")))
B12: =VLOOKUP($C$11:$C$36,Personnel!$A$1:$B$1234,2,FALSE) -> 0 | E12: =VLOOKUP($B$11:$B$36,'Constr. Wage Rate Calculations'!$A$19:$Z$288,22,FALSE) -> 0 | G12: =VLOOKUP($B$11:$B$36,'Constr. Wage Rate Calculations'!$A$19:$Z$288,23,FALSE) -> 0 | I12: =VLOOKUP($B$11:$B$36,'Constr. Wage Rate Calculations'!$A$19:$Z$288,24,FALSE) -> 0 | J12: =VLOOKUP($B$11:$B$36,'Constr. Wage Rate Calculations'!$A$19:$Z$288,25,FALSE) -> 0 | K12: =IF($D12>=1,$J12+(D12*E12)+(F12*G12)+(H12*I12),IF($F12>=1,$J12+(D12*E12)+(F12*G12)+(H12*I12),IF($H12>=1,$J12+(D12*E12)+(F12*G12)+(H12*I12),"")))
B13: =VLOOKUP($C$11:$C$36,Personnel!$A$1:$B$1234,2,FALSE) -> 0 | E13: =VLOOKUP($B$11:$B$36,'Constr. Wage Rate Calculations'!$A$19:$Z$288,22,FALSE) -> 0 | G13: =VLOOKUP($B$11:$B$36,'Constr. Wage Rate Calculations'!$A$19:$Z$288,23,FALSE) -> 0 | I13: =VLOOKUP($B$11:$B$36,'Constr. Wage Rate Calculations'!$A$19:$Z$288,24,FALSE) -> 0 | J13: =VLOOKUP($B$11:$B$36,'Constr. Wage Rate Calculations'!$A$19:$Z$288,25,FALSE) -> 0 | K13: =IF($D13>=1,$J13+(D13*E13)+(F13*G13)+(H13*I13),IF($F13>=1,$J13+(D13*E13)+(F13*G13)+(H13*I13),IF($H13>=1,$J13+(D13*E13)+(F13*G13)+(H13*I13),"")))
B14: =VLOOKUP($C$11:$C$36,Personnel!$A$1:$B$1234,2,FALSE) -> 0 | E14: =VLOOKUP($B$11:$B$36,'Constr. Wage Rate Calculations'!$A$19:$Z$288,22,FALSE) -> 0 | G14: =VLOOKUP($B$11:$B$36,'Constr. Wage Rate Calculations'!$A$19:$Z$288,23,FALSE) -> 0 | I14: =VLOOKUP($B$11:$B$36,'Constr. Wage Rate Calculations'!$A$19:$Z$288,24,FALSE) -> 0 | J14: =VLOOKUP($B$11:$B$36,'Constr. Wage Rate Calculations'!$A$19:$Z$288,25,FALSE) -> 0 | K14: =IF($D14>=1,$J14+(D14*E14)+(F14*G14)+(H14*I14),IF($F14>=1,$J14+(D14*E14)+(F14*G14)+(H14*I14),IF($H14>=1,$J14+(D14*E14)+(F14*G14)+(H14*I14),"")))
B15: =VLOOKUP($C$11:$C$36,Personnel!$A$1:$B$1234,2,FALSE) -> 0 | E15: =VLOOKUP($B$11:$B$36,'Constr. Wage Rate Calculations'!$A$19:$Z$288,22,FALSE) -> 0 | G15: =VLOOKUP($B$11:$B$36,'Constr. Wage Rate Calculations'!$A$19:$Z$288,23,FALSE) -> 0 | I15: =VLOOKUP($B$11:$B$36,'Constr. Wage Rate Calculations'!$A$19:$Z$288,24,FALSE) -> 0 | J15: =VLOOKUP($B$11:$B$36,'Constr. Wage Rate Calculations'!$A$19:$Z$288,25,FALSE) -> 0 | K15: =IF($D15>=1,$J15+(D15*E15)+(F15*G15)+(H15*I15),IF($F15>=1,$J15+(D15*E15)+(F15*G15)+(H15*I15),IF($H15>=1,$J15+(D15*E15)+(F15*G15)+(H15*I15),"")))
B16: =VLOOKUP($C$11:$C$36,Personnel!$A$1:$B$1234,2,FALSE) -> 0 | E16: =VLOOKUP($B$11:$B$36,'Constr. Wage Rate Calculations'!$A$19:$Z$288,22,FALSE) -> 0 | G16: =VLOOKUP($B$11:$B$36,'Constr. Wage Rate Calculations'!$A$19:$Z$288,23,FALSE) -> 0 | I16: =VLOOKUP($B$11:$B$36,'Constr. Wage Rate Calculations'!$A$19:$Z$288,24,FALSE) -> 0 | J16: =VLOOKUP($B$11:$B$36,'Constr. Wage Rate Calculations'!$A$19:$Z$288,25,FALSE) -> 0 | K16: =IF($D16>=1,$J16+(D16*E16)+(F16*G16)+(H16*I16),IF($F16>=1,$J16+(D16*E16)+(F16*G16)+(H16*I16),IF($H16>=1,$J16+(D16*E16)+(F16*G16)+(H16*I16),"")))
B17: =VLOOKUP($C$11:$C$36,Personnel!$A$1:$B$1234,2,FALSE) -> 0 | E17: =VLOOKUP($B$11:$B$36,'Constr. Wage Rate Calculations'!$A$19:$Z$288,22,FALSE) -> 0 | G17: =VLOOKUP($B$11:$B$36,'Constr. Wage Rate Calculations'!$A$19:$Z$288,23,FALSE) -> 0 | I17: =VLOOKUP($B$11:$B$36,'Constr. Wage Rate Calculations'!$A$19:$Z$288,24,FALSE) -> 0 | J17: =VLOOKUP($B$11:$B$36,'Constr. Wage Rate Calculations'!$A$19:$Z$288,25,FALSE) -> 0 | K17: =IF($D17>=1,$J17+(D17*E17)+(F17*G17)+(H17*I17),IF($F17>=1,$J17+(D17*E17)+(F17*G17)+(H17*I17),IF($H17>=1,$J17+(D17*E17)+(F17*G17)+(H17*I17),"")))
B18: =VLOOKUP($C$11:$C$36,Personnel!$A$1:$B$1234,2,FALSE) -> 0 | E18: =VLOOKUP($B$11:$B$36,'Constr. Wage Rate Calculations'!$A$19:$Z$288,22,FALSE) -> 0 | G18: =VLOOKUP($B$11:$B$36,'Constr. Wage Rate Calculations'!$A$19:$Z$288,23,FALSE) -> 0 | I18: =VLOOKUP($B$11:$B$36,'Constr. Wage Rate Calculations'!$A$19:$Z$288,24,FALSE) -> 0 | J18: =VLOOKUP($B$11:$B$36,'Constr. Wage Rate Calculations'!$A$19:$Z$288,25,FALSE) -> 0 | K18: =IF($D18>=1,$J18+(D18*E18)+(F18*G18)+(H18*I18),IF($F18>=1,$J18+(D18*E18)+(F18*G18)+(H18*I18),IF($H18>=1,$J18+(D18*E18)+(F18*G18)+(H18*I18),"")))
B19: =VLOOKUP($C$11:$C$36,Personnel!$A$1:$B$1234,2,FALSE) -> 0 | E19: =VLOOKUP($B$11:$B$36,'Constr. Wage Rate Calculations'!$A$19:$Z$288,22,FALSE) -> 0 | G19: =VLOOKUP($B$11:$B$36,'Constr. Wage Rate Calculations'!$A$19:$Z$288,23,FALSE) -> 0 | I19: =VLOOKUP($B$11:$B$36,'Constr. Wage Rate Calculations'!$A$19:$Z$288,24,FALSE) -> 0 | J19: =VLOOKUP($B$11:$B$36,'Constr. Wage Rate Calculations'!$A$19:$Z$288,25,FALSE) -> 0 | K19: =IF($D19>=1,$J19+(D19*E19)+(F19*G19)+(H19*I19),IF($F19>=1,$J19+(D19*E19)+(F19*G19)+(H19*I19),IF($H19>=1,$J19+(D19*E19)+(F19*G19)+(H19*I19),"")))
B20: =VLOOKUP($C$11:$C$36,Personnel!$A$1:$B$1234,2,FALSE) -> 0 | E20: =VLOOKUP($B$11:$B$36,'Constr. Wage Rate Calculations'!$A$19:$Z$288,22,FALSE) -> 0 | G20: =VLOOKUP($B$11:$B$36,'Constr. Wage Rate Calculations'!$A$19:$Z$288,23,FALSE) -> 0 | I20: =VLOOKUP($B$11:$B$36,'Constr. Wage Rate Calculations'!$A$19:$Z$288,24,FALSE) -> 0 | J20: =VLOOKUP($B$11:$B$36,'Constr. Wage Rate Calculations'!$A$19:$Z$288,25,FALSE) -> 0 | K20: =IF($D20>=1,$J20+(D20*E20)+(F20*G20)+(H20*I20),IF($F20>=1,$J20+(D20*E20)+(F20*G20)+(H20*I20),IF($H20>=1,$J20+(D20*E20)+(F20*G20)+(H20*I20),"")))
B21: =VLOOKUP($C$11:$C$36,Personnel!$A$1:$B$1234,2,FALSE) -> 0 | E21: =VLOOKUP($B$11:$B$36,'Constr. Wage Rate Calculations'!$A$19:$Z$288,22,FALSE) -> 0 | G21: =VLOOKUP($B$11:$B$36,'Constr. Wage Rate Calculations'!$A$19:$Z$288,23,FALSE) -> 0 | I21: =VLOOKUP($B$11:$B$36,'Constr. Wage Rate Calculations'!$A$19:$Z$288,24,FALSE) -> 0 | J21: =VLOOKUP($B$11:$B$36,'Constr. Wage Rate Calculations'!$A$19:$Z$288,25,FALSE) -> 0 | K21: =IF($D21>=1,$J21+(D21*E21)+(F21*G21)+(H21*I21),IF($F21>=1,$J21+(D21*E21)+(F21*G21)+(H21*I21),IF($H21>=1,$J21+(D21*E21)+(F21*G21)+(H21*I21),"")))
B22: =VLOOKUP($C$11:$C$36,Personnel!$A$1:$B$1234,2,FALSE) -> 0 | E22: =VLOOKUP($B$11:$B$36,'Constr. Wage Rate Calculations'!$A$19:$Z$288,22,FALSE) -> 0 | G22: =VLOOKUP($B$11:$B$36,'Constr. Wage Rate Calculations'!$A$19:$Z$288,23,FALSE) -> 0 | I22: =VLOOKUP($B$11:$B$36,'Constr. Wage Rate Calculations'!$A$19:$Z$288,24,FALSE) -> 0 | J22: =VLOOKUP($B$11:$B$36,'Constr. Wage Rate Calculations'!$A$19:$Z$288,25,FALSE) -> 0 | K22: =IF($D22>=1,$J22+(D22*E22)+(F22*G22)+(H22*I22),IF($F22>=1,$J22+(D22*E22)+(F22*G22)+(H22*I22),IF($H22>=1,$J22+(D22*E22)+(F22*G22)+(H22*I22),"")))
... B35: =VLOOKUP($C$11:$C$36,Personnel!$A$1:$B$1234,2,FALSE) -> 0 | E35: =VLOOKUP($B$11:$B$36,'Constr. Wage Rate Calculations'!$A$19:$Z$288,22,FALSE) -> 0 | G35: =VLOOKUP($B$11:$B$36,'Constr. Wage Rate Calculations'!$A$19:$Z$288,23,FALSE) -> 0 | I35: =VLOOKUP($B$11:$B$36,'Constr. Wage Rate Calculations'!$A$19:$Z$288,24,FALSE) -> 0 | J35: =VLOOKUP($B$11:$B$36,'Constr. Wage Rate Calculations'!$A$19:$Z$288,25,FALSE) -> 0 | K35: =IF($D35>=1,$J35+(D35*E35)+(F35*G35)+(H35*I35),IF($F35>=1,$J35+(D35*E35)+(F35*G35)+(H35*I35),IF($H35>=1,$J35+(D35*E35)+(F35*G35)+(H35*I35),"")))
B36: =VLOOKUP($C$11:$C$36,Personnel!$A$1:$B$1234,2,FALSE) -> 0 | E36: =VLOOKUP($B$11:$B$36,'Constr. Wage Rate Calculations'!$A$19:$Z$288,22,FALSE) -> 0 | G36: =VLOOKUP($B$11:$B$36,'Constr. Wage Rate Calculations'!$A$19:$Z$288,23,FALSE) -> 0 | I36: =VLOOKUP($B$11:$B$36,'Constr. Wage Rate Calculations'!$A$19:$Z$288,24,FALSE) -> 0 | J36: =VLOOKUP($B$11:$B$36,'Constr. Wage Rate Calculations'!$A$19:$Z$288,25,FALSE) -> 0 | K36: =IF($D36>=1,$J36+(D36*E36)+(F36*G36)+(H36*I36),IF($F36>=1,$J36+(D36*E36)+(F36*G36)+(H36*I36),IF($H36>=1,$J36+(D36*E36)+(F36*G36)+(H36*I36),""))) | M36: =SUM(M11:M35) -> 0
I37: TOTAL LABOUR | K37: =SUM(K11:K36) -> 0 | M37: =SUMIFS(D11:D36,D11:D36,"<3",D11:D36,"<5") -> 0 | N37: =SUMIFS(D11:D36,D11:D36,">3",D11:D36,">5") -> 0 | O37: =SUM(F11:F36,H11:H36,M37,N37)-M36 -> 0
A39: Equipment ID | B39: Equipment | H39: Days | I39: Hrs. | J39: Rate | K39: Total
B40: =VLOOKUP($C$40:$C$61,Equipment!$A$1:$B$2322,2,FALSE) -> 0 | J40: =VLOOKUP($B$40:$B$61,'Alberta Equip. Rates Year 3'!$B$13:$K$314,10,FALSE) -> 0 | K40: =(H40+I40)*J40 -> 0
B41: =VLOOKUP($C$40:$C$61,Equipment!$A$1:$B$2322,2,FALSE) -> 0 | J41: =VLOOKUP($B$40:$B$61,'Alberta Equip. Rates Year 3'!$B$13:$K$314,10,FALSE) -> 0 | K41: =(H41+I41)*J41 -> 0
B42: =VLOOKUP($C$40:$C$61,Equipment!$A$1:$B$2322,2,FALSE) -> 0 | J42: =VLOOKUP($B$40:$B$61,'Alberta Equip. Rates Year 3'!$B$13:$K$314,10,FALSE) -> 0 | K42: =(H42+I42)*J42 -> 0
B43: =VLOOKUP($C$40:$C$61,Equipment!$A$1:$B$2322,2,FALSE) -> 0 | J43: =VLOOKUP($B$40:$B$61,'Alberta Equip. Rates Year 3'!$B$13:$K$314,10,FALSE) -> 0 | K43: =(H43+I43)*J43 -> 0
B44: =VLOOKUP($C$40:$C$61,Equipment!$A$1:$B$2322,2,FALSE) -> 0 | J44: =VLOOKUP($B$40:$B$61,'Alberta Equip. Rates Year 3'!$B$13:$K$314,10,FALSE) -> 0 | K44: =(H44+I44)*J44 -> 0
B45: =VLOOKUP($C$40:$C$61,Equipment!$A$1:$B$2322,2,FALSE) -> 0 | J45: =VLOOKUP($B$40:$B$61,'Alberta Equip. Rates Year 3'!$B$13:$K$314,10,FALSE) -> 0 | K45: =(H45+I45)*J45 -> 0
B46: =VLOOKUP($C$40:$C$61,Equipment!$A$1:$B$2322,2,FALSE) -> 0 | J46: =VLOOKUP($B$40:$B$61,'Alberta Equip. Rates Year 3'!$B$13:$K$314,10,FALSE) -> 0 | K46: =(H46+I46)*J46 -> 0
B47: =VLOOKUP($C$40:$C$61,Equipment!$A$1:$B$2322,2,FALSE) -> 0 | J47: =VLOOKUP($B$40:$B$61,'Alberta Equip. Rates Year 3'!$B$13:$K$314,10,FALSE) -> 0 | K47: =(H47+I47)*J47 -> 0
B48: =VLOOKUP($C$40:$C$61,Equipment!$A$1:$B$2322,2,FALSE) -> 0 | J48: =VLOOKUP($B$40:$B$61,'Alberta Equip. Rates Year 3'!$B$13:$K$314,10,FALSE) -> 0 | K48: =(H48+I48)*J48 -> 0
B49: =VLOOKUP($C$40:$C$61,Equipment!$A$1:$B$2322,2,FALSE) -> 0 | J49: =VLOOKUP($B$40:$B$61,'Alberta Equip. Rates Year 3'!$B$13:$K$314,10,FALSE) -> 0 | K49: =(H49+I49)*J49 -> 0
B50: =VLOOKUP($C$40:$C$61,Equipment!$A$1:$B$2322,2,FALSE) -> 0 | J50: =VLOOKUP($B$40:$B$61,'Alberta Equip. Rates Year 3'!$B$13:$K$314,10,FALSE) -> 0 | K50: =(H50+I50)*J50 -> 0
B51: =VLOOKUP($C$40:$C$61,Equipment!$A$1:$B$2322,2,FALSE) -> 0 | J51: =VLOOKUP($B$40:$B$61,'Alberta Equip. Rates Year 3'!$B$13:$K$314,10,FALSE) -> 0 | K51: =(H51+I51)*J51 -> 0
... B61: =VLOOKUP($C$40:$C$61,Equipment!$A$1:$B$2322,2,FALSE) -> 0 | J61: =VLOOKUP($B$40:$B$61,'Alberta Equip. Rates Year 3'!$B$13:$K$314,10,FALSE) -> 0 | K61: =(H61+I61)*J61 -> 0
I62: TOTAL EQUIPMENT | K62: =SUM(K40:K61) -> 0
A64: Scope of Work: | I64: LABOUR | K64: =K37 -> 0
I65: EQUIPMENT | K65: =K62 -> 0
I66: SMALL TOOLS | K66: =(O37)*14.15 -> 0
I67: MATERIALS
I68: TRUCKING
I69: SUBCONTRACTORS
I70: FIELD LOG TOTAL* | K70: =SUM(K64:K69) -> 0
A72: Client: | H72: Company Representitive:
A74: * Field Log Total does no include markups
A75: 41218.479

Sheet Field Log (37)
J1: Date:
G6: Field Log ID: | J6: Status:
A7: Address: | G7: Account #: | J7: Account:
G8: Foreman:
A10: Employee ID | B10: Labor Type | C10: Employee | D10: RT Hours | E10: RT Rate | F10: OT Hours | G10: OT Rate | H10: DT Hours | I10: DT Rate | J10: Sub. | K10: Total | M10: Additional Hours
B11: =VLOOKUP($C$11:$C$25,Personnel!$A$1:$B$1234,2,FALSE) -> 0 | E11: =VLOOKUP($B$11:$B$25,'Constr. Wage Rate Calculations'!$A$19:$Z$288,22,FALSE) -> 0 | G11: =VLOOKUP($B$11:$B$25,'Constr. Wage Rate Calculations'!$A$19:$Z$288,23,FALSE) -> 0 | I11: =VLOOKUP($B$11:$B$25,'Constr. Wage Rate Calculations'!$A$19:$Z$288,24,FALSE) -> 0 | J11: =VLOOKUP($B$11:$B$25,'Constr. Wage Rate Calculations'!$A$19:$Z$288,25,FALSE) -> 0 | K11: =IF($D11>=1,$J11+(D11*E11)+(F11*G11)+(H11*I11),IF($F11>=1,$J11+(D11*E11)+(F11*G11)+(H11*I11),IF($H11>=1,$J11+(D11*E11)+(F11*G11)+(H11*I11),"")))
B12: =VLOOKUP($C$11:$C$25,Personnel!$A$1:$B$1234,2,FALSE) -> 0 | E12: =VLOOKUP($B$11:$B$25,'Constr. Wage Rate Calculations'!$A$19:$Z$288,22,FALSE) -> 0 | G12: =VLOOKUP($B$11:$B$25,'Constr. Wage Rate Calculations'!$A$19:$Z$288,23,FALSE) -> 0 | I12: =VLOOKUP($B$11:$B$25,'Constr. Wage Rate Calculations'!$A$19:$Z$288,24,FALSE) -> 0 | K12: =IF($D12>=1,$J12+(D12*E12)+(F12*G12)+(H12*I12),IF($F12>=1,$J12+(D12*E12)+(F12*G12)+(H12*I12),IF($H12>=1,$J12+(D12*E12)+(F12*G12)+(H12*I12),"")))
B13: =VLOOKUP($C$11:$C$25,Personnel!$A$1:$B$1234,2,FALSE) -> 0 | E13: =VLOOKUP($B$11:$B$25,'Constr. Wage Rate Calculations'!$A$19:$Z$288,22,FALSE) -> 0 | G13: =VLOOKUP($B$11:$B$25,'Constr. Wage Rate Calculations'!$A$19:$Z$288,23,FALSE) -> 0 | I13: =VLOOKUP($B$11:$B$25,'Constr. Wage Rate Calculations'!$A$19:$Z$288,24,FALSE) -> 0 | J13: =VLOOKUP($B$11:$B$25,'Constr. Wage Rate Calculations'!$A$19:$Z$288,25,FALSE) -> 0 | K13: =IF($D13>=1,$J13+(D13*E13)+(F13*G13)+(H13*I13),IF($F13>=1,$J13+(D13*E13)+(F13*G13)+(H13*I13),IF($H13>=1,$J13+(D13*E13)+(F13*G13)+(H13*I13),"")))
B14: =VLOOKUP($C$11:$C$25,Personnel!$A$1:$B$1234,2,FALSE) -> 0 | E14: =VLOOKUP($B$11:$B$25,'Constr. Wage Rate Calculations'!$A$19:$Z$288,22,FALSE) -> 0 | G14: =VLOOKUP($B$11:$B$25,'Constr. Wage Rate Calculations'!$A$19:$Z$288,23,FALSE) -> 0 | I14: =VLOOKUP($B$11:$B$25,'Constr. Wage Rate Calculations'!$A$19:$Z$288,24,FALSE) -> 0 | J14: =VLOOKUP($B$11:$B$25,'Constr. Wage Rate Calculations'!$A$19:$Z$288,25,FALSE) -> 0 | K14: =IF($D14>=1,$J14+(D14*E14)+(F14*G14)+(H14*I14),IF($F14>=1,$J14+(D14*E14)+(F14*G14)+(H14*I14),IF($H14>=1,$J14+(D14*E14)+(F14*G14)+(H14*I14),"")))
B15: =VLOOKUP($C$11:$C$25,Personnel!$A$1:$B$1234,2,FALSE) -> 0 | E15: =VLOOKUP($B$11:$B$25,'Constr. Wage Rate Calculations'!$A$19:$Z$288,22,FALSE) -> 0 | G15: =VLOOKUP($B$11:$B$25,'Constr. Wage Rate Calculations'!$A$19:$Z$288,23,FALSE) -> 0 | I15: =VLOOKUP($B$11:$B$25,'Constr. Wage Rate Calculations'!$A$19:$Z$288,24,FALSE) -> 0 | J15: =VLOOKUP($B$11:$B$25,'Constr. Wage Rate Calculations'!$A$19:$Z$288,25,FALSE) -> 0 | K15: =IF($D15>=1,$J15+(D15*E15)+(F15*G15)+(H15*I15),IF($F15>=1,$J15+(D15*E15)+(F15*G15)+(H15*I15),IF($H15>=1,$J15+(D15*E15)+(F15*G15)+(H15*I15),"")))
B16: =VLOOKUP($C$11:$C$25,Personnel!$A$1:$B$1234,2,FALSE) -> 0 | E16: =VLOOKUP($B$11:$B$25,'Constr. Wage Rate Calculations'!$A$19:$Z$288,22,FALSE) -> 0 | G16: =VLOOKUP($B$11:$B$25,'Constr. Wage Rate Calculations'!$A$19:$Z$288,23,FALSE) -> 0 | I16: =VLOOKUP($B$11:$B$25,'Constr. Wage Rate Calculations'!$A$19:$Z$288,24,FALSE) -> 0 | J16: =VLOOKUP($B$11:$B$25,'Constr. Wage Rate Calculations'!$A$19:$Z$288,25,FALSE) -> 0 | K16: =IF($D16>=1,$J16+(D16*E16)+(F16*G16)+(H16*I16),IF($F16>=1,$J16+(D16*E16)+(F16*G16)+(H16*I16),IF($H16>=1,$J16+(D16*E16)+(F16*G16)+(H16*I16),"")))
B17: =VLOOKUP($C$11:$C$25,Personnel!$A$1:$B$1234,2,FALSE) -> 0 | E17: =VLOOKUP($B$11:$B$25,'Constr. Wage Rate Calculations'!$A$19:$Z$288,22,FALSE) -> 0 | G17: =VLOOKUP($B$11:$B$25,'Constr. Wage Rate Calculations'!$A$19:$Z$288,23,FALSE) -> 0 | I17: =VLOOKUP($B$11:$B$25,'Constr. Wage Rate Calculations'!$A$19:$Z$288,24,FALSE) -> 0 | J17: =VLOOKUP($B$11:$B$25,'Constr. Wage Rate Calculations'!$A$19:$Z$288,25,FALSE) -> 0 | K17: =IF($D17>=1,$J17+(D17*E17)+(F17*G17)+(H17*I17),IF($F17>=1,$J17+(D17*E17)+(F17*G17)+(H17*I17),IF($H17>=1,$J17+(D17*E17)+(F17*G17)+(H17*I17),"")))
B18: =VLOOKUP($C$11:$C$25,Personnel!$A$1:$B$1234,2,FALSE) -> 0 | E18: =VLOOKUP($B$11:$B$25,'Constr. Wage Rate Calculations'!$A$19:$Z$288,22,FALSE) -> 0 | G18: =VLOOKUP($B$11:$B$25,'Constr. Wage Rate Calculations'!$A$19:$Z$288,23,FALSE) -> 0 | I18: =VLOOKUP($B$11:$B$25,'Constr. Wage Rate Calculations'!$A$19:$Z$288,24,FALSE) -> 0 | J18: =VLOOKUP($B$11:$B$25,'Constr. Wage Rate Calculations'!$A$19:$Z$288,25,FALSE) -> 0 | K18: =IF($D18>=1,$J18+(D18*E18)+(F18*G18)+(H18*I18),IF($F18>=1,$J18+(D18*E18)+(F18*G18)+(H18*I18),IF($H18>=1,$J18+(D18*E18)+(F18*G18)+(H18*I18),"")))
B19: =VLOOKUP($C$11:$C$25,Personnel!$A$1:$B$1234,2,FALSE) -> 0 | E19: =VLOOKUP($B$11:$B$25,'Constr. Wage Rate Calculations'!$A$19:$Z$288,22,FALSE) -> 0 | G19: =VLOOKUP($B$11:$B$25,'Constr. Wage Rate Calculations'!$A$19:$Z$288,23,FALSE) -> 0 | I19: =VLOOKUP($B$11:$B$25,'Constr. Wage Rate Calculations'!$A$19:$Z$288,24,FALSE) -> 0 | J19: =VLOOKUP($B$11:$B$25,'Constr. Wage Rate Calculations'!$A$19:$Z$288,25,FALSE) -> 0 | K19: =IF($D19>=1,$J19+(D19*E19)+(F19*G19)+(H19*I19),IF($F19>=1,$J19+(D19*E19)+(F19*G19)+(H19*I19),IF($H19>=1,$J19+(D19*E19)+(F19*G19)+(H19*I19),"")))
B20: =VLOOKUP($C$11:$C$25,Personnel!$A$1:$B$1234,2,FALSE) -> 0 | E20: =VLOOKUP($B$11:$B$25,'Constr. Wage Rate Calculations'!$A$19:$Z$288,22,FALSE) -> 0 | G20: =VLOOKUP($B$11:$B$25,'Constr. Wage Rate Calculations'!$A$19:$Z$288,23,FALSE) -> 0 | I20: =VLOOKUP($B$11:$B$25,'Constr. Wage Rate Calculations'!$A$19:$Z$288,24,FALSE) -> 0 | J20: =VLOOKUP($B$11:$B$25,'Constr. Wage Rate Calculations'!$A$19:$Z$288,25,FALSE) -> 0 | K20: =IF($D20>=1,$J20+(D20*E20)+(F20*G20)+(H20*I20),IF($F20>=1,$J20+(D20*E20)+(F20*G20)+(H20*I20),IF($H20>=1,$J20+(D20*E20)+(F20*G20)+(H20*I20),"")))
B21: =VLOOKUP($C$11:$C$25,Personnel!$A$1:$B$1234,2,FALSE) -> 0 | E21: =VLOOKUP($B$11:$B$25,'Constr. Wage Rate Calculations'!$A$19:$Z$288,22,FALSE) -> 0 | G21: =VLOOKUP($B$11:$B$25,'Constr. Wage Rate Calculations'!$A$19:$Z$288,23,FALSE) -> 0 | I21: =VLOOKUP($B$11:$B$25,'Constr. Wage Rate Calculations'!$A$19:$Z$288,24,FALSE) -> 0 | J21: =VLOOKUP($B$11:$B$25,'Constr. Wage Rate Calculations'!$A$19:$Z$288,25,FALSE) -> 0 | K21: =IF($D21>=1,$J21+(D21*E21)+(F21*G21)+(H21*I21),IF($F21>=1,$J21+(D21*E21)+(F21*G21)+(H21*I21),IF($H21>=1,$J21+(D21*E21)+(F21*G21)+(H21*I21),"")))
B22: =VLOOKUP($C$11:$C$25,Personnel!$A$1:$B$1234,2,FALSE) -> 0 | E22: =VLOOKUP($B$11:$B$25,'Constr. Wage Rate Calculations'!$A$19:$Z$288,22,FALSE) -> 0 | G22: =VLOOKUP($B$11:$B$25,'Constr. Wage Rate Calculations'!$A$19:$Z$288,23,FALSE) -> 0 | I22: =VLOOKUP($B$11:$B$25,'Constr. Wage Rate Calculations'!$A$19:$Z$288,24,FALSE) -> 0 | J22: =VLOOKUP($B$11:$B$25,'Constr. Wage Rate Calculations'!$A$19:$Z$288,25,FALSE) -> 0 | K22: =IF($D22>=1,$J22+(D22*E22)+(F22*G22)+(H22*I22),IF($F22>=1,$J22+(D22*E22)+(F22*G22)+(H22*I22),IF($H22>=1,$J22+(D22*E22)+(F22*G22)+(H22*I22),"")))
B23: =VLOOKUP($C$11:$C$25,Personnel!$A$1:$B$1234,2,FALSE) -> 0 | E23: =VLOOKUP($B$11:$B$25,'Constr. Wage Rate Calculations'!$A$19:$Z$288,22,FALSE) -> 0 | G23: =VLOOKUP($B$11:$B$25,'Constr. Wage Rate Calculations'!$A$19:$Z$288,23,FALSE) -> 0 | I23: =VLOOKUP($B$11:$B$25,'Constr. Wage Rate Calculations'!$A$19:$Z$288,24,FALSE) -> 0 | J23: =VLOOKUP($B$11:$B$25,'Constr. Wage Rate Calculations'!$A$19:$Z$288,25,FALSE) -> 0 | K23: =IF($D23>=1,$J23+(D23*E23)+(F23*G23)+(H23*I23),IF($F23>=1,$J23+(D23*E23)+(F23*G23)+(H23*I23),IF($H23>=1,$J23+(D23*E23)+(F23*G23)+(H23*I23),"")))
B24: =VLOOKUP($C$11:$C$25,Personnel!$A$1:$B$1234,2,FALSE) -> 0 | E24: =VLOOKUP($B$11:$B$25,'Constr. Wage Rate Calculations'!$A$19:$Z$288,22,FALSE) -> 0 | G24: =VLOOKUP($B$11:$B$25,'Constr. Wage Rate Calculations'!$A$19:$Z$288,23,FALSE) -> 0 | I24: =VLOOKUP($B$11:$B$25,'Constr. Wage Rate Calculations'!$A$19:$Z$288,24,FALSE) -> 0 | J24: =VLOOKUP($B$11:$B$25,'Constr. Wage Rate Calculations'!$A$19:$Z$288,25,FALSE) -> 0 | K24: =IF($D24>=1,$J24+(D24*E24)+(F24*G24)+(H24*I24),IF($F24>=1,$J24+(D24*E24)+(F24*G24)+(H24*I24),IF($H24>=1,$J24+(D24*E24)+(F24*G24)+(H24*I24),"")))
B25: =VLOOKUP($C$11:$C$25,Personnel!$A$1:$B$1234,2,FALSE) -> 0 | E25: =VLOOKUP($B$11:$B$25,'Constr. Wage Rate Calculations'!$A$19:$Z$288,22,FALSE) -> 0 | G25: =VLOOKUP($B$11:$B$25,'Constr. Wage Rate Calculations'!$A$19:$Z$288,23,FALSE) -> 0 | I25: =VLOOKUP($B$11:$B$25,'Constr. Wage Rate Calculations'!$A$19:$Z$288,24,FALSE) -> 0 | J25: =VLOOKUP($B$11:$B$25,'Constr. Wage Rate Calculations'!$A$19:$Z$288,25,FALSE) -> 0 | K25: =IF($D25>=1,$J25+(D25*E25)+(F25*G25)+(H25*I25),IF($F25>=1,$J25+(D25*E25)+(F25*G25)+(H25*I25),IF($H25>=1,$J25+(D25*E25)+(F25*G25)+(H25*I25),""))) | M25: =SUM(M11:M24) -> 0
I26: TOTAL LABOUR | K26: =SUM(K11:K25) -> 0 | M26: =SUMIFS(D11:D25,D11:D25,"<3",D11:D25,"<5") -> 0 | N26: =SUMIFS(D11:D25,D11:D25,">3",D11:D25,">5") -> 0 | O26: =SUM(F11:F25,H11:H25,M26,N26)-M25 -> 0
A28: Equipment ID | B28: Equipment | H28: Days | I28: Hrs. | J28: Rate | K28: Total
B29: =VLOOKUP($C$29:$C$74,Equipment!$A$1:$B$2322,2,FALSE) -> 0 | J29: =VLOOKUP($B$29:$B$74,'Alberta Equip. Rates Year 3'!$B$13:$K$314,10,FALSE) -> 0 | K29: =(H29+I29)*J29 -> 0
B30: =VLOOKUP($C$29:$C$74,Equipment!$A$1:$B$2322,2,FALSE) -> 0 | J30: =VLOOKUP($B$29:$B$74,'Alberta Equip. Rates Year 3'!$B$13:$K$314,10,FALSE) -> 0 | K30: =(H30+I30)*J30 -> 0
B31: =VLOOKUP($C$29:$C$74,Equipment!$A$1:$B$2322,2,FALSE) -> 0 | J31: =VLOOKUP($B$29:$B$74,'Alberta Equip. Rates Year 3'!$B$13:$K$314,10,FALSE) -> 0 | K31: =(H31+I31)*J31 -> 0
B32: =VLOOKUP($C$29:$C$74,Equipment!$A$1:$B$2322,2,FALSE) -> 0 | J32: =VLOOKUP($B$29:$B$74,'Alberta Equip. Rates Year 3'!$B$13:$K$314,10,FALSE) -> 0 | K32: =(H32+I32)*J32 -> 0
B33: =VLOOKUP($C$29:$C$74,Equipment!$A$1:$B$2322,2,FALSE) -> 0 | J33: =VLOOKUP($B$29:$B$74,'Alberta Equip. Rates Year 3'!$B$13:$K$314,10,FALSE) -> 0 | K33: =(H33+I33)*J33 -> 0
B34: =VLOOKUP($C$29:$C$74,Equipment!$A$1:$B$2322,2,FALSE) -> 0 | J34: =VLOOKUP($B$29:$B$74,'Alberta Equip. Rates Year 3'!$B$13:$K$314,10,FALSE) -> 0 | K34: =(H34+I34)*J34 -> 0
B35: =VLOOKUP($C$29:$C$74,Equipment!$A$1:$B$2322,2,FALSE) -> 0 | J35: =VLOOKUP($B$29:$B$74,'Alberta Equip. Rates Year 3'!$B$13:$K$314,10,FALSE) -> 0 | K35: =(H35+I35)*J35 -> 0
B36: =VLOOKUP($C$29:$C$74,Equipment!$A$1:$B$2322,2,FALSE) -> 0 | J36: =VLOOKUP($B$29:$B$74,'Alberta Equip. Rates Year 3'!$B$13:$K$314,10,FALSE) -> 0 | K36: =(H36+I36)*J36 -> 0
B37: =VLOOKUP($C$29:$C$74,Equipment!$A$1:$B$2322,2,FALSE) -> 0 | J37: =VLOOKUP($B$29:$B$74,'Alberta Equip. Rates Year 3'!$B$13:$K$314,10,FALSE) -> 0 | K37: =(H37+I37)*J37 -> 0
B38: =VLOOKUP($C$29:$C$74,Equipment!$A$1:$B$2322,2,FALSE) -> 0 | J38: =VLOOKUP($B$29:$B$74,'Alberta Equip. Rates Year 3'!$B$13:$K$314,10,FALSE) -> 0 | K38: =(H38+I38)*J38 -> 0
B39: =VLOOKUP($C$29:$C$74,Equipment!$A$1:$B$2322,2,FALSE) -> 0 | J39: =VLOOKUP($B$29:$B$74,'Alberta Equip. Rates Year 3'!$B$13:$K$314,10,FALSE) -> 0 | K39: =(H39+I39)*J39 -> 0
B40: =VLOOKUP($C$29:$C$74,Equipment!$A$1:$B$2322,2,FALSE) -> 0 | J40: =VLOOKUP($B$29:$B$74,'Alberta Equip. Rates Year 3'!$B$13:$K$314,10,FALSE) -> 0 | K40: =(H40+I40)*J40 -> 0
... B74: =VLOOKUP($C$29:$C$74,Equipment!$A$1:$B$2322,2,FALSE) -> 0 | J74: =VLOOKUP($B$29:$B$74,'Alberta Equip. Rates Year 3'!$B$13:$K$314,10,FALSE) -> 0 | K74: =(H74+I74)*J74 -> 0
I75: TOTAL EQUIPMENT | K75: =SUM(K29:K74) -> 0
A77: Scope of Work: | I77: LABOUR | K77: =K26 -> 0
I78: EQUIPMENT | K78: =K75 -> 0
I79: SMALL TOOLS | K79: =(O26)*14.15 -> 0
I80: MATERIALS
I81: TRUCKING
I82: SUBCONTRACTORS
I83: FIELD LOG TOTAL* | K83: =SUM(K77:K82) -> 0
A85: Client: | H85: Company Representitive:
A87: * Field Log Total does no include markups
A88: 41218.479

Sheet Field Log (36)
J1: Date:
G6: Field Log ID: | J6: Status:
A7: Address: | G7: Account #: | J7: Account:
G8: Foreman:
A10: Employee ID | B10: Labor Type | C10: Employee | D10: RT Hours | E10: RT Rate | F10: OT Hours | G10: OT Rate | H10: DT Hours | I10: DT Rate | J10: Sub. | K10: Total | M10: Additional Hours
B11: =VLOOKUP($C$11:$C$25,Personnel!$A$1:$B$1234,2,FALSE) -> 0 | E11: =VLOOKUP($B$11:$B$25,'Constr. Wage Rate Calculations'!$A$19:$Z$288,22,FALSE) -> 0 | G11: =VLOOKUP($B$11:$B$25,'Constr. Wage Rate Calculations'!$A$19:$Z$288,23,FALSE) -> 0 | I11: =VLOOKUP($B$11:$B$25,'Constr. Wage Rate Calculations'!$A$19:$Z$288,24,FALSE) -> 0 | J11: =VLOOKUP($B$11:$B$25,'Constr. Wage Rate Calculations'!$A$19:$Z$288,25,FALSE) -> 0 | K11: =IF($D11>=1,$J11+(D11*E11)+(F11*G11)+(H11*I11),IF($F11>=1,$J11+(D11*E11)+(F11*G11)+(H11*I11),IF($H11>=1,$J11+(D11*E11)+(F11*G11)+(H11*I11),"")))
B12: =VLOOKUP($C$11:$C$25,Personnel!$A$1:$B$1234,2,FALSE) -> 0 | E12: =VLOOKUP($B$11:$B$25,'Constr. Wage Rate Calculations'!$A$19:$Z$288,22,FALSE) -> 0 | G12: =VLOOKUP($B$11:$B$25,'Constr. Wage Rate Calculations'!$A$19:$Z$288,23,FALSE) -> 0 | I12: =VLOOKUP($B$11:$B$25,'Constr. Wage Rate Calculations'!$A$19:$Z$288,24,FALSE) -> 0 | K12: =IF($D12>=1,$J12+(D12*E12)+(F12*G12)+(H12*I12),IF($F12>=1,$J12+(D12*E12)+(F12*G12)+(H12*I12),IF($H12>=1,$J12+(D12*E12)+(F12*G12)+(H12*I12),"")))
B13: =VLOOKUP($C$11:$C$25,Personnel!$A$1:$B$1234,2,FALSE) -> 0 | E13: =VLOOKUP($B$11:$B$25,'Constr. Wage Rate Calculations'!$A$19:$Z$288,22,FALSE) -> 0 | G13: =VLOOKUP($B$11:$B$25,'Constr. Wage Rate Calculations'!$A$19:$Z$288,23,FALSE) -> 0 | I13: =VLOOKUP($B$11:$B$25,'Constr. Wage Rate Calculations'!$A$19:$Z$288,24,FALSE) -> 0 | J13: =VLOOKUP($B$11:$B$25,'Constr. Wage Rate Calculations'!$A$19:$Z$288,25,FALSE) -> 0 | K13: =IF($D13>=1,$J13+(D13*E13)+(F13*G13)+(H13*I13),IF($F13>=1,$J13+(D13*E13)+(F13*G13)+(H13*I13),IF($H13>=1,$J13+(D13*E13)+(F13*G13)+(H13*I13),"")))
B14: =VLOOKUP($C$11:$C$25,Personnel!$A$1:$B$1234,2,FALSE) -> 0 | E14: =VLOOKUP($B$11:$B$25,'Constr. Wage Rate Calculations'!$A$19:$Z$288,22,FALSE) -> 0 | G14: =VLOOKUP($B$11:$B$25,'Constr. Wage Rate Calculations'!$A$19:$Z$288,23,FALSE) -> 0 | I14: =VLOOKUP($B$11:$B$25,'Constr. Wage Rate Calculations'!$A$19:$Z$288,24,FALSE) -> 0 | J14: =VLOOKUP($B$11:$B$25,'Constr. Wage Rate Calculations'!$A$19:$Z$288,25,FALSE) -> 0 | K14: =IF($D14>=1,$J14+(D14*E14)+(F14*G14)+(H14*I14),IF($F14>=1,$J14+(D14*E14)+(F14*G14)+(H14*I14),IF($H14>=1,$J14+(D14*E14)+(F14*G14)+(H14*I14),"")))
B15: =VLOOKUP($C$11:$C$25,Personnel!$A$1:$B$1234,2,FALSE) -> 0 | E15: =VLOOKUP($B$11:$B$25,'Constr. Wage Rate Calculations'!$A$19:$Z$288,22,FALSE) -> 0 | G15: =VLOOKUP($B$11:$B$25,'Constr. Wage Rate Calculations'!$A$19:$Z$288,23,FALSE) -> 0 | I15: =VLOOKUP($B$11:$B$25,'Constr. Wage Rate Calculations'!$A$19:$Z$288,24,FALSE) -> 0 | J15: =VLOOKUP($B$11:$B$25,'Constr. Wage Rate Calculations'!$A$19:$Z$288,25,FALSE) -> 0 | K15: =IF($D15>=1,$J15+(D15*E15)+(F15*G15)+(H15*I15),IF($F15>=1,$J15+(D15*E15)+(F15*G15)+(H15*I15),IF($H15>=1,$J15+(D15*E15)+(F15*G15)+(H15*I15),"")))
B16: =VLOOKUP($C$11:$C$25,Personnel!$A$1:$B$1234,2,FALSE) -> 0 | E16: =VLOOKUP($B$11:$B$25,'Constr. Wage Rate Calculations'!$A$19:$Z$288,22,FALSE) -> 0 | G16: =VLOOKUP($B$11:$B$25,'Constr. Wage Rate Calculations'!$A$19:$Z$288,23,FALSE) -> 0 | I16: =VLOOKUP($B$11:$B$25,'Constr. Wage Rate Calculations'!$A$19:$Z$288,24,FALSE) -> 0 | J16: =VLOOKUP($B$11:$B$25,'Constr. Wage Rate Calculations'!$A$19:$Z$288,25,FALSE) -> 0 | K16: =IF($D16>=1,$J16+(D16*E16)+(F16*G16)+(H16*I16),IF($F16>=1,$J16+(D16*E16)+(F16*G16)+(H16*I16),IF($H16>=1,$J16+(D16*E16)+(F16*G16)+(H16*I16),"")))
B17: =VLOOKUP($C$11:$C$25,Personnel!$A$1:$B$1234,2,FALSE) -> 0 | E17: =VLOOKUP($B$11:$B$25,'Constr. Wage Rate Calculations'!$A$19:$Z$288,22,FALSE) -> 0 | G17: =VLOOKUP($B$11:$B$25,'Constr. Wage Rate Calculations'!$A$19:$Z$288,23,FALSE) -> 0 | I17: =VLOOKUP($B$11:$B$25,'Constr. Wage Rate Calculations'!$A$19:$Z$288,24,FALSE) -> 0 | J17: =VLOOKUP($B$11:$B$25,'Constr. Wage Rate Calculations'!$A$19:$Z$288,25,FALSE) -> 0 | K17: =IF($D17>=1,$J17+(D17*E17)+(F17*G17)+(H17*I17),IF($F17>=1,$J17+(D17*E17)+(F17*G17)+(H17*I17),IF($H17>=1,$J17+(D17*E17)+(F17*G17)+(H17*I17),"")))
B18: =VLOOKUP($C$11:$C$25,Personnel!$A$1:$B$1234,2,FALSE) -> 0 | E18: =VLOOKUP($B$11:$B$25,'Constr. Wage Rate Calculations'!$A$19:$Z$288,22,FALSE) -> 0 | G18: =VLOOKUP($B$11:$B$25,'Constr. Wage Rate Calculations'!$A$19:$Z$288,23,FALSE) -> 0 | I18: =VLOOKUP($B$11:$B$25,'Constr. Wage Rate Calculations'!$A$19:$Z$288,24,FALSE) -> 0 | J18: =VLOOKUP($B$11:$B$25,'Constr. Wage Rate Calculations'!$A$19:$Z$288,25,FALSE) -> 0 | K18: =IF($D18>=1,$J18+(D18*E18)+(F18*G18)+(H18*I18),IF($F18>=1,$J18+(D18*E18)+(F18*G18)+(H18*I18),IF($H18>=1,$J18+(D18*E18)+(F18*G18)+(H18*I18),"")))
B19: =VLOOKUP($C$11:$C$25,Personnel!$A$1:$B$1234,2,FALSE) -> 0 | E19: =VLOOKUP($B$11:$B$25,'Constr. Wage Rate Calculations'!$A$19:$Z$288,22,FALSE) -> 0 | G19: =VLOOKUP($B$11:$B$25,'Constr. Wage Rate Calculations'!$A$19:$Z$288,23,FALSE) -> 0 | I19: =VLOOKUP($B$11:$B$25,'Constr. Wage Rate Calculations'!$A$19:$Z$288,24,FALSE) -> 0 | J19: =VLOOKUP($B$11:$B$25,'Constr. Wage Rate Calculations'!$A$19:$Z$288,25,FALSE) -> 0 | K19: =IF($D19>=1,$J19+(D19*E19)+(F19*G19)+(H19*I19),IF($F19>=1,$J19+(D19*E19)+(F19*G19)+(H19*I19),IF($H19>=1,$J19+(D19*E19)+(F19*G19)+(H19*I19),"")))
B20: =VLOOKUP($C$11:$C$25,Personnel!$A$1:$B$1234,2,FALSE) -> 0 | E20: =VLOOKUP($B$11:$B$25,'Constr. Wage Rate Calculations'!$A$19:$Z$288,22,FALSE) -> 0 | G20: =VLOOKUP($B$11:$B$25,'Constr. Wage Rate Calculations'!$A$19:$Z$288,23,FALSE) -> 0 | I20: =VLOOKUP($B$11:$B$25,'Constr. Wage Rate Calculations'!$A$19:$Z$288,24,FALSE) -> 0 | J20: =VLOOKUP($B$11:$B$25,'Constr. Wage Rate Calculations'!$A$19:$Z$288,25,FALSE) -> 0 | K20: =IF($D20>=1,$J20+(D20*E20)+(F20*G20)+(H20*I20),IF($F20>=1,$J20+(D20*E20)+(F20*G20)+(H20*I20),IF($H20>=1,$J20+(D20*E20)+(F20*G20)+(H20*I20),"")))
B21: =VLOOKUP($C$11:$C$25,Personnel!$A$1:$B$1234,2,FALSE) -> 0 | E21: =VLOOKUP($B$11:$B$25,'Constr. Wage Rate Calculations'!$A$19:$Z$288,22,FALSE) -> 0 | G21: =VLOOKUP($B$11:$B$25,'Constr. Wage Rate Calculations'!$A$19:$Z$288,23,FALSE) -> 0 | I21: =VLOOKUP($B$11:$B$25,'Constr. Wage Rate Calculations'!$A$19:$Z$288,24,FALSE) -> 0 | J21: =VLOOKUP($B$11:$B$25,'Constr. Wage Rate Calculations'!$A$19:$Z$288,25,FALSE) -> 0 | K21: =IF($D21>=1,$J21+(D21*E21)+(F21*G21)+(H21*I21),IF($F21>=1,$J21+(D21*E21)+(F21*G21)+(H21*I21),IF($H21>=1,$J21+(D21*E21)+(F21*G21)+(H21*I21),"")))
B22: =VLOOKUP($C$11:$C$25,Personnel!$A$1:$B$1234,2,FALSE) -> 0 | E22: =VLOOKUP($B$11:$B$25,'Constr. Wage Rate Calculations'!$A$19:$Z$288,22,FALSE) -> 0 | G22: =VLOOKUP($B$11:$B$25,'Constr. Wage Rate Calculations'!$A$19:$Z$288,23,FALSE) -> 0 | I22: =VLOOKUP($B$11:$B$25,'Constr. Wage Rate Calculations'!$A$19:$Z$288,24,FALSE) -> 0 | J22: =VLOOKUP($B$11:$B$25,'Constr. Wage Rate Calculations'!$A$19:$Z$288,25,FALSE) -> 0 | K22: =IF($D22>=1,$J22+(D22*E22)+(F22*G22)+(H22*I22),IF($F22>=1,$J22+(D22*E22)+(F22*G22)+(H22*I22),IF($H22>=1,$J22+(D22*E22)+(F22*G22)+(H22*I22),"")))
B23: =VLOOKUP($C$11:$C$25,Personnel!$A$1:$B$1234,2,FALSE) -> 0 | E23: =VLOOKUP($B$11:$B$25,'Constr. Wage Rate Calculations'!$A$19:$Z$288,22,FALSE) -> 0 | G23: =VLOOKUP($B$11:$B$25,'Constr. Wage Rate Calculations'!$A$19:$Z$288,23,FALSE) -> 0 | I23: =VLOOKUP($B$11:$B$25,'Constr. Wage Rate Calculations'!$A$19:$Z$288,24,FALSE) -> 0 | J23: =VLOOKUP($B$11:$B$25,'Constr. Wage Rate Calculations'!$A$19:$Z$288,25,FALSE) -> 0 | K23: =IF($D23>=1,$J23+(D23*E23)+(F23*G23)+(H23*I23),IF($F23>=1,$J23+(D23*E23)+(F23*G23)+(H23*I23),IF($H23>=1,$J23+(D23*E23)+(F23*G23)+(H23*I23),"")))
B24: =VLOOKUP($C$11:$C$25,Personnel!$A$1:$B$1234,2,FALSE) -> 0 | E24: =VLOOKUP($B$11:$B$25,'Constr. Wage Rate Calculations'!$A$19:$Z$288,22,FALSE) -> 0 | G24: =VLOOKUP($B$11:$B$25,'Constr. Wage Rate Calculations'!$A$19:$Z$288,23,FALSE) -> 0 | I24: =VLOOKUP($B$11:$B$25,'Constr. Wage Rate Calculations'!$A$19:$Z$288,24,FALSE) -> 0 | J24: =VLOOKUP($B$11:$B$25,'Constr. Wage Rate Calculations'!$A$19:$Z$288,25,FALSE) -> 0 | K24: =IF($D24>=1,$J24+(D24*E24)+(F24*G24)+(H24*I24),IF($F24>=1,$J24+(D24*E24)+(F24*G24)+(H24*I24),IF($H24>=1,$J24+(D24*E24)+(F24*G24)+(H24*I24),"")))
B25: =VLOOKUP($C$11:$C$25,Personnel!$A$1:$B$1234,2,FALSE) -> 0 | E25: =VLOOKUP($B$11:$B$25,'Constr. Wage Rate Calculations'!$A$19:$Z$288,22,FALSE) -> 0 | G25: =VLOOKUP($B$11:$B$25,'Constr. Wage Rate Calculations'!$A$19:$Z$288,23,FALSE) -> 0 | I25: =VLOOKUP($B$11:$B$25,'Constr. Wage Rate Calculations'!$A$19:$Z$288,24,FALSE) -> 0 | J25: =VLOOKUP($B$11:$B$25,'Constr. Wage Rate Calculations'!$A$19:$Z$288,25,FALSE) -> 0 | K25: =IF($D25>=1,$J25+(D25*E25)+(F25*G25)+(H25*I25),IF($F25>=1,$J25+(D25*E25)+(F25*G25)+(H25*I25),IF($H25>=1,$J25+(D25*E25)+(F25*G25)+(H25*I25),""))) | M25: =SUM(M11:M24) -> 0
I26: TOTAL LABOUR | K26: =SUM(K11:K25) -> 0 | M26: =SUMIFS(D11:D25,D11:D25,"<3",D11:D25,"<5") -> 0 | N26: =SUMIFS(D11:D25,D11:D25,">3",D11:D25,">5") -> 0 | O26: =SUM(F11:F25,H11:H25,M26,N26)-M25 -> 0
A28: Equipment ID | B28: Equipment | H28: Days | I28: Hrs. | J28: Rate | K28: Total
B29: =VLOOKUP($C$29:$C$88,Equipment!$A$1:$B$2322,2,FALSE) -> 0 | J29: =VLOOKUP($B$29:$B$88,'Alberta Equip. Rates Year 3'!$B$13:$K$314,10,FALSE) -> 0 | K29: =(H29+I29)*J29 -> 0
B30: =VLOOKUP($C$29:$C$88,Equipment!$A$1:$B$2322,2,FALSE) -> 0 | J30: =VLOOKUP($B$29:$B$88,'Alberta Equip. Rates Year 3'!$B$13:$K$314,10,FALSE) -> 0 | K30: =(H30+I30)*J30 -> 0
B31: =VLOOKUP($C$29:$C$88,Equipment!$A$1:$B$2322,2,FALSE) -> 0 | J31: =VLOOKUP($B$29:$B$88,'Alberta Equip. Rates Year 3'!$B$13:$K$314,10,FALSE) -> 0 | K31: =(H31+I31)*J31 -> 0
B32: =VLOOKUP($C$29:$C$88,Equipment!$A$1:$B$2322,2,FALSE) -> 0 | J32: =VLOOKUP($B$29:$B$88,'Alberta Equip. Rates Year 3'!$B$13:$K$314,10,FALSE) -> 0 | K32: =(H32+I32)*J32 -> 0
B33: =VLOOKUP($C$29:$C$88,Equipment!$A$1:$B$2322,2,FALSE) -> 0 | J33: =VLOOKUP($B$29:$B$88,'Alberta Equip. Rates Year 3'!$B$13:$K$314,10,FALSE) -> 0 | K33: =(H33+I33)*J33 -> 0
B34: =VLOOKUP($C$29:$C$88,Equipment!$A$1:$B$2322,2,FALSE) -> 0 | J34: =VLOOKUP($B$29:$B$88,'Alberta Equip. Rates Year 3'!$B$13:$K$314,10,FALSE) -> 0 | K34: =(H34+I34)*J34 -> 0
B35: =VLOOKUP($C$29:$C$88,Equipment!$A$1:$B$2322,2,FALSE) -> 0 | J35: =VLOOKUP($B$29:$B$88,'Alberta Equip. Rates Year 3'!$B$13:$K$314,10,FALSE) -> 0 | K35: =(H35+I35)*J35 -> 0
B36: =VLOOKUP($C$29:$C$88,Equipment!$A$1:$B$2322,2,FALSE) -> 0 | J36: =VLOOKUP($B$29:$B$88,'Alberta Equip. Rates Year 3'!$B$13:$K$314,10,FALSE) -> 0 | K36: =(H36+I36)*J36 -> 0
B37: =VLOOKUP($C$29:$C$88,Equipment!$A$1:$B$2322,2,FALSE) -> 0 | J37: =VLOOKUP($B$29:$B$88,'Alberta Equip. Rates Year 3'!$B$13:$K$314,10,FALSE) -> 0 | K37: =(H37+I37)*J37 -> 0
B38: =VLOOKUP($C$29:$C$88,Equipment!$A$1:$B$2322,2,FALSE) -> 0 | J38: =VLOOKUP($B$29:$B$88,'Alberta Equip. Rates Year 3'!$B$13:$K$314,10,FALSE) -> 0 | K38: =(H38+I38)*J38 -> 0
B39: =VLOOKUP($C$29:$C$88,Equipment!$A$1:$B$2322,2,FALSE) -> 0 | J39: =VLOOKUP($B$29:$B$88,'Alberta Equip. Rates Year 3'!$B$13:$K$314,10,FALSE) -> 0 | K39: =(H39+I39)*J39 -> 0
B40: =VLOOKUP($C$29:$C$88,Equipment!$A$1:$B$2322,2,FALSE) -> 0 | J40: =VLOOKUP($B$29:$B$88,'Alberta Equip. Rates Year 3'!$B$13:$K$314,10,FALSE) -> 0 | K40: =(H40+I40)*J40 -> 0
... B88: =VLOOKUP($C$29:$C$88,Equipment!$A$1:$B$2322,2,FALSE) -> 0 | J88: =VLOOKUP($B$29:$B$88,'Alberta Equip. Rates Year 3'!$B$13:$K$314,10,FALSE) -> 0 | K88: =(H88+I88)*J88 -> 0
I89: TOTAL EQUIPMENT | K89: =SUM(K29:K88) -> 0
A91: Scope of Work: | I91: LABOUR | K91: =K26 -> 0
I92: EQUIPMENT | K92: =K89 -> 0
I93: SMALL TOOLS | K93: =(O26)*14.15 -> 0
I94: MATERIALS
I95: TRUCKING
I96: SUBCONTRACTORS
I97: FIELD LOG TOTAL* | K97: =SUM(K91:K96) -> 0
A99: Client: | H99: Company Representitive:
A101: * Field Log Total does no include markups
A102: 41218.479

Sheet Field Log (34)
J1: Date:
G6: Field Log ID: | J6: Status:
A7: Address: | G7: Account #: | J7: Account:
G8: Foreman:
A10: Employee ID | B10: Labor Type | C10: Employee | D10: RT Hours | E10: RT Rate | F10: OT Hours | G10: OT Rate | H10: DT Hours | I10: DT Rate | J10: Sub. | K10: Total | M10: Additional Hours
B11: =VLOOKUP($C$11:$C$25,Personnel!$A$1:$B$1234,2,FALSE) -> 0 | E11: =VLOOKUP($B$11:$B$25,'Constr. Wage Rate Calculations'!$A$19:$Z$288,22,FALSE) -> 0 | G11: =VLOOKUP($B$11:$B$25,'Constr. Wage Rate Calculations'!$A$19:$Z$288,23,FALSE) -> 0 | I11: =VLOOKUP($B$11:$B$25,'Constr. Wage Rate Calculations'!$A$19:$Z$288,24,FALSE) -> 0 | J11: =VLOOKUP($B$11:$B$25,'Constr. Wage Rate Calculations'!$A$19:$Z$288,25,FALSE) -> 0 | K11: =IF($D11>=1,$J11+(D11*E11)+(F11*G11)+(H11*I11),IF($F11>=1,$J11+(D11*E11)+(F11*G11)+(H11*I11),IF($H11>=1,$J11+(D11*E11)+(F11*G11)+(H11*I11),"")))
B12: =VLOOKUP($C$11:$C$25,Personnel!$A$1:$B$1234,2,FALSE) -> 0 | E12: =VLOOKUP($B$11:$B$25,'Constr. Wage Rate Calculations'!$A$19:$Z$288,22,FALSE) -> 0 | G12: =VLOOKUP($B$11:$B$25,'Constr. Wage Rate Calculations'!$A$19:$Z$288,23,FALSE) -> 0 | I12: =VLOOKUP($B$11:$B$25,'Constr. Wage Rate Calculations'!$A$19:$Z$288,24,FALSE) -> 0 | K12: =IF($D12>=1,$J12+(D12*E12)+(F12*G12)+(H12*I12),IF($F12>=1,$J12+(D12*E12)+(F12*G12)+(H12*I12),IF($H12>=1,$J12+(D12*E12)+(F12*G12)+(H12*I12),"")))
B13: =VLOOKUP($C$11:$C$25,Personnel!$A$1:$B$1234,2,FALSE) -> 0 | E13: =VLOOKUP($B$11:$B$25,'Constr. Wage Rate Calculations'!$A$19:$Z$288,22,FALSE) -> 0 | G13: =VLOOKUP($B$11:$B$25,'Constr. Wage Rate Calculations'!$A$19:$Z$288,23,FALSE) -> 0 | I13: =VLOOKUP($B$11:$B$25,'Constr. Wage Rate Calculations'!$A$19:$Z$288,24,FALSE) -> 0 | J13: =VLOOKUP($B$11:$B$25,'Constr. Wage Rate Calculations'!$A$19:$Z$288,25,FALSE) -> 0 | K13: =IF($D13>=1,$J13+(D13*E13)+(F13*G13)+(H13*I13),IF($F13>=1,$J13+(D13*E13)+(F13*G13)+(H13*I13),IF($H13>=1,$J13+(D13*E13)+(F13*G13)+(H13*I13),"")))
B14: =VLOOKUP($C$11:$C$25,Personnel!$A$1:$B$1234,2,FALSE) -> 0 | E14: =VLOOKUP($B$11:$B$25,'Constr. Wage Rate Calculations'!$A$19:$Z$288,22,FALSE) -> 0 | G14: =VLOOKUP($B$11:$B$25,'Constr. Wage Rate Calculations'!$A$19:$Z$288,23,FALSE) -> 0 | I14: =VLOOKUP($B$11:$B$25,'Constr. Wage Rate Calculations'!$A$19:$Z$288,24,FALSE) -> 0 | J14: =VLOOKUP($B$11:$B$25,'Constr. Wage Rate Calculations'!$A$19:$Z$288,25,FALSE) -> 0 | K14: =IF($D14>=1,$J14+(D14*E14)+(F14*G14)+(H14*I14),IF($F14>=1,$J14+(D14*E14)+(F14*G14)+(H14*I14),IF($H14>=1,$J14+(D14*E14)+(F14*G14)+(H14*I14),"")))
B15: =VLOOKUP($C$11:$C$25,Personnel!$A$1:$B$1234,2,FALSE) -> 0 | E15: =VLOOKUP($B$11:$B$25,'Constr. Wage Rate Calculations'!$A$19:$Z$288,22,FALSE) -> 0 | G15: =VLOOKUP($B$11:$B$25,'Constr. Wage Rate Calculations'!$A$19:$Z$288,23,FALSE) -> 0 | I15: =VLOOKUP($B$11:$B$25,'Constr. Wage Rate Calculations'!$A$19:$Z$288,24,FALSE) -> 0 | J15: =VLOOKUP($B$11:$B$25,'Constr. Wage Rate Calculations'!$A$19:$Z$288,25,FALSE) -> 0 | K15: =IF($D15>=1,$J15+(D15*E15)+(F15*G15)+(H15*I15),IF($F15>=1,$J15+(D15*E15)+(F15*G15)+(H15*I15),IF($H15>=1,$J15+(D15*E15)+(F15*G15)+(H15*I15),"")))
B16: =VLOOKUP($C$11:$C$25,Personnel!$A$1:$B$1234,2,FALSE) -> 0 | E16: =VLOOKUP($B$11:$B$25,'Constr. Wage Rate Calculations'!$A$19:$Z$288,22,FALSE) -> 0 | G16: =VLOOKUP($B$11:$B$25,'Constr. Wage Rate Calculations'!$A$19:$Z$288,23,FALSE) -> 0 | I16: =VLOOKUP($B$11:$B$25,'Constr. Wage Rate Calculations'!$A$19:$Z$288,24,FALSE) -> 0 | J16: =VLOOKUP($B$11:$B$25,'Constr. Wage Rate Calculations'!$A$19:$Z$288,25,FALSE) -> 0 | K16: =IF($D16>=1,$J16+(D16*E16)+(F16*G16)+(H16*I16),IF($F16>=1,$J16+(D16*E16)+(F16*G16)+(H16*I16),IF($H16>=1,$J16+(D16*E16)+(F16*G16)+(H16*I16),"")))
B17: =VLOOKUP($C$11:$C$25,Personnel!$A$1:$B$1234,2,FALSE) -> 0 | E17: =VLOOKUP($B$11:$B$25,'Constr. Wage Rate Calculations'!$A$19:$Z$288,22,FALSE) -> 0 | G17: =VLOOKUP($B$11:$B$25,'Constr. Wage Rate Calculations'!$A$19:$Z$288,23,FALSE) -> 0 | I17: =VLOOKUP($B$11:$B$25,'Constr. Wage Rate Calculations'!$A$19:$Z$288,24,FALSE) -> 0 | J17: =VLOOKUP($B$11:$B$25,'Constr. Wage Rate Calculations'!$A$19:$Z$288,25,FALSE) -> 0 | K17: =IF($D17>=1,$J17+(D17*E17)+(F17*G17)+(H17*I17),IF($F17>=1,$J17+(D17*E17)+(F17*G17)+(H17*I17),IF($H17>=1,$J17+(D17*E17)+(F17*G17)+(H17*I17),"")))
B18: =VLOOKUP($C$11:$C$25,Personnel!$A$1:$B$1234,2,FALSE) -> 0 | E18: =VLOOKUP($B$11:$B$25,'Constr. Wage Rate Calculations'!$A$19:$Z$288,22,FALSE) -> 0 | G18: =VLOOKUP($B$11:$B$25,'Constr. Wage Rate Calculations'!$A$19:$Z$288,23,FALSE) -> 0 | I18: =VLOOKUP($B$11:$B$25,'Constr. Wage Rate Calculations'!$A$19:$Z$288,24,FALSE) -> 0 | J18: =VLOOKUP($B$11:$B$25,'Constr. Wage Rate Calculations'!$A$19:$Z$288,25,FALSE) -> 0 | K18: =IF($D18>=1,$J18+(D18*E18)+(F18*G18)+(H18*I18),IF($F18>=1,$J18+(D18*E18)+(F18*G18)+(H18*I18),IF($H18>=1,$J18+(D18*E18)+(F18*G18)+(H18*I18),"")))
B19: =VLOOKUP($C$11:$C$25,Personnel!$A$1:$B$1234,2,FALSE) -> 0 | E19: =VLOOKUP($B$11:$B$25,'Constr. Wage Rate Calculations'!$A$19:$Z$288,22,FALSE) -> 0 | G19: =VLOOKUP($B$11:$B$25,'Constr. Wage Rate Calculations'!$A$19:$Z$288,23,FALSE) -> 0 | I19: =VLOOKUP($B$11:$B$25,'Constr. Wage Rate Calculations'!$A$19:$Z$288,24,FALSE) -> 0 | J19: =VLOOKUP($B$11:$B$25,'Constr. Wage Rate Calculations'!$A$19:$Z$288,25,FALSE) -> 0 | K19: =IF($D19>=1,$J19+(D19*E19)+(F19*G19)+(H19*I19),IF($F19>=1,$J19+(D19*E19)+(F19*G19)+(H19*I19),IF($H19>=1,$J19+(D19*E19)+(F19*G19)+(H19*I19),"")))
B20: =VLOOKUP($C$11:$C$25,Personnel!$A$1:$B$1234,2,FALSE) -> 0 | E20: =VLOOKUP($B$11:$B$25,'Constr. Wage Rate Calculations'!$A$19:$Z$288,22,FALSE) -> 0 | G20: =VLOOKUP($B$11:$B$25,'Constr. Wage Rate Calculations'!$A$19:$Z$288,23,FALSE) -> 0 | I20: =VLOOKUP($B$11:$B$25,'Constr. Wage Rate Calculations'!$A$19:$Z$288,24,FALSE) -> 0 | J20: =VLOOKUP($B$11:$B$25,'Constr. Wage Rate Calculations'!$A$19:$Z$288,25,FALSE) -> 0 | K20: =IF($D20>=1,$J20+(D20*E20)+(F20*G20)+(H20*I20),IF($F20>=1,$J20+(D20*E20)+(F20*G20)+(H20*I20),IF($H20>=1,$J20+(D20*E20)+(F20*G20)+(H20*I20),"")))
B21: =VLOOKUP($C$11:$C$25,Personnel!$A$1:$B$1234,2,FALSE) -> 0 | E21: =VLOOKUP($B$11:$B$25,'Constr. Wage Rate Calculations'!$A$19:$Z$288,22,FALSE) -> 0 | G21: =VLOOKUP($B$11:$B$25,'Constr. Wage Rate Calculations'!$A$19:$Z$288,23,FALSE) -> 0 | I21: =VLOOKUP($B$11:$B$25,'Constr. Wage Rate Calculations'!$A$19:$Z$288,24,FALSE) -> 0 | J21: =VLOOKUP($B$11:$B$25,'Constr. Wage Rate Calculations'!$A$19:$Z$288,25,FALSE) -> 0 | K21: =IF($D21>=1,$J21+(D21*E21)+(F21*G21)+(H21*I21),IF($F21>=1,$J21+(D21*E21)+(F21*G21)+(H21*I21),IF($H21>=1,$J21+(D21*E21)+(F21*G21)+(H21*I21),"")))
B22: =VLOOKUP($C$11:$C$25,Personnel!$A$1:$B$1234,2,FALSE) -> 0 | E22: =VLOOKUP($B$11:$B$25,'Constr. Wage Rate Calculations'!$A$19:$Z$288,22,FALSE) -> 0 | G22: =VLOOKUP($B$11:$B$25,'Constr. Wage Rate Calculations'!$A$19:$Z$288,23,FALSE) -> 0 | I22: =VLOOKUP($B$11:$B$25,'Constr. Wage Rate Calculations'!$A$19:$Z$288,24,FALSE) -> 0 | J22: =VLOOKUP($B$11:$B$25,'Constr. Wage Rate Calculations'!$A$19:$Z$288,25,FALSE) -> 0 | K22: =IF($D22>=1,$J22+(D22*E22)+(F22*G22)+(H22*I22),IF($F22>=1,$J22+(D22*E22)+(F22*G22)+(H22*I22),IF($H22>=1,$J22+(D22*E22)+(F22*G22)+(H22*I22),"")))
B23: =VLOOKUP($C$11:$C$25,Personnel!$A$1:$B$1234,2,FALSE) -> 0 | E23: =VLOOKUP($B$11:$B$25,'Constr. Wage Rate Calculations'!$A$19:$Z$288,22,FALSE) -> 0 | G23: =VLOOKUP($B$11:$B$25,'Constr. Wage Rate Calculations'!$A$19:$Z$288,23,FALSE) -> 0 | I23: =VLOOKUP($B$11:$B$25,'Constr. Wage Rate Calculations'!$A$19:$Z$288,24,FALSE) -> 0 | J23: =VLOOKUP($B$11:$B$25,'Constr. Wage Rate Calculations'!$A$19:$Z$288,25,FALSE) -> 0 | K23: =IF($D23>=1,$J23+(D23*E23)+(F23*G23)+(H23*I23),IF($F23>=1,$J23+(D23*E23)+(F23*G23)+(H23*I23),IF($H23>=1,$J23+(D23*E23)+(F23*G23)+(H23*I23),"")))
B24: =VLOOKUP($C$11:$C$25,Personnel!$A$1:$B$1234,2,FALSE) -> 0 | E24: =VLOOKUP($B$11:$B$25,'Constr. Wage Rate Calculations'!$A$19:$Z$288,22,FALSE) -> 0 | G24: =VLOOKUP($B$11:$B$25,'Constr. Wage Rate Calculations'!$A$19:$Z$288,23,FALSE) -> 0 | I24: =VLOOKUP($B$11:$B$25,'Constr. Wage Rate Calculations'!$A$19:$Z$288,24,FALSE) -> 0 | J24: =VLOOKUP($B$11:$B$25,'Constr. Wage Rate Calculations'!$A$19:$Z$288,25,FALSE) -> 0 | K24: =IF($D24>=1,$J24+(D24*E24)+(F24*G24)+(H24*I24),IF($F24>=1,$J24+(D24*E24)+(F24*G24)+(H24*I24),IF($H24>=1,$J24+(D24*E24)+(F24*G24)+(H24*I24),"")))
B25: =VLOOKUP($C$11:$C$25,Personnel!$A$1:$B$1234,2,FALSE) -> 0 | E25: =VLOOKUP($B$11:$B$25,'Constr. Wage Rate Calculations'!$A$19:$Z$288,22,FALSE) -> 0 | G25: =VLOOKUP($B$11:$B$25,'Constr. Wage Rate Calculations'!$A$19:$Z$288,23,FALSE) -> 0 | I25: =VLOOKUP($B$11:$B$25,'Constr. Wage Rate Calculations'!$A$19:$Z$288,24,FALSE) -> 0 | J25: =VLOOKUP($B$11:$B$25,'Constr. Wage Rate Calculations'!$A$19:$Z$288,25,FALSE) -> 0 | K25: =IF($D25>=1,$J25+(D25*E25)+(F25*G25)+(H25*I25),IF($F25>=1,$J25+(D25*E25)+(F25*G25)+(H25*I25),IF($H25>=1,$J25+(D25*E25)+(F25*G25)+(H25*I25),""))) | M25: =SUM(M11:M24) -> 0
I26: TOTAL LABOUR | K26: =SUM(K11:K25) -> 0 | M26: =SUMIFS(D11:D25,D11:D25,"<3",D11:D25,"<5") -> 0 | N26: =SUMIFS(D11:D25,D11:D25,">3",D11:D25,">5") -> 0 | O26: =SUM(F11:F25,H11:H25,M26,N26)-M25 -> 0
A28: Equipment ID | B28: Equipment | H28: Days | I28: Hrs. | J28: Rate | K28: Total
B29: =VLOOKUP($C$29:$C$42,Equipment!$A$1:$B$2322,2,FALSE) -> 0 | J29: =VLOOKUP($B$29:$B$42,'Alberta Equip. Rates Year 3'!$B$13:$K$314,10,FALSE) -> 0 | K29: =(H29+I29)*J29 -> 0
B30: =VLOOKUP($C$29:$C$42,Equipment!$A$1:$B$2322,2,FALSE) -> 0 | J30: =VLOOKUP($B$29:$B$42,'Alberta Equip. Rates Year 3'!$B$13:$K$314,10,FALSE) -> 0 | K30: =(H30+I30)*J30 -> 0
B31: =VLOOKUP($C$29:$C$42,Equipment!$A$1:$B$2322,2,FALSE) -> 0 | J31: =VLOOKUP($B$29:$B$42,'Alberta Equip. Rates Year 3'!$B$13:$K$314,10,FALSE) -> 0 | K31: =(H31+I31)*J31 -> 0
B32: =VLOOKUP($C$29:$C$42,Equipment!$A$1:$B$2322,2,FALSE) -> 0 | J32: =VLOOKUP($B$29:$B$42,'Alberta Equip. Rates Year 3'!$B$13:$K$314,10,FALSE) -> 0 | K32: =(H32+I32)*J32 -> 0
B33: =VLOOKUP($C$29:$C$42,Equipment!$A$1:$B$2322,2,FALSE) -> 0 | J33: =VLOOKUP($B$29:$B$42,'Alberta Equip. Rates Year 3'!$B$13:$K$314,10,FALSE) -> 0 | K33: =(H33+I33)*J33 -> 0
B34: =VLOOKUP($C$29:$C$42,Equipment!$A$1:$B$2322,2,FALSE) -> 0 | J34: =VLOOKUP($B$29:$B$42,'Alberta Equip. Rates Year 3'!$B$13:$K$314,10,FALSE) -> 0 | K34: =(H34+I34)*J34 -> 0
B35: =VLOOKUP($C$29:$C$42,Equipment!$A$1:$B$2322,2,FALSE) -> 0 | J35: =VLOOKUP($B$29:$B$42,'Alberta Equip. Rates Year 3'!$B$13:$K$314,10,FALSE) -> 0 | K35: =(H35+I35)*J35 -> 0
B36: =VLOOKUP($C$29:$C$42,Equipment!$A$1:$B$2322,2,FALSE) -> 0 | J36: =VLOOKUP($B$29:$B$42,'Alberta Equip. Rates Year 3'!$B$13:$K$314,10,FALSE) -> 0 | K36: =(H36+I36)*J36 -> 0
B37: =VLOOKUP($C$29:$C$42,Equipment!$A$1:$B$2322,2,FALSE) -> 0 | J37: =VLOOKUP($B$29:$B$42,'Alberta Equip. Rates Year 3'!$B$13:$K$314,10,FALSE) -> 0 | K37: =(H37+I37)*J37 -> 0
B38: =VLOOKUP($C$29:$C$42,Equipment!$A$1:$B$2322,2,FALSE) -> 0 | J38: =VLOOKUP($B$29:$B$42,'Alberta Equip. Rates Year 3'!$B$13:$K$314,10,FALSE) -> 0 | K38: =(H38+I38)*J38 -> 0
B39: =VLOOKUP($C$29:$C$42,Equipment!$A$1:$B$2322,2,FALSE) -> 0 | J39: =VLOOKUP($B$29:$B$42,'Alberta Equip. Rates Year 3'!$B$13:$K$314,10,FALSE) -> 0 | K39: =(H39+I39)*J39 -> 0
B40: =VLOOKUP($C$29:$C$42,Equipment!$A$1:$B$2322,2,FALSE) -> 0 | J40: =VLOOKUP($B$29:$B$42,'Alberta Equip. Rates Year 3'!$B$13:$K$314,10,FALSE) -> 0 | K40: =(H40+I40)*J40 -> 0
... B42: =VLOOKUP($C$29:$C$42,Equipment!$A$1:$B$2322,2,FALSE) -> 0 | J42: =VLOOKUP($B$29:$B$42,'Alberta Equip. Rates Year 3'!$B$13:$K$314,10,FALSE) -> 0 | K42: =(H42+I42)*J42 -> 0
I43: TOTAL EQUIPMENT | K43: =SUM(K29:K42) -> 0
A45: Scope of Work: | I45: LABOUR | K45: =K26 -> 0
I46: EQUIPMENT | K46: =K43 -> 0
I47: SMALL TOOLS | K47: =(O26)*14.15 -> 0
I48: MATERIALS
I49: TRUCKING
I50: SUBCONTRACTORS
I51: FIELD LOG TOTAL* | K51: =SUM(K45:K50) -> 0
A53: Client: | H53: Company Representitive:
A55: * Field Log Total does no include markups
A56: 41218.479

Sheet Field Log (13)
J1: Date:
G6: Field Log ID: | J6: Status:
A7: Address: | G7: Account #: | J7: Account:
G8: Foreman:
A10: Employee ID | B10: Labor Type | C10: Employee | D10: RT Hours | E10: RT Rate | F10: OT Hours | G10: OT Rate | H10: DT Hours | I10: DT Rate | J10: Sub. | K10: Total | M10: Additional Hours
B11: =VLOOKUP($C$11:$C$41,Personnel!$A$1:$B$1234,2,FALSE) -> 0 | E11: =VLOOKUP($B$11:$B$41,'Constr. Wage Rate Calculations'!$A$19:$Z$288,22,FALSE) -> 0 | G11: =VLOOKUP($B$11:$B$41,'Constr. Wage Rate Calculations'!$A$19:$Z$288,23,FALSE) -> 0 | I11: =VLOOKUP($B$11:$B$41,'Constr. Wage Rate Calculations'!$A$19:$Z$288,24,FALSE) -> 0 | J11: =VLOOKUP($B$11:$B$41,'Constr. Wage Rate Calculations'!$A$19:$Z$288,25,FALSE) -> 0 | K11: =IF($D11>=1,$J11+(D11*E11)+(F11*G11)+(H11*I11),IF($F11>=1,$J11+(D11*E11)+(F11*G11)+(H11*I11),IF($H11>=1,$J11+(D11*E11)+(F11*G11)+(H11*I11),"")))
B12: =VLOOKUP($C$11:$C$41,Personnel!$A$1:$B$1234,2,FALSE) -> 0 | E12: =VLOOKUP($B$11:$B$41,'Constr. Wage Rate Calculations'!$A$19:$Z$288,22,FALSE) -> 0 | G12: =VLOOKUP($B$11:$B$41,'Constr. Wage Rate Calculations'!$A$19:$Z$288,23,FALSE) -> 0 | I12: =VLOOKUP($B$11:$B$41,'Constr. Wage Rate Calculations'!$A$19:$Z$288,24,FALSE) -> 0 | K12: =IF($D12>=1,$J12+(D12*E12)+(F12*G12)+(H12*I12),IF($F12>=1,$J12+(D12*E12)+(F12*G12)+(H12*I12),IF($H12>=1,$J12+(D12*E12)+(F12*G12)+(H12*I12),"")))
B13: =VLOOKUP($C$11:$C$41,Personnel!$A$1:$B$1234,2,FALSE) -> 0 | E13: =VLOOKUP($B$11:$B$41,'Constr. Wage Rate Calculations'!$A$19:$Z$288,22,FALSE) -> 0 | G13: =VLOOKUP($B$11:$B$41,'Constr. Wage Rate Calculations'!$A$19:$Z$288,23,FALSE) -> 0 | I13: =VLOOKUP($B$11:$B$41,'Constr. Wage Rate Calculations'!$A$19:$Z$288,24,FALSE) -> 0 | J13: =VLOOKUP($B$11:$B$41,'Constr. Wage Rate Calculations'!$A$19:$Z$288,25,FALSE) -> 0 | K13: =IF($D13>=1,$J13+(D13*E13)+(F13*G13)+(H13*I13),IF($F13>=1,$J13+(D13*E13)+(F13*G13)+(H13*I13),IF($H13>=1,$J13+(D13*E13)+(F13*G13)+(H13*I13),"")))
B14: =VLOOKUP($C$11:$C$41,Personnel!$A$1:$B$1234,2,FALSE) -> 0 | E14: =VLOOKUP($B$11:$B$41,'Constr. Wage Rate Calculations'!$A$19:$Z$288,22,FALSE) -> 0 | G14: =VLOOKUP($B$11:$B$41,'Constr. Wage Rate Calculations'!$A$19:$Z$288,23,FALSE) -> 0 | I14: =VLOOKUP($B$11:$B$41,'Constr. Wage Rate Calculations'!$A$19:$Z$288,24,FALSE) -> 0 | J14: =VLOOKUP($B$11:$B$41,'Constr. Wage Rate Calculations'!$A$19:$Z$288,25,FALSE) -> 0 | K14: =IF($D14>=1,$J14+(D14*E14)+(F14*G14)+(H14*I14),IF($F14>=1,$J14+(D14*E14)+(F14*G14)+(H14*I14),IF($H14>=1,$J14+(D14*E14)+(F14*G14)+(H14*I14),"")))
B15: =VLOOKUP($C$11:$C$41,Personnel!$A$1:$B$1234,2,FALSE) -> 0 | E15: =VLOOKUP($B$11:$B$41,'Constr. Wage Rate Calculations'!$A$19:$Z$288,22,FALSE) -> 0 | G15: =VLOOKUP($B$11:$B$41,'Constr. Wage Rate Calculations'!$A$19:$Z$288,23,FALSE) -> 0 | I15: =VLOOKUP($B$11:$B$41,'Constr. Wage Rate Calculations'!$A$19:$Z$288,24,FALSE) -> 0 | J15: =VLOOKUP($B$11:$B$41,'Constr. Wage Rate Calculations'!$A$19:$Z$288,25,FALSE) -> 0 | K15: =IF($D15>=1,$J15+(D15*E15)+(F15*G15)+(H15*I15),IF($F15>=1,$J15+(D15*E15)+(F15*G15)+(H15*I15),IF($H15>=1,$J15+(D15*E15)+(F15*G15)+(H15*I15),"")))
B16: =VLOOKUP($C$11:$C$41,Personnel!$A$1:$B$1234,2,FALSE) -> 0 | E16: =VLOOKUP($B$11:$B$41,'Constr. Wage Rate Calculations'!$A$19:$Z$288,22,FALSE) -> 0 | G16: =VLOOKUP($B$11:$B$41,'Constr. Wage Rate Calculations'!$A$19:$Z$288,23,FALSE) -> 0 | I16: =VLOOKUP($B$11:$B$41,'Constr. Wage Rate Calculations'!$A$19:$Z$288,24,FALSE) -> 0 | J16: =VLOOKUP($B$11:$B$41,'Constr. Wage Rate Calculations'!$A$19:$Z$288,25,FALSE) -> 0 | K16: =IF($D16>=1,$J16+(D16*E16)+(F16*G16)+(H16*I16),IF($F16>=1,$J16+(D16*E16)+(F16*G16)+(H16*I16),IF($H16>=1,$J16+(D16*E16)+(F16*G16)+(H16*I16),"")))
B17: =VLOOKUP($C$11:$C$41,Personnel!$A$1:$B$1234,2,FALSE) -> 0 | E17: =VLOOKUP($B$11:$B$41,'Constr. Wage Rate Calculations'!$A$19:$Z$288,22,FALSE) -> 0 | G17: =VLOOKUP($B$11:$B$41,'Constr. Wage Rate Calculations'!$A$19:$Z$288,23,FALSE) -> 0 | I17: =VLOOKUP($B$11:$B$41,'Constr. Wage Rate Calculations'!$A$19:$Z$288,24,FALSE) -> 0 | J17: =VLOOKUP($B$11:$B$41,'Constr. Wage Rate Calculations'!$A$19:$Z$288,25,FALSE) -> 0 | K17: =IF($D17>=1,$J17+(D17*E17)+(F17*G17)+(H17*I17),IF($F17>=1,$J17+(D17*E17)+(F17*G17)+(H17*I17),IF($H17>=1,$J17+(D17*E17)+(F17*G17)+(H17*I17),"")))
B18: =VLOOKUP($C$11:$C$41,Personnel!$A$1:$B$1234,2,FALSE) -> 0 | E18: =VLOOKUP($B$11:$B$41,'Constr. Wage Rate Calculations'!$A$19:$Z$288,22,FALSE) -> 0 | G18: =VLOOKUP($B$11:$B$41,'Constr. Wage Rate Calculations'!$A$19:$Z$288,23,FALSE) -> 0 | I18: =VLOOKUP($B$11:$B$41,'Constr. Wage Rate Calculations'!$A$19:$Z$288,24,FALSE) -> 0 | J18: =VLOOKUP($B$11:$B$41,'Constr. Wage Rate Calculations'!$A$19:$Z$288,25,FALSE) -> 0 | K18: =IF($D18>=1,$J18+(D18*E18)+(F18*G18)+(H18*I18),IF($F18>=1,$J18+(D18*E18)+(F18*G18)+(H18*I18),IF($H18>=1,$J18+(D18*E18)+(F18*G18)+(H18*I18),"")))
B19: =VLOOKUP($C$11:$C$41,Personnel!$A$1:$B$1234,2,FALSE) -> 0 | E19: =VLOOKUP($B$11:$B$41,'Constr. Wage Rate Calculations'!$A$19:$Z$288,22,FALSE) -> 0 | G19: =VLOOKUP($B$11:$B$41,'Constr. Wage Rate Calculations'!$A$19:$Z$288,23,FALSE) -> 0 | I19: =VLOOKUP($B$11:$B$41,'Constr. Wage Rate Calculations'!$A$19:$Z$288,24,FALSE) -> 0 | J19: =VLOOKUP($B$11:$B$41,'Constr. Wage Rate Calculations'!$A$19:$Z$288,25,FALSE) -> 0 | K19: =IF($D19>=1,$J19+(D19*E19)+(F19*G19)+(H19*I19),IF($F19>=1,$J19+(D19*E19)+(F19*G19)+(H19*I19),IF($H19>=1,$J19+(D19*E19)+(F19*G19)+(H19*I19),"")))
B20: =VLOOKUP($C$11:$C$41,Personnel!$A$1:$B$1234,2,FALSE) -> 0 | E20: =VLOOKUP($B$11:$B$41,'Constr. Wage Rate Calculations'!$A$19:$Z$288,22,FALSE) -> 0 | G20: =VLOOKUP($B$11:$B$41,'Constr. Wage Rate Calculations'!$A$19:$Z$288,23,FALSE) -> 0 | I20: =VLOOKUP($B$11:$B$41,'Constr. Wage Rate Calculations'!$A$19:$Z$288,24,FALSE) -> 0 | J20: =VLOOKUP($B$11:$B$41,'Constr. Wage Rate Calculations'!$A$19:$Z$288,25,FALSE) -> 0 | K20: =IF($D20>=1,$J20+(D20*E20)+(F20*G20)+(H20*I20),IF($F20>=1,$J20+(D20*E20)+(F20*G20)+(H20*I20),IF($H20>=1,$J20+(D20*E20)+(F20*G20)+(H20*I20),"")))
B21: =VLOOKUP($C$11:$C$41,Personnel!$A$1:$B$1234,2,FALSE) -> 0 | E21: =VLOOKUP($B$11:$B$41,'Constr. Wage Rate Calculations'!$A$19:$Z$288,22,FALSE) -> 0 | G21: =VLOOKUP($B$11:$B$41,'Constr. Wage Rate Calculations'!$A$19:$Z$288,23,FALSE) -> 0 | I21: =VLOOKUP($B$11:$B$41,'Constr. Wage Rate Calculations'!$A$19:$Z$288,24,FALSE) -> 0 | J21: =VLOOKUP($B$11:$B$41,'Constr. Wage Rate Calculations'!$A$19:$Z$288,25,FALSE) -> 0 | K21: =IF($D21>=1,$J21+(D21*E21)+(F21*G21)+(H21*I21),IF($F21>=1,$J21+(D21*E21)+(F21*G21)+(H21*I21),IF($H21>=1,$J21+(D21*E21)+(F21*G21)+(H21*I21),"")))
B22: =VLOOKUP($C$11:$C$41,Personnel!$A$1:$B$1234,2,FALSE) -> 0 | E22: =VLOOKUP($B$11:$B$41,'Constr. Wage Rate Calculations'!$A$19:$Z$288,22,FALSE) -> 0 | G22: =VLOOKUP($B$11:$B$41,'Constr. Wage Rate Calculations'!$A$19:$Z$288,23,FALSE) -> 0 | I22: =VLOOKUP($B$11:$B$41,'Constr. Wage Rate Calculations'!$A$19:$Z$288,24,FALSE) -> 0 | J22: =VLOOKUP($B$11:$B$41,'Constr. Wage Rate Calculations'!$A$19:$Z$288,25,FALSE) -> 0 | K22: =IF($D22>=1,$J22+(D22*E22)+(F22*G22)+(H22*I22),IF($F22>=1,$J22+(D22*E22)+(F22*G22)+(H22*I22),IF($H22>=1,$J22+(D22*E22)+(F22*G22)+(H22*I22),"")))
B23: =VLOOKUP($C$11:$C$41,Personnel!$A$1:$B$1234,2,FALSE) -> 0 | E23: =VLOOKUP($B$11:$B$41,'Constr. Wage Rate Calculations'!$A$19:$Z$288,22,FALSE) -> 0 | G23: =VLOOKUP($B$11:$B$41,'Constr. Wage Rate Calculations'!$A$19:$Z$288,23,FALSE) -> 0 | I23: =VLOOKUP($B$11:$B$41,'Constr. Wage Rate Calculations'!$A$19:$Z$288,24,FALSE) -> 0 | J23: =VLOOKUP($B$11:$B$41,'Constr. Wage Rate Calculations'!$A$19:$Z$288,25,FALSE) -> 0 | K23: =IF($D23>=1,$J23+(D23*E23)+(F23*G23)+(H23*I23),IF($F23>=1,$J23+(D23*E23)+(F23*G23)+(H23*I23),IF($H23>=1,$J23+(D23*E23)+(F23*G23)+(H23*I23),"")))
B24: =VLOOKUP($C$11:$C$41,Personnel!$A$1:$B$1234,2,FALSE) -> 0 | E24: =VLOOKUP($B$11:$B$41,'Constr. Wage Rate Calculations'!$A$19:$Z$288,22,FALSE) -> 0 | G24: =VLOOKUP($B$11:$B$41,'Constr. Wage Rate Calculations'!$A$19:$Z$288,23,FALSE) -> 0 | I24: =VLOOKUP($B$11:$B$41,'Constr. Wage Rate Calculations'!$A$19:$Z$288,24,FALSE) -> 0 | J24: =VLOOKUP($B$11:$B$41,'Constr. Wage Rate Calculations'!$A$19:$Z$288,25,FALSE) -> 0 | K24: =IF($D24>=1,$J24+(D24*E24)+(F24*G24)+(H24*I24),IF($F24>=1,$J24+(D24*E24)+(F24*G24)+(H24*I24),IF($H24>=1,$J24+(D24*E24)+(F24*G24)+(H24*I24),"")))
... B40: =VLOOKUP($C$11:$C$41,Personnel!$A$1:$B$1234,2,FALSE) -> 0 | E40: =VLOOKUP($B$11:$B$41,'Constr. Wage Rate Calculations'!$A$19:$Z$288,22,FALSE) -> 0 | G40: =VLOOKUP($B$11:$B$41,'Constr. Wage Rate Calculations'!$A$19:$Z$288,23,FALSE) -> 0 | I40: =VLOOKUP($B$11:$B$41,'Constr. Wage Rate Calculations'!$A$19:$Z$288,24,FALSE) -> 0 | J40: =VLOOKUP($B$11:$B$41,'Constr. Wage Rate Calculations'!$A$19:$Z$288,25,FALSE) -> 0 | K40: =IF($D40>=1,$J40+(D40*E40)+(F40*G40)+(H40*I40),IF($F40>=1,$J40+(D40*E40)+(F40*G40)+(H40*I40),IF($H40>=1,$J40+(D40*E40)+(F40*G40)+(H40*I40),"")))
B41: =VLOOKUP($C$11:$C$41,Personnel!$A$1:$B$1234,2,FALSE) -> 0 | E41: =VLOOKUP($B$11:$B$41,'Constr. Wage Rate Calculations'!$A$19:$Z$288,22,FALSE) -> 0 | G41: =VLOOKUP($B$11:$B$41,'Constr. Wage Rate Calculations'!$A$19:$Z$288,23,FALSE) -> 0 | I41: =VLOOKUP($B$11:$B$41,'Constr. Wage Rate Calculations'!$A$19:$Z$288,24,FALSE) -> 0 | J41: =VLOOKUP($B$11:$B$41,'Constr. Wage Rate Calculations'!$A$19:$Z$288,25,FALSE) -> 0 | K41: =IF($D41>=1,$J41+(D41*E41)+(F41*G41)+(H41*I41),IF($F41>=1,$J41+(D41*E41)+(F41*G41)+(H41*I41),IF($H41>=1,$J41+(D41*E41)+(F41*G41)+(H41*I41),""))) | M41: =SUM(M11:M40) -> 0
I42: TOTAL LABOUR | K42: =SUM(K11:K41) -> 0 | M42: =SUMIFS(D11:D41,D11:D41,"<3",D11:D41,"<5") -> 0 | N42: =SUMIFS(D11:D41,D11:D41,">3",D11:D41,">5") -> 0 | O42: =SUM(F11:F41,H11:H41,M42,N42)-M41 -> 0
A44: Equipment ID | B44: Equipment | H44: Days | I44: Hrs. | J44: Rate | K44: Total
B45: =VLOOKUP($C$45:$C$64,Equipment!$A$1:$B$2322,2,FALSE) -> 0 | J45: =VLOOKUP($B$45:$B$64,'Alberta Equip. Rates Year 3'!$B$13:$K$314,10,FALSE) -> 0 | K45: =(H45+I45)*J45 -> 0
B46: =VLOOKUP($C$45:$C$64,Equipment!$A$1:$B$2322,2,FALSE) -> 0 | J46: =VLOOKUP($B$45:$B$64,'Alberta Equip. Rates Year 3'!$B$13:$K$314,10,FALSE) -> 0 | K46: =(H46+I46)*J46 -> 0
B47: =VLOOKUP($C$45:$C$64,Equipment!$A$1:$B$2322,2,FALSE) -> 0 | J47: =VLOOKUP($B$45:$B$64,'Alberta Equip. Rates Year 3'!$B$13:$K$314,10,FALSE) -> 0 | K47: =(H47+I47)*J47 -> 0
B48: =VLOOKUP($C$45:$C$64,Equipment!$A$1:$B$2322,2,FALSE) -> 0 | J48: =VLOOKUP($B$45:$B$64,'Alberta Equip. Rates Year 3'!$B$13:$K$314,10,FALSE) -> 0 | K48: =(H48+I48)*J48 -> 0
B49: =VLOOKUP($C$45:$C$64,Equipment!$A$1:$B$2322,2,FALSE) -> 0 | J49: =VLOOKUP($B$45:$B$64,'Alberta Equip. Rates Year 3'!$B$13:$K$314,10,FALSE) -> 0 | K49: =(H49+I49)*J49 -> 0
B50: =VLOOKUP($C$45:$C$64,Equipment!$A$1:$B$2322,2,FALSE) -> 0 | J50: =VLOOKUP($B$45:$B$64,'Alberta Equip. Rates Year 3'!$B$13:$K$314,10,FALSE) -> 0 | K50: =(H50+I50)*J50 -> 0
B51: =VLOOKUP($C$45:$C$64,Equipment!$A$1:$B$2322,2,FALSE) -> 0 | J51: =VLOOKUP($B$45:$B$64,'Alberta Equip. Rates Year 3'!$B$13:$K$314,10,FALSE) -> 0 | K51: =(H51+I51)*J51 -> 0
B52: =VLOOKUP($C$45:$C$64,Equipment!$A$1:$B$2322,2,FALSE) -> 0 | J52: =VLOOKUP($B$45:$B$64,'Alberta Equip. Rates Year 3'!$B$13:$K$314,10,FALSE) -> 0 | K52: =(H52+I52)*J52 -> 0
B53: =VLOOKUP($C$45:$C$64,Equipment!$A$1:$B$2322,2,FALSE) -> 0 | J53: =VLOOKUP($B$45:$B$64,'Alberta Equip. Rates Year 3'!$B$13:$K$314,10,FALSE) -> 0 | K53: =(H53+I53)*J53 -> 0
B54: =VLOOKUP($C$45:$C$64,Equipment!$A$1:$B$2322,2,FALSE) -> 0 | J54: =VLOOKUP($B$45:$B$64,'Alberta Equip. Rates Year 3'!$B$13:$K$314,10,FALSE) -> 0 | K54: =(H54+I54)*J54 -> 0
B55: =VLOOKUP($C$45:$C$64,Equipment!$A$1:$B$2322,2,FALSE) -> 0 | J55: =VLOOKUP($B$45:$B$64,'Alberta Equip. Rates Year 3'!$B$13:$K$314,10,FALSE) -> 0 | K55: =(H55+I55)*J55 -> 0
B56: =VLOOKUP($C$45:$C$64,Equipment!$A$1:$B$2322,2,FALSE) -> 0 | J56: =VLOOKUP($B$45:$B$64,'Alberta Equip. Rates Year 3'!$B$13:$K$314,10,FALSE) -> 0 | K56: =(H56+I56)*J56 -> 0
... B64: =VLOOKUP($C$45:$C$64,Equipment!$A$1:$B$2322,2,FALSE) -> 0 | J64: =VLOOKUP($B$45:$B$64,'Alberta Equip. Rates Year 3'!$B$13:$K$314,10,FALSE) -> 0 | K64: =(H64+I64)*J64 -> 0
I65: TOTAL EQUIPMENT | K65: =SUM(K45:K64) -> 0
A67: Scope of Work: | I67: LABOUR | K67: =K42 -> 0
I68: EQUIPMENT | K68: =K65 -> 0
I69: SMALL TOOLS | K69: =(O42)*14.15 -> 0
I70: MATERIALS
I71: TRUCKING
I72: SUBCONTRACTORS
I73: FIELD LOG TOTAL* | K73: =SUM(K67:K72) -> 0
A75: Client: | H75: Company Representitive:
A77: * Field Log Total does no include markups
A78: 41218.479

Sheet Field Log (22)
J1: Date:
G6: Field Log ID: | J6: Status:
A7: Address: | G7: Account #: | J7: Account:
G8: Foreman:
A10: Employee ID | B10: Labor Type | C10: Employee | D10: RT Hours | E10: RT Rate | F10: OT Hours | G10: OT Rate | H10: DT Hours | I10: DT Rate | J10: Sub. | K10: Total | M10: Additional Hours
B11: =VLOOKUP($C$11:$C$33,Personnel!$A$1:$B$1234,2,FALSE) -> 0 | E11: =VLOOKUP($B$11:$B$33,'Constr. Wage Rate Calculations'!$A$19:$Z$288,22,FALSE) -> 0 | G11: =VLOOKUP($B$11:$B$33,'Constr. Wage Rate Calculations'!$A$19:$Z$288,23,FALSE) -> 0 | I11: =VLOOKUP($B$11:$B$33,'Constr. Wage Rate Calculations'!$A$19:$Z$288,24,FALSE) -> 0 | J11: =VLOOKUP($B$11:$B$33,'Constr. Wage Rate Calculations'!$A$19:$Z$288,25,FALSE) -> 0 | K11: =IF($D11>=1,$J11+(D11*E11)+(F11*G11)+(H11*I11),IF($F11>=1,$J11+(D11*E11)+(F11*G11)+(H11*I11),IF($H11>=1,$J11+(D11*E11)+(F11*G11)+(H11*I11),"")))
B12: =VLOOKUP($C$11:$C$33,Personnel!$A$1:$B$1234,2,FALSE) -> 0 | E12: =VLOOKUP($B$11:$B$33,'Constr. Wage Rate Calculations'!$A$19:$Z$288,22,FALSE) -> 0 | G12: =VLOOKUP($B$11:$B$33,'Constr. Wage Rate Calculations'!$A$19:$Z$288,23,FALSE) -> 0 | I12: =VLOOKUP($B$11:$B$33,'Constr. Wage Rate Calculations'!$A$19:$Z$288,24,FALSE) -> 0 | J12: =VLOOKUP($B$11:$B$33,'Constr. Wage Rate Calculations'!$A$19:$Z$288,25,FALSE) -> 0 | K12: =IF($D12>=1,$J12+(D12*E12)+(F12*G12)+(H12*I12),IF($F12>=1,$J12+(D12*E12)+(F12*G12)+(H12*I12),IF($H12>=1,$J12+(D12*E12)+(F12*G12)+(H12*I12),"")))
B13: =VLOOKUP($C$11:$C$33,Personnel!$A$1:$B$1234,2,FALSE) -> 0 | E13: =VLOOKUP($B$11:$B$33,'Constr. Wage Rate Calculations'!$A$19:$Z$288,22,FALSE) -> 0 | G13: =VLOOKUP($B$11:$B$33,'Constr. Wage Rate Calculations'!$A$19:$Z$288,23,FALSE) -> 0 | I13: =VLOOKUP($B$11:$B$33,'Constr. Wage Rate Calculations'!$A$19:$Z$288,24,FALSE) -> 0 | J13: =VLOOKUP($B$11:$B$33,'Constr. Wage Rate Calculations'!$A$19:$Z$288,25,FALSE) -> 0 | K13: =IF($D13>=1,$J13+(D13*E13)+(F13*G13)+(H13*I13),IF($F13>=1,$J13+(D13*E13)+(F13*G13)+(H13*I13),IF($H13>=1,$J13+(D13*E13)+(F13*G13)+(H13*I13),"")))
B14: =VLOOKUP($C$11:$C$33,Personnel!$A$1:$B$1234,2,FALSE) -> 0 | E14: =VLOOKUP($B$11:$B$33,'Constr. Wage Rate Calculations'!$A$19:$Z$288,22,FALSE) -> 0 | G14: =VLOOKUP($B$11:$B$33,'Constr. Wage Rate Calculations'!$A$19:$Z$288,23,FALSE) -> 0 | I14: =VLOOKUP($B$11:$B$33,'Constr. Wage Rate Calculations'!$A$19:$Z$288,24,FALSE) -> 0 | J14: =VLOOKUP($B$11:$B$33,'Constr. Wage Rate Calculations'!$A$19:$Z$288,25,FALSE) -> 0 | K14: =IF($D14>=1,$J14+(D14*E14)+(F14*G14)+(H14*I14),IF($F14>=1,$J14+(D14*E14)+(F14*G14)+(H14*I14),IF($H14>=1,$J14+(D14*E14)+(F14*G14)+(H14*I14),"")))
B15: =VLOOKUP($C$11:$C$33,Personnel!$A$1:$B$1234,2,FALSE) -> 0 | E15: =VLOOKUP($B$11:$B$33,'Constr. Wage Rate Calculations'!$A$19:$Z$288,22,FALSE) -> 0 | G15: =VLOOKUP($B$11:$B$33,'Constr. Wage Rate Calculations'!$A$19:$Z$288,23,FALSE) -> 0 | I15: =VLOOKUP($B$11:$B$33,'Constr. Wage Rate Calculations'!$A$19:$Z$288,24,FALSE) -> 0 | J15: =VLOOKUP($B$11:$B$33,'Constr. Wage Rate Calculations'!$A$19:$Z$288,25,FALSE) -> 0 | K15: =IF($D15>=1,$J15+(D15*E15)+(F15*G15)+(H15*I15),IF($F15>=1,$J15+(D15*E15)+(F15*G15)+(H15*I15),IF($H15>=1,$J15+(D15*E15)+(F15*G15)+(H15*I15),"")))
B16: =VLOOKUP($C$11:$C$33,Personnel!$A$1:$B$1234,2,FALSE) -> 0 | E16: =VLOOKUP($B$11:$B$33,'Constr. Wage Rate Calculations'!$A$19:$Z$288,22,FALSE) -> 0 | G16: =VLOOKUP($B$11:$B$33,'Constr. Wage Rate Calculations'!$A$19:$Z$288,23,FALSE) -> 0 | I16: =VLOOKUP($B$11:$B$33,'Constr. Wage Rate Calculations'!$A$19:$Z$288,24,FALSE) -> 0 | J16: =VLOOKUP($B$11:$B$33,'Constr. Wage Rate Calculations'!$A$19:$Z$288,25,FALSE) -> 0 | K16: =IF($D16>=1,$J16+(D16*E16)+(F16*G16)+(H16*I16),IF($F16>=1,$J16+(D16*E16)+(F16*G16)+(H16*I16),IF($H16>=1,$J16+(D16*E16)+(F16*G16)+(H16*I16),"")))
B17: =VLOOKUP($C$11:$C$33,Personnel!$A$1:$B$1234,2,FALSE) -> 0 | E17: =VLOOKUP($B$11:$B$33,'Constr. Wage Rate Calculations'!$A$19:$Z$288,22,FALSE) -> 0 | G17: =VLOOKUP($B$11:$B$33,'Constr. Wage Rate Calculations'!$A$19:$Z$288,23,FALSE) -> 0 | I17: =VLOOKUP($B$11:$B$33,'Constr. Wage Rate Calculations'!$A$19:$Z$288,24,FALSE) -> 0 | J17: =VLOOKUP($B$11:$B$33,'Constr. Wage Rate Calculations'!$A$19:$Z$288,25,FALSE) -> 0 | K17: =IF($D17>=1,$J17+(D17*E17)+(F17*G17)+(H17*I17),IF($F17>=1,$J17+(D17*E17)+(F17*G17)+(H17*I17),IF($H17>=1,$J17+(D17*E17)+(F17*G17)+(H17*I17),"")))
B18: =VLOOKUP($C$11:$C$33,Personnel!$A$1:$B$1234,2,FALSE) -> 0 | E18: =VLOOKUP($B$11:$B$33,'Constr. Wage Rate Calculations'!$A$19:$Z$288,22,FALSE) -> 0 | G18: =VLOOKUP($B$11:$B$33,'Constr. Wage Rate Calculations'!$A$19:$Z$288,23,FALSE) -> 0 | I18: =VLOOKUP($B$11:$B$33,'Constr. Wage Rate Calculations'!$A$19:$Z$288,24,FALSE) -> 0 | J18: =VLOOKUP($B$11:$B$33,'Constr. Wage Rate Calculations'!$A$19:$Z$288,25,FALSE) -> 0 | K18: =IF($D18>=1,$J18+(D18*E18)+(F18*G18)+(H18*I18),IF($F18>=1,$J18+(D18*E18)+(F18*G18)+(H18*I18),IF($H18>=1,$J18+(D18*E18)+(F18*G18)+(H18*I18),"")))
